{
  "type": "Feature",
  "properties": {
    "gn:admin1_code":"04",
    "gn:admin2_code":"408.0",
    "gn:admin3_code":"40816.0",
    "gn:asciiname":"Obertresleinsbach",
    "gn:country_code":"AT",
    "gn:dem":438,
    "gn:feature_class":"P",
    "gn:feature_code":"PPL",
    "gn:name":"Obertresleinsbach",
    "gn:population":96,
    "gn:timezone":"Europe/Vienna",
    "iso:country":"AT",
    "wof:name":"Obertresleinsbach",
    "wof:placetype":"locality",
    "wof:population":96
},
  "geometry": {"coordinates":[13.72227,48.38915],"type":"Point"}
}