{
  "type": "Feature",
  "properties": {
    "gn:admin1_code":"03",
    "gn:admin2_code":"309.0",
    "gn:admin3_code":"30939.0",
    "gn:asciiname":"Pyhrabruck",
    "gn:country_code":"AT",
    "gn:dem":561,
    "gn:feature_class":"P",
    "gn:feature_code":"PPL",
    "gn:name":"Pyhrabruck",
    "gn:population":53,
    "gn:timezone":"Europe/Vienna",
    "iso:country":"AT",
    "wof:name":"Pyhrabruck",
    "wof:placetype":"locality",
    "wof:population":53
},
  "geometry": {"coordinates":[14.81667,48.76667],"type":"Point"}
}