{
  "type": "Feature",
  "properties": {
    "gn:admin1_code":"06",
    "gn:admin2_code":"623.0",
    "gn:admin3_code":"62389.0",
    "gn:asciiname":"Reithberg",
    "gn:country_code":"AT",
    "gn:dem":439,
    "gn:feature_class":"P",
    "gn:feature_code":"PPL",
    "gn:name":"Reithberg",
    "gn:population":0,
    "gn:timezone":"Europe/Vienna",
    "iso:country":"AT",
    "wof:name":"Reithberg",
    "wof:placetype":"locality"
},
  "geometry": {"coordinates":[15.71667,46.96667],"type":"Point"}
}