{
  "type": "Feature",
  "properties": {
    "gn:admin1_code":"6.0",
    "gn:admin2_code":"606",
    "gn:admin3_code":"60645.0",
    "gn:asciiname":"Boden",
    "gn:country_code":"AT",
    "gn:dem":754,
    "gn:feature_class":"P",
    "gn:feature_code":"PPL",
    "gn:name":"Boden",
    "gn:population":0,
    "gn:timezone":"Europe/Vienna",
    "iso:country":"AT",
    "name:ceb_x_preferred":[
        "Boden"
    ],
    "name:deu_x_preferred":[
        "Boden"
    ],
    "name:epo_x_preferred":[
        "Boden"
    ],
    "name:est_x_preferred":[
        "Boden"
    ],
    "name:fin_x_preferred":[
        "Boden"
    ],
    "name:fra_x_preferred":[
        "Boden"
    ],
    "name:heb_x_preferred":[
        "\u05d1\u05d5\u05d3\u05df"
    ],
    "name:hrv_x_preferred":[
        "Boden"
    ],
    "name:ita_x_preferred":[
        "Boden"
    ],
    "name:nld_x_preferred":[
        "Boden"
    ],
    "name:pol_x_preferred":[
        "Boden"
    ],
    "name:rus_x_preferred":[
        "\u0411\u0443\u0434\u0435\u043d"
    ],
    "name:swe_x_preferred":[
        "Boden"
    ],
    "name:ukr_x_preferred":[
        "\u0411\u0443\u0434\u0435\u043d"
    ],
    "wof:name":"Boden",
    "wof:placetype":"locality"
},
  "geometry": {"coordinates":[15.41667,47.23333],"type":"Point"}
}