{
  "type": "Feature",
  "properties": {
    "gn:admin1_code":"04",
    "gn:admin2_code":"414.0",
    "gn:admin3_code":"41408.0",
    "gn:asciiname":"Ruprechtsberg",
    "gn:country_code":"AT",
    "gn:dem":491,
    "gn:feature_class":"P",
    "gn:feature_code":"PPL",
    "gn:name":"Ruprechtsberg",
    "gn:population":59,
    "gn:timezone":"Europe/Vienna",
    "iso:country":"AT",
    "wof:name":"Ruprechtsberg",
    "wof:placetype":"locality",
    "wof:population":59
},
  "geometry": {"coordinates":[13.64811,48.39889],"type":"Point"}
}