{
  "type": "Feature",
  "properties": {
    "gn:admin1_code":"03",
    "gn:admin2_code":"321.0",
    "gn:admin3_code":"32143.0",
    "gn:asciiname":"Wipfing",
    "gn:country_code":"AT",
    "gn:dem":170,
    "gn:feature_class":"P",
    "gn:feature_code":"PPL",
    "gn:name":"Wipfing",
    "gn:population":395,
    "gn:timezone":"Europe/Vienna",
    "iso:country":"AT",
    "wof:name":"Wipfing",
    "wof:placetype":"locality",
    "wof:population":395
},
  "geometry": {"coordinates":[16.14304,48.32327],"type":"Point"}
}