{
  "type": "Feature",
  "properties": {
    "gn:admin1_code":"6.0",
    "gn:admin2_code":"620",
    "gn:admin3_code":"62021.0",
    "gn:asciiname":"Mitterspiel",
    "gn:country_code":"AT",
    "gn:dem":1099,
    "gn:feature_class":"P",
    "gn:feature_code":"PPL",
    "gn:name":"Mitterspiel",
    "gn:population":0,
    "gn:timezone":"Europe/Vienna",
    "iso:country":"AT",
    "wof:name":"Mitterspiel",
    "wof:placetype":"locality"
},
  "geometry": {"coordinates":[14.35972,47.31917],"type":"Point"}
}