{
  "type": "Feature",
  "properties": {
    "gn:admin1_code":"4.0",
    "gn:admin2_code":"412",
    "gn:admin3_code":"41221.0",
    "gn:asciiname":"Hof",
    "gn:country_code":"AT",
    "gn:dem":484,
    "gn:feature_class":"P",
    "gn:feature_code":"PPL",
    "gn:name":"Hof",
    "gn:population":93,
    "gn:timezone":"Europe/Vienna",
    "iso:country":"AT",
    "wof:name":"Hof",
    "wof:placetype":"locality",
    "wof:population":93
},
  "geometry": {"coordinates":[13.484,48.16757],"type":"Point"}
}