{
  "type": "Feature",
  "properties": {
    "gn:admin1_code":"2.0",
    "gn:admin2_code":"205",
    "gn:admin3_code":"20506.0",
    "gn:asciiname":"Steindorf",
    "gn:country_code":"AT",
    "gn:dem":865,
    "gn:feature_class":"P",
    "gn:feature_code":"PPL",
    "gn:name":"Steindorf",
    "gn:population":0,
    "gn:timezone":"Europe/Vienna",
    "iso:country":"AT",
    "name:als_x_preferred":[
        "Steindorf"
    ],
    "name:ara_x_preferred":[
        "\u0634\u062a\u0627\u064a\u0646\u062f\u0648\u0631\u0641"
    ],
    "name:ceb_x_preferred":[
        "Steindorf"
    ],
    "name:deu_x_preferred":[
        "Steindorf"
    ],
    "name:epo_x_preferred":[
        "Steindorf"
    ],
    "name:eus_x_preferred":[
        "Steindorf"
    ],
    "name:fas_x_preferred":[
        "\u0634\u062a\u0627\u06cc\u0646\u062f\u0648\u0631\u0641"
    ],
    "name:fra_x_preferred":[
        "Steindorf"
    ],
    "name:hun_x_preferred":[
        "Steindorf"
    ],
    "name:hye_x_preferred":[
        "\u0547\u057f\u0561\u0575\u0576\u0564\u0578\u0580\u0586"
    ],
    "name:ind_x_preferred":[
        "Steindorf"
    ],
    "name:ita_x_preferred":[
        "Steindorf"
    ],
    "name:jpn_x_preferred":[
        "\u30b7\u30e5\u30bf\u30a4\u30f3\u30c9\u30eb\u30d5"
    ],
    "name:kaz_x_preferred":[
        "\u0428\u0442\u0430\u0439\u043d\u0434\u043e\u0440\u0444"
    ],
    "name:kir_x_preferred":[
        "\u0428\u0442\u0430\u0439\u043d\u0434\u043e\u0440\u0444"
    ],
    "name:lmo_x_preferred":[
        "Steindorf"
    ],
    "name:msa_x_preferred":[
        "Steindorf"
    ],
    "name:nld_x_preferred":[
        "Steindorf"
    ],
    "name:pol_x_preferred":[
        "Steindorf"
    ],
    "name:por_x_preferred":[
        "Steindorf"
    ],
    "name:ron_x_preferred":[
        "Steindorf"
    ],
    "name:rus_x_preferred":[
        "\u0428\u0442\u0430\u0439\u043d\u0434\u043e\u0440\u0444"
    ],
    "name:spa_x_preferred":[
        "Steindorf"
    ],
    "name:srp_x_preferred":[
        "\u0428\u0442\u0430\u0458\u043d\u0434\u043e\u0440\u0444"
    ],
    "name:ukr_x_preferred":[
        "\u0428\u0442\u0430\u0439\u043d\u0434\u043e\u0440\u0444"
    ],
    "name:uzb_x_preferred":[
        "Steindorf"
    ],
    "name:vie_x_preferred":[
        "Steindorf"
    ],
    "name:vol_x_preferred":[
        "Steindorf"
    ],
    "name:war_x_preferred":[
        "Steindorf"
    ],
    "name:zho_x_preferred":[
        "\u65bd\u6cf0\u56e0\u591a\u592b"
    ],
    "wof:name":"Steindorf",
    "wof:placetype":"locality"
},
  "geometry": {"coordinates":[14.15139,46.89306],"type":"Point"}
}