{
  "type": "Feature",
  "properties": {
    "gn:admin1_code":"2.0",
    "gn:admin2_code":"205",
    "gn:admin3_code":"20506.0",
    "gn:asciiname":"Steindorf",
    "gn:country_code":"AT",
    "gn:dem":865,
    "gn:feature_class":"P",
    "gn:feature_code":"PPL",
    "gn:name":"Steindorf",
    "gn:population":0,
    "gn:timezone":"Europe/Vienna",
    "iso:country":"AT",
    "wof:name":"Steindorf",
    "wof:placetype":"locality"
},
  "geometry": {"coordinates":[14.15139,46.89306],"type":"Point"}
}