{
  "type": "Feature",
  "properties": {
    "gn:admin1_code":"2.0",
    "gn:admin2_code":"209",
    "gn:admin3_code":"20913.0",
    "gn:asciiname":"Kleinrojach",
    "gn:country_code":"AT",
    "gn:dem":425,
    "gn:feature_class":"P",
    "gn:feature_code":"PPL",
    "gn:name":"Kleinrojach",
    "gn:population":175,
    "gn:timezone":"Europe/Vienna",
    "iso:country":"AT",
    "wof:name":"Kleinrojach",
    "wof:placetype":"locality",
    "wof:population":175
},
  "geometry": {"coordinates":[14.82347,46.78984000000001],"type":"Point"}
}