{
  "type": "Feature",
  "properties": {
    "gn:admin1_code":"5.0",
    "gn:admin2_code":"502",
    "gn:admin3_code":"50209.0",
    "gn:asciiname":"Hinterwiestal",
    "gn:cc2":"AT",
    "gn:country_code":"AT",
    "gn:dem":738,
    "gn:feature_class":"P",
    "gn:feature_code":"PPL",
    "gn:name":"Hinterwiestal",
    "gn:population":134,
    "gn:timezone":"Europe/Vienna",
    "iso:country":"AT",
    "name:und_x_variant":[
        "Hinterwiesthal",
        "Hinterwiestal"
    ],
    "wof:name":"Hinterwiestal",
    "wof:placetype":"locality",
    "wof:population":134
},
  "geometry": {"coordinates":[13.13333,47.73333],"type":"Point"}
}