{
  "type": "Feature",
  "properties": {
    "gn:gn_country":"AT",
    "gn:gn_fcode":"PPL",
    "gn:gn_pop":0,
    "iso:country":"AT",
    "name:ceb_x_preferred":[
        "Nu\u00dfdorf am Haunsberg"
    ],
    "name:dan_x_preferred":[
        "Nu\u00dfdorf am Haunsberg"
    ],
    "name:deu_x_preferred":[
        "Nu\u00dfdorf am Haunsberg"
    ],
    "name:eng_x_preferred":[
        "Nu\u00dfdorf am Haunsberg"
    ],
    "name:epo_x_preferred":[
        "Nu\u00dfdorf am Haunsberg"
    ],
    "name:fas_x_preferred":[
        "\u0646\u0648\u0633\u062f\u0648\u0631\u0641 \u0627\u0645 \u0647\u0627\u0646\u0633\u0628\u0631\u06af"
    ],
    "name:fra_x_preferred":[
        "Nu\u00dfdorf am Haunsberg"
    ],
    "name:hun_x_preferred":[
        "Nu\u00dfdorf am Haunsberg"
    ],
    "name:ita_x_preferred":[
        "Nu\u00dfdorf am Haunsberg"
    ],
    "name:nld_x_preferred":[
        "Nu\u00dfdorf am Haunsberg"
    ],
    "name:pol_x_preferred":[
        "Nu\u00dfdorf am Haunsberg"
    ],
    "name:rus_x_preferred":[
        "\u041d\u0443\u0441\u0434\u043e\u0440\u0444"
    ],
    "name:slk_x_preferred":[
        "Nu\u00dfdorf am Haunsberg"
    ],
    "name:spa_x_preferred":[
        "Nu\u00dfdorf am Haunsberg"
    ],
    "name:swe_x_preferred":[
        "Nu\u00dfdorf am Haunsberg"
    ],
    "name:ukr_x_preferred":[
        "\u041d\u0443\u0441\u0434\u043e\u0440\u0444-\u0430\u043c-\u0413\u0430\u0443\u043d\u0441\u0431\u0435\u0440\u0433"
    ],
    "name:uzb_x_preferred":[
        "Nu\u00dfdorf am Haunsberg"
    ],
    "name:vol_x_preferred":[
        "Nu\u00dfdorf am Haunsberg"
    ],
    "name:war_x_preferred":[
        "Nu\u00dfdorf am Haunsberg"
    ],
    "name:zho_x_preferred":[
        "\u8c6a\u6069\u65af\u5c71\u9e93\u52aa\u65af\u591a\u592b"
    ],
    "qs_pg:aaroncc":"AT",
    "qs_pg:gn_country":"AT",
    "qs_pg:gn_fcode":"PPL",
    "qs_pg:gn_pop":0,
    "qs_pg:name":"Nu\u00dfdorf am Haunsberg",
    "qs_pg:name_adm0":"\u00d6sterreich",
    "qs_pg:name_adm1":"Salzburg",
    "qs_pg:photos":16,
    "qs_pg:photos_1k":3,
    "qs_pg:photos_9k":1,
    "qs_pg:photos_9r":1,
    "qs_pg:photos_all":16,
    "qs_pg:photos_sr":1,
    "qs_pg:pop_sr":0,
    "qs_pg:qs_pg_placetype":"locality",
    "qs_pg:qs_pg_placetype_gp":"Town",
    "qs_pg:woe_adm0":23424750,
    "woe:adm0_id":23424750,
    "woe:name_adm0":"\u00d6sterreich",
    "woe:name_adm1":"Salzburg",
    "woe:placetype":"Town",
    "wof:name":"Nu\u00dfdorf am Haunsberg",
    "wof:placetype":"locality"
},
  "geometry": {"coordinates":[13.07028,47.83278],"type":"Point"}
}