{
  "type": "Feature",
  "properties": {
    "gn:admin1_code":"6.0",
    "gn:admin2_code":"616",
    "gn:admin3_code":"61625.0",
    "gn:asciiname":"Krems",
    "gn:country_code":"AT",
    "gn:dem":399,
    "gn:feature_class":"P",
    "gn:feature_code":"PPL",
    "gn:name":"Krems",
    "gn:population":0,
    "gn:timezone":"Europe/Vienna",
    "iso:country":"AT",
    "wof:name":"Krems",
    "wof:placetype":"locality"
},
  "geometry": {"coordinates":[15.18333,47.03333],"type":"Point"}
}