{
  "type": "Feature",
  "properties": {
    "iso:country":"AT",
    "name:cat_x_preferred":[
        "Niederleis"
    ],
    "name:ceb_x_preferred":[
        "Niederleis"
    ],
    "name:ces_x_preferred":[
        "Niederleis"
    ],
    "name:che_x_preferred":[
        "\u041d\u0438\u0434\u0435\u0440\u043b\u0430\u0439\u0441"
    ],
    "name:deu_x_preferred":[
        "Niederleis"
    ],
    "name:eng_x_preferred":[
        "Niederleis"
    ],
    "name:epo_x_preferred":[
        "Niederleis"
    ],
    "name:fas_x_preferred":[
        "\u0646\u06cc\u062f\u0631\u0644\u0627\u06cc\u0633"
    ],
    "name:fra_x_preferred":[
        "Niederleis"
    ],
    "name:hun_x_preferred":[
        "Niederleis"
    ],
    "name:ita_x_preferred":[
        "Niederleis"
    ],
    "name:jpn_x_preferred":[
        "\u30cb\u30fc\u30c0\u30fc\u30e9\u30a4\u30b9"
    ],
    "name:kaz_x_preferred":[
        "\u041d\u0438\u0434\u0435\u0440\u043b\u0430\u0439\u0441"
    ],
    "name:lld_x_preferred":[
        "Niederleis"
    ],
    "name:nld_x_preferred":[
        "Niederleis"
    ],
    "name:nob_x_preferred":[
        "Niederleis"
    ],
    "name:pol_x_preferred":[
        "Niederleis"
    ],
    "name:por_x_preferred":[
        "Niederleis"
    ],
    "name:rus_x_preferred":[
        "\u041d\u0438\u0434\u0435\u0440\u043b\u0430\u0439\u0441"
    ],
    "name:slk_x_preferred":[
        "Niederleis"
    ],
    "name:spa_x_preferred":[
        "Niederleis"
    ],
    "name:swe_x_preferred":[
        "Niederleis"
    ],
    "name:tat_x_preferred":[
        "\u041d\u0438\u0434\u0435\u0440\u043b\u0430\u0439\u0441"
    ],
    "name:uzb_x_preferred":[
        "Niederleis"
    ],
    "name:vec_x_preferred":[
        "Niederleis"
    ],
    "name:vie_x_preferred":[
        "Niederleis"
    ],
    "name:vol_x_preferred":[
        "Niederleis"
    ],
    "name:war_x_preferred":[
        "Niederleis"
    ],
    "name:zho_x_preferred":[
        "Niederleis"
    ],
    "qs_pg:aaroncc":"AT",
    "qs_pg:name":"Niederleis",
    "qs_pg:name_adm0":"\u00d6sterreich",
    "qs_pg:name_adm1":"Nieder\u00f6sterreich",
    "qs_pg:photos":80,
    "qs_pg:photos_1k":16,
    "qs_pg:photos_9k":1,
    "qs_pg:photos_9r":3,
    "qs_pg:photos_all":80,
    "qs_pg:photos_sr":3,
    "qs_pg:pop_sr":0,
    "qs_pg:qs_pg_placetype":"locality",
    "qs_pg:qs_pg_placetype_gp":"Town",
    "qs_pg:woe_adm0":23424750,
    "woe:adm0_id":23424750,
    "woe:name_adm0":"\u00d6sterreich",
    "woe:name_adm1":"Nieder\u00f6sterreich",
    "woe:placetype":"Town",
    "wof:name":"Niederleis",
    "wof:placetype":"locality"
},
  "geometry": {"coordinates":[16.392191,48.573905],"type":"Point"}
}