{
  "type": "Feature",
  "properties": {
    "iso:country":"AT",
    "name:chi_x_preferred":[
        "Niederleis"
    ],
    "name:cze_x_preferred":[
        "Niederleis"
    ],
    "name:dut_x_preferred":[
        "Niederleis"
    ],
    "name:eng_x_preferred":[
        "Niederleis"
    ],
    "name:fre_x_preferred":[
        "Niederleis"
    ],
    "name:ger_x_preferred":[
        "Niederleis"
    ],
    "name:hun_x_preferred":[
        "Niederleis"
    ],
    "name:ita_x_preferred":[
        "Niederleis"
    ],
    "name:kaz_x_preferred":[
        "\u041d\u0438\u0434\u0435\u0440\u043b\u0430\u0439\u0441"
    ],
    "name:pol_x_preferred":[
        "Niederleis"
    ],
    "name:por_x_preferred":[
        "Niederleis"
    ],
    "name:rus_x_preferred":[
        "\u041d\u0438\u0434\u0435\u0440\u043b\u0430\u0439\u0441"
    ],
    "name:slo_x_preferred":[
        "Niederleis"
    ],
    "name:swe_x_preferred":[
        "Niederleis"
    ],
    "name:uzb_x_preferred":[
        "Niederleis"
    ],
    "name:vie_x_preferred":[
        "Niederleis"
    ],
    "name:vol_x_preferred":[
        "Niederleis"
    ],
    "name:war_x_preferred":[
        "Niederleis"
    ],
    "qs_pg:aaroncc":"AT",
    "qs_pg:name":"Niederleis",
    "qs_pg:name_adm0":"\u00d6sterreich",
    "qs_pg:name_adm1":"Nieder\u00f6sterreich",
    "qs_pg:photos":80,
    "qs_pg:photos_1k":16,
    "qs_pg:photos_9k":1,
    "qs_pg:photos_9r":3,
    "qs_pg:photos_all":80,
    "qs_pg:photos_sr":3,
    "qs_pg:pop_sr":0,
    "qs_pg:qs_pg_placetype":"locality",
    "qs_pg:qs_pg_placetype_gp":"Town",
    "qs_pg:woe_adm0":23424750,
    "woe:adm0_id":23424750,
    "woe:name_adm0":"\u00d6sterreich",
    "woe:name_adm1":"Nieder\u00f6sterreich",
    "woe:placetype":"Town",
    "wof:name":"Niederleis",
    "wof:placetype":"locality"
},
  "geometry": {"coordinates":[16.392191,48.573905],"type":"Point"}
}