{
  "type": "Feature",
  "properties": {
    "gn:admin1_code":"3.0",
    "gn:admin2_code":"311",
    "gn:admin3_code":"31107.0",
    "gn:asciiname":"Goggitsch",
    "gn:country_code":"AT",
    "gn:dem":485,
    "gn:feature_class":"P",
    "gn:feature_code":"PPL",
    "gn:name":"Goggitsch",
    "gn:population":137,
    "gn:timezone":"Europe/Vienna",
    "iso:country":"AT",
    "wof:name":"Goggitsch",
    "wof:placetype":"locality",
    "wof:population":137
},
  "geometry": {"coordinates":[15.6768,48.77531],"type":"Point"}
}