{
  "type": "Feature",
  "properties": {
    "gn:admin1_code":"4.0",
    "gn:admin2_code":"407",
    "gn:admin3_code":"40710.0",
    "gn:asciiname":"Laizing",
    "gn:country_code":"AT",
    "gn:dem":478,
    "gn:feature_class":"P",
    "gn:feature_code":"PPL",
    "gn:name":"Laizing",
    "gn:population":41,
    "gn:timezone":"Europe/Vienna",
    "iso:country":"AT",
    "wof:name":"Laizing",
    "wof:placetype":"locality",
    "wof:population":41
},
  "geometry": {"coordinates":[13.89513,47.9647],"type":"Point"}
}