{
  "type": "Feature",
  "properties": {
    "iso:country":"AT",
    "name:deu_x_preferred":[
        "Stockenboi"
    ],
    "name:eng_x_preferred":[
        "Stockenboi"
    ],
    "name:fra_x_preferred":[
        "Stockenboi"
    ],
    "name:fur_x_preferred":[
        "Stockenboi"
    ],
    "name:hun_x_preferred":[
        "Stockenboi"
    ],
    "name:ita_x_preferred":[
        "Stockenboi"
    ],
    "name:nld_x_preferred":[
        "Stockenboi"
    ],
    "name:nob_x_preferred":[
        "Stockenboi"
    ],
    "name:pol_x_preferred":[
        "Stockenboi"
    ],
    "name:por_x_preferred":[
        "Stockenboi"
    ],
    "name:rus_x_preferred":[
        "\u0428\u0442\u043e\u043a\u043a\u0435\u043d\u0431\u043e\u0439"
    ],
    "name:slk_x_preferred":[
        "Stockenboi"
    ],
    "name:slv_x_preferred":[
        "Stockenboi"
    ],
    "name:vie_x_preferred":[
        "Stockenboi"
    ],
    "name:vol_x_preferred":[
        "Stockenboi"
    ],
    "name:war_x_preferred":[
        "Stockenboi"
    ],
    "name:zho_x_preferred":[
        "\u65bd\u6258\u80af\u535a\u4f0a"
    ],
    "qs_pg:aaroncc":"AT",
    "qs_pg:name":"Stockenboi",
    "qs_pg:name_adm0":"\u00d6sterreich",
    "qs_pg:name_adm1":"K\u00e4rnten",
    "qs_pg:photos":83,
    "qs_pg:photos_1k":17,
    "qs_pg:photos_9k":1,
    "qs_pg:photos_9r":3,
    "qs_pg:photos_all":83,
    "qs_pg:photos_sr":3,
    "qs_pg:pop_sr":0,
    "qs_pg:qs_pg_placetype":"locality",
    "qs_pg:qs_pg_placetype_gp":"Town",
    "qs_pg:woe_adm0":23424750,
    "woe:adm0_id":23424750,
    "woe:name_adm0":"\u00d6sterreich",
    "woe:name_adm1":"K\u00e4rnten",
    "woe:placetype":"Town",
    "wof:name":"Stockenboi",
    "wof:placetype":"locality"
},
  "geometry": {"coordinates":[13.474388,46.718253],"type":"Point"}
}