{
  "type": "Feature",
  "properties": {
    "iso:country":"AT",
    "name:deu_x_preferred":[
        "Inneres M\u00fclln"
    ],
    "name:eng_x_preferred":[
        "Inneres Muelln"
    ],
    "wof:name":"Inneres Muelln",
    "wof:placetype":"neighbourhood"
},
  "geometry": {"coordinates":[13.03508443506905,47.80620123876259],"type":"Point"}
}