{
  "type": "Feature",
  "properties": {
    "gn:admin1_code":"5.0",
    "gn:admin2_code":"503",
    "gn:admin3_code":"50325.0",
    "gn:asciiname":"Kletzlberg",
    "gn:country_code":"AT",
    "gn:dem":556,
    "gn:feature_class":"P",
    "gn:feature_code":"PPL",
    "gn:name":"Kletzlberg",
    "gn:population":0,
    "gn:timezone":"Europe/Vienna",
    "iso:country":"AT",
    "wof:name":"Kletzlberg",
    "wof:placetype":"locality"
},
  "geometry": {"coordinates":[13.01944,47.96028],"type":"Point"}
}