{
  "type": "Feature",
  "properties": {
    "gn:admin1_code":"6.0",
    "gn:admin2_code":"612",
    "gn:admin3_code":"61258.0",
    "gn:asciiname":"Kirchenlandl",
    "gn:country_code":"AT",
    "gn:dem":521,
    "gn:feature_class":"P",
    "gn:feature_code":"PPL",
    "gn:name":"Kirchenlandl",
    "gn:population":437,
    "gn:timezone":"Europe/Vienna",
    "iso:country":"AT",
    "name:deu_x_colloquial":[
        "Kirchlandl"
    ],
    "name:deu_x_preferred":[
        "Kirchlandl"
    ],
    "wof:name":"Kirchenlandl",
    "wof:placetype":"locality",
    "wof:population":437
},
  "geometry": {"coordinates":[14.73445,47.65693],"type":"Point"}
}