{
  "type": "Feature",
  "properties": {
    "gn:admin1_code":"03",
    "gn:admin2_code":"316.0",
    "gn:admin3_code":"31606.0",
    "gn:asciiname":"Stuetzenhofen",
    "gn:country_code":"AT",
    "gn:dem":299,
    "gn:feature_class":"P",
    "gn:feature_code":"PPL",
    "gn:name":"St\u00fctzenhofen",
    "gn:population":105,
    "gn:timezone":"Europe/Vienna",
    "iso:country":"AT",
    "wof:name":"Stuetzenhofen",
    "wof:placetype":"locality",
    "wof:population":105
},
  "geometry": {"coordinates":[16.61667000000001,48.73333],"type":"Point"}
}