{
  "type": "Feature",
  "properties": {
    "gn:admin1_code":"8.0",
    "gn:admin2_code":"803",
    "gn:admin3_code":"80301.0",
    "gn:asciiname":"Kehlegg",
    "gn:country_code":"AT",
    "gn:dem":791,
    "gn:feature_class":"P",
    "gn:feature_code":"PPL",
    "gn:name":"Kehlegg",
    "gn:population":0,
    "gn:timezone":"Europe/Vienna",
    "iso:country":"AT",
    "wof:name":"Kehlegg",
    "wof:placetype":"locality"
},
  "geometry": {"coordinates":[9.77779,47.40198],"type":"Point"}
}