{
  "type": "Feature",
  "properties": {
    "iso:country":"AT",
    "name:deu_x_preferred":[
        "Ragnitz"
    ],
    "name:eng_x_preferred":[
        "Ragnitz"
    ],
    "wof:name":"Ragnitz",
    "wof:placetype":"neighbourhood"
},
  "geometry": {"coordinates":[15.49236110310723,47.080833014223],"type":"Point"}
}