{
  "type": "Feature",
  "properties": {
    "gn:admin1_code":"4.0",
    "gn:admin2_code":"405",
    "gn:admin3_code":"40508.0",
    "gn:asciiname":"Grosssteingrub",
    "gn:country_code":"AT",
    "gn:dem":371,
    "gn:feature_class":"P",
    "gn:feature_code":"PPL",
    "gn:name":"Grosssteingrub",
    "gn:population":0,
    "gn:timezone":"Europe/Vienna",
    "iso:country":"AT",
    "wof:name":"Grosssteingrub",
    "wof:placetype":"locality"
},
  "geometry": {"coordinates":[13.92388,48.30312],"type":"Point"}
}