{
  "type": "Feature",
  "properties": {
    "gn:admin1_code":"4.0",
    "gn:admin2_code":"417",
    "gn:admin3_code":"41746.0",
    "gn:asciiname":"Wagrain",
    "gn:country_code":"AT",
    "gn:dem":428,
    "gn:feature_class":"P",
    "gn:feature_code":"PPL",
    "gn:name":"Wagrain",
    "gn:population":1429,
    "gn:timezone":"Europe/Vienna",
    "iso:country":"AT",
    "name:bar_x_preferred":[
        "Wougroa"
    ],
    "name:ceb_x_preferred":[
        "Wagrain"
    ],
    "name:deu_x_preferred":[
        "Wagrain"
    ],
    "name:epo_x_preferred":[
        "Wagrain"
    ],
    "name:fas_x_preferred":[
        "\u0648\u0627\u06af\u0631\u0627\u06cc\u0646"
    ],
    "name:fra_x_preferred":[
        "Wagrain"
    ],
    "name:hun_x_preferred":[
        "Wagrain"
    ],
    "name:ita_x_preferred":[
        "Wagrain"
    ],
    "name:kaz_x_preferred":[
        "\u0412\u0430\u0433\u0440\u0430\u0439\u043d"
    ],
    "name:nld_x_preferred":[
        "Wagrain"
    ],
    "name:nno_x_preferred":[
        "Wagrain"
    ],
    "name:pol_x_preferred":[
        "Wagrain"
    ],
    "name:rus_x_preferred":[
        "\u0412\u0430\u0433\u0440\u0430\u0439\u043d"
    ],
    "name:slk_x_preferred":[
        "Wagrain"
    ],
    "name:spa_x_preferred":[
        "Wagrain"
    ],
    "name:swe_x_preferred":[
        "Wagrain"
    ],
    "name:ukr_x_preferred":[
        "\u0412\u0430\u0433\u0440\u0430\u0439\u043d"
    ],
    "name:uzb_x_preferred":[
        "Wagrain"
    ],
    "name:vie_x_preferred":[
        "Wagrain"
    ],
    "name:vol_x_preferred":[
        "Wagrain"
    ],
    "name:war_x_preferred":[
        "Wagrain"
    ],
    "name:zho_x_preferred":[
        "\u74e6\u683c\u8d56\u6069"
    ],
    "wof:name":"Wagrain",
    "wof:placetype":"locality",
    "wof:population":1429
},
  "geometry": {"coordinates":[13.67163,48.00503],"type":"Point"}
}