{
  "type": "Feature",
  "properties": {
    "gn:admin1_code":"4.0",
    "gn:admin2_code":"417",
    "gn:admin3_code":"41746.0",
    "gn:asciiname":"Wagrain",
    "gn:country_code":"AT",
    "gn:dem":428,
    "gn:feature_class":"P",
    "gn:feature_code":"PPL",
    "gn:name":"Wagrain",
    "gn:population":1429,
    "gn:timezone":"Europe/Vienna",
    "iso:country":"AT",
    "wof:name":"Wagrain",
    "wof:placetype":"locality",
    "wof:population":1429
},
  "geometry": {"coordinates":[13.67163,48.00503],"type":"Point"}
}