{
  "type": "Feature",
  "properties": {
    "gn:admin1_code":"07",
    "gn:admin2_code":"706.0",
    "gn:admin3_code":"70604.0",
    "gn:asciiname":"Puschlin",
    "gn:country_code":"AT",
    "gn:dem":1498,
    "gn:feature_class":"P",
    "gn:feature_code":"PPL",
    "gn:name":"Puschlin",
    "gn:population":0,
    "gn:timezone":"Europe/Vienna",
    "iso:country":"AT",
    "wof:name":"Puschlin",
    "wof:placetype":"locality"
},
  "geometry": {"coordinates":[10.66667,47.11667],"type":"Point"}
}