{
  "type": "Feature",
  "properties": {
    "gn:admin1_code":"05",
    "gn:admin2_code":"504.0",
    "gn:admin3_code":"50411.0",
    "gn:asciiname":"Unterwand",
    "gn:country_code":"AT",
    "gn:dem":1252,
    "gn:feature_class":"P",
    "gn:feature_code":"PPLL",
    "gn:name":"Unterwand",
    "gn:population":0,
    "gn:timezone":"Europe/Vienna",
    "iso:country":"AT",
    "wof:name":"Unterwand",
    "wof:placetype":"locality"
},
  "geometry": {"coordinates":[13.23333,47.28333],"type":"Point"}
}