{
  "type": "Feature",
  "properties": {
    "gn:admin1_code":"07",
    "gn:admin2_code":"702.0",
    "gn:admin3_code":"70208.0",
    "gn:asciiname":"Winnebach",
    "gn:country_code":"AT",
    "gn:dem":2413,
    "gn:feature_class":"P",
    "gn:feature_code":"PPL",
    "gn:name":"Winnebach",
    "gn:population":0,
    "gn:timezone":"Europe/Vienna",
    "iso:country":"AT",
    "wof:name":"Winnebach",
    "wof:placetype":"locality"
},
  "geometry": {"coordinates":[11.03333,47.08333],"type":"Point"}
}