{
  "type": "Feature",
  "properties": {
    "gn:admin1_code":"06",
    "gn:admin2_code":"617.0",
    "gn:admin3_code":"61730.0",
    "gn:asciiname":"Steinberg bei Weiz",
    "gn:cc2":"AT",
    "gn:country_code":"AT",
    "gn:dem":614,
    "gn:feature_class":"P",
    "gn:feature_code":"PPL",
    "gn:name":"Steinberg bei Weiz",
    "gn:population":283,
    "gn:timezone":"Europe/Vienna",
    "iso:country":"AT",
    "name:und_x_variant":[
        "Steinberg",
        "Steinberg bei Weiz"
    ],
    "wof:name":"Steinberg bei Weiz",
    "wof:placetype":"locality",
    "wof:population":283
},
  "geometry": {"coordinates":[15.59343,47.19569],"type":"Point"}
}