{
  "type": "Feature",
  "properties": {
    "gn:admin1_code":"2.0",
    "gn:admin2_code":"205",
    "gn:admin3_code":"20531.0",
    "gn:asciiname":"Nassing",
    "gn:country_code":"AT",
    "gn:dem":847,
    "gn:feature_class":"P",
    "gn:feature_code":"PPL",
    "gn:name":"Nassing",
    "gn:population":9,
    "gn:timezone":"Europe/Vienna",
    "iso:country":"AT",
    "wof:name":"Nassing",
    "wof:placetype":"locality",
    "wof:population":9
},
  "geometry": {"coordinates":[14.18333,46.86667],"type":"Point"}
}