{
  "type": "Feature",
  "properties": {
    "gn:admin1_code":"02",
    "gn:admin2_code":"205.0",
    "gn:admin3_code":"20530.0",
    "gn:asciiname":"Olschnoegg",
    "gn:country_code":"AT",
    "gn:dem":871,
    "gn:feature_class":"P",
    "gn:feature_code":"PPL",
    "gn:name":"Olschn\u00f6gg",
    "gn:population":18,
    "gn:timezone":"Europe/Vienna",
    "iso:country":"AT",
    "wof:name":"Olschnoegg",
    "wof:placetype":"locality",
    "wof:population":18
},
  "geometry": {"coordinates":[14.33333,46.93333],"type":"Point"}
}