{
  "type": "Feature",
  "properties": {
    "gn:gn_country":"AT",
    "gn:gn_fcode":"PPL",
    "gn:gn_pop":0,
    "iso:country":"AT",
    "name:ceb_x_preferred":[
        "Aufhausen"
    ],
    "name:deu_x_preferred":[
        "Aufhausen"
    ],
    "name:epo_x_preferred":[
        "Aufhausen"
    ],
    "name:eus_x_preferred":[
        "Aufhausen"
    ],
    "name:fas_x_preferred":[
        "\u0622\u0648\u0641\u0647\u0627\u0648\u0632\u0646"
    ],
    "name:fra_x_preferred":[
        "Aufhausen"
    ],
    "name:hun_x_preferred":[
        "Aufhausen"
    ],
    "name:hye_x_preferred":[
        "\u0531\u0578\u0582\u0586\u0570\u0561\u0578\u0582\u0566\u0565\u0576"
    ],
    "name:ita_x_preferred":[
        "Aufhausen"
    ],
    "name:kaz_x_preferred":[
        "\u0410\u0443\u0444\u0445\u0430\u0443\u0437\u0435\u043d"
    ],
    "name:kir_x_preferred":[
        "\u0410\u0443\u0444\u0445\u0430\u0443\u0437\u0435\u043d"
    ],
    "name:lat_x_preferred":[
        "Aufhausen"
    ],
    "name:lmo_x_preferred":[
        "Aufhausen"
    ],
    "name:msa_x_preferred":[
        "Aufhausen"
    ],
    "name:nld_x_preferred":[
        "Aufhausen"
    ],
    "name:pol_x_preferred":[
        "Aufhausen"
    ],
    "name:por_x_preferred":[
        "Aufhausen"
    ],
    "name:ron_x_preferred":[
        "Aufhausen"
    ],
    "name:rus_x_preferred":[
        "\u0410\u0443\u0444\u0445\u0430\u0443\u0437\u0435\u043d"
    ],
    "name:spa_x_preferred":[
        "Aufhausen"
    ],
    "name:srp_x_preferred":[
        "\u0410\u0443\u0444\u0445\u0430\u0443\u0437\u0435\u043d"
    ],
    "name:ukr_x_preferred":[
        "\u0410\u0443\u0444\u0433\u0430\u0443\u0437\u0435\u043d"
    ],
    "name:uzb_x_preferred":[
        "Aufhausen"
    ],
    "name:vie_x_preferred":[
        "Aufhausen"
    ],
    "name:vol_x_preferred":[
        "Aufhausen"
    ],
    "name:war_x_preferred":[
        "Aufhausen"
    ],
    "name:zho_x_preferred":[
        "\u5965\u592b\u8c6a\u68ee"
    ],
    "qs_pg:aaroncc":"AT",
    "qs_pg:gn_country":"AT",
    "qs_pg:gn_fcode":"PPL",
    "qs_pg:gn_pop":0,
    "qs_pg:name":"Aufhausen",
    "qs_pg:name_adm0":"\u00d6sterreich",
    "qs_pg:name_adm1":"Salzburg",
    "qs_pg:photos":14,
    "qs_pg:photos_1k":3,
    "qs_pg:photos_9k":1,
    "qs_pg:photos_9r":1,
    "qs_pg:photos_all":14,
    "qs_pg:photos_sr":1,
    "qs_pg:pop_sr":0,
    "qs_pg:qs_pg_placetype":"locality",
    "qs_pg:qs_pg_placetype_gp":"Town",
    "qs_pg:woe_adm0":23424750,
    "woe:adm0_id":23424750,
    "woe:name_adm0":"\u00d6sterreich",
    "woe:name_adm1":"Salzburg",
    "woe:placetype":"Town",
    "wof:name":"Aufhausen",
    "wof:placetype":"locality"
},
  "geometry": {"coordinates":[12.76182,47.29716],"type":"Point"}
}