{
  "type": "Feature",
  "properties": {
    "gn:admin1_code":"4.0",
    "gn:admin2_code":"405",
    "gn:admin3_code":"40509.0",
    "gn:asciiname":"Altau",
    "gn:country_code":"AT",
    "gn:dem":261,
    "gn:feature_class":"P",
    "gn:feature_code":"PPL",
    "gn:name":"Altau",
    "gn:population":23,
    "gn:timezone":"Europe/Vienna",
    "iso:country":"AT",
    "wof:name":"Altau",
    "wof:placetype":"locality",
    "wof:population":23
},
  "geometry": {"coordinates":[14.05083,48.30872],"type":"Point"}
}