{
  "type": "Feature",
  "properties": {
    "gn:admin1_code":"3.0",
    "gn:admin2_code":"325",
    "gn:admin3_code":"32519.0",
    "gn:asciiname":"Kronegg",
    "gn:country_code":"AT",
    "gn:dem":823,
    "gn:feature_class":"P",
    "gn:feature_code":"PPL",
    "gn:name":"Kronegg",
    "gn:population":66,
    "gn:timezone":"Europe/Vienna",
    "iso:country":"AT",
    "wof:name":"Kronegg",
    "wof:placetype":"locality",
    "wof:population":66
},
  "geometry": {"coordinates":[14.95,48.43333],"type":"Point"}
}