{
  "type": "Feature",
  "properties": {
    "gn:gn_country":"AT",
    "gn:gn_fcode":"PPL",
    "gn:gn_pop":0,
    "iso:country":"AT",
    "name:ceb_x_preferred":[
        "Breitenau"
    ],
    "name:deu_x_preferred":[
        "Breitenau"
    ],
    "name:fra_x_preferred":[
        "Breitenau"
    ],
    "name:ita_x_preferred":[
        "Breitenau"
    ],
    "name:nld_x_preferred":[
        "Breitenau"
    ],
    "name:pol_x_preferred":[
        "Breitenau"
    ],
    "name:rus_x_preferred":[
        "\u0411\u0440\u0430\u0439\u0442\u0435\u043d\u0430\u0443"
    ],
    "name:srp_x_preferred":[
        "\u0411\u0440\u0430\u0458\u0442\u0435\u043d\u0430\u0443"
    ],
    "name:swe_x_preferred":[
        "Breitenau"
    ],
    "name:vol_x_preferred":[
        "Breitenau"
    ],
    "qs_pg:aaroncc":"AT",
    "qs_pg:gn_country":"AT",
    "qs_pg:gn_fcode":"PPL",
    "qs_pg:gn_pop":0,
    "qs_pg:name":"Breitenau",
    "qs_pg:name_adm0":"\u00d6sterreich",
    "qs_pg:name_adm1":"Steiermark",
    "qs_pg:photos":64,
    "qs_pg:photos_1k":13,
    "qs_pg:photos_9k":1,
    "qs_pg:photos_9r":2,
    "qs_pg:photos_all":64,
    "qs_pg:photos_sr":2,
    "qs_pg:pop_sr":0,
    "qs_pg:qs_pg_placetype":"locality",
    "qs_pg:qs_pg_placetype_gp":"Town",
    "qs_pg:woe_adm0":23424750,
    "woe:adm0_id":23424750,
    "woe:name_adm0":"\u00d6sterreich",
    "woe:name_adm1":"Steiermark",
    "woe:placetype":"Town",
    "wof:name":"Breitenau",
    "wof:placetype":"locality"
},
  "geometry": {"coordinates":[15.48333,47.38333],"type":"Point"}
}