{
  "type": "Feature",
  "properties": {
    "gn:admin1_code":"3.0",
    "gn:admin2_code":"319",
    "gn:admin3_code":"31926.0",
    "gn:asciiname":"Berging",
    "gn:country_code":"AT",
    "gn:dem":260,
    "gn:feature_class":"P",
    "gn:feature_code":"PPL",
    "gn:name":"Berging",
    "gn:population":13,
    "gn:timezone":"Europe/Vienna",
    "iso:country":"AT",
    "wof:name":"Berging",
    "wof:placetype":"locality",
    "wof:population":13
},
  "geometry": {"coordinates":[15.86597,48.22716],"type":"Point"}
}