{
  "type": "Feature",
  "properties": {
    "gn:admin1_code":"03",
    "gn:admin2_code":"309.0",
    "gn:admin3_code":"30912.0",
    "gn:asciiname":"Thaures",
    "gn:country_code":"AT",
    "gn:dem":593,
    "gn:feature_class":"P",
    "gn:feature_code":"PPL",
    "gn:name":"Thaures",
    "gn:population":89,
    "gn:timezone":"Europe/Vienna",
    "iso:country":"AT",
    "wof:name":"Thaures",
    "wof:placetype":"locality",
    "wof:population":89
},
  "geometry": {"coordinates":[14.98333,48.65],"type":"Point"}
}