{
  "type": "Feature",
  "properties": {
    "gn:admin1_code":"06",
    "gn:admin2_code":"610.0",
    "gn:admin3_code":"61053.0",
    "gn:asciiname":"Schoenegg",
    "gn:country_code":"AT",
    "gn:dem":322,
    "gn:feature_class":"P",
    "gn:feature_code":"PPL",
    "gn:name":"Sch\u00f6negg",
    "gn:population":141,
    "gn:timezone":"Europe/Vienna",
    "iso:country":"AT",
    "wof:name":"Schoenegg",
    "wof:placetype":"locality",
    "wof:population":141
},
  "geometry": {"coordinates":[15.51667,46.75],"type":"Point"}
}