{
  "type": "Feature",
  "properties": {
    "gn:admin1_code":"6.0",
    "gn:admin2_code":"611",
    "gn:admin3_code":"61113.0",
    "gn:asciiname":"Kleinlainsach",
    "gn:country_code":"AT",
    "gn:dem":736,
    "gn:feature_class":"P",
    "gn:feature_code":"PPL",
    "gn:name":"Kleinlainsach",
    "gn:population":0,
    "gn:timezone":"Europe/Vienna",
    "iso:country":"AT",
    "wof:name":"Kleinlainsach",
    "wof:placetype":"locality"
},
  "geometry": {"coordinates":[15.01667,47.35],"type":"Point"}
}