{
  "type": "Feature",
  "properties": {
    "gn:admin1_code":"04",
    "gn:admin2_code":"409.0",
    "gn:admin3_code":"40917.0",
    "gn:asciiname":"Weigersdorf",
    "gn:country_code":"AT",
    "gn:dem":424,
    "gn:feature_class":"P",
    "gn:feature_code":"PPL",
    "gn:name":"Weigersdorf",
    "gn:population":0,
    "gn:timezone":"Europe/Vienna",
    "iso:country":"AT",
    "wof:name":"Weigersdorf",
    "wof:placetype":"locality"
},
  "geometry": {"coordinates":[14.1158,47.93222],"type":"Point"}
}