{
  "type": "Feature",
  "properties": {
    "gn:admin1_code":"4.0",
    "gn:admin2_code":"411",
    "gn:admin3_code":"41118.0",
    "gn:asciiname":"Obenberg",
    "gn:country_code":"AT",
    "gn:dem":338,
    "gn:feature_class":"P",
    "gn:feature_code":"PPL",
    "gn:name":"Obenberg",
    "gn:population":135,
    "gn:timezone":"Europe/Vienna",
    "iso:country":"AT",
    "wof:name":"Obenberg",
    "wof:placetype":"locality",
    "wof:population":135
},
  "geometry": {"coordinates":[14.5465,48.28108],"type":"Point"}
}