{
  "type": "Feature",
  "properties": {
    "gn:admin1_code":"4.0",
    "gn:admin2_code":"408",
    "gn:admin3_code":"40801.0",
    "gn:asciiname":"Kottingaistersheim",
    "gn:country_code":"AT",
    "gn:dem":439,
    "gn:feature_class":"P",
    "gn:feature_code":"PPL",
    "gn:name":"Kottingaistersheim",
    "gn:population":33,
    "gn:timezone":"Europe/Vienna",
    "iso:country":"AT",
    "wof:name":"Kottingaistersheim",
    "wof:placetype":"locality",
    "wof:population":33
},
  "geometry": {"coordinates":[13.73995,48.18154000000001],"type":"Point"}
}