{
  "type": "Feature",
  "properties": {
    "gn:admin1_code":"6.0",
    "gn:admin2_code":"623",
    "gn:admin3_code":"62383.0",
    "gn:asciiname":"Hart",
    "gn:cc2":"AT",
    "gn:country_code":"AT",
    "gn:dem":246,
    "gn:feature_class":"P",
    "gn:feature_code":"PPL",
    "gn:name":"Hart",
    "gn:population":0,
    "gn:timezone":"Europe/Vienna",
    "iso:country":"AT",
    "name:und_x_variant":[
        "Unterhart",
        "Hart"
    ],
    "wof:name":"Hart",
    "wof:placetype":"locality"
},
  "geometry": {"coordinates":[15.76667,46.73333],"type":"Point"}
}