{
  "type": "Feature",
  "properties": {
    "gn:admin1_code":"04",
    "gn:admin2_code":"406.0",
    "gn:admin3_code":"40618.0",
    "gn:asciiname":"Stiftungsberg",
    "gn:country_code":"AT",
    "gn:dem":825,
    "gn:feature_class":"P",
    "gn:feature_code":"PPL",
    "gn:name":"Stiftungsberg",
    "gn:population":96,
    "gn:timezone":"Europe/Vienna",
    "iso:country":"AT",
    "wof:name":"Stiftungsberg",
    "wof:placetype":"locality",
    "wof:population":96
},
  "geometry": {"coordinates":[14.60504,48.48151],"type":"Point"}
}