{
  "type": "Feature",
  "properties": {
    "gn:admin1_code":"4.0",
    "gn:admin2_code":"406",
    "gn:admin3_code":"40617.0",
    "gn:asciiname":"Ennsedt",
    "gn:country_code":"AT",
    "gn:dem":776,
    "gn:feature_class":"P",
    "gn:feature_code":"PPL",
    "gn:name":"Ennsedt",
    "gn:population":91,
    "gn:timezone":"Europe/Vienna",
    "iso:country":"AT",
    "wof:name":"Ennsedt",
    "wof:placetype":"locality",
    "wof:population":91
},
  "geometry": {"coordinates":[14.69258,48.43546],"type":"Point"}
}