{
  "type": "Feature",
  "properties": {
    "gn:admin1_code":"4.0",
    "gn:admin2_code":"406",
    "gn:admin3_code":"40615.0",
    "gn:asciiname":"Kerschbaum",
    "gn:country_code":"AT",
    "gn:dem":729,
    "gn:feature_class":"P",
    "gn:feature_code":"PPL",
    "gn:name":"Kerschbaum",
    "gn:population":331,
    "gn:timezone":"Europe/Vienna",
    "iso:country":"AT",
    "wof:name":"Kerschbaum",
    "wof:placetype":"locality",
    "wof:population":331
},
  "geometry": {"coordinates":[14.46667,48.58333],"type":"Point"}
}