{
  "type": "Feature",
  "properties": {
    "gn:admin1_code":"5.0",
    "gn:admin2_code":"504",
    "gn:admin3_code":"50419.0",
    "gn:asciiname":"Spangl",
    "gn:country_code":"AT",
    "gn:dem":863,
    "gn:feature_class":"P",
    "gn:feature_code":"PPL",
    "gn:name":"Spangl",
    "gn:population":0,
    "gn:timezone":"Europe/Vienna",
    "iso:country":"AT",
    "wof:name":"Spangl",
    "wof:placetype":"locality"
},
  "geometry": {"coordinates":[13.36311,47.44031],"type":"Point"}
}