{
  "type": "Feature",
  "properties": {
    "gn:admin1_code":"4.0",
    "gn:admin2_code":"408",
    "gn:admin3_code":"40810.0",
    "gn:asciiname":"Freindorf",
    "gn:country_code":"AT",
    "gn:dem":371,
    "gn:feature_class":"P",
    "gn:feature_code":"PPL",
    "gn:name":"Freindorf",
    "gn:population":88,
    "gn:timezone":"Europe/Vienna",
    "iso:country":"AT",
    "wof:name":"Freindorf",
    "wof:placetype":"locality",
    "wof:population":88
},
  "geometry": {"coordinates":[13.8202,48.34804000000001],"type":"Point"}
}