{
  "type": "Feature",
  "properties": {
    "gn:admin1_code":"3.0",
    "gn:admin2_code":"322",
    "gn:admin3_code":"32219.0",
    "gn:asciiname":"Jetzles",
    "gn:country_code":"AT",
    "gn:dem":532,
    "gn:feature_class":"P",
    "gn:feature_code":"PPL",
    "gn:name":"Jetzles",
    "gn:population":106,
    "gn:timezone":"Europe/Vienna",
    "iso:country":"AT",
    "wof:name":"Jetzles",
    "wof:placetype":"locality",
    "wof:population":106
},
  "geometry": {"coordinates":[15.18787,48.77909],"type":"Point"}
}