{
  "type": "Feature",
  "properties": {
    "gn:admin1_code":"03",
    "gn:admin2_code":"305.0",
    "gn:admin3_code":"30538.0",
    "gn:asciiname":"Ried",
    "gn:country_code":"AT",
    "gn:dem":289,
    "gn:feature_class":"P",
    "gn:feature_code":"PPL",
    "gn:name":"Ried",
    "gn:population":56,
    "gn:timezone":"Europe/Vienna",
    "iso:country":"AT",
    "name:bar_x_preferred":[
        "Ried"
    ],
    "name:ceb_x_preferred":[
        "Ried"
    ],
    "name:ces_x_preferred":[
        "Ried"
    ],
    "name:deu_x_preferred":[
        "Ried"
    ],
    "name:epo_x_preferred":[
        "Ried"
    ],
    "name:fra_x_preferred":[
        "Ried"
    ],
    "name:ita_x_preferred":[
        "Ried"
    ],
    "name:nld_x_preferred":[
        "Ried"
    ],
    "name:pol_x_preferred":[
        "Ried"
    ],
    "name:ron_x_preferred":[
        "Ried"
    ],
    "name:swe_x_preferred":[
        "Ried"
    ],
    "wof:name":"Ried",
    "wof:placetype":"locality",
    "wof:population":56
},
  "geometry": {"coordinates":[14.73333,48.15],"type":"Point"}
}