{
  "type": "Feature",
  "properties": {
    "gn:admin1_code":"5.0",
    "gn:admin2_code":"505",
    "gn:admin3_code":"50515.0",
    "gn:asciiname":"Lamm",
    "gn:country_code":"AT",
    "gn:dem":1149,
    "gn:feature_class":"P",
    "gn:feature_code":"PPL",
    "gn:name":"Lamm",
    "gn:population":386,
    "gn:timezone":"Europe/Vienna",
    "iso:country":"AT",
    "wof:name":"Lamm",
    "wof:placetype":"locality",
    "wof:population":386
},
  "geometry": {"coordinates":[13.55,47.13333],"type":"Point"}
}