{
  "type": "Feature",
  "properties": {
    "iso:country":"AT",
    "qs:a0":"\u00d6sterreich",
    "qs:a1":"*Ober\u00f6sterreich",
    "qs:a1r":"0",
    "qs:a2":"Gmunden",
    "qs:adm0":"\u00d6sterreich",
    "qs:la_lc":"*",
    "qs:level":"locality",
    "qs:loc":"Viechtwang",
    "qs:loc_alt":"Viechtwang",
    "qs:pop":0,
    "qs:type":"buffered point",
    "wof:name":"Viechtwang",
    "wof:placetype":"locality"
},
  "geometry": {"coordinates":[13.960342,47.920213],"type":"Point"}
}