{
  "type": "Feature",
  "properties": {
    "gn:admin1_code":"03",
    "gn:admin2_code":"305.0",
    "gn:admin3_code":"30501.0",
    "gn:asciiname":"Wallmersdorf",
    "gn:cc2":"AT",
    "gn:country_code":"AT",
    "gn:dem":334,
    "gn:feature_class":"P",
    "gn:feature_code":"PPL",
    "gn:name":"Wallmersdorf",
    "gn:population":113,
    "gn:timezone":"Europe/Vienna",
    "iso:country":"AT",
    "name:und_x_variant":[
        "Walmersdorf"
    ],
    "wof:name":"Wallmersdorf",
    "wof:placetype":"locality",
    "wof:population":113
},
  "geometry": {"coordinates":[14.80751,48.05296],"type":"Point"}
}