{
  "type": "Feature",
  "properties": {
    "gn:admin1_code":"4.0",
    "gn:admin2_code":"418",
    "gn:admin3_code":"41808.0",
    "gn:asciiname":"Au bei der Traun",
    "gn:country_code":"AT",
    "gn:dem":326,
    "gn:feature_class":"P",
    "gn:feature_code":"PPL",
    "gn:name":"Au bei der Traun",
    "gn:population":167,
    "gn:timezone":"Europe/Vienna",
    "iso:country":"AT",
    "wof:name":"Au bei der Traun",
    "wof:placetype":"locality",
    "wof:population":167
},
  "geometry": {"coordinates":[13.96307,48.12419000000001],"type":"Point"}
}