{
  "type": "Feature",
  "properties": {
    "gn:admin1_code":"2.0",
    "gn:admin2_code":"209",
    "gn:admin3_code":"20909.0",
    "gn:asciiname":"Achalm",
    "gn:country_code":"AT",
    "gn:dem":417,
    "gn:feature_class":"P",
    "gn:feature_code":"PPL",
    "gn:name":"Achalm",
    "gn:population":182,
    "gn:timezone":"Europe/Vienna",
    "iso:country":"AT",
    "wof:name":"Achalm",
    "wof:placetype":"locality",
    "wof:population":182
},
  "geometry": {"coordinates":[14.93333,46.65],"type":"Point"}
}