{
  "type": "Feature",
  "properties": {
    "gn:admin1_code":"2.0",
    "gn:admin2_code":"204",
    "gn:admin3_code":"20409.0",
    "gn:asciiname":"Replach",
    "gn:country_code":"AT",
    "gn:dem":451,
    "gn:feature_class":"P",
    "gn:feature_code":"PPL",
    "gn:name":"Replach",
    "gn:population":77,
    "gn:timezone":"Europe/Vienna",
    "iso:country":"AT",
    "wof:name":"Replach",
    "wof:placetype":"locality",
    "wof:population":77
},
  "geometry": {"coordinates":[14.43453,46.63683],"type":"Point"}
}