{
  "type": "Feature",
  "properties": {
    "gn:admin1_code":"4.0",
    "gn:admin2_code":"409",
    "gn:admin3_code":"40917.0",
    "gn:asciiname":"Hofern",
    "gn:country_code":"AT",
    "gn:dem":414,
    "gn:feature_class":"P",
    "gn:feature_code":"PPL",
    "gn:name":"Hofern",
    "gn:population":0,
    "gn:timezone":"Europe/Vienna",
    "iso:country":"AT",
    "wof:name":"Hofern",
    "wof:placetype":"locality"
},
  "geometry": {"coordinates":[14.12267,47.94791],"type":"Point"}
}