{
  "type": "Feature",
  "properties": {
    "gn:admin1_code":"3.0",
    "gn:admin2_code":"320",
    "gn:admin3_code":"32001.0",
    "gn:asciiname":"Brettl",
    "gn:country_code":"AT",
    "gn:dem":473,
    "gn:feature_class":"P",
    "gn:feature_code":"PPL",
    "gn:name":"Brettl",
    "gn:population":0,
    "gn:timezone":"Europe/Vienna",
    "iso:country":"AT",
    "wof:name":"Brettl",
    "wof:placetype":"locality"
},
  "geometry": {"coordinates":[15.06037,47.95498],"type":"Point"}
}