{
  "type": "Feature",
  "properties": {
    "gn:admin1_code":"4.0",
    "gn:admin2_code":"415",
    "gn:admin3_code":"41516.0",
    "gn:asciiname":"Baschallern",
    "gn:country_code":"AT",
    "gn:dem":392,
    "gn:feature_class":"P",
    "gn:feature_code":"PPL",
    "gn:name":"Baschallern",
    "gn:population":0,
    "gn:timezone":"Europe/Vienna",
    "iso:country":"AT",
    "wof:name":"Baschallern",
    "wof:placetype":"locality"
},
  "geometry": {"coordinates":[14.33333,48.06667],"type":"Point"}
}