{
  "type": "Feature",
  "properties": {
    "gn:admin1_code":"2.0",
    "gn:admin2_code":"210",
    "gn:admin3_code":"21005.0",
    "gn:asciiname":"Kaidern",
    "gn:country_code":"AT",
    "gn:dem":788,
    "gn:feature_class":"P",
    "gn:feature_code":"PPL",
    "gn:name":"Kaidern",
    "gn:population":29,
    "gn:timezone":"Europe/Vienna",
    "iso:country":"AT",
    "wof:name":"Kaidern",
    "wof:placetype":"locality",
    "wof:population":29
},
  "geometry": {"coordinates":[14.07028,46.77056],"type":"Point"}
}