{
  "type": "Feature",
  "properties": {
    "gn:admin1_code":"02",
    "gn:admin2_code":"209.0",
    "gn:admin3_code":"20913.0",
    "gn:asciiname":"Siebending",
    "gn:country_code":"AT",
    "gn:dem":420,
    "gn:feature_class":"P",
    "gn:feature_code":"PPL",
    "gn:name":"Siebending",
    "gn:population":107,
    "gn:timezone":"Europe/Vienna",
    "iso:country":"AT",
    "wof:name":"Siebending",
    "wof:placetype":"locality",
    "wof:population":107
},
  "geometry": {"coordinates":[14.85,46.76667],"type":"Point"}
}