{
  "type": "Feature",
  "properties": {
    "gn:admin1_code":"3.0",
    "gn:admin2_code":"318",
    "gn:admin3_code":"31808.0",
    "gn:asciiname":"Hart",
    "gn:country_code":"AT",
    "gn:dem":496,
    "gn:feature_class":"P",
    "gn:feature_code":"PPL",
    "gn:name":"Hart",
    "gn:population":337,
    "gn:timezone":"Europe/Vienna",
    "iso:country":"AT",
    "name:bel_x_preferred":[
        "\u0425\u0430\u0440\u0442"
    ],
    "name:bul_x_preferred":[
        "\u0425\u0430\u0440\u0442"
    ],
    "name:ceb_x_preferred":[
        "Hart"
    ],
    "name:ces_x_preferred":[
        "Hart"
    ],
    "name:deu_x_preferred":[
        "Hart"
    ],
    "name:fin_x_preferred":[
        "Hart"
    ],
    "name:fra_x_preferred":[
        "Hart"
    ],
    "name:ita_x_preferred":[
        "Hart"
    ],
    "name:nds_x_preferred":[
        "Hart"
    ],
    "name:nld_x_preferred":[
        "Hart"
    ],
    "name:pol_x_preferred":[
        "Hart"
    ],
    "name:por_x_preferred":[
        "Hart"
    ],
    "name:rus_x_preferred":[
        "\u0425\u0430\u0440\u0442"
    ],
    "name:slv_x_preferred":[
        "Hart"
    ],
    "name:spa_x_preferred":[
        "Hart"
    ],
    "name:srp_x_preferred":[
        "\u0425\u0430\u0440\u0442"
    ],
    "name:swe_x_preferred":[
        "Hart"
    ],
    "name:ukr_x_preferred":[
        "\u0425\u0430\u0440\u0442"
    ],
    "wof:name":"Hart",
    "wof:placetype":"locality",
    "wof:population":337
},
  "geometry": {"coordinates":[15.93614,47.66729],"type":"Point"}
}