{
  "type": "Feature",
  "properties": {
    "gn:admin1_code":"4.0",
    "gn:admin2_code":"405",
    "gn:admin3_code":"40507.0",
    "gn:asciiname":"Stieglhoefen",
    "gn:country_code":"AT",
    "gn:dem":269,
    "gn:feature_class":"P",
    "gn:feature_code":"PPL",
    "gn:name":"Stieglh\u00f6fen",
    "gn:population":72,
    "gn:timezone":"Europe/Vienna",
    "iso:country":"AT",
    "wof:name":"Stieglhoefen",
    "wof:placetype":"locality",
    "wof:population":72
},
  "geometry": {"coordinates":[14.01263,48.30466],"type":"Point"}
}