{
  "type": "Feature",
  "properties": {
    "gn:admin1_code":"6.0",
    "gn:admin2_code":"622",
    "gn:admin3_code":"62205.0",
    "gn:asciiname":"Burgstall",
    "gn:country_code":"AT",
    "gn:dem":375,
    "gn:feature_class":"P",
    "gn:feature_code":"PPL",
    "gn:name":"Burgstall",
    "gn:population":0,
    "gn:timezone":"Europe/Vienna",
    "iso:country":"AT",
    "wof:name":"Burgstall",
    "wof:placetype":"locality"
},
  "geometry": {"coordinates":[16.01719,47.22486],"type":"Point"}
}