{
  "type": "Feature",
  "properties": {
    "gn:admin1_code":"3.0",
    "gn:admin2_code":"315",
    "gn:admin3_code":"31534.0",
    "gn:asciiname":"Weisspyhra",
    "gn:country_code":"AT",
    "gn:dem":614,
    "gn:feature_class":"P",
    "gn:feature_code":"PPL",
    "gn:name":"Wei\u00dfpyhra",
    "gn:population":40,
    "gn:timezone":"Europe/Vienna",
    "iso:country":"AT",
    "wof:name":"Weisspyhra",
    "wof:placetype":"locality",
    "wof:population":40
},
  "geometry": {"coordinates":[15.15791,48.30718],"type":"Point"}
}