{
  "type": "Feature",
  "properties": {
    "gn:admin1_code":"04",
    "gn:admin2_code":"418.0",
    "gn:admin3_code":"41808.0",
    "gn:asciiname":"Wallnstorf",
    "gn:country_code":"AT",
    "gn:dem":345,
    "gn:feature_class":"P",
    "gn:feature_code":"PPL",
    "gn:name":"Wallnstorf",
    "gn:population":28,
    "gn:timezone":"Europe/Vienna",
    "iso:country":"AT",
    "wof:name":"Wallnstorf",
    "wof:placetype":"locality",
    "wof:population":28
},
  "geometry": {"coordinates":[13.93333,48.13333],"type":"Point"}
}