{
  "type": "Feature",
  "properties": {
    "gn:admin1_code":"2.0",
    "gn:admin2_code":"206",
    "gn:admin3_code":"20607.0",
    "gn:asciiname":"Innerfragant",
    "gn:country_code":"AT",
    "gn:dem":1141,
    "gn:feature_class":"P",
    "gn:feature_code":"PPL",
    "gn:name":"Innerfragant",
    "gn:population":47,
    "gn:timezone":"Europe/Vienna",
    "iso:country":"AT",
    "wof:name":"Innerfragant",
    "wof:placetype":"locality",
    "wof:population":47
},
  "geometry": {"coordinates":[13.05833,46.96528],"type":"Point"}
}