{
  "type": "Feature",
  "properties": {
    "gn:admin1_code":"4.0",
    "gn:admin2_code":"414",
    "gn:admin3_code":"41410.0",
    "gn:asciiname":"Kritzing",
    "gn:country_code":"AT",
    "gn:dem":452,
    "gn:feature_class":"P",
    "gn:feature_code":"PPL",
    "gn:name":"Kritzing",
    "gn:population":105,
    "gn:timezone":"Europe/Vienna",
    "iso:country":"AT",
    "wof:name":"Kritzing",
    "wof:placetype":"locality",
    "wof:population":105
},
  "geometry": {"coordinates":[13.53421,48.54593],"type":"Point"}
}