{
  "type": "Feature",
  "properties": {
    "gn:admin1_code":"03",
    "gn:admin2_code":"306.0",
    "gn:admin3_code":"30625.0",
    "gn:asciiname":"Einoede",
    "gn:country_code":"AT",
    "gn:dem":291,
    "gn:feature_class":"P",
    "gn:feature_code":"PPL",
    "gn:name":"Ein\u00f6de",
    "gn:population":93,
    "gn:timezone":"Europe/Vienna",
    "iso:country":"AT",
    "wof:name":"Einoede",
    "wof:placetype":"locality",
    "wof:population":93
},
  "geometry": {"coordinates":[16.23539,48.02254],"type":"Point"}
}