{
  "type": "Feature",
  "properties": {
    "gn:admin1_code":"4.0",
    "gn:asciiname":"Adligstadt",
    "gn:country_code":"AT",
    "gn:dem":725,
    "gn:feature_class":"P",
    "gn:feature_code":"PPL",
    "gn:name":"Adligstadt",
    "gn:population":0,
    "gn:timezone":"Europe/Vienna",
    "iso:country":"AT",
    "wof:name":"Adligstadt",
    "wof:placetype":"locality"
},
  "geometry": {"coordinates":[12.74066,47.84139],"type":"Point"}
}