{
  "type": "Feature",
  "properties": {
    "gn:admin1_code":"02",
    "gn:admin2_code":"205.0",
    "gn:admin3_code":"20531.0",
    "gn:asciiname":"Sankt Andrae",
    "gn:country_code":"AT",
    "gn:dem":972,
    "gn:feature_class":"P",
    "gn:feature_code":"PPL",
    "gn:name":"Sankt Andr\u00e4",
    "gn:population":71,
    "gn:timezone":"Europe/Vienna",
    "iso:country":"AT",
    "wof:name":"Sankt Andrae",
    "wof:placetype":"locality",
    "wof:population":71
},
  "geometry": {"coordinates":[14.17222,46.87194],"type":"Point"}
}