{
  "type": "Feature",
  "properties": {
    "gn:admin1_code":"4.0",
    "gn:admin2_code":"412",
    "gn:admin3_code":"41205.0",
    "gn:asciiname":"Erltberg",
    "gn:country_code":"AT",
    "gn:dem":456,
    "gn:feature_class":"P",
    "gn:feature_code":"PPL",
    "gn:name":"Erltberg",
    "gn:population":0,
    "gn:timezone":"Europe/Vienna",
    "iso:country":"AT",
    "wof:name":"Erltberg",
    "wof:placetype":"locality"
},
  "geometry": {"coordinates":[13.4074,48.24102],"type":"Point"}
}