{
  "type": "Feature",
  "properties": {
    "gn:admin1_code":"2.0",
    "gn:admin2_code":"205",
    "gn:admin3_code":"20519.0",
    "gn:asciiname":"Lorenzenberg",
    "gn:country_code":"AT",
    "gn:dem":610,
    "gn:feature_class":"P",
    "gn:feature_code":"PPL",
    "gn:name":"Lorenzenberg",
    "gn:population":41,
    "gn:timezone":"Europe/Vienna",
    "iso:country":"AT",
    "wof:name":"Lorenzenberg",
    "wof:placetype":"locality",
    "wof:population":41
},
  "geometry": {"coordinates":[14.43333,46.91667],"type":"Point"}
}