{
  "type": "Feature",
  "properties": {
    "gn:admin1_code":"2.0",
    "gn:admin2_code":"207",
    "gn:admin3_code":"20713.0",
    "gn:asciiname":"Goeriach",
    "gn:country_code":"AT",
    "gn:dem":661,
    "gn:feature_class":"P",
    "gn:feature_code":"PPL",
    "gn:name":"G\u00f6riach",
    "gn:population":99,
    "gn:timezone":"Europe/Vienna",
    "iso:country":"AT",
    "wof:name":"Goeriach",
    "wof:placetype":"locality",
    "wof:population":99
},
  "geometry": {"coordinates":[13.61583,46.56167],"type":"Point"}
}