{
  "type": "Feature",
  "properties": {
    "gn:admin1_code":"06",
    "gn:admin2_code":"623.0",
    "gn:admin3_code":"62380.0",
    "gn:asciiname":"Liergl",
    "gn:country_code":"AT",
    "gn:dem":378,
    "gn:feature_class":"P",
    "gn:feature_code":"PPL",
    "gn:name":"Liergl",
    "gn:population":0,
    "gn:timezone":"Europe/Vienna",
    "iso:country":"AT",
    "wof:name":"Liergl",
    "wof:placetype":"locality"
},
  "geometry": {"coordinates":[15.86667,46.86667],"type":"Point"}
}