{
  "type": "Feature",
  "properties": {
    "gn:admin1_code":"2.0",
    "gn:admin2_code":"207",
    "gn:admin3_code":"20711.0",
    "gn:asciiname":"Mallenitzen",
    "gn:country_code":"AT",
    "gn:dem":585,
    "gn:feature_class":"P",
    "gn:feature_code":"PPL",
    "gn:name":"Mallenitzen",
    "gn:population":244,
    "gn:timezone":"Europe/Vienna",
    "iso:country":"AT",
    "wof:name":"Mallenitzen",
    "wof:placetype":"locality",
    "wof:population":244
},
  "geometry": {"coordinates":[13.98757,46.55437],"type":"Point"}
}