{
  "type": "Feature",
  "properties": {
    "gn:admin1_code":"7.0",
    "gn:admin2_code":"704",
    "gn:admin3_code":"70410.0",
    "gn:asciiname":"Haberberg",
    "gn:country_code":"AT",
    "gn:dem":870,
    "gn:feature_class":"P",
    "gn:feature_code":"PPL",
    "gn:name":"Haberberg",
    "gn:population":0,
    "gn:timezone":"Europe/Vienna",
    "iso:country":"AT",
    "wof:name":"Haberberg",
    "wof:placetype":"locality"
},
  "geometry": {"coordinates":[12.46667,47.55],"type":"Point"}
}