{
  "type": "Feature",
  "properties": {
    "gn:admin1_code":"2.0",
    "gn:admin2_code":"210",
    "gn:admin3_code":"21002.0",
    "gn:asciiname":"Boesenlacken",
    "gn:country_code":"AT",
    "gn:dem":569,
    "gn:feature_class":"P",
    "gn:feature_code":"PPL",
    "gn:name":"B\u00f6senlacken",
    "gn:population":120,
    "gn:timezone":"Europe/Vienna",
    "iso:country":"AT",
    "wof:name":"Boesenlacken",
    "wof:placetype":"locality",
    "wof:population":120
},
  "geometry": {"coordinates":[14.10915,46.70359000000001],"type":"Point"}
}