{
  "type": "Feature",
  "properties": {
    "gn:admin1_code":"04",
    "gn:admin2_code":"415.0",
    "gn:admin3_code":"41521.0",
    "gn:asciiname":"Wickendorf",
    "gn:country_code":"AT",
    "gn:dem":366,
    "gn:feature_class":"P",
    "gn:feature_code":"PPL",
    "gn:name":"Wickendorf",
    "gn:population":0,
    "gn:timezone":"Europe/Vienna",
    "iso:country":"AT",
    "wof:name":"Wickendorf",
    "wof:placetype":"locality"
},
  "geometry": {"coordinates":[14.34196,48.10365],"type":"Point"}
}