{
  "type": "Feature",
  "properties": {
    "gn:admin1_code":"3.0",
    "gn:admin2_code":"309",
    "gn:admin3_code":"30940.0",
    "gn:asciiname":"Grossneusiedl",
    "gn:country_code":"AT",
    "gn:dem":588,
    "gn:feature_class":"P",
    "gn:feature_code":"PPL",
    "gn:name":"Grossneusiedl",
    "gn:population":0,
    "gn:timezone":"Europe/Vienna",
    "iso:country":"AT",
    "wof:name":"Grossneusiedl",
    "wof:placetype":"locality"
},
  "geometry": {"coordinates":[15.01667,48.71667],"type":"Point"}
}