{
  "type": "Feature",
  "properties": {
    "gn:admin1_code":"3.0",
    "gn:admin2_code":"320",
    "gn:admin3_code":"32015.0",
    "gn:asciiname":"Ewixengraben",
    "gn:country_code":"AT",
    "gn:dem":368,
    "gn:feature_class":"P",
    "gn:feature_code":"PPL",
    "gn:name":"Ewixengraben",
    "gn:population":0,
    "gn:timezone":"Europe/Vienna",
    "iso:country":"AT",
    "wof:name":"Ewixengraben",
    "wof:placetype":"locality"
},
  "geometry": {"coordinates":[15.03788,48.02059000000001],"type":"Point"}
}