{
  "type": "Feature",
  "properties": {
    "gn:admin1_code":"3.0",
    "gn:admin2_code":"322",
    "gn:admin3_code":"32210.0",
    "gn:asciiname":"Illmau",
    "gn:country_code":"AT",
    "gn:dem":534,
    "gn:feature_class":"P",
    "gn:feature_code":"PPL",
    "gn:name":"Illmau",
    "gn:population":0,
    "gn:timezone":"Europe/Vienna",
    "iso:country":"AT",
    "wof:name":"Illmau",
    "wof:placetype":"locality"
},
  "geometry": {"coordinates":[15.23333,48.93333],"type":"Point"}
}