{
  "type": "Feature",
  "properties": {
    "gn:gn_country":"AT",
    "gn:gn_fcode":"PPL",
    "gn:gn_pop":0,
    "iso:country":"AT",
    "name:unk_x_variant":[
        "Sankt Anton"
    ],
    "qs_pg:aaroncc":"AT",
    "qs_pg:gn_country":"AT",
    "qs_pg:gn_fcode":"PPL",
    "qs_pg:gn_pop":0,
    "qs_pg:name":"St. Anton an der Je\u00dfnitz",
    "qs_pg:name_adm0":"\u00d6sterreich",
    "qs_pg:name_adm1":"Nieder\u00f6sterreich",
    "qs_pg:photos":22,
    "qs_pg:photos_1k":4,
    "qs_pg:photos_9k":1,
    "qs_pg:photos_9r":1,
    "qs_pg:photos_all":22,
    "qs_pg:photos_sr":1,
    "qs_pg:pop_sr":0,
    "qs_pg:qs_pg_placetype":"locality",
    "qs_pg:qs_pg_placetype_gp":"Town",
    "qs_pg:woe_adm0":23424750,
    "woe:adm0_id":23424750,
    "woe:name_adm0":"\u00d6sterreich",
    "woe:name_adm1":"Nieder\u00f6sterreich",
    "woe:placetype":"Town",
    "wof:name":"St. Anton an der Je\u00dfnitz",
    "wof:placetype":"locality"
},
  "geometry": {"coordinates":[15.20688,47.96148],"type":"Point"}
}