{
  "type": "Feature",
  "properties": {
    "gn:admin1_code":"1.0",
    "gn:admin2_code":"105",
    "gn:admin3_code":"10504.0",
    "gn:asciiname":"Kenndorf",
    "gn:country_code":"AT",
    "gn:dem":323,
    "gn:feature_class":"P",
    "gn:feature_code":"PPL",
    "gn:name":"Kenndorf",
    "gn:population":0,
    "gn:timezone":"Europe/Vienna",
    "iso:country":"AT",
    "wof:name":"Kenndorf",
    "wof:placetype":"locality"
},
  "geometry": {"coordinates":[16.1525,46.98083],"type":"Point"}
}