{
  "type": "Feature",
  "properties": {
    "gn:admin1_code":"4.0",
    "gn:admin2_code":"417",
    "gn:admin3_code":"41744.0",
    "gn:asciiname":"Zehentpoint",
    "gn:country_code":"AT",
    "gn:dem":551,
    "gn:feature_class":"P",
    "gn:feature_code":"PPL",
    "gn:name":"Zehentpoint",
    "gn:population":26,
    "gn:timezone":"Europe/Vienna",
    "iso:country":"AT",
    "wof:name":"Zehentpoint",
    "wof:placetype":"locality",
    "wof:population":26
},
  "geometry": {"coordinates":[13.6312,48.0613],"type":"Point"}
}