{
  "type": "Feature",
  "properties": {
    "gn:admin1_code":"4.0",
    "gn:admin2_code":"413",
    "gn:admin3_code":"41332.0",
    "gn:asciiname":"Erdmannsdorf",
    "gn:country_code":"AT",
    "gn:dem":584,
    "gn:feature_class":"P",
    "gn:feature_code":"PPL",
    "gn:name":"Erdmannsdorf",
    "gn:population":158,
    "gn:timezone":"Europe/Vienna",
    "iso:country":"AT",
    "name:deu_x_preferred":[
        "Erdmannsdorf"
    ],
    "name:pol_x_preferred":[
        "Erdmannsdorf"
    ],
    "name:rus_x_preferred":[
        "\u042d\u0440\u0434\u043c\u0430\u043d\u0441\u0434\u043e\u0440\u0444"
    ],
    "wof:name":"Erdmannsdorf",
    "wof:placetype":"locality",
    "wof:population":158
},
  "geometry": {"coordinates":[14.04679,48.42493],"type":"Point"}
}