{
  "type": "Feature",
  "properties": {
    "gn:admin1_code":"3.0",
    "gn:admin2_code":"315",
    "gn:admin3_code":"31503.0",
    "gn:asciiname":"Gumprechtsberg",
    "gn:country_code":"AT",
    "gn:dem":284,
    "gn:feature_class":"P",
    "gn:feature_code":"PPL",
    "gn:name":"Gumprechtsberg",
    "gn:population":0,
    "gn:timezone":"Europe/Vienna",
    "iso:country":"AT",
    "wof:name":"Gumprechtsberg",
    "wof:placetype":"locality"
},
  "geometry": {"coordinates":[15.18333,48.13333],"type":"Point"}
}