{
  "type": "Feature",
  "properties": {
    "gn:admin1_code":"03",
    "gn:admin2_code":"311.0",
    "gn:admin3_code":"31104.0",
    "gn:asciiname":"Johannesthal",
    "gn:country_code":"AT",
    "gn:dem":449,
    "gn:feature_class":"P",
    "gn:feature_code":"PPLL",
    "gn:name":"Johannesthal",
    "gn:population":0,
    "gn:timezone":"Europe/Vienna",
    "iso:country":"AT",
    "wof:name":"Johannesthal",
    "wof:placetype":"locality"
},
  "geometry": {"coordinates":[15.65556,48.82222],"type":"Point"}
}