{
  "type": "Feature",
  "properties": {
    "gn:admin1_code":"6.0",
    "gn:admin2_code":"621",
    "gn:admin3_code":"62143.0",
    "gn:asciiname":"Pernreit",
    "gn:country_code":"AT",
    "gn:dem":733,
    "gn:feature_class":"P",
    "gn:feature_code":"PPL",
    "gn:name":"Pernreit",
    "gn:population":88,
    "gn:timezone":"Europe/Vienna",
    "iso:country":"AT",
    "wof:name":"Pernreit",
    "wof:placetype":"locality",
    "wof:population":88
},
  "geometry": {"coordinates":[15.675,47.61175],"type":"Point"}
}