{
  "type": "Feature",
  "properties": {
    "gn:admin1_code":"04",
    "gn:admin2_code":"403.0",
    "gn:admin3_code":"40301.0",
    "gn:asciiname":"Unterleithen",
    "gn:country_code":"AT",
    "gn:dem":314,
    "gn:feature_class":"P",
    "gn:feature_code":"PPL",
    "gn:name":"Unterleithen",
    "gn:population":318,
    "gn:timezone":"Europe/Vienna",
    "iso:country":"AT",
    "wof:name":"Unterleithen",
    "wof:placetype":"locality",
    "wof:population":318
},
  "geometry": {"coordinates":[14.03333,48.18333],"type":"Point"}
}