{
  "type": "Feature",
  "properties": {
    "gn:admin1_code":"7.0",
    "gn:admin2_code":"702",
    "gn:admin3_code":"70208.0",
    "gn:asciiname":"Oberastlehn",
    "gn:cc2":"AT",
    "gn:country_code":"AT",
    "gn:dem":1182,
    "gn:feature_class":"P",
    "gn:feature_code":"PPL",
    "gn:name":"Oberastlehn",
    "gn:population":0,
    "gn:timezone":"Europe/Vienna",
    "iso:country":"AT",
    "name:und_x_variant":[
        "Ober Astlen",
        "Oberastlehn"
    ],
    "wof:name":"Oberastlehn",
    "wof:placetype":"locality"
},
  "geometry": {"coordinates":[10.96667,47.05],"type":"Point"}
}