{
  "type": "Feature",
  "properties": {
    "gn:admin1_code":"03",
    "gn:admin2_code":"311.0",
    "gn:admin3_code":"31129.0",
    "gn:asciiname":"Starrein",
    "gn:country_code":"AT",
    "gn:dem":451,
    "gn:feature_class":"P",
    "gn:feature_code":"PPL",
    "gn:name":"Starrein",
    "gn:population":130,
    "gn:timezone":"Europe/Vienna",
    "iso:country":"AT",
    "wof:name":"Starrein",
    "wof:placetype":"locality",
    "wof:population":130
},
  "geometry": {"coordinates":[15.76667,48.76667],"type":"Point"}
}