{
  "type": "Feature",
  "properties": {
    "gn:admin1_code":"3.0",
    "gn:admin2_code":"321",
    "gn:admin3_code":"32135.0",
    "gn:asciiname":"Frauenhofen",
    "gn:country_code":"AT",
    "gn:dem":176,
    "gn:feature_class":"P",
    "gn:feature_code":"PPL",
    "gn:name":"Frauenhofen",
    "gn:population":106,
    "gn:timezone":"Europe/Vienna",
    "iso:country":"AT",
    "wof:name":"Frauenhofen",
    "wof:placetype":"locality",
    "wof:population":106
},
  "geometry": {"coordinates":[16.07866,48.30706],"type":"Point"}
}