{
  "type": "Feature",
  "properties": {
    "gn:admin1_code":"2.0",
    "gn:admin2_code":"210",
    "gn:admin3_code":"21003.0",
    "gn:asciiname":"Kulm",
    "gn:country_code":"AT",
    "gn:dem":586,
    "gn:feature_class":"P",
    "gn:feature_code":"PPL",
    "gn:name":"Kulm",
    "gn:population":7,
    "gn:timezone":"Europe/Vienna",
    "iso:country":"AT",
    "name:ceb_x_preferred":[
        "Kulm"
    ],
    "name:chv_x_preferred":[
        "\u041a\u0443\u043b\u044c\u043c"
    ],
    "name:dan_x_preferred":[
        "Kulm"
    ],
    "name:deu_x_preferred":[
        "Kulm"
    ],
    "name:fra_x_preferred":[
        "Kulm"
    ],
    "name:ita_x_preferred":[
        "Kulm"
    ],
    "name:jpn_x_preferred":[
        "\u30af\u30eb\u30e0"
    ],
    "name:nld_x_preferred":[
        "Kulm"
    ],
    "name:pol_x_preferred":[
        "Kulm"
    ],
    "name:rus_x_preferred":[
        "\u041a\u0443\u043b\u044c\u043c"
    ],
    "name:slk_x_preferred":[
        "Kulm"
    ],
    "name:swe_x_preferred":[
        "Kulm"
    ],
    "wof:name":"Kulm",
    "wof:placetype":"locality",
    "wof:population":7
},
  "geometry": {"coordinates":[14.25631,46.73651],"type":"Point"}
}