{
  "type": "Feature",
  "properties": {
    "gn:admin1_code":"2.0",
    "gn:admin2_code":"210",
    "gn:admin3_code":"21003.0",
    "gn:asciiname":"Kulm",
    "gn:country_code":"AT",
    "gn:dem":586,
    "gn:feature_class":"P",
    "gn:feature_code":"PPL",
    "gn:name":"Kulm",
    "gn:population":7,
    "gn:timezone":"Europe/Vienna",
    "iso:country":"AT",
    "wof:name":"Kulm",
    "wof:placetype":"locality",
    "wof:population":7
},
  "geometry": {"coordinates":[14.25631,46.73651],"type":"Point"}
}