{
  "type": "Feature",
  "properties": {
    "gn:admin1_code":"4.0",
    "gn:admin2_code":"417",
    "gn:admin3_code":"41716.0",
    "gn:asciiname":"Biber",
    "gn:country_code":"AT",
    "gn:dem":495,
    "gn:feature_class":"P",
    "gn:feature_code":"PPL",
    "gn:name":"Biber",
    "gn:population":69,
    "gn:timezone":"Europe/Vienna",
    "iso:country":"AT",
    "name:ceb_x_preferred":[
        "Biber"
    ],
    "name:ces_x_preferred":[
        "Biber"
    ],
    "name:deu_x_preferred":[
        "Biber"
    ],
    "name:fra_x_preferred":[
        "Biber"
    ],
    "name:hun_x_preferred":[
        "Biber"
    ],
    "name:ita_x_preferred":[
        "Biber"
    ],
    "name:kor_x_preferred":[
        "\ube44\ubc84"
    ],
    "name:nld_x_preferred":[
        "Biber"
    ],
    "name:pol_x_preferred":[
        "Biber"
    ],
    "name:rus_x_preferred":[
        "\u0411\u0438\u0431\u0435\u0440"
    ],
    "name:srp_x_preferred":[
        "\u0411\u0438\u0431\u0435\u0440"
    ],
    "name:swe_x_preferred":[
        "Biber"
    ],
    "name:ukr_x_preferred":[
        "\u0411\u0456\u0431\u0435\u0440"
    ],
    "wof:name":"Biber",
    "wof:placetype":"locality",
    "wof:population":69
},
  "geometry": {"coordinates":[13.53657,48.03792],"type":"Point"}
}