{
  "type": "Feature",
  "properties": {
    "gn:admin1_code":"4.0",
    "gn:admin2_code":"417",
    "gn:admin3_code":"41716.0",
    "gn:asciiname":"Biber",
    "gn:country_code":"AT",
    "gn:dem":495,
    "gn:feature_class":"P",
    "gn:feature_code":"PPL",
    "gn:name":"Biber",
    "gn:population":69,
    "gn:timezone":"Europe/Vienna",
    "iso:country":"AT",
    "wof:name":"Biber",
    "wof:placetype":"locality",
    "wof:population":69
},
  "geometry": {"coordinates":[13.53657,48.03792],"type":"Point"}
}