{
  "type": "Feature",
  "properties": {
    "gn:admin1_code":"06",
    "gn:admin2_code":"623.0",
    "gn:admin3_code":"62380.0",
    "gn:asciiname":"Liesberg",
    "gn:country_code":"AT",
    "gn:dem":357,
    "gn:feature_class":"P",
    "gn:feature_code":"PPL",
    "gn:name":"Liesberg",
    "gn:population":0,
    "gn:timezone":"Europe/Vienna",
    "iso:country":"AT",
    "name:als_x_preferred":[
        "Liesberg"
    ],
    "name:ceb_x_preferred":[
        "Liesberg"
    ],
    "name:chv_x_preferred":[
        "\u041b\u0438\u0441\u0431\u0435\u0440\u0433"
    ],
    "name:deu_x_preferred":[
        "Liesberg"
    ],
    "name:epo_x_preferred":[
        "Liesberg"
    ],
    "name:eus_x_preferred":[
        "Liesberg"
    ],
    "name:fra_x_preferred":[
        "Liesberg"
    ],
    "name:ita_x_preferred":[
        "Liesberg"
    ],
    "name:kaz_x_preferred":[
        "\u041b\u0438\u0441\u0431\u0435\u0440\u0433"
    ],
    "name:lmo_x_preferred":[
        "Liesberg"
    ],
    "name:msa_x_preferred":[
        "Liesberg"
    ],
    "name:nld_x_preferred":[
        "Liesberg"
    ],
    "name:nno_x_preferred":[
        "Liesberg"
    ],
    "name:rus_x_preferred":[
        "\u041b\u0438\u0441\u0431\u0435\u0440\u0433"
    ],
    "name:spa_x_preferred":[
        "Liesberg"
    ],
    "name:sqi_x_preferred":[
        "Liesberg"
    ],
    "name:swe_x_preferred":[
        "Liesberg"
    ],
    "name:uzb_x_preferred":[
        "Liesberg"
    ],
    "name:vol_x_preferred":[
        "Liesberg"
    ],
    "name:war_x_preferred":[
        "Liesberg"
    ],
    "name:zho_x_preferred":[
        "\u5229\u65af\u4f2f\u683c"
    ],
    "wof:name":"Liesberg",
    "wof:placetype":"locality"
},
  "geometry": {"coordinates":[15.78333,46.86667],"type":"Point"}
}