{
  "type": "Feature",
  "properties": {
    "gn:admin1_code":"02",
    "gn:admin2_code":"206.0",
    "gn:admin3_code":"20637.0",
    "gn:asciiname":"Rottenstein",
    "gn:country_code":"AT",
    "gn:dem":1447,
    "gn:feature_class":"P",
    "gn:feature_code":"PPL",
    "gn:name":"Rottenstein",
    "gn:population":71,
    "gn:timezone":"Europe/Vienna",
    "iso:country":"AT",
    "wof:name":"Rottenstein",
    "wof:placetype":"locality",
    "wof:population":71
},
  "geometry": {"coordinates":[13.23333,46.78333],"type":"Point"}
}