{
  "type": "Feature",
  "properties": {
    "gn:admin1_code":"04",
    "gn:admin2_code":"406.0",
    "gn:admin3_code":"40619.0",
    "gn:asciiname":"Pehersdorf",
    "gn:country_code":"AT",
    "gn:dem":724,
    "gn:feature_class":"P",
    "gn:feature_code":"PPL",
    "gn:name":"Pehersdorf",
    "gn:population":61,
    "gn:timezone":"Europe/Vienna",
    "iso:country":"AT",
    "wof:name":"Pehersdorf",
    "wof:placetype":"locality",
    "wof:population":61
},
  "geometry": {"coordinates":[14.68494,48.40926],"type":"Point"}
}