{
  "type": "Feature",
  "properties": {
    "gn:admin1_code":"03",
    "gn:admin2_code":"309.0",
    "gn:admin3_code":"30912.0",
    "gn:asciiname":"Rothfarn",
    "gn:cc2":"AT",
    "gn:country_code":"AT",
    "gn:dem":588,
    "gn:feature_class":"P",
    "gn:feature_code":"PPL",
    "gn:name":"Rothfarn",
    "gn:population":76,
    "gn:timezone":"Europe/Vienna",
    "iso:country":"AT",
    "name:und_x_variant":[
        "Rothfahrn"
    ],
    "wof:name":"Rothfarn",
    "wof:placetype":"locality",
    "wof:population":76
},
  "geometry": {"coordinates":[14.99754,48.64601],"type":"Point"}
}