{
  "type": "Feature",
  "properties": {
    "gn:admin1_code":"3.0",
    "gn:admin2_code":"321",
    "gn:admin3_code":"32114.0",
    "gn:asciiname":"Kollersdorf",
    "gn:country_code":"AT",
    "gn:dem":184,
    "gn:feature_class":"P",
    "gn:feature_code":"PPL",
    "gn:name":"Kollersdorf",
    "gn:population":175,
    "gn:timezone":"Europe/Vienna",
    "iso:country":"AT",
    "wof:name":"Kollersdorf",
    "wof:placetype":"locality",
    "wof:population":175
},
  "geometry": {"coordinates":[15.85,48.41667],"type":"Point"}
}