{
  "type": "Feature",
  "properties": {
    "gn:admin1_code":"02",
    "gn:admin2_code":"203.0",
    "gn:admin3_code":"20305.0",
    "gn:asciiname":"Radnig",
    "gn:country_code":"AT",
    "gn:dem":731,
    "gn:feature_class":"P",
    "gn:feature_code":"PPL",
    "gn:name":"Radnig",
    "gn:population":208,
    "gn:timezone":"Europe/Vienna",
    "iso:country":"AT",
    "wof:name":"Radnig",
    "wof:placetype":"locality",
    "wof:population":208
},
  "geometry": {"coordinates":[13.36109,46.63995],"type":"Point"}
}