{
  "type": "Feature",
  "properties": {
    "gn:admin1_code":"3.0",
    "gn:admin2_code":"305",
    "gn:admin3_code":"30531.0",
    "gn:asciiname":"Dollberg",
    "gn:country_code":"AT",
    "gn:dem":328,
    "gn:feature_class":"P",
    "gn:feature_code":"PPL",
    "gn:name":"Dollberg",
    "gn:population":0,
    "gn:timezone":"Europe/Vienna",
    "iso:country":"AT",
    "name:deu_x_preferred":[
        "Dollberg"
    ],
    "name:epo_x_preferred":[
        "Dollberg"
    ],
    "name:lmo_x_preferred":[
        "Dollberg"
    ],
    "wof:name":"Dollberg",
    "wof:placetype":"locality"
},
  "geometry": {"coordinates":[14.56667,48.16667],"type":"Point"}
}