{
  "type": "Feature",
  "properties": {
    "gn:admin1_code":"3.0",
    "gn:admin2_code":"313",
    "gn:admin3_code":"31324.0",
    "gn:asciiname":"Loiwein",
    "gn:country_code":"AT",
    "gn:dem":522,
    "gn:feature_class":"P",
    "gn:feature_code":"PPL",
    "gn:name":"Loiwein",
    "gn:population":273,
    "gn:timezone":"Europe/Vienna",
    "iso:country":"AT",
    "wof:name":"Loiwein",
    "wof:placetype":"locality",
    "wof:population":273
},
  "geometry": {"coordinates":[15.43333,48.48333],"type":"Point"}
}