{
  "type": "Feature",
  "properties": {
    "gn:admin1_code":"6.0",
    "gn:admin2_code":"614",
    "gn:admin3_code":"61442.0",
    "gn:asciiname":"St. Ruprecht-Falkendorf",
    "gn:country_code":"AT",
    "gn:dem":1051,
    "gn:feature_class":"P",
    "gn:feature_code":"PPLA3",
    "gn:name":"St. Ruprecht-Falkendorf",
    "gn:population":0,
    "gn:timezone":"Europe/Vienna",
    "iso:country":"AT",
    "wof:name":"St. Ruprecht-Falkendorf",
    "wof:placetype":"locality"
},
  "geometry": {"coordinates":[14.01752,47.1011],"type":"Point"}
}