{
  "type": "Feature",
  "properties": {
    "gn:admin1_code":"7.0",
    "gn:admin2_code":"707",
    "gn:admin3_code":"70731.0",
    "gn:asciiname":"Zettersfeld",
    "gn:country_code":"AT",
    "gn:dem":1774,
    "gn:feature_class":"P",
    "gn:feature_code":"PPL",
    "gn:name":"Zettersfeld",
    "gn:population":7,
    "gn:timezone":"Europe/Vienna",
    "iso:country":"AT",
    "wof:name":"Zettersfeld",
    "wof:placetype":"locality",
    "wof:population":7
},
  "geometry": {"coordinates":[12.78126,46.86553],"type":"Point"}
}