{
  "type": "Feature",
  "properties": {
    "gn:admin1_code":"3.0",
    "gn:admin2_code":"325",
    "gn:admin3_code":"32530.0",
    "gn:asciiname":"Hoermanns",
    "gn:cc2":"AT",
    "gn:country_code":"AT",
    "gn:dem":589,
    "gn:feature_class":"P",
    "gn:feature_code":"PPL",
    "gn:name":"H\u00f6rmanns",
    "gn:population":95,
    "gn:timezone":"Europe/Vienna",
    "iso:country":"AT",
    "name:und_x_variant":[
        "H\u00f6rmanns bei Weitra"
    ],
    "wof:name":"Hoermanns",
    "wof:placetype":"locality",
    "wof:population":95
},
  "geometry": {"coordinates":[15.21984,48.67917],"type":"Point"}
}