{
  "type": "Feature",
  "properties": {
    "gn:admin1_code":"3.0",
    "gn:admin2_code":"313",
    "gn:admin3_code":"31311.0",
    "gn:asciiname":"Gfoehleramt",
    "gn:country_code":"AT",
    "gn:dem":587,
    "gn:feature_class":"P",
    "gn:feature_code":"PPL",
    "gn:name":"Gf\u00f6hleramt",
    "gn:population":290,
    "gn:timezone":"Europe/Vienna",
    "iso:country":"AT",
    "wof:name":"Gfoehleramt",
    "wof:placetype":"locality",
    "wof:population":290
},
  "geometry": {"coordinates":[15.51667,48.51667],"type":"Point"}
}