{
  "type": "Feature",
  "properties": {
    "gn:admin1_code":"4.0",
    "gn:admin2_code":"412",
    "gn:admin3_code":"41224.0",
    "gn:asciiname":"Fraham",
    "gn:country_code":"AT",
    "gn:dem":351,
    "gn:feature_class":"P",
    "gn:feature_code":"PPL",
    "gn:name":"Fraham",
    "gn:population":45,
    "gn:timezone":"Europe/Vienna",
    "iso:country":"AT",
    "name:ceb_x_preferred":[
        "Fraham"
    ],
    "name:deu_x_preferred":[
        "Fraham"
    ],
    "name:fas_x_preferred":[
        "\u0641\u0631\u0622\u0645"
    ],
    "name:fra_x_preferred":[
        "Fraham"
    ],
    "name:fur_x_preferred":[
        "Fraham"
    ],
    "name:hun_x_preferred":[
        "Fraham"
    ],
    "name:ita_x_preferred":[
        "Fraham"
    ],
    "name:nld_x_preferred":[
        "Fraham"
    ],
    "name:pol_x_preferred":[
        "Fraham"
    ],
    "name:por_x_preferred":[
        "Fraham"
    ],
    "name:rus_x_preferred":[
        "\u0424\u0440\u0430\u0445\u0430\u043c"
    ],
    "name:slk_x_preferred":[
        "Fraham"
    ],
    "name:spa_x_preferred":[
        "Fraham"
    ],
    "name:swe_x_preferred":[
        "Fraham"
    ],
    "name:uzb_x_preferred":[
        "Fraham"
    ],
    "name:vie_x_preferred":[
        "Fraham"
    ],
    "name:vol_x_preferred":[
        "Fraham"
    ],
    "name:war_x_preferred":[
        "Fraham"
    ],
    "name:zho_x_preferred":[
        "\u5f17\u62c9\u54c8\u59c6"
    ],
    "wof:name":"Fraham",
    "wof:placetype":"locality",
    "wof:population":45
},
  "geometry": {"coordinates":[13.37234,48.3251],"type":"Point"}
}