{
  "type": "Feature",
  "properties": {
    "gn:admin1_code":"4.0",
    "gn:admin2_code":"412",
    "gn:admin3_code":"41224.0",
    "gn:asciiname":"Fraham",
    "gn:country_code":"AT",
    "gn:dem":351,
    "gn:feature_class":"P",
    "gn:feature_code":"PPL",
    "gn:name":"Fraham",
    "gn:population":45,
    "gn:timezone":"Europe/Vienna",
    "iso:country":"AT",
    "wof:name":"Fraham",
    "wof:placetype":"locality",
    "wof:population":45
},
  "geometry": {"coordinates":[13.37234,48.3251],"type":"Point"}
}