{
  "type": "Feature",
  "properties": {
    "gn:admin1_code":"02",
    "gn:admin2_code":"210.0",
    "gn:admin3_code":"21002.0",
    "gn:asciiname":"Radweg",
    "gn:country_code":"AT",
    "gn:dem":631,
    "gn:feature_class":"P",
    "gn:feature_code":"PPL",
    "gn:name":"Radweg",
    "gn:population":305,
    "gn:timezone":"Europe/Vienna",
    "iso:country":"AT",
    "wof:name":"Radweg",
    "wof:placetype":"locality",
    "wof:population":305
},
  "geometry": {"coordinates":[14.13333,46.68333],"type":"Point"}
}