{
  "type": "Feature",
  "properties": {
    "iso:country":"AT",
    "name:deu_x_preferred":[
        "Waltendorf"
    ],
    "name:fin_x_preferred":[
        "Waltendorf"
    ],
    "name:unk_x_variant":[
        "Waltendorf"
    ],
    "qs:gn_adm0_cc":"AT",
    "qs:gn_fcode":"PPLX",
    "qs:gn_local":7871499,
    "qs:gn_nam_loc":"Graz, Graz Stadt, Steiermark, AT",
    "qs:gn_namadm1":"06",
    "qs:gn_name":"Waltendorf",
    "qs:local_max":3393,
    "qs:local_sum":13910,
    "qs:localhoods":22,
    "qs:name":"Waltendorf",
    "qs:name_adm0":"\u00d6sterreich",
    "qs:name_adm1":"Steiermark",
    "qs:name_adm2":"Graz Stadt",
    "qs:name_lau":"Graz",
    "qs:name_local":"Graz",
    "qs:photo_max":332,
    "qs:photo_sum":3393,
    "qs:placetype":"Suburb",
    "qs:quad_count":125,
    "qs:woe_adm0":23424750,
    "qs:woe_adm1":2344713,
    "qs:woe_adm2":12591740,
    "qs:woe_lau":12674996,
    "qs:woe_local":12674996,
    "qs:woe_ver":"7.10.0",
    "wd:wordcount":138,
    "wof:lang":[
        "ger"
    ],
    "wof:name":"Waltendorf",
    "wof:placetype":"neighbourhood"
},
  "geometry": {"coordinates":[15.447746,47.067909],"type":"Point"}
}