{
  "type": "Feature",
  "properties": {
    "gn:admin1_code":"2.0",
    "gn:admin2_code":"210",
    "gn:admin3_code":"21008.0",
    "gn:asciiname":"Buggl in Bach",
    "gn:country_code":"AT",
    "gn:dem":1073,
    "gn:feature_class":"P",
    "gn:feature_code":"PPL",
    "gn:name":"Buggl in Bach",
    "gn:population":10,
    "gn:timezone":"Europe/Vienna",
    "iso:country":"AT",
    "wof:name":"Buggl in Bach",
    "wof:placetype":"locality",
    "wof:population":10
},
  "geometry": {"coordinates":[14.15242,46.77164000000001],"type":"Point"}
}