{
  "type": "Feature",
  "properties": {
    "gn:admin1_code":"3.0",
    "gn:admin2_code":"305",
    "gn:admin3_code":"30542.0",
    "gn:asciiname":"Kirchstetten",
    "gn:country_code":"AT",
    "gn:dem":389,
    "gn:feature_class":"P",
    "gn:feature_code":"PPL",
    "gn:name":"Kirchstetten",
    "gn:population":0,
    "gn:timezone":"Europe/Vienna",
    "iso:country":"AT",
    "name:ceb_x_preferred":[
        "Kirchstetten"
    ],
    "name:deu_x_preferred":[
        "Kirchstetten"
    ],
    "name:epo_x_preferred":[
        "Kirchstetten"
    ],
    "name:fas_x_preferred":[
        "\u06a9\u0631\u06cc\u0634\u062a\u062a\u0646"
    ],
    "name:fra_x_preferred":[
        "Kirchstetten"
    ],
    "name:hun_x_preferred":[
        "Kirchstetten"
    ],
    "name:ita_x_preferred":[
        "Kirchstetten"
    ],
    "name:kaz_x_preferred":[
        "\u041a\u0438\u0440\u0445\u0448\u0442\u0435\u0442\u0442\u0435\u043d"
    ],
    "name:nld_x_preferred":[
        "Kirchstetten"
    ],
    "name:pol_x_preferred":[
        "Kirchstetten"
    ],
    "name:por_x_preferred":[
        "Kirchstetten"
    ],
    "name:rus_x_preferred":[
        "\u041a\u0438\u0440\u0445\u0448\u0442\u0435\u0442\u0442\u0435\u043d"
    ],
    "name:slk_x_preferred":[
        "Kirchstetten"
    ],
    "name:spa_x_preferred":[
        "Kirchstetten"
    ],
    "name:swe_x_preferred":[
        "Kirchstetten"
    ],
    "name:uzb_x_preferred":[
        "Kirchstetten"
    ],
    "name:vie_x_preferred":[
        "Kirchstetten"
    ],
    "name:vol_x_preferred":[
        "Kirchstetten"
    ],
    "name:war_x_preferred":[
        "Kirchstetten"
    ],
    "name:zho_x_preferred":[
        "\u57fa\u5e0c\u65bd\u6cf0\u6ed5"
    ],
    "wof:name":"Kirchstetten",
    "wof:placetype":"locality"
},
  "geometry": {"coordinates":[14.68333,48.08333],"type":"Point"}
}