{
  "type": "Feature",
  "properties": {
    "gn:admin1_code":"3.0",
    "gn:admin2_code":"305",
    "gn:admin3_code":"30542.0",
    "gn:asciiname":"Kirchstetten",
    "gn:country_code":"AT",
    "gn:dem":389,
    "gn:feature_class":"P",
    "gn:feature_code":"PPL",
    "gn:name":"Kirchstetten",
    "gn:population":0,
    "gn:timezone":"Europe/Vienna",
    "iso:country":"AT",
    "wof:name":"Kirchstetten",
    "wof:placetype":"locality"
},
  "geometry": {"coordinates":[14.68333,48.08333],"type":"Point"}
}