{
  "type": "Feature",
  "properties": {
    "gn:admin1_code":"2.0",
    "gn:admin2_code":"210",
    "gn:admin3_code":"21002.0",
    "gn:asciiname":"Glanhofen",
    "gn:country_code":"AT",
    "gn:dem":680,
    "gn:feature_class":"P",
    "gn:feature_code":"PPL",
    "gn:name":"Glanhofen",
    "gn:population":266,
    "gn:timezone":"Europe/Vienna",
    "iso:country":"AT",
    "wof:name":"Glanhofen",
    "wof:placetype":"locality",
    "wof:population":266
},
  "geometry": {"coordinates":[14.08333,46.68333],"type":"Point"}
}