{
  "type": "Feature",
  "properties": {
    "gn:admin1_code":"2.0",
    "gn:admin2_code":"210",
    "gn:admin3_code":"21005.0",
    "gn:asciiname":"Linz",
    "gn:country_code":"AT",
    "gn:dem":713,
    "gn:feature_class":"P",
    "gn:feature_code":"PPL",
    "gn:name":"Linz",
    "gn:population":46,
    "gn:timezone":"Europe/Vienna",
    "iso:country":"AT",
    "wof:name":"Linz",
    "wof:placetype":"locality",
    "wof:population":46
},
  "geometry": {"coordinates":[14.04963,46.72971],"type":"Point"}
}