{
  "type": "Feature",
  "properties": {
    "gn:admin1_code":"07",
    "gn:admin2_code":"705.0",
    "gn:admin3_code":"70505.0",
    "gn:asciiname":"Ramsau",
    "gn:country_code":"AT",
    "gn:dem":562,
    "gn:feature_class":"P",
    "gn:feature_code":"PPL",
    "gn:name":"Ramsau",
    "gn:population":0,
    "gn:timezone":"Europe/Vienna",
    "iso:country":"AT",
    "wof:name":"Ramsau",
    "wof:placetype":"locality"
},
  "geometry": {"coordinates":[11.96445,47.49093],"type":"Point"}
}