{
  "type": "Feature",
  "properties": {
    "gn:admin1_code":"4.0",
    "gn:admin2_code":"408",
    "gn:admin3_code":"40813.0",
    "gn:asciiname":"Oberdoppl",
    "gn:country_code":"AT",
    "gn:dem":390,
    "gn:feature_class":"P",
    "gn:feature_code":"PPL",
    "gn:name":"Oberdoppl",
    "gn:population":16,
    "gn:timezone":"Europe/Vienna",
    "iso:country":"AT",
    "wof:name":"Oberdoppl",
    "wof:placetype":"locality",
    "wof:population":16
},
  "geometry": {"coordinates":[13.84715,48.18824],"type":"Point"}
}