{
  "type": "Feature",
  "properties": {
    "gn:admin1_code":"6.0",
    "gn:admin2_code":"617",
    "gn:admin3_code":"61760.0",
    "gn:asciiname":"Hohenberg",
    "gn:country_code":"AT",
    "gn:dem":381,
    "gn:feature_class":"P",
    "gn:feature_code":"PPL",
    "gn:name":"Hohenberg",
    "gn:population":0,
    "gn:timezone":"Europe/Vienna",
    "iso:country":"AT",
    "wof:name":"Hohenberg",
    "wof:placetype":"locality"
},
  "geometry": {"coordinates":[15.71667,47.11667],"type":"Point"}
}