{
  "type": "Feature",
  "properties": {
    "iso:country":"AT",
    "qs:a0":"\u00d6sterreich",
    "qs:a1":"*Ober\u00f6sterreich",
    "qs:a1r":"0",
    "qs:a2":"Steyr - Land",
    "qs:adm0":"\u00d6sterreich",
    "qs:la_lc":"*",
    "qs:level":"locality",
    "qs:loc":"Dietachdorf",
    "qs:loc_alt":"Dietachdorf",
    "qs:pop":0,
    "qs:type":"buffered point",
    "wof:name":"Dietachdorf",
    "wof:placetype":"locality"
},
  "geometry": {"coordinates":[14.420113,48.089481],"type":"Point"}
}