{
  "type": "Feature",
  "properties": {
    "gn:admin1_code":"4.0",
    "gn:admin2_code":"415",
    "gn:admin3_code":"41507.0",
    "gn:asciiname":"Grabner",
    "gn:country_code":"AT",
    "gn:dem":577,
    "gn:feature_class":"P",
    "gn:feature_code":"PPL",
    "gn:name":"Grabner",
    "gn:population":0,
    "gn:timezone":"Europe/Vienna",
    "iso:country":"AT",
    "name:slv_x_preferred":[
        "Grabner"
    ],
    "wof:name":"Grabner",
    "wof:placetype":"locality"
},
  "geometry": {"coordinates":[14.52684,47.82243],"type":"Point"}
}