{
  "type": "Feature",
  "properties": {
    "gn:admin1_code":"07",
    "gn:admin2_code":"709.0",
    "gn:admin3_code":"70905.0",
    "gn:asciiname":"Sankt Margarethen",
    "gn:country_code":"AT",
    "gn:dem":530,
    "gn:feature_class":"P",
    "gn:feature_code":"PPL",
    "gn:name":"Sankt Margarethen",
    "gn:population":0,
    "gn:timezone":"Europe/Vienna",
    "iso:country":"AT",
    "wof:name":"Sankt Margarethen",
    "wof:placetype":"locality"
},
  "geometry": {"coordinates":[11.77073,47.37961],"type":"Point"}
}