{
  "type": "Feature",
  "properties": {
    "gn:admin1_code":"2.0",
    "gn:admin2_code":"207",
    "gn:admin3_code":"20725.0",
    "gn:asciiname":"Oberjeserz",
    "gn:country_code":"AT",
    "gn:dem":692,
    "gn:feature_class":"P",
    "gn:feature_code":"PPL",
    "gn:name":"Oberjeserz",
    "gn:population":190,
    "gn:timezone":"Europe/Vienna",
    "iso:country":"AT",
    "wof:name":"Oberjeserz",
    "wof:placetype":"locality",
    "wof:population":190
},
  "geometry": {"coordinates":[14.01667,46.63333],"type":"Point"}
}