{
  "type": "Feature",
  "properties": {
    "gn:admin1_code":"3.0",
    "gn:admin2_code":"313",
    "gn:admin3_code":"31326.0",
    "gn:asciiname":"Oberndorf",
    "gn:country_code":"AT",
    "gn:dem":873,
    "gn:feature_class":"P",
    "gn:feature_code":"PPL",
    "gn:name":"Oberndorf",
    "gn:population":31,
    "gn:timezone":"Europe/Vienna",
    "iso:country":"AT",
    "name:ceb_x_preferred":[
        "Oberndorf"
    ],
    "name:deu_x_preferred":[
        "Oberndorf"
    ],
    "name:epo_x_preferred":[
        "Oberndorf"
    ],
    "name:eus_x_preferred":[
        "Oberndorf"
    ],
    "name:fra_x_preferred":[
        "Oberndorf"
    ],
    "name:ita_x_preferred":[
        "Oberndorf"
    ],
    "name:jpn_x_preferred":[
        "\u30aa\u30fc\u30d9\u30eb\u30f3\u30c9\u30eb\u30d5"
    ],
    "name:nds_x_preferred":[
        "Oberndorf"
    ],
    "name:nld_x_preferred":[
        "Oberndorf"
    ],
    "name:pol_x_preferred":[
        "Oberndorf"
    ],
    "name:rus_x_preferred":[
        "\u041e\u0431\u0435\u0440\u043d\u0434\u043e\u0440\u0444"
    ],
    "name:swe_x_preferred":[
        "Oberndorf"
    ],
    "name:vol_x_preferred":[
        "Oberndorf"
    ],
    "name:zho_x_preferred":[
        "\u5967\u4f2f\u6069\u591a\u592b"
    ],
    "wof:name":"Oberndorf",
    "wof:placetype":"locality",
    "wof:population":31
},
  "geometry": {"coordinates":[15.34887,48.3371],"type":"Point"}
}