{
  "type": "Feature",
  "properties": {
    "gn:admin1_code":"3.0",
    "gn:admin2_code":"313",
    "gn:admin3_code":"31326.0",
    "gn:asciiname":"Oberndorf",
    "gn:country_code":"AT",
    "gn:dem":873,
    "gn:feature_class":"P",
    "gn:feature_code":"PPL",
    "gn:name":"Oberndorf",
    "gn:population":31,
    "gn:timezone":"Europe/Vienna",
    "iso:country":"AT",
    "wof:name":"Oberndorf",
    "wof:placetype":"locality",
    "wof:population":31
},
  "geometry": {"coordinates":[15.34887,48.3371],"type":"Point"}
}