{
  "type": "Feature",
  "properties": {
    "gn:admin1_code":"5.0",
    "gn:admin2_code":"505",
    "gn:admin3_code":"50506.0",
    "gn:asciiname":"Hintering",
    "gn:country_code":"AT",
    "gn:dem":1371,
    "gn:feature_class":"P",
    "gn:feature_code":"PPL",
    "gn:name":"Hintering",
    "gn:population":0,
    "gn:timezone":"Europe/Vienna",
    "iso:country":"AT",
    "wof:name":"Hintering",
    "wof:placetype":"locality"
},
  "geometry": {"coordinates":[13.85,47.06667],"type":"Point"}
}