{
  "type": "Feature",
  "properties": {
    "gn:admin1_code":"06",
    "gn:admin2_code":"606.0",
    "gn:admin3_code":"60665.0",
    "gn:asciiname":"Rohrbach",
    "gn:country_code":"AT",
    "gn:dem":389,
    "gn:feature_class":"P",
    "gn:feature_code":"PPL",
    "gn:name":"Rohrbach",
    "gn:population":833,
    "gn:timezone":"Europe/Vienna",
    "iso:country":"AT",
    "name:bar_x_preferred":[
        "Rohrbach"
    ],
    "name:bos_x_preferred":[
        "Rohrbach"
    ],
    "name:ceb_x_preferred":[
        "Rohrbach"
    ],
    "name:deu_x_preferred":[
        "Rohrbach"
    ],
    "name:epo_x_preferred":[
        "Rohrbach"
    ],
    "name:eus_x_preferred":[
        "Rohrbach"
    ],
    "name:fra_x_preferred":[
        "Rohrbach"
    ],
    "name:ita_x_preferred":[
        "Rohrbach"
    ],
    "name:kir_x_preferred":[
        "\u0420\u043e\u0440\u0431\u0430\u0445"
    ],
    "name:nld_x_preferred":[
        "Rohrbach"
    ],
    "name:pol_x_preferred":[
        "Rohrbach"
    ],
    "name:rus_x_preferred":[
        "\u0420\u043e\u0440\u0431\u0430\u0445"
    ],
    "name:srp_x_preferred":[
        "\u0420\u043e\u0440\u0431\u0430\u0445"
    ],
    "name:swe_x_preferred":[
        "Rohrbach"
    ],
    "name:ukr_x_preferred":[
        "\u0420\u043e\u0440\u0431\u0430\u0445"
    ],
    "name:vol_x_preferred":[
        "Rohrbach"
    ],
    "wof:name":"Rohrbach",
    "wof:placetype":"locality",
    "wof:population":833
},
  "geometry": {"coordinates":[15.28333,47.05],"type":"Point"}
}