{
  "type": "Feature",
  "properties": {
    "gn:admin1_code":"05",
    "gn:admin2_code":"506.0",
    "gn:admin3_code":"50624.0",
    "gn:asciiname":"Stubach",
    "gn:country_code":"AT",
    "gn:dem":878,
    "gn:feature_class":"P",
    "gn:feature_code":"PPL",
    "gn:name":"Stubach",
    "gn:population":158,
    "gn:timezone":"Europe/Vienna",
    "iso:country":"AT",
    "wof:name":"Stubach",
    "wof:placetype":"locality",
    "wof:population":158
},
  "geometry": {"coordinates":[12.56667,47.25],"type":"Point"}
}