{
  "type": "Feature",
  "properties": {
    "gn:admin1_code":"08",
    "gn:admin2_code":"801.0",
    "gn:admin3_code":"80119.0",
    "gn:asciiname":"Valleu",
    "gn:cc2":"AT",
    "gn:country_code":"AT",
    "gn:dem":706,
    "gn:feature_class":"P",
    "gn:feature_code":"PPL",
    "gn:name":"Valleu",
    "gn:population":0,
    "gn:timezone":"Europe/Vienna",
    "iso:country":"AT",
    "name:und_x_variant":[
        "Vallen",
        "Valleu"
    ],
    "wof:name":"Valleu",
    "wof:placetype":"locality"
},
  "geometry": {"coordinates":[9.86667,47.11667],"type":"Point"}
}