{
  "type": "Feature",
  "properties": {
    "gn:admin1_code":"7.0",
    "gn:admin2_code":"707",
    "gn:admin3_code":"70713.0",
    "gn:asciiname":"Ausserlerch",
    "gn:country_code":"AT",
    "gn:dem":1495,
    "gn:feature_class":"P",
    "gn:feature_code":"PPLL",
    "gn:name":"Au\u00dferlerch",
    "gn:population":0,
    "gn:timezone":"Europe/Vienna",
    "iso:country":"AT",
    "wof:name":"Ausserlerch",
    "wof:placetype":"locality"
},
  "geometry": {"coordinates":[12.50244,46.72827],"type":"Point"}
}