{
  "type": "Feature",
  "properties": {
    "gn:admin1_code":"4.0",
    "gn:admin2_code":"409",
    "gn:admin3_code":"40916.0",
    "gn:asciiname":"Kniewas",
    "gn:country_code":"AT",
    "gn:dem":486,
    "gn:feature_class":"P",
    "gn:feature_code":"PPL",
    "gn:name":"Kniewas",
    "gn:population":0,
    "gn:timezone":"Europe/Vienna",
    "iso:country":"AT",
    "wof:name":"Kniewas",
    "wof:placetype":"locality"
},
  "geometry": {"coordinates":[14.16667,47.78333],"type":"Point"}
}