{
  "type": "Feature",
  "properties": {
    "iso:country":"AT",
    "name:ceb_x_preferred":[
        "Scharnstein Airport"
    ],
    "name:deu_x_preferred":[
        "Flugplatz Scharnstein bei Gmunden"
    ],
    "name:eng_x_preferred":[
        "Scharnstein Airport"
    ],
    "name:ron_x_preferred":[
        "Aeroportul Scharnstein"
    ],
    "name:swe_x_preferred":[
        "Scharnstein Airport"
    ],
    "oa:elevation_ft":"1742",
    "oa:type":"small_airport",
    "woe:hierarchy":{
        "country_id":23424750,
        "county_id":12591713,
        "localadmin_id":12674453,
        "planet_id":1,
        "state_id":2344711
    },
    "wof:name":"Flugfeld Scharnstein",
    "wof:placetype":"campus"
},
  "geometry": {"coordinates":[13.9382,47.8978],"type":"Point"}
}