{
  "type": "Feature",
  "properties": {
    "gn:admin1_code":"06",
    "gn:asciiname":"Wartegg",
    "gn:country_code":"AT",
    "gn:dem":333,
    "gn:feature_class":"P",
    "gn:feature_code":"PPL",
    "gn:name":"Wartegg",
    "gn:population":0,
    "gn:timezone":"Europe/Vienna",
    "iso:country":"AT",
    "wof:name":"Wartegg",
    "wof:placetype":"locality"
},
  "geometry": {"coordinates":[16.06667,46.91667],"type":"Point"}
}