{
  "type": "Feature",
  "properties": {
    "gn:admin1_code":"3.0",
    "gn:admin2_code":"321",
    "gn:admin3_code":"32104.0",
    "gn:asciiname":"Moosbierbaum",
    "gn:country_code":"AT",
    "gn:dem":183,
    "gn:feature_class":"P",
    "gn:feature_code":"PPL",
    "gn:name":"Moosbierbaum",
    "gn:population":283,
    "gn:timezone":"Europe/Vienna",
    "iso:country":"AT",
    "wof:name":"Moosbierbaum",
    "wof:placetype":"locality",
    "wof:population":283
},
  "geometry": {"coordinates":[15.90048,48.30478],"type":"Point"}
}