{
  "type": "Feature",
  "properties": {
    "gn:admin1_code":"4.0",
    "gn:admin2_code":"406",
    "gn:admin3_code":"40626.0",
    "gn:asciiname":"Oberpassberg",
    "gn:country_code":"AT",
    "gn:dem":703,
    "gn:feature_class":"P",
    "gn:feature_code":"PPL",
    "gn:name":"Oberpassberg",
    "gn:population":0,
    "gn:timezone":"Europe/Vienna",
    "iso:country":"AT",
    "wof:name":"Oberpassberg",
    "wof:placetype":"locality"
},
  "geometry": {"coordinates":[14.52152,48.5807],"type":"Point"}
}