{
  "type": "Feature",
  "properties": {
    "gn:admin1_code":"4.0",
    "gn:admin2_code":"404",
    "gn:admin3_code":"40410.0",
    "gn:asciiname":"Baumgarten",
    "gn:country_code":"AT",
    "gn:dem":454,
    "gn:feature_class":"P",
    "gn:feature_code":"PPL",
    "gn:name":"Baumgarten",
    "gn:population":36,
    "gn:timezone":"Europe/Vienna",
    "iso:country":"AT",
    "wof:name":"Baumgarten",
    "wof:placetype":"locality",
    "wof:population":36
},
  "geometry": {"coordinates":[12.95417,48.14224],"type":"Point"}
}