{
  "type": "Feature",
  "properties": {
    "gn:admin1_code":"4.0",
    "gn:admin2_code":"406",
    "gn:admin3_code":"40607.0",
    "gn:asciiname":"Doerfl",
    "gn:country_code":"AT",
    "gn:dem":482,
    "gn:feature_class":"P",
    "gn:feature_code":"PPL",
    "gn:name":"D\u00f6rfl",
    "gn:population":222,
    "gn:timezone":"Europe/Vienna",
    "iso:country":"AT",
    "wof:name":"Doerfl",
    "wof:placetype":"locality",
    "wof:population":222
},
  "geometry": {"coordinates":[14.5277,48.43751],"type":"Point"}
}