{
  "type": "Feature",
  "properties": {
    "gn:admin1_code":"04",
    "gn:admin2_code":"408.0",
    "gn:admin3_code":"40831.0",
    "gn:asciiname":"Weidenholz",
    "gn:country_code":"AT",
    "gn:dem":367,
    "gn:feature_class":"P",
    "gn:feature_code":"PPL",
    "gn:name":"Weidenholz",
    "gn:population":333,
    "gn:timezone":"Europe/Vienna",
    "iso:country":"AT",
    "wof:name":"Weidenholz",
    "wof:placetype":"locality",
    "wof:population":333
},
  "geometry": {"coordinates":[13.84963,48.33393],"type":"Point"}
}