{
  "type": "Feature",
  "properties": {
    "gn:admin1_code":"1.0",
    "gn:admin2_code":"104",
    "gn:admin3_code":"10426.0",
    "gn:asciiname":"Maria am Weinberg",
    "gn:cc2":"AT",
    "gn:country_code":"AT",
    "gn:dem":218,
    "gn:feature_class":"P",
    "gn:feature_code":"PPL",
    "gn:name":"Maria am Weinberg",
    "gn:population":0,
    "gn:timezone":"Europe/Vienna",
    "iso:country":"AT",
    "name:und_x_variant":[
        "Maria Weinberg",
        "Maria am Weinberg"
    ],
    "wof:name":"Maria am Weinberg",
    "wof:placetype":"locality"
},
  "geometry": {"coordinates":[16.45,47.13333],"type":"Point"}
}