{
  "type": "Feature",
  "properties": {
    "gn:admin1_code":"4.0",
    "gn:admin2_code":"408",
    "gn:admin3_code":"40815.0",
    "gn:asciiname":"Moospolling",
    "gn:country_code":"AT",
    "gn:dem":395,
    "gn:feature_class":"P",
    "gn:feature_code":"PPL",
    "gn:name":"Moospolling",
    "gn:population":0,
    "gn:timezone":"Europe/Vienna",
    "iso:country":"AT",
    "wof:name":"Moospolling",
    "wof:placetype":"locality"
},
  "geometry": {"coordinates":[13.81667,48.31667],"type":"Point"}
}