{
  "type": "Feature",
  "properties": {
    "gn:admin1_code":"04",
    "gn:admin2_code":"407.0",
    "gn:admin3_code":"40702.0",
    "gn:asciiname":"Unterjoch",
    "gn:country_code":"AT",
    "gn:dem":573,
    "gn:feature_class":"P",
    "gn:feature_code":"PPL",
    "gn:name":"Unterjoch",
    "gn:population":131,
    "gn:timezone":"Europe/Vienna",
    "iso:country":"AT",
    "name:ceb_x_preferred":[
        "Unterjoch"
    ],
    "name:deu_x_preferred":[
        "Unterjoch"
    ],
    "name:fas_x_preferred":[
        "\u0627\u0648\u0646\u062a\u0631\u06cc\u0648\u062e"
    ],
    "wof:name":"Unterjoch",
    "wof:placetype":"locality",
    "wof:population":131
},
  "geometry": {"coordinates":[13.59859,47.64215],"type":"Point"}
}