{
  "type": "Feature",
  "properties": {
    "gn:admin1_code":"4.0",
    "gn:admin2_code":"417",
    "gn:admin3_code":"41722.0",
    "gn:asciiname":"Walding",
    "gn:country_code":"AT",
    "gn:dem":577,
    "gn:feature_class":"P",
    "gn:feature_code":"PPL",
    "gn:name":"Walding",
    "gn:population":29,
    "gn:timezone":"Europe/Vienna",
    "iso:country":"AT",
    "wof:name":"Walding",
    "wof:placetype":"locality",
    "wof:population":29
},
  "geometry": {"coordinates":[13.65463,48.11947],"type":"Point"}
}