{
  "type": "Feature",
  "properties": {
    "gn:admin1_code":"4.0",
    "gn:admin2_code":"417",
    "gn:admin3_code":"41722.0",
    "gn:asciiname":"Walding",
    "gn:country_code":"AT",
    "gn:dem":577,
    "gn:feature_class":"P",
    "gn:feature_code":"PPL",
    "gn:name":"Walding",
    "gn:population":29,
    "gn:timezone":"Europe/Vienna",
    "iso:country":"AT",
    "name:ceb_x_preferred":[
        "Walding"
    ],
    "name:ces_x_preferred":[
        "Walding"
    ],
    "name:deu_x_preferred":[
        "Walding"
    ],
    "name:fas_x_preferred":[
        "\u0648\u0627\u0644\u062f\u06cc\u0646\u06af"
    ],
    "name:fra_x_preferred":[
        "Walding"
    ],
    "name:hun_x_preferred":[
        "Walding"
    ],
    "name:ita_x_preferred":[
        "Walding"
    ],
    "name:kaz_x_preferred":[
        "\u0412\u0430\u043b\u044c\u0434\u0438\u043d\u0433"
    ],
    "name:nld_x_preferred":[
        "Walding"
    ],
    "name:pol_x_preferred":[
        "Walding"
    ],
    "name:por_x_preferred":[
        "Walding"
    ],
    "name:rus_x_preferred":[
        "\u0412\u0430\u043b\u044c\u0434\u0438\u043d\u0433"
    ],
    "name:slk_x_preferred":[
        "Walding"
    ],
    "name:spa_x_preferred":[
        "Walding"
    ],
    "name:swe_x_preferred":[
        "Walding"
    ],
    "name:uzb_x_preferred":[
        "Walding"
    ],
    "name:vie_x_preferred":[
        "Walding"
    ],
    "name:vol_x_preferred":[
        "Walding"
    ],
    "name:war_x_preferred":[
        "Walding"
    ],
    "name:zho_x_preferred":[
        "\u74e6\u5c14\u4e01"
    ],
    "wof:name":"Walding",
    "wof:placetype":"locality",
    "wof:population":29
},
  "geometry": {"coordinates":[13.65463,48.11947],"type":"Point"}
}