{
  "type": "Feature",
  "properties": {
    "iso:country":"AT",
    "name:deu_x_preferred":[
        "Goethesiedlung"
    ],
    "name:eng_x_preferred":[
        "Goethesiedlung"
    ],
    "wof:name":"Goethesiedlung",
    "wof:placetype":"neighbourhood"
},
  "geometry": {"coordinates":[13.04150743482177,47.82598013339665],"type":"Point"}
}