{
  "type": "Feature",
  "properties": {
    "iso:country":"AT",
    "name:bar_x_preferred":[
        "Itter"
    ],
    "name:ceb_x_preferred":[
        "Itter"
    ],
    "name:ces_x_preferred":[
        "Itter"
    ],
    "name:deu_x_preferred":[
        "Itter"
    ],
    "name:eng_x_preferred":[
        "Itter"
    ],
    "name:fra_x_preferred":[
        "Itter"
    ],
    "name:hun_x_preferred":[
        "Itter"
    ],
    "name:ita_x_preferred":[
        "Itter"
    ],
    "name:jpn_x_preferred":[
        "\u30a4\u30c3\u30bf\u30fc"
    ],
    "name:kaz_x_preferred":[
        "\u0418\u0442\u0442\u0435\u0440"
    ],
    "name:nld_x_preferred":[
        "Itter"
    ],
    "name:pnb_x_preferred":[
        "\u0627\u06cc\u062a\u0631"
    ],
    "name:pol_x_preferred":[
        "Itter"
    ],
    "name:rus_x_preferred":[
        "\u0418\u0442\u0442\u0435\u0440"
    ],
    "name:slk_x_preferred":[
        "Itter"
    ],
    "name:swe_x_preferred":[
        "Itter"
    ],
    "name:ukr_x_preferred":[
        "\u0406\u0442\u0442\u0435\u0440"
    ],
    "name:uzb_x_preferred":[
        "Itter"
    ],
    "name:vol_x_preferred":[
        "Itter"
    ],
    "name:war_x_preferred":[
        "Itter"
    ],
    "name:zho_x_preferred":[
        "\u4f0a\u7279\u5c14"
    ],
    "name:zho_x_variant":[
        "Itter"
    ],
    "qs:a0":"\u00d6sterreich",
    "qs:a1":"*Tirol",
    "qs:a1r":"0",
    "qs:a2":"Kitzb\u00fchel",
    "qs:adm0":"\u00d6sterreich",
    "qs:la_lc":"*",
    "qs:level":"locality",
    "qs:loc":"Itter",
    "qs:loc_alt":"Itter",
    "qs:pop":0,
    "qs:type":"buffered point",
    "wd:wordcount":89,
    "wof:name":"Itter",
    "wof:placetype":"locality"
},
  "geometry": {"coordinates":[12.14436,47.472568],"type":"Point"}
}