{
  "type": "Feature",
  "properties": {
    "gn:admin1_code":"06",
    "gn:admin2_code":"614.0",
    "gn:admin3_code":"61439.0",
    "gn:asciiname":"Wildbad Einoed",
    "gn:country_code":"AT",
    "gn:dem":739,
    "gn:feature_class":"P",
    "gn:feature_code":"PPL",
    "gn:name":"Wildbad Ein\u00f6d",
    "gn:population":31,
    "gn:timezone":"Europe/Vienna",
    "iso:country":"AT",
    "wof:name":"Wildbad Einoed",
    "wof:placetype":"locality",
    "wof:population":31
},
  "geometry": {"coordinates":[14.41389,47.02193],"type":"Point"}
}