{
  "type": "Feature",
  "properties": {
    "gn:admin1_code":"4.0",
    "gn:admin2_code":"404",
    "gn:admin3_code":"40440.0",
    "gn:asciiname":"Wimhub",
    "gn:country_code":"AT",
    "gn:dem":411,
    "gn:feature_class":"P",
    "gn:feature_code":"PPL",
    "gn:name":"Wimhub",
    "gn:population":21,
    "gn:timezone":"Europe/Vienna",
    "iso:country":"AT",
    "wof:name":"Wimhub",
    "wof:placetype":"locality",
    "wof:population":21
},
  "geometry": {"coordinates":[13.27578,48.20383],"type":"Point"}
}