{
  "type": "Feature",
  "properties": {
    "gn:admin1_code":"3.0",
    "gn:admin2_code":"319",
    "gn:admin3_code":"31949.0",
    "gn:asciiname":"Allhang",
    "gn:country_code":"AT",
    "gn:dem":303,
    "gn:feature_class":"P",
    "gn:feature_code":"PPL",
    "gn:name":"Allhang",
    "gn:population":0,
    "gn:timezone":"Europe/Vienna",
    "iso:country":"AT",
    "wof:name":"Allhang",
    "wof:placetype":"locality"
},
  "geometry": {"coordinates":[16.13565,48.2416],"type":"Point"}
}