{
  "type": "Feature",
  "properties": {
    "gn:admin1_code":"2.0",
    "gn:admin2_code":"205",
    "gn:admin3_code":"20534.0",
    "gn:asciiname":"Grassdorf",
    "gn:country_code":"AT",
    "gn:dem":623,
    "gn:feature_class":"P",
    "gn:feature_code":"PPL",
    "gn:name":"Gra\u00dfdorf",
    "gn:population":201,
    "gn:timezone":"Europe/Vienna",
    "iso:country":"AT",
    "wof:name":"Grassdorf",
    "wof:placetype":"locality",
    "wof:population":201
},
  "geometry": {"coordinates":[14.31845,46.762],"type":"Point"}
}