{
  "type": "Feature",
  "properties": {
    "gn:admin1_code":"06",
    "gn:admin2_code":"612.0",
    "gn:admin3_code":"61261.0",
    "gn:asciiname":"Strimitzen",
    "gn:country_code":"AT",
    "gn:dem":795,
    "gn:feature_class":"P",
    "gn:feature_code":"PPL",
    "gn:name":"Strimitzen",
    "gn:population":46,
    "gn:timezone":"Europe/Vienna",
    "iso:country":"AT",
    "wof:name":"Strimitzen",
    "wof:placetype":"locality",
    "wof:population":46
},
  "geometry": {"coordinates":[13.98333,47.46667],"type":"Point"}
}