{
  "type": "Feature",
  "properties": {
    "gn:country":"AT",
    "gn:fcode":"PPL",
    "gn:population":0,
    "iso:country":"AT",
    "name:dan_x_preferred":[
        "Hinterri\u00df"
    ],
    "name:deu_x_preferred":[
        "Hinterri\u00df"
    ],
    "name:eng_x_preferred":[
        "Hinterri\u00df"
    ],
    "name:jpn_x_preferred":[
        "\u30d2\u30f3\u30bf\u30fc\u30ea\u30b9"
    ],
    "name:nld_x_preferred":[
        "Hinterri\u00df"
    ],
    "name:und_x_variant":[
        "Hinterriss"
    ],
    "qs_pg:aaroncc":"AT",
    "qs_pg:gn_country":"AT",
    "qs_pg:gn_fcode":"PPL",
    "qs_pg:gn_pop":0,
    "qs_pg:name":"Hinterri\u00df",
    "qs_pg:name_adm0":"\u00d6sterreich",
    "qs_pg:name_adm1":"Tirol",
    "qs_pg:photos":822,
    "qs_pg:photos_1k":167,
    "qs_pg:photos_9k":4,
    "qs_pg:photos_9r":6,
    "qs_pg:photos_all":822,
    "qs_pg:photos_sr":9,
    "qs_pg:pop_sr":0,
    "qs_pg:qs_pg_placetype":"locality",
    "qs_pg:qs_pg_placetype_gp":"Town",
    "qs_pg:woe_adm0":23424750,
    "woe:adm0_id":23424750,
    "woe:name_adm0":"\u00d6sterreich",
    "woe:name_adm1":"Tirol",
    "woe:placetype":"Town",
    "wof:name":"Hinterri\u00df",
    "wof:placetype":"locality"
},
  "geometry": {"coordinates":[11.46667,47.46667],"type":"Point"}
}