{
  "type": "Feature",
  "properties": {
    "gn:admin1_code":"02",
    "gn:admin2_code":"205.0",
    "gn:admin3_code":"20520.0",
    "gn:asciiname":"Sankt Stefan am Krappfeld",
    "gn:cc2":"AT",
    "gn:country_code":"AT",
    "gn:dem":617,
    "gn:feature_class":"P",
    "gn:feature_code":"PPL",
    "gn:name":"Sankt Stefan am Krappfeld",
    "gn:population":34,
    "gn:timezone":"Europe/Vienna",
    "iso:country":"AT",
    "name:und_x_variant":[
        "Sankt Stefan",
        "Sankt Stefan am Krappfelde",
        "Sankt Stefan am Krappfeld"
    ],
    "wof:name":"Sankt Stefan am Krappfeld",
    "wof:placetype":"locality",
    "wof:population":34
},
  "geometry": {"coordinates":[14.44616,46.86829],"type":"Point"}
}