{
  "type": "Feature",
  "properties": {
    "gn:admin1_code":"06",
    "gn:admin2_code":"606.0",
    "gn:admin3_code":"60645.0",
    "gn:asciiname":"Pollau",
    "gn:country_code":"AT",
    "gn:dem":908,
    "gn:feature_class":"P",
    "gn:feature_code":"PPL",
    "gn:name":"P\u00f6llau",
    "gn:population":0,
    "gn:timezone":"Europe/Vienna",
    "iso:country":"AT",
    "name:und_x_variant":[
        "P\u00f6llau"
    ],
    "wof:name":"Pollau",
    "wof:placetype":"locality"
},
  "geometry": {"coordinates":[15.36667,47.21667],"type":"Point"}
}