{
  "type": "Feature",
  "properties": {
    "gn:admin1_code":"06",
    "gn:admin2_code":"610.0",
    "gn:admin3_code":"61052.0",
    "gn:asciiname":"Prosdorf",
    "gn:country_code":"AT",
    "gn:dem":362,
    "gn:feature_class":"P",
    "gn:feature_code":"PPL",
    "gn:name":"Prosdorf",
    "gn:population":0,
    "gn:timezone":"Europe/Vienna",
    "iso:country":"AT",
    "wof:name":"Prosdorf",
    "wof:placetype":"locality"
},
  "geometry": {"coordinates":[15.58333,46.96667],"type":"Point"}
}