{
  "type": "Feature",
  "properties": {
    "gn:admin1_code":"04",
    "gn:admin2_code":"408.0",
    "gn:admin3_code":"40828.0",
    "gn:asciiname":"Ort an der Strass",
    "gn:cc2":"AT",
    "gn:country_code":"AT",
    "gn:dem":401,
    "gn:feature_class":"P",
    "gn:feature_code":"PPL",
    "gn:name":"Ort an der Strass",
    "gn:population":0,
    "gn:timezone":"Europe/Vienna",
    "iso:country":"AT",
    "name:und_x_variant":[
        "Ort",
        "Ort an der Strass"
    ],
    "wof:name":"Ort an der Strass",
    "wof:placetype":"locality"
},
  "geometry": {"coordinates":[13.739,48.34975],"type":"Point"}
}