{
  "type": "Feature",
  "properties": {
    "gn:admin1_code":"7.0",
    "gn:admin2_code":"702",
    "gn:admin3_code":"70222.0",
    "gn:asciiname":"Walchenbach",
    "gn:country_code":"AT",
    "gn:dem":802,
    "gn:feature_class":"P",
    "gn:feature_code":"PPL",
    "gn:name":"Walchenbach",
    "gn:population":56,
    "gn:timezone":"Europe/Vienna",
    "iso:country":"AT",
    "wof:name":"Walchenbach",
    "wof:placetype":"locality",
    "wof:population":56
},
  "geometry": {"coordinates":[10.77767,47.27081],"type":"Point"}
}