{
  "type": "Feature",
  "properties": {
    "gn:admin1_code":"02",
    "gn:admin2_code":"208.0",
    "gn:admin3_code":"20817.0",
    "gn:asciiname":"Sankt Margarethen ob Toellerberg",
    "gn:country_code":"AT",
    "gn:dem":461,
    "gn:feature_class":"P",
    "gn:feature_code":"PPL",
    "gn:name":"Sankt Margarethen ob T\u00f6llerberg",
    "gn:population":152,
    "gn:timezone":"Europe/Vienna",
    "iso:country":"AT",
    "name:und_x_variant":[
        "Sankt Margarethen ober Tollerberg",
        "Sankt Margarethen",
        "Sankt Margarethen ob T\u00f6llerberg"
    ],
    "wof:name":"Sankt Margarethen ob Toellerberg",
    "wof:placetype":"locality",
    "wof:population":152
},
  "geometry": {"coordinates":[14.57263,46.67647],"type":"Point"}
}