{
  "type": "Feature",
  "properties": {
    "iso:country":"AT",
    "name:deu_x_preferred":[
        "Thumegg"
    ],
    "name:eng_x_preferred":[
        "Thumegg"
    ],
    "wof:name":"Thumegg",
    "wof:placetype":"neighbourhood"
},
  "geometry": {"coordinates":[13.04516954603939,47.7838100122871],"type":"Point"}
}