{
  "type": "Feature",
  "properties": {
    "gn:admin1_code":"4.0",
    "gn:admin2_code":"418",
    "gn:admin3_code":"41808.0",
    "gn:asciiname":"Poetzlberg",
    "gn:country_code":"AT",
    "gn:dem":403,
    "gn:feature_class":"P",
    "gn:feature_code":"PPL",
    "gn:name":"P\u00f6tzlberg",
    "gn:population":18,
    "gn:timezone":"Europe/Vienna",
    "iso:country":"AT",
    "wof:name":"Poetzlberg",
    "wof:placetype":"locality",
    "wof:population":18
},
  "geometry": {"coordinates":[13.93118,48.16402],"type":"Point"}
}