{
  "type": "Feature",
  "properties": {
    "gn:admin1_code":"04",
    "gn:admin2_code":"407.0",
    "gn:admin3_code":"40702.0",
    "gn:asciiname":"Wurmstein",
    "gn:country_code":"AT",
    "gn:dem":838,
    "gn:feature_class":"P",
    "gn:feature_code":"PPL",
    "gn:name":"Wurmstein",
    "gn:population":55,
    "gn:timezone":"Europe/Vienna",
    "iso:country":"AT",
    "wof:name":"Wurmstein",
    "wof:placetype":"locality",
    "wof:population":55
},
  "geometry": {"coordinates":[13.6336,47.64908],"type":"Point"}
}