{
  "type": "Feature",
  "properties": {
    "gn:admin1_code":"7.0",
    "gn:admin2_code":"707",
    "gn:admin3_code":"70717.0",
    "gn:asciiname":"Klausen",
    "gn:country_code":"AT",
    "gn:dem":940,
    "gn:feature_class":"P",
    "gn:feature_code":"PPL",
    "gn:name":"Klausen",
    "gn:population":45,
    "gn:timezone":"Europe/Vienna",
    "iso:country":"AT",
    "name:ceb_x_preferred":[
        "Klausen"
    ],
    "name:deu_x_preferred":[
        "Klausen"
    ],
    "name:epo_x_preferred":[
        "Klausen"
    ],
    "name:fra_x_preferred":[
        "Klausen"
    ],
    "name:ita_x_preferred":[
        "Klausen"
    ],
    "name:nld_x_preferred":[
        "Klausen"
    ],
    "name:pol_x_preferred":[
        "Klausen"
    ],
    "name:spa_x_preferred":[
        "Klausen"
    ],
    "name:swe_x_preferred":[
        "Klausen"
    ],
    "wof:name":"Klausen",
    "wof:placetype":"locality",
    "wof:population":45
},
  "geometry": {"coordinates":[12.55,46.96667],"type":"Point"}
}