{
  "type": "Feature",
  "properties": {
    "gn:admin1_code":"6.0",
    "gn:admin2_code":"606",
    "gn:admin3_code":"60665.0",
    "gn:asciiname":"Oberberg",
    "gn:country_code":"AT",
    "gn:dem":501,
    "gn:feature_class":"P",
    "gn:feature_code":"PPL",
    "gn:name":"Oberberg",
    "gn:population":318,
    "gn:timezone":"Europe/Vienna",
    "iso:country":"AT",
    "wof:name":"Oberberg",
    "wof:placetype":"locality",
    "wof:population":318
},
  "geometry": {"coordinates":[15.31667,47.06667],"type":"Point"}
}