{
  "type": "Feature",
  "properties": {
    "gn:admin1_code":"06",
    "gn:admin2_code":"623.0",
    "gn:admin3_code":"62386.0",
    "gn:asciiname":"Obertiefenbach",
    "gn:country_code":"AT",
    "gn:dem":331,
    "gn:feature_class":"P",
    "gn:feature_code":"PPL",
    "gn:name":"Obertiefenbach",
    "gn:population":0,
    "gn:timezone":"Europe/Vienna",
    "iso:country":"AT",
    "name:ceb_x_preferred":[
        "Obertiefenbach"
    ],
    "name:deu_x_preferred":[
        "Obertiefenbach"
    ],
    "name:epo_x_preferred":[
        "Obertiefenbach"
    ],
    "name:eus_x_preferred":[
        "Obertiefenbach"
    ],
    "name:fas_x_preferred":[
        "\u0627\u0648\u0628\u0631\u062a\u06cc\u0641\u0646\u0628\u0627\u062e"
    ],
    "name:fra_x_preferred":[
        "Obertiefenbach"
    ],
    "name:hun_x_preferred":[
        "Obertiefenbach"
    ],
    "name:hye_x_preferred":[
        "\u0555\u0562\u0565\u0580\u057f\u056b\u0586\u0565\u0576\u0562\u0561\u056d"
    ],
    "name:ita_x_preferred":[
        "Obertiefenbach"
    ],
    "name:msa_x_preferred":[
        "Obertiefenbach"
    ],
    "name:nld_x_preferred":[
        "Obertiefenbach"
    ],
    "name:pol_x_preferred":[
        "Obertiefenbach"
    ],
    "name:por_x_preferred":[
        "Obertiefenbach"
    ],
    "name:ron_x_preferred":[
        "Obertiefenbach"
    ],
    "name:rus_x_preferred":[
        "\u041e\u0431\u0435\u0440\u0442\u0438\u0444\u0435\u043d\u0431\u0430\u0445"
    ],
    "name:spa_x_preferred":[
        "Obertiefenbach"
    ],
    "name:srp_x_preferred":[
        "\u041e\u0431\u0435\u0440\u0442\u0438\u0444\u0435\u043d\u0431\u0430\u0445"
    ],
    "name:ukr_x_preferred":[
        "\u041e\u0431\u0435\u0440\u0442\u0456\u0444\u0435\u043d\u0431\u0430\u0445"
    ],
    "name:uzb_x_preferred":[
        "Obertiefenbach"
    ],
    "name:vie_x_preferred":[
        "Obertiefenbach"
    ],
    "name:vol_x_preferred":[
        "Obertiefenbach"
    ],
    "name:war_x_preferred":[
        "Obertiefenbach"
    ],
    "name:zho_x_preferred":[
        "\u4e0a\u8482\u82ac\u5df4\u8d6b"
    ],
    "wof:name":"Obertiefenbach",
    "wof:placetype":"locality"
},
  "geometry": {"coordinates":[15.96667,47.01667],"type":"Point"}
}