{
  "type": "Feature",
  "properties": {
    "gn:admin1_code":"4.0",
    "gn:admin2_code":"410",
    "gn:admin3_code":"41011.0",
    "gn:asciiname":"Kronstorfberg",
    "gn:country_code":"AT",
    "gn:dem":271,
    "gn:feature_class":"P",
    "gn:feature_code":"PPL",
    "gn:name":"Kronstorfberg",
    "gn:population":34,
    "gn:timezone":"Europe/Vienna",
    "iso:country":"AT",
    "wof:name":"Kronstorfberg",
    "wof:placetype":"locality",
    "wof:population":34
},
  "geometry": {"coordinates":[14.46397,48.13949],"type":"Point"}
}