{
  "type": "Feature",
  "properties": {
    "gn:admin1_code":"06",
    "gn:admin2_code":"603.0",
    "gn:admin3_code":"60344.0",
    "gn:asciiname":"Vochera am Weinberg",
    "gn:cc2":"AT",
    "gn:country_code":"AT",
    "gn:dem":380,
    "gn:feature_class":"P",
    "gn:feature_code":"PPL",
    "gn:name":"Vochera am Weinberg",
    "gn:population":239,
    "gn:timezone":"Europe/Vienna",
    "iso:country":"AT",
    "name:und_x_variant":[
        "Vochera",
        "Vochera am Weinberg"
    ],
    "wof:name":"Vochera am Weinberg",
    "wof:placetype":"locality",
    "wof:population":239
},
  "geometry": {"coordinates":[15.23333,46.88333],"type":"Point"}
}