{
  "type": "Feature",
  "properties": {
    "gn:admin1_code":"7.0",
    "gn:admin2_code":"704",
    "gn:admin3_code":"70406.0",
    "gn:asciiname":"Gruberberg",
    "gn:country_code":"AT",
    "gn:dem":979,
    "gn:feature_class":"P",
    "gn:feature_code":"PPL",
    "gn:name":"Gruberberg",
    "gn:population":75,
    "gn:timezone":"Europe/Vienna",
    "iso:country":"AT",
    "wof:name":"Gruberberg",
    "wof:placetype":"locality",
    "wof:population":75
},
  "geometry": {"coordinates":[12.15,47.41667],"type":"Point"}
}