{
  "type": "Feature",
  "properties": {
    "gn:admin1_code":"03",
    "gn:admin2_code":"315.0",
    "gn:admin3_code":"31513.0",
    "gn:asciiname":"Obersiegendorf",
    "gn:country_code":"AT",
    "gn:dem":287,
    "gn:feature_class":"P",
    "gn:feature_code":"PPL",
    "gn:name":"Obersiegendorf",
    "gn:population":0,
    "gn:timezone":"Europe/Vienna",
    "iso:country":"AT",
    "wof:name":"Obersiegendorf",
    "wof:placetype":"locality"
},
  "geometry": {"coordinates":[15.36667,48.15],"type":"Point"}
}