{
  "type": "Feature",
  "properties": {
    "gn:admin1_code":"4.0",
    "gn:admin2_code":"408",
    "gn:admin3_code":"40807.0",
    "gn:asciiname":"Arming",
    "gn:country_code":"AT",
    "gn:dem":608,
    "gn:feature_class":"P",
    "gn:feature_code":"PPL",
    "gn:name":"Arming",
    "gn:population":36,
    "gn:timezone":"Europe/Vienna",
    "iso:country":"AT",
    "wof:name":"Arming",
    "wof:placetype":"locality",
    "wof:population":36
},
  "geometry": {"coordinates":[13.61918,48.14782],"type":"Point"}
}