{
  "type": "Feature",
  "properties": {
    "gn:admin1_code":"4.0",
    "gn:admin2_code":"417",
    "gn:admin3_code":"41706.0",
    "gn:asciiname":"Berg",
    "gn:country_code":"AT",
    "gn:dem":650,
    "gn:feature_class":"P",
    "gn:feature_code":"PPL",
    "gn:name":"Berg",
    "gn:population":0,
    "gn:timezone":"Europe/Vienna",
    "iso:country":"AT",
    "name:und_x_variant":[
        "Berg im Attergau"
    ],
    "wof:name":"Berg",
    "wof:placetype":"locality"
},
  "geometry": {"coordinates":[13.52546,47.94038],"type":"Point"}
}