{
  "type": "Feature",
  "properties": {
    "gn:admin1_code":"5.0",
    "gn:admin2_code":"503",
    "gn:admin3_code":"50302.0",
    "gn:asciiname":"Raith",
    "gn:country_code":"AT",
    "gn:dem":577,
    "gn:feature_class":"P",
    "gn:feature_code":"PPL",
    "gn:name":"Raith",
    "gn:population":0,
    "gn:timezone":"Europe/Vienna",
    "iso:country":"AT",
    "wof:name":"Raith",
    "wof:placetype":"locality"
},
  "geometry": {"coordinates":[13.02361,47.90778],"type":"Point"}
}