{
  "type": "Feature",
  "properties": {
    "gn:admin1_code":"06",
    "gn:admin2_code":"612.0",
    "gn:admin3_code":"61263.0",
    "gn:asciiname":"Streichhof",
    "gn:country_code":"AT",
    "gn:dem":804,
    "gn:feature_class":"P",
    "gn:feature_code":"PPL",
    "gn:name":"Streichhof",
    "gn:population":0,
    "gn:timezone":"Europe/Vienna",
    "iso:country":"AT",
    "wof:name":"Streichhof",
    "wof:placetype":"locality"
},
  "geometry": {"coordinates":[14.33333,47.53333],"type":"Point"}
}