{
  "type": "Feature",
  "properties": {
    "gn:admin1_code":"02",
    "gn:admin2_code":"207.0",
    "gn:admin3_code":"20702.0",
    "gn:asciiname":"Oberthoerl",
    "gn:country_code":"AT",
    "gn:dem":724,
    "gn:feature_class":"P",
    "gn:feature_code":"PPL",
    "gn:name":"Oberth\u00f6rl",
    "gn:population":56,
    "gn:timezone":"Europe/Vienna",
    "iso:country":"AT",
    "wof:name":"Oberthoerl",
    "wof:placetype":"locality",
    "wof:population":56
},
  "geometry": {"coordinates":[13.65,46.53333],"type":"Point"}
}