{
  "type": "Feature",
  "properties": {
    "gn:admin1_code":"4.0",
    "gn:admin2_code":"417",
    "gn:admin3_code":"41752.0",
    "gn:asciiname":"Ketzerhub",
    "gn:country_code":"AT",
    "gn:dem":563,
    "gn:feature_class":"P",
    "gn:feature_code":"PPL",
    "gn:name":"Ketzerhub",
    "gn:population":20,
    "gn:timezone":"Europe/Vienna",
    "iso:country":"AT",
    "wof:name":"Ketzerhub",
    "wof:placetype":"locality",
    "wof:population":20
},
  "geometry": {"coordinates":[13.58331,48.07134],"type":"Point"}
}