{
  "type": "Feature",
  "properties": {
    "gn:gn_country":"AT",
    "gn:gn_fcode":"PPL",
    "gn:gn_pop":0,
    "iso:country":"AT",
    "name:ara_x_preferred":[
        "\u0641\u064a\u0646\u062f\u0648\u0631\u0641"
    ],
    "name:ceb_x_preferred":[
        "Windorf"
    ],
    "name:ces_x_preferred":[
        "Windorf"
    ],
    "name:deu_x_preferred":[
        "Windorf"
    ],
    "name:epo_x_preferred":[
        "Windorf"
    ],
    "name:eus_x_preferred":[
        "Windorf"
    ],
    "name:fas_x_preferred":[
        "\u0648\u06cc\u0646\u062f\u0648\u0631\u0641"
    ],
    "name:fin_x_preferred":[
        "Windorf"
    ],
    "name:fra_x_preferred":[
        "Windorf"
    ],
    "name:hun_x_preferred":[
        "Windorf"
    ],
    "name:hye_x_preferred":[
        "\u054e\u056b\u0576\u0564\u0578\u0580\u0586"
    ],
    "name:ind_x_preferred":[
        "Windorf"
    ],
    "name:ita_x_preferred":[
        "Windorf"
    ],
    "name:kaz_x_preferred":[
        "\u0412\u0438\u043d\u0434\u043e\u0440\u0444"
    ],
    "name:kir_x_preferred":[
        "\u0412\u0438\u043d\u0434\u043e\u0440\u0444"
    ],
    "name:lmo_x_preferred":[
        "Windorf"
    ],
    "name:msa_x_preferred":[
        "Windorf"
    ],
    "name:nld_x_preferred":[
        "Windorf"
    ],
    "name:pol_x_preferred":[
        "Windorf"
    ],
    "name:ron_x_preferred":[
        "Windorf"
    ],
    "name:rus_x_preferred":[
        "\u0412\u0438\u043d\u0434\u043e\u0440\u0444"
    ],
    "name:spa_x_preferred":[
        "Windorf"
    ],
    "name:srp_x_preferred":[
        "\u0412\u0438\u043d\u0434\u043e\u0440\u0444"
    ],
    "name:swe_x_preferred":[
        "Windorf"
    ],
    "name:ukr_x_preferred":[
        "\u0412\u0456\u043d\u0434\u043e\u0440\u0444"
    ],
    "name:uzb_x_preferred":[
        "Windorf"
    ],
    "name:vie_x_preferred":[
        "Windorf"
    ],
    "name:vol_x_preferred":[
        "Windorf"
    ],
    "name:war_x_preferred":[
        "Windorf"
    ],
    "name:zho_x_preferred":[
        "\u6e29\u591a\u592b"
    ],
    "qs_pg:aaroncc":"AT",
    "qs_pg:gn_country":"AT",
    "qs_pg:gn_fcode":"PPL",
    "qs_pg:gn_pop":0,
    "qs_pg:name":"Windorf",
    "qs_pg:name_adm0":"\u00d6sterreich",
    "qs_pg:name_adm1":"Steiermark",
    "qs_pg:photos":63,
    "qs_pg:photos_1k":13,
    "qs_pg:photos_9k":1,
    "qs_pg:photos_9r":2,
    "qs_pg:photos_all":63,
    "qs_pg:photos_sr":2,
    "qs_pg:pop_sr":0,
    "qs_pg:qs_pg_placetype":"locality",
    "qs_pg:qs_pg_placetype_gp":"Town",
    "qs_pg:woe_adm0":23424750,
    "woe:adm0_id":23424750,
    "woe:name_adm0":"\u00d6sterreich",
    "woe:name_adm1":"Steiermark",
    "woe:placetype":"Town",
    "wof:name":"Windorf",
    "wof:placetype":"locality"
},
  "geometry": {"coordinates":[15.40028,46.9925],"type":"Point"}
}