{
  "type": "Feature",
  "properties": {
    "iso:country":"AT",
    "name:deu_x_preferred":[
        "Rechte Altstadt"
    ],
    "name:eng_x_preferred":[
        "Rechte Altstadt"
    ],
    "wof:name":"Rechte Altstadt",
    "wof:placetype":"neighbourhood"
},
  "geometry": {"coordinates":[13.04368181335724,47.8036262582963],"type":"Point"}
}