{
  "type": "Feature",
  "properties": {
    "gn:admin1_code":"2.0",
    "gn:admin2_code":"204",
    "gn:admin3_code":"20403.0",
    "gn:asciiname":"Babniak",
    "gn:country_code":"AT",
    "gn:dem":463,
    "gn:feature_class":"P",
    "gn:feature_code":"PPL",
    "gn:name":"Babniak",
    "gn:population":0,
    "gn:timezone":"Europe/Vienna",
    "iso:country":"AT",
    "wof:name":"Babniak",
    "wof:placetype":"locality"
},
  "geometry": {"coordinates":[14.23785,46.52769],"type":"Point"}
}