{
  "type": "Feature",
  "properties": {
    "gn:admin1_code":"4.0",
    "gn:admin2_code":"404",
    "gn:admin3_code":"40409.0",
    "gn:asciiname":"Emmersberg",
    "gn:country_code":"AT",
    "gn:dem":473,
    "gn:feature_class":"P",
    "gn:feature_code":"PPL",
    "gn:name":"Emmersberg",
    "gn:population":43,
    "gn:timezone":"Europe/Vienna",
    "iso:country":"AT",
    "wof:name":"Emmersberg",
    "wof:placetype":"locality",
    "wof:population":43
},
  "geometry": {"coordinates":[12.9558,48.08138],"type":"Point"}
}