{
  "type": "Feature",
  "properties": {
    "gn:admin1_code":"4.0",
    "gn:admin2_code":"416",
    "gn:admin3_code":"41608.0",
    "gn:asciiname":"Waldinger-Ebene",
    "gn:country_code":"AT",
    "gn:dem":259,
    "gn:feature_class":"P",
    "gn:feature_code":"PPL",
    "gn:name":"Waldinger-Ebene",
    "gn:population":0,
    "gn:timezone":"Europe/Vienna",
    "iso:country":"AT",
    "wof:name":"Waldinger-Ebene",
    "wof:placetype":"locality"
},
  "geometry": {"coordinates":[14.11639,48.32167000000001],"type":"Point"}
}