{
  "type": "Feature",
  "properties": {
    "gn:admin1_code":"2.0",
    "gn:admin2_code":"203",
    "gn:admin3_code":"20316.0",
    "gn:asciiname":"Karnitzen",
    "gn:country_code":"AT",
    "gn:dem":604,
    "gn:feature_class":"P",
    "gn:feature_code":"PPL",
    "gn:name":"Karnitzen",
    "gn:population":60,
    "gn:timezone":"Europe/Vienna",
    "iso:country":"AT",
    "wof:name":"Karnitzen",
    "wof:placetype":"locality",
    "wof:population":60
},
  "geometry": {"coordinates":[13.55606,46.59747],"type":"Point"}
}