{
  "type": "Feature",
  "properties": {
    "gn:admin1_code":"03",
    "gn:admin2_code":"317.0",
    "gn:admin3_code":"31726.0",
    "gn:asciiname":"Stangau",
    "gn:country_code":"AT",
    "gn:dem":429,
    "gn:elevation":"440.0",
    "gn:feature_class":"P",
    "gn:feature_code":"PPL",
    "gn:name":"Stangau",
    "gn:population":238,
    "gn:timezone":"Europe/Vienna",
    "iso:country":"AT",
    "wof:name":"Stangau",
    "wof:placetype":"locality",
    "wof:population":238
},
  "geometry": {"coordinates":[16.13304,48.10568],"type":"Point"}
}