{
  "type": "Feature",
  "properties": {
    "iso:country":"AT",
    "name:deu_x_preferred":[
        "Itzling"
    ],
    "name:eng_x_preferred":[
        "Itzling"
    ],
    "wof:name":"Itzling",
    "wof:placetype":"neighbourhood"
},
  "geometry": {"coordinates":[13.04253887757229,47.82328923754545],"type":"Point"}
}