{
  "type": "Feature",
  "properties": {
    "gn:admin1_code":"2.0",
    "gn:admin2_code":"205",
    "gn:admin3_code":"20519.0",
    "gn:asciiname":"Grafendorf",
    "gn:country_code":"AT",
    "gn:dem":881,
    "gn:feature_class":"P",
    "gn:feature_code":"PPL",
    "gn:name":"Grafendorf",
    "gn:population":0,
    "gn:timezone":"Europe/Vienna",
    "iso:country":"AT",
    "wof:name":"Grafendorf",
    "wof:placetype":"locality"
},
  "geometry": {"coordinates":[14.41667,46.93333],"type":"Point"}
}