{
  "type": "Feature",
  "properties": {
    "gn:admin1_code":"07",
    "gn:admin2_code":"702.0",
    "gn:admin3_code":"70217.0",
    "gn:asciiname":"Scheibrand",
    "gn:country_code":"AT",
    "gn:dem":1955,
    "gn:feature_class":"P",
    "gn:feature_code":"PPL",
    "gn:name":"Scheibrand",
    "gn:population":0,
    "gn:timezone":"Europe/Vienna",
    "iso:country":"AT",
    "wof:name":"Scheibrand",
    "wof:placetype":"locality"
},
  "geometry": {"coordinates":[10.81667,47.08333],"type":"Point"}
}