{
  "type": "Feature",
  "properties": {
    "gn:admin1_code":"3.0",
    "gn:admin2_code":"325",
    "gn:admin3_code":"32508.0",
    "gn:asciiname":"Etlas",
    "gn:country_code":"AT",
    "gn:dem":675,
    "gn:feature_class":"P",
    "gn:feature_code":"PPL",
    "gn:name":"Etlas",
    "gn:population":15,
    "gn:timezone":"Europe/Vienna",
    "iso:country":"AT",
    "wof:name":"Etlas",
    "wof:placetype":"locality",
    "wof:population":15
},
  "geometry": {"coordinates":[14.97617,48.59512],"type":"Point"}
}