{
  "type": "Feature",
  "properties": {
    "gn:admin1_code":"03",
    "gn:admin2_code":"316.0",
    "gn:admin3_code":"31627.0",
    "gn:asciiname":"Ritzendorf",
    "gn:country_code":"AT",
    "gn:dem":230,
    "gn:feature_class":"P",
    "gn:feature_code":"PPL",
    "gn:name":"Ritzendorf",
    "gn:population":25,
    "gn:timezone":"Europe/Vienna",
    "iso:country":"AT",
    "wof:name":"Ritzendorf",
    "wof:placetype":"locality",
    "wof:population":25
},
  "geometry": {"coordinates":[16.42134,48.44534],"type":"Point"}
}