{
  "type": "Feature",
  "properties": {
    "gn:admin1_code":"3.0",
    "gn:admin2_code":"315",
    "gn:admin3_code":"31543.0",
    "gn:asciiname":"Merkendorf",
    "gn:country_code":"AT",
    "gn:dem":234,
    "gn:feature_class":"P",
    "gn:feature_code":"PPL",
    "gn:name":"Merkendorf",
    "gn:population":85,
    "gn:timezone":"Europe/Vienna",
    "iso:country":"AT",
    "name:ceb_x_preferred":[
        "Merkendorf"
    ],
    "name:deu_x_preferred":[
        "Merkendorf"
    ],
    "name:epo_x_preferred":[
        "Merkendorf"
    ],
    "name:fra_x_preferred":[
        "Merkendorf"
    ],
    "name:ita_x_preferred":[
        "Merkendorf"
    ],
    "name:kaz_x_preferred":[
        "\u041c\u0435\u0440\u043a\u0435\u043d\u0434\u043e\u0440\u0444"
    ],
    "name:nld_x_preferred":[
        "Merkendorf"
    ],
    "name:nor_x_preferred":[
        "Merkendorf"
    ],
    "name:pol_x_preferred":[
        "Merkendorf"
    ],
    "name:ron_x_preferred":[
        "Merkendorf"
    ],
    "name:rus_x_preferred":[
        "\u041c\u0435\u0440\u043a\u0435\u043d\u0434\u043e\u0440\u0444"
    ],
    "name:slk_x_preferred":[
        "Merkendorf"
    ],
    "name:srp_x_preferred":[
        "\u041c\u0435\u0440\u043a\u0435\u043d\u0434\u043e\u0440\u0444"
    ],
    "name:swe_x_preferred":[
        "Merkendorf"
    ],
    "name:vol_x_preferred":[
        "Merkendorf"
    ],
    "name:zho_x_preferred":[
        "\u6885\u5c14\u80af\u591a\u592b"
    ],
    "wof:name":"Merkendorf",
    "wof:placetype":"locality",
    "wof:population":85
},
  "geometry": {"coordinates":[15.36833,48.18864],"type":"Point"}
}