{
  "type": "Feature",
  "properties": {
    "gn:admin1_code":"4.0",
    "gn:admin2_code":"417",
    "gn:admin3_code":"41749.0",
    "gn:asciiname":"Schachmahd",
    "gn:country_code":"AT",
    "gn:dem":535,
    "gn:feature_class":"P",
    "gn:feature_code":"PPL",
    "gn:name":"Schachmahd",
    "gn:population":0,
    "gn:timezone":"Europe/Vienna",
    "iso:country":"AT",
    "wof:name":"Schachmahd",
    "wof:placetype":"locality"
},
  "geometry": {"coordinates":[13.56906,47.86915],"type":"Point"}
}