{
  "type": "Feature",
  "properties": {
    "gn:admin1_code":"4.0",
    "gn:admin2_code":"404",
    "gn:admin3_code":"40442.0",
    "gn:asciiname":"Weilhart",
    "gn:country_code":"AT",
    "gn:dem":420,
    "gn:feature_class":"P",
    "gn:feature_code":"PPL",
    "gn:name":"Weilhart",
    "gn:population":37,
    "gn:timezone":"Europe/Vienna",
    "iso:country":"AT",
    "wof:name":"Weilhart",
    "wof:placetype":"locality",
    "wof:population":37
},
  "geometry": {"coordinates":[12.96391,48.18354],"type":"Point"}
}