{
  "type": "Feature",
  "properties": {
    "gn:admin1_code":"7.0",
    "gn:admin2_code":"709",
    "gn:admin3_code":"70915.0",
    "gn:asciiname":"Holdernach",
    "gn:country_code":"AT",
    "gn:dem":600,
    "gn:feature_class":"P",
    "gn:feature_code":"PPL",
    "gn:name":"Holdernach",
    "gn:population":287,
    "gn:timezone":"Europe/Vienna",
    "iso:country":"AT",
    "wof:name":"Holdernach",
    "wof:placetype":"locality",
    "wof:population":287
},
  "geometry": {"coordinates":[11.86667,47.36667],"type":"Point"}
}