{
  "type": "Feature",
  "properties": {
    "gn:admin1_code":"1.0",
    "gn:admin2_code":"109",
    "gn:admin3_code":"10922.0",
    "gn:asciiname":"Duernbach im Burgenland",
    "gn:cc2":"AT",
    "gn:country_code":"AT",
    "gn:dem":286,
    "gn:feature_class":"P",
    "gn:feature_code":"PPL",
    "gn:name":"D\u00fcrnbach im Burgenland",
    "gn:population":325,
    "gn:timezone":"Europe/Vienna",
    "iso:country":"AT",
    "name:und_x_variant":[
        "D\u00fcrnbach",
        "D\u00fcrnbach bei Grosspetersdorf",
        "D\u00fcrnbach im Burgenland"
    ],
    "wof:name":"Duernbach im Burgenland",
    "wof:placetype":"locality",
    "wof:population":325
},
  "geometry": {"coordinates":[16.39031,47.26356],"type":"Point"}
}