{
  "type": "Feature",
  "properties": {
    "gn:admin1_code":"06",
    "gn:admin2_code":"612.0",
    "gn:admin3_code":"61267.0",
    "gn:asciiname":"Untergrimming",
    "gn:country_code":"AT",
    "gn:dem":672,
    "gn:elevation":"550.0",
    "gn:feature_class":"P",
    "gn:feature_code":"PPL",
    "gn:name":"Untergrimming",
    "gn:population":140,
    "gn:timezone":"Europe/Vienna",
    "iso:country":"AT",
    "wof:name":"Untergrimming",
    "wof:placetype":"locality",
    "wof:population":140
},
  "geometry": {"coordinates":[14.05692,47.52794],"type":"Point"}
}