{
  "type": "Feature",
  "properties": {
    "gn:admin1_code":"05",
    "gn:admin2_code":"503.0",
    "gn:admin3_code":"50310.0",
    "gn:asciiname":"Pebering",
    "gn:country_code":"AT",
    "gn:dem":584,
    "gn:feature_class":"P",
    "gn:feature_code":"PPL",
    "gn:name":"Pebering",
    "gn:population":421,
    "gn:timezone":"Europe/Vienna",
    "iso:country":"AT",
    "wof:name":"Pebering",
    "wof:placetype":"locality",
    "wof:population":421
},
  "geometry": {"coordinates":[13.11667,47.85],"type":"Point"}
}