{
  "type": "Feature",
  "properties": {
    "gn:admin1_code":"4.0",
    "gn:admin2_code":"409",
    "gn:admin3_code":"40904.0",
    "gn:asciiname":"Lauterbach",
    "gn:country_code":"AT",
    "gn:dem":435,
    "gn:feature_class":"P",
    "gn:feature_code":"PPL",
    "gn:name":"Lauterbach",
    "gn:population":410,
    "gn:timezone":"Europe/Vienna",
    "iso:country":"AT",
    "name:ceb_x_preferred":[
        "Lauterbach"
    ],
    "name:chv_x_preferred":[
        "\u041b\u0430\u0443\u0442\u0435\u0440\u0431\u0430\u0445"
    ],
    "name:deu_x_preferred":[
        "Lauterbach"
    ],
    "name:epo_x_preferred":[
        "Lauterbach"
    ],
    "name:fra_x_preferred":[
        "Lauterbach"
    ],
    "name:heb_x_preferred":[
        "\u05dc\u05d5\u05d9\u05d8\u05e8\u05d1\u05da"
    ],
    "name:hun_x_preferred":[
        "Lauterbach"
    ],
    "name:ita_x_preferred":[
        "Lauterbach"
    ],
    "name:jpn_x_preferred":[
        "\u30e9\u30a6\u30bf\u30fc\u30d0\u30c3\u30cf"
    ],
    "name:nld_x_preferred":[
        "Lauterbach"
    ],
    "name:nor_x_preferred":[
        "Lauterbach"
    ],
    "name:pol_x_preferred":[
        "Lauterbach"
    ],
    "name:ron_x_preferred":[
        "Lauterbach"
    ],
    "name:rus_x_preferred":[
        "\u041b\u0430\u0443\u0442\u0435\u0440\u0431\u0430\u0445"
    ],
    "name:srp_x_preferred":[
        "\u041b\u0430\u0443\u0442\u0435\u0440\u0431\u0430\u0445"
    ],
    "name:swe_x_preferred":[
        "Lauterbach"
    ],
    "name:vol_x_preferred":[
        "Lauterbach"
    ],
    "wof:name":"Lauterbach",
    "wof:placetype":"locality",
    "wof:population":410
},
  "geometry": {"coordinates":[14.09756,47.90527],"type":"Point"}
}