{
  "type": "Feature",
  "properties": {
    "gn:admin1_code":"4.0",
    "gn:admin2_code":"412",
    "gn:admin3_code":"41231.0",
    "gn:asciiname":"Wietraun",
    "gn:country_code":"AT",
    "gn:dem":470,
    "gn:feature_class":"P",
    "gn:feature_code":"PPL",
    "gn:name":"Wietraun",
    "gn:population":20,
    "gn:timezone":"Europe/Vienna",
    "iso:country":"AT",
    "wof:name":"Wietraun",
    "wof:placetype":"locality",
    "wof:population":20
},
  "geometry": {"coordinates":[13.56537,48.28165],"type":"Point"}
}