{
  "type": "Feature",
  "properties": {
    "gn:admin1_code":"4.0",
    "gn:admin2_code":"413",
    "gn:admin3_code":"41312.0",
    "gn:asciiname":"Marsbach",
    "gn:country_code":"AT",
    "gn:dem":529,
    "gn:feature_class":"P",
    "gn:feature_code":"PPL",
    "gn:name":"Marsbach",
    "gn:population":41,
    "gn:timezone":"Europe/Vienna",
    "iso:country":"AT",
    "wof:name":"Marsbach",
    "wof:placetype":"locality",
    "wof:population":41
},
  "geometry": {"coordinates":[13.8211,48.46074],"type":"Point"}
}