{
  "type": "Feature",
  "properties": {
    "gn:admin1_code":"4.0",
    "gn:admin2_code":"405",
    "gn:admin3_code":"40505.0",
    "gn:asciiname":"Schloegenleiten",
    "gn:country_code":"AT",
    "gn:dem":445,
    "gn:feature_class":"P",
    "gn:feature_code":"PPL",
    "gn:name":"Schl\u00f6genleiten",
    "gn:population":15,
    "gn:timezone":"Europe/Vienna",
    "iso:country":"AT",
    "wof:name":"Schloegenleiten",
    "wof:placetype":"locality",
    "wof:population":15
},
  "geometry": {"coordinates":[13.8808,48.41901],"type":"Point"}
}