{
  "type": "Feature",
  "properties": {
    "gn:admin1_code":"4.0",
    "gn:admin2_code":"410",
    "gn:admin3_code":"41012.0",
    "gn:asciiname":"Bergham",
    "gn:country_code":"AT",
    "gn:dem":306,
    "gn:feature_class":"P",
    "gn:feature_code":"PPL",
    "gn:name":"Bergham",
    "gn:population":1171,
    "gn:timezone":"Europe/Vienna",
    "iso:country":"AT",
    "wof:name":"Bergham",
    "wof:placetype":"locality",
    "wof:population":1171
},
  "geometry": {"coordinates":[14.23141,48.28182],"type":"Point"}
}