{
  "type": "Feature",
  "properties": {
    "gn:admin1_code":"3.0",
    "gn:admin2_code":"315",
    "gn:admin3_code":"31514.0",
    "gn:asciiname":"Mallau",
    "gn:country_code":"AT",
    "gn:dem":295,
    "gn:feature_class":"P",
    "gn:feature_code":"PPL",
    "gn:name":"Mallau",
    "gn:population":55,
    "gn:timezone":"Europe/Vienna",
    "iso:country":"AT",
    "wof:name":"Mallau",
    "wof:placetype":"locality",
    "wof:population":55
},
  "geometry": {"coordinates":[15.41708,48.10531],"type":"Point"}
}