{
  "type": "Feature",
  "properties": {
    "gn:admin1_code":"06",
    "gn:admin2_code":"617.0",
    "gn:admin3_code":"61751.0",
    "gn:asciiname":"Trennstein",
    "gn:country_code":"AT",
    "gn:dem":685,
    "gn:feature_class":"P",
    "gn:feature_code":"PPL",
    "gn:name":"Trennstein",
    "gn:population":166,
    "gn:timezone":"Europe/Vienna",
    "iso:country":"AT",
    "wof:name":"Trennstein",
    "wof:placetype":"locality",
    "wof:population":166
},
  "geometry": {"coordinates":[15.65,47.25],"type":"Point"}
}