{
  "type": "Feature",
  "properties": {
    "gn:admin1_code":"04",
    "gn:admin2_code":"405.0",
    "gn:admin3_code":"40506.0",
    "gn:asciiname":"Poxham",
    "gn:country_code":"AT",
    "gn:dem":277,
    "gn:feature_class":"P",
    "gn:feature_code":"PPL",
    "gn:name":"Poxham",
    "gn:population":137,
    "gn:timezone":"Europe/Vienna",
    "iso:country":"AT",
    "wof:name":"Poxham",
    "wof:placetype":"locality",
    "wof:population":137
},
  "geometry": {"coordinates":[13.97779,48.3583],"type":"Point"}
}