{
  "type": "Feature",
  "properties": {
    "gn:admin1_code":"7.0",
    "gn:admin2_code":"704",
    "gn:admin3_code":"70405.0",
    "gn:asciiname":"Magnesilwerk",
    "gn:country_code":"AT",
    "gn:dem":972,
    "gn:feature_class":"P",
    "gn:feature_code":"PPL",
    "gn:name":"Magnesilwerk",
    "gn:population":0,
    "gn:timezone":"Europe/Vienna",
    "iso:country":"AT",
    "wof:name":"Magnesilwerk",
    "wof:placetype":"locality"
},
  "geometry": {"coordinates":[12.63333,47.46667],"type":"Point"}
}