{
  "type": "Feature",
  "properties": {
    "gn:admin1_code":"03",
    "gn:admin2_code":"305.0",
    "gn:admin3_code":"30538.0",
    "gn:asciiname":"Ufer",
    "gn:country_code":"AT",
    "gn:dem":276,
    "gn:feature_class":"P",
    "gn:feature_code":"PPL",
    "gn:name":"Ufer",
    "gn:population":0,
    "gn:timezone":"Europe/Vienna",
    "iso:country":"AT",
    "wof:name":"Ufer",
    "wof:placetype":"locality"
},
  "geometry": {"coordinates":[14.71667,48.16667],"type":"Point"}
}