{
  "type": "Feature",
  "properties": {
    "gn:admin1_code":"6.0",
    "gn:admin2_code":"614",
    "gn:admin3_code":"61439.0",
    "gn:asciiname":"Strimitzen",
    "gn:country_code":"AT",
    "gn:dem":850,
    "gn:feature_class":"P",
    "gn:feature_code":"PPL",
    "gn:name":"Strimitzen",
    "gn:population":0,
    "gn:timezone":"Europe/Vienna",
    "iso:country":"AT",
    "wof:name":"Strimitzen",
    "wof:placetype":"locality"
},
  "geometry": {"coordinates":[14.4275,47.07889],"type":"Point"}
}