{
  "type": "Feature",
  "properties": {
    "gn:admin1_code":"4.0",
    "gn:admin2_code":"405",
    "gn:admin3_code":"40505.0",
    "gn:asciiname":"Rennersdorf",
    "gn:country_code":"AT",
    "gn:dem":503,
    "gn:feature_class":"P",
    "gn:feature_code":"PPL",
    "gn:name":"Rennersdorf",
    "gn:population":10,
    "gn:timezone":"Europe/Vienna",
    "iso:country":"AT",
    "wof:name":"Rennersdorf",
    "wof:placetype":"locality",
    "wof:population":10
},
  "geometry": {"coordinates":[13.91238,48.41972],"type":"Point"}
}