{
  "type": "Feature",
  "properties": {
    "gn:admin1_code":"04",
    "gn:admin2_code":"412.0",
    "gn:admin3_code":"41202.0",
    "gn:asciiname":"Viehausen",
    "gn:country_code":"AT",
    "gn:dem":335,
    "gn:feature_class":"P",
    "gn:feature_code":"PPL",
    "gn:name":"Viehausen",
    "gn:population":43,
    "gn:timezone":"Europe/Vienna",
    "iso:country":"AT",
    "wof:name":"Viehausen",
    "wof:placetype":"locality",
    "wof:population":43
},
  "geometry": {"coordinates":[13.3913,48.35556],"type":"Point"}
}