{
  "type": "Feature",
  "properties": {
    "gn:admin1_code":"04",
    "gn:admin2_code":"413.0",
    "gn:admin3_code":"41342.0",
    "gn:asciiname":"Sonnleiten",
    "gn:country_code":"AT",
    "gn:dem":715,
    "gn:feature_class":"P",
    "gn:feature_code":"PPL",
    "gn:name":"Sonnleiten",
    "gn:population":0,
    "gn:timezone":"Europe/Vienna",
    "iso:country":"AT",
    "wof:name":"Sonnleiten",
    "wof:placetype":"locality"
},
  "geometry": {"coordinates":[13.94328,48.67895],"type":"Point"}
}