{
  "type": "Feature",
  "properties": {
    "gn:admin1_code":"4.0",
    "gn:admin2_code":"417",
    "gn:admin3_code":"41739.0",
    "gn:asciiname":"Moos",
    "gn:country_code":"AT",
    "gn:dem":481,
    "gn:feature_class":"P",
    "gn:feature_code":"PPL",
    "gn:name":"Moos",
    "gn:population":34,
    "gn:timezone":"Europe/Vienna",
    "iso:country":"AT",
    "name:als_x_preferred":[
        "Moos"
    ],
    "name:ceb_x_preferred":[
        "Moos"
    ],
    "name:deu_x_preferred":[
        "Moos"
    ],
    "name:epo_x_preferred":[
        "Moos"
    ],
    "name:fra_x_preferred":[
        "Moos"
    ],
    "name:hun_x_preferred":[
        "Moos"
    ],
    "name:ita_x_preferred":[
        "Moos"
    ],
    "name:nld_x_preferred":[
        "Moos"
    ],
    "name:pol_x_preferred":[
        "Moos"
    ],
    "name:por_x_preferred":[
        "Moos"
    ],
    "name:rus_x_preferred":[
        "\u041c\u043e\u043e\u0441"
    ],
    "name:swe_x_preferred":[
        "Moos"
    ],
    "name:vol_x_preferred":[
        "Moos"
    ],
    "wof:name":"Moos",
    "wof:placetype":"locality",
    "wof:population":34
},
  "geometry": {"coordinates":[13.57013,47.94349],"type":"Point"}
}