{
  "type": "Feature",
  "properties": {
    "gn:admin1_code":"3.0",
    "gn:admin2_code":"316",
    "gn:admin3_code":"31633.0",
    "gn:asciiname":"Sonnenbergen",
    "gn:country_code":"AT",
    "gn:dem":246,
    "gn:feature_class":"P",
    "gn:feature_code":"PPLL",
    "gn:name":"Sonnenbergen",
    "gn:population":0,
    "gn:timezone":"Europe/Vienna",
    "iso:country":"AT",
    "wof:name":"Sonnenbergen",
    "wof:placetype":"locality"
},
  "geometry": {"coordinates":[16.57611,48.55111],"type":"Point"}
}