{
  "type": "Feature",
  "properties": {
    "gn:admin1_code":"06",
    "gn:admin2_code":"612.0",
    "gn:admin3_code":"61259.0",
    "gn:asciiname":"Roeth",
    "gn:country_code":"AT",
    "gn:dem":1049,
    "gn:feature_class":"P",
    "gn:feature_code":"PPL",
    "gn:name":"R\u00f6th",
    "gn:population":0,
    "gn:timezone":"Europe/Vienna",
    "iso:country":"AT",
    "wof:name":"Roeth",
    "wof:placetype":"locality"
},
  "geometry": {"coordinates":[14.23333,47.58333],"type":"Point"}
}