{
  "type": "Feature",
  "properties": {
    "gn:admin1_code":"5.0",
    "gn:admin2_code":"503",
    "gn:admin3_code":"50326.0",
    "gn:asciiname":"Mayrhof",
    "gn:country_code":"AT",
    "gn:dem":415,
    "gn:feature_class":"P",
    "gn:feature_code":"PPL",
    "gn:name":"Mayrhof",
    "gn:population":0,
    "gn:timezone":"Europe/Vienna",
    "iso:country":"AT",
    "name:ceb_x_preferred":[
        "Mayrhof"
    ],
    "name:deu_x_preferred":[
        "Mayrhof"
    ],
    "name:fas_x_preferred":[
        "\u0645\u0627\u06cc\u0631\u0647\u0648\u0641"
    ],
    "name:fra_x_preferred":[
        "Mayrhof"
    ],
    "name:hun_x_preferred":[
        "Mayrhof"
    ],
    "name:ita_x_preferred":[
        "Mayrhof"
    ],
    "name:kaz_x_preferred":[
        "\u041c\u0430\u0439\u0440\u0445\u043e\u0444"
    ],
    "name:nld_x_preferred":[
        "Mayrhof"
    ],
    "name:pol_x_preferred":[
        "Mayrhof"
    ],
    "name:por_x_preferred":[
        "Mayrhof"
    ],
    "name:rus_x_preferred":[
        "\u041c\u0430\u0439\u0440\u0445\u043e\u0444"
    ],
    "name:slk_x_preferred":[
        "Mayrhof"
    ],
    "name:spa_x_preferred":[
        "Mayrhof"
    ],
    "name:swe_x_preferred":[
        "Mayrhof"
    ],
    "name:uzb_x_preferred":[
        "Mayrhof"
    ],
    "name:vie_x_preferred":[
        "Mayrhof"
    ],
    "name:vol_x_preferred":[
        "Mayrhof"
    ],
    "name:war_x_preferred":[
        "Mayrhof"
    ],
    "name:zho_x_preferred":[
        "\u8fc8\u5c14\u970d\u592b"
    ],
    "wof:name":"Mayrhof",
    "wof:placetype":"locality"
},
  "geometry": {"coordinates":[12.9475,47.9425],"type":"Point"}
}