{
  "type": "Feature",
  "properties": {
    "gn:admin1_code":"7.0",
    "gn:admin2_code":"704",
    "gn:admin3_code":"70412.0",
    "gn:asciiname":"Moserberg",
    "gn:country_code":"AT",
    "gn:dem":623,
    "gn:feature_class":"P",
    "gn:feature_code":"PPL",
    "gn:name":"Moserberg",
    "gn:population":0,
    "gn:timezone":"Europe/Vienna",
    "iso:country":"AT",
    "wof:name":"Moserberg",
    "wof:placetype":"locality"
},
  "geometry": {"coordinates":[12.41667,47.66667],"type":"Point"}
}