{
  "type": "Feature",
  "properties": {
    "gn:admin1_code":"4.0",
    "gn:admin2_code":"410",
    "gn:admin3_code":"41006.0",
    "gn:asciiname":"Hart",
    "gn:country_code":"AT",
    "gn:dem":283,
    "gn:feature_class":"P",
    "gn:feature_code":"PPL",
    "gn:name":"Hart",
    "gn:population":39,
    "gn:timezone":"Europe/Vienna",
    "iso:country":"AT",
    "wof:name":"Hart",
    "wof:placetype":"locality",
    "wof:population":39
},
  "geometry": {"coordinates":[14.44771,48.165],"type":"Point"}
}