{
  "type": "Feature",
  "properties": {
    "gn:admin1_code":"6.0",
    "gn:admin2_code":"610",
    "gn:admin3_code":"61058.0",
    "gn:asciiname":"Lind bei Sankt Veit am Vogau",
    "gn:cc2":"AT",
    "gn:country_code":"AT",
    "gn:dem":264,
    "gn:feature_class":"P",
    "gn:feature_code":"PPL",
    "gn:name":"Lind bei Sankt Veit am Vogau",
    "gn:population":0,
    "gn:timezone":"Europe/Vienna",
    "iso:country":"AT",
    "name:und_x_variant":[
        "Lind",
        "Lind bei Sankt Veit am Vogau"
    ],
    "wof:name":"Lind bei Sankt Veit am Vogau",
    "wof:placetype":"locality"
},
  "geometry": {"coordinates":[15.63333,46.73333],"type":"Point"}
}