{
  "type": "Feature",
  "properties": {
    "gn:admin1_code":"3.0",
    "gn:admin2_code":"311",
    "gn:admin3_code":"31129.0",
    "gn:asciiname":"Obermixnitz",
    "gn:country_code":"AT",
    "gn:dem":422,
    "gn:feature_class":"P",
    "gn:feature_code":"PPL",
    "gn:name":"Obermixnitz",
    "gn:population":104,
    "gn:timezone":"Europe/Vienna",
    "iso:country":"AT",
    "wof:name":"Obermixnitz",
    "wof:placetype":"locality",
    "wof:population":104
},
  "geometry": {"coordinates":[15.81667,48.75],"type":"Point"}
}