{
  "type": "Feature",
  "properties": {
    "gn:admin1_code":"6.0",
    "gn:admin2_code":"617",
    "gn:admin3_code":"61766.0",
    "gn:asciiname":"Landscha bei Weiz",
    "gn:cc2":"AT",
    "gn:country_code":"AT",
    "gn:dem":506,
    "gn:feature_class":"P",
    "gn:feature_code":"PPL",
    "gn:name":"Landscha bei Weiz",
    "gn:population":0,
    "gn:timezone":"Europe/Vienna",
    "iso:country":"AT",
    "name:und_x_variant":[
        "Landscha",
        "Landscha bei Weiz"
    ],
    "wof:name":"Landscha bei Weiz",
    "wof:placetype":"locality"
},
  "geometry": {"coordinates":[15.61667,47.21667],"type":"Point"}
}