{
  "type": "Feature",
  "properties": {
    "gn:admin1_code":"3.0",
    "gn:admin2_code":"319",
    "gn:admin3_code":"31934.0",
    "gn:asciiname":"Unterzell",
    "gn:country_code":"AT",
    "gn:dem":427,
    "gn:feature_class":"P",
    "gn:feature_code":"PPL",
    "gn:name":"Unterzell",
    "gn:population":0,
    "gn:timezone":"Europe/Vienna",
    "iso:country":"AT",
    "wof:name":"Unterzell",
    "wof:placetype":"locality"
},
  "geometry": {"coordinates":[15.73517,48.13301],"type":"Point"}
}