{
  "type": "Feature",
  "properties": {
    "gn:admin1_code":"5.0",
    "gn:admin2_code":"503",
    "gn:admin3_code":"50316.0",
    "gn:asciiname":"Midering",
    "gn:country_code":"AT",
    "gn:dem":531,
    "gn:feature_class":"P",
    "gn:feature_code":"PPL",
    "gn:name":"Midering",
    "gn:population":0,
    "gn:timezone":"Europe/Vienna",
    "iso:country":"AT",
    "wof:name":"Midering",
    "wof:placetype":"locality"
},
  "geometry": {"coordinates":[13.07806,47.86139],"type":"Point"}
}