{
  "type": "Feature",
  "properties": {
    "gn:admin1_code":"06",
    "gn:admin2_code":"603.0",
    "gn:admin3_code":"60350.0",
    "gn:asciiname":"Oberrossegg",
    "gn:country_code":"AT",
    "gn:dem":327,
    "gn:feature_class":"P",
    "gn:feature_code":"PPL",
    "gn:name":"Oberrossegg",
    "gn:population":0,
    "gn:timezone":"Europe/Vienna",
    "iso:country":"AT",
    "wof:name":"Oberrossegg",
    "wof:placetype":"locality"
},
  "geometry": {"coordinates":[15.28333,46.91667],"type":"Point"}
}