{
  "type": "Feature",
  "properties": {
    "gn:admin1_code":"02",
    "gn:admin2_code":"205.0",
    "gn:admin3_code":"20512.0",
    "gn:asciiname":"Silberegg",
    "gn:country_code":"AT",
    "gn:dem":594,
    "gn:feature_class":"P",
    "gn:feature_code":"PPL",
    "gn:name":"Silberegg",
    "gn:population":385,
    "gn:timezone":"Europe/Vienna",
    "iso:country":"AT",
    "wof:name":"Silberegg",
    "wof:placetype":"locality",
    "wof:population":385
},
  "geometry": {"coordinates":[14.49361,46.85167],"type":"Point"}
}