{
  "type": "Feature",
  "properties": {
    "gn:admin1_code":"07",
    "gn:admin2_code":"704.0",
    "gn:admin3_code":"70403.0",
    "gn:asciiname":"Pertrach",
    "gn:country_code":"AT",
    "gn:dem":932,
    "gn:feature_class":"P",
    "gn:feature_code":"PPL",
    "gn:name":"Pertrach",
    "gn:population":0,
    "gn:timezone":"Europe/Vienna",
    "iso:country":"AT",
    "wof:name":"Pertrach",
    "wof:placetype":"locality"
},
  "geometry": {"coordinates":[12.55,47.48333],"type":"Point"}
}