{
  "type": "Feature",
  "properties": {
    "gn:admin1_code":"4.0",
    "gn:admin2_code":"408",
    "gn:admin3_code":"40833.0",
    "gn:asciiname":"Ortmanau",
    "gn:country_code":"AT",
    "gn:dem":426,
    "gn:feature_class":"P",
    "gn:feature_code":"PPL",
    "gn:name":"Ortmanau",
    "gn:population":32,
    "gn:timezone":"Europe/Vienna",
    "iso:country":"AT",
    "wof:name":"Ortmanau",
    "wof:placetype":"locality",
    "wof:population":32
},
  "geometry": {"coordinates":[13.70407,48.20294000000001],"type":"Point"}
}