{
  "type": "Feature",
  "properties": {
    "gn:admin1_code":"5.0",
    "gn:admin2_code":"503",
    "gn:admin3_code":"50303.0",
    "gn:asciiname":"Muntigl",
    "gn:country_code":"AT",
    "gn:dem":414,
    "gn:feature_class":"P",
    "gn:feature_code":"PPL",
    "gn:name":"Muntigl",
    "gn:population":461,
    "gn:timezone":"Europe/Vienna",
    "iso:country":"AT",
    "wof:name":"Muntigl",
    "wof:placetype":"locality",
    "wof:population":461
},
  "geometry": {"coordinates":[13.01433,47.85337],"type":"Point"}
}