{
  "type": "Feature",
  "properties": {
    "gn:admin1_code":"02",
    "gn:admin2_code":"206.0",
    "gn:admin3_code":"20640.0",
    "gn:asciiname":"Reinthal",
    "gn:cc2":"AT",
    "gn:country_code":"AT",
    "gn:dem":915,
    "gn:feature_class":"P",
    "gn:feature_code":"PPL",
    "gn:name":"Reinthal",
    "gn:population":97,
    "gn:timezone":"Europe/Vienna",
    "iso:country":"AT",
    "name:und_x_variant":[
        "Reintal",
        "Reinthal"
    ],
    "wof:name":"Reinthal",
    "wof:placetype":"locality",
    "wof:population":97
},
  "geometry": {"coordinates":[12.88028,46.86472],"type":"Point"}
}