{
  "type": "Feature",
  "properties": {
    "gn:admin1_code":"06",
    "gn:admin2_code":"623.0",
    "gn:admin3_code":"62330.0",
    "gn:asciiname":"Simmersberg",
    "gn:country_code":"AT",
    "gn:dem":354,
    "gn:feature_class":"P",
    "gn:feature_code":"PPL",
    "gn:name":"Simmersberg",
    "gn:population":0,
    "gn:timezone":"Europe/Vienna",
    "iso:country":"AT",
    "name:ceb_x_preferred":[
        "Simmersberg"
    ],
    "name:deu_x_preferred":[
        "Simmersberg"
    ],
    "wof:name":"Simmersberg",
    "wof:placetype":"locality"
},
  "geometry": {"coordinates":[15.71667,46.86667],"type":"Point"}
}