{
  "type": "Feature",
  "properties": {
    "gn:admin1_code":"6.0",
    "gn:admin2_code":"620",
    "gn:admin3_code":"62048.0",
    "gn:asciiname":"Grossfeistritz",
    "gn:cc2":"AT",
    "gn:country_code":"AT",
    "gn:dem":692,
    "gn:feature_class":"P",
    "gn:feature_code":"PPL",
    "gn:name":"Gro\u00dffeistritz",
    "gn:population":135,
    "gn:timezone":"Europe/Vienna",
    "iso:country":"AT",
    "name:und_x_variant":[
        "Gro\u00dffeistritz"
    ],
    "wof:name":"Grossfeistritz",
    "wof:placetype":"locality",
    "wof:population":135
},
  "geometry": {"coordinates":[14.76935,47.16062],"type":"Point"}
}