{
  "type": "Feature",
  "properties": {
    "gn:admin1_code":"4.0",
    "gn:admin2_code":"413",
    "gn:admin3_code":"41305.0",
    "gn:asciiname":"Hoelling",
    "gn:country_code":"AT",
    "gn:dem":579,
    "gn:feature_class":"P",
    "gn:feature_code":"PPL",
    "gn:name":"H\u00f6lling",
    "gn:population":86,
    "gn:timezone":"Europe/Vienna",
    "iso:country":"AT",
    "wof:name":"Hoelling",
    "wof:placetype":"locality",
    "wof:population":86
},
  "geometry": {"coordinates":[13.99813,48.51405],"type":"Point"}
}