{
  "type": "Feature",
  "properties": {
    "gn:admin1_code":"3.0",
    "gn:admin2_code":"306",
    "gn:admin3_code":"30639.0",
    "gn:asciiname":"Josefsthal",
    "gn:country_code":"AT",
    "gn:dem":210,
    "gn:feature_class":"P",
    "gn:feature_code":"PPL",
    "gn:name":"Josefsthal",
    "gn:population":0,
    "gn:timezone":"Europe/Vienna",
    "iso:country":"AT",
    "wof:name":"Josefsthal",
    "wof:placetype":"locality"
},
  "geometry": {"coordinates":[16.27212999999999,48.01158],"type":"Point"}
}