{
  "type": "Feature",
  "properties": {
    "gn:admin1_code":"2.0",
    "gn:admin2_code":"203",
    "gn:admin3_code":"20305.0",
    "gn:asciiname":"Suessenberg",
    "gn:country_code":"AT",
    "gn:dem":656,
    "gn:feature_class":"P",
    "gn:feature_code":"PPL",
    "gn:name":"S\u00fc\u00dfenberg",
    "gn:population":16,
    "gn:timezone":"Europe/Vienna",
    "iso:country":"AT",
    "wof:name":"Suessenberg",
    "wof:placetype":"locality",
    "wof:population":16
},
  "geometry": {"coordinates":[13.40585,46.61171],"type":"Point"}
}