{
  "type": "Feature",
  "properties": {
    "gn:admin1_code":"03",
    "gn:admin2_code":"310.0",
    "gn:admin3_code":"31038.0",
    "gn:asciiname":"Mitterretzbach",
    "gn:country_code":"AT",
    "gn:dem":256,
    "gn:feature_class":"P",
    "gn:feature_code":"PPL",
    "gn:name":"Mitterretzbach",
    "gn:population":235,
    "gn:timezone":"Europe/Vienna",
    "iso:country":"AT",
    "wof:name":"Mitterretzbach",
    "wof:placetype":"locality",
    "wof:population":235
},
  "geometry": {"coordinates":[15.97451,48.78434],"type":"Point"}
}