{
  "type": "Feature",
  "properties": {
    "gn:admin1_code":"04",
    "gn:admin2_code":"407.0",
    "gn:admin3_code":"40702.0",
    "gn:asciiname":"Sarstein",
    "gn:country_code":"AT",
    "gn:dem":554,
    "gn:feature_class":"P",
    "gn:feature_code":"PPL",
    "gn:name":"Sarstein",
    "gn:population":218,
    "gn:timezone":"Europe/Vienna",
    "iso:country":"AT",
    "wof:name":"Sarstein",
    "wof:placetype":"locality",
    "wof:population":218
},
  "geometry": {"coordinates":[13.65,47.61667],"type":"Point"}
}