{
  "type": "Feature",
  "properties": {
    "gn:admin1_code":"06",
    "gn:admin2_code":"623.0",
    "gn:admin3_code":"62380.0",
    "gn:asciiname":"Ebersdorfbergen",
    "gn:country_code":"AT",
    "gn:dem":305,
    "gn:feature_class":"P",
    "gn:feature_code":"PPL",
    "gn:name":"Ebersdorfbergen",
    "gn:population":0,
    "gn:timezone":"Europe/Vienna",
    "iso:country":"AT",
    "wof:name":"Ebersdorfbergen",
    "wof:placetype":"locality"
},
  "geometry": {"coordinates":[15.85,46.85],"type":"Point"}
}