{
  "type": "Feature",
  "properties": {
    "iso:country":"AT",
    "name:ceb_x_preferred":[
        "Stolzalpe"
    ],
    "name:deu_x_preferred":[
        "Stolzalpe"
    ],
    "name:eng_x_preferred":[
        "Stolzalpe"
    ],
    "name:fra_x_preferred":[
        "Stolzalpe"
    ],
    "name:hun_x_preferred":[
        "Stolzalpe"
    ],
    "name:ita_x_preferred":[
        "Stolzalpe"
    ],
    "name:nld_x_preferred":[
        "Stolzalpe"
    ],
    "name:slk_x_preferred":[
        "Stolzalpe"
    ],
    "name:swe_x_preferred":[
        "Stolzalpe"
    ],
    "name:vie_x_preferred":[
        "Stolzalpe"
    ],
    "name:vol_x_preferred":[
        "Stolzalpe"
    ],
    "name:war_x_preferred":[
        "Stolzalpe"
    ],
    "name:zho_x_preferred":[
        "\u65bd\u6258\u5c14\u5bdf\u5c14\u73c0"
    ],
    "qs_pg:aaroncc":"AT",
    "qs_pg:name":"Stolzalpe",
    "qs_pg:name_adm0":"\u00d6sterreich",
    "qs_pg:name_adm1":"Steiermark",
    "qs_pg:photos":23,
    "qs_pg:photos_1k":5,
    "qs_pg:photos_9k":1,
    "qs_pg:photos_9r":1,
    "qs_pg:photos_all":23,
    "qs_pg:photos_sr":1,
    "qs_pg:pop_sr":0,
    "qs_pg:qs_pg_placetype":"locality",
    "qs_pg:qs_pg_placetype_gp":"Town",
    "qs_pg:woe_adm0":23424750,
    "woe:adm0_id":23424750,
    "woe:name_adm0":"\u00d6sterreich",
    "woe:name_adm1":"Steiermark",
    "woe:placetype":"Town",
    "wof:name":"Stolzalpe",
    "wof:placetype":"locality"
},
  "geometry": {"coordinates":[14.218025,47.094902],"type":"Point"}
}