{
  "type": "Feature",
  "properties": {
    "gn:admin1_code":"03",
    "gn:admin2_code":"310.0",
    "gn:admin3_code":"31041.0",
    "gn:asciiname":"Waitzendorf",
    "gn:country_code":"AT",
    "gn:dem":331,
    "gn:feature_class":"P",
    "gn:feature_code":"PPL",
    "gn:name":"Waitzendorf",
    "gn:population":212,
    "gn:timezone":"Europe/Vienna",
    "iso:country":"AT",
    "wof:name":"Waitzendorf",
    "wof:placetype":"locality",
    "wof:population":212
},
  "geometry": {"coordinates":[15.8749,48.73808],"type":"Point"}
}