{
  "type": "Feature",
  "properties": {
    "gn:admin1_code":"03",
    "gn:admin2_code":"322.0",
    "gn:admin3_code":"32210.0",
    "gn:asciiname":"Tiefenbach",
    "gn:country_code":"AT",
    "gn:dem":502,
    "gn:feature_class":"P",
    "gn:feature_code":"PPL",
    "gn:name":"Tiefenbach",
    "gn:population":53,
    "gn:timezone":"Europe/Vienna",
    "iso:country":"AT",
    "name:ceb_x_preferred":[
        "Tiefenbach"
    ],
    "name:deu_x_preferred":[
        "Tiefenbach"
    ],
    "name:epo_x_preferred":[
        "Tiefenbach"
    ],
    "name:fra_x_preferred":[
        "Tiefenbach"
    ],
    "name:hun_x_preferred":[
        "Tiefenbach"
    ],
    "name:ita_x_preferred":[
        "Tiefenbach"
    ],
    "name:lmo_x_preferred":[
        "Tiefenbach"
    ],
    "name:nld_x_preferred":[
        "Tiefenbach"
    ],
    "name:pol_x_preferred":[
        "Tiefenbach"
    ],
    "name:por_x_preferred":[
        "Tiefenbach"
    ],
    "name:ron_x_preferred":[
        "Tiefenbach"
    ],
    "name:rus_x_preferred":[
        "\u0422\u0438\u0444\u0435\u043d\u0431\u0430\u0445"
    ],
    "name:swe_x_preferred":[
        "Tiefenbach"
    ],
    "name:vol_x_preferred":[
        "Tiefenbach"
    ],
    "wof:name":"Tiefenbach",
    "wof:placetype":"locality",
    "wof:population":53
},
  "geometry": {"coordinates":[15.26667,48.93333],"type":"Point"}
}