{
  "type": "Feature",
  "properties": {
    "gn:admin1_code":"3.0",
    "gn:admin2_code":"319",
    "gn:admin3_code":"31903.0",
    "gn:asciiname":"Ausserkasten",
    "gn:country_code":"AT",
    "gn:dem":268,
    "gn:feature_class":"P",
    "gn:feature_code":"PPL",
    "gn:name":"Ausserkasten",
    "gn:population":0,
    "gn:timezone":"Europe/Vienna",
    "iso:country":"AT",
    "wof:name":"Ausserkasten",
    "wof:placetype":"locality"
},
  "geometry": {"coordinates":[15.76521,48.16357],"type":"Point"}
}