{
  "type": "Feature",
  "properties": {
    "gn:admin1_code":"04",
    "gn:admin2_code":"408.0",
    "gn:admin3_code":"40804.0",
    "gn:asciiname":"Unteraubach",
    "gn:country_code":"AT",
    "gn:dem":416,
    "gn:feature_class":"P",
    "gn:feature_code":"PPL",
    "gn:name":"Unteraubach",
    "gn:population":43,
    "gn:timezone":"Europe/Vienna",
    "iso:country":"AT",
    "wof:name":"Unteraubach",
    "wof:placetype":"locality",
    "wof:population":43
},
  "geometry": {"coordinates":[13.7966,48.37815],"type":"Point"}
}