{
  "type": "Feature",
  "properties": {
    "gn:admin1_code":"04",
    "gn:admin2_code":"408.0",
    "gn:admin3_code":"40830.0",
    "gn:asciiname":"Oberunterstetten",
    "gn:country_code":"AT",
    "gn:dem":366,
    "gn:feature_class":"P",
    "gn:feature_code":"PPL",
    "gn:name":"Oberunterstetten",
    "gn:population":0,
    "gn:timezone":"Europe/Vienna",
    "iso:country":"AT",
    "wof:name":"Oberunterstetten",
    "wof:placetype":"locality"
},
  "geometry": {"coordinates":[13.78333,48.25],"type":"Point"}
}