{
  "type": "Feature",
  "properties": {
    "gn:admin1_code":"3.0",
    "gn:admin2_code":"319",
    "gn:admin3_code":"31906.0",
    "gn:asciiname":"Lehengegend",
    "gn:country_code":"AT",
    "gn:dem":600,
    "gn:feature_class":"P",
    "gn:feature_code":"PPL",
    "gn:name":"Lehengegend",
    "gn:population":95,
    "gn:timezone":"Europe/Vienna",
    "iso:country":"AT",
    "wof:name":"Lehengegend",
    "wof:placetype":"locality",
    "wof:population":95
},
  "geometry": {"coordinates":[15.31468,47.99142],"type":"Point"}
}