{
  "type": "Feature",
  "properties": {
    "gn:admin1_code":"02",
    "gn:admin2_code":"204.0",
    "gn:admin3_code":"20425.0",
    "gn:asciiname":"Sankt Lorenzen",
    "gn:country_code":"AT",
    "gn:dem":446,
    "gn:feature_class":"P",
    "gn:feature_code":"PPL",
    "gn:name":"Sankt Lorenzen",
    "gn:population":0,
    "gn:timezone":"Europe/Vienna",
    "iso:country":"AT",
    "wof:name":"Sankt Lorenzen",
    "wof:placetype":"locality"
},
  "geometry": {"coordinates":[14.43333,46.65],"type":"Point"}
}