{
  "type": "Feature",
  "properties": {
    "gn:admin1_code":"4.0",
    "gn:admin2_code":"414",
    "gn:admin3_code":"41420.0",
    "gn:asciiname":"Ginzldorf",
    "gn:country_code":"AT",
    "gn:dem":610,
    "gn:feature_class":"P",
    "gn:feature_code":"PPL",
    "gn:name":"Ginzldorf",
    "gn:population":72,
    "gn:timezone":"Europe/Vienna",
    "iso:country":"AT",
    "wof:name":"Ginzldorf",
    "wof:placetype":"locality",
    "wof:population":72
},
  "geometry": {"coordinates":[13.65274,48.49983],"type":"Point"}
}