{
  "type": "Feature",
  "properties": {
    "gn:admin1_code":"3.0",
    "gn:admin2_code":"315",
    "gn:admin3_code":"31541.0",
    "gn:asciiname":"Oberfehl",
    "gn:country_code":"AT",
    "gn:dem":508,
    "gn:feature_class":"P",
    "gn:feature_code":"PPL",
    "gn:name":"Oberfehl",
    "gn:population":0,
    "gn:timezone":"Europe/Vienna",
    "iso:country":"AT",
    "wof:name":"Oberfehl",
    "wof:placetype":"locality"
},
  "geometry": {"coordinates":[15.0202,48.24085],"type":"Point"}
}