{
  "type": "Feature",
  "properties": {
    "gn:gn_country":"AT",
    "gn:gn_fcode":"PPL",
    "gn:gn_pop":2100,
    "gn:population":2100,
    "iso:country":"AT",
    "name:bre_x_preferred":[
        "Sankt Georgen am Walde"
    ],
    "name:cat_x_preferred":[
        "Sankt Georgen am Walde"
    ],
    "name:ceb_x_preferred":[
        "Sankt Georgen am Walde"
    ],
    "name:ces_x_preferred":[
        "Sankt Georgen am Walde"
    ],
    "name:deu_x_preferred":[
        "St. Georgen am Walde"
    ],
    "name:eng_x_preferred":[
        "Sankt Georgen am Walde"
    ],
    "name:fas_x_preferred":[
        "\u0632\u0627\u0646\u06a9\u062a \u06af\u0648\u0631\u06af\u0646 \u0627\u0645 \u0648\u0627\u0644\u062f"
    ],
    "name:fra_x_preferred":[
        "Sankt Georgen am Walde"
    ],
    "name:hun_x_preferred":[
        "Sankt Georgen am Walde"
    ],
    "name:ita_x_preferred":[
        "Sankt Georgen am Walde"
    ],
    "name:kaz_x_preferred":[
        "\u0421\u0430\u043d\u043a\u0442-\u0413\u0435\u043e\u0440\u0433\u0435\u043d-\u043d\u0430-\u0412\u0430\u043b\u044c\u0434\u0435"
    ],
    "name:nld_x_preferred":[
        "Sankt Georgen am Walde"
    ],
    "name:pol_x_preferred":[
        "St. Georgen am Walde"
    ],
    "name:por_x_preferred":[
        "Sankt Georgen am Walde"
    ],
    "name:rus_x_preferred":[
        "\u0421\u0430\u043d\u043a\u0442-\u0413\u0435\u043e\u0440\u0433\u0435\u043d-\u043d\u0430-\u0412\u0430\u043b\u044c\u0434\u0435"
    ],
    "name:slk_x_preferred":[
        "Sankt Georgen am Walde"
    ],
    "name:spa_x_preferred":[
        "Sankt Georgen am Walde"
    ],
    "name:sqi_x_preferred":[
        "Sankt Georgen am Walde"
    ],
    "name:swe_x_preferred":[
        "Sankt Georgen am Walde"
    ],
    "name:uzb_x_preferred":[
        "Sankt Georgen am Walde"
    ],
    "name:vie_x_preferred":[
        "Sankt Georgen an der Gusen"
    ],
    "name:vol_x_preferred":[
        "Sankt Georgen am Walde"
    ],
    "name:war_x_preferred":[
        "Sankt Georgen am Walde"
    ],
    "name:zho_x_preferred":[
        "\u6797\u7554\u5723\u683c\u5965\u5c14\u6839"
    ],
    "qs_pg:aaroncc":"AT",
    "qs_pg:gn_country":"AT",
    "qs_pg:gn_fcode":"PPL",
    "qs_pg:gn_pop":2100,
    "qs_pg:name":"Sankt Georgen am Walde",
    "qs_pg:photos_9r":0,
    "qs_pg:photos_sr":0,
    "qs_pg:pop_sr":4,
    "qs_pg:qs_pg_placetype":"locality",
    "wof:name":"Sankt Georgen am Walde",
    "wof:placetype":"locality",
    "wof:population":2100
},
  "geometry": {"coordinates":[14.90235,48.35979],"type":"Point"}
}