{
  "type": "Feature",
  "properties": {
    "gn:admin1_code":"06",
    "gn:admin2_code":"622.0",
    "gn:admin3_code":"62274.0",
    "gn:asciiname":"Unterlimbach",
    "gn:country_code":"AT",
    "gn:dem":336,
    "gn:feature_class":"P",
    "gn:feature_code":"PPL",
    "gn:name":"Unterlimbach",
    "gn:population":249,
    "gn:timezone":"Europe/Vienna",
    "iso:country":"AT",
    "wof:name":"Unterlimbach",
    "wof:placetype":"locality",
    "wof:population":249
},
  "geometry": {"coordinates":[16.06667,47.18333],"type":"Point"}
}