{
  "type": "Feature",
  "properties": {
    "gn:admin1_code":"7.0",
    "gn:admin2_code":"706",
    "gn:asciiname":"Mittelspiss",
    "gn:country_code":"AT",
    "gn:dem":1792,
    "gn:feature_class":"P",
    "gn:feature_code":"PPL",
    "gn:name":"Mittelspiss",
    "gn:population":0,
    "gn:timezone":"Europe/Vienna",
    "iso:country":"AT",
    "name:deu_x_preferred":[
        "Mittelspiss"
    ],
    "wof:name":"Mittelspiss",
    "wof:placetype":"locality"
},
  "geometry": {"coordinates":[10.43333,46.95],"type":"Point"}
}