{
  "type": "Feature",
  "properties": {
    "gn:admin1_code":"4.0",
    "gn:admin2_code":"404",
    "gn:admin3_code":"40442.0",
    "gn:asciiname":"Reuhub",
    "gn:country_code":"AT",
    "gn:dem":413,
    "gn:feature_class":"P",
    "gn:feature_code":"PPL",
    "gn:name":"Reuhub",
    "gn:population":23,
    "gn:timezone":"Europe/Vienna",
    "iso:country":"AT",
    "wof:name":"Reuhub",
    "wof:placetype":"locality",
    "wof:population":23
},
  "geometry": {"coordinates":[12.99309,48.18065],"type":"Point"}
}