{
  "type": "Feature",
  "properties": {
    "gn:admin1_code":"4.0",
    "gn:admin2_code":"417",
    "gn:admin3_code":"41716.0",
    "gn:asciiname":"Winteredt",
    "gn:country_code":"AT",
    "gn:dem":593,
    "gn:feature_class":"P",
    "gn:feature_code":"PPL",
    "gn:name":"Winteredt",
    "gn:population":58,
    "gn:timezone":"Europe/Vienna",
    "iso:country":"AT",
    "wof:name":"Winteredt",
    "wof:placetype":"locality",
    "wof:population":58
},
  "geometry": {"coordinates":[13.52803,48.06426],"type":"Point"}
}