{
  "type": "Feature",
  "properties": {
    "gn:admin1_code":"3.0",
    "gn:admin2_code":"320",
    "gn:admin3_code":"32006.0",
    "gn:asciiname":"Pfoisau",
    "gn:country_code":"AT",
    "gn:dem":326,
    "gn:feature_class":"P",
    "gn:feature_code":"PPL",
    "gn:name":"Pfoisau",
    "gn:population":41,
    "gn:timezone":"Europe/Vienna",
    "iso:country":"AT",
    "wof:name":"Pfoisau",
    "wof:placetype":"locality",
    "wof:population":41
},
  "geometry": {"coordinates":[15.19851,48.03999],"type":"Point"}
}