{
  "type": "Feature",
  "properties": {
    "gn:admin1_code":"04",
    "gn:admin2_code":"416.0",
    "gn:admin3_code":"41602.0",
    "gn:asciiname":"Preising",
    "gn:country_code":"AT",
    "gn:dem":658,
    "gn:feature_class":"P",
    "gn:feature_code":"PPL",
    "gn:name":"Preising",
    "gn:population":62,
    "gn:timezone":"Europe/Vienna",
    "iso:country":"AT",
    "wof:name":"Preising",
    "wof:placetype":"locality",
    "wof:population":62
},
  "geometry": {"coordinates":[14.35767,48.38995],"type":"Point"}
}