{
  "type": "Feature",
  "properties": {
    "gn:admin1_code":"3.0",
    "gn:admin2_code":"319",
    "gn:admin3_code":"31943.0",
    "gn:asciiname":"Gemeinlebarn",
    "gn:country_code":"AT",
    "gn:dem":187,
    "gn:feature_class":"P",
    "gn:feature_code":"PPL",
    "gn:name":"Gemeinlebarn",
    "gn:population":736,
    "gn:timezone":"Europe/Vienna",
    "iso:country":"AT",
    "wof:name":"Gemeinlebarn",
    "wof:placetype":"locality",
    "wof:population":736
},
  "geometry": {"coordinates":[15.80555,48.33605],"type":"Point"}
}