{
  "type": "Feature",
  "properties": {
    "gn:admin1_code":"4.0",
    "gn:admin2_code":"417",
    "gn:admin3_code":"41747.0",
    "gn:asciiname":"Thalberg",
    "gn:country_code":"AT",
    "gn:dem":496,
    "gn:feature_class":"P",
    "gn:feature_code":"PPL",
    "gn:name":"Thalberg",
    "gn:population":0,
    "gn:timezone":"Europe/Vienna",
    "iso:country":"AT",
    "wof:name":"Thalberg",
    "wof:placetype":"locality"
},
  "geometry": {"coordinates":[13.50537,48.00566],"type":"Point"}
}