{
  "type": "Feature",
  "properties": {
    "gn:admin1_code":"2.0",
    "gn:admin2_code":"209",
    "gn:admin3_code":"20905.0",
    "gn:asciiname":"Hinterwoelch",
    "gn:country_code":"AT",
    "gn:dem":820,
    "gn:feature_class":"P",
    "gn:feature_code":"PPL",
    "gn:name":"Hinterw\u00f6lch",
    "gn:population":49,
    "gn:timezone":"Europe/Vienna",
    "iso:country":"AT",
    "wof:name":"Hinterwoelch",
    "wof:placetype":"locality",
    "wof:population":49
},
  "geometry": {"coordinates":[14.85,46.88333],"type":"Point"}
}