{
  "type": "Feature",
  "properties": {
    "gn:admin1_code":"4.0",
    "gn:admin2_code":"416",
    "gn:admin3_code":"41602.0",
    "gn:asciiname":"Stratreith",
    "gn:country_code":"AT",
    "gn:dem":724,
    "gn:feature_class":"P",
    "gn:feature_code":"PPL",
    "gn:name":"Stratreith",
    "gn:population":183,
    "gn:timezone":"Europe/Vienna",
    "iso:country":"AT",
    "wof:name":"Stratreith",
    "wof:placetype":"locality",
    "wof:population":183
},
  "geometry": {"coordinates":[14.31361,48.39111],"type":"Point"}
}