{
  "type": "Feature",
  "properties": {
    "gn:admin1_code":"03",
    "gn:admin2_code":"319.0",
    "gn:admin3_code":"31902.0",
    "gn:asciiname":"Wimmersdorf",
    "gn:country_code":"AT",
    "gn:dem":239,
    "gn:feature_class":"P",
    "gn:feature_code":"PPL",
    "gn:name":"Wimmersdorf",
    "gn:population":147,
    "gn:timezone":"Europe/Vienna",
    "iso:country":"AT",
    "wof:name":"Wimmersdorf",
    "wof:placetype":"locality",
    "wof:population":147
},
  "geometry": {"coordinates":[15.96846,48.23085],"type":"Point"}
}