{
  "type": "Feature",
  "properties": {
    "gn:admin1_code":"4.0",
    "gn:admin2_code":"413",
    "gn:admin3_code":"41304.0",
    "gn:asciiname":"Blumau",
    "gn:country_code":"AT",
    "gn:dem":564,
    "gn:feature_class":"P",
    "gn:feature_code":"PPL",
    "gn:name":"Blumau",
    "gn:population":104,
    "gn:timezone":"Europe/Vienna",
    "iso:country":"AT",
    "wof:name":"Blumau",
    "wof:placetype":"locality",
    "wof:population":104
},
  "geometry": {"coordinates":[13.97023,48.47713],"type":"Point"}
}