{
  "type": "Feature",
  "properties": {
    "gn:admin1_code":"03",
    "gn:admin2_code":"310.0",
    "gn:admin3_code":"31052.0",
    "gn:asciiname":"Watzelsdorf",
    "gn:country_code":"AT",
    "gn:dem":249,
    "gn:feature_class":"P",
    "gn:feature_code":"PPL",
    "gn:name":"Watzelsdorf",
    "gn:population":430,
    "gn:timezone":"Europe/Vienna",
    "iso:country":"AT",
    "wof:name":"Watzelsdorf",
    "wof:placetype":"locality",
    "wof:population":430
},
  "geometry": {"coordinates":[15.98333,48.68333],"type":"Point"}
}