{
  "type": "Feature",
  "properties": {
    "gn:admin1_code":"4.0",
    "gn:admin2_code":"412",
    "gn:admin3_code":"41204.0",
    "gn:asciiname":"Pumberg",
    "gn:country_code":"AT",
    "gn:dem":542,
    "gn:feature_class":"P",
    "gn:feature_code":"PPL",
    "gn:name":"Pumberg",
    "gn:population":92,
    "gn:timezone":"Europe/Vienna",
    "iso:country":"AT",
    "wof:name":"Pumberg",
    "wof:placetype":"locality",
    "wof:population":92
},
  "geometry": {"coordinates":[13.55494,48.1447],"type":"Point"}
}