{
  "type": "Feature",
  "properties": {
    "gn:admin1_code":"4.0",
    "gn:admin2_code":"412",
    "gn:admin3_code":"41233.0",
    "gn:asciiname":"Rabenfurt",
    "gn:country_code":"AT",
    "gn:dem":378,
    "gn:feature_class":"P",
    "gn:feature_code":"PPL",
    "gn:name":"Rabenfurt",
    "gn:population":87,
    "gn:timezone":"Europe/Vienna",
    "iso:country":"AT",
    "wof:name":"Rabenfurt",
    "wof:placetype":"locality",
    "wof:population":87
},
  "geometry": {"coordinates":[13.45156,48.27959],"type":"Point"}
}