{
  "type": "Feature",
  "properties": {
    "gn:admin1_code":"04",
    "gn:admin2_code":"408.0",
    "gn:admin3_code":"40819.0",
    "gn:asciiname":"Teucht",
    "gn:country_code":"AT",
    "gn:dem":434,
    "gn:feature_class":"P",
    "gn:feature_code":"PPL",
    "gn:name":"Teucht",
    "gn:population":0,
    "gn:timezone":"Europe/Vienna",
    "iso:country":"AT",
    "wof:name":"Teucht",
    "wof:placetype":"locality"
},
  "geometry": {"coordinates":[13.76295,48.36948],"type":"Point"}
}