{
  "type": "Feature",
  "properties": {
    "gn:admin1_code":"4.0",
    "gn:admin2_code":"404",
    "gn:admin3_code":"40434.0",
    "gn:asciiname":"Thal",
    "gn:country_code":"AT",
    "gn:dem":461,
    "gn:feature_class":"P",
    "gn:feature_code":"PPL",
    "gn:name":"Thal",
    "gn:population":20,
    "gn:timezone":"Europe/Vienna",
    "iso:country":"AT",
    "wof:name":"Thal",
    "wof:placetype":"locality",
    "wof:population":20
},
  "geometry": {"coordinates":[13.24754,48.19699],"type":"Point"}
}