{
  "type": "Feature",
  "properties": {
    "gn:admin1_code":"6.0",
    "gn:admin2_code":"621",
    "gn:admin3_code":"62144.0",
    "gn:asciiname":"Gschwand",
    "gn:country_code":"AT",
    "gn:dem":1137,
    "gn:feature_class":"P",
    "gn:feature_code":"PPL",
    "gn:name":"Gschwand",
    "gn:population":0,
    "gn:timezone":"Europe/Vienna",
    "iso:country":"AT",
    "wof:name":"Gschwand",
    "wof:placetype":"locality"
},
  "geometry": {"coordinates":[15.43333,47.73333],"type":"Point"}
}