{
  "type": "Feature",
  "properties": {
    "gn:admin1_code":"4.0",
    "gn:admin2_code":"415",
    "gn:admin3_code":"41512.0",
    "gn:asciiname":"Anzenbach",
    "gn:country_code":"AT",
    "gn:dem":502,
    "gn:feature_class":"P",
    "gn:feature_code":"PPL",
    "gn:name":"Anzenbach",
    "gn:population":0,
    "gn:timezone":"Europe/Vienna",
    "iso:country":"AT",
    "wof:name":"Anzenbach",
    "wof:placetype":"locality"
},
  "geometry": {"coordinates":[14.46667,47.85],"type":"Point"}
}