{
  "type": "Feature",
  "properties": {
    "iso:country":"AT",
    "name:cat_x_preferred":[
        "Rohrmoos-Untertal"
    ],
    "name:ceb_x_preferred":[
        "Rohrmoos-Untertal"
    ],
    "name:che_x_preferred":[
        "\u0420\u043e\u0440\u043c\u043e\u0441-\u0423\u043d\u0442\u0435\u0440\u0442\u0430\u043b\u044c"
    ],
    "name:deu_x_preferred":[
        "Rohrmoos-Untertal"
    ],
    "name:eng_x_preferred":[
        "Rohrmoos-Untertal"
    ],
    "name:fra_x_preferred":[
        "Rohrmoos-Untertal"
    ],
    "name:hun_x_preferred":[
        "Rohrmoos-Untertal"
    ],
    "name:ita_x_preferred":[
        "Rohrmoos-Untertal"
    ],
    "name:jpn_x_preferred":[
        "\u30ed\u30fc\u30eb\u30e2\u30fc\u30b9\uff1d\u30a6\u30f3\u30bf\u30fc\u30bf\u30fc\u30eb"
    ],
    "name:kaz_x_preferred":[
        "\u0420\u043e\u0440\u043c\u043e\u0441-\u0423\u043d\u0442\u0435\u0440\u0442\u0430\u043b\u044c"
    ],
    "name:nld_x_preferred":[
        "Rohrmoos-Untertal"
    ],
    "name:nob_x_preferred":[
        "Rohrmoos-Untertal"
    ],
    "name:rus_x_preferred":[
        "\u0420\u043e\u0440\u043c\u043e\u0441-\u0423\u043d\u0442\u0435\u0440\u0442\u0430\u043b\u044c"
    ],
    "name:slk_x_preferred":[
        "Rohrmoos-Untertal"
    ],
    "name:swe_x_preferred":[
        "Rohrmoos-Untertal"
    ],
    "name:tat_x_preferred":[
        "\u0420\u043e\u0440\u043c\u043e\u0441-\u0423\u043d\u0442\u0435\u0440\u0442\u0430\u043b\u044c"
    ],
    "name:uzb_x_preferred":[
        "Rohrmoos-Untertal"
    ],
    "name:war_x_preferred":[
        "Rohrmoos-Untertal"
    ],
    "name:zho_x_preferred":[
        "Rohrmoos-Untertal"
    ],
    "qs_pg:aaroncc":"AT",
    "qs_pg:name":"Rohrmoos-untertal",
    "qs_pg:name_adm0":"\u00d6sterreich",
    "qs_pg:name_adm1":"Steiermark",
    "qs_pg:photos":232,
    "qs_pg:photos_1k":47,
    "qs_pg:photos_9k":1,
    "qs_pg:photos_9r":4,
    "qs_pg:photos_all":232,
    "qs_pg:photos_sr":4,
    "qs_pg:pop_sr":0,
    "qs_pg:qs_pg_placetype":"locality",
    "qs_pg:qs_pg_placetype_gp":"Town",
    "qs_pg:woe_adm0":23424750,
    "woe:adm0_id":23424750,
    "woe:name_adm0":"\u00d6sterreich",
    "woe:name_adm1":"Steiermark",
    "woe:placetype":"Town",
    "wof:name":"Rohrmoos-untertal",
    "wof:placetype":"locality"
},
  "geometry": {"coordinates":[13.672227,47.383648],"type":"Point"}
}