{
  "type": "Feature",
  "properties": {
    "gn:admin1_code":"4.0",
    "gn:admin2_code":"413",
    "gn:admin3_code":"41333.0",
    "gn:asciiname":"Guenterreith",
    "gn:country_code":"AT",
    "gn:dem":647,
    "gn:feature_class":"P",
    "gn:feature_code":"PPL",
    "gn:name":"G\u00fcnterreith",
    "gn:population":42,
    "gn:timezone":"Europe/Vienna",
    "iso:country":"AT",
    "wof:name":"Guenterreith",
    "wof:placetype":"locality",
    "wof:population":42
},
  "geometry": {"coordinates":[14.01529,48.62956],"type":"Point"}
}