{
  "type": "Feature",
  "properties": {
    "gn:admin1_code":"4.0",
    "gn:admin2_code":"412",
    "gn:admin3_code":"41222.0",
    "gn:asciiname":"Osternach",
    "gn:country_code":"AT",
    "gn:dem":442,
    "gn:feature_class":"P",
    "gn:feature_code":"PPL",
    "gn:name":"Osternach",
    "gn:population":52,
    "gn:timezone":"Europe/Vienna",
    "iso:country":"AT",
    "wof:name":"Osternach",
    "wof:placetype":"locality",
    "wof:population":52
},
  "geometry": {"coordinates":[13.53099,48.23814],"type":"Point"}
}