{
  "type": "Feature",
  "properties": {
    "gn:admin1_code":"06",
    "gn:admin2_code":"616.0",
    "gn:admin3_code":"61612.0",
    "gn:asciiname":"Oberwald",
    "gn:country_code":"AT",
    "gn:dem":947,
    "gn:feature_class":"P",
    "gn:feature_code":"PPL",
    "gn:name":"Oberwald",
    "gn:population":261,
    "gn:timezone":"Europe/Vienna",
    "iso:country":"AT",
    "name:ceb_x_preferred":[
        "Oberwald"
    ],
    "name:deu_x_preferred":[
        "Oberwald"
    ],
    "name:fra_x_preferred":[
        "Oberwald"
    ],
    "name:ita_x_preferred":[
        "Oberwald"
    ],
    "name:nld_x_preferred":[
        "Oberwald"
    ],
    "name:pms_x_preferred":[
        "Oberwald"
    ],
    "name:pnb_x_preferred":[
        "\u0627\u0648\u0628\u0631\u0648\u0627\u0644\u0688"
    ],
    "name:por_x_preferred":[
        "Oberwald"
    ],
    "name:roh_x_preferred":[
        "Oberwald"
    ],
    "name:ron_x_preferred":[
        "Oberwald"
    ],
    "name:spa_x_preferred":[
        "Oberwald"
    ],
    "name:swe_x_preferred":[
        "Oberwald"
    ],
    "name:vol_x_preferred":[
        "Oberwald"
    ],
    "wof:name":"Oberwald",
    "wof:placetype":"locality",
    "wof:population":261
},
  "geometry": {"coordinates":[15.15,46.96667],"type":"Point"}
}