{
  "type": "Feature",
  "properties": {
    "gn:admin1_code":"06",
    "gn:admin2_code":"616.0",
    "gn:admin3_code":"61612.0",
    "gn:asciiname":"Oberwald",
    "gn:country_code":"AT",
    "gn:dem":947,
    "gn:feature_class":"P",
    "gn:feature_code":"PPL",
    "gn:name":"Oberwald",
    "gn:population":261,
    "gn:timezone":"Europe/Vienna",
    "iso:country":"AT",
    "wof:name":"Oberwald",
    "wof:placetype":"locality",
    "wof:population":261
},
  "geometry": {"coordinates":[15.15,46.96667],"type":"Point"}
}