{
  "type": "Feature",
  "properties": {
    "iso:country":"AT",
    "name:ceb_x_preferred":[
        "Bad Bleiberg"
    ],
    "name:dan_x_preferred":[
        "Bad Bleiberg"
    ],
    "name:deu_x_preferred":[
        "Bad Bleiberg"
    ],
    "name:eng_x_preferred":[
        "Bad Bleiberg"
    ],
    "name:epo_x_preferred":[
        "Bad Bleiberg"
    ],
    "name:fas_x_preferred":[
        "\u0628\u062f \u0628\u0644\u0627\u06cc\u0628\u0631\u06af"
    ],
    "name:fra_x_preferred":[
        "Bad Bleiberg"
    ],
    "name:fur_x_preferred":[
        "Bad Bleiberg"
    ],
    "name:heb_x_preferred":[
        "\u05d1\u05d0\u05d3 \u05d1\u05dc\u05d9\u05d9\u05d1\u05e8\u05d2"
    ],
    "name:hun_x_preferred":[
        "Bad Bleiberg"
    ],
    "name:ita_x_preferred":[
        "Bad Bleiberg"
    ],
    "name:kaz_x_preferred":[
        "\u0411\u0430\u0434-\u0411\u043b\u0430\u0439\u0431\u0435\u0440\u0433"
    ],
    "name:lit_x_preferred":[
        "Bad Bleibergas"
    ],
    "name:nld_x_preferred":[
        "Bad Bleiberg"
    ],
    "name:pol_x_preferred":[
        "Bad Bleiberg"
    ],
    "name:por_x_preferred":[
        "Bad Bleiberg"
    ],
    "name:rus_x_preferred":[
        "\u0411\u0430\u0434-\u0411\u043b\u0430\u0439\u0431\u0435\u0440\u0433"
    ],
    "name:slk_x_preferred":[
        "Bad Bleiberg"
    ],
    "name:slv_x_preferred":[
        "Bad Bleiberg"
    ],
    "name:spa_x_preferred":[
        "Bad Bleiberg"
    ],
    "name:swe_x_preferred":[
        "Bad Bleiberg"
    ],
    "name:ukr_x_preferred":[
        "\u0411\u0430\u0434-\u0411\u043b\u044f\u0439\u0431\u0435\u0440\u0491"
    ],
    "name:ukr_x_variant":[
        "\u0411\u0430\u0434-\u0411\u043b\u0430\u0439\u0431\u0435\u0440\u0433"
    ],
    "name:uzb_x_preferred":[
        "Bad Bleiberg"
    ],
    "name:vol_x_preferred":[
        "Bad Bleiberg"
    ],
    "name:war_x_preferred":[
        "Bad Bleiberg"
    ],
    "name:zho_x_preferred":[
        "\u5df4\u7279\u5e03\u83b1\u8d1d\u683c"
    ],
    "qs_pg:aaroncc":"AT",
    "qs_pg:name":"Bad Bleiberg",
    "qs_pg:name_adm0":"\u00d6sterreich",
    "qs_pg:name_adm1":"K\u00e4rnten",
    "qs_pg:photos":71,
    "qs_pg:photos_1k":14,
    "qs_pg:photos_9k":1,
    "qs_pg:photos_9r":2,
    "qs_pg:photos_all":71,
    "qs_pg:photos_sr":2,
    "qs_pg:pop_sr":0,
    "qs_pg:qs_pg_placetype":"locality",
    "qs_pg:qs_pg_placetype_gp":"Town",
    "qs_pg:woe_adm0":23424750,
    "woe:adm0_id":23424750,
    "woe:name_adm0":"\u00d6sterreich",
    "woe:name_adm1":"K\u00e4rnten",
    "woe:placetype":"Town",
    "wof:name":"Bad Bleiberg",
    "wof:placetype":"locality"
},
  "geometry": {"coordinates":[13.679652,46.624595],"type":"Point"}
}