{
  "type": "Feature",
  "properties": {
    "iso:country":"AT",
    "name:deu_x_preferred":[
        "Goigner"
    ],
    "name:eng_x_preferred":[
        "Goigner"
    ],
    "wof:name":"Goigner",
    "wof:placetype":"neighbourhood"
},
  "geometry": {"coordinates":[15.47927187550079,47.08422356463218],"type":"Point"}
}