{
  "type": "Feature",
  "properties": {
    "gn:admin1_code":"2.0",
    "gn:admin2_code":"206",
    "gn:admin3_code":"20605.0",
    "gn:asciiname":"Mitten",
    "gn:country_code":"AT",
    "gn:dem":1448,
    "gn:feature_class":"P",
    "gn:feature_code":"PPL",
    "gn:name":"Mitten",
    "gn:population":148,
    "gn:timezone":"Europe/Vienna",
    "iso:country":"AT",
    "wof:name":"Mitten",
    "wof:placetype":"locality",
    "wof:population":148
},
  "geometry": {"coordinates":[12.895,46.99167],"type":"Point"}
}