{
  "type": "Feature",
  "properties": {
    "gn:admin1_code":"3.0",
    "gn:admin2_code":"321",
    "gn:admin3_code":"32119.0",
    "gn:asciiname":"Kronau",
    "gn:country_code":"AT",
    "gn:dem":173,
    "gn:feature_class":"P",
    "gn:feature_code":"PPL",
    "gn:name":"Kronau",
    "gn:population":73,
    "gn:timezone":"Europe/Vienna",
    "iso:country":"AT",
    "wof:name":"Kronau",
    "wof:placetype":"locality",
    "wof:population":73
},
  "geometry": {"coordinates":[16.00485,48.32601],"type":"Point"}
}