{
  "type": "Feature",
  "properties": {
    "gn:admin1_code":"02",
    "gn:admin2_code":"207.0",
    "gn:admin3_code":"20724.0",
    "gn:asciiname":"Vordersauerwald",
    "gn:country_code":"AT",
    "gn:dem":1069,
    "gn:feature_class":"P",
    "gn:feature_code":"PPL",
    "gn:name":"Vordersauerwald",
    "gn:population":0,
    "gn:timezone":"Europe/Vienna",
    "iso:country":"AT",
    "wof:name":"Vordersauerwald",
    "wof:placetype":"locality"
},
  "geometry": {"coordinates":[13.85,46.71667],"type":"Point"}
}