{
  "type": "Feature",
  "properties": {
    "gn:admin1_code":"2.0",
    "gn:admin2_code":"207",
    "gn:admin3_code":"20727.0",
    "gn:asciiname":"Gottestal",
    "gn:cc2":"AT",
    "gn:country_code":"AT",
    "gn:dem":530,
    "gn:feature_class":"P",
    "gn:feature_code":"PPL",
    "gn:name":"Gottestal",
    "gn:population":178,
    "gn:timezone":"Europe/Vienna",
    "iso:country":"AT",
    "name:und_x_variant":[
        "Gottesthal",
        "Gottestal"
    ],
    "wof:name":"Gottestal",
    "wof:placetype":"locality",
    "wof:population":178
},
  "geometry": {"coordinates":[13.93333,46.61667],"type":"Point"}
}