{
  "type": "Feature",
  "properties": {
    "gn:admin1_code":"4.0",
    "gn:admin2_code":"411",
    "gn:admin3_code":"41125.0",
    "gn:asciiname":"Ettenberg",
    "gn:country_code":"AT",
    "gn:dem":546,
    "gn:feature_class":"P",
    "gn:feature_code":"PPL",
    "gn:name":"Ettenberg",
    "gn:population":404,
    "gn:timezone":"Europe/Vienna",
    "iso:country":"AT",
    "wof:name":"Ettenberg",
    "wof:placetype":"locality",
    "wof:population":404
},
  "geometry": {"coordinates":[14.93866,48.29039],"type":"Point"}
}