{
  "type": "Feature",
  "properties": {
    "gn:admin1_code":"2.0",
    "gn:admin2_code":"209",
    "gn:admin3_code":"20909.0",
    "gn:asciiname":"Magdalensberg",
    "gn:country_code":"AT",
    "gn:dem":517,
    "gn:feature_class":"P",
    "gn:feature_code":"PPL",
    "gn:name":"Magdalensberg",
    "gn:population":450,
    "gn:timezone":"Europe/Vienna",
    "iso:country":"AT",
    "name:ceb_x_preferred":[
        "Magdalensberg"
    ],
    "name:deu_x_preferred":[
        "Magdalensberg"
    ],
    "name:epo_x_preferred":[
        "Magdalensberg"
    ],
    "name:fas_x_preferred":[
        "\u0645\u0627\u06af\u062f\u0627\u0644\u0646\u0633\u0628\u0631\u06af"
    ],
    "name:fra_x_preferred":[
        "Magdalensberg"
    ],
    "name:fur_x_preferred":[
        "Magdalensberg"
    ],
    "name:hun_x_preferred":[
        "Magdalensberg"
    ],
    "name:ita_x_preferred":[
        "Magdalensberg"
    ],
    "name:kaz_x_preferred":[
        "\u041c\u0430\u0433\u0434\u0430\u043b\u0435\u043d\u0441\u0431\u0435\u0440\u0433"
    ],
    "name:nld_x_preferred":[
        "Magdalensberg"
    ],
    "name:nor_x_preferred":[
        "Magdalensberg"
    ],
    "name:pol_x_preferred":[
        "Magdalensberg"
    ],
    "name:por_x_preferred":[
        "Magdalensberg"
    ],
    "name:rus_x_preferred":[
        "\u041c\u0430\u0433\u0434\u0430\u043b\u0435\u043d\u0441\u0431\u0435\u0440\u0433"
    ],
    "name:slk_x_preferred":[
        "Magdalensberg"
    ],
    "name:slv_x_preferred":[
        "\u0160talenska gora"
    ],
    "name:spa_x_preferred":[
        "Magdalensberg"
    ],
    "name:swe_x_preferred":[
        "Magdalensberg"
    ],
    "name:uzb_x_preferred":[
        "Magdalensberg"
    ],
    "name:vie_x_preferred":[
        "Magdalensberg"
    ],
    "name:vol_x_preferred":[
        "Magdalensberg"
    ],
    "name:war_x_preferred":[
        "Magdalensberg"
    ],
    "name:zho_x_preferred":[
        "\u9a6c\u683c\u8fbe\u4f26\u65af\u8d1d\u683c"
    ],
    "wof:name":"Magdalensberg",
    "wof:placetype":"locality",
    "wof:population":450
},
  "geometry": {"coordinates":[14.96667,46.65],"type":"Point"}
}