{
  "type": "Feature",
  "properties": {
    "gn:admin1_code":"2.0",
    "gn:admin2_code":"209",
    "gn:admin3_code":"20909.0",
    "gn:asciiname":"Magdalensberg",
    "gn:country_code":"AT",
    "gn:dem":517,
    "gn:feature_class":"P",
    "gn:feature_code":"PPL",
    "gn:name":"Magdalensberg",
    "gn:population":450,
    "gn:timezone":"Europe/Vienna",
    "iso:country":"AT",
    "wof:name":"Magdalensberg",
    "wof:placetype":"locality",
    "wof:population":450
},
  "geometry": {"coordinates":[14.96667,46.65],"type":"Point"}
}