{
  "type": "Feature",
  "properties": {
    "gn:admin1_code":"2.0",
    "gn:admin2_code":"205",
    "gn:admin3_code":"20511.0",
    "gn:asciiname":"Unterwald",
    "gn:country_code":"AT",
    "gn:dem":1044,
    "gn:feature_class":"P",
    "gn:feature_code":"PPL",
    "gn:name":"Unterwald",
    "gn:population":59,
    "gn:timezone":"Europe/Vienna",
    "iso:country":"AT",
    "wof:name":"Unterwald",
    "wof:placetype":"locality",
    "wof:population":59
},
  "geometry": {"coordinates":[14.52861,46.97083],"type":"Point"}
}