{
  "type": "Feature",
  "properties": {
    "gn:admin1_code":"4.0",
    "gn:admin2_code":"404",
    "gn:admin3_code":"40418.0",
    "gn:asciiname":"Friedburg",
    "gn:cc2":"AT",
    "gn:country_code":"AT",
    "gn:dem":511,
    "gn:feature_class":"P",
    "gn:feature_code":"PPL",
    "gn:name":"Friedburg",
    "gn:population":714,
    "gn:timezone":"Europe/Vienna",
    "iso:country":"AT",
    "name:und_x_variant":[
        "Friburg",
        "Friedburg"
    ],
    "wof:name":"Friedburg",
    "wof:placetype":"locality",
    "wof:population":714
},
  "geometry": {"coordinates":[13.25,48.01667],"type":"Point"}
}