{
  "type": "Feature",
  "properties": {
    "gn:admin1_code":"1.0",
    "gn:admin2_code":"109",
    "gn:admin3_code":"10905.0",
    "gn:asciiname":"Kleinpetersdorf",
    "gn:country_code":"AT",
    "gn:dem":282,
    "gn:feature_class":"P",
    "gn:feature_code":"PPL",
    "gn:name":"Kleinpetersdorf",
    "gn:population":271,
    "gn:timezone":"Europe/Vienna",
    "iso:country":"AT",
    "wof:name":"Kleinpetersdorf",
    "wof:placetype":"locality",
    "wof:population":271
},
  "geometry": {"coordinates":[16.33333,47.21667],"type":"Point"}
}