{
  "type": "Feature",
  "properties": {
    "gn:admin1_code":"04",
    "gn:admin2_code":"412.0",
    "gn:admin3_code":"41227.0",
    "gn:asciiname":"Sankt Marienkirchen am Hausruck",
    "gn:cc2":"AT",
    "gn:country_code":"AT",
    "gn:dem":518,
    "gn:feature_class":"P",
    "gn:feature_code":"PPL",
    "gn:name":"Sankt Marienkirchen am Hausruck",
    "gn:population":292,
    "gn:timezone":"Europe/Vienna",
    "iso:country":"AT",
    "name:und_x_variant":[
        "Sankt Marienkirchen",
        "Sankt Marienkirchen am Hausruck"
    ],
    "wof:name":"Sankt Marienkirchen am Hausruck",
    "wof:placetype":"locality",
    "wof:population":292
},
  "geometry": {"coordinates":[13.57704,48.1828],"type":"Point"}
}