{
  "type": "Feature",
  "properties": {
    "gn:admin1_code":"2.0",
    "gn:admin2_code":"210",
    "gn:admin3_code":"21009.0",
    "gn:asciiname":"Langacker",
    "gn:country_code":"AT",
    "gn:dem":639,
    "gn:feature_class":"P",
    "gn:feature_code":"PPL",
    "gn:name":"Langacker",
    "gn:population":30,
    "gn:timezone":"Europe/Vienna",
    "iso:country":"AT",
    "wof:name":"Langacker",
    "wof:placetype":"locality",
    "wof:population":30
},
  "geometry": {"coordinates":[14.04735,46.71839],"type":"Point"}
}