{
  "type": "Feature",
  "properties": {
    "gn:admin1_code":"5.0",
    "gn:admin2_code":"505",
    "gn:admin3_code":"50503.0",
    "gn:asciiname":"Althofen",
    "gn:country_code":"AT",
    "gn:dem":1076,
    "gn:feature_class":"P",
    "gn:feature_code":"PPL",
    "gn:name":"Althofen",
    "gn:population":0,
    "gn:timezone":"Europe/Vienna",
    "iso:country":"AT",
    "name:bul_x_preferred":[
        "\u0410\u043b\u0442\u0445\u043e\u0444\u0435\u043d"
    ],
    "name:ceb_x_preferred":[
        "Althofen"
    ],
    "name:ces_x_preferred":[
        "Althofen"
    ],
    "name:deu_x_preferred":[
        "Althofen"
    ],
    "name:epo_x_preferred":[
        "Althofen"
    ],
    "name:fas_x_preferred":[
        "\u0627\u0644\u062a\u0627\u0641\u0646"
    ],
    "name:fra_x_preferred":[
        "Althofen"
    ],
    "name:hun_x_preferred":[
        "Althofen"
    ],
    "name:ind_x_preferred":[
        "Althofen"
    ],
    "name:ita_x_preferred":[
        "Althofen"
    ],
    "name:kaz_x_preferred":[
        "\u0410\u043b\u044c\u0442\u0445\u043e\u0444\u0435\u043d"
    ],
    "name:nld_x_preferred":[
        "Althofen"
    ],
    "name:pol_x_preferred":[
        "Althofen"
    ],
    "name:por_x_preferred":[
        "Althofen"
    ],
    "name:rus_x_preferred":[
        "\u0410\u043b\u044c\u0442\u0445\u043e\u0444\u0435\u043d"
    ],
    "name:slk_x_preferred":[
        "Althofen"
    ],
    "name:spa_x_preferred":[
        "Althofen"
    ],
    "name:swe_x_preferred":[
        "Althofen"
    ],
    "name:ukr_x_preferred":[
        "\u0410\u043b\u044c\u0442\u0433\u043e\u0444\u0435\u043d"
    ],
    "name:uzb_x_preferred":[
        "Althofen"
    ],
    "name:vie_x_preferred":[
        "Althofen"
    ],
    "name:vol_x_preferred":[
        "Althofen"
    ],
    "name:war_x_preferred":[
        "Althofen"
    ],
    "name:zho_x_preferred":[
        "\u963f\u5c14\u7279\u970d\u82ac"
    ],
    "wof:name":"Althofen",
    "wof:placetype":"locality"
},
  "geometry": {"coordinates":[13.73333,47.15],"type":"Point"}
}