{
  "type": "Feature",
  "properties": {
    "gn:admin1_code":"5.0",
    "gn:admin2_code":"505",
    "gn:admin3_code":"50503.0",
    "gn:asciiname":"Althofen",
    "gn:country_code":"AT",
    "gn:dem":1076,
    "gn:feature_class":"P",
    "gn:feature_code":"PPL",
    "gn:name":"Althofen",
    "gn:population":0,
    "gn:timezone":"Europe/Vienna",
    "iso:country":"AT",
    "wof:name":"Althofen",
    "wof:placetype":"locality"
},
  "geometry": {"coordinates":[13.73333,47.15],"type":"Point"}
}