{
  "type": "Feature",
  "properties": {
    "gn:admin1_code":"04",
    "gn:admin2_code":"408.0",
    "gn:admin3_code":"40809.0",
    "gn:asciiname":"Reischau",
    "gn:country_code":"AT",
    "gn:dem":487,
    "gn:feature_class":"P",
    "gn:feature_code":"PPL",
    "gn:name":"Reischau",
    "gn:population":12,
    "gn:timezone":"Europe/Vienna",
    "iso:country":"AT",
    "wof:name":"Reischau",
    "wof:placetype":"locality",
    "wof:population":12
},
  "geometry": {"coordinates":[13.63489,48.19836],"type":"Point"}
}