{
  "type": "Feature",
  "properties": {
    "gn:admin1_code":"7.0",
    "gn:admin2_code":"707",
    "gn:admin3_code":"70704.0",
    "gn:asciiname":"Kobreil",
    "gn:country_code":"AT",
    "gn:dem":1526,
    "gn:feature_class":"P",
    "gn:feature_code":"PPL",
    "gn:name":"Kobreil",
    "gn:population":6,
    "gn:timezone":"Europe/Vienna",
    "iso:country":"AT",
    "wof:name":"Kobreil",
    "wof:placetype":"locality",
    "wof:population":6
},
  "geometry": {"coordinates":[12.56845,46.77981],"type":"Point"}
}