{
  "type": "Feature",
  "properties": {
    "gn:admin1_code":"02",
    "gn:admin2_code":"207.0",
    "gn:admin3_code":"20711.0",
    "gn:asciiname":"Sigmontitsch",
    "gn:country_code":"AT",
    "gn:dem":531,
    "gn:feature_class":"P",
    "gn:feature_code":"PPL",
    "gn:name":"Sigmontitsch",
    "gn:population":76,
    "gn:timezone":"Europe/Vienna",
    "iso:country":"AT",
    "wof:name":"Sigmontitsch",
    "wof:placetype":"locality",
    "wof:population":76
},
  "geometry": {"coordinates":[13.81702,46.55579],"type":"Point"}
}