{
  "type": "Feature",
  "properties": {
    "gn:admin1_code":"05",
    "gn:admin2_code":"503.0",
    "gn:admin3_code":"50304.0",
    "gn:asciiname":"Reit",
    "gn:country_code":"AT",
    "gn:dem":590,
    "gn:feature_class":"P",
    "gn:feature_code":"PPL",
    "gn:name":"Reit",
    "gn:population":0,
    "gn:timezone":"Europe/Vienna",
    "iso:country":"AT",
    "wof:name":"Reit",
    "wof:placetype":"locality"
},
  "geometry": {"coordinates":[13.05,47.98333],"type":"Point"}
}