{
  "type": "Feature",
  "properties": {
    "gn:admin1_code":"4.0",
    "gn:admin2_code":"417",
    "gn:admin3_code":"41747.0",
    "gn:asciiname":"Muehlreith",
    "gn:country_code":"AT",
    "gn:dem":582,
    "gn:feature_class":"P",
    "gn:feature_code":"PPL",
    "gn:name":"M\u00fchlreith",
    "gn:population":80,
    "gn:timezone":"Europe/Vienna",
    "iso:country":"AT",
    "wof:name":"Muehlreith",
    "wof:placetype":"locality",
    "wof:population":80
},
  "geometry": {"coordinates":[13.4622,47.9655],"type":"Point"}
}