{
  "type": "Feature",
  "properties": {
    "gn:admin1_code":"3.0",
    "gn:admin2_code":"319",
    "gn:admin3_code":"31930.0",
    "gn:asciiname":"Neustift",
    "gn:country_code":"AT",
    "gn:dem":365,
    "gn:feature_class":"P",
    "gn:feature_code":"PPL",
    "gn:name":"Neustift",
    "gn:population":101,
    "gn:timezone":"Europe/Vienna",
    "iso:country":"AT",
    "name:ceb_x_preferred":[
        "Neustift"
    ],
    "name:deu_x_preferred":[
        "Neustift"
    ],
    "name:ita_x_preferred":[
        "Neustift"
    ],
    "name:nld_x_preferred":[
        "Neustift"
    ],
    "name:pol_x_preferred":[
        "Neustift"
    ],
    "name:swe_x_preferred":[
        "Neustift"
    ],
    "wof:name":"Neustift",
    "wof:placetype":"locality",
    "wof:population":101
},
  "geometry": {"coordinates":[15.55158,48.27896],"type":"Point"}
}