{
  "type": "Feature",
  "properties": {
    "gn:admin1_code":"4.0",
    "gn:admin2_code":"411",
    "gn:admin3_code":"41116.0",
    "gn:asciiname":"Aisthofen",
    "gn:country_code":"AT",
    "gn:dem":255,
    "gn:feature_class":"P",
    "gn:feature_code":"PPL",
    "gn:name":"Aisthofen",
    "gn:population":245,
    "gn:timezone":"Europe/Vienna",
    "iso:country":"AT",
    "wof:name":"Aisthofen",
    "wof:placetype":"locality",
    "wof:population":245
},
  "geometry": {"coordinates":[14.59225,48.25846],"type":"Point"}
}