{
  "type": "Feature",
  "properties": {
    "gn:admin1_code":"07",
    "gn:admin2_code":"708.0",
    "gn:admin3_code":"70817.0",
    "gn:asciiname":"Oberwinkel",
    "gn:country_code":"AT",
    "gn:dem":1232,
    "gn:feature_class":"P",
    "gn:feature_code":"PPL",
    "gn:name":"Oberwinkel",
    "gn:population":0,
    "gn:timezone":"Europe/Vienna",
    "iso:country":"AT",
    "wof:name":"Oberwinkel",
    "wof:placetype":"locality"
},
  "geometry": {"coordinates":[10.35,47.26667],"type":"Point"}
}