{
  "type": "Feature",
  "properties": {
    "gn:admin1_code":"02",
    "gn:admin2_code":"207.0",
    "gn:admin3_code":"20711.0",
    "gn:asciiname":"Untergreuth",
    "gn:country_code":"AT",
    "gn:dem":746,
    "gn:feature_class":"P",
    "gn:feature_code":"PPL",
    "gn:name":"Untergreuth",
    "gn:population":60,
    "gn:timezone":"Europe/Vienna",
    "iso:country":"AT",
    "wof:name":"Untergreuth",
    "wof:placetype":"locality",
    "wof:population":60
},
  "geometry": {"coordinates":[13.93333,46.55],"type":"Point"}
}