{
  "type": "Feature",
  "properties": {
    "gn:admin1_code":"8.0",
    "gn:admin2_code":"802",
    "gn:admin3_code":"80206.0",
    "gn:asciiname":"Mellenstockvorsaess",
    "gn:country_code":"AT",
    "gn:dem":974,
    "gn:feature_class":"P",
    "gn:feature_code":"PPLF",
    "gn:name":"Mellenstockvors\u00e4\u00df",
    "gn:population":0,
    "gn:timezone":"Europe/Vienna",
    "iso:country":"AT",
    "wof:name":"Mellenstockvorsaess",
    "wof:placetype":"locality"
},
  "geometry": {"coordinates":[9.96898,47.36925],"type":"Point"}
}