{
  "type": "Feature",
  "properties": {
    "gn:admin1_code":"1.0",
    "gn:admin2_code":"109",
    "gn:admin3_code":"10902.0",
    "gn:asciiname":"Dreihuetten",
    "gn:country_code":"AT",
    "gn:dem":656,
    "gn:feature_class":"P",
    "gn:feature_code":"PPL",
    "gn:name":"Dreih\u00fctten",
    "gn:population":116,
    "gn:timezone":"Europe/Vienna",
    "iso:country":"AT",
    "name:hun_x_preferred":[
        "H\u00e1roms\u00e1tor"
    ],
    "wof:name":"Dreihuetten",
    "wof:placetype":"locality",
    "wof:population":116
},
  "geometry": {"coordinates":[16.21994,47.42074],"type":"Point"}
}