{
  "type": "Feature",
  "properties": {
    "gn:admin1_code":"3.0",
    "gn:admin2_code":"320",
    "gn:admin3_code":"32018.0",
    "gn:asciiname":"Hofa",
    "gn:country_code":"AT",
    "gn:dem":291,
    "gn:feature_class":"P",
    "gn:feature_code":"PPLL",
    "gn:name":"Hofa",
    "gn:population":24,
    "gn:timezone":"Europe/Vienna",
    "iso:country":"AT",
    "wof:name":"Hofa",
    "wof:placetype":"locality",
    "wof:population":24
},
  "geometry": {"coordinates":[15.05925,48.11121],"type":"Point"}
}