{
  "type": "Feature",
  "properties": {
    "gn:admin1_code":"06",
    "gn:admin2_code":"614.0",
    "gn:admin3_code":"61446.0",
    "gn:asciiname":"Unterdorf",
    "gn:country_code":"AT",
    "gn:dem":755,
    "gn:feature_class":"P",
    "gn:feature_code":"PPL",
    "gn:name":"Unterdorf",
    "gn:population":0,
    "gn:timezone":"Europe/Vienna",
    "iso:country":"AT",
    "wof:name":"Unterdorf",
    "wof:placetype":"locality"
},
  "geometry": {"coordinates":[14.31667,47.13333],"type":"Point"}
}