{
  "type": "Feature",
  "properties": {
    "gn:admin1_code":"3.0",
    "gn:admin2_code":"320",
    "gn:admin3_code":"32015.0",
    "gn:asciiname":"Reidlingdorf",
    "gn:country_code":"AT",
    "gn:dem":574,
    "gn:feature_class":"P",
    "gn:feature_code":"PPLL",
    "gn:name":"Reidlingdorf",
    "gn:population":34,
    "gn:timezone":"Europe/Vienna",
    "iso:country":"AT",
    "wof:name":"Reidlingdorf",
    "wof:placetype":"locality",
    "wof:population":34
},
  "geometry": {"coordinates":[15.00003,48.04435],"type":"Point"}
}