{
  "type": "Feature",
  "properties": {
    "gn:admin1_code":"2.0",
    "gn:admin2_code":"205",
    "gn:admin3_code":"20505.0",
    "gn:asciiname":"Schratzbach",
    "gn:country_code":"AT",
    "gn:dem":980,
    "gn:feature_class":"P",
    "gn:feature_code":"PPLL",
    "gn:name":"Schratzbach",
    "gn:population":28,
    "gn:timezone":"Europe/Vienna",
    "iso:country":"AT",
    "wof:name":"Schratzbach",
    "wof:placetype":"locality",
    "wof:population":28
},
  "geometry": {"coordinates":[14.3725,46.99917],"type":"Point"}
}