{
  "type": "Feature",
  "properties": {
    "gn:admin1_code":"4.0",
    "gn:admin2_code":"404",
    "gn:admin3_code":"40427.0",
    "gn:asciiname":"Haeusl",
    "gn:country_code":"AT",
    "gn:dem":407,
    "gn:feature_class":"P",
    "gn:feature_code":"PPL",
    "gn:name":"H\u00e4usl",
    "gn:population":15,
    "gn:timezone":"Europe/Vienna",
    "iso:country":"AT",
    "wof:name":"Haeusl",
    "wof:placetype":"locality",
    "wof:population":15
},
  "geometry": {"coordinates":[13.02532,48.19313],"type":"Point"}
}