{
  "type": "Feature",
  "properties": {
    "gn:admin1_code":"06",
    "gn:admin2_code":"623.0",
    "gn:admin3_code":"62380.0",
    "gn:asciiname":"Woerth",
    "gn:country_code":"AT",
    "gn:dem":309,
    "gn:feature_class":"P",
    "gn:feature_code":"PPL",
    "gn:name":"W\u00f6rth",
    "gn:population":255,
    "gn:timezone":"Europe/Vienna",
    "iso:country":"AT",
    "wof:name":"Woerth",
    "wof:placetype":"locality",
    "wof:population":255
},
  "geometry": {"coordinates":[15.76583,46.90417],"type":"Point"}
}