{
  "type": "Feature",
  "properties": {
    "gn:admin1_code":"6.0",
    "gn:admin2_code":"610",
    "gn:admin3_code":"61052.0",
    "gn:asciiname":"Baerndorf",
    "gn:country_code":"AT",
    "gn:dem":418,
    "gn:feature_class":"P",
    "gn:feature_code":"PPL",
    "gn:name":"B\u00e4rndorf",
    "gn:population":0,
    "gn:timezone":"Europe/Vienna",
    "iso:country":"AT",
    "name:und_x_variant":[
        "B\u00e4rnsdorf",
        "B\u00e4rndorf"
    ],
    "wof:name":"Baerndorf",
    "wof:placetype":"locality"
},
  "geometry": {"coordinates":[15.56667,46.95],"type":"Point"}
}