{
  "type": "Feature",
  "properties": {
    "gn:admin1_code":"04",
    "gn:asciiname":"Sankt Florian",
    "gn:country_code":"AT",
    "gn:dem":410,
    "gn:feature_class":"P",
    "gn:feature_code":"PPL",
    "gn:name":"Sankt Florian",
    "gn:population":157,
    "gn:timezone":"Europe/Vienna",
    "iso:country":"AT",
    "name:ceb_x_preferred":[
        "Sankt Florian"
    ],
    "name:ces_x_preferred":[
        "Sankt Florian"
    ],
    "name:deu_x_preferred":[
        "St. Florian"
    ],
    "name:epo_x_preferred":[
        "St. Florian"
    ],
    "name:fas_x_preferred":[
        "\u0632\u0627\u0646\u06a9\u062a \u0641\u0644\u0648\u0631\u06cc\u0627\u0646"
    ],
    "name:fra_x_preferred":[
        "Sankt Florian"
    ],
    "name:hun_x_preferred":[
        "Sankt Florian"
    ],
    "name:ita_x_preferred":[
        "Sankt Florian"
    ],
    "name:kaz_x_preferred":[
        "\u0421\u0430\u043d\u043a\u0442-\u0424\u043b\u043e\u0440\u0438\u0430\u043d"
    ],
    "name:nld_x_preferred":[
        "Sankt Florian"
    ],
    "name:pol_x_preferred":[
        "St. Florian"
    ],
    "name:por_x_preferred":[
        "Sankt Florian"
    ],
    "name:ron_x_preferred":[
        "Sankt Florian"
    ],
    "name:rus_x_preferred":[
        "\u0421\u0430\u043d\u043a\u0442-\u0424\u043b\u043e\u0440\u0438\u0430\u043d"
    ],
    "name:slk_x_preferred":[
        "Sankt Florian"
    ],
    "name:spa_x_preferred":[
        "St. Florian"
    ],
    "name:swe_x_preferred":[
        "Sankt Florian"
    ],
    "name:uzb_x_preferred":[
        "Sankt Florian"
    ],
    "name:vie_x_preferred":[
        "Sankt Florian"
    ],
    "name:vol_x_preferred":[
        "Sankt Florian"
    ],
    "name:war_x_preferred":[
        "Sankt Florian"
    ],
    "name:zho_x_preferred":[
        "\u8056\u5f17\u6d1b\u91cc\u5b89"
    ],
    "wof:name":"Sankt Florian",
    "wof:placetype":"locality",
    "wof:population":157
},
  "geometry": {"coordinates":[13.14094,48.16723],"type":"Point"}
}