{
  "type": "Feature",
  "properties": {
    "gn:admin1_code":"04",
    "gn:asciiname":"Sankt Florian",
    "gn:country_code":"AT",
    "gn:dem":410,
    "gn:feature_class":"P",
    "gn:feature_code":"PPL",
    "gn:name":"Sankt Florian",
    "gn:population":157,
    "gn:timezone":"Europe/Vienna",
    "iso:country":"AT",
    "wof:name":"Sankt Florian",
    "wof:placetype":"locality",
    "wof:population":157
},
  "geometry": {"coordinates":[13.14094,48.16723],"type":"Point"}
}