{
  "type": "Feature",
  "properties": {
    "gn:admin1_code":"04",
    "gn:admin2_code":"412.0",
    "gn:admin3_code":"41208.0",
    "gn:asciiname":"Reiset",
    "gn:country_code":"AT",
    "gn:dem":433,
    "gn:feature_class":"P",
    "gn:feature_code":"PPL",
    "gn:name":"Reiset",
    "gn:population":21,
    "gn:timezone":"Europe/Vienna",
    "iso:country":"AT",
    "wof:name":"Reiset",
    "wof:placetype":"locality",
    "wof:population":21
},
  "geometry": {"coordinates":[13.37774,48.25274],"type":"Point"}
}