{
  "type": "Feature",
  "properties": {
    "gn:admin1_code":"5.0",
    "gn:admin2_code":"503",
    "gn:admin3_code":"50325.0",
    "gn:asciiname":"Eisping",
    "gn:country_code":"AT",
    "gn:dem":456,
    "gn:feature_class":"P",
    "gn:feature_code":"PPL",
    "gn:name":"Eisping",
    "gn:population":63,
    "gn:timezone":"Europe/Vienna",
    "iso:country":"AT",
    "wof:name":"Eisping",
    "wof:placetype":"locality",
    "wof:population":63
},
  "geometry": {"coordinates":[13.01667,47.98333],"type":"Point"}
}