{
  "type": "Feature",
  "properties": {
    "gn:admin1_code":"6.0",
    "gn:admin2_code":"620",
    "gn:admin3_code":"62036.0",
    "gn:asciiname":"Hirschfeld",
    "gn:country_code":"AT",
    "gn:dem":750,
    "gn:feature_class":"P",
    "gn:feature_code":"PPL",
    "gn:name":"Hirschfeld",
    "gn:population":0,
    "gn:timezone":"Europe/Vienna",
    "iso:country":"AT",
    "wof:name":"Hirschfeld",
    "wof:placetype":"locality"
},
  "geometry": {"coordinates":[14.43056,47.16806],"type":"Point"}
}