{
  "type": "Feature",
  "properties": {
    "gn:admin1_code":"6.0",
    "gn:admin2_code":"620",
    "gn:admin3_code":"62036.0",
    "gn:asciiname":"Hirschfeld",
    "gn:country_code":"AT",
    "gn:dem":750,
    "gn:feature_class":"P",
    "gn:feature_code":"PPL",
    "gn:name":"Hirschfeld",
    "gn:population":0,
    "gn:timezone":"Europe/Vienna",
    "iso:country":"AT",
    "name:ceb_x_preferred":[
        "Hirschfeld"
    ],
    "name:deu_x_preferred":[
        "Hirschfeld"
    ],
    "name:epo_x_preferred":[
        "Hirschfeld"
    ],
    "name:fra_x_preferred":[
        "Hirschfeld"
    ],
    "name:heb_x_preferred":[
        "\u05d4\u05d9\u05e8\u05e9\u05e4\u05dc\u05d3"
    ],
    "name:ita_x_preferred":[
        "Hirschfeld"
    ],
    "name:mkd_x_preferred":[
        "\u0425\u0438\u0440\u0448\u0444\u0435\u043b\u0434"
    ],
    "name:nds_x_preferred":[
        "Hirschfeld"
    ],
    "name:nld_x_preferred":[
        "Hirschfeld"
    ],
    "name:pol_x_preferred":[
        "Hirschfeld"
    ],
    "name:por_x_preferred":[
        "Hirschfeld"
    ],
    "name:rus_x_preferred":[
        "\u0425\u0438\u0440\u0448\u0444\u0435\u043b\u044c\u0434"
    ],
    "name:spa_x_preferred":[
        "Hirschfeld"
    ],
    "name:swe_x_preferred":[
        "Hirschfeld"
    ],
    "name:vol_x_preferred":[
        "Hirschfeld"
    ],
    "wof:name":"Hirschfeld",
    "wof:placetype":"locality"
},
  "geometry": {"coordinates":[14.43056,47.16806],"type":"Point"}
}