{
  "type": "Feature",
  "properties": {
    "gn:admin1_code":"5.0",
    "gn:admin2_code":"503",
    "gn:admin3_code":"50332.0",
    "gn:asciiname":"Innerwall",
    "gn:country_code":"AT",
    "gn:dem":618,
    "gn:feature_class":"P",
    "gn:feature_code":"PPL",
    "gn:name":"Innerwall",
    "gn:population":0,
    "gn:timezone":"Europe/Vienna",
    "iso:country":"AT",
    "wof:name":"Innerwall",
    "wof:placetype":"locality"
},
  "geometry": {"coordinates":[13.04889,47.95083],"type":"Point"}
}