{
  "type": "Feature",
  "properties": {
    "gn:admin1_code":"5.0",
    "gn:admin2_code":"503",
    "gn:admin3_code":"50329.0",
    "gn:asciiname":"Moospirach",
    "gn:country_code":"AT",
    "gn:dem":445,
    "gn:feature_class":"P",
    "gn:feature_code":"PPL",
    "gn:name":"Moospirach",
    "gn:population":34,
    "gn:timezone":"Europe/Vienna",
    "iso:country":"AT",
    "wof:name":"Moospirach",
    "wof:placetype":"locality",
    "wof:population":34
},
  "geometry": {"coordinates":[12.90472,47.99611],"type":"Point"}
}