{
  "type": "Feature",
  "properties": {
    "gn:admin1_code":"05",
    "gn:admin2_code":"504.0",
    "gn:admin3_code":"50405.0",
    "gn:asciiname":"Bergl",
    "gn:country_code":"AT",
    "gn:dem":1028,
    "gn:feature_class":"P",
    "gn:feature_code":"PPL",
    "gn:name":"Bergl",
    "gn:population":63,
    "gn:timezone":"Europe/Vienna",
    "iso:country":"AT",
    "wof:name":"Bergl",
    "wof:placetype":"locality",
    "wof:population":63
},
  "geometry": {"coordinates":[13.11667,47.25],"type":"Point"}
}