{
  "type": "Feature",
  "properties": {
    "gn:country":"AT",
    "gn:fcode":"PPLA3",
    "gn:population":0,
    "iso:country":"AT",
    "name:bul_x_preferred":[
        "\u0413\u0430\u043b\u0442\u044e\u0440"
    ],
    "name:ceb_x_preferred":[
        "Galt\u00fcr"
    ],
    "name:ces_x_preferred":[
        "Galt\u00fcr"
    ],
    "name:deu_x_preferred":[
        "Galt\u00fcr"
    ],
    "name:eng_x_preferred":[
        "Galt\u00fcr"
    ],
    "name:est_x_preferred":[
        "Galt\u00fcr"
    ],
    "name:fas_x_preferred":[
        "\u06af\u0627\u0644\u062a\u0648\u0631"
    ],
    "name:fra_x_preferred":[
        "Galt\u00fcr"
    ],
    "name:hun_x_preferred":[
        "Galt\u00fcr"
    ],
    "name:ita_x_preferred":[
        "Galt\u00fcr"
    ],
    "name:kaz_x_preferred":[
        "\u0413\u0430\u043b\u044c\u0442\u044e\u0440"
    ],
    "name:lmo_x_preferred":[
        "Galt\u00fcr"
    ],
    "name:nld_x_preferred":[
        "Galt\u00fcr"
    ],
    "name:nob_x_preferred":[
        "Galt\u00fcr"
    ],
    "name:pnb_x_preferred":[
        "\u06af\u0627\u0644\u0679\u0631"
    ],
    "name:pol_x_preferred":[
        "Galt\u00fcr"
    ],
    "name:rus_x_preferred":[
        "\u0413\u0430\u043b\u044c\u0442\u044e\u0440"
    ],
    "name:slk_x_preferred":[
        "Galt\u00fcr"
    ],
    "name:spa_x_preferred":[
        "Galt\u00fcr"
    ],
    "name:swe_x_preferred":[
        "Galt\u00fcr"
    ],
    "name:ukr_x_preferred":[
        "\u0413\u0430\u043b\u044c\u0442\u044e\u0440"
    ],
    "name:und_x_variant":[
        "Platz"
    ],
    "name:uzb_x_preferred":[
        "Galt\u00fcr"
    ],
    "name:vol_x_preferred":[
        "Galt\u00fcr"
    ],
    "name:war_x_preferred":[
        "Galt\u00fcr"
    ],
    "name:zho_x_preferred":[
        "\u52a0\u5c14\u8482"
    ],
    "qs_pg:aaroncc":"AT",
    "qs_pg:gn_country":"AT",
    "qs_pg:gn_fcode":"PPLA3",
    "qs_pg:gn_pop":0,
    "qs_pg:name":"Galt\u00fcr",
    "qs_pg:name_adm0":"\u00d6sterreich",
    "qs_pg:name_adm1":"Tirol",
    "qs_pg:photos":1904,
    "qs_pg:photos_1k":386,
    "qs_pg:photos_9k":8,
    "qs_pg:photos_9r":9,
    "qs_pg:photos_all":1904,
    "qs_pg:photos_sr":15,
    "qs_pg:pop_sr":0,
    "qs_pg:qs_pg_placetype":"locality",
    "qs_pg:qs_pg_placetype_gp":"Town",
    "qs_pg:woe_adm0":23424750,
    "woe:adm0_id":23424750,
    "woe:name_adm0":"\u00d6sterreich",
    "woe:name_adm1":"Tirol",
    "woe:placetype":"Town",
    "wof:name":"Galt\u00fcr",
    "wof:placetype":"locality"
},
  "geometry": {"coordinates":[10.18333,46.96667],"type":"Point"}
}