{
  "type": "Feature",
  "properties": {
    "gn:admin1_code":"3.0",
    "gn:admin2_code":"305",
    "gn:admin3_code":"30527.0",
    "gn:asciiname":"Hart",
    "gn:country_code":"AT",
    "gn:dem":263,
    "gn:feature_class":"P",
    "gn:feature_code":"PPL",
    "gn:name":"Hart",
    "gn:population":461,
    "gn:timezone":"Europe/Vienna",
    "iso:country":"AT",
    "wof:name":"Hart",
    "wof:placetype":"locality",
    "wof:population":461
},
  "geometry": {"coordinates":[14.91667,48.11667],"type":"Point"}
}