{
  "type": "Feature",
  "properties": {
    "iso:country":"AT",
    "name:dut_x_preferred":[
        "Abersee"
    ],
    "name:eng_x_preferred":[
        "Abersee"
    ],
    "name:ger_x_preferred":[
        "Abersee"
    ],
    "qs_pg:aaroncc":"AT",
    "qs_pg:name":"Abersee",
    "qs_pg:name_adm0":"\u00d6sterreich",
    "qs_pg:name_adm1":"Salzburg",
    "qs_pg:photos":130,
    "qs_pg:photos_1k":26,
    "qs_pg:photos_9k":1,
    "qs_pg:photos_9r":3,
    "qs_pg:photos_all":130,
    "qs_pg:photos_sr":3,
    "qs_pg:pop_sr":0,
    "qs_pg:qs_pg_placetype":"locality",
    "qs_pg:qs_pg_placetype_gp":"Town",
    "qs_pg:woe_adm0":23424750,
    "woe:adm0_id":23424750,
    "woe:name_adm0":"\u00d6sterreich",
    "woe:name_adm1":"Salzburg",
    "woe:placetype":"Town",
    "wof:name":"Abersee",
    "wof:placetype":"locality"
},
  "geometry": {"coordinates":[13.403627,47.741408],"type":"Point"}
}