{
  "type": "Feature",
  "properties": {
    "gn:admin1_code":"02",
    "gn:admin2_code":"209.0",
    "gn:admin3_code":"20901.0",
    "gn:asciiname":"Wiesenau",
    "gn:country_code":"AT",
    "gn:dem":655,
    "gn:feature_class":"P",
    "gn:feature_code":"PPL",
    "gn:name":"Wiesenau",
    "gn:population":81,
    "gn:timezone":"Europe/Vienna",
    "iso:country":"AT",
    "wof:name":"Wiesenau",
    "wof:placetype":"locality",
    "wof:population":81
},
  "geometry": {"coordinates":[14.81556,46.945],"type":"Point"}
}