{
  "type": "Feature",
  "properties": {
    "gn:admin1_code":"4.0",
    "gn:admin2_code":"417",
    "gn:admin3_code":"41723.0",
    "gn:asciiname":"Oberkogl",
    "gn:country_code":"AT",
    "gn:dem":543,
    "gn:feature_class":"P",
    "gn:feature_code":"PPL",
    "gn:name":"Oberkogl",
    "gn:population":4,
    "gn:timezone":"Europe/Vienna",
    "iso:country":"AT",
    "wof:name":"Oberkogl",
    "wof:placetype":"locality",
    "wof:population":4
},
  "geometry": {"coordinates":[13.45186,48.01074000000001],"type":"Point"}
}