{
  "type": "Feature",
  "properties": {
    "gn:admin1_code":"06",
    "gn:admin2_code":"622.0",
    "gn:admin3_code":"62252.0",
    "gn:asciiname":"Ruppersdorf",
    "gn:country_code":"AT",
    "gn:dem":320,
    "gn:feature_class":"P",
    "gn:feature_code":"PPL",
    "gn:name":"Ruppersdorf",
    "gn:population":146,
    "gn:timezone":"Europe/Vienna",
    "iso:country":"AT",
    "wof:name":"Ruppersdorf",
    "wof:placetype":"locality",
    "wof:population":146
},
  "geometry": {"coordinates":[15.98333,47.03333],"type":"Point"}
}