{
  "type": "Feature",
  "properties": {
    "gn:admin1_code":"4.0",
    "gn:admin2_code":"406",
    "gn:admin3_code":"40624.0",
    "gn:asciiname":"Frensdorf",
    "gn:country_code":"AT",
    "gn:dem":371,
    "gn:feature_class":"P",
    "gn:feature_code":"PPL",
    "gn:name":"Frensdorf",
    "gn:population":343,
    "gn:timezone":"Europe/Vienna",
    "iso:country":"AT",
    "name:ara_x_preferred":[
        "\u0641\u0631\u064a\u0646\u0633\u062f\u0648\u0631\u0641"
    ],
    "name:ceb_x_preferred":[
        "Frensdorf"
    ],
    "name:deu_x_preferred":[
        "Frensdorf"
    ],
    "name:epo_x_preferred":[
        "Frensdorf"
    ],
    "name:eus_x_preferred":[
        "Frensdorf"
    ],
    "name:fas_x_preferred":[
        "\u0641\u0631\u0646\u0633\u062f\u0648\u0631\u0641"
    ],
    "name:fra_x_preferred":[
        "Frensdorf"
    ],
    "name:hun_x_preferred":[
        "Frensdorf"
    ],
    "name:hye_x_preferred":[
        "\u0556\u0580\u0565\u0576\u057d\u0564\u0578\u0580\u0586"
    ],
    "name:ita_x_preferred":[
        "Frensdorf"
    ],
    "name:jpn_x_preferred":[
        "\u30d5\u30ec\u30f3\u30b9\u30c9\u30eb\u30d5"
    ],
    "name:kaz_x_preferred":[
        "\u0424\u0440\u0435\u043d\u0441\u0434\u043e\u0440\u0444"
    ],
    "name:kir_x_preferred":[
        "\u0424\u0440\u0435\u043d\u0441\u0434\u043e\u0440\u0444"
    ],
    "name:lmo_x_preferred":[
        "Frensdorf"
    ],
    "name:msa_x_preferred":[
        "Frensdorf"
    ],
    "name:nld_x_preferred":[
        "Frensdorf"
    ],
    "name:pol_x_preferred":[
        "Frensdorf"
    ],
    "name:por_x_preferred":[
        "Frensdorf"
    ],
    "name:ron_x_preferred":[
        "Frensdorf"
    ],
    "name:rus_x_preferred":[
        "\u0424\u0440\u0435\u043d\u0441\u0434\u043e\u0440\u0444"
    ],
    "name:spa_x_preferred":[
        "Frensdorf"
    ],
    "name:srp_x_preferred":[
        "\u0424\u0440\u0435\u043d\u0441\u0434\u043e\u0440\u0444"
    ],
    "name:ukr_x_preferred":[
        "\u0424\u0440\u0435\u043d\u0441\u0434\u043e\u0440\u0444"
    ],
    "name:uzb_x_preferred":[
        "Frensdorf"
    ],
    "name:vol_x_preferred":[
        "Frensdorf"
    ],
    "name:war_x_preferred":[
        "Frensdorf"
    ],
    "name:zho_x_preferred":[
        "\u5f17\u4f26\u65af\u591a\u592b"
    ],
    "wof:name":"Frensdorf",
    "wof:placetype":"locality",
    "wof:population":343
},
  "geometry": {"coordinates":[14.51453,48.32153],"type":"Point"}
}