{
  "type": "Feature",
  "properties": {
    "gn:admin1_code":"4.0",
    "gn:admin2_code":"406",
    "gn:admin3_code":"40624.0",
    "gn:asciiname":"Frensdorf",
    "gn:country_code":"AT",
    "gn:dem":371,
    "gn:feature_class":"P",
    "gn:feature_code":"PPL",
    "gn:name":"Frensdorf",
    "gn:population":343,
    "gn:timezone":"Europe/Vienna",
    "iso:country":"AT",
    "wof:name":"Frensdorf",
    "wof:placetype":"locality",
    "wof:population":343
},
  "geometry": {"coordinates":[14.51453,48.32153],"type":"Point"}
}