{
  "type": "Feature",
  "properties": {
    "gn:admin1_code":"4.0",
    "gn:admin2_code":"413",
    "gn:admin3_code":"41327.0",
    "gn:asciiname":"Hinterleithen",
    "gn:country_code":"AT",
    "gn:dem":643,
    "gn:feature_class":"P",
    "gn:feature_code":"PPL",
    "gn:name":"Hinterleithen",
    "gn:population":7,
    "gn:timezone":"Europe/Vienna",
    "iso:country":"AT",
    "wof:name":"Hinterleithen",
    "wof:placetype":"locality",
    "wof:population":7
},
  "geometry": {"coordinates":[13.79806,48.52583],"type":"Point"}
}