{
  "type": "Feature",
  "properties": {
    "gn:admin1_code":"03",
    "gn:admin2_code":"319.0",
    "gn:admin3_code":"31902.0",
    "gn:asciiname":"Siegersdorf",
    "gn:country_code":"AT",
    "gn:dem":207,
    "gn:feature_class":"P",
    "gn:feature_code":"PPL",
    "gn:name":"Siegersdorf",
    "gn:population":404,
    "gn:timezone":"Europe/Vienna",
    "iso:country":"AT",
    "wof:name":"Siegersdorf",
    "wof:placetype":"locality",
    "wof:population":404
},
  "geometry": {"coordinates":[15.94185,48.252],"type":"Point"}
}