{
  "type": "Feature",
  "properties": {
    "gn:admin1_code":"4.0",
    "gn:admin2_code":"414",
    "gn:admin3_code":"41409.0",
    "gn:asciiname":"Wollersbach",
    "gn:country_code":"AT",
    "gn:dem":489,
    "gn:feature_class":"P",
    "gn:feature_code":"PPL",
    "gn:name":"Wollersbach",
    "gn:population":0,
    "gn:timezone":"Europe/Vienna",
    "iso:country":"AT",
    "wof:name":"Wollersbach",
    "wof:placetype":"locality"
},
  "geometry": {"coordinates":[13.60806,48.54944],"type":"Point"}
}