{
  "type": "Feature",
  "properties": {
    "gn:admin1_code":"2.0",
    "gn:admin2_code":"207",
    "gn:admin3_code":"20725.0",
    "gn:asciiname":"Sankt Stefan",
    "gn:country_code":"AT",
    "gn:dem":479,
    "gn:feature_class":"P",
    "gn:feature_code":"PPL",
    "gn:name":"Sankt Stefan",
    "gn:population":0,
    "gn:timezone":"Europe/Vienna",
    "iso:country":"AT",
    "wof:name":"Sankt Stefan",
    "wof:placetype":"locality"
},
  "geometry": {"coordinates":[14.03889,46.585],"type":"Point"}
}