{
  "type": "Feature",
  "properties": {
    "gn:admin1_code":"4.0",
    "gn:admin2_code":"412",
    "gn:admin3_code":"41233.0",
    "gn:asciiname":"Reschenedt",
    "gn:country_code":"AT",
    "gn:dem":384,
    "gn:feature_class":"P",
    "gn:feature_code":"PPL",
    "gn:name":"Reschenedt",
    "gn:population":9,
    "gn:timezone":"Europe/Vienna",
    "iso:country":"AT",
    "wof:name":"Reschenedt",
    "wof:placetype":"locality",
    "wof:population":9
},
  "geometry": {"coordinates":[13.51614,48.29733],"type":"Point"}
}