{
  "type": "Feature",
  "properties": {
    "gn:admin1_code":"6.0",
    "gn:admin2_code":"616",
    "gn:admin3_code":"61633.0",
    "gn:asciiname":"Koeppling",
    "gn:country_code":"AT",
    "gn:dem":383,
    "gn:feature_class":"P",
    "gn:feature_code":"PPL",
    "gn:name":"K\u00f6ppling",
    "gn:population":490,
    "gn:timezone":"Europe/Vienna",
    "iso:country":"AT",
    "wof:name":"Koeppling",
    "wof:placetype":"locality",
    "wof:population":490
},
  "geometry": {"coordinates":[15.24459,47.00934],"type":"Point"}
}