{
  "type": "Feature",
  "properties": {
    "gn:admin1_code":"6.0",
    "gn:admin2_code":"606",
    "gn:admin3_code":"60629.0",
    "gn:asciiname":"Haselsdorfberg",
    "gn:country_code":"AT",
    "gn:dem":337,
    "gn:feature_class":"P",
    "gn:feature_code":"PPL",
    "gn:name":"Haselsdorfberg",
    "gn:population":0,
    "gn:timezone":"Europe/Vienna",
    "iso:country":"AT",
    "wof:name":"Haselsdorfberg",
    "wof:placetype":"locality"
},
  "geometry": {"coordinates":[15.33333,46.98333],"type":"Point"}
}