{
  "type": "Feature",
  "properties": {
    "iso:country":"AT",
    "name:deu_x_preferred":[
        "Oberer Tollinggraben"
    ],
    "qs:gn_adm0_cc":"AT",
    "qs:gn_fcode":"PPLX",
    "qs:gn_local":2766439,
    "qs:gn_nam_loc":"buchbach",
    "qs:gn_namadm1":"06",
    "qs:gn_name":"Oberer Tollinggraben",
    "qs:local_max":53,
    "qs:local_sum":53,
    "qs:localhoods":1,
    "qs:name":"Oberer Tollinggraben",
    "qs:name_adm0":"\u00d6sterreich",
    "qs:name_adm1":"Steiermark",
    "qs:name_adm2":"Leoben",
    "qs:name_lau":"St. Peter-Freienstein",
    "qs:name_local":"St. Peter-Freienstein",
    "qs:photo_max":33,
    "qs:photo_sum":53,
    "qs:placetype":"Suburb",
    "qs:quad_count":13,
    "qs:woe_adm0":23424750,
    "qs:woe_adm1":2344713,
    "qs:woe_adm2":12591737,
    "qs:woe_lau":12675052,
    "qs:woe_local":12675052,
    "qs:woe_ver":"7.10.0",
    "wof:lang":[
        "ger"
    ],
    "wof:name":"Oberer Tollinggraben",
    "wof:placetype":"neighbourhood"
},
  "geometry": {"coordinates":[15.034272,47.396842],"type":"Point"}
}