{
  "type": "Feature",
  "properties": {
    "gn:admin1_code":"3.0",
    "gn:admin2_code":"318",
    "gn:admin3_code":"31839.0",
    "gn:asciiname":"Gadenweith",
    "gn:country_code":"AT",
    "gn:dem":564,
    "gn:feature_class":"P",
    "gn:feature_code":"PPL",
    "gn:name":"Gadenweith",
    "gn:population":15,
    "gn:timezone":"Europe/Vienna",
    "iso:country":"AT",
    "wof:name":"Gadenweith",
    "wof:placetype":"locality",
    "wof:population":15
},
  "geometry": {"coordinates":[15.9482,47.7496],"type":"Point"}
}