{
  "type": "Feature",
  "properties": {
    "gn:admin1_code":"03",
    "gn:admin2_code":"313.0",
    "gn:admin3_code":"31303.0",
    "gn:asciiname":"Schenkenbrunn",
    "gn:country_code":"AT",
    "gn:dem":467,
    "gn:feature_class":"P",
    "gn:feature_code":"PPL",
    "gn:name":"Schenkenbrunn",
    "gn:population":149,
    "gn:timezone":"Europe/Vienna",
    "iso:country":"AT",
    "wof:name":"Schenkenbrunn",
    "wof:placetype":"locality",
    "wof:population":149
},
  "geometry": {"coordinates":[15.48333,48.33333],"type":"Point"}
}