{
  "type": "Feature",
  "properties": {
    "gn:admin1_code":"4.0",
    "gn:admin2_code":"417",
    "gn:admin3_code":"41729.0",
    "gn:asciiname":"Schweinegg",
    "gn:country_code":"AT",
    "gn:dem":644,
    "gn:feature_class":"P",
    "gn:feature_code":"PPL",
    "gn:name":"Schweinegg",
    "gn:population":48,
    "gn:timezone":"Europe/Vienna",
    "iso:country":"AT",
    "wof:name":"Schweinegg",
    "wof:placetype":"locality",
    "wof:population":48
},
  "geometry": {"coordinates":[13.44636,48.08103],"type":"Point"}
}