{
  "type": "Feature",
  "properties": {
    "gn:admin1_code":"4.0",
    "gn:admin2_code":"412",
    "gn:admin3_code":"41213.0",
    "gn:asciiname":"Bergham",
    "gn:country_code":"AT",
    "gn:dem":503,
    "gn:feature_class":"P",
    "gn:feature_code":"PPL",
    "gn:name":"Bergham",
    "gn:population":6,
    "gn:timezone":"Europe/Vienna",
    "iso:country":"AT",
    "wof:name":"Bergham",
    "wof:placetype":"locality",
    "wof:population":6
},
  "geometry": {"coordinates":[13.3859,48.16448],"type":"Point"}
}