{
  "type": "Feature",
  "properties": {
    "gn:admin1_code":"7.0",
    "gn:admin2_code":"702",
    "gn:admin3_code":"70218.0",
    "gn:asciiname":"Haderlehn",
    "gn:country_code":"AT",
    "gn:dem":811,
    "gn:feature_class":"P",
    "gn:feature_code":"PPL",
    "gn:name":"Haderlehn",
    "gn:population":0,
    "gn:timezone":"Europe/Vienna",
    "iso:country":"AT",
    "wof:name":"Haderlehn",
    "wof:placetype":"locality"
},
  "geometry": {"coordinates":[10.86226,47.2075],"type":"Point"}
}