{
  "type": "Feature",
  "properties": {
    "gn:admin1_code":"6.0",
    "gn:admin2_code":"610",
    "gn:admin3_code":"61007.0",
    "gn:asciiname":"Liebensdorf",
    "gn:country_code":"AT",
    "gn:dem":375,
    "gn:feature_class":"P",
    "gn:feature_code":"PPL",
    "gn:name":"Liebensdorf",
    "gn:population":877,
    "gn:timezone":"Europe/Vienna",
    "iso:country":"AT",
    "wof:name":"Liebensdorf",
    "wof:placetype":"locality",
    "wof:population":877
},
  "geometry": {"coordinates":[15.56727,46.98218],"type":"Point"}
}