{
  "type": "Feature",
  "properties": {
    "gn:admin1_code":"4.0",
    "gn:admin2_code":"404",
    "gn:admin3_code":"40427.0",
    "gn:asciiname":"Enknach",
    "gn:country_code":"AT",
    "gn:dem":395,
    "gn:feature_class":"P",
    "gn:feature_code":"PPL",
    "gn:name":"Enknach",
    "gn:population":21,
    "gn:timezone":"Europe/Vienna",
    "iso:country":"AT",
    "wof:name":"Enknach",
    "wof:placetype":"locality",
    "wof:population":21
},
  "geometry": {"coordinates":[13.03923,48.19825],"type":"Point"}
}