{
  "type": "Feature",
  "properties": {
    "gn:admin1_code":"2.0",
    "gn:admin2_code":"205",
    "gn:admin3_code":"20515.0",
    "gn:asciiname":"Grassendorf",
    "gn:country_code":"AT",
    "gn:dem":1000,
    "gn:feature_class":"P",
    "gn:feature_code":"PPL",
    "gn:name":"Grassendorf",
    "gn:population":17,
    "gn:timezone":"Europe/Vienna",
    "iso:country":"AT",
    "name:als_x_preferred":[
        "Grassendorf"
    ],
    "name:ara_x_preferred":[
        "\u063a\u0631\u0627\u0633\u064a\u0646\u062f\u0648\u0631\u0641"
    ],
    "name:cat_x_preferred":[
        "Grassendorf"
    ],
    "name:ceb_x_preferred":[
        "Grassendorf"
    ],
    "name:deu_x_preferred":[
        "Grassendorf"
    ],
    "name:eus_x_preferred":[
        "Grassendorf"
    ],
    "name:fas_x_preferred":[
        "\u06af\u0631\u0627\u0633\u0646\u062f\u0631\u0641"
    ],
    "name:fra_x_preferred":[
        "Grassendorf"
    ],
    "name:hun_x_preferred":[
        "Grassendorf"
    ],
    "name:hye_x_preferred":[
        "\u0533\u0580\u0561\u057d\u0565\u0576\u0564\u0578\u0580\u0586"
    ],
    "name:ita_x_preferred":[
        "Grassendorf"
    ],
    "name:kaz_x_preferred":[
        "\u0413\u0440\u0430\u0441\u0441\u0435\u043d\u0434\u043e\u0440\u0444"
    ],
    "name:lat_x_preferred":[
        "Grassendorf"
    ],
    "name:mlg_x_preferred":[
        "Grassendorf"
    ],
    "name:msa_x_preferred":[
        "Grassendorf"
    ],
    "name:nld_x_preferred":[
        "Grassendorf"
    ],
    "name:oci_x_preferred":[
        "Grassendorf"
    ],
    "name:pfl_x_preferred":[
        "Grassendorf"
    ],
    "name:pms_x_preferred":[
        "Grassendorf"
    ],
    "name:pol_x_preferred":[
        "Grassendorf"
    ],
    "name:por_x_preferred":[
        "Grassendorf"
    ],
    "name:ron_x_preferred":[
        "Grassendorf"
    ],
    "name:rus_x_preferred":[
        "\u0413\u0440\u0430\u0441\u0435\u043d\u0434\u043e\u0440\u0444"
    ],
    "name:slk_x_preferred":[
        "Grassendorf"
    ],
    "name:slv_x_preferred":[
        "Grassendorf"
    ],
    "name:spa_x_preferred":[
        "Grassendorf"
    ],
    "name:swe_x_preferred":[
        "Grassendorf"
    ],
    "name:ukr_x_preferred":[
        "\u0413\u0440\u0430\u0441\u0441\u0435\u043d\u0434\u043e\u0440\u0444"
    ],
    "name:uzb_x_preferred":[
        "Grassendorf"
    ],
    "name:vie_x_preferred":[
        "Grassendorf"
    ],
    "name:vol_x_preferred":[
        "Grassendorf"
    ],
    "name:war_x_preferred":[
        "Grassendorf"
    ],
    "name:zho_x_preferred":[
        "\u683c\u62c9\u68ee\u591a\u592b"
    ],
    "wof:name":"Grassendorf",
    "wof:placetype":"locality",
    "wof:population":17
},
  "geometry": {"coordinates":[14.25,46.78333],"type":"Point"}
}