{
  "type": "Feature",
  "properties": {
    "gn:admin1_code":"2.0",
    "gn:admin2_code":"205",
    "gn:admin3_code":"20515.0",
    "gn:asciiname":"Grassendorf",
    "gn:country_code":"AT",
    "gn:dem":1000,
    "gn:feature_class":"P",
    "gn:feature_code":"PPL",
    "gn:name":"Grassendorf",
    "gn:population":17,
    "gn:timezone":"Europe/Vienna",
    "iso:country":"AT",
    "wof:name":"Grassendorf",
    "wof:placetype":"locality",
    "wof:population":17
},
  "geometry": {"coordinates":[14.25,46.78333],"type":"Point"}
}