{
  "type": "Feature",
  "properties": {
    "gn:admin1_code":"3.0",
    "gn:admin2_code":"319",
    "gn:admin3_code":"31946.0",
    "gn:asciiname":"Haselbach",
    "gn:country_code":"AT",
    "gn:dem":259,
    "gn:feature_class":"P",
    "gn:feature_code":"PPL",
    "gn:name":"Haselbach",
    "gn:population":60,
    "gn:timezone":"Europe/Vienna",
    "iso:country":"AT",
    "name:ceb_x_preferred":[
        "Haselbach"
    ],
    "name:deu_x_preferred":[
        "Haselbach"
    ],
    "name:epo_x_preferred":[
        "Haselbach"
    ],
    "name:fra_x_preferred":[
        "Haselbach"
    ],
    "name:ita_x_preferred":[
        "Haselbach"
    ],
    "name:nld_x_preferred":[
        "Haselbach"
    ],
    "name:pol_x_preferred":[
        "Haselbach"
    ],
    "name:ron_x_preferred":[
        "Haselbach"
    ],
    "name:rus_x_preferred":[
        "\u0425\u0430\u0437\u0435\u043b\u044c\u0431\u0430\u0445"
    ],
    "name:swe_x_preferred":[
        "Haselbach"
    ],
    "name:vol_x_preferred":[
        "Haselbach"
    ],
    "wof:name":"Haselbach",
    "wof:placetype":"locality",
    "wof:population":60
},
  "geometry": {"coordinates":[15.81667,48.25],"type":"Point"}
}