{
  "type": "Feature",
  "properties": {
    "gn:admin1_code":"4.0",
    "gn:admin2_code":"418",
    "gn:admin3_code":"41816.0",
    "gn:asciiname":"Geisensheim",
    "gn:country_code":"AT",
    "gn:dem":319,
    "gn:feature_class":"P",
    "gn:feature_code":"PPL",
    "gn:name":"Geisensheim",
    "gn:population":119,
    "gn:timezone":"Europe/Vienna",
    "iso:country":"AT",
    "wof:name":"Geisensheim",
    "wof:placetype":"locality",
    "wof:population":119
},
  "geometry": {"coordinates":[13.92397,48.19585],"type":"Point"}
}