{
  "type": "Feature",
  "properties": {
    "gn:admin1_code":"4.0",
    "gn:admin2_code":"415",
    "gn:admin3_code":"41508.0",
    "gn:asciiname":"Brunngraben",
    "gn:country_code":"AT",
    "gn:dem":455,
    "gn:feature_class":"P",
    "gn:feature_code":"PPL",
    "gn:name":"Brunngraben",
    "gn:population":0,
    "gn:timezone":"Europe/Vienna",
    "iso:country":"AT",
    "wof:name":"Brunngraben",
    "wof:placetype":"locality"
},
  "geometry": {"coordinates":[14.41526,47.95251],"type":"Point"}
}