{
  "type": "Feature",
  "properties": {
    "gn:admin1_code":"3.0",
    "gn:admin2_code":"315",
    "gn:admin3_code":"31551.0",
    "gn:asciiname":"Altendorf",
    "gn:country_code":"AT",
    "gn:dem":388,
    "gn:feature_class":"P",
    "gn:feature_code":"PPLL",
    "gn:name":"Altendorf",
    "gn:population":186,
    "gn:timezone":"Europe/Vienna",
    "iso:country":"AT",
    "wof:name":"Altendorf",
    "wof:placetype":"locality",
    "wof:population":186
},
  "geometry": {"coordinates":[15.31417,48.04687],"type":"Point"}
}