{
  "type": "Feature",
  "properties": {
    "gn:admin1_code":"3.0",
    "gn:admin2_code":"315",
    "gn:admin3_code":"31551.0",
    "gn:asciiname":"Altendorf",
    "gn:country_code":"AT",
    "gn:dem":388,
    "gn:feature_class":"P",
    "gn:feature_code":"PPLL",
    "gn:name":"Altendorf",
    "gn:population":186,
    "gn:timezone":"Europe/Vienna",
    "iso:country":"AT",
    "name:als_x_preferred":[
        "Altendorf"
    ],
    "name:ceb_x_preferred":[
        "Altendorf"
    ],
    "name:deu_x_preferred":[
        "Altendorf"
    ],
    "name:epo_x_preferred":[
        "Altendorf"
    ],
    "name:eus_x_preferred":[
        "Altendorf"
    ],
    "name:fra_x_preferred":[
        "Altendorf"
    ],
    "name:ita_x_preferred":[
        "Altendorf"
    ],
    "name:lmo_x_preferred":[
        "Altendorf"
    ],
    "name:nld_x_preferred":[
        "Altendorf"
    ],
    "name:pol_x_preferred":[
        "Altendorf"
    ],
    "name:por_x_preferred":[
        "Altendorf"
    ],
    "name:rus_x_preferred":[
        "\u0410\u043b\u044c\u0442\u0435\u043d\u0434\u043e\u0440\u0444"
    ],
    "name:srp_x_preferred":[
        "\u0410\u043b\u0442\u0435\u043d\u0434\u043e\u0440\u0444"
    ],
    "name:swe_x_preferred":[
        "Altendorf"
    ],
    "name:vol_x_preferred":[
        "Altendorf"
    ],
    "name:zho_x_preferred":[
        "\u963f\u5c14\u6ed5\u591a\u592b"
    ],
    "wof:name":"Altendorf",
    "wof:placetype":"locality",
    "wof:population":186
},
  "geometry": {"coordinates":[15.31417,48.04687],"type":"Point"}
}