{
  "type": "Feature",
  "properties": {
    "gn:admin1_code":"4.0",
    "gn:admin2_code":"411",
    "gn:admin3_code":"41114.0",
    "gn:asciiname":"Niedersebern",
    "gn:country_code":"AT",
    "gn:dem":240,
    "gn:feature_class":"P",
    "gn:feature_code":"PPL",
    "gn:name":"Niedersebern",
    "gn:population":0,
    "gn:timezone":"Europe/Vienna",
    "iso:country":"AT",
    "wof:name":"Niedersebern",
    "wof:placetype":"locality"
},
  "geometry": {"coordinates":[14.58169,48.24297],"type":"Point"}
}