{
  "type": "Feature",
  "properties": {
    "gn:admin1_code":"06",
    "gn:admin2_code":"623.0",
    "gn:admin3_code":"62379.0",
    "gn:asciiname":"Paurach",
    "gn:country_code":"AT",
    "gn:dem":312,
    "gn:feature_class":"P",
    "gn:feature_code":"PPL",
    "gn:name":"Paurach",
    "gn:population":246,
    "gn:timezone":"Europe/Vienna",
    "iso:country":"AT",
    "wof:name":"Paurach",
    "wof:placetype":"locality",
    "wof:population":246
},
  "geometry": {"coordinates":[15.83278,46.97],"type":"Point"}
}