{
  "type": "Feature",
  "properties": {
    "gn:admin1_code":"04",
    "gn:admin2_code":"411.0",
    "gn:admin3_code":"41114.0",
    "gn:asciiname":"Tabor",
    "gn:country_code":"AT",
    "gn:dem":238,
    "gn:feature_class":"P",
    "gn:feature_code":"PPL",
    "gn:name":"Tabor",
    "gn:population":0,
    "gn:timezone":"Europe/Vienna",
    "iso:country":"AT",
    "wof:name":"Tabor",
    "wof:placetype":"locality"
},
  "geometry": {"coordinates":[14.63396,48.19396],"type":"Point"}
}