{
  "type": "Feature",
  "properties": {
    "gn:admin1_code":"2.0",
    "gn:admin2_code":"208",
    "gn:admin3_code":"20802.0",
    "gn:asciiname":"Kogelschwaiger",
    "gn:country_code":"AT",
    "gn:dem":1328,
    "gn:feature_class":"P",
    "gn:feature_code":"PPL",
    "gn:name":"Kogelschwaiger",
    "gn:population":0,
    "gn:timezone":"Europe/Vienna",
    "iso:country":"AT",
    "wof:name":"Kogelschwaiger",
    "wof:placetype":"locality"
},
  "geometry": {"coordinates":[14.66556,46.79028],"type":"Point"}
}