{
  "type": "Feature",
  "properties": {
    "gn:admin1_code":"8.0",
    "gn:admin2_code":"802",
    "gn:admin3_code":"80238.0",
    "gn:asciiname":"Simlisgschwend",
    "gn:country_code":"AT",
    "gn:dem":786,
    "gn:feature_class":"P",
    "gn:feature_code":"PPL",
    "gn:name":"Simlisgschwend",
    "gn:population":0,
    "gn:timezone":"Europe/Vienna",
    "iso:country":"AT",
    "wof:name":"Simlisgschwend",
    "wof:placetype":"locality"
},
  "geometry": {"coordinates":[9.93,47.5175],"type":"Point"}
}