{
  "type": "Feature",
  "properties": {
    "gn:admin1_code":"3.0",
    "gn:admin2_code":"308",
    "gn:admin3_code":"30856.0",
    "gn:asciiname":"Silberwald",
    "gn:country_code":"AT",
    "gn:dem":164,
    "gn:feature_class":"P",
    "gn:feature_code":"PPL",
    "gn:name":"Silberwald",
    "gn:population":0,
    "gn:timezone":"Europe/Vienna",
    "iso:country":"AT",
    "wof:name":"Silberwald",
    "wof:placetype":"locality"
},
  "geometry": {"coordinates":[16.68,48.32694],"type":"Point"}
}