{
  "type": "Feature",
  "properties": {
    "gn:admin1_code":"3.0",
    "gn:admin2_code":"322",
    "gn:admin3_code":"32214.0",
    "gn:asciiname":"Artolz",
    "gn:country_code":"AT",
    "gn:dem":613,
    "gn:feature_class":"P",
    "gn:feature_code":"PPL",
    "gn:name":"Artolz",
    "gn:population":57,
    "gn:timezone":"Europe/Vienna",
    "iso:country":"AT",
    "wof:name":"Artolz",
    "wof:placetype":"locality",
    "wof:population":57
},
  "geometry": {"coordinates":[15.16667,48.83333],"type":"Point"}
}