{
  "type": "Feature",
  "properties": {
    "gn:admin1_code":"04",
    "gn:admin2_code":"407.0",
    "gn:admin3_code":"40702.0",
    "gn:asciiname":"Posern",
    "gn:country_code":"AT",
    "gn:dem":589,
    "gn:feature_class":"P",
    "gn:feature_code":"PPL",
    "gn:name":"Posern",
    "gn:population":174,
    "gn:timezone":"Europe/Vienna",
    "iso:country":"AT",
    "wof:name":"Posern",
    "wof:placetype":"locality",
    "wof:population":174
},
  "geometry": {"coordinates":[13.61773,47.65466],"type":"Point"}
}