{
  "type": "Feature",
  "properties": {
    "gn:admin1_code":"3.0",
    "gn:admin2_code":"305",
    "gn:admin3_code":"30520.0",
    "gn:asciiname":"Niederneuhofen",
    "gn:country_code":"AT",
    "gn:dem":313,
    "gn:feature_class":"P",
    "gn:feature_code":"PPL",
    "gn:name":"Niederneuhofen",
    "gn:population":0,
    "gn:timezone":"Europe/Vienna",
    "iso:country":"AT",
    "wof:name":"Niederneuhofen",
    "wof:placetype":"locality"
},
  "geometry": {"coordinates":[14.85291,48.06007],"type":"Point"}
}