{
  "type": "Feature",
  "properties": {
    "gn:admin1_code":"4.0",
    "gn:admin2_code":"417",
    "gn:admin3_code":"41746.0",
    "gn:asciiname":"Obereinwald",
    "gn:country_code":"AT",
    "gn:dem":513,
    "gn:feature_class":"P",
    "gn:feature_code":"PPL",
    "gn:name":"Obereinwald",
    "gn:population":0,
    "gn:timezone":"Europe/Vienna",
    "iso:country":"AT",
    "wof:name":"Obereinwald",
    "wof:placetype":"locality"
},
  "geometry": {"coordinates":[13.63796,48.03857],"type":"Point"}
}