{
  "type": "Feature",
  "properties": {
    "gn:country":"AT",
    "gn:fcode":"PPL",
    "gn:population":0,
    "iso:country":"AT",
    "name:bar_x_preferred":[
        "Stodschlaining"
    ],
    "name:ceb_x_preferred":[
        "Stadtschlaining"
    ],
    "name:ces_x_preferred":[
        "Stadtschlaining"
    ],
    "name:deu_x_preferred":[
        "Stadtschlaining"
    ],
    "name:eng_x_preferred":[
        "Stadtschlaining"
    ],
    "name:epo_x_preferred":[
        "Stadtschlaining"
    ],
    "name:fas_x_preferred":[
        "\u0627\u0634\u062a\u0627\u0686\u0644\u0627\u06cc\u0646\u06cc\u0646\u06af"
    ],
    "name:fra_x_preferred":[
        "Stadtschlaining"
    ],
    "name:heb_x_preferred":[
        "\u05e9\u05d8\u05d0\u05d3\u05d8\u05e9\u05dc\u05d9\u05d9\u05e0\u05d9\u05e0\u05d2"
    ],
    "name:hun_x_preferred":[
        "V\u00e1rosszal\u00f3nak"
    ],
    "name:ita_x_preferred":[
        "Stadtschlaining"
    ],
    "name:jpn_x_preferred":[
        "\u30b7\u30e5\u30bf\u30c3\u30c8\u30b7\u30e5\u30e9\u30a4\u30cb\u30f3\u30b0"
    ],
    "name:kaz_x_preferred":[
        "\u0428\u0442\u0430\u0434\u0442\u0448\u043b\u0430\u0439\u043d\u0438\u043d\u0433"
    ],
    "name:nld_x_preferred":[
        "Stadtschlaining"
    ],
    "name:pol_x_preferred":[
        "Stadtschlaining"
    ],
    "name:por_x_preferred":[
        "Stadtschlaining"
    ],
    "name:rus_x_preferred":[
        "\u0428\u0442\u0430\u0434\u0442\u0448\u043b\u0430\u0439\u043d\u0438\u043d\u0433"
    ],
    "name:slk_x_preferred":[
        "Stadtschlaining"
    ],
    "name:spa_x_preferred":[
        "Stadtschlaining"
    ],
    "name:swe_x_preferred":[
        "Stadtschlaining"
    ],
    "name:uzb_x_preferred":[
        "Stadtschlaining"
    ],
    "name:vol_x_preferred":[
        "Stadtschlaining"
    ],
    "name:war_x_preferred":[
        "Stadtschlaining"
    ],
    "name:zho_x_preferred":[
        "Stadtschlaining"
    ],
    "qs_pg:aaroncc":"AT",
    "qs_pg:gn_country":"AT",
    "qs_pg:gn_fcode":"PPL",
    "qs_pg:gn_pop":0,
    "qs_pg:name":"Stadtschlaining",
    "qs_pg:name_adm0":"\u00d6sterreich",
    "qs_pg:name_adm1":"Burgenland",
    "qs_pg:photos":51,
    "qs_pg:photos_1k":10,
    "qs_pg:photos_9k":1,
    "qs_pg:photos_9r":2,
    "qs_pg:photos_all":51,
    "qs_pg:photos_sr":2,
    "qs_pg:pop_sr":0,
    "qs_pg:qs_pg_placetype":"locality",
    "qs_pg:qs_pg_placetype_gp":"Town",
    "qs_pg:woe_adm0":23424750,
    "woe:adm0_id":23424750,
    "woe:name_adm0":"\u00d6sterreich",
    "woe:name_adm1":"Burgenland",
    "woe:placetype":"Town",
    "wof:name":"Stadtschlaining",
    "wof:placetype":"locality"
},
  "geometry": {"coordinates":[16.28333,47.31667],"type":"Point"}
}