{
  "type": "Feature",
  "properties": {
    "gn:admin1_code":"4.0",
    "gn:admin2_code":"417",
    "gn:admin3_code":"41719.0",
    "gn:asciiname":"Laiter",
    "gn:country_code":"AT",
    "gn:dem":644,
    "gn:feature_class":"P",
    "gn:feature_code":"PPL",
    "gn:name":"Laiter",
    "gn:population":171,
    "gn:timezone":"Europe/Vienna",
    "iso:country":"AT",
    "wof:name":"Laiter",
    "wof:placetype":"locality",
    "wof:population":171
},
  "geometry": {"coordinates":[13.31667,47.93333],"type":"Point"}
}