{
  "type": "Feature",
  "properties": {
    "gn:admin1_code":"03",
    "gn:admin2_code":"315.0",
    "gn:admin3_code":"31537.0",
    "gn:asciiname":"Ockert",
    "gn:country_code":"AT",
    "gn:dem":279,
    "gn:feature_class":"P",
    "gn:feature_code":"PPL",
    "gn:name":"Ockert",
    "gn:population":45,
    "gn:timezone":"Europe/Vienna",
    "iso:country":"AT",
    "wof:name":"Ockert",
    "wof:placetype":"locality",
    "wof:population":45
},
  "geometry": {"coordinates":[15.23419,48.10053],"type":"Point"}
}