{
  "type": "Feature",
  "properties": {
    "gn:admin1_code":"3.0",
    "gn:admin2_code":"320",
    "gn:admin3_code":"32002.0",
    "gn:asciiname":"Grossegg",
    "gn:cc2":"AT",
    "gn:country_code":"AT",
    "gn:dem":1017,
    "gn:feature_class":"P",
    "gn:feature_code":"PPL",
    "gn:name":"Grossegg",
    "gn:population":0,
    "gn:timezone":"Europe/Vienna",
    "iso:country":"AT",
    "name:und_x_variant":[
        "Grosseck",
        "Grossegg"
    ],
    "wof:name":"Grossegg",
    "wof:placetype":"locality"
},
  "geometry": {"coordinates":[14.88333,47.75],"type":"Point"}
}