{
  "type": "Feature",
  "properties": {
    "gn:admin1_code":"4.0",
    "gn:admin2_code":"414",
    "gn:admin3_code":"41409.0",
    "gn:asciiname":"Sonndorf",
    "gn:country_code":"AT",
    "gn:dem":514,
    "gn:feature_class":"P",
    "gn:feature_code":"PPL",
    "gn:name":"Sonndorf",
    "gn:population":0,
    "gn:timezone":"Europe/Vienna",
    "iso:country":"AT",
    "wof:name":"Sonndorf",
    "wof:placetype":"locality"
},
  "geometry": {"coordinates":[13.58806,48.54167],"type":"Point"}
}