{
  "type": "Feature",
  "properties": {
    "gn:admin1_code":"4.0",
    "gn:admin2_code":"408",
    "gn:admin3_code":"40827.0",
    "gn:asciiname":"Aigendorf",
    "gn:country_code":"AT",
    "gn:dem":330,
    "gn:feature_class":"P",
    "gn:feature_code":"PPL",
    "gn:name":"Aigendorf",
    "gn:population":26,
    "gn:timezone":"Europe/Vienna",
    "iso:country":"AT",
    "wof:name":"Aigendorf",
    "wof:placetype":"locality",
    "wof:population":26
},
  "geometry": {"coordinates":[13.88672,48.23405],"type":"Point"}
}