{
  "type": "Feature",
  "properties": {
    "gn:admin1_code":"4.0",
    "gn:admin2_code":"417",
    "gn:admin3_code":"41748.0",
    "gn:asciiname":"Egg",
    "gn:country_code":"AT",
    "gn:dem":640,
    "gn:feature_class":"P",
    "gn:feature_code":"PPL",
    "gn:name":"Egg",
    "gn:population":49,
    "gn:timezone":"Europe/Vienna",
    "iso:country":"AT",
    "wof:name":"Egg",
    "wof:placetype":"locality",
    "wof:population":49
},
  "geometry": {"coordinates":[13.40529,47.95401],"type":"Point"}
}