{
  "type": "Feature",
  "properties": {
    "gn:admin1_code":"02",
    "gn:admin2_code":"205.0",
    "gn:admin3_code":"20512.0",
    "gn:asciiname":"Poelling",
    "gn:country_code":"AT",
    "gn:dem":526,
    "gn:feature_class":"P",
    "gn:feature_code":"PPL",
    "gn:name":"P\u00f6lling",
    "gn:population":16,
    "gn:timezone":"Europe/Vienna",
    "iso:country":"AT",
    "wof:name":"Poelling",
    "wof:placetype":"locality",
    "wof:population":16
},
  "geometry": {"coordinates":[14.47389,46.78161],"type":"Point"}
}