{
  "type": "Feature",
  "properties": {
    "iso:country":"AT",
    "name:deu_x_preferred":[
        "Welzenegg Burgfried"
    ],
    "name:unk_x_variant":[
        "Welzenegg Burgfried"
    ],
    "qs:gn_adm0_cc":"AT",
    "qs:gn_local":2774326,
    "qs:gn_namadm1":"02",
    "qs:local_max":5010,
    "qs:local_sum":14043,
    "qs:localhoods":10,
    "qs:name":"Welzenegg Burgfried",
    "qs:name_adm0":"\u00d6sterreich",
    "qs:name_adm1":"K\u00e4rnten",
    "qs:name_adm2":"Klagenfurt Stadt",
    "qs:name_lau":"Klagenfurt",
    "qs:name_local":"Klagenfurt",
    "qs:photo_max":81,
    "qs:photo_sum":326,
    "qs:placetype":"Suburb",
    "qs:quad_count":23,
    "qs:woe_adm0":23424750,
    "qs:woe_adm1":2344709,
    "qs:woe_adm2":12591676,
    "qs:woe_lau":12673562,
    "qs:woe_local":12673562,
    "qs:woe_ver":"7.10.0",
    "wof:lang":[
        "ger"
    ],
    "wof:name":"Welzenegg Burgfried",
    "wof:placetype":"neighbourhood"
},
  "geometry": {"coordinates":[14.326152,46.619505],"type":"Point"}
}