{
  "type": "Feature",
  "properties": {
    "gn:admin1_code":"04",
    "gn:admin2_code":"404.0",
    "gn:admin3_code":"40427.0",
    "gn:asciiname":"Schuetzing",
    "gn:country_code":"AT",
    "gn:dem":417,
    "gn:feature_class":"P",
    "gn:feature_code":"PPL",
    "gn:name":"Sch\u00fctzing",
    "gn:population":47,
    "gn:timezone":"Europe/Vienna",
    "iso:country":"AT",
    "wof:name":"Schuetzing",
    "wof:placetype":"locality",
    "wof:population":47
},
  "geometry": {"coordinates":[13.04961,48.15526],"type":"Point"}
}