{
  "type": "Feature",
  "properties": {
    "gn:admin1_code":"5.0",
    "gn:admin2_code":"503",
    "gn:admin3_code":"50329.0",
    "gn:asciiname":"Aglassing",
    "gn:country_code":"AT",
    "gn:dem":439,
    "gn:feature_class":"P",
    "gn:feature_code":"PPL",
    "gn:name":"Aglassing",
    "gn:population":56,
    "gn:timezone":"Europe/Vienna",
    "iso:country":"AT",
    "wof:name":"Aglassing",
    "wof:placetype":"locality",
    "wof:population":56
},
  "geometry": {"coordinates":[12.92389,47.96],"type":"Point"}
}