{
  "type": "Feature",
  "properties": {
    "gn:admin1_code":"8.0",
    "gn:admin2_code":"801",
    "gn:admin3_code":"80128.0",
    "gn:asciiname":"Doerfle",
    "gn:country_code":"AT",
    "gn:dem":689,
    "gn:feature_class":"P",
    "gn:feature_code":"PPL",
    "gn:name":"D\u00f6rfle",
    "gn:population":0,
    "gn:timezone":"Europe/Vienna",
    "iso:country":"AT",
    "wof:name":"Doerfle",
    "wof:placetype":"locality"
},
  "geometry": {"coordinates":[9.91667,47.06667],"type":"Point"}
}