{
  "type": "Feature",
  "properties": {
    "gn:admin1_code":"02",
    "gn:admin2_code":"206.0",
    "gn:admin3_code":"20637.0",
    "gn:asciiname":"Pobersach",
    "gn:country_code":"AT",
    "gn:dem":588,
    "gn:feature_class":"P",
    "gn:feature_code":"PPL",
    "gn:name":"Pobersach",
    "gn:population":0,
    "gn:timezone":"Europe/Vienna",
    "iso:country":"AT",
    "wof:name":"Pobersach",
    "wof:placetype":"locality"
},
  "geometry": {"coordinates":[13.21667,46.75],"type":"Point"}
}