{
  "type": "Feature",
  "properties": {
    "gn:admin1_code":"3.0",
    "gn:admin2_code":"315",
    "gn:admin3_code":"31507.0",
    "gn:asciiname":"Gerolding",
    "gn:country_code":"AT",
    "gn:dem":451,
    "gn:feature_class":"P",
    "gn:feature_code":"PPLA3",
    "gn:name":"Gerolding",
    "gn:population":246,
    "gn:timezone":"Europe/Vienna",
    "iso:country":"AT",
    "name:deu_x_preferred":[
        "Gerolding"
    ],
    "wof:name":"Gerolding",
    "wof:placetype":"locality",
    "wof:population":246
},
  "geometry": {"coordinates":[15.41667,48.25],"type":"Point"}
}