{
  "type": "Feature",
  "properties": {
    "gn:admin1_code":"6.0",
    "gn:admin2_code":"623",
    "gn:admin3_code":"62388.0",
    "gn:asciiname":"Oberrosenberg",
    "gn:country_code":"AT",
    "gn:dem":382,
    "gn:feature_class":"P",
    "gn:feature_code":"PPL",
    "gn:name":"Oberrosenberg",
    "gn:population":81,
    "gn:timezone":"Europe/Vienna",
    "iso:country":"AT",
    "wof:name":"Oberrosenberg",
    "wof:placetype":"locality",
    "wof:population":81
},
  "geometry": {"coordinates":[15.73028,46.79327],"type":"Point"}
}