{
  "type": "Feature",
  "properties": {
    "gn:admin1_code":"3.0",
    "gn:admin2_code":"316",
    "gn:admin3_code":"31633.0",
    "gn:asciiname":"Kettlasbrunn",
    "gn:country_code":"AT",
    "gn:dem":221,
    "gn:feature_class":"P",
    "gn:feature_code":"PPL",
    "gn:name":"Kettlasbrunn",
    "gn:population":511,
    "gn:timezone":"Europe/Vienna",
    "iso:country":"AT",
    "wof:name":"Kettlasbrunn",
    "wof:placetype":"locality",
    "wof:population":511
},
  "geometry": {"coordinates":[16.65,48.55],"type":"Point"}
}