{
  "type": "Feature",
  "properties": {
    "gn:admin1_code":"4.0",
    "gn:admin2_code":"417",
    "gn:admin3_code":"41723.0",
    "gn:asciiname":"Forsterreith",
    "gn:country_code":"AT",
    "gn:dem":565,
    "gn:feature_class":"P",
    "gn:feature_code":"PPL",
    "gn:name":"Forsterreith",
    "gn:population":46,
    "gn:timezone":"Europe/Vienna",
    "iso:country":"AT",
    "wof:name":"Forsterreith",
    "wof:placetype":"locality",
    "wof:population":46
},
  "geometry": {"coordinates":[13.45126,48.0205],"type":"Point"}
}