{
  "type": "Feature",
  "properties": {
    "gn:admin1_code":"4.0",
    "gn:admin2_code":"409",
    "gn:admin3_code":"40915.0",
    "gn:asciiname":"Gradau",
    "gn:country_code":"AT",
    "gn:dem":747,
    "gn:feature_class":"P",
    "gn:feature_code":"PPL",
    "gn:name":"Gradau",
    "gn:population":0,
    "gn:timezone":"Europe/Vienna",
    "iso:country":"AT",
    "wof:name":"Gradau",
    "wof:placetype":"locality"
},
  "geometry": {"coordinates":[14.26667,47.73333],"type":"Point"}
}