{
  "type": "Feature",
  "properties": {
    "gn:admin1_code":"03",
    "gn:admin2_code":"305.0",
    "gn:admin3_code":"30516.0",
    "gn:asciiname":"Wenten",
    "gn:country_code":"AT",
    "gn:dem":833,
    "gn:feature_class":"P",
    "gn:feature_code":"PPL",
    "gn:name":"Wenten",
    "gn:population":76,
    "gn:timezone":"Europe/Vienna",
    "iso:country":"AT",
    "wof:name":"Wenten",
    "wof:placetype":"locality",
    "wof:population":76
},
  "geometry": {"coordinates":[14.76667,47.76667],"type":"Point"}
}