{
  "type": "Feature",
  "properties": {
    "gn:admin1_code":"4.0",
    "gn:admin2_code":"415",
    "gn:admin3_code":"41508.0",
    "gn:asciiname":"Sonnleithnersiedlung",
    "gn:country_code":"AT",
    "gn:dem":405,
    "gn:feature_class":"P",
    "gn:feature_code":"PPL",
    "gn:name":"Sonnleithnersiedlung",
    "gn:population":0,
    "gn:timezone":"Europe/Vienna",
    "iso:country":"AT",
    "wof:name":"Sonnleithnersiedlung",
    "wof:placetype":"locality"
},
  "geometry": {"coordinates":[14.43131,47.95119],"type":"Point"}
}