{
  "type": "Feature",
  "properties": {
    "gn:admin1_code":"06",
    "gn:admin2_code":"610.0",
    "gn:admin3_code":"61049.0",
    "gn:asciiname":"Ratsch an der Weinstrasse",
    "gn:cc2":"AT",
    "gn:country_code":"AT",
    "gn:dem":349,
    "gn:feature_class":"P",
    "gn:feature_code":"PPLA3",
    "gn:name":"Ratsch an der Weinstra\u00dfe",
    "gn:population":334,
    "gn:timezone":"Europe/Vienna",
    "iso:country":"AT",
    "name:ceb_x_preferred":[
        "Ratsch an der Weinstra\u00dfe"
    ],
    "name:deu_x_preferred":[
        "Ratsch an der Weinstra\u00dfe"
    ],
    "name:fas_x_preferred":[
        "\u0631\u0627\u0686 \u0622\u0646\u062f\u0631 \u0648\u0627\u06cc\u0646\u0633\u062a\u0631\u0627\u0633"
    ],
    "name:fra_x_preferred":[
        "Ratsch an der Weinstra\u00dfe"
    ],
    "name:ita_x_preferred":[
        "Ratsch an der Weinstra\u00dfe"
    ],
    "name:nld_x_preferred":[
        "Ratsch an der Weinstra\u00dfe"
    ],
    "name:slk_x_preferred":[
        "Ratsch an der Weinstra\u00dfe"
    ],
    "name:swe_x_preferred":[
        "Ratsch an der Weinstra\u00dfe"
    ],
    "name:und_x_variant":[
        "Ratsch",
        "Ratsch an der Weinstra\u00dfe"
    ],
    "name:uzb_x_preferred":[
        "Ratsch an der Weinstra\u00dfe"
    ],
    "name:vie_x_preferred":[
        "Ratsch an der Weinstra\u00dfe"
    ],
    "name:vol_x_preferred":[
        "Ratsch an der Weinstra\u00dfe"
    ],
    "name:war_x_preferred":[
        "Ratsch an der Weinstra\u00dfe"
    ],
    "wof:name":"Ratsch an der Weinstrasse",
    "wof:placetype":"locality",
    "wof:population":334
},
  "geometry": {"coordinates":[15.57111,46.68944000000001],"type":"Point"}
}