{
  "type": "Feature",
  "properties": {
    "gn:admin1_code":"07",
    "gn:admin2_code":"704.0",
    "gn:admin3_code":"70419.0",
    "gn:asciiname":"Winkl",
    "gn:cc2":"AT",
    "gn:country_code":"AT",
    "gn:dem":993,
    "gn:feature_class":"P",
    "gn:feature_code":"PPL",
    "gn:name":"Winkl",
    "gn:population":0,
    "gn:timezone":"Europe/Vienna",
    "iso:country":"AT",
    "name:und_x_variant":[
        "Winkel",
        "Winkl"
    ],
    "wof:name":"Winkl",
    "wof:placetype":"locality"
},
  "geometry": {"coordinates":[12.56667,47.56667],"type":"Point"}
}