{
  "type": "Feature",
  "properties": {
    "gn:admin1_code":"06",
    "gn:admin2_code":"603.0",
    "gn:admin3_code":"60348.0",
    "gn:asciiname":"Rosenhof",
    "gn:country_code":"AT",
    "gn:dem":642,
    "gn:feature_class":"P",
    "gn:feature_code":"PPL",
    "gn:name":"Rosenhof",
    "gn:population":0,
    "gn:timezone":"Europe/Vienna",
    "iso:country":"AT",
    "wof:name":"Rosenhof",
    "wof:placetype":"locality"
},
  "geometry": {"coordinates":[15.21667,46.95],"type":"Point"}
}