{
  "type": "Feature",
  "properties": {
    "gn:admin1_code":"5.0",
    "gn:admin2_code":"504",
    "gn:admin3_code":"50411.0",
    "gn:asciiname":"Kleinellmau",
    "gn:country_code":"AT",
    "gn:dem":1220,
    "gn:feature_class":"P",
    "gn:feature_code":"PPL",
    "gn:name":"Kleinellmau",
    "gn:population":0,
    "gn:timezone":"Europe/Vienna",
    "iso:country":"AT",
    "wof:name":"Kleinellmau",
    "wof:placetype":"locality"
},
  "geometry": {"coordinates":[13.25234,47.23385],"type":"Point"}
}