{
  "type": "Feature",
  "properties": {
    "gn:admin1_code":"5.0",
    "gn:admin2_code":"503",
    "gn:admin3_code":"50304.0",
    "gn:asciiname":"Manglberg",
    "gn:country_code":"AT",
    "gn:dem":558,
    "gn:feature_class":"P",
    "gn:feature_code":"PPL",
    "gn:name":"Manglberg",
    "gn:population":0,
    "gn:timezone":"Europe/Vienna",
    "iso:country":"AT",
    "wof:name":"Manglberg",
    "wof:placetype":"locality"
},
  "geometry": {"coordinates":[13.07694,47.99528],"type":"Point"}
}