{
  "type": "Feature",
  "properties": {
    "gn:admin1_code":"4.0",
    "gn:admin2_code":"412",
    "gn:admin3_code":"41204.0",
    "gn:asciiname":"Putting",
    "gn:country_code":"AT",
    "gn:dem":536,
    "gn:feature_class":"P",
    "gn:feature_code":"PPL",
    "gn:name":"Putting",
    "gn:population":21,
    "gn:timezone":"Europe/Vienna",
    "iso:country":"AT",
    "wof:name":"Putting",
    "wof:placetype":"locality",
    "wof:population":21
},
  "geometry": {"coordinates":[13.5276,48.15289],"type":"Point"}
}