{
  "type": "Feature",
  "properties": {
    "gn:admin1_code":"4.0",
    "gn:admin2_code":"417",
    "gn:admin3_code":"41723.0",
    "gn:asciiname":"Graben",
    "gn:country_code":"AT",
    "gn:dem":530,
    "gn:feature_class":"P",
    "gn:feature_code":"PPL",
    "gn:name":"Graben",
    "gn:population":107,
    "gn:timezone":"Europe/Vienna",
    "iso:country":"AT",
    "wof:name":"Graben",
    "wof:placetype":"locality",
    "wof:population":107
},
  "geometry": {"coordinates":[13.48327,48.01091],"type":"Point"}
}