{
  "type": "Feature",
  "properties": {
    "gn:admin1_code":"4.0",
    "gn:admin2_code":"417",
    "gn:admin3_code":"41723.0",
    "gn:asciiname":"Graben",
    "gn:country_code":"AT",
    "gn:dem":530,
    "gn:feature_class":"P",
    "gn:feature_code":"PPL",
    "gn:name":"Graben",
    "gn:population":107,
    "gn:timezone":"Europe/Vienna",
    "iso:country":"AT",
    "name:afr_x_preferred":[
        "Slenkdal"
    ],
    "name:ara_x_preferred":[
        "\u0635\u062f\u0648\u0639 \u0623\u062e\u062f\u0648\u062f\u064a\u0629"
    ],
    "name:arg_x_preferred":[
        "Fuesa tectonica"
    ],
    "name:bul_x_preferred":[
        "\u0413\u0440\u0430\u0431\u0435\u043d"
    ],
    "name:cat_x_preferred":[
        "Graben"
    ],
    "name:ces_x_preferred":[
        "P\u0159\u00edkop"
    ],
    "name:dan_x_preferred":[
        "Gravs\u00e6nkning"
    ],
    "name:deu_x_preferred":[
        "Graben"
    ],
    "name:epo_x_preferred":[
        "Grabeno"
    ],
    "name:est_x_preferred":[
        "Alang"
    ],
    "name:eus_x_preferred":[
        "Graben"
    ],
    "name:fas_x_preferred":[
        "\u0641\u0631\u0648\u0632\u0645\u06cc\u0646"
    ],
    "name:fra_x_preferred":[
        "Graben"
    ],
    "name:glg_x_preferred":[
        "Fosa tect\u00f3nica"
    ],
    "name:heb_x_preferred":[
        "\u05d2\u05e8\u05d0\u05d1\u05df"
    ],
    "name:hrv_x_preferred":[
        "Tektonski rov"
    ],
    "name:hye_x_preferred":[
        "\u0533\u0580\u0561\u0562\u0565\u0576"
    ],
    "name:ind_x_preferred":[
        "Graben"
    ],
    "name:ita_x_preferred":[
        "Graben"
    ],
    "name:kat_x_preferred":[
        "\u10d2\u10e0\u10d0\u10d1\u10d4\u10dc\u10d8"
    ],
    "name:kaz_x_preferred":[
        "\u0413\u0440\u0430\u0431\u0435\u043d"
    ],
    "name:kor_x_preferred":[
        "\uc9c0\uad6c"
    ],
    "name:lit_x_preferred":[
        "Grabenas"
    ],
    "name:msa_x_preferred":[
        "Graben"
    ],
    "name:nld_x_preferred":[
        "Slenk"
    ],
    "name:nno_x_preferred":[
        "Graben"
    ],
    "name:nor_x_preferred":[
        "Graben"
    ],
    "name:pol_x_preferred":[
        "R\u00f3w tektoniczny"
    ],
    "name:por_x_preferred":[
        "Graben"
    ],
    "name:rus_x_preferred":[
        "\u0413\u0440\u0430\u0431\u0435\u043d"
    ],
    "name:slk_x_preferred":[
        "Priekopov\u00e1 prepadlina"
    ],
    "name:slv_x_preferred":[
        "Tektonski jarek"
    ],
    "name:spa_x_preferred":[
        "Fosa tect\u00f3nica"
    ],
    "name:sqi_x_preferred":[
        "Hendeku tektonik"
    ],
    "name:srp_x_preferred":[
        "\u0413\u0440\u0430\u0431\u0435\u043d"
    ],
    "name:tur_x_preferred":[
        "Graben"
    ],
    "name:ukr_x_preferred":[
        "\u0413\u0440\u0430\u0431\u0435\u043d"
    ],
    "name:vie_x_preferred":[
        "\u0110\u1ecba h\u00e0o"
    ],
    "wof:name":"Graben",
    "wof:placetype":"locality",
    "wof:population":107
},
  "geometry": {"coordinates":[13.48327,48.01091],"type":"Point"}
}