{
  "type": "Feature",
  "properties": {
    "gn:admin1_code":"02",
    "gn:admin2_code":"205.0",
    "gn:admin3_code":"20530.0",
    "gn:asciiname":"Sankt Peter",
    "gn:country_code":"AT",
    "gn:dem":916,
    "gn:feature_class":"P",
    "gn:feature_code":"PPL",
    "gn:name":"Sankt Peter",
    "gn:population":24,
    "gn:timezone":"Europe/Vienna",
    "iso:country":"AT",
    "wof:name":"Sankt Peter",
    "wof:placetype":"locality",
    "wof:population":24
},
  "geometry": {"coordinates":[14.28333,46.88333],"type":"Point"}
}