{
  "type": "Feature",
  "properties": {
    "gn:admin1_code":"4.0",
    "gn:admin2_code":"404",
    "gn:admin3_code":"40402.0",
    "gn:asciiname":"Buchleiting",
    "gn:country_code":"AT",
    "gn:dem":437,
    "gn:feature_class":"P",
    "gn:feature_code":"PPL",
    "gn:name":"Buchleiting",
    "gn:population":20,
    "gn:timezone":"Europe/Vienna",
    "iso:country":"AT",
    "wof:name":"Buchleiting",
    "wof:placetype":"locality",
    "wof:population":20
},
  "geometry": {"coordinates":[13.30393,48.19785],"type":"Point"}
}