{
  "type": "Feature",
  "properties": {
    "gn:admin1_code":"2.0",
    "gn:admin2_code":"207",
    "gn:admin3_code":"20705.0",
    "gn:asciiname":"Erlachbach",
    "gn:country_code":"AT",
    "gn:dem":931,
    "gn:feature_class":"P",
    "gn:feature_code":"PPL",
    "gn:name":"Erlachbach",
    "gn:population":0,
    "gn:timezone":"Europe/Vienna",
    "iso:country":"AT",
    "wof:name":"Erlachbach",
    "wof:placetype":"locality"
},
  "geometry": {"coordinates":[13.61694,46.63139],"type":"Point"}
}