{
  "type": "Feature",
  "properties": {
    "gn:admin1_code":"05",
    "gn:admin2_code":"504.0",
    "gn:admin3_code":"50410.0",
    "gn:asciiname":"Hasling",
    "gn:country_code":"AT",
    "gn:dem":767,
    "gn:feature_class":"P",
    "gn:feature_code":"PPLL",
    "gn:name":"Hasling",
    "gn:population":117,
    "gn:timezone":"Europe/Vienna",
    "iso:country":"AT",
    "wof:name":"Hasling",
    "wof:placetype":"locality",
    "wof:population":117
},
  "geometry": {"coordinates":[13.11667,47.31667],"type":"Point"}
}