{
  "type": "Feature",
  "properties": {
    "gn:admin1_code":"2.0",
    "gn:admin2_code":"207",
    "gn:admin3_code":"20724.0",
    "gn:asciiname":"Kanzelhoehe",
    "gn:country_code":"AT",
    "gn:dem":1511,
    "gn:elevation":"1530.0",
    "gn:feature_class":"P",
    "gn:feature_code":"PPL",
    "gn:name":"Kanzelh\u00f6he",
    "gn:population":33,
    "gn:timezone":"Europe/Vienna",
    "iso:country":"AT",
    "name:deu_x_preferred":[
        "Kanzelh\u00f6he/Gerlitzen"
    ],
    "wof:name":"Kanzelhoehe",
    "wof:placetype":"locality",
    "wof:population":33
},
  "geometry": {"coordinates":[13.90167,46.67833],"type":"Point"}
}