{
  "type": "Feature",
  "properties": {
    "gn:admin1_code":"4.0",
    "gn:admin2_code":"413",
    "gn:admin3_code":"41328.0",
    "gn:asciiname":"Daglesbach",
    "gn:country_code":"AT",
    "gn:dem":596,
    "gn:feature_class":"P",
    "gn:feature_code":"PPL",
    "gn:name":"Daglesbach",
    "gn:population":24,
    "gn:timezone":"Europe/Vienna",
    "iso:country":"AT",
    "wof:name":"Daglesbach",
    "wof:placetype":"locality",
    "wof:population":24
},
  "geometry": {"coordinates":[13.86736,48.52357],"type":"Point"}
}