{
  "type": "Feature",
  "properties": {
    "gn:admin1_code":"4.0",
    "gn:admin2_code":"417",
    "gn:admin3_code":"41708.0",
    "gn:asciiname":"Ramsau",
    "gn:country_code":"AT",
    "gn:dem":589,
    "gn:feature_class":"P",
    "gn:feature_code":"PPL",
    "gn:name":"Ramsau",
    "gn:population":14,
    "gn:timezone":"Europe/Vienna",
    "iso:country":"AT",
    "name:bos_x_preferred":[
        "Ramsau"
    ],
    "name:ceb_x_preferred":[
        "Ramsau"
    ],
    "name:ces_x_preferred":[
        "Ramsau"
    ],
    "name:deu_x_preferred":[
        "Ramsau"
    ],
    "name:fra_x_preferred":[
        "Ramsau"
    ],
    "name:ita_x_preferred":[
        "Ramsau"
    ],
    "name:nld_x_preferred":[
        "Ramsau"
    ],
    "name:pol_x_preferred":[
        "Ramsau"
    ],
    "name:rus_x_preferred":[
        "\u0420\u0430\u043c\u0437\u0430\u0443"
    ],
    "name:spa_x_preferred":[
        "Ramsau"
    ],
    "name:swe_x_preferred":[
        "Ramsau"
    ],
    "wof:name":"Ramsau",
    "wof:placetype":"locality",
    "wof:population":14
},
  "geometry": {"coordinates":[13.40345,48.03468],"type":"Point"}
}