{
  "type": "Feature",
  "properties": {
    "gn:admin1_code":"02",
    "gn:admin2_code":"207.0",
    "gn:admin3_code":"20702.0",
    "gn:asciiname":"Pessendellach",
    "gn:country_code":"AT",
    "gn:dem":652,
    "gn:feature_class":"P",
    "gn:feature_code":"PPL",
    "gn:name":"Pessendellach",
    "gn:population":57,
    "gn:timezone":"Europe/Vienna",
    "iso:country":"AT",
    "wof:name":"Pessendellach",
    "wof:placetype":"locality",
    "wof:population":57
},
  "geometry": {"coordinates":[13.64652,46.54732],"type":"Point"}
}