{
  "type": "Feature",
  "properties": {
    "gn:admin1_code":"4.0",
    "gn:admin2_code":"408",
    "gn:admin3_code":"40819.0",
    "gn:asciiname":"Koeppensteegen",
    "gn:country_code":"AT",
    "gn:dem":428,
    "gn:feature_class":"P",
    "gn:feature_code":"PPL",
    "gn:name":"K\u00f6ppensteegen",
    "gn:population":0,
    "gn:timezone":"Europe/Vienna",
    "iso:country":"AT",
    "wof:name":"Koeppensteegen",
    "wof:placetype":"locality"
},
  "geometry": {"coordinates":[13.74733,48.36646],"type":"Point"}
}