{
  "type": "Feature",
  "properties": {
    "gn:admin1_code":"4.0",
    "gn:admin2_code":"405",
    "gn:admin3_code":"40512.0",
    "gn:asciiname":"Knieparz ob der Leiten",
    "gn:country_code":"AT",
    "gn:dem":596,
    "gn:feature_class":"P",
    "gn:feature_code":"PPL",
    "gn:name":"Knieparz ob der Leiten",
    "gn:population":43,
    "gn:timezone":"Europe/Vienna",
    "iso:country":"AT",
    "wof:name":"Knieparz ob der Leiten",
    "wof:placetype":"locality",
    "wof:population":43
},
  "geometry": {"coordinates":[13.93916,48.36594],"type":"Point"}
}