{
  "type": "Feature",
  "properties": {
    "gn:admin1_code":"8.0",
    "gn:admin2_code":"801",
    "gn:admin3_code":"80118.0",
    "gn:asciiname":"Litze",
    "gn:country_code":"AT",
    "gn:dem":770,
    "gn:feature_class":"P",
    "gn:feature_code":"PPLL",
    "gn:name":"Litze",
    "gn:population":28,
    "gn:timezone":"Europe/Vienna",
    "iso:country":"AT",
    "wof:name":"Litze",
    "wof:placetype":"locality",
    "wof:population":28
},
  "geometry": {"coordinates":[9.86079,47.22073],"type":"Point"}
}