{
  "type": "Feature",
  "properties": {
    "iso:country":"AT",
    "name:deu_x_preferred":[
        "Walserfeld"
    ],
    "name:unk_x_variant":[
        "Walserfeld"
    ],
    "qs:gn_fcode":"PPL",
    "qs:gn_local":0,
    "qs:gn_namadm1":"05",
    "qs:gn_name":"Walserfeld",
    "qs:local_max":138,
    "qs:local_sum":278,
    "qs:localhoods":4,
    "qs:name":"Walserfeld",
    "qs:name_adm0":"\u00d6sterreich",
    "qs:name_adm1":"Salzburg",
    "qs:name_adm2":"Salzburg-Umgebung",
    "qs:name_lau":"Wals-Siezenheim",
    "qs:name_local":"Wals-Siezenheim",
    "qs:photo_max":2,
    "qs:photo_sum":11,
    "qs:placetype":"Suburb",
    "qs:quad_count":9,
    "qs:woe_adm0":23424750,
    "qs:woe_adm1":2344712,
    "qs:woe_adm2":12591721,
    "qs:woe_lau":12674753,
    "qs:woe_local":12674753,
    "qs:woe_ver":"7.10.0",
    "wof:lang":[
        "ger"
    ],
    "wof:name":"Walserfeld",
    "wof:placetype":"neighbourhood"
},
  "geometry": {"coordinates":[12.948303,47.779634],"type":"Point"}
}