{
  "type": "Feature",
  "properties": {
    "gn:admin1_code":"4.0",
    "gn:admin2_code":"414",
    "gn:admin3_code":"41417.0",
    "gn:asciiname":"Voglgrub",
    "gn:country_code":"AT",
    "gn:dem":569,
    "gn:feature_class":"P",
    "gn:feature_code":"PPL",
    "gn:name":"Voglgrub",
    "gn:population":24,
    "gn:timezone":"Europe/Vienna",
    "iso:country":"AT",
    "wof:name":"Voglgrub",
    "wof:placetype":"locality",
    "wof:population":24
},
  "geometry": {"coordinates":[13.70489,48.44876],"type":"Point"}
}