{
  "type": "Feature",
  "properties": {
    "gn:admin1_code":"7.0",
    "gn:admin2_code":"707",
    "gn:admin3_code":"70733.0",
    "gn:asciiname":"Untertilliach",
    "gn:country_code":"AT",
    "gn:dem":1164,
    "gn:feature_class":"P",
    "gn:feature_code":"PPLA3",
    "gn:name":"Untertilliach",
    "gn:population":237,
    "gn:timezone":"Europe/Vienna",
    "iso:country":"AT",
    "name:ceb_x_preferred":[
        "Untertilliach"
    ],
    "name:ces_x_preferred":[
        "Untertilliach"
    ],
    "name:deu_x_preferred":[
        "Untertilliach"
    ],
    "name:est_x_preferred":[
        "Untertilliach"
    ],
    "name:fas_x_preferred":[
        "\u0627\u0646\u062a\u0631\u06cc\u0644\u06cc\u0627\u062e"
    ],
    "name:fra_x_preferred":[
        "Untertilliach"
    ],
    "name:hun_x_preferred":[
        "Untertilliach"
    ],
    "name:ita_x_preferred":[
        "Untertilliach"
    ],
    "name:kaz_x_preferred":[
        "\u0423\u043d\u0442\u0435\u0440\u0442\u0438\u043b\u043b\u0438\u0430\u0445"
    ],
    "name:lmo_x_preferred":[
        "Untertilliach"
    ],
    "name:nld_x_preferred":[
        "Untertilliach"
    ],
    "name:pol_x_preferred":[
        "Untertilliach"
    ],
    "name:rus_x_preferred":[
        "\u0423\u043d\u0442\u0435\u0440\u0442\u0438\u043b\u043b\u0438\u0430\u0445"
    ],
    "name:slk_x_preferred":[
        "Untertilliach"
    ],
    "name:spa_x_preferred":[
        "Untertilliach"
    ],
    "name:swe_x_preferred":[
        "Untertilliach"
    ],
    "name:ukr_x_preferred":[
        "\u0423\u043d\u0442\u0435\u0440\u0442\u0456\u043b\u043b\u0456\u044f\u0445"
    ],
    "name:uzb_x_preferred":[
        "Untertilliach"
    ],
    "name:vol_x_preferred":[
        "Untertilliach"
    ],
    "name:war_x_preferred":[
        "Untertilliach"
    ],
    "name:zho_x_preferred":[
        "\u4e0b\u8482\u5229\u4e9a\u8d6b"
    ],
    "wof:name":"Untertilliach",
    "wof:placetype":"locality",
    "wof:population":237
},
  "geometry": {"coordinates":[12.70861,46.70417],"type":"Point"}
}