{
  "type": "Feature",
  "properties": {
    "gn:admin1_code":"7.0",
    "gn:admin2_code":"707",
    "gn:admin3_code":"70733.0",
    "gn:asciiname":"Untertilliach",
    "gn:country_code":"AT",
    "gn:dem":1164,
    "gn:feature_class":"P",
    "gn:feature_code":"PPLA3",
    "gn:name":"Untertilliach",
    "gn:population":237,
    "gn:timezone":"Europe/Vienna",
    "iso:country":"AT",
    "name:kaz_x_preferred":[
        "\u0423\u043d\u0442\u0435\u0440\u0442\u0438\u043b\u043b\u0438\u0430\u0445"
    ],
    "name:rus_x_preferred":[
        "\u0423\u043d\u0442\u0435\u0440\u0442\u0438\u043b\u043b\u0438\u0430\u0445"
    ],
    "name:ukr_x_preferred":[
        "\u0423\u043d\u0442\u0435\u0440\u0442\u0456\u043b\u043b\u0456\u044f\u0445"
    ],
    "name:zho_x_preferred":[
        "\u4e0b\u8482\u5229\u4e9a\u8d6b"
    ],
    "wof:name":"Untertilliach",
    "wof:placetype":"locality",
    "wof:population":237
},
  "geometry": {"coordinates":[12.70861,46.70417],"type":"Point"}
}