{
  "type": "Feature",
  "properties": {
    "gn:admin1_code":"4.0",
    "gn:admin2_code":"412",
    "gn:admin3_code":"41233.0",
    "gn:asciiname":"Wimm",
    "gn:country_code":"AT",
    "gn:dem":444,
    "gn:feature_class":"P",
    "gn:feature_code":"PPL",
    "gn:name":"Wimm",
    "gn:population":23,
    "gn:timezone":"Europe/Vienna",
    "iso:country":"AT",
    "wof:name":"Wimm",
    "wof:placetype":"locality",
    "wof:population":23
},
  "geometry": {"coordinates":[13.48022,48.26765],"type":"Point"}
}