{
  "type": "Feature",
  "properties": {
    "gn:admin1_code":"2.0",
    "gn:admin2_code":"201",
    "gn:admin3_code":"20101.0",
    "gn:asciiname":"Krottendorf",
    "gn:country_code":"AT",
    "gn:dem":545,
    "gn:feature_class":"P",
    "gn:feature_code":"PPL",
    "gn:name":"Krottendorf",
    "gn:population":0,
    "gn:timezone":"Europe/Vienna",
    "iso:country":"AT",
    "wof:name":"Krottendorf",
    "wof:placetype":"locality"
},
  "geometry": {"coordinates":[14.26667,46.58333],"type":"Point"}
}