{
  "type": "Feature",
  "properties": {
    "gn:admin1_code":"03",
    "gn:admin2_code":"313.0",
    "gn:admin3_code":"31308.0",
    "gn:asciiname":"Sittendorf",
    "gn:country_code":"AT",
    "gn:dem":191,
    "gn:feature_class":"P",
    "gn:feature_code":"PPL",
    "gn:name":"Sittendorf",
    "gn:population":392,
    "gn:timezone":"Europe/Vienna",
    "iso:country":"AT",
    "wof:name":"Sittendorf",
    "wof:placetype":"locality",
    "wof:population":392
},
  "geometry": {"coordinates":[15.73333,48.43333],"type":"Point"}
}