{
  "type": "Feature",
  "properties": {
    "gn:admin1_code":"4.0",
    "gn:admin2_code":"408",
    "gn:admin3_code":"40803.0",
    "gn:asciiname":"Gschwendthaeuser",
    "gn:country_code":"AT",
    "gn:dem":389,
    "gn:feature_class":"P",
    "gn:feature_code":"PPL",
    "gn:name":"Gschwendth\u00e4user",
    "gn:population":0,
    "gn:timezone":"Europe/Vienna",
    "iso:country":"AT",
    "wof:name":"Gschwendthaeuser",
    "wof:placetype":"locality"
},
  "geometry": {"coordinates":[13.77059,48.32165],"type":"Point"}
}