{
  "type": "Feature",
  "properties": {
    "gn:admin1_code":"04",
    "gn:admin2_code":"411.0",
    "gn:admin3_code":"41117.0",
    "gn:asciiname":"Wansch",
    "gn:country_code":"AT",
    "gn:dem":551,
    "gn:feature_class":"P",
    "gn:feature_code":"PPL",
    "gn:name":"Wansch",
    "gn:population":35,
    "gn:timezone":"Europe/Vienna",
    "iso:country":"AT",
    "wof:name":"Wansch",
    "wof:placetype":"locality",
    "wof:population":35
},
  "geometry": {"coordinates":[14.71996,48.30375],"type":"Point"}
}