{
  "type": "Feature",
  "properties": {
    "gn:admin1_code":"3.0",
    "gn:admin2_code":"309",
    "gn:admin3_code":"30940.0",
    "gn:asciiname":"Grosshobarten",
    "gn:country_code":"AT",
    "gn:dem":556,
    "gn:feature_class":"P",
    "gn:feature_code":"PPL",
    "gn:name":"Grossh\u00f6barten",
    "gn:population":0,
    "gn:timezone":"Europe/Vienna",
    "iso:country":"AT",
    "wof:name":"Grosshobarten",
    "wof:placetype":"locality"
},
  "geometry": {"coordinates":[15.03333,48.73333],"type":"Point"}
}