{
  "type": "Feature",
  "properties": {
    "gn:admin1_code":"8.0",
    "gn:admin2_code":"804",
    "gn:admin3_code":"80411.0",
    "gn:asciiname":"Innerlaterns",
    "gn:country_code":"AT",
    "gn:dem":1047,
    "gn:feature_class":"P",
    "gn:feature_code":"PPL",
    "gn:name":"Innerlaterns",
    "gn:population":0,
    "gn:timezone":"Europe/Vienna",
    "iso:country":"AT",
    "wof:name":"Innerlaterns",
    "wof:placetype":"locality"
},
  "geometry": {"coordinates":[9.74246,47.25764],"type":"Point"}
}