{
  "type": "Feature",
  "properties": {
    "gn:admin1_code":"04",
    "gn:admin2_code":"413.0",
    "gn:admin3_code":"41322.0",
    "gn:asciiname":"Roemersdorf",
    "gn:cc2":"AT",
    "gn:country_code":"AT",
    "gn:dem":603,
    "gn:feature_class":"P",
    "gn:feature_code":"PPL",
    "gn:name":"R\u00f6mersdorf",
    "gn:population":30,
    "gn:timezone":"Europe/Vienna",
    "iso:country":"AT",
    "name:und_x_variant":[
        "R\u00f6merstorf",
        "R\u00f6mersdorf"
    ],
    "wof:name":"Roemersdorf",
    "wof:placetype":"locality",
    "wof:population":30
},
  "geometry": {"coordinates":[13.88406,48.49124000000001],"type":"Point"}
}