{
  "type": "Feature",
  "properties": {
    "gn:admin1_code":"3.0",
    "gn:admin2_code":"325",
    "gn:admin3_code":"32530.0",
    "gn:asciiname":"Neuhof",
    "gn:country_code":"AT",
    "gn:dem":639,
    "gn:feature_class":"P",
    "gn:feature_code":"PPL",
    "gn:name":"Neuhof",
    "gn:population":0,
    "gn:timezone":"Europe/Vienna",
    "iso:country":"AT",
    "name:ceb_x_preferred":[
        "Neuhof"
    ],
    "name:deu_x_preferred":[
        "Neuhof"
    ],
    "name:epo_x_preferred":[
        "Neuhof"
    ],
    "name:eus_x_preferred":[
        "Neuhof"
    ],
    "name:fra_x_preferred":[
        "Neuhof"
    ],
    "name:hun_x_preferred":[
        "Neuhof"
    ],
    "name:ita_x_preferred":[
        "Neuhof"
    ],
    "name:lav_x_preferred":[
        "Neuhof"
    ],
    "name:mkd_x_preferred":[
        "\u041d\u043e\u0458\u0445\u043e\u0444"
    ],
    "name:nld_x_preferred":[
        "Neuhof"
    ],
    "name:pol_x_preferred":[
        "Neuhof"
    ],
    "name:rus_x_preferred":[
        "\u041d\u0435\u0439\u0433\u043e\u0444"
    ],
    "name:srp_x_preferred":[
        "\u041d\u043e\u0458\u0445\u043e\u0444"
    ],
    "name:swe_x_preferred":[
        "Neuhof"
    ],
    "name:vol_x_preferred":[
        "Neuhof"
    ],
    "wof:name":"Neuhof",
    "wof:placetype":"locality"
},
  "geometry": {"coordinates":[15.18333,48.58333],"type":"Point"}
}