{
  "type": "Feature",
  "properties": {
    "gn:admin1_code":"3.0",
    "gn:admin2_code":"305",
    "gn:admin3_code":"30515.0",
    "gn:asciiname":"Reinthal",
    "gn:country_code":"AT",
    "gn:dem":554,
    "gn:feature_class":"P",
    "gn:feature_code":"PPL",
    "gn:name":"Reinthal",
    "gn:population":0,
    "gn:timezone":"Europe/Vienna",
    "iso:country":"AT",
    "wof:name":"Reinthal",
    "wof:placetype":"locality"
},
  "geometry": {"coordinates":[14.51217,48.02202],"type":"Point"}
}