{
  "type": "Feature",
  "properties": {
    "gn:admin1_code":"4.0",
    "gn:admin2_code":"408",
    "gn:admin3_code":"40806.0",
    "gn:asciiname":"Mairhof",
    "gn:country_code":"AT",
    "gn:dem":443,
    "gn:feature_class":"P",
    "gn:feature_code":"PPL",
    "gn:name":"Mairhof",
    "gn:population":34,
    "gn:timezone":"Europe/Vienna",
    "iso:country":"AT",
    "wof:name":"Mairhof",
    "wof:placetype":"locality",
    "wof:population":34
},
  "geometry": {"coordinates":[13.71639,48.16297],"type":"Point"}
}