{
  "type": "Feature",
  "properties": {
    "gn:admin1_code":"2.0",
    "gn:admin2_code":"209",
    "gn:admin3_code":"20923.0",
    "gn:asciiname":"Kleinedling",
    "gn:country_code":"AT",
    "gn:dem":439,
    "gn:feature_class":"P",
    "gn:feature_code":"PPL",
    "gn:name":"Kleinedling",
    "gn:population":1840,
    "gn:timezone":"Europe/Vienna",
    "iso:country":"AT",
    "wof:name":"Kleinedling",
    "wof:placetype":"locality",
    "wof:population":1840
},
  "geometry": {"coordinates":[14.82778,46.81417],"type":"Point"}
}