{
  "type": "Feature",
  "properties": {
    "gn:admin1_code":"4.0",
    "gn:admin2_code":"404",
    "gn:admin3_code":"40409.0",
    "gn:asciiname":"Preisenberg",
    "gn:country_code":"AT",
    "gn:dem":454,
    "gn:feature_class":"P",
    "gn:feature_code":"PPL",
    "gn:name":"Preisenberg",
    "gn:population":14,
    "gn:timezone":"Europe/Vienna",
    "iso:country":"AT",
    "wof:name":"Preisenberg",
    "wof:placetype":"locality",
    "wof:population":14
},
  "geometry": {"coordinates":[12.94644,48.08519],"type":"Point"}
}