{
  "type": "Feature",
  "properties": {
    "gn:admin1_code":"4.0",
    "gn:admin2_code":"408",
    "gn:admin3_code":"40803.0",
    "gn:asciiname":"Dunkenedt",
    "gn:country_code":"AT",
    "gn:dem":388,
    "gn:feature_class":"P",
    "gn:feature_code":"PPL",
    "gn:name":"Dunkenedt",
    "gn:population":0,
    "gn:timezone":"Europe/Vienna",
    "iso:country":"AT",
    "wof:name":"Dunkenedt",
    "wof:placetype":"locality"
},
  "geometry": {"coordinates":[13.73772,48.31494],"type":"Point"}
}