{
  "type": "Feature",
  "properties": {
    "gn:admin1_code":"02",
    "gn:admin2_code":"204.0",
    "gn:admin3_code":"20403.0",
    "gn:asciiname":"Wellersdorf",
    "gn:country_code":"AT",
    "gn:dem":445,
    "gn:feature_class":"P",
    "gn:feature_code":"PPL",
    "gn:name":"Wellersdorf",
    "gn:population":0,
    "gn:timezone":"Europe/Vienna",
    "iso:country":"AT",
    "name:deu_x_preferred":[
        "Wellersdorf"
    ],
    "name:slv_x_preferred":[
        "Velinja Ves"
    ],
    "wof:name":"Wellersdorf",
    "wof:placetype":"locality"
},
  "geometry": {"coordinates":[14.18333,46.53333],"type":"Point"}
}