{
  "type": "Feature",
  "properties": {
    "gn:admin1_code":"4.0",
    "gn:admin2_code":"407",
    "gn:admin3_code":"40720.0",
    "gn:asciiname":"Falkenohren",
    "gn:country_code":"AT",
    "gn:dem":452,
    "gn:feature_class":"P",
    "gn:feature_code":"PPL",
    "gn:name":"Falkenohren",
    "gn:population":0,
    "gn:timezone":"Europe/Vienna",
    "iso:country":"AT",
    "wof:name":"Falkenohren",
    "wof:placetype":"locality"
},
  "geometry": {"coordinates":[13.9014,47.9867],"type":"Point"}
}