{
  "type": "Feature",
  "properties": {
    "gn:admin1_code":"4.0",
    "gn:admin2_code":"408",
    "gn:admin3_code":"40810.0",
    "gn:asciiname":"Irrenedt",
    "gn:country_code":"AT",
    "gn:dem":390,
    "gn:feature_class":"P",
    "gn:feature_code":"PPL",
    "gn:name":"Irrenedt",
    "gn:population":17,
    "gn:timezone":"Europe/Vienna",
    "iso:country":"AT",
    "wof:name":"Irrenedt",
    "wof:placetype":"locality",
    "wof:population":17
},
  "geometry": {"coordinates":[13.82359,48.37455],"type":"Point"}
}