{
  "type": "Feature",
  "properties": {
    "gn:admin1_code":"2.0",
    "gn:admin2_code":"207",
    "gn:admin3_code":"20711.0",
    "gn:asciiname":"Goritschach",
    "gn:country_code":"AT",
    "gn:dem":626,
    "gn:feature_class":"P",
    "gn:feature_code":"PPL",
    "gn:name":"Goritschach",
    "gn:population":143,
    "gn:timezone":"Europe/Vienna",
    "iso:country":"AT",
    "wof:name":"Goritschach",
    "wof:placetype":"locality",
    "wof:population":143
},
  "geometry": {"coordinates":[13.86153,46.55355],"type":"Point"}
}