{
  "type": "Feature",
  "properties": {
    "gn:admin1_code":"4.0",
    "gn:admin2_code":"413",
    "gn:admin3_code":"41339.0",
    "gn:asciiname":"Geiselreith",
    "gn:country_code":"AT",
    "gn:dem":629,
    "gn:feature_class":"P",
    "gn:feature_code":"PPL",
    "gn:name":"Geiselreith",
    "gn:population":0,
    "gn:timezone":"Europe/Vienna",
    "iso:country":"AT",
    "wof:name":"Geiselreith",
    "wof:placetype":"locality"
},
  "geometry": {"coordinates":[13.96045,48.62315],"type":"Point"}
}