{
  "type": "Feature",
  "properties": {
    "gn:admin1_code":"4.0",
    "gn:admin2_code":"411",
    "gn:admin3_code":"41126.0",
    "gn:asciiname":"Lehenbrunn",
    "gn:country_code":"AT",
    "gn:dem":349,
    "gn:feature_class":"P",
    "gn:feature_code":"PPL",
    "gn:name":"Lehenbrunn",
    "gn:population":0,
    "gn:timezone":"Europe/Vienna",
    "iso:country":"AT",
    "wof:name":"Lehenbrunn",
    "wof:placetype":"locality"
},
  "geometry": {"coordinates":[14.66786,48.26223],"type":"Point"}
}