{
  "type": "Feature",
  "properties": {
    "gn:admin1_code":"3.0",
    "gn:admin2_code":"309",
    "gn:admin3_code":"30916.0",
    "gn:asciiname":"Neuthaures",
    "gn:country_code":"AT",
    "gn:dem":566,
    "gn:feature_class":"P",
    "gn:feature_code":"PPL",
    "gn:name":"Neuthaures",
    "gn:population":0,
    "gn:timezone":"Europe/Vienna",
    "iso:country":"AT",
    "wof:name":"Neuthaures",
    "wof:placetype":"locality"
},
  "geometry": {"coordinates":[15.06667,48.88333],"type":"Point"}
}