{
  "type": "Feature",
  "properties": {
    "gn:admin1_code":"06",
    "gn:admin2_code":"606.0",
    "gn:admin3_code":"60665.0",
    "gn:asciiname":"Reiteregg",
    "gn:country_code":"AT",
    "gn:dem":411,
    "gn:feature_class":"P",
    "gn:feature_code":"PPL",
    "gn:name":"Reiteregg",
    "gn:population":0,
    "gn:timezone":"Europe/Vienna",
    "iso:country":"AT",
    "wof:name":"Reiteregg",
    "wof:placetype":"locality"
},
  "geometry": {"coordinates":[15.26667,47.03333],"type":"Point"}
}