{
  "type": "Feature",
  "properties": {
    "gn:admin1_code":"06",
    "gn:admin2_code":"610.0",
    "gn:admin3_code":"61023.0",
    "gn:asciiname":"Remschnigg",
    "gn:country_code":"AT",
    "gn:dem":388,
    "gn:feature_class":"P",
    "gn:feature_code":"PPL",
    "gn:name":"Remschnigg",
    "gn:population":0,
    "gn:timezone":"Europe/Vienna",
    "iso:country":"AT",
    "wof:name":"Remschnigg",
    "wof:placetype":"locality"
},
  "geometry": {"coordinates":[15.42976,46.66454],"type":"Point"}
}