{
  "type": "Feature",
  "properties": {
    "gn:admin1_code":"6.0",
    "gn:admin2_code":"616",
    "gn:admin3_code":"61612.0",
    "gn:asciiname":"Oberschrottner",
    "gn:country_code":"AT",
    "gn:dem":671,
    "gn:feature_class":"P",
    "gn:feature_code":"PPL",
    "gn:name":"Oberschr\u00f6ttner",
    "gn:population":0,
    "gn:timezone":"Europe/Vienna",
    "iso:country":"AT",
    "wof:name":"Oberschrottner",
    "wof:placetype":"locality"
},
  "geometry": {"coordinates":[15.15861,46.99139],"type":"Point"}
}