{
  "type": "Feature",
  "properties": {
    "gn:admin1_code":"7.0",
    "gn:admin2_code":"702",
    "gn:admin3_code":"70217.0",
    "gn:asciiname":"Bichl",
    "gn:country_code":"AT",
    "gn:dem":1320,
    "gn:feature_class":"P",
    "gn:feature_code":"PPL",
    "gn:name":"Bichl",
    "gn:population":0,
    "gn:timezone":"Europe/Vienna",
    "iso:country":"AT",
    "name:ara_x_preferred":[
        "\u0628\u064a\u0634\u0644"
    ],
    "name:ceb_x_preferred":[
        "Bichl"
    ],
    "name:deu_x_preferred":[
        "Bichl"
    ],
    "name:epo_x_preferred":[
        "Bichl"
    ],
    "name:eus_x_preferred":[
        "Bichl"
    ],
    "name:fas_x_preferred":[
        "\u0628\u06cc\u0634\u0644"
    ],
    "name:fra_x_preferred":[
        "Bichl"
    ],
    "name:hun_x_preferred":[
        "Bichl"
    ],
    "name:hye_x_preferred":[
        "\u0532\u056b\u056d\u056c"
    ],
    "name:ita_x_preferred":[
        "Bichl"
    ],
    "name:lat_x_preferred":[
        "Bichl"
    ],
    "name:lmo_x_preferred":[
        "Bichl"
    ],
    "name:msa_x_preferred":[
        "Bichl"
    ],
    "name:nld_x_preferred":[
        "Bichl"
    ],
    "name:pol_x_preferred":[
        "Bichl"
    ],
    "name:por_x_preferred":[
        "Bichl"
    ],
    "name:ron_x_preferred":[
        "Bichl"
    ],
    "name:rus_x_preferred":[
        "\u0411\u0438\u0445\u043b\u044c"
    ],
    "name:spa_x_preferred":[
        "Bichl"
    ],
    "name:srp_x_preferred":[
        "\u0411\u0438\u0445\u043b"
    ],
    "name:ukr_x_preferred":[
        "\u0411\u0456\u0445\u043b\u044c"
    ],
    "name:uzb_x_preferred":[
        "Bichl"
    ],
    "name:vie_x_preferred":[
        "Bichl"
    ],
    "name:vol_x_preferred":[
        "Bichl"
    ],
    "name:war_x_preferred":[
        "Bichl"
    ],
    "name:zho_x_preferred":[
        "\u6bd4\u5e0c\u5c14"
    ],
    "wof:name":"Bichl",
    "wof:placetype":"locality"
},
  "geometry": {"coordinates":[10.83333,47.08333],"type":"Point"}
}