{
  "type": "Feature",
  "properties": {
    "gn:admin1_code":"03",
    "gn:admin2_code":"315.0",
    "gn:admin3_code":"31551.0",
    "gn:asciiname":"Texing",
    "gn:country_code":"AT",
    "gn:dem":356,
    "gn:feature_class":"P",
    "gn:feature_code":"PPL",
    "gn:name":"Texing",
    "gn:population":322,
    "gn:timezone":"Europe/Vienna",
    "iso:country":"AT",
    "wof:name":"Texing",
    "wof:placetype":"locality",
    "wof:population":322
},
  "geometry": {"coordinates":[15.32421,48.04882],"type":"Point"}
}