{
  "type": "Feature",
  "properties": {
    "gn:admin1_code":"03",
    "gn:admin2_code":"313.0",
    "gn:admin3_code":"31343.0",
    "gn:asciiname":"Priel",
    "gn:country_code":"AT",
    "gn:dem":366,
    "gn:feature_class":"P",
    "gn:feature_code":"PPL",
    "gn:name":"Priel",
    "gn:population":178,
    "gn:timezone":"Europe/Vienna",
    "iso:country":"AT",
    "wof:name":"Priel",
    "wof:placetype":"locality",
    "wof:population":178
},
  "geometry": {"coordinates":[15.56667,48.45],"type":"Point"}
}