{
  "type": "Feature",
  "properties": {
    "gn:admin1_code":"3.0",
    "gn:admin2_code":"325",
    "gn:admin3_code":"32530.0",
    "gn:asciiname":"Niederneustift",
    "gn:country_code":"AT",
    "gn:dem":655,
    "gn:feature_class":"P",
    "gn:feature_code":"PPL",
    "gn:name":"Niederneustift",
    "gn:population":291,
    "gn:timezone":"Europe/Vienna",
    "iso:country":"AT",
    "wof:name":"Niederneustift",
    "wof:placetype":"locality",
    "wof:population":291
},
  "geometry": {"coordinates":[15.05427,48.60235],"type":"Point"}
}