{
  "type": "Feature",
  "properties": {
    "gn:admin1_code":"03",
    "gn:admin2_code":"315.0",
    "gn:admin3_code":"31519.0",
    "gn:asciiname":"Weitenegg",
    "gn:country_code":"AT",
    "gn:dem":213,
    "gn:feature_class":"P",
    "gn:feature_code":"PPL",
    "gn:name":"Weitenegg",
    "gn:population":43,
    "gn:timezone":"Europe/Vienna",
    "iso:country":"AT",
    "wof:name":"Weitenegg",
    "wof:placetype":"locality",
    "wof:population":43
},
  "geometry": {"coordinates":[15.29692,48.23013],"type":"Point"}
}