{
  "type": "Feature",
  "properties": {
    "gn:admin1_code":"6.0",
    "gn:admin2_code":"606",
    "gn:admin3_code":"60651.0",
    "gn:asciiname":"Land-UEbelbach",
    "gn:country_code":"AT",
    "gn:dem":566,
    "gn:feature_class":"P",
    "gn:feature_code":"PPL",
    "gn:name":"Land-\u00dcbelbach",
    "gn:population":587,
    "gn:timezone":"Europe/Vienna",
    "iso:country":"AT",
    "wof:name":"Land-UEbelbach",
    "wof:placetype":"locality",
    "wof:population":587
},
  "geometry": {"coordinates":[15.25855,47.22105],"type":"Point"}
}