{
  "type": "Feature",
  "properties": {
    "gn:admin1_code":"5.0",
    "gn:admin2_code":"503",
    "gn:admin3_code":"50330.0",
    "gn:asciiname":"Unterburgau",
    "gn:country_code":"AT",
    "gn:dem":494,
    "gn:feature_class":"P",
    "gn:feature_code":"PPL",
    "gn:name":"Unterburgau",
    "gn:population":29,
    "gn:timezone":"Europe/Vienna",
    "iso:country":"AT",
    "wof:name":"Unterburgau",
    "wof:placetype":"locality",
    "wof:population":29
},
  "geometry": {"coordinates":[13.51112,47.79344],"type":"Point"}
}