{
  "type": "Feature",
  "properties": {
    "iso:country":"AT",
    "name:bar_x_preferred":[
        "Golling"
    ],
    "name:ceb_x_preferred":[
        "Golling an der Salzach"
    ],
    "name:chi_x_preferred":[
        "Golling an der Salzach"
    ],
    "name:deu_x_preferred":[
        "Golling an der Salzach"
    ],
    "name:dut_x_preferred":[
        "Golling an der Salzach"
    ],
    "name:eng_x_preferred":[
        "Golling"
    ],
    "name:fra_x_preferred":[
        "Golling an der Salzach"
    ],
    "name:fre_x_preferred":[
        "Golling an der Salzach"
    ],
    "name:ger_x_preferred":[
        "Golling an der Salzach"
    ],
    "name:hun_x_preferred":[
        "Golling an der Salzach"
    ],
    "name:ita_x_preferred":[
        "Golling an der Salzach"
    ],
    "name:kaz_x_preferred":[
        "\u0413\u043e\u043b\u043b\u0438\u043d\u0433-\u043d\u0430-\u0417\u0430\u043b\u044c\u0446\u0430\u0445\u0435"
    ],
    "name:nld_x_preferred":[
        "Golling an der Salzach"
    ],
    "name:pol_x_preferred":[
        "Golling an der Salzach"
    ],
    "name:rus_x_preferred":[
        "\u0413\u043e\u043b\u043b\u0438\u043d\u0433-\u0430\u043d-\u0434\u0435\u0440-\u0417\u0430\u043b\u044c\u0446\u0430\u0445"
    ],
    "name:rus_x_variant":[
        "\u0413\u043e\u043b\u043b\u0438\u043d\u0433-\u043d\u0430-\u0417\u0430\u043b\u044c\u0446\u0430\u0445\u0435"
    ],
    "name:slk_x_preferred":[
        "Golling an der Salzach"
    ],
    "name:slo_x_preferred":[
        "Golling an der Salzach"
    ],
    "name:swe_x_preferred":[
        "Golling an der Salzach"
    ],
    "name:ukr_x_preferred":[
        "\u0413\u043e\u043b\u043b\u0456\u043d\u0433-\u0430\u043d-\u0434\u0435\u0440-\u0417\u0430\u043b\u044c\u0446\u0430\u0445"
    ],
    "name:unk_x_variant":[
        "Golling"
    ],
    "name:uzb_x_preferred":[
        "Golling an der Salzach"
    ],
    "name:vol_x_preferred":[
        "Golling an der Salzach"
    ],
    "name:war_x_preferred":[
        "Golling an der Salzach"
    ],
    "name:zho_x_preferred":[
        "\u8428\u5c14\u5bdf\u8d6b\u6cb3\u7554\u6208\u7075"
    ],
    "qs:a0":"\u00d6sterreich",
    "qs:a1":"*Salzburg",
    "qs:a1r":"0",
    "qs:a2":"Hallein",
    "qs:adm0":"\u00d6sterreich",
    "qs:la_lc":"*",
    "qs:level":"locality",
    "qs:loc":"Golling an der Salzach",
    "qs:loc_alt":"Golling an der Salzach",
    "qs:pop":0,
    "qs:type":"buffered point",
    "wd:wordcount":471,
    "wof:lang":[
        "ger"
    ],
    "wof:name":"Golling an der Salzach",
    "wof:placetype":"locality"
},
  "geometry": {"coordinates":[13.177959,47.597929],"type":"Point"}
}