{
  "type": "Feature",
  "properties": {
    "gn:admin1_code":"4.0",
    "gn:admin2_code":"408",
    "gn:admin3_code":"40809.0",
    "gn:asciiname":"Starhemberg",
    "gn:country_code":"AT",
    "gn:dem":522,
    "gn:feature_class":"P",
    "gn:feature_code":"PPL",
    "gn:name":"Starhemberg",
    "gn:population":40,
    "gn:timezone":"Europe/Vienna",
    "iso:country":"AT",
    "wof:name":"Starhemberg",
    "wof:placetype":"locality",
    "wof:population":40
},
  "geometry": {"coordinates":[13.64081,48.18632],"type":"Point"}
}