{
  "type": "Feature",
  "properties": {
    "gn:admin1_code":"02",
    "gn:admin2_code":"205.0",
    "gn:admin3_code":"20515.0",
    "gn:asciiname":"Pflugern",
    "gn:country_code":"AT",
    "gn:dem":952,
    "gn:feature_class":"P",
    "gn:feature_code":"PPL",
    "gn:name":"Pflugern",
    "gn:population":28,
    "gn:timezone":"Europe/Vienna",
    "iso:country":"AT",
    "wof:name":"Pflugern",
    "wof:placetype":"locality",
    "wof:population":28
},
  "geometry": {"coordinates":[14.27917,46.76917],"type":"Point"}
}