{
  "type": "Feature",
  "properties": {
    "gn:admin1_code":"9.0",
    "gn:admin2_code":"900",
    "gn:admin3_code":"914.0",
    "gn:asciiname":"Hinterhainbach",
    "gn:country_code":"AT",
    "gn:dem":388,
    "gn:feature_class":"P",
    "gn:feature_code":"PPL",
    "gn:name":"Hinterhainbach",
    "gn:population":0,
    "gn:timezone":"Europe/Vienna",
    "iso:country":"AT",
    "wof:name":"Hinterhainbach",
    "wof:placetype":"locality"
},
  "geometry": {"coordinates":[16.21724,48.2472],"type":"Point"}
}