{
  "type": "Feature",
  "properties": {
    "gn:admin1_code":"6.0",
    "gn:admin2_code":"610",
    "gn:admin3_code":"61056.0",
    "gn:asciiname":"Labuttendorf",
    "gn:country_code":"AT",
    "gn:dem":280,
    "gn:feature_class":"P",
    "gn:feature_code":"PPL",
    "gn:name":"Labuttendorf",
    "gn:population":169,
    "gn:timezone":"Europe/Vienna",
    "iso:country":"AT",
    "wof:name":"Labuttendorf",
    "wof:placetype":"locality",
    "wof:population":169
},
  "geometry": {"coordinates":[15.64111,46.78528],"type":"Point"}
}