{
  "type": "Feature",
  "properties": {
    "gn:admin1_code":"06",
    "gn:admin2_code":"623.0",
    "gn:admin3_code":"62379.0",
    "gn:asciiname":"Reiting",
    "gn:country_code":"AT",
    "gn:dem":327,
    "gn:feature_class":"P",
    "gn:feature_code":"PPL",
    "gn:name":"Reiting",
    "gn:population":113,
    "gn:timezone":"Europe/Vienna",
    "iso:country":"AT",
    "wof:name":"Reiting",
    "wof:placetype":"locality",
    "wof:population":113
},
  "geometry": {"coordinates":[15.87145,46.9192],"type":"Point"}
}