{
  "type": "Feature",
  "properties": {
    "gn:admin1_code":"5.0",
    "gn:admin2_code":"503",
    "gn:admin3_code":"50339.0",
    "gn:asciiname":"Moedlham",
    "gn:country_code":"AT",
    "gn:dem":593,
    "gn:feature_class":"P",
    "gn:feature_code":"PPL",
    "gn:name":"M\u00f6dlham",
    "gn:population":454,
    "gn:timezone":"Europe/Vienna",
    "iso:country":"AT",
    "wof:name":"Moedlham",
    "wof:placetype":"locality",
    "wof:population":454
},
  "geometry": {"coordinates":[13.05667,47.89889],"type":"Point"}
}