{
  "type": "Feature",
  "properties": {
    "gn:admin1_code":"5.0",
    "gn:admin2_code":"506",
    "gn:admin3_code":"50627.0",
    "gn:asciiname":"Frohnwies",
    "gn:country_code":"AT",
    "gn:dem":953,
    "gn:feature_class":"P",
    "gn:feature_code":"PPL",
    "gn:name":"Frohnwies",
    "gn:population":47,
    "gn:timezone":"Europe/Vienna",
    "iso:country":"AT",
    "wof:name":"Frohnwies",
    "wof:placetype":"locality",
    "wof:population":47
},
  "geometry": {"coordinates":[12.75,47.51667],"type":"Point"}
}