{
  "type": "Feature",
  "properties": {
    "gn:admin1_code":"3.0",
    "gn:admin2_code":"305",
    "gn:admin3_code":"30534.0",
    "gn:asciiname":"Bruderberg",
    "gn:country_code":"AT",
    "gn:dem":351,
    "gn:feature_class":"P",
    "gn:feature_code":"PPL",
    "gn:name":"Bruderberg",
    "gn:population":0,
    "gn:timezone":"Europe/Vienna",
    "iso:country":"AT",
    "wof:name":"Bruderberg",
    "wof:placetype":"locality"
},
  "geometry": {"coordinates":[14.66667,48.11667],"type":"Point"}
}