{
  "type": "Feature",
  "properties": {
    "gn:admin1_code":"05",
    "gn:admin2_code":"505.0",
    "gn:admin3_code":"50503.0",
    "gn:asciiname":"Vordergoriach",
    "gn:country_code":"AT",
    "gn:dem":1265,
    "gn:feature_class":"P",
    "gn:feature_code":"PPL",
    "gn:name":"Vorderg\u00f6riach",
    "gn:population":0,
    "gn:timezone":"Europe/Vienna",
    "iso:country":"AT",
    "wof:name":"Vordergoriach",
    "wof:placetype":"locality"
},
  "geometry": {"coordinates":[13.75,47.16667],"type":"Point"}
}