{
  "type": "Feature",
  "properties": {
    "gn:admin1_code":"6.0",
    "gn:admin2_code":"616",
    "gn:admin3_code":"61628.0",
    "gn:asciiname":"Lercheck",
    "gn:cc2":"AT",
    "gn:country_code":"AT",
    "gn:dem":634,
    "gn:feature_class":"P",
    "gn:feature_code":"PPL",
    "gn:name":"Lercheck",
    "gn:population":0,
    "gn:timezone":"Europe/Vienna",
    "iso:country":"AT",
    "name:und_x_variant":[
        "Lerchegg",
        "Lercheck"
    ],
    "wof:name":"Lercheck",
    "wof:placetype":"locality"
},
  "geometry": {"coordinates":[15.18333,47.11667],"type":"Point"}
}