{
  "type": "Feature",
  "properties": {
    "gn:admin1_code":"8.0",
    "gn:admin2_code":"801",
    "gn:admin3_code":"80118.0",
    "gn:asciiname":"Plazera",
    "gn:country_code":"AT",
    "gn:dem":883,
    "gn:feature_class":"P",
    "gn:feature_code":"PPL",
    "gn:name":"Plazera",
    "gn:population":17,
    "gn:timezone":"Europe/Vienna",
    "iso:country":"AT",
    "wof:name":"Plazera",
    "wof:placetype":"locality",
    "wof:population":17
},
  "geometry": {"coordinates":[9.85418,47.21578],"type":"Point"}
}