{
  "type": "Feature",
  "properties": {
    "gn:admin1_code":"4.0",
    "gn:admin2_code":"415",
    "gn:admin3_code":"41509.0",
    "gn:asciiname":"Doellergraben",
    "gn:country_code":"AT",
    "gn:dem":552,
    "gn:feature_class":"P",
    "gn:feature_code":"PPL",
    "gn:name":"D\u00f6llergraben",
    "gn:population":0,
    "gn:timezone":"Europe/Vienna",
    "iso:country":"AT",
    "wof:name":"Doellergraben",
    "wof:placetype":"locality"
},
  "geometry": {"coordinates":[14.4344,47.9325],"type":"Point"}
}