{
  "type": "Feature",
  "properties": {
    "iso:country":"AT",
    "name:deu_x_preferred":[
        "Sankt Peter"
    ],
    "name:deu_x_variant":[
        "St. Peter"
    ],
    "name:eng_x_preferred":[
        "Sankt Peter"
    ],
    "wof:name":"Sankt Peter",
    "wof:placetype":"neighbourhood"
},
  "geometry": {"coordinates":[15.47255517792998,47.05519892987517],"type":"Point"}
}