{
  "type": "Feature",
  "properties": {
    "gn:admin1_code":"06",
    "gn:admin2_code":"620.0",
    "gn:admin3_code":"62021.0",
    "gn:asciiname":"Scharnitzgraben",
    "gn:country_code":"AT",
    "gn:dem":1373,
    "gn:feature_class":"P",
    "gn:feature_code":"PPL",
    "gn:name":"Scharnitzgraben",
    "gn:population":0,
    "gn:timezone":"Europe/Vienna",
    "iso:country":"AT",
    "wof:name":"Scharnitzgraben",
    "wof:placetype":"locality"
},
  "geometry": {"coordinates":[14.33333,47.33333],"type":"Point"}
}