{
  "type": "Feature",
  "properties": {
    "gn:admin1_code":"3.0",
    "gn:admin2_code":"320",
    "gn:admin3_code":"32017.0",
    "gn:asciiname":"Pellendorf",
    "gn:country_code":"AT",
    "gn:dem":327,
    "gn:feature_class":"P",
    "gn:feature_code":"PPL",
    "gn:name":"Pellendorf",
    "gn:population":16,
    "gn:timezone":"Europe/Vienna",
    "iso:country":"AT",
    "wof:name":"Pellendorf",
    "wof:placetype":"locality",
    "wof:population":16
},
  "geometry": {"coordinates":[15.18898,48.12156],"type":"Point"}
}