{
  "type": "Feature",
  "properties": {
    "iso:country":"AT",
    "name:ceb_x_preferred":[
        "Weinburg am Sa\u00dfbach"
    ],
    "name:deu_x_preferred":[
        "Weinburg am Sa\u00dfbach"
    ],
    "name:eng_x_preferred":[
        "Weinburg am Sa\u00dfbach"
    ],
    "name:fas_x_preferred":[
        "\u0648\u0627\u06cc\u0646\u0628\u0648\u0631\u06af \u0627\u0645 \u0633\u0627\u0633\u0628\u0627\u062e"
    ],
    "name:fra_x_preferred":[
        "Weinburg am Sa\u00dfbach"
    ],
    "name:hun_x_preferred":[
        "Weinburg am Sa\u00dfbach"
    ],
    "name:ita_x_preferred":[
        "Weinburg am Sa\u00dfbach"
    ],
    "name:kaz_x_preferred":[
        "\u0412\u0430\u0439\u043d\u0431\u0443\u0440\u0433-\u043d\u0430-\u0417\u0430\u0441\u0431\u0430\u0445\u0435"
    ],
    "name:nld_x_preferred":[
        "Weinburg am Sa\u00dfbach"
    ],
    "name:rus_x_preferred":[
        "\u0412\u0430\u0439\u043d\u0431\u0443\u0440\u0433-\u043d\u0430-\u0417\u0430\u0441\u0431\u0430\u0445\u0435"
    ],
    "name:slk_x_preferred":[
        "Weinburg am Sa\u00dfbach"
    ],
    "name:spa_x_preferred":[
        "Weinburg am Sa\u00dfbach"
    ],
    "name:swe_x_preferred":[
        "Weinburg am Sa\u00dfbach"
    ],
    "name:uzb_x_preferred":[
        "Weinburg am Sa\u00dfbach"
    ],
    "name:vie_x_preferred":[
        "Weinburg am Sa\u00dfbach"
    ],
    "name:vol_x_preferred":[
        "Weinburg am Sa\u00dfbach"
    ],
    "name:war_x_preferred":[
        "Weinburg am Sa\u00dfbach"
    ],
    "name:zho_x_preferred":[
        "Weinburg am Sa\u00dfbach"
    ],
    "qs_pg:aaroncc":"AT",
    "qs_pg:name":"Weinburg am Sa\u00dfbach",
    "qs_pg:name_adm0":"\u00d6sterreich",
    "qs_pg:name_adm1":"Steiermark",
    "qs_pg:photos":22,
    "qs_pg:photos_1k":4,
    "qs_pg:photos_9k":1,
    "qs_pg:photos_9r":1,
    "qs_pg:photos_all":22,
    "qs_pg:photos_sr":1,
    "qs_pg:pop_sr":0,
    "qs_pg:qs_pg_placetype":"locality",
    "qs_pg:qs_pg_placetype_gp":"Town",
    "qs_pg:woe_adm0":23424750,
    "woe:adm0_id":23424750,
    "woe:name_adm0":"\u00d6sterreich",
    "woe:name_adm1":"Steiermark",
    "woe:placetype":"Town",
    "wof:name":"Weinburg am Sa\u00dfbach",
    "wof:placetype":"locality"
},
  "geometry": {"coordinates":[15.7090755,46.765603],"type":"Point"}
}