{
  "type": "Feature",
  "properties": {
    "gn:admin1_code":"04",
    "gn:admin2_code":"409.0",
    "gn:admin3_code":"40903.0",
    "gn:asciiname":"Loigistal",
    "gn:country_code":"AT",
    "gn:dem":619,
    "gn:feature_class":"P",
    "gn:feature_code":"PPL",
    "gn:name":"Loigistal",
    "gn:population":0,
    "gn:timezone":"Europe/Vienna",
    "iso:country":"AT",
    "wof:name":"Loigistal",
    "wof:placetype":"locality"
},
  "geometry": {"coordinates":[14.17532,47.70367],"type":"Point"}
}