{
  "type": "Feature",
  "properties": {
    "gn:admin1_code":"3.0",
    "gn:admin2_code":"322",
    "gn:admin3_code":"32216.0",
    "gn:asciiname":"Oberndorf Bei Weikertschlag",
    "gn:country_code":"AT",
    "gn:dem":459,
    "gn:elevation":"0.0",
    "gn:feature_class":"P",
    "gn:feature_code":"PPL",
    "gn:name":"Oberndorf Bei Weikertschlag",
    "gn:population":0,
    "gn:timezone":"Europe/Vienna",
    "iso:country":"AT",
    "wof:name":"Oberndorf Bei Weikertschlag",
    "wof:placetype":"locality"
},
  "geometry": {"coordinates":[15.46474,48.9119],"type":"Point"}
}