{
  "type": "Feature",
  "properties": {
    "gn:admin1_code":"4.0",
    "gn:admin2_code":"412",
    "gn:admin3_code":"41209.0",
    "gn:asciiname":"Roith",
    "gn:country_code":"AT",
    "gn:dem":491,
    "gn:feature_class":"P",
    "gn:feature_code":"PPL",
    "gn:name":"Roith",
    "gn:population":69,
    "gn:timezone":"Europe/Vienna",
    "iso:country":"AT",
    "wof:name":"Roith",
    "wof:placetype":"locality",
    "wof:population":69
},
  "geometry": {"coordinates":[13.54275,48.20666],"type":"Point"}
}