{
  "type": "Feature",
  "properties": {
    "gn:admin1_code":"3.0",
    "gn:admin2_code":"310",
    "gn:admin3_code":"31037.0",
    "gn:asciiname":"Obernalb",
    "gn:country_code":"AT",
    "gn:dem":246,
    "gn:feature_class":"P",
    "gn:feature_code":"PPL",
    "gn:name":"Obernalb",
    "gn:population":490,
    "gn:timezone":"Europe/Vienna",
    "iso:country":"AT",
    "wof:name":"Obernalb",
    "wof:placetype":"locality",
    "wof:population":490
},
  "geometry": {"coordinates":[15.93919,48.74651],"type":"Point"}
}