{
  "type": "Feature",
  "properties": {
    "gn:admin1_code":"05",
    "gn:admin2_code":"505.0",
    "gn:admin3_code":"50509.0",
    "gn:asciiname":"Oberweissburg",
    "gn:country_code":"AT",
    "gn:dem":1165,
    "gn:feature_class":"P",
    "gn:feature_code":"PPL",
    "gn:name":"Oberwei\u00dfburg",
    "gn:population":321,
    "gn:timezone":"Europe/Vienna",
    "iso:country":"AT",
    "wof:name":"Oberweissburg",
    "wof:placetype":"locality",
    "wof:population":321
},
  "geometry": {"coordinates":[13.59462,47.1041],"type":"Point"}
}