{
  "type": "Feature",
  "properties": {
    "gn:admin1_code":"2.0",
    "gn:admin2_code":"206",
    "gn:admin3_code":"20637.0",
    "gn:asciiname":"Fellbach",
    "gn:country_code":"AT",
    "gn:dem":578,
    "gn:feature_class":"P",
    "gn:feature_code":"PPL",
    "gn:name":"Fellbach",
    "gn:population":78,
    "gn:timezone":"Europe/Vienna",
    "iso:country":"AT",
    "name:als_x_preferred":[
        "Fellbach"
    ],
    "name:ara_x_preferred":[
        "\u0641\u0644\u0628\u0627\u062e"
    ],
    "name:azb_x_preferred":[
        "\u0641\u0644\u0628\u0627\u062e"
    ],
    "name:aze_x_preferred":[
        "Fellbax"
    ],
    "name:bar_x_preferred":[
        "F\u00f6iboch"
    ],
    "name:ceb_x_preferred":[
        "Fellbach"
    ],
    "name:deu_x_preferred":[
        "Fellbach"
    ],
    "name:epo_x_preferred":[
        "Fellbach"
    ],
    "name:fas_x_preferred":[
        "\u0641\u0644\u0628\u0627\u062e"
    ],
    "name:fra_x_preferred":[
        "Fellbach"
    ],
    "name:hun_x_preferred":[
        "Fellbach"
    ],
    "name:ita_x_preferred":[
        "Fellbach"
    ],
    "name:jpn_x_preferred":[
        "\u30d5\u30a7\u30eb\u30d0\u30c3\u30cf"
    ],
    "name:lat_x_preferred":[
        "Fellbach"
    ],
    "name:lmo_x_preferred":[
        "Fellbach"
    ],
    "name:msa_x_preferred":[
        "Fellbach"
    ],
    "name:nld_x_preferred":[
        "Fellbach"
    ],
    "name:pms_x_preferred":[
        "Fellbach"
    ],
    "name:pol_x_preferred":[
        "Fellbach"
    ],
    "name:por_x_preferred":[
        "Fellbach"
    ],
    "name:ron_x_preferred":[
        "Fellbach"
    ],
    "name:rus_x_preferred":[
        "\u0424\u0435\u043b\u043b\u044c\u0431\u0430\u0445"
    ],
    "name:srp_x_preferred":[
        "\u0424\u0435\u043b\u0431\u0430\u0445"
    ],
    "name:swa_x_preferred":[
        "Fellbach"
    ],
    "name:swe_x_preferred":[
        "Fellbach"
    ],
    "name:tat_x_preferred":[
        "\u0424\u0435\u043b\u043b\u0431\u0430\u0445"
    ],
    "name:tur_x_preferred":[
        "Fellbach"
    ],
    "name:ukr_x_preferred":[
        "\u0424\u0435\u043b\u043b\u044c\u0431\u0430\u0445"
    ],
    "name:uzb_x_preferred":[
        "Fellbach"
    ],
    "name:vep_x_preferred":[
        "Fell'bah"
    ],
    "name:vol_x_preferred":[
        "Fellbach"
    ],
    "name:war_x_preferred":[
        "Fellbach"
    ],
    "name:zho_x_preferred":[
        "\u8d39\u5c14\u5df4\u8d6b"
    ],
    "wof:name":"Fellbach",
    "wof:placetype":"locality",
    "wof:population":78
},
  "geometry": {"coordinates":[13.33111,46.75556],"type":"Point"}
}