{
  "type": "Feature",
  "properties": {
    "gn:admin1_code":"4.0",
    "gn:admin2_code":"417",
    "gn:admin3_code":"41713.0",
    "gn:asciiname":"Alt Lenzing",
    "gn:country_code":"AT",
    "gn:dem":491,
    "gn:feature_class":"P",
    "gn:feature_code":"PPL",
    "gn:name":"Alt Lenzing",
    "gn:population":692,
    "gn:timezone":"Europe/Vienna",
    "iso:country":"AT",
    "wof:name":"Alt Lenzing",
    "wof:placetype":"locality",
    "wof:population":692
},
  "geometry": {"coordinates":[13.62498,47.96886],"type":"Point"}
}