{
  "type": "Feature",
  "properties": {
    "gn:admin1_code":"4.0",
    "gn:admin2_code":"417",
    "gn:admin3_code":"41722.0",
    "gn:asciiname":"Simmering",
    "gn:country_code":"AT",
    "gn:dem":610,
    "gn:feature_class":"P",
    "gn:feature_code":"PPL",
    "gn:name":"Simmering",
    "gn:population":4,
    "gn:timezone":"Europe/Vienna",
    "iso:country":"AT",
    "wof:name":"Simmering",
    "wof:placetype":"locality",
    "wof:population":4
},
  "geometry": {"coordinates":[13.62262,48.12646],"type":"Point"}
}