{
  "type": "Feature",
  "properties": {
    "gn:admin1_code":"4.0",
    "gn:admin2_code":"417",
    "gn:admin3_code":"41722.0",
    "gn:asciiname":"Simmering",
    "gn:country_code":"AT",
    "gn:dem":610,
    "gn:feature_class":"P",
    "gn:feature_code":"PPL",
    "gn:name":"Simmering",
    "gn:population":4,
    "gn:timezone":"Europe/Vienna",
    "iso:country":"AT",
    "name:ara_x_preferred":[
        "\u063a\u0644\u064a"
    ],
    "name:cat_x_preferred":[
        "Xup-xup"
    ],
    "name:cym_x_preferred":[
        "Mudferwi"
    ],
    "name:deu_x_preferred":[
        "Simmern"
    ],
    "name:fas_x_preferred":[
        "\u0622\u0631\u0627\u0645\u200c\u067e\u0632\u06cc"
    ],
    "name:fin_x_preferred":[
        "Hauduttaminen"
    ],
    "name:fra_x_preferred":[
        "Mijotage"
    ],
    "name:lav_x_preferred":[
        "Sutin\u0101\u0161ana"
    ],
    "name:msa_x_preferred":[
        "Mereneh"
    ],
    "name:nld_x_preferred":[
        "Stoven"
    ],
    "name:rus_x_preferred":[
        "\u0422\u043e\u043c\u043b\u0435\u043d\u0438\u0435"
    ],
    "name:swe_x_preferred":[
        "Sjudning"
    ],
    "name:ukr_x_preferred":[
        "\u0422\u043e\u043c\u043b\u0456\u043d\u043d\u044f"
    ],
    "wof:name":"Simmering",
    "wof:placetype":"locality",
    "wof:population":4
},
  "geometry": {"coordinates":[13.62262,48.12646],"type":"Point"}
}