{
  "type": "Feature",
  "properties": {
    "gn:admin1_code":"2.0",
    "gn:admin2_code":"203",
    "gn:admin3_code":"20305.0",
    "gn:asciiname":"Postran",
    "gn:country_code":"AT",
    "gn:dem":603,
    "gn:feature_class":"P",
    "gn:feature_code":"PPL",
    "gn:name":"Postran",
    "gn:population":121,
    "gn:timezone":"Europe/Vienna",
    "iso:country":"AT",
    "wof:name":"Postran",
    "wof:placetype":"locality",
    "wof:population":121
},
  "geometry": {"coordinates":[13.33468,46.61929],"type":"Point"}
}