{
  "type": "Feature",
  "properties": {
    "gn:admin1_code":"6.0",
    "gn:admin2_code":"612",
    "gn:admin3_code":"61257.0",
    "gn:asciiname":"Bleiberg",
    "gn:country_code":"AT",
    "gn:dem":802,
    "gn:feature_class":"P",
    "gn:feature_code":"PPL",
    "gn:name":"Bleiberg",
    "gn:population":120,
    "gn:timezone":"Europe/Vienna",
    "iso:country":"AT",
    "wof:name":"Bleiberg",
    "wof:placetype":"locality",
    "wof:population":120
},
  "geometry": {"coordinates":[14.07005,47.49479],"type":"Point"}
}