{
  "type": "Feature",
  "properties": {
    "gn:admin1_code":"4.0",
    "gn:admin2_code":"414",
    "gn:admin3_code":"41417.0",
    "gn:asciiname":"Gruebl",
    "gn:country_code":"AT",
    "gn:dem":548,
    "gn:feature_class":"P",
    "gn:feature_code":"PPL",
    "gn:name":"Gr\u00fcbl",
    "gn:population":8,
    "gn:timezone":"Europe/Vienna",
    "iso:country":"AT",
    "wof:name":"Gruebl",
    "wof:placetype":"locality",
    "wof:population":8
},
  "geometry": {"coordinates":[13.7484,48.46458],"type":"Point"}
}