{
  "type": "Feature",
  "properties": {
    "gn:admin1_code":"04",
    "gn:admin2_code":"412.0",
    "gn:admin3_code":"41205.0",
    "gn:asciiname":"Untereitzing",
    "gn:country_code":"AT",
    "gn:dem":413,
    "gn:feature_class":"P",
    "gn:feature_code":"PPL",
    "gn:name":"Untereitzing",
    "gn:population":458,
    "gn:timezone":"Europe/Vienna",
    "iso:country":"AT",
    "wof:name":"Untereitzing",
    "wof:placetype":"locality",
    "wof:population":458
},
  "geometry": {"coordinates":[13.43001,48.24045],"type":"Point"}
}