{
  "type": "Feature",
  "properties": {
    "gn:admin1_code":"4.0",
    "gn:admin2_code":"404",
    "gn:admin3_code":"40434.0",
    "gn:asciiname":"Hofing",
    "gn:country_code":"AT",
    "gn:dem":393,
    "gn:feature_class":"P",
    "gn:feature_code":"PPL",
    "gn:name":"Hofing",
    "gn:population":34,
    "gn:timezone":"Europe/Vienna",
    "iso:country":"AT",
    "wof:name":"Hofing",
    "wof:placetype":"locality",
    "wof:population":34
},
  "geometry": {"coordinates":[13.24891,48.22848],"type":"Point"}
}