{
  "type": "Feature",
  "properties": {
    "gn:admin1_code":"4.0",
    "gn:admin2_code":"417",
    "gn:admin3_code":"41747.0",
    "gn:asciiname":"Wilding",
    "gn:country_code":"AT",
    "gn:dem":539,
    "gn:feature_class":"P",
    "gn:feature_code":"PPL",
    "gn:name":"Wilding",
    "gn:population":38,
    "gn:timezone":"Europe/Vienna",
    "iso:country":"AT",
    "wof:name":"Wilding",
    "wof:placetype":"locality",
    "wof:population":38
},
  "geometry": {"coordinates":[13.45383,47.99834],"type":"Point"}
}