{
  "type": "Feature",
  "properties": {
    "gn:admin1_code":"04",
    "gn:admin2_code":"406.0",
    "gn:admin3_code":"40626.0",
    "gn:asciiname":"Oberwindhaag",
    "gn:country_code":"AT",
    "gn:dem":743,
    "gn:feature_class":"P",
    "gn:feature_code":"PPL",
    "gn:name":"Oberwindhaag",
    "gn:population":102,
    "gn:timezone":"Europe/Vienna",
    "iso:country":"AT",
    "wof:name":"Oberwindhaag",
    "wof:placetype":"locality",
    "wof:population":102
},
  "geometry": {"coordinates":[14.5707,48.58263],"type":"Point"}
}