{
  "type": "Feature",
  "properties": {
    "gn:admin1_code":"4.0",
    "gn:admin2_code":"414",
    "gn:admin3_code":"41430.0",
    "gn:asciiname":"Oberndobl",
    "gn:country_code":"AT",
    "gn:dem":444,
    "gn:feature_class":"P",
    "gn:feature_code":"PPL",
    "gn:name":"Oberndobl",
    "gn:population":0,
    "gn:timezone":"Europe/Vienna",
    "iso:country":"AT",
    "wof:name":"Oberndobl",
    "wof:placetype":"locality"
},
  "geometry": {"coordinates":[13.59781,48.31186],"type":"Point"}
}