{
  "type": "Feature",
  "properties": {
    "gn:admin1_code":"4.0",
    "gn:admin2_code":"416",
    "gn:admin3_code":"41626.0",
    "gn:asciiname":"Joergensbuehl",
    "gn:country_code":"AT",
    "gn:dem":346,
    "gn:feature_class":"P",
    "gn:feature_code":"PPL",
    "gn:name":"J\u00f6rgensb\u00fchl",
    "gn:population":0,
    "gn:timezone":"Europe/Vienna",
    "iso:country":"AT",
    "wof:name":"Joergensbuehl",
    "wof:placetype":"locality"
},
  "geometry": {"coordinates":[14.15185,48.3575],"type":"Point"}
}