{
  "type": "Feature",
  "properties": {
    "gn:admin1_code":"06",
    "gn:admin2_code":"616.0",
    "gn:admin3_code":"61631.0",
    "gn:asciiname":"Piberegg",
    "gn:country_code":"AT",
    "gn:dem":599,
    "gn:feature_class":"P",
    "gn:feature_code":"PPLA3",
    "gn:name":"Piberegg",
    "gn:population":0,
    "gn:timezone":"Europe/Vienna",
    "iso:country":"AT",
    "name:ceb_x_preferred":[
        "Piberegg"
    ],
    "name:deu_x_preferred":[
        "Piberegg"
    ],
    "name:fas_x_preferred":[
        "\u067e\u06cc\u0628\u0631\u06af"
    ],
    "name:fra_x_preferred":[
        "Piberegg"
    ],
    "name:ita_x_preferred":[
        "Piberegg"
    ],
    "name:nld_x_preferred":[
        "Piberegg"
    ],
    "name:rus_x_preferred":[
        "\u041f\u0438\u0431\u0435\u0440\u0435\u0433"
    ],
    "name:slk_x_preferred":[
        "Piberegg"
    ],
    "name:swe_x_preferred":[
        "Piberegg"
    ],
    "name:uzb_x_preferred":[
        "Piberegg"
    ],
    "name:vie_x_preferred":[
        "Piberegg"
    ],
    "name:vol_x_preferred":[
        "Piberegg"
    ],
    "name:war_x_preferred":[
        "Piberegg"
    ],
    "name:zho_x_preferred":[
        "\u76ae\u4f2f\u96f7\u683c"
    ],
    "wof:name":"Piberegg",
    "wof:placetype":"locality"
},
  "geometry": {"coordinates":[15.08333,47.08333],"type":"Point"}
}