{
  "type": "Feature",
  "properties": {
    "gn:admin1_code":"4.0",
    "gn:admin2_code":"405",
    "gn:admin3_code":"40509.0",
    "gn:asciiname":"Leumuehle",
    "gn:country_code":"AT",
    "gn:dem":264,
    "gn:feature_class":"P",
    "gn:feature_code":"PPL",
    "gn:name":"Leum\u00fchle",
    "gn:population":315,
    "gn:timezone":"Europe/Vienna",
    "iso:country":"AT",
    "wof:name":"Leumuehle",
    "wof:placetype":"locality",
    "wof:population":315
},
  "geometry": {"coordinates":[14.01349,48.32396],"type":"Point"}
}