{
  "type": "Feature",
  "properties": {
    "gn:admin1_code":"05",
    "gn:admin2_code":"504.0",
    "gn:admin3_code":"50404.0",
    "gn:asciiname":"Furstenmoos",
    "gn:country_code":"AT",
    "gn:dem":1000,
    "gn:feature_class":"P",
    "gn:feature_code":"PPL",
    "gn:name":"F\u00fcrstenmoos",
    "gn:population":0,
    "gn:timezone":"Europe/Vienna",
    "iso:country":"AT",
    "wof:name":"Furstenmoos",
    "wof:placetype":"locality"
},
  "geometry": {"coordinates":[13.28333,47.43333],"type":"Point"}
}