{
  "type": "Feature",
  "properties": {
    "gn:admin1_code":"4.0",
    "gn:admin2_code":"403",
    "gn:admin3_code":"40301.0",
    "gn:asciiname":"Mitterlaab",
    "gn:country_code":"AT",
    "gn:dem":338,
    "gn:feature_class":"P",
    "gn:feature_code":"PPL",
    "gn:name":"Mitterlaab",
    "gn:population":84,
    "gn:timezone":"Europe/Vienna",
    "iso:country":"AT",
    "wof:name":"Mitterlaab",
    "wof:placetype":"locality",
    "wof:population":84
},
  "geometry": {"coordinates":[14.03727,48.20391],"type":"Point"}
}