{
  "type": "Feature",
  "properties": {
    "gn:admin1_code":"4.0",
    "gn:admin2_code":"404",
    "gn:admin3_code":"40402.0",
    "gn:asciiname":"Niederham",
    "gn:country_code":"AT",
    "gn:dem":451,
    "gn:feature_class":"P",
    "gn:feature_code":"PPL",
    "gn:name":"Niederham",
    "gn:population":6,
    "gn:timezone":"Europe/Vienna",
    "iso:country":"AT",
    "wof:name":"Niederham",
    "wof:placetype":"locality",
    "wof:population":6
},
  "geometry": {"coordinates":[13.295,48.17616],"type":"Point"}
}