{
  "type": "Feature",
  "properties": {
    "gn:admin1_code":"3.0",
    "gn:admin2_code":"315",
    "gn:admin3_code":"31537.0",
    "gn:asciiname":"Reisenhof",
    "gn:country_code":"AT",
    "gn:dem":284,
    "gn:feature_class":"P",
    "gn:feature_code":"PPL",
    "gn:name":"Reisenhof",
    "gn:population":15,
    "gn:timezone":"Europe/Vienna",
    "iso:country":"AT",
    "wof:name":"Reisenhof",
    "wof:placetype":"locality",
    "wof:population":15
},
  "geometry": {"coordinates":[15.20216,48.13029],"type":"Point"}
}