{
  "type": "Feature",
  "properties": {
    "gn:admin1_code":"3.0",
    "gn:admin2_code":"305",
    "gn:admin3_code":"30541.0",
    "gn:asciiname":"Oberhombach",
    "gn:country_code":"AT",
    "gn:dem":309,
    "gn:feature_class":"P",
    "gn:feature_code":"PPL",
    "gn:name":"Oberh\u00f6mbach",
    "gn:population":0,
    "gn:timezone":"Europe/Vienna",
    "iso:country":"AT",
    "wof:name":"Oberhombach",
    "wof:placetype":"locality"
},
  "geometry": {"coordinates":[14.85403,48.07579000000001],"type":"Point"}
}