{
  "type": "Feature",
  "properties": {
    "gn:admin1_code":"6.0",
    "gn:admin2_code":"606",
    "gn:admin3_code":"60656.0",
    "gn:asciiname":"Kasten",
    "gn:country_code":"AT",
    "gn:dem":316,
    "gn:feature_class":"P",
    "gn:feature_code":"PPL",
    "gn:name":"Kasten",
    "gn:population":395,
    "gn:timezone":"Europe/Vienna",
    "iso:country":"AT",
    "wof:name":"Kasten",
    "wof:placetype":"locality",
    "wof:population":395
},
  "geometry": {"coordinates":[15.45,46.93333],"type":"Point"}
}