{
  "type": "Feature",
  "properties": {
    "gn:admin1_code":"03",
    "gn:admin2_code":"305.0",
    "gn:admin3_code":"30538.0",
    "gn:asciiname":"Schweinberg",
    "gn:country_code":"AT",
    "gn:dem":289,
    "gn:feature_class":"P",
    "gn:feature_code":"PPL",
    "gn:name":"Schweinberg",
    "gn:population":43,
    "gn:timezone":"Europe/Vienna",
    "iso:country":"AT",
    "wof:name":"Schweinberg",
    "wof:placetype":"locality",
    "wof:population":43
},
  "geometry": {"coordinates":[14.73333,48.15],"type":"Point"}
}