{
  "type": "Feature",
  "properties": {
    "gn:admin1_code":"3.0",
    "gn:admin2_code":"317",
    "gn:admin3_code":"31703.0",
    "gn:asciiname":"Breitenfurt-West",
    "gn:country_code":"AT",
    "gn:dem":376,
    "gn:feature_class":"P",
    "gn:feature_code":"PPL",
    "gn:name":"Breitenfurt-West",
    "gn:population":0,
    "gn:timezone":"Europe/Vienna",
    "iso:country":"AT",
    "wof:name":"Breitenfurt-West",
    "wof:placetype":"locality"
},
  "geometry": {"coordinates":[16.13776,48.14112],"type":"Point"}
}