{
  "type": "Feature",
  "properties": {
    "gn:admin1_code":"4.0",
    "gn:admin2_code":"411",
    "gn:admin3_code":"41114.0",
    "gn:asciiname":"Au an der Donau",
    "gn:country_code":"AT",
    "gn:dem":237,
    "gn:feature_class":"P",
    "gn:feature_code":"PPL",
    "gn:name":"Au an der Donau",
    "gn:population":900,
    "gn:timezone":"Europe/Vienna",
    "iso:country":"AT",
    "name:und_x_variant":[
        "Au"
    ],
    "wof:name":"Au an der Donau",
    "wof:placetype":"locality",
    "wof:population":900
},
  "geometry": {"coordinates":[14.58323,48.22879],"type":"Point"}
}