{
  "type": "Feature",
  "properties": {
    "gn:admin1_code":"4.0",
    "gn:admin2_code":"414",
    "gn:admin3_code":"41411.0",
    "gn:asciiname":"Strass",
    "gn:country_code":"AT",
    "gn:dem":613,
    "gn:feature_class":"P",
    "gn:feature_code":"PPLL",
    "gn:name":"Stra\u00df",
    "gn:population":48,
    "gn:timezone":"Europe/Vienna",
    "iso:country":"AT",
    "wof:name":"Strass",
    "wof:placetype":"locality",
    "wof:population":48
},
  "geometry": {"coordinates":[13.68279,48.4579],"type":"Point"}
}