{
  "type": "Feature",
  "properties": {
    "gn:admin1_code":"4.0",
    "gn:admin2_code":"414",
    "gn:admin3_code":"41411.0",
    "gn:asciiname":"Strass",
    "gn:country_code":"AT",
    "gn:dem":613,
    "gn:feature_class":"P",
    "gn:feature_code":"PPLL",
    "gn:name":"Stra\u00df",
    "gn:population":48,
    "gn:timezone":"Europe/Vienna",
    "iso:country":"AT",
    "name:deu_x_preferred":[
        "Strass"
    ],
    "name:fra_x_preferred":[
        "Strass"
    ],
    "name:ita_x_preferred":[
        "Strass"
    ],
    "name:nld_x_preferred":[
        "Strass"
    ],
    "name:pol_x_preferred":[
        "Strass"
    ],
    "name:rus_x_preferred":[
        "\u0428\u0442\u0440\u0430\u0441"
    ],
    "wof:name":"Strass",
    "wof:placetype":"locality",
    "wof:population":48
},
  "geometry": {"coordinates":[13.68279,48.4579],"type":"Point"}
}