{
  "type": "Feature",
  "properties": {
    "gn:admin1_code":"08",
    "gn:admin2_code":"803.0",
    "gn:admin3_code":"80303.0",
    "gn:asciiname":"Rheindorf",
    "gn:country_code":"AT",
    "gn:dem":405,
    "gn:feature_class":"P",
    "gn:feature_code":"PPL",
    "gn:name":"Rheindorf",
    "gn:population":0,
    "gn:timezone":"Europe/Vienna",
    "iso:country":"AT",
    "wof:name":"Rheindorf",
    "wof:placetype":"locality"
},
  "geometry": {"coordinates":[9.65645,47.43524],"type":"Point"}
}