{
  "type": "Feature",
  "properties": {
    "gn:gn_country":"AT",
    "gn:gn_fcode":"PPLA3",
    "gn:gn_pop":0,
    "iso:country":"AT",
    "name:chi_x_preferred":[
        "Rohrberg"
    ],
    "name:cze_x_preferred":[
        "Rohrberg"
    ],
    "name:dut_x_preferred":[
        "Rohrberg"
    ],
    "name:eng_x_preferred":[
        "Rohrberg"
    ],
    "name:fre_x_preferred":[
        "Rohrberg"
    ],
    "name:ger_x_preferred":[
        "Rohrberg"
    ],
    "name:hun_x_preferred":[
        "Rohrberg"
    ],
    "name:ita_x_preferred":[
        "Rohrberg"
    ],
    "name:kaz_x_preferred":[
        "\u0420\u043e\u0440\u0431\u0435\u0440\u0433"
    ],
    "name:pol_x_preferred":[
        "Rohrberg"
    ],
    "name:rus_x_preferred":[
        "\u0420\u043e\u0440\u0431\u0435\u0440\u0433"
    ],
    "name:slo_x_preferred":[
        "Rohrberg"
    ],
    "name:swe_x_preferred":[
        "Rohrberg"
    ],
    "name:ukr_x_preferred":[
        "\u0420\u043e\u0440\u0431\u0435\u0440\u0433"
    ],
    "name:uzb_x_preferred":[
        "Rohrberg"
    ],
    "name:vol_x_preferred":[
        "Rohrberg"
    ],
    "name:war_x_preferred":[
        "Rohrberg"
    ],
    "qs_pg:aaroncc":"AT",
    "qs_pg:gn_country":"AT",
    "qs_pg:gn_fcode":"PPLA3",
    "qs_pg:gn_pop":0,
    "qs_pg:name":"Rohrberg",
    "qs_pg:name_adm0":"\u00d6sterreich",
    "qs_pg:name_adm1":"Tirol",
    "qs_pg:photos":67,
    "qs_pg:photos_1k":14,
    "qs_pg:photos_9k":1,
    "qs_pg:photos_9r":2,
    "qs_pg:photos_all":67,
    "qs_pg:photos_sr":2,
    "qs_pg:pop_sr":0,
    "qs_pg:qs_pg_placetype":"locality",
    "qs_pg:qs_pg_placetype_gp":"Town",
    "qs_pg:woe_adm0":23424750,
    "woe:adm0_id":23424750,
    "woe:name_adm0":"\u00d6sterreich",
    "woe:name_adm1":"Tirol",
    "woe:placetype":"Town",
    "wof:name":"Rohrberg",
    "wof:placetype":"locality"
},
  "geometry": {"coordinates":[11.91667,47.23333],"type":"Point"}
}