{
  "type": "Feature",
  "properties": {
    "gn:country":"AT",
    "gn:fcode":"PPLA3",
    "gn:population":0,
    "iso:country":"AT",
    "name:cat_x_preferred":[
        "Rohrberg"
    ],
    "name:ceb_x_preferred":[
        "Rohrberg"
    ],
    "name:ces_x_preferred":[
        "Rohrberg"
    ],
    "name:che_x_preferred":[
        "\u0420\u043e\u0440\u0431\u0435\u0440\u0433"
    ],
    "name:deu_x_preferred":[
        "Rohrberg"
    ],
    "name:eng_x_preferred":[
        "Rohrberg"
    ],
    "name:est_x_preferred":[
        "Rohrberg"
    ],
    "name:fas_x_preferred":[
        "\u0631\u0648\u0647\u0631\u0628\u0631\u06af"
    ],
    "name:fra_x_preferred":[
        "Rohrberg"
    ],
    "name:hun_x_preferred":[
        "Rohrberg"
    ],
    "name:ita_x_preferred":[
        "Rohrberg"
    ],
    "name:kaz_x_preferred":[
        "\u0420\u043e\u0440\u0431\u0435\u0440\u0433"
    ],
    "name:lld_x_preferred":[
        "Rohrberg"
    ],
    "name:nld_x_preferred":[
        "Rohrberg"
    ],
    "name:nob_x_preferred":[
        "Rohrberg"
    ],
    "name:pol_x_preferred":[
        "Rohrberg"
    ],
    "name:por_x_preferred":[
        "Rohrberg"
    ],
    "name:rus_x_preferred":[
        "\u0420\u043e\u0440\u0431\u0435\u0440\u0433"
    ],
    "name:slk_x_preferred":[
        "Rohrberg"
    ],
    "name:spa_x_preferred":[
        "Rohrberg"
    ],
    "name:swe_x_preferred":[
        "Rohrberg"
    ],
    "name:tat_x_preferred":[
        "\u0420\u043e\u0440\u0431\u0435\u0440\u0433"
    ],
    "name:ukr_x_preferred":[
        "\u0420\u043e\u0440\u0431\u0435\u0440\u0433"
    ],
    "name:uzb_x_preferred":[
        "Rohrberg"
    ],
    "name:vec_x_preferred":[
        "Rohrberg"
    ],
    "name:vol_x_preferred":[
        "Rohrberg"
    ],
    "name:war_x_preferred":[
        "Rohrberg"
    ],
    "name:zho_x_preferred":[
        "Rohrberg"
    ],
    "qs_pg:aaroncc":"AT",
    "qs_pg:gn_country":"AT",
    "qs_pg:gn_fcode":"PPLA3",
    "qs_pg:gn_pop":0,
    "qs_pg:name":"Rohrberg",
    "qs_pg:name_adm0":"\u00d6sterreich",
    "qs_pg:name_adm1":"Tirol",
    "qs_pg:photos":67,
    "qs_pg:photos_1k":14,
    "qs_pg:photos_9k":1,
    "qs_pg:photos_9r":2,
    "qs_pg:photos_all":67,
    "qs_pg:photos_sr":2,
    "qs_pg:pop_sr":0,
    "qs_pg:qs_pg_placetype":"locality",
    "qs_pg:qs_pg_placetype_gp":"Town",
    "qs_pg:woe_adm0":23424750,
    "woe:adm0_id":23424750,
    "woe:name_adm0":"\u00d6sterreich",
    "woe:name_adm1":"Tirol",
    "woe:placetype":"Town",
    "wof:name":"Rohrberg",
    "wof:placetype":"locality"
},
  "geometry": {"coordinates":[11.91667,47.23333],"type":"Point"}
}