{
  "type": "Feature",
  "properties": {
    "gn:admin1_code":"04",
    "gn:admin2_code":"411.0",
    "gn:admin3_code":"41119.0",
    "gn:asciiname":"Unter Sankt Georgen",
    "gn:country_code":"AT",
    "gn:dem":720,
    "gn:feature_class":"P",
    "gn:feature_code":"PPL",
    "gn:name":"Unter Sankt Georgen",
    "gn:population":152,
    "gn:timezone":"Europe/Vienna",
    "iso:country":"AT",
    "wof:name":"Unter Sankt Georgen",
    "wof:placetype":"locality",
    "wof:population":152
},
  "geometry": {"coordinates":[14.88333,48.33333],"type":"Point"}
}