{
  "type": "Feature",
  "properties": {
    "gn:admin1_code":"03",
    "gn:admin2_code":"309.0",
    "gn:admin3_code":"30912.0",
    "gn:asciiname":"Schroffen",
    "gn:country_code":"AT",
    "gn:dem":703,
    "gn:feature_class":"P",
    "gn:feature_code":"PPL",
    "gn:name":"Schroffen",
    "gn:population":54,
    "gn:timezone":"Europe/Vienna",
    "iso:country":"AT",
    "wof:name":"Schroffen",
    "wof:placetype":"locality",
    "wof:population":54
},
  "geometry": {"coordinates":[14.93935,48.62531],"type":"Point"}
}