{
  "type": "Feature",
  "properties": {
    "gn:admin1_code":"3.0",
    "gn:admin2_code":"320",
    "gn:admin3_code":"32015.0",
    "gn:asciiname":"Lehmgstetten",
    "gn:country_code":"AT",
    "gn:dem":322,
    "gn:feature_class":"P",
    "gn:feature_code":"PPL",
    "gn:name":"Lehmgstetten",
    "gn:population":124,
    "gn:timezone":"Europe/Vienna",
    "iso:country":"AT",
    "wof:name":"Lehmgstetten",
    "wof:placetype":"locality",
    "wof:population":124
},
  "geometry": {"coordinates":[15.02303,48.04969000000001],"type":"Point"}
}