{
  "type": "Feature",
  "properties": {
    "gn:admin1_code":"1.0",
    "gn:admin2_code":"105",
    "gn:admin3_code":"10505.0",
    "gn:asciiname":"Windisch-Minihof",
    "gn:country_code":"AT",
    "gn:dem":276,
    "gn:feature_class":"P",
    "gn:feature_code":"PPL",
    "gn:name":"Windisch-Minihof",
    "gn:population":435,
    "gn:timezone":"Europe/Vienna",
    "iso:country":"AT",
    "wof:name":"Windisch-Minihof",
    "wof:placetype":"locality",
    "wof:population":435
},
  "geometry": {"coordinates":[16.09542,46.8908],"type":"Point"}
}