{
  "type": "Feature",
  "properties": {
    "gn:admin1_code":"04",
    "gn:admin2_code":"414.0",
    "gn:admin3_code":"41430.0",
    "gn:asciiname":"Reischenbach",
    "gn:country_code":"AT",
    "gn:dem":370,
    "gn:feature_class":"P",
    "gn:feature_code":"PPL",
    "gn:name":"Reischenbach",
    "gn:population":43,
    "gn:timezone":"Europe/Vienna",
    "iso:country":"AT",
    "wof:name":"Reischenbach",
    "wof:placetype":"locality",
    "wof:population":43
},
  "geometry": {"coordinates":[13.62888,48.32915],"type":"Point"}
}