{
  "type": "Feature",
  "properties": {
    "gn:admin1_code":"03",
    "gn:admin2_code":"319.0",
    "gn:admin3_code":"31934.0",
    "gn:asciiname":"Reichenhag",
    "gn:country_code":"AT",
    "gn:dem":279,
    "gn:feature_class":"P",
    "gn:feature_code":"PPL",
    "gn:name":"Reichenhag",
    "gn:population":105,
    "gn:timezone":"Europe/Vienna",
    "iso:country":"AT",
    "wof:name":"Reichenhag",
    "wof:placetype":"locality",
    "wof:population":105
},
  "geometry": {"coordinates":[15.71491,48.16975],"type":"Point"}
}