{
  "type": "Feature",
  "properties": {
    "gn:admin1_code":"03",
    "gn:admin2_code":"319.0",
    "gn:admin3_code":"31930.0",
    "gn:asciiname":"Weyersdorf",
    "gn:country_code":"AT",
    "gn:dem":447,
    "gn:feature_class":"P",
    "gn:feature_code":"PPL",
    "gn:name":"Weyersdorf",
    "gn:population":0,
    "gn:timezone":"Europe/Vienna",
    "iso:country":"AT",
    "wof:name":"Weyersdorf",
    "wof:placetype":"locality"
},
  "geometry": {"coordinates":[15.53196,48.27364],"type":"Point"}
}