{
  "type": "Feature",
  "properties": {
    "gn:admin1_code":"4.0",
    "gn:admin2_code":"406",
    "gn:admin3_code":"40624.0",
    "gn:asciiname":"Altenhaus",
    "gn:country_code":"AT",
    "gn:dem":379,
    "gn:feature_class":"P",
    "gn:feature_code":"PPL",
    "gn:name":"Altenhaus",
    "gn:population":123,
    "gn:timezone":"Europe/Vienna",
    "iso:country":"AT",
    "wof:name":"Altenhaus",
    "wof:placetype":"locality",
    "wof:population":123
},
  "geometry": {"coordinates":[14.52577,48.32476],"type":"Point"}
}