{
  "type": "Feature",
  "properties": {
    "gn:admin1_code":"06",
    "gn:admin2_code":"623.0",
    "gn:admin3_code":"62335.0",
    "gn:asciiname":"Poehrl",
    "gn:country_code":"AT",
    "gn:dem":375,
    "gn:feature_class":"P",
    "gn:feature_code":"PPL",
    "gn:name":"P\u00f6hrl",
    "gn:population":0,
    "gn:timezone":"Europe/Vienna",
    "iso:country":"AT",
    "wof:name":"Poehrl",
    "wof:placetype":"locality"
},
  "geometry": {"coordinates":[15.95,46.76667],"type":"Point"}
}