{
  "type": "Feature",
  "properties": {
    "gn:admin1_code":"4.0",
    "gn:admin2_code":"412",
    "gn:admin3_code":"41216.0",
    "gn:asciiname":"Rottenberg",
    "gn:country_code":"AT",
    "gn:dem":424,
    "gn:feature_class":"P",
    "gn:feature_code":"PPL",
    "gn:name":"Rottenberg",
    "gn:population":7,
    "gn:timezone":"Europe/Vienna",
    "iso:country":"AT",
    "wof:name":"Rottenberg",
    "wof:placetype":"locality",
    "wof:population":7
},
  "geometry": {"coordinates":[13.39512,48.30058],"type":"Point"}
}