{
  "type": "Feature",
  "properties": {
    "gn:admin1_code":"4.0",
    "gn:admin2_code":"417",
    "gn:admin3_code":"41702.0",
    "gn:asciiname":"Abtsdorf",
    "gn:cc2":"AT",
    "gn:country_code":"AT",
    "gn:dem":528,
    "gn:feature_class":"P",
    "gn:feature_code":"PPL",
    "gn:name":"Abtsdorf",
    "gn:population":358,
    "gn:timezone":"Europe/Vienna",
    "iso:country":"AT",
    "name:und_x_variant":[
        "Abtstorf",
        "Abtsdorf"
    ],
    "wof:name":"Abtsdorf",
    "wof:placetype":"locality",
    "wof:population":358
},
  "geometry": {"coordinates":[13.5119,47.91019],"type":"Point"}
}