{
  "type": "Feature",
  "properties": {
    "gn:admin1_code":"4.0",
    "gn:admin2_code":"417",
    "gn:admin3_code":"41702.0",
    "gn:asciiname":"Abtsdorf",
    "gn:cc2":"AT",
    "gn:country_code":"AT",
    "gn:dem":528,
    "gn:feature_class":"P",
    "gn:feature_code":"PPL",
    "gn:name":"Abtsdorf",
    "gn:population":358,
    "gn:timezone":"Europe/Vienna",
    "iso:country":"AT",
    "name:bak_x_preferred":[
        "\u0410\u0431\u0442\u0441\u0434\u043e\u0440\u0444"
    ],
    "name:ceb_x_preferred":[
        "Abtsdorf"
    ],
    "name:deu_x_preferred":[
        "Abtsdorf"
    ],
    "name:epo_x_preferred":[
        "Abtsdorf"
    ],
    "name:fas_x_preferred":[
        "\u0627\u0628\u0633\u062f\u0631\u0627\u0641"
    ],
    "name:kaz_x_preferred":[
        "\u0410\u0431\u0442\u0441\u0434\u043e\u0440\u0444"
    ],
    "name:kir_x_preferred":[
        "\u0410\u0431\u0442\u0441\u0434\u043e\u0440\u0444"
    ],
    "name:mkd_x_preferred":[
        "\u0410\u0431\u0442\u0441\u0434\u043e\u0440\u0444"
    ],
    "name:nld_x_preferred":[
        "Abtsdorf"
    ],
    "name:ron_x_preferred":[
        "Abtsdorf"
    ],
    "name:rus_x_preferred":[
        "\u0410\u0431\u0442\u0441\u0434\u043e\u0440\u0444"
    ],
    "name:ukr_x_preferred":[
        "\u0410\u0431\u0442\u0441\u0434\u043e\u0440\u0444"
    ],
    "name:und_x_variant":[
        "Abtstorf"
    ],
    "name:uzb_x_preferred":[
        "Abtsdorf"
    ],
    "name:vol_x_preferred":[
        "Abtsdorf"
    ],
    "wof:name":"Abtsdorf",
    "wof:placetype":"locality",
    "wof:population":358
},
  "geometry": {"coordinates":[13.5119,47.91019],"type":"Point"}
}