{
  "type": "Feature",
  "properties": {
    "gn:admin1_code":"4.0",
    "gn:admin2_code":"408",
    "gn:admin3_code":"40831.0",
    "gn:asciiname":"Stroiss",
    "gn:country_code":"AT",
    "gn:dem":355,
    "gn:feature_class":"P",
    "gn:feature_code":"PPL",
    "gn:name":"Stroi\u00df",
    "gn:population":30,
    "gn:timezone":"Europe/Vienna",
    "iso:country":"AT",
    "wof:name":"Stroiss",
    "wof:placetype":"locality",
    "wof:population":30
},
  "geometry": {"coordinates":[13.86535,48.34438],"type":"Point"}
}