{
  "type": "Feature",
  "properties": {
    "gn:admin1_code":"4.0",
    "gn:admin2_code":"415",
    "gn:admin3_code":"41509.0",
    "gn:asciiname":"Hintsteingraben",
    "gn:country_code":"AT",
    "gn:dem":630,
    "gn:feature_class":"P",
    "gn:feature_code":"PPL",
    "gn:name":"Hintsteingraben",
    "gn:population":0,
    "gn:timezone":"Europe/Vienna",
    "iso:country":"AT",
    "wof:name":"Hintsteingraben",
    "wof:placetype":"locality"
},
  "geometry": {"coordinates":[14.40702,47.91864],"type":"Point"}
}