{
  "type": "Feature",
  "properties": {
    "gn:admin1_code":"06",
    "gn:admin2_code":"606.0",
    "gn:admin3_code":"60654.0",
    "gn:asciiname":"Oberschoeckl",
    "gn:country_code":"AT",
    "gn:dem":507,
    "gn:feature_class":"P",
    "gn:feature_code":"PPL",
    "gn:name":"Obersch\u00f6ckl",
    "gn:population":807,
    "gn:timezone":"Europe/Vienna",
    "iso:country":"AT",
    "wof:name":"Oberschoeckl",
    "wof:placetype":"locality",
    "wof:population":807
},
  "geometry": {"coordinates":[15.48333,47.15],"type":"Point"}
}