{
  "type": "Feature",
  "properties": {
    "gn:admin1_code":"4.0",
    "gn:admin2_code":"413",
    "gn:admin3_code":"41327.0",
    "gn:asciiname":"Muehlholz",
    "gn:country_code":"AT",
    "gn:dem":577,
    "gn:feature_class":"P",
    "gn:feature_code":"PPL",
    "gn:name":"M\u00fchlholz",
    "gn:population":22,
    "gn:timezone":"Europe/Vienna",
    "iso:country":"AT",
    "wof:name":"Muehlholz",
    "wof:placetype":"locality",
    "wof:population":22
},
  "geometry": {"coordinates":[13.795,48.51028],"type":"Point"}
}