{
  "type": "Feature",
  "properties": {
    "gn:admin1_code":"2.0",
    "gn:admin2_code":"204",
    "gn:admin3_code":"20442.0",
    "gn:asciiname":"Kreuzbichl",
    "gn:country_code":"AT",
    "gn:dem":465,
    "gn:feature_class":"P",
    "gn:feature_code":"PPL",
    "gn:name":"Kreuzbichl",
    "gn:population":9,
    "gn:timezone":"Europe/Vienna",
    "iso:country":"AT",
    "wof:name":"Kreuzbichl",
    "wof:placetype":"locality",
    "wof:population":9
},
  "geometry": {"coordinates":[14.37595,46.65344],"type":"Point"}
}