{
  "type": "Feature",
  "properties": {
    "gn:admin1_code":"2.0",
    "gn:admin2_code":"204",
    "gn:admin3_code":"20402.0",
    "gn:asciiname":"Goritschach",
    "gn:country_code":"AT",
    "gn:dem":423,
    "gn:feature_class":"P",
    "gn:feature_code":"PPL",
    "gn:name":"Goritschach",
    "gn:population":60,
    "gn:timezone":"Europe/Vienna",
    "iso:country":"AT",
    "wof:name":"Goritschach",
    "wof:placetype":"locality",
    "wof:population":60
},
  "geometry": {"coordinates":[14.40951,46.56323],"type":"Point"}
}