{
  "type": "Feature",
  "properties": {
    "gn:admin1_code":"5.0",
    "gn:admin2_code":"503",
    "gn:admin3_code":"50302.0",
    "gn:asciiname":"Gollacken",
    "gn:country_code":"AT",
    "gn:dem":433,
    "gn:feature_class":"P",
    "gn:feature_code":"PPL",
    "gn:name":"Gollacken",
    "gn:population":187,
    "gn:timezone":"Europe/Vienna",
    "iso:country":"AT",
    "wof:name":"Gollacken",
    "wof:placetype":"locality",
    "wof:population":187
},
  "geometry": {"coordinates":[13.00306,47.89],"type":"Point"}
}