{
  "type": "Feature",
  "properties": {
    "gn:admin1_code":"3.0",
    "gn:admin2_code":"325",
    "gn:admin3_code":"32508.0",
    "gn:asciiname":"Freitzenschlag",
    "gn:country_code":"AT",
    "gn:dem":749,
    "gn:feature_class":"P",
    "gn:feature_code":"PPL",
    "gn:name":"Freitzenschlag",
    "gn:population":117,
    "gn:timezone":"Europe/Vienna",
    "iso:country":"AT",
    "wof:name":"Freitzenschlag",
    "wof:placetype":"locality",
    "wof:population":117
},
  "geometry": {"coordinates":[14.98333,48.56667],"type":"Point"}
}