{
  "type": "Feature",
  "properties": {
    "gn:admin1_code":"02",
    "gn:admin2_code":"203.0",
    "gn:admin3_code":"20306.0",
    "gn:asciiname":"Stranig",
    "gn:country_code":"AT",
    "gn:dem":627,
    "gn:feature_class":"P",
    "gn:feature_code":"PPL",
    "gn:name":"Stranig",
    "gn:population":93,
    "gn:timezone":"Europe/Vienna",
    "iso:country":"AT",
    "wof:name":"Stranig",
    "wof:placetype":"locality",
    "wof:population":93
},
  "geometry": {"coordinates":[13.16051,46.63547],"type":"Point"}
}