{
  "type": "Feature",
  "properties": {
    "gn:admin1_code":"4.0",
    "gn:admin2_code":"404",
    "gn:admin3_code":"40435.0",
    "gn:asciiname":"Wies",
    "gn:country_code":"AT",
    "gn:dem":469,
    "gn:feature_class":"P",
    "gn:feature_code":"PPL",
    "gn:name":"Wies",
    "gn:population":11,
    "gn:timezone":"Europe/Vienna",
    "iso:country":"AT",
    "name:bos_x_preferred":[
        "Wies"
    ],
    "name:deu_x_preferred":[
        "Wies"
    ],
    "name:epo_x_preferred":[
        "Wies"
    ],
    "name:fas_x_preferred":[
        "\u0648\u0627\u06cc\u0633"
    ],
    "name:fin_x_preferred":[
        "Wies"
    ],
    "name:fra_x_preferred":[
        "Wies"
    ],
    "name:hun_x_preferred":[
        "Wies"
    ],
    "name:ita_x_preferred":[
        "Wies"
    ],
    "name:kaz_x_preferred":[
        "\u0412\u0438\u0441"
    ],
    "name:nld_x_preferred":[
        "Wies"
    ],
    "name:pol_x_preferred":[
        "Wies"
    ],
    "name:rus_x_preferred":[
        "\u0412\u0438\u0441"
    ],
    "name:slk_x_preferred":[
        "Wies"
    ],
    "name:spa_x_preferred":[
        "Wies"
    ],
    "name:uzb_x_preferred":[
        "Wies"
    ],
    "name:vie_x_preferred":[
        "Wies"
    ],
    "name:vol_x_preferred":[
        "Wies"
    ],
    "name:war_x_preferred":[
        "Wies"
    ],
    "wof:name":"Wies",
    "wof:placetype":"locality",
    "wof:population":11
},
  "geometry": {"coordinates":[13.0285,48.10488],"type":"Point"}
}