{
  "type": "Feature",
  "properties": {
    "gn:admin1_code":"4.0",
    "gn:admin2_code":"404",
    "gn:admin3_code":"40435.0",
    "gn:asciiname":"Wies",
    "gn:country_code":"AT",
    "gn:dem":469,
    "gn:feature_class":"P",
    "gn:feature_code":"PPL",
    "gn:name":"Wies",
    "gn:population":11,
    "gn:timezone":"Europe/Vienna",
    "iso:country":"AT",
    "wof:name":"Wies",
    "wof:placetype":"locality",
    "wof:population":11
},
  "geometry": {"coordinates":[13.0285,48.10488],"type":"Point"}
}