{
  "type": "Feature",
  "properties": {
    "gn:admin1_code":"03",
    "gn:admin2_code":"302.0",
    "gn:admin3_code":"30201.0",
    "gn:asciiname":"Oberzwischenbrunn",
    "gn:country_code":"AT",
    "gn:dem":267,
    "gn:feature_class":"P",
    "gn:feature_code":"PPL",
    "gn:name":"Oberzwischenbrunn",
    "gn:population":70,
    "gn:timezone":"Europe/Vienna",
    "iso:country":"AT",
    "wof:name":"Oberzwischenbrunn",
    "wof:placetype":"locality",
    "wof:population":70
},
  "geometry": {"coordinates":[15.68573,48.20843],"type":"Point"}
}