{
  "type": "Feature",
  "properties": {
    "gn:admin1_code":"06",
    "gn:admin2_code":"622.0",
    "gn:admin3_code":"62235.0",
    "gn:asciiname":"Unterneuberg",
    "gn:country_code":"AT",
    "gn:dem":625,
    "gn:feature_class":"P",
    "gn:feature_code":"PPL",
    "gn:name":"Unterneuberg",
    "gn:population":536,
    "gn:timezone":"Europe/Vienna",
    "iso:country":"AT",
    "wof:name":"Unterneuberg",
    "wof:placetype":"locality",
    "wof:population":536
},
  "geometry": {"coordinates":[15.85,47.31667],"type":"Point"}
}