{
  "type": "Feature",
  "properties": {
    "gn:admin1_code":"3.0",
    "gn:admin2_code":"320",
    "gn:admin3_code":"32009.0",
    "gn:asciiname":"Kaltenbrunn",
    "gn:country_code":"AT",
    "gn:dem":580,
    "gn:feature_class":"P",
    "gn:feature_code":"PPL",
    "gn:name":"Kaltenbrunn",
    "gn:population":0,
    "gn:timezone":"Europe/Vienna",
    "iso:country":"AT",
    "wof:name":"Kaltenbrunn",
    "wof:placetype":"locality"
},
  "geometry": {"coordinates":[15.02063,48.02185],"type":"Point"}
}