{
  "type": "Feature",
  "properties": {
    "gn:admin1_code":"5.0",
    "gn:admin2_code":"503",
    "gn:admin3_code":"50304.0",
    "gn:asciiname":"Strauchmuhle",
    "gn:country_code":"AT",
    "gn:dem":584,
    "gn:feature_class":"P",
    "gn:feature_code":"PPL",
    "gn:name":"Strauchm\u00fchle",
    "gn:population":0,
    "gn:timezone":"Europe/Vienna",
    "iso:country":"AT",
    "wof:name":"Strauchmuhle",
    "wof:placetype":"locality"
},
  "geometry": {"coordinates":[13.05222,47.97833],"type":"Point"}
}