{
  "type": "Feature",
  "properties": {
    "gn:admin1_code":"06",
    "gn:admin2_code":"611.0",
    "gn:admin3_code":"61120.0",
    "gn:asciiname":"Roetzgraben",
    "gn:country_code":"AT",
    "gn:dem":833,
    "gn:feature_class":"P",
    "gn:feature_code":"PPL",
    "gn:name":"R\u00f6tzgraben",
    "gn:population":0,
    "gn:timezone":"Europe/Vienna",
    "iso:country":"AT",
    "wof:name":"Roetzgraben",
    "wof:placetype":"locality"
},
  "geometry": {"coordinates":[15.03333,47.45],"type":"Point"}
}