{
  "type": "Feature",
  "properties": {
    "gn:admin1_code":"5.0",
    "gn:admin2_code":"503",
    "gn:admin3_code":"50306.0",
    "gn:asciiname":"Wagnergraben",
    "gn:country_code":"AT",
    "gn:dem":473,
    "gn:feature_class":"P",
    "gn:feature_code":"PPLA3",
    "gn:name":"Wagnergraben",
    "gn:population":21,
    "gn:timezone":"Europe/Vienna",
    "iso:country":"AT",
    "wof:name":"Wagnergraben",
    "wof:placetype":"locality",
    "wof:population":21
},
  "geometry": {"coordinates":[13.02395,48.02036],"type":"Point"}
}