{
  "type": "Feature",
  "properties": {
    "gn:admin1_code":"2.0",
    "gn:admin2_code":"209",
    "gn:admin3_code":"20913.0",
    "gn:asciiname":"Blaiken",
    "gn:country_code":"AT",
    "gn:dem":406,
    "gn:feature_class":"P",
    "gn:feature_code":"PPL",
    "gn:name":"Blaiken",
    "gn:population":497,
    "gn:timezone":"Europe/Vienna",
    "iso:country":"AT",
    "wof:name":"Blaiken",
    "wof:placetype":"locality",
    "wof:population":497
},
  "geometry": {"coordinates":[14.83489,46.76679],"type":"Point"}
}