{
  "type": "Feature",
  "properties": {
    "gn:admin1_code":"3.0",
    "gn:admin2_code":"318",
    "gn:admin3_code":"31805.0",
    "gn:asciiname":"Klamm",
    "gn:country_code":"AT",
    "gn:dem":707,
    "gn:feature_class":"P",
    "gn:feature_code":"PPL",
    "gn:name":"Klamm",
    "gn:population":0,
    "gn:timezone":"Europe/Vienna",
    "iso:country":"AT",
    "wof:name":"Klamm",
    "wof:placetype":"locality"
},
  "geometry": {"coordinates":[15.86786,47.66076],"type":"Point"}
}