{
  "type": "Feature",
  "properties": {
    "gn:admin1_code":"6.0",
    "gn:admin2_code":"610",
    "gn:admin3_code":"61027.0",
    "gn:asciiname":"Gundersdorf",
    "gn:country_code":"AT",
    "gn:dem":284,
    "gn:feature_class":"P",
    "gn:feature_code":"PPL",
    "gn:name":"Gundersdorf",
    "gn:population":112,
    "gn:timezone":"Europe/Vienna",
    "iso:country":"AT",
    "wof:name":"Gundersdorf",
    "wof:placetype":"locality",
    "wof:population":112
},
  "geometry": {"coordinates":[15.58333,46.85],"type":"Point"}
}