{
  "type": "Feature",
  "properties": {
    "gn:admin1_code":"6.0",
    "gn:admin2_code":"610",
    "gn:admin3_code":"61027.0",
    "gn:asciiname":"Gundersdorf",
    "gn:country_code":"AT",
    "gn:dem":284,
    "gn:feature_class":"P",
    "gn:feature_code":"PPL",
    "gn:name":"Gundersdorf",
    "gn:population":112,
    "gn:timezone":"Europe/Vienna",
    "iso:country":"AT",
    "name:ceb_x_preferred":[
        "Gundersdorf"
    ],
    "name:deu_x_preferred":[
        "Gundersdorf"
    ],
    "name:fas_x_preferred":[
        "\u06af\u0648\u0646\u062f\u0631\u0634\u062f\u0648\u0631\u0641"
    ],
    "name:fra_x_preferred":[
        "Gundersdorf"
    ],
    "name:ita_x_preferred":[
        "Gundersdorf"
    ],
    "name:kaz_x_preferred":[
        "\u0413\u0443\u043d\u0434\u0435\u0440\u0441\u0434\u043e\u0440\u0444"
    ],
    "name:nld_x_preferred":[
        "Gundersdorf"
    ],
    "name:rus_x_preferred":[
        "\u0413\u0443\u043d\u0434\u0435\u0440\u0441\u0434\u043e\u0440\u0444"
    ],
    "name:slk_x_preferred":[
        "Gundersdorf"
    ],
    "name:swe_x_preferred":[
        "Gundersdorf"
    ],
    "name:uzb_x_preferred":[
        "Gundersdorf"
    ],
    "name:vie_x_preferred":[
        "Gundersdorf"
    ],
    "name:vol_x_preferred":[
        "Gundersdorf"
    ],
    "name:war_x_preferred":[
        "Gundersdorf"
    ],
    "name:zho_x_preferred":[
        "\u8d21\u5fb7\u5c14\u65af\u591a\u592b"
    ],
    "wof:name":"Gundersdorf",
    "wof:placetype":"locality",
    "wof:population":112
},
  "geometry": {"coordinates":[15.58333,46.85],"type":"Point"}
}