{
  "type": "Feature",
  "properties": {
    "gn:admin1_code":"2.0",
    "gn:admin2_code":"203",
    "gn:admin3_code":"20306.0",
    "gn:asciiname":"Lenzhof",
    "gn:country_code":"AT",
    "gn:dem":1077,
    "gn:feature_class":"P",
    "gn:feature_code":"PPL",
    "gn:name":"Lenzhof",
    "gn:population":10,
    "gn:timezone":"Europe/Vienna",
    "iso:country":"AT",
    "wof:name":"Lenzhof",
    "wof:placetype":"locality",
    "wof:population":10
},
  "geometry": {"coordinates":[13.11536,46.67029],"type":"Point"}
}