{
  "type": "Feature",
  "properties": {
    "gn:admin1_code":"06",
    "gn:admin2_code":"623.0",
    "gn:admin3_code":"62380.0",
    "gn:asciiname":"Krenneck",
    "gn:country_code":"AT",
    "gn:dem":332,
    "gn:feature_class":"P",
    "gn:feature_code":"PPL",
    "gn:name":"Krenneck",
    "gn:population":0,
    "gn:timezone":"Europe/Vienna",
    "iso:country":"AT",
    "wof:name":"Krenneck",
    "wof:placetype":"locality"
},
  "geometry": {"coordinates":[15.76667,46.91667],"type":"Point"}
}