{
  "type": "Feature",
  "properties": {
    "gn:admin1_code":"3.0",
    "gn:admin2_code":"307",
    "gn:admin3_code":"30741.0",
    "gn:asciiname":"Altkettenhof",
    "gn:country_code":"AT",
    "gn:dem":165,
    "gn:feature_class":"P",
    "gn:feature_code":"PPL",
    "gn:name":"Altkettenhof",
    "gn:population":0,
    "gn:timezone":"Europe/Vienna",
    "iso:country":"AT",
    "wof:name":"Altkettenhof",
    "wof:placetype":"locality"
},
  "geometry": {"coordinates":[16.46667,48.11667],"type":"Point"}
}