{
  "type": "Feature",
  "properties": {
    "gn:admin1_code":"03",
    "gn:admin2_code":"320.0",
    "gn:admin3_code":"32006.0",
    "gn:asciiname":"Schachau",
    "gn:country_code":"AT",
    "gn:dem":269,
    "gn:feature_class":"P",
    "gn:feature_code":"PPL",
    "gn:name":"Schachau",
    "gn:population":106,
    "gn:timezone":"Europe/Vienna",
    "iso:country":"AT",
    "wof:name":"Schachau",
    "wof:placetype":"locality",
    "wof:population":106
},
  "geometry": {"coordinates":[15.2298,48.08347],"type":"Point"}
}