{
  "type": "Feature",
  "properties": {
    "gn:admin1_code":"4.0",
    "gn:admin2_code":"418",
    "gn:admin3_code":"41814.0",
    "gn:asciiname":"Weinberg",
    "gn:country_code":"AT",
    "gn:dem":471,
    "gn:feature_class":"P",
    "gn:feature_code":"PPL",
    "gn:name":"Weinberg",
    "gn:population":48,
    "gn:timezone":"Europe/Vienna",
    "iso:country":"AT",
    "wof:name":"Weinberg",
    "wof:placetype":"locality",
    "wof:population":48
},
  "geometry": {"coordinates":[13.81617,48.15137],"type":"Point"}
}