{
  "type": "Feature",
  "properties": {
    "gn:admin1_code":"04",
    "gn:admin2_code":"410.0",
    "gn:admin3_code":"41020.0",
    "gn:asciiname":"Thal",
    "gn:country_code":"AT",
    "gn:dem":349,
    "gn:feature_class":"P",
    "gn:feature_code":"PPL",
    "gn:name":"Thal",
    "gn:population":38,
    "gn:timezone":"Europe/Vienna",
    "iso:country":"AT",
    "wof:name":"Thal",
    "wof:placetype":"locality",
    "wof:population":38
},
  "geometry": {"coordinates":[14.29579,48.12806],"type":"Point"}
}