{
  "type": "Feature",
  "properties": {
    "gn:admin1_code":"3.0",
    "gn:admin2_code":"319",
    "gn:admin3_code":"31925.0",
    "gn:asciiname":"Goldegg",
    "gn:country_code":"AT",
    "gn:dem":465,
    "gn:feature_class":"P",
    "gn:feature_code":"PPL",
    "gn:name":"Goldegg",
    "gn:population":25,
    "gn:timezone":"Europe/Vienna",
    "iso:country":"AT",
    "name:ceb_x_preferred":[
        "Goldegg"
    ],
    "name:fas_x_preferred":[
        "\u06af\u0644\u062f\u06af"
    ],
    "name:fra_x_preferred":[
        "Goldegg"
    ],
    "name:hun_x_preferred":[
        "Goldegg"
    ],
    "name:ita_x_preferred":[
        "Goldegg"
    ],
    "name:rus_x_preferred":[
        "\u0413\u043e\u043b\u044c\u0434\u0435\u0433\u0433"
    ],
    "name:slk_x_preferred":[
        "Goldegg"
    ],
    "name:spa_x_preferred":[
        "Goldegg"
    ],
    "name:swe_x_preferred":[
        "Goldegg"
    ],
    "name:ukr_x_preferred":[
        "\u0413\u043e\u043b\u044c\u0434\u0435\u0433\u0433-\u0456\u043c-\u041f\u043e\u043d\u0433\u0430\u0443"
    ],
    "name:uzb_x_preferred":[
        "Goldegg"
    ],
    "name:vol_x_preferred":[
        "Goldegg"
    ],
    "name:war_x_preferred":[
        "Goldegg"
    ],
    "name:zho_x_preferred":[
        "\u6208\u5c14\u5fb7\u683c"
    ],
    "wof:name":"Goldegg",
    "wof:placetype":"locality",
    "wof:population":25
},
  "geometry": {"coordinates":[15.51667,48.23333],"type":"Point"}
}