{
  "type": "Feature",
  "properties": {
    "gn:admin1_code":"04",
    "gn:admin2_code":"406.0",
    "gn:admin3_code":"40625.0",
    "gn:asciiname":"Ritzenedt",
    "gn:country_code":"AT",
    "gn:dem":762,
    "gn:feature_class":"P",
    "gn:feature_code":"PPL",
    "gn:name":"Ritzenedt",
    "gn:population":63,
    "gn:timezone":"Europe/Vienna",
    "iso:country":"AT",
    "wof:name":"Ritzenedt",
    "wof:placetype":"locality",
    "wof:population":63
},
  "geometry": {"coordinates":[14.72185,48.48331],"type":"Point"}
}