{
  "type": "Feature",
  "properties": {
    "gn:admin1_code":"2.0",
    "gn:admin2_code":"208",
    "gn:admin3_code":"20801.0",
    "gn:asciiname":"Einersdorf",
    "gn:country_code":"AT",
    "gn:dem":516,
    "gn:feature_class":"P",
    "gn:feature_code":"PPL",
    "gn:name":"Einersdorf",
    "gn:population":282,
    "gn:timezone":"Europe/Vienna",
    "iso:country":"AT",
    "name:deu_x_preferred":[
        "Einersdorf"
    ],
    "name:slv_x_preferred":[
        "Non\u010da Ves"
    ],
    "wof:name":"Einersdorf",
    "wof:placetype":"locality",
    "wof:population":282
},
  "geometry": {"coordinates":[14.80556,46.60278],"type":"Point"}
}