{
  "type": "Feature",
  "properties": {
    "gn:admin1_code":"2.0",
    "gn:admin2_code":"208",
    "gn:admin3_code":"20802.0",
    "gn:asciiname":"Krass",
    "gn:country_code":"AT",
    "gn:dem":1001,
    "gn:feature_class":"P",
    "gn:feature_code":"PPL",
    "gn:name":"Kra\u00df",
    "gn:population":0,
    "gn:timezone":"Europe/Vienna",
    "iso:country":"AT",
    "wof:name":"Krass",
    "wof:placetype":"locality"
},
  "geometry": {"coordinates":[14.67868,46.71639],"type":"Point"}
}