{
  "type": "Feature",
  "properties": {
    "gn:admin1_code":"2.0",
    "gn:admin2_code":"204",
    "gn:admin3_code":"20402.0",
    "gn:asciiname":"Kosasmojach",
    "gn:country_code":"AT",
    "gn:dem":419,
    "gn:feature_class":"P",
    "gn:feature_code":"PPL",
    "gn:name":"Kosasmojach",
    "gn:population":26,
    "gn:timezone":"Europe/Vienna",
    "iso:country":"AT",
    "wof:name":"Kosasmojach",
    "wof:placetype":"locality",
    "wof:population":26
},
  "geometry": {"coordinates":[14.43083,46.56889],"type":"Point"}
}