{
  "type": "Feature",
  "properties": {
    "gn:admin1_code":"3.0",
    "gn:admin2_code":"321",
    "gn:admin3_code":"32139.0",
    "gn:asciiname":"Egelsee",
    "gn:country_code":"AT",
    "gn:dem":227,
    "gn:feature_class":"P",
    "gn:feature_code":"PPL",
    "gn:name":"Egelsee",
    "gn:population":44,
    "gn:timezone":"Europe/Vienna",
    "iso:country":"AT",
    "name:deu_x_preferred":[
        "Egelsee"
    ],
    "wof:name":"Egelsee",
    "wof:placetype":"locality",
    "wof:population":44
},
  "geometry": {"coordinates":[15.84108,48.2608],"type":"Point"}
}