{
  "type": "Feature",
  "properties": {
    "gn:country":"AT",
    "gn:fcode":"PPL",
    "gn:population":0,
    "iso:country":"AT",
    "name:deu_x_preferred":[
        "Rottenegg"
    ],
    "name:eng_x_preferred":[
        "Rottenegg"
    ],
    "name:fra_x_preferred":[
        "Rottenegg"
    ],
    "qs_pg:aaroncc":"AT",
    "qs_pg:gn_country":"AT",
    "qs_pg:gn_fcode":"PPL",
    "qs_pg:gn_pop":0,
    "qs_pg:name":"Rottenegg",
    "qs_pg:name_adm0":"\u00d6sterreich",
    "qs_pg:name_adm1":"Ober\u00f6sterreich",
    "qs_pg:photos":414,
    "qs_pg:photos_1k":84,
    "qs_pg:photos_9k":2,
    "qs_pg:photos_9r":5,
    "qs_pg:photos_all":414,
    "qs_pg:photos_sr":6,
    "qs_pg:pop_sr":0,
    "qs_pg:qs_pg_placetype":"locality",
    "qs_pg:qs_pg_placetype_gp":"Town",
    "qs_pg:woe_adm0":23424750,
    "woe:adm0_id":23424750,
    "woe:name_adm0":"\u00d6sterreich",
    "woe:name_adm1":"Ober\u00f6sterreich",
    "woe:placetype":"Town",
    "wof:name":"Rottenegg",
    "wof:placetype":"locality"
},
  "geometry": {"coordinates":[14.134,48.36845],"type":"Point"}
}