{
  "type": "Feature",
  "properties": {
    "gn:admin1_code":"3.0",
    "gn:admin2_code":"323",
    "gn:admin3_code":"32325.0",
    "gn:asciiname":"Dreibuchen",
    "gn:country_code":"AT",
    "gn:dem":582,
    "gn:feature_class":"P",
    "gn:feature_code":"PPL",
    "gn:name":"Dreibuchen",
    "gn:population":0,
    "gn:timezone":"Europe/Vienna",
    "iso:country":"AT",
    "wof:name":"Dreibuchen",
    "wof:placetype":"locality"
},
  "geometry": {"coordinates":[16.24011,47.66478],"type":"Point"}
}