{
  "type": "Feature",
  "properties": {
    "gn:admin1_code":"5.0",
    "gn:admin2_code":"503",
    "gn:admin3_code":"50308.0",
    "gn:asciiname":"Moosham",
    "gn:country_code":"AT",
    "gn:dem":477,
    "gn:feature_class":"P",
    "gn:feature_code":"PPL",
    "gn:name":"Moosham",
    "gn:population":0,
    "gn:timezone":"Europe/Vienna",
    "iso:country":"AT",
    "wof:name":"Moosham",
    "wof:placetype":"locality"
},
  "geometry": {"coordinates":[13.05444,47.86417],"type":"Point"}
}