{
  "type": "Feature",
  "properties": {
    "gn:admin1_code":"4.0",
    "gn:admin2_code":"417",
    "gn:admin3_code":"41747.0",
    "gn:asciiname":"Unterholz",
    "gn:country_code":"AT",
    "gn:dem":539,
    "gn:feature_class":"P",
    "gn:feature_code":"PPL",
    "gn:name":"Unterholz",
    "gn:population":55,
    "gn:timezone":"Europe/Vienna",
    "iso:country":"AT",
    "wof:name":"Unterholz",
    "wof:placetype":"locality",
    "wof:population":55
},
  "geometry": {"coordinates":[13.4858,47.98332],"type":"Point"}
}