{
  "type": "Feature",
  "properties": {
    "gn:admin1_code":"4.0",
    "gn:admin2_code":"408",
    "gn:admin3_code":"40803.0",
    "gn:asciiname":"Feichten",
    "gn:country_code":"AT",
    "gn:dem":444,
    "gn:feature_class":"P",
    "gn:feature_code":"PPL",
    "gn:name":"Feichten",
    "gn:population":0,
    "gn:timezone":"Europe/Vienna",
    "iso:country":"AT",
    "name:ara_x_preferred":[
        "\u0641\u064a\u0634\u062a\u0646"
    ],
    "name:ceb_x_preferred":[
        "Feichten a.d.Alz"
    ],
    "name:fas_x_preferred":[
        "\u0641\u0627\u06cc\u0634\u062a\u0646"
    ],
    "name:hye_x_preferred":[
        "\u0531\u056c\u0581\u056b \u0556\u0561\u0575\u056d\u057f\u0565\u0576"
    ],
    "name:ilo_x_preferred":[
        "Feichten"
    ],
    "name:kaz_x_preferred":[
        "\u0424\u0430\u0439\u0445\u0442\u0435\u043d-\u043d\u0430-\u0410\u043b\u044c\u0446\u0435"
    ],
    "name:msa_x_preferred":[
        "Feichten"
    ],
    "name:por_x_preferred":[
        "Feichten"
    ],
    "name:rus_x_preferred":[
        "\u0424\u0430\u0439\u0445\u0442\u0435\u043d-\u0430\u043d-\u0434\u0435\u0440-\u0410\u043b\u044c\u0446"
    ],
    "name:spa_x_preferred":[
        "Feichten"
    ],
    "name:ukr_x_preferred":[
        "\u0424\u0430\u0439\u0445\u0442\u0435\u043d"
    ],
    "name:war_x_preferred":[
        "Feichten"
    ],
    "wof:name":"Feichten",
    "wof:placetype":"locality"
},
  "geometry": {"coordinates":[13.79235,48.33389],"type":"Point"}
}