{
  "type": "Feature",
  "properties": {
    "gn:admin1_code":"06",
    "gn:admin2_code":"610.0",
    "gn:admin3_code":"61021.0",
    "gn:asciiname":"Sankt Margarethen bei Lebring",
    "gn:cc2":"AT",
    "gn:country_code":"AT",
    "gn:dem":294,
    "gn:feature_class":"P",
    "gn:feature_code":"PPL",
    "gn:name":"Sankt Margarethen bei Lebring",
    "gn:population":780,
    "gn:timezone":"Europe/Vienna",
    "iso:country":"AT",
    "name:und_x_variant":[
        "Sankt Margarethen",
        "Sankt Margarethen bei Lebring"
    ],
    "wof:name":"Sankt Margarethen bei Lebring",
    "wof:placetype":"locality",
    "wof:population":780
},
  "geometry": {"coordinates":[15.52778,46.86361],"type":"Point"}
}