{
  "type": "Feature",
  "properties": {
    "gn:admin1_code":"2.0",
    "gn:admin2_code":"203",
    "gn:admin3_code":"20305.0",
    "gn:asciiname":"Kreuth ob Moeschach",
    "gn:country_code":"AT",
    "gn:dem":824,
    "gn:feature_class":"P",
    "gn:feature_code":"PPL",
    "gn:name":"Kreuth ob M\u00f6schach",
    "gn:population":13,
    "gn:timezone":"Europe/Vienna",
    "iso:country":"AT",
    "wof:name":"Kreuth ob Moeschach",
    "wof:placetype":"locality",
    "wof:population":13
},
  "geometry": {"coordinates":[13.34384,46.63217],"type":"Point"}
}