{
  "type": "Feature",
  "properties": {
    "gn:admin1_code":"7.0",
    "gn:admin2_code":"709",
    "gn:admin3_code":"70907.0",
    "gn:asciiname":"Haeusern",
    "gn:country_code":"AT",
    "gn:dem":1240,
    "gn:feature_class":"P",
    "gn:feature_code":"PPL",
    "gn:name":"H\u00e4usern",
    "gn:population":0,
    "gn:timezone":"Europe/Vienna",
    "iso:country":"AT",
    "wof:name":"Haeusern",
    "wof:placetype":"locality"
},
  "geometry": {"coordinates":[11.73333,47.41667],"type":"Point"}
}