{
  "type": "Feature",
  "properties": {
    "gn:admin1_code":"2.0",
    "gn:admin2_code":"208",
    "gn:admin3_code":"20806.0",
    "gn:asciiname":"Glantschach",
    "gn:country_code":"AT",
    "gn:dem":474,
    "gn:feature_class":"P",
    "gn:feature_code":"PPL",
    "gn:name":"Glantschach",
    "gn:population":156,
    "gn:timezone":"Europe/Vienna",
    "iso:country":"AT",
    "wof:name":"Glantschach",
    "wof:placetype":"locality",
    "wof:population":156
},
  "geometry": {"coordinates":[14.53333,46.55],"type":"Point"}
}