{
  "type": "Feature",
  "properties": {
    "gn:admin1_code":"4.0",
    "gn:asciiname":"Lohnau",
    "gn:country_code":"AT",
    "gn:dem":420,
    "gn:feature_class":"P",
    "gn:feature_code":"PPL",
    "gn:name":"Lohnau",
    "gn:population":293,
    "gn:timezone":"Europe/Vienna",
    "iso:country":"AT",
    "wof:name":"Lohnau",
    "wof:placetype":"locality",
    "wof:population":293
},
  "geometry": {"coordinates":[13.1218,48.14513],"type":"Point"}
}