{
  "type": "Feature",
  "properties": {
    "gn:admin1_code":"03",
    "gn:admin2_code":"305.0",
    "gn:admin3_code":"30508.0",
    "gn:asciiname":"Windpassing",
    "gn:country_code":"AT",
    "gn:dem":243,
    "gn:feature_class":"P",
    "gn:feature_code":"PPL",
    "gn:name":"Windpassing",
    "gn:population":0,
    "gn:timezone":"Europe/Vienna",
    "iso:country":"AT",
    "name:deu_x_preferred":[
        "Windpassing"
    ],
    "name:msa_x_preferred":[
        "Windpassing"
    ],
    "wof:name":"Windpassing",
    "wof:placetype":"locality"
},
  "geometry": {"coordinates":[14.51663,48.22456],"type":"Point"}
}