{
  "type": "Feature",
  "properties": {
    "gn:gn_country":"AT",
    "gn:gn_fcode":"PPL",
    "gn:gn_pop":0,
    "iso:country":"AT",
    "name:bar_x_preferred":[
        "Wois-Siazenham"
    ],
    "name:chi_x_preferred":[
        "\u6c83\u65af\u585e\u723e\u5c91\u6d77\u59c6"
    ],
    "name:cze_x_preferred":[
        "Wals-Siezenheim"
    ],
    "name:dan_x_preferred":[
        "Wals-Siezenheim"
    ],
    "name:dut_x_preferred":[
        "Wals-Siezenheim"
    ],
    "name:eng_x_preferred":[
        "Wals-Siezenheim"
    ],
    "name:fre_x_preferred":[
        "Wals-Siezenheim"
    ],
    "name:geo_x_preferred":[
        "\u10d5\u10d0\u10da\u10e1-\u10d6\u10d8\u10ea\u10d4\u10dc\u10f0\u10d0\u10d8\u10db\u10d8"
    ],
    "name:ger_x_preferred":[
        "Wals-Siezenheim"
    ],
    "name:gre_x_preferred":[
        "\u0392\u03b1\u03bb\u03c2-\u0396\u03af\u03c4\u03c3\u03b5\u03bd\u03c7\u03b1\u03ca\u03bc"
    ],
    "name:hrv_x_preferred":[
        "Wals-Siezenheim"
    ],
    "name:hun_x_preferred":[
        "Wals-Siezenheim"
    ],
    "name:ita_x_preferred":[
        "Wals-Siezenheim"
    ],
    "name:kaz_x_preferred":[
        "\u0412\u0430\u043b\u044c\u0441-\u0417\u0438\u0446\u0435\u043d\u0445\u0430\u0439\u043c"
    ],
    "name:lit_x_preferred":[
        "Valsas-Zycenheimas"
    ],
    "name:mar_x_preferred":[
        "\u0935\u093e\u0932\u094d\u0938-\u0938\u093f\u092f\u0947\u091d\u0947\u0928\u0939\u093e\u0907\u092e"
    ],
    "name:nan_x_preferred":[
        "Wals-Siezenheim"
    ],
    "name:per_x_preferred":[
        "\u0648\u0627\u0644\u0632-\u0632\u06cc\u062a\u0633\u0646\u0647\u0627\u06cc\u0645"
    ],
    "name:pol_x_preferred":[
        "Wals-Siezenheim"
    ],
    "name:rum_x_preferred":[
        "Wals-Siezenheim"
    ],
    "name:rus_x_preferred":[
        "\u0412\u0430\u043b\u044c\u0441-\u0417\u0438\u0446\u0435\u043d\u0445\u0430\u0439\u043c"
    ],
    "name:slo_x_preferred":[
        "Wals-Siezenheim"
    ],
    "name:srp_x_preferred":[
        "\u0412\u0430\u043b\u0441-\u0421\u0438\u0437\u0435\u043d\u0445\u0430\u0458\u043c"
    ],
    "name:swe_x_preferred":[
        "Wals-Siezenheim"
    ],
    "name:ukr_x_preferred":[
        "\u0412\u0430\u043b\u044c\u0441-\u0417\u0456\u0446\u0435\u043d\u0433\u0430\u0439\u043c"
    ],
    "name:unk_x_variant":[
        "Stezenheim"
    ],
    "name:uzb_x_preferred":[
        "Wals-Siezenheim"
    ],
    "name:vol_x_preferred":[
        "Wals-Siezenheim"
    ],
    "name:war_x_preferred":[
        "Wals-Siezenheim"
    ],
    "qs_pg:aaroncc":"AT",
    "qs_pg:gn_country":"AT",
    "qs_pg:gn_fcode":"PPL",
    "qs_pg:gn_pop":0,
    "qs_pg:name":"Wals-siezenheim",
    "qs_pg:name_adm0":"\u00d6sterreich",
    "qs_pg:name_adm1":"Salzburg",
    "qs_pg:photos_9r":0,
    "qs_pg:photos_sr":0,
    "qs_pg:pop_sr":0,
    "qs_pg:qs_pg_placetype":"locality",
    "qs_pg:qs_pg_placetype_gp":"Town",
    "qs_pg:woe_adm0":23424750,
    "woe:adm0_id":23424750,
    "woe:name_adm0":"\u00d6sterreich",
    "woe:name_adm1":"Salzburg",
    "woe:placetype":"Town",
    "wof:name":"Wals-siezenheim",
    "wof:placetype":"locality"
},
  "geometry": {"coordinates":[12.99039,47.81529],"type":"Point"}
}