{
  "type": "Feature",
  "properties": {
    "gn:admin1_code":"4.0",
    "gn:admin2_code":"404",
    "gn:admin3_code":"40403.0",
    "gn:asciiname":"Rietzing",
    "gn:country_code":"AT",
    "gn:dem":474,
    "gn:feature_class":"P",
    "gn:feature_code":"PPL",
    "gn:name":"Rietzing",
    "gn:population":5,
    "gn:timezone":"Europe/Vienna",
    "iso:country":"AT",
    "wof:name":"Rietzing",
    "wof:placetype":"locality",
    "wof:population":5
},
  "geometry": {"coordinates":[13.08377,48.06388],"type":"Point"}
}