{
  "type": "Feature",
  "properties": {
    "gn:admin1_code":"3.0",
    "gn:admin2_code":"315",
    "gn:admin3_code":"31537.0",
    "gn:asciiname":"Kalcha",
    "gn:country_code":"AT",
    "gn:dem":323,
    "gn:feature_class":"P",
    "gn:feature_code":"PPL",
    "gn:name":"Kalcha",
    "gn:population":18,
    "gn:timezone":"Europe/Vienna",
    "iso:country":"AT",
    "wof:name":"Kalcha",
    "wof:placetype":"locality",
    "wof:population":18
},
  "geometry": {"coordinates":[15.2204,48.15083],"type":"Point"}
}