{
  "type": "Feature",
  "properties": {
    "gn:admin1_code":"4.0",
    "gn:admin2_code":"408",
    "gn:admin3_code":"40819.0",
    "gn:asciiname":"Steingrueneredt",
    "gn:country_code":"AT",
    "gn:dem":446,
    "gn:feature_class":"P",
    "gn:feature_code":"PPL",
    "gn:name":"Steingr\u00fcneredt",
    "gn:population":0,
    "gn:timezone":"Europe/Vienna",
    "iso:country":"AT",
    "wof:name":"Steingrueneredt",
    "wof:placetype":"locality"
},
  "geometry": {"coordinates":[13.75385,48.36443],"type":"Point"}
}