{
  "type": "Feature",
  "properties": {
    "gn:admin1_code":"06",
    "gn:admin2_code":"623.0",
    "gn:admin3_code":"62386.0",
    "gn:asciiname":"Forchaugraben",
    "gn:country_code":"AT",
    "gn:dem":344,
    "gn:feature_class":"P",
    "gn:feature_code":"PPL",
    "gn:name":"Forchaugraben",
    "gn:population":0,
    "gn:timezone":"Europe/Vienna",
    "iso:country":"AT",
    "wof:name":"Forchaugraben",
    "wof:placetype":"locality"
},
  "geometry": {"coordinates":[15.96667,46.98333],"type":"Point"}
}