{
  "type": "Feature",
  "properties": {
    "gn:admin1_code":"3.0",
    "gn:admin2_code":"320",
    "gn:admin3_code":"32014.0",
    "gn:asciiname":"Edelbach",
    "gn:country_code":"AT",
    "gn:dem":280,
    "gn:feature_class":"P",
    "gn:feature_code":"PPL",
    "gn:name":"Edelbach",
    "gn:population":27,
    "gn:timezone":"Europe/Vienna",
    "iso:country":"AT",
    "wof:name":"Edelbach",
    "wof:placetype":"locality",
    "wof:population":27
},
  "geometry": {"coordinates":[15.01917,48.10439],"type":"Point"}
}