{
  "type": "Feature",
  "properties": {
    "gn:admin1_code":"06",
    "gn:admin2_code":"612.0",
    "gn:admin3_code":"61206.0",
    "gn:asciiname":"Harsbach",
    "gn:country_code":"AT",
    "gn:dem":628,
    "gn:feature_class":"P",
    "gn:feature_code":"PPL",
    "gn:name":"Harsbach",
    "gn:population":0,
    "gn:timezone":"Europe/Vienna",
    "iso:country":"AT",
    "wof:name":"Harsbach",
    "wof:placetype":"locality"
},
  "geometry": {"coordinates":[14.36667,47.58333],"type":"Point"}
}