{
  "type": "Feature",
  "properties": {
    "gn:admin1_code":"2.0",
    "gn:admin2_code":"203",
    "gn:admin3_code":"20306.0",
    "gn:asciiname":"Oberbuchach",
    "gn:country_code":"AT",
    "gn:dem":885,
    "gn:feature_class":"P",
    "gn:feature_code":"PPL",
    "gn:name":"Oberbuchach",
    "gn:population":20,
    "gn:timezone":"Europe/Vienna",
    "iso:country":"AT",
    "wof:name":"Oberbuchach",
    "wof:placetype":"locality",
    "wof:population":20
},
  "geometry": {"coordinates":[13.1157,46.63146],"type":"Point"}
}