{
  "type": "Feature",
  "properties": {
    "gn:admin1_code":"06",
    "gn:admin2_code":"623.0",
    "gn:admin3_code":"62375.0",
    "gn:asciiname":"Vorstatt",
    "gn:country_code":"AT",
    "gn:dem":487,
    "gn:feature_class":"P",
    "gn:feature_code":"PPL",
    "gn:name":"Vorstatt",
    "gn:population":0,
    "gn:timezone":"Europe/Vienna",
    "iso:country":"AT",
    "wof:name":"Vorstatt",
    "wof:placetype":"locality"
},
  "geometry": {"coordinates":[15.93333,46.85],"type":"Point"}
}