{
  "type": "Feature",
  "properties": {
    "gn:admin1_code":"2.0",
    "gn:admin2_code":"210",
    "gn:admin3_code":"21001.0",
    "gn:asciiname":"Hochrindl-Tatermann",
    "gn:country_code":"AT",
    "gn:dem":1383,
    "gn:feature_class":"P",
    "gn:feature_code":"PPLL",
    "gn:name":"Hochrindl-Tatermann",
    "gn:population":17,
    "gn:timezone":"Europe/Vienna",
    "iso:country":"AT",
    "wof:name":"Hochrindl-Tatermann",
    "wof:placetype":"locality",
    "wof:population":17
},
  "geometry": {"coordinates":[14.00635,46.85268],"type":"Point"}
}