{
  "type": "Feature",
  "properties": {
    "gn:admin1_code":"02",
    "gn:admin2_code":"206.0",
    "gn:admin3_code":"20605.0",
    "gn:asciiname":"Ranach",
    "gn:country_code":"AT",
    "gn:dem":1303,
    "gn:feature_class":"P",
    "gn:feature_code":"PPL",
    "gn:name":"Ranach",
    "gn:population":33,
    "gn:timezone":"Europe/Vienna",
    "iso:country":"AT",
    "wof:name":"Ranach",
    "wof:placetype":"locality",
    "wof:population":33
},
  "geometry": {"coordinates":[12.88333,46.96667],"type":"Point"}
}