{
  "type": "Feature",
  "properties": {
    "gn:admin1_code":"4.0",
    "gn:admin2_code":"414",
    "gn:admin3_code":"41409.0",
    "gn:asciiname":"Lanzendorf",
    "gn:country_code":"AT",
    "gn:dem":488,
    "gn:feature_class":"P",
    "gn:feature_code":"PPL",
    "gn:name":"Lanzendorf",
    "gn:population":30,
    "gn:timezone":"Europe/Vienna",
    "iso:country":"AT",
    "wof:name":"Lanzendorf",
    "wof:placetype":"locality",
    "wof:population":30
},
  "geometry": {"coordinates":[13.5599,48.52085],"type":"Point"}
}