{
  "type": "Feature",
  "properties": {
    "gn:admin1_code":"3.0",
    "gn:admin2_code":"310",
    "gn:admin3_code":"31035.0",
    "gn:asciiname":"Rafing",
    "gn:country_code":"AT",
    "gn:dem":337,
    "gn:feature_class":"P",
    "gn:feature_code":"PPL",
    "gn:name":"Rafing",
    "gn:population":160,
    "gn:timezone":"Europe/Vienna",
    "iso:country":"AT",
    "wof:name":"Rafing",
    "wof:placetype":"locality",
    "wof:population":160
},
  "geometry": {"coordinates":[15.82872,48.69555],"type":"Point"}
}