{
  "type": "Feature",
  "properties": {
    "iso:country":"AT",
    "name:ceb_x_preferred":[
        "Sch\u00e4rding-Suben Airport"
    ],
    "name:deu_x_preferred":[
        "Flugplatz Sch\u00e4rding-Suben"
    ],
    "name:eng_x_preferred":[
        "Sch\u00e4rding-Suben Airport"
    ],
    "name:hun_x_preferred":[
        "Sch\u00e4rding-Suben rep\u00fcl\u0151t\u00e9r"
    ],
    "name:ron_x_preferred":[
        "Aeroportul Sch\u00e4rding-Suben"
    ],
    "name:swe_x_preferred":[
        "Sch\u00e4rding-Suben Airport"
    ],
    "oa:elevation_ft":"1070",
    "oa:type":"small_airport",
    "woe:hierarchy":{
        "country_id":23424750,
        "county_id":12591710,
        "localadmin_id":12674501,
        "planet_id":1,
        "state_id":2344711
    },
    "wof:name":"Flugplatz Sch\u00e4rding-suben",
    "wof:placetype":"campus"
},
  "geometry": {"coordinates":[13.4483,48.4029],"type":"Point"}
}