{
  "type": "Feature",
  "properties": {
    "gn:admin1_code":"04",
    "gn:admin2_code":"407.0",
    "gn:admin3_code":"40702.0",
    "gn:asciiname":"Gschwandt",
    "gn:country_code":"AT",
    "gn:dem":565,
    "gn:feature_class":"P",
    "gn:feature_code":"PPL",
    "gn:name":"Gschwandt",
    "gn:population":645,
    "gn:timezone":"Europe/Vienna",
    "iso:country":"AT",
    "wof:name":"Gschwandt",
    "wof:placetype":"locality",
    "wof:population":645
},
  "geometry": {"coordinates":[13.61738,47.63168],"type":"Point"}
}