{
  "type": "Feature",
  "properties": {
    "gn:admin1_code":"04",
    "gn:admin2_code":"407.0",
    "gn:admin3_code":"40702.0",
    "gn:asciiname":"Gschwandt",
    "gn:country_code":"AT",
    "gn:dem":565,
    "gn:feature_class":"P",
    "gn:feature_code":"PPL",
    "gn:name":"Gschwandt",
    "gn:population":645,
    "gn:timezone":"Europe/Vienna",
    "iso:country":"AT",
    "name:ceb_x_preferred":[
        "Gschwandt"
    ],
    "name:deu_x_preferred":[
        "Gschwandt"
    ],
    "name:fas_x_preferred":[
        "\u0634\u0648\u0627\u0646\u062a"
    ],
    "name:fin_x_preferred":[
        "Gschwandt"
    ],
    "name:fra_x_preferred":[
        "Gschwandt"
    ],
    "name:fur_x_preferred":[
        "Gschwandt"
    ],
    "name:hun_x_preferred":[
        "Gschwandt"
    ],
    "name:ita_x_preferred":[
        "Gschwandt"
    ],
    "name:kaz_x_preferred":[
        "\u0413\u0448\u0432\u0430\u043d\u0434\u0442"
    ],
    "name:nld_x_preferred":[
        "Gschwandt"
    ],
    "name:pol_x_preferred":[
        "Gschwandt"
    ],
    "name:por_x_preferred":[
        "Gschwandt"
    ],
    "name:rus_x_preferred":[
        "\u0413\u0448\u0432\u0430\u043d\u0434\u0442"
    ],
    "name:slk_x_preferred":[
        "Gschwandt"
    ],
    "name:spa_x_preferred":[
        "Gschwandt"
    ],
    "name:swe_x_preferred":[
        "Gschwandt"
    ],
    "name:uzb_x_preferred":[
        "Gschwandt"
    ],
    "name:vie_x_preferred":[
        "Gschwandt"
    ],
    "name:vol_x_preferred":[
        "Gschwandt"
    ],
    "name:war_x_preferred":[
        "Gschwandt"
    ],
    "name:zho_x_preferred":[
        "\u683c\u65bd\u842c\u7279"
    ],
    "wof:name":"Gschwandt",
    "wof:placetype":"locality",
    "wof:population":645
},
  "geometry": {"coordinates":[13.61738,47.63168],"type":"Point"}
}