{
  "type": "Feature",
  "properties": {
    "iso:country":"AT",
    "wof:name":"Altlerchenfeld",
    "wof:placetype":"neighbourhood"
},
  "geometry": {"coordinates":[16.34323178772713,48.20887868592111],"type":"Point"}
}