{
  "type": "Feature",
  "properties": {
    "gn:admin1_code":"4.0",
    "gn:admin2_code":"417",
    "gn:admin3_code":"41749.0",
    "gn:asciiname":"Seeberg",
    "gn:country_code":"AT",
    "gn:dem":477,
    "gn:feature_class":"P",
    "gn:feature_code":"PPL",
    "gn:name":"Seeberg",
    "gn:population":35,
    "gn:timezone":"Europe/Vienna",
    "iso:country":"AT",
    "name:als_x_preferred":[
        "Seeberg"
    ],
    "name:ceb_x_preferred":[
        "Seeberg"
    ],
    "name:deu_x_preferred":[
        "Seeberg"
    ],
    "name:epo_x_preferred":[
        "Seeberg"
    ],
    "name:eus_x_preferred":[
        "Seeberg"
    ],
    "name:fra_x_preferred":[
        "Seeberg"
    ],
    "name:ita_x_preferred":[
        "Seeberg"
    ],
    "name:kaz_x_preferred":[
        "\u0417\u0435\u0435\u0431\u0435\u0440\u0433"
    ],
    "name:lmo_x_preferred":[
        "Seeberg"
    ],
    "name:msa_x_preferred":[
        "Seeberg"
    ],
    "name:nld_x_preferred":[
        "Seeberg"
    ],
    "name:nno_x_preferred":[
        "Seeberg"
    ],
    "name:rus_x_preferred":[
        "\u0417\u0435\u0431\u0435\u0440\u0433"
    ],
    "name:spa_x_preferred":[
        "Seeberg"
    ],
    "name:sqi_x_preferred":[
        "Seeberg"
    ],
    "name:swe_x_preferred":[
        "Seeberg"
    ],
    "name:vol_x_preferred":[
        "Seeberg"
    ],
    "name:war_x_preferred":[
        "Seeberg"
    ],
    "name:zho_x_preferred":[
        "\u585e\u8c9d\u683c"
    ],
    "wof:name":"Seeberg",
    "wof:placetype":"locality",
    "wof:population":35
},
  "geometry": {"coordinates":[13.57833,47.91778],"type":"Point"}
}