{
  "type": "Feature",
  "properties": {
    "gn:admin1_code":"06",
    "gn:admin2_code":"610.0",
    "gn:admin3_code":"61056.0",
    "gn:asciiname":"Priebing",
    "gn:country_code":"AT",
    "gn:dem":252,
    "gn:feature_class":"P",
    "gn:feature_code":"PPL",
    "gn:name":"Priebing",
    "gn:population":91,
    "gn:timezone":"Europe/Vienna",
    "iso:country":"AT",
    "wof:name":"Priebing",
    "wof:placetype":"locality",
    "wof:population":91
},
  "geometry": {"coordinates":[15.73333,46.75],"type":"Point"}
}