{
  "type": "Feature",
  "properties": {
    "gn:admin1_code":"2.0",
    "gn:admin2_code":"205",
    "gn:admin3_code":"20527.0",
    "gn:asciiname":"Baiersdorf",
    "gn:country_code":"AT",
    "gn:dem":533,
    "gn:feature_class":"P",
    "gn:feature_code":"PPL",
    "gn:name":"Baiersdorf",
    "gn:population":28,
    "gn:timezone":"Europe/Vienna",
    "iso:country":"AT",
    "wof:name":"Baiersdorf",
    "wof:placetype":"locality",
    "wof:population":28
},
  "geometry": {"coordinates":[14.39981,46.74512],"type":"Point"}
}