{
  "type": "Feature",
  "properties": {
    "gn:admin1_code":"7.0",
    "gn:admin2_code":"705",
    "gn:admin3_code":"70515.0",
    "gn:asciiname":"Oberlangkampfen",
    "gn:country_code":"AT",
    "gn:dem":492,
    "gn:feature_class":"P",
    "gn:feature_code":"PPL",
    "gn:name":"Oberlangkampfen",
    "gn:population":921,
    "gn:timezone":"Europe/Vienna",
    "iso:country":"AT",
    "wof:name":"Oberlangkampfen",
    "wof:placetype":"locality",
    "wof:population":921
},
  "geometry": {"coordinates":[12.08865,47.52132],"type":"Point"}
}