{
  "type": "Feature",
  "properties": {
    "gn:country":"AT",
    "gn:fcode":"PPL",
    "gn:population":0,
    "iso:country":"AT",
    "name:cat_x_preferred":[
        "Japons"
    ],
    "name:ceb_x_preferred":[
        "Japons"
    ],
    "name:ces_x_preferred":[
        "Japons"
    ],
    "name:che_x_preferred":[
        "\u042f\u043f\u043e\u043d\u0441"
    ],
    "name:deu_x_preferred":[
        "Japons"
    ],
    "name:eng_x_preferred":[
        "Japons"
    ],
    "name:epo_x_preferred":[
        "Japons"
    ],
    "name:fas_x_preferred":[
        "\u06cc\u0627\u067e\u0648\u0646\u0633"
    ],
    "name:fra_x_preferred":[
        "Japons"
    ],
    "name:heb_x_preferred":[
        "\u05d9\u05d0\u05e4\u05d5\u05e0\u05e1"
    ],
    "name:hun_x_preferred":[
        "Japons"
    ],
    "name:ita_x_preferred":[
        "Japons"
    ],
    "name:kaz_x_preferred":[
        "\u042f\u043f\u043e\u043d\u0441"
    ],
    "name:lld_x_preferred":[
        "Japons"
    ],
    "name:nld_x_preferred":[
        "Japons"
    ],
    "name:nob_x_preferred":[
        "Japons"
    ],
    "name:pol_x_preferred":[
        "Japons"
    ],
    "name:por_x_preferred":[
        "Japons"
    ],
    "name:rus_x_preferred":[
        "\u042f\u043f\u043e\u043d\u0441"
    ],
    "name:slk_x_preferred":[
        "Japons"
    ],
    "name:spa_x_preferred":[
        "Japons"
    ],
    "name:swe_x_preferred":[
        "Japons"
    ],
    "name:tat_x_preferred":[
        "\u042f\u043f\u043e\u043d\u0441"
    ],
    "name:urd_x_preferred":[
        "\u062c\u067e\u0648\u0646\u0633"
    ],
    "name:uzb_x_preferred":[
        "Japons"
    ],
    "name:vec_x_preferred":[
        "Japons"
    ],
    "name:vie_x_preferred":[
        "Japons"
    ],
    "name:vol_x_preferred":[
        "Japons"
    ],
    "name:war_x_preferred":[
        "Japons"
    ],
    "name:zho_x_preferred":[
        "Japons"
    ],
    "qs_pg:aaroncc":"AT",
    "qs_pg:gn_country":"AT",
    "qs_pg:gn_fcode":"PPL",
    "qs_pg:gn_pop":0,
    "qs_pg:name":"Japons",
    "qs_pg:name_adm0":"\u00d6sterreich",
    "qs_pg:name_adm1":"Nieder\u00f6sterreich",
    "qs_pg:photos":80,
    "qs_pg:photos_1k":16,
    "qs_pg:photos_9k":1,
    "qs_pg:photos_9r":3,
    "qs_pg:photos_all":80,
    "qs_pg:photos_sr":3,
    "qs_pg:pop_sr":0,
    "qs_pg:qs_pg_placetype":"locality",
    "qs_pg:qs_pg_placetype_gp":"Town",
    "qs_pg:woe_adm0":23424750,
    "woe:adm0_id":23424750,
    "woe:name_adm0":"\u00d6sterreich",
    "woe:name_adm1":"Nieder\u00f6sterreich",
    "woe:placetype":"Town",
    "wof:name":"Japons",
    "wof:placetype":"locality"
},
  "geometry": {"coordinates":[15.55664,48.78176],"type":"Point"}
}