{
  "type": "Feature",
  "properties": {
    "gn:admin1_code":"03",
    "gn:admin2_code":"325.0",
    "gn:admin3_code":"32517.0",
    "gn:asciiname":"Oed",
    "gn:country_code":"AT",
    "gn:dem":854,
    "gn:feature_class":"P",
    "gn:feature_code":"PPL",
    "gn:name":"Oed",
    "gn:population":67,
    "gn:timezone":"Europe/Vienna",
    "iso:country":"AT",
    "wof:name":"Oed",
    "wof:placetype":"locality",
    "wof:population":67
},
  "geometry": {"coordinates":[15.13333,48.38333],"type":"Point"}
}