{
  "type": "Feature",
  "properties": {
    "gn:admin1_code":"6.0",
    "gn:admin2_code":"623",
    "gn:admin3_code":"62386.0",
    "gn:asciiname":"Grubberg",
    "gn:country_code":"AT",
    "gn:dem":371,
    "gn:feature_class":"P",
    "gn:feature_code":"PPL",
    "gn:name":"Grubberg",
    "gn:population":0,
    "gn:timezone":"Europe/Vienna",
    "iso:country":"AT",
    "wof:name":"Grubberg",
    "wof:placetype":"locality"
},
  "geometry": {"coordinates":[15.93333,47.03333],"type":"Point"}
}