{
  "type": "Feature",
  "properties": {
    "gn:admin1_code":"2.0",
    "gn:admin2_code":"210",
    "gn:admin3_code":"21002.0",
    "gn:asciiname":"Metzing",
    "gn:country_code":"AT",
    "gn:dem":671,
    "gn:feature_class":"P",
    "gn:feature_code":"PPL",
    "gn:name":"Metzing",
    "gn:population":185,
    "gn:timezone":"Europe/Vienna",
    "iso:country":"AT",
    "wof:name":"Metzing",
    "wof:placetype":"locality",
    "wof:population":185
},
  "geometry": {"coordinates":[14.07632,46.73383],"type":"Point"}
}