{
  "type": "Feature",
  "properties": {
    "gn:admin1_code":"2.0",
    "gn:admin2_code":"210",
    "gn:admin3_code":"21002.0",
    "gn:asciiname":"Metzing",
    "gn:country_code":"AT",
    "gn:dem":671,
    "gn:feature_class":"P",
    "gn:feature_code":"PPL",
    "gn:name":"Metzing",
    "gn:population":185,
    "gn:timezone":"Europe/Vienna",
    "iso:country":"AT",
    "name:als_x_preferred":[
        "Metzingen"
    ],
    "name:cat_x_preferred":[
        "Metzing"
    ],
    "name:ceb_x_preferred":[
        "Metzing"
    ],
    "name:deu_x_preferred":[
        "Metzing"
    ],
    "name:eus_x_preferred":[
        "Metzing"
    ],
    "name:fas_x_preferred":[
        "\u0645\u062a\u0633\u06cc\u0646\u06af"
    ],
    "name:fra_x_preferred":[
        "Metzing"
    ],
    "name:hun_x_preferred":[
        "Metzing"
    ],
    "name:ita_x_preferred":[
        "Metzing"
    ],
    "name:kaz_x_preferred":[
        "\u041c\u0435\u0446\u0435\u043d"
    ],
    "name:lat_x_preferred":[
        "Metzing"
    ],
    "name:ltz_x_preferred":[
        "Metzing"
    ],
    "name:msa_x_preferred":[
        "Metzing"
    ],
    "name:nld_x_preferred":[
        "Metzing"
    ],
    "name:oci_x_preferred":[
        "Metzing"
    ],
    "name:pfl_x_preferred":[
        "Metzing"
    ],
    "name:pms_x_preferred":[
        "Metzing"
    ],
    "name:pol_x_preferred":[
        "Metzing"
    ],
    "name:por_x_preferred":[
        "Metzing"
    ],
    "name:rus_x_preferred":[
        "\u041c\u0435\u0446\u0435\u043d"
    ],
    "name:slk_x_preferred":[
        "Metzing"
    ],
    "name:spa_x_preferred":[
        "Metzing"
    ],
    "name:swe_x_preferred":[
        "Metzing"
    ],
    "name:ukr_x_preferred":[
        "\u041c\u0435\u0446\u0435\u043d"
    ],
    "name:uzb_x_preferred":[
        "Metzing"
    ],
    "name:vie_x_preferred":[
        "Metzing"
    ],
    "name:vol_x_preferred":[
        "Metzing"
    ],
    "name:war_x_preferred":[
        "Metzing"
    ],
    "name:zho_x_preferred":[
        "\u6885\u7279\u8d5e"
    ],
    "wof:name":"Metzing",
    "wof:placetype":"locality",
    "wof:population":185
},
  "geometry": {"coordinates":[14.07632,46.73383],"type":"Point"}
}