{
  "type": "Feature",
  "properties": {
    "gn:admin1_code":"3.0",
    "gn:admin2_code":"316",
    "gn:admin3_code":"31630.0",
    "gn:asciiname":"Herrnleis",
    "gn:country_code":"AT",
    "gn:dem":272,
    "gn:feature_class":"P",
    "gn:feature_code":"PPL",
    "gn:name":"Herrnleis",
    "gn:population":138,
    "gn:timezone":"Europe/Vienna",
    "iso:country":"AT",
    "wof:name":"Herrnleis",
    "wof:placetype":"locality",
    "wof:population":138
},
  "geometry": {"coordinates":[16.43333,48.51667],"type":"Point"}
}