{
  "type": "Feature",
  "properties": {
    "gn:admin1_code":"4.0",
    "gn:admin2_code":"412",
    "gn:admin3_code":"41231.0",
    "gn:asciiname":"Grosswimm",
    "gn:country_code":"AT",
    "gn:dem":449,
    "gn:feature_class":"P",
    "gn:feature_code":"PPL",
    "gn:name":"Gro\u00dfwimm",
    "gn:population":0,
    "gn:timezone":"Europe/Vienna",
    "iso:country":"AT",
    "wof:name":"Grosswimm",
    "wof:placetype":"locality"
},
  "geometry": {"coordinates":[13.58133,48.27128],"type":"Point"}
}