{
  "type": "Feature",
  "properties": {
    "gn:admin1_code":"08",
    "gn:admin2_code":"802.0",
    "gn:admin3_code":"80204.0",
    "gn:asciiname":"Vorsaess Schoenenbach",
    "gn:country_code":"AT",
    "gn:dem":1022,
    "gn:feature_class":"P",
    "gn:feature_code":"PPLF",
    "gn:name":"Vors\u00e4\u00df Sch\u00f6nenbach",
    "gn:population":0,
    "gn:timezone":"Europe/Vienna",
    "iso:country":"AT",
    "name:und_x_variant":[
        "Sch\u00f6nenbach"
    ],
    "wof:name":"Vorsaess Schoenenbach",
    "wof:placetype":"locality"
},
  "geometry": {"coordinates":[10.02944,47.37472],"type":"Point"}
}