{
  "type": "Feature",
  "properties": {
    "gn:admin1_code":"04",
    "gn:admin2_code":"411.0",
    "gn:admin3_code":"41125.0",
    "gn:asciiname":"Schlossberg",
    "gn:country_code":"AT",
    "gn:dem":482,
    "gn:feature_class":"P",
    "gn:feature_code":"PPL",
    "gn:name":"Schlossberg",
    "gn:population":0,
    "gn:timezone":"Europe/Vienna",
    "iso:country":"AT",
    "name:ceb_x_preferred":[
        "Schlossberg"
    ],
    "name:deu_x_preferred":[
        "Schlossberg"
    ],
    "name:fra_x_preferred":[
        "Schlossberg"
    ],
    "name:ita_x_preferred":[
        "Schlo\u00dfberg"
    ],
    "name:nld_x_preferred":[
        "Schlo\u00dfberg"
    ],
    "name:pol_x_preferred":[
        "Schlossberg"
    ],
    "name:rus_x_preferred":[
        "\u0428\u043b\u043e\u0441\u0431\u0435\u0440\u0433"
    ],
    "name:slk_x_preferred":[
        "Schlossberg"
    ],
    "name:swe_x_preferred":[
        "Schlossberg"
    ],
    "name:und_x_variant":[
        "Schlo\u00dfberg"
    ],
    "wof:name":"Schlossberg",
    "wof:placetype":"locality"
},
  "geometry": {"coordinates":[14.95119,48.28188],"type":"Point"}
}