{
  "type": "Feature",
  "properties": {
    "gn:admin1_code":"04",
    "gn:admin2_code":"417.0",
    "gn:admin3_code":"41716.0",
    "gn:asciiname":"Wegleiten",
    "gn:country_code":"AT",
    "gn:dem":472,
    "gn:feature_class":"P",
    "gn:feature_code":"PPL",
    "gn:name":"Wegleiten",
    "gn:population":34,
    "gn:timezone":"Europe/Vienna",
    "iso:country":"AT",
    "wof:name":"Wegleiten",
    "wof:placetype":"locality",
    "wof:population":34
},
  "geometry": {"coordinates":[13.5552,48.03422],"type":"Point"}
}