{
  "type": "Feature",
  "properties": {
    "gn:admin1_code":"6.0",
    "gn:admin2_code":"620",
    "gn:admin3_code":"62032.0",
    "gn:asciiname":"Moeschitzgraben",
    "gn:country_code":"AT",
    "gn:dem":1303,
    "gn:feature_class":"P",
    "gn:feature_code":"PPL",
    "gn:name":"M\u00f6schitzgraben",
    "gn:population":64,
    "gn:timezone":"Europe/Vienna",
    "iso:country":"AT",
    "wof:name":"Moeschitzgraben",
    "wof:placetype":"locality",
    "wof:population":64
},
  "geometry": {"coordinates":[14.55,47.15],"type":"Point"}
}