{
  "type": "Feature",
  "properties": {
    "gn:admin1_code":"2.0",
    "gn:admin2_code":"210",
    "gn:admin3_code":"21008.0",
    "gn:asciiname":"Gall",
    "gn:country_code":"AT",
    "gn:dem":1117,
    "gn:feature_class":"P",
    "gn:feature_code":"PPL",
    "gn:name":"Gall",
    "gn:population":44,
    "gn:timezone":"Europe/Vienna",
    "iso:country":"AT",
    "wof:name":"Gall",
    "wof:placetype":"locality",
    "wof:population":44
},
  "geometry": {"coordinates":[14.16385,46.7608],"type":"Point"}
}