{
  "type": "Feature",
  "properties": {
    "gn:admin1_code":"2.0",
    "gn:admin2_code":"210",
    "gn:admin3_code":"21008.0",
    "gn:asciiname":"Gall",
    "gn:country_code":"AT",
    "gn:dem":1117,
    "gn:feature_class":"P",
    "gn:feature_code":"PPL",
    "gn:name":"Gall",
    "gn:population":44,
    "gn:timezone":"Europe/Vienna",
    "iso:country":"AT",
    "name:ara_x_preferred":[
        "\u0639\u0641\u0635\u0629"
    ],
    "name:cat_x_preferred":[
        "Agalla"
    ],
    "name:ces_x_preferred":[
        "H\u00e1lka"
    ],
    "name:dan_x_preferred":[
        "Galle"
    ],
    "name:deu_x_preferred":[
        "Pflanzengalle"
    ],
    "name:epo_x_preferred":[
        "Gajlo"
    ],
    "name:est_x_preferred":[
        "Pahk"
    ],
    "name:eus_x_preferred":[
        "Zezidio"
    ],
    "name:fas_x_preferred":[
        "\u06af\u0627\u0644"
    ],
    "name:fin_x_preferred":[
        "\u00c4k\u00e4m\u00e4"
    ],
    "name:fra_x_preferred":[
        "Galle"
    ],
    "name:gle_x_preferred":[
        "G\u00e1l"
    ],
    "name:glg_x_preferred":[
        "Bugallo"
    ],
    "name:heb_x_preferred":[
        "\u05e2\u05e4\u05e5"
    ],
    "name:hun_x_preferred":[
        "Gubacs"
    ],
    "name:ido_x_preferred":[
        "Galo"
    ],
    "name:ita_x_preferred":[
        "Galla"
    ],
    "name:jpn_x_preferred":[
        "\u866b\u3053\u3076"
    ],
    "name:kaz_x_preferred":[
        "\u0413\u0430\u043b\u043b"
    ],
    "name:kir_x_preferred":[
        "\u0413\u0430\u043b\u043b\u0434\u0430\u0440"
    ],
    "name:lat_x_preferred":[
        "Galla"
    ],
    "name:lit_x_preferred":[
        "Galas"
    ],
    "name:mal_x_preferred":[
        "\u0d17\u0d3e\u0d7e"
    ],
    "name:nld_x_preferred":[
        "Gal"
    ],
    "name:nor_x_preferred":[
        "Galle"
    ],
    "name:pol_x_preferred":[
        "Galas"
    ],
    "name:por_x_preferred":[
        "Galha"
    ],
    "name:ron_x_preferred":[
        "Gal\u0103"
    ],
    "name:rus_x_preferred":[
        "\u0413\u0430\u043b\u043b"
    ],
    "name:slk_x_preferred":[
        "H\u00e1lka"
    ],
    "name:spa_x_preferred":[
        "Agalla"
    ],
    "name:swe_x_preferred":[
        "Gallbildning"
    ],
    "name:ukr_x_preferred":[
        "\u0413\u0430\u043b"
    ],
    "wof:name":"Gall",
    "wof:placetype":"locality",
    "wof:population":44
},
  "geometry": {"coordinates":[14.16385,46.7608],"type":"Point"}
}