{
  "type": "Feature",
  "properties": {
    "gn:admin1_code":"3.0",
    "gn:admin2_code":"307",
    "gn:admin3_code":"30711.0",
    "gn:asciiname":"Haslau an der Donau",
    "gn:cc2":"AT",
    "gn:country_code":"AT",
    "gn:dem":187,
    "gn:feature_class":"P",
    "gn:feature_code":"PPL",
    "gn:name":"Haslau an der Donau",
    "gn:population":974,
    "gn:timezone":"Europe/Vienna",
    "iso:country":"AT",
    "name:und_x_variant":[
        "Haslau",
        "Haslau an der Donau"
    ],
    "wof:name":"Haslau an der Donau",
    "wof:placetype":"locality",
    "wof:population":974
},
  "geometry": {"coordinates":[16.71667,48.11667],"type":"Point"}
}