{
  "type": "Feature",
  "properties": {
    "gn:admin1_code":"06",
    "gn:asciiname":"Packwinkel",
    "gn:country_code":"AT",
    "gn:dem":1207,
    "gn:feature_class":"P",
    "gn:feature_code":"PPL",
    "gn:name":"Packwinkel",
    "gn:population":0,
    "gn:timezone":"Europe/Vienna",
    "iso:country":"AT",
    "wof:name":"Packwinkel",
    "wof:placetype":"locality"
},
  "geometry": {"coordinates":[14.98333,46.95],"type":"Point"}
}