{
  "type": "Feature",
  "properties": {
    "gn:admin1_code":"4.0",
    "gn:admin2_code":"417",
    "gn:admin3_code":"41752.0",
    "gn:asciiname":"Kalletsberg",
    "gn:country_code":"AT",
    "gn:dem":589,
    "gn:feature_class":"P",
    "gn:feature_code":"PPL",
    "gn:name":"Kalletsberg",
    "gn:population":40,
    "gn:timezone":"Europe/Vienna",
    "iso:country":"AT",
    "wof:name":"Kalletsberg",
    "wof:placetype":"locality",
    "wof:population":40
},
  "geometry": {"coordinates":[13.61691,48.06692],"type":"Point"}
}