{
  "type": "Feature",
  "properties": {
    "gn:admin1_code":"4.0",
    "gn:admin2_code":"417",
    "gn:admin3_code":"41722.0",
    "gn:asciiname":"Vornwald",
    "gn:country_code":"AT",
    "gn:dem":525,
    "gn:feature_class":"P",
    "gn:feature_code":"PPL",
    "gn:name":"Vornwald",
    "gn:population":16,
    "gn:timezone":"Europe/Vienna",
    "iso:country":"AT",
    "wof:name":"Vornwald",
    "wof:placetype":"locality",
    "wof:population":16
},
  "geometry": {"coordinates":[13.64545,48.07415],"type":"Point"}
}