{
  "type": "Feature",
  "properties": {
    "gn:admin1_code":"3.0",
    "gn:admin2_code":"316",
    "gn:admin3_code":"31633.0",
    "gn:asciiname":"Ausser dem Steinhubel",
    "gn:country_code":"AT",
    "gn:dem":204,
    "gn:feature_class":"P",
    "gn:feature_code":"PPLL",
    "gn:name":"Au\u00dfer dem Steinh\u00fcbel",
    "gn:population":0,
    "gn:timezone":"Europe/Vienna",
    "iso:country":"AT",
    "wof:name":"Ausser dem Steinhubel",
    "wof:placetype":"locality"
},
  "geometry": {"coordinates":[16.52222,48.57111],"type":"Point"}
}