{
  "type": "Feature",
  "properties": {
    "gn:admin1_code":"07",
    "gn:admin2_code":"702.0",
    "gn:admin3_code":"70213.0",
    "gn:asciiname":"Pipurg",
    "gn:country_code":"AT",
    "gn:dem":1774,
    "gn:feature_class":"P",
    "gn:feature_code":"PPL",
    "gn:name":"Pipurg",
    "gn:population":0,
    "gn:timezone":"Europe/Vienna",
    "iso:country":"AT",
    "wof:name":"Pipurg",
    "wof:placetype":"locality"
},
  "geometry": {"coordinates":[10.88333,47.28333],"type":"Point"}
}