{
  "type": "Feature",
  "properties": {
    "gn:admin1_code":"6.0",
    "gn:admin2_code":"622",
    "gn:admin3_code":"62256.0",
    "gn:asciiname":"Vockenberg",
    "gn:country_code":"AT",
    "gn:dem":411,
    "gn:feature_class":"P",
    "gn:feature_code":"PPL",
    "gn:name":"Vockenberg",
    "gn:population":391,
    "gn:timezone":"Europe/Vienna",
    "iso:country":"AT",
    "wof:name":"Vockenberg",
    "wof:placetype":"locality",
    "wof:population":391
},
  "geometry": {"coordinates":[15.83417,47.23533],"type":"Point"}
}