{
  "type": "Feature",
  "properties": {
    "gn:admin1_code":"03",
    "gn:admin2_code":"323.0",
    "gn:admin3_code":"32325.0",
    "gn:asciiname":"Schlattental",
    "gn:cc2":"AT",
    "gn:country_code":"AT",
    "gn:dem":527,
    "gn:feature_class":"P",
    "gn:feature_code":"PPL",
    "gn:name":"Schlattental",
    "gn:population":0,
    "gn:timezone":"Europe/Vienna",
    "iso:country":"AT",
    "name:und_x_variant":[
        "Schlattenthal",
        "Schlattental"
    ],
    "wof:name":"Schlattental",
    "wof:placetype":"locality"
},
  "geometry": {"coordinates":[16.23333,47.65],"type":"Point"}
}