{
  "type": "Feature",
  "properties": {
    "gn:admin1_code":"02",
    "gn:admin2_code":"206.0",
    "gn:admin3_code":"20644.0",
    "gn:asciiname":"Zandlach",
    "gn:country_code":"AT",
    "gn:dem":873,
    "gn:feature_class":"P",
    "gn:feature_code":"PPL",
    "gn:name":"Zandlach",
    "gn:population":249,
    "gn:timezone":"Europe/Vienna",
    "iso:country":"AT",
    "wof:name":"Zandlach",
    "wof:placetype":"locality",
    "wof:population":249
},
  "geometry": {"coordinates":[13.31667,46.88333],"type":"Point"}
}