{
  "type": "Feature",
  "properties": {
    "gn:gn_country":"AT",
    "gn:gn_fcode":"PPLA3",
    "gn:gn_pop":0,
    "iso:country":"AT",
    "name:bar_x_preferred":[
        "L\u00e5ngk\u00e5mpfn"
    ],
    "name:deu_x_preferred":[
        "Langkampfen"
    ],
    "name:eng_x_preferred":[
        "Langkampfen"
    ],
    "name:fra_x_preferred":[
        "Langkampfen"
    ],
    "name:hun_x_preferred":[
        "Langkampfen"
    ],
    "name:ita_x_preferred":[
        "Langkampfen"
    ],
    "name:kaz_x_preferred":[
        "\u041b\u0430\u043d\u0433\u0430\u043c\u043f\u0444\u0435\u043d"
    ],
    "name:lmo_x_preferred":[
        "Langkampfen"
    ],
    "name:nld_x_preferred":[
        "Langkampfen"
    ],
    "name:pnb_x_preferred":[
        "\u0644\u0627\u0646\u06af\u06a9\u0627\u0645\u067e\u0641\u0646"
    ],
    "name:pol_x_preferred":[
        "Langkampfen"
    ],
    "name:rus_x_preferred":[
        "\u041b\u0430\u043d\u0433\u043a\u0430\u043c\u043f\u0444\u0435\u043d"
    ],
    "name:slk_x_preferred":[
        "Langkampfen"
    ],
    "name:swe_x_preferred":[
        "Langkampfen"
    ],
    "name:ukr_x_preferred":[
        "\u041b\u0430\u043d\u0433\u043a\u0430\u043c\u043f\u0444\u0435\u043d"
    ],
    "name:uzb_x_preferred":[
        "Langkampfen"
    ],
    "name:vol_x_preferred":[
        "Langkampfen"
    ],
    "name:war_x_preferred":[
        "Langkampfen"
    ],
    "name:zho_x_preferred":[
        "Langkampfen"
    ],
    "qs_pg:aaroncc":"AT",
    "qs_pg:gn_country":"AT",
    "qs_pg:gn_fcode":"PPLA3",
    "qs_pg:gn_pop":0,
    "qs_pg:name":"Langkampfen",
    "qs_pg:name_adm0":"\u00d6sterreich",
    "qs_pg:name_adm1":"Tirol",
    "qs_pg:photos_9k":1,
    "qs_pg:photos_9r":1,
    "qs_pg:photos_all":1,
    "qs_pg:photos_sr":0,
    "qs_pg:pop_sr":0,
    "qs_pg:qs_pg_placetype":"locality",
    "qs_pg:qs_pg_placetype_gp":"Town",
    "qs_pg:woe_adm0":23424750,
    "woe:adm0_id":23424750,
    "woe:name_adm0":"\u00d6sterreich",
    "woe:name_adm1":"Tirol",
    "woe:placetype":"Town",
    "wof:name":"Langkampfen",
    "wof:placetype":"locality"
},
  "geometry": {"coordinates":[12.09325,47.55111],"type":"Point"}
}