{
  "type": "Feature",
  "properties": {
    "gn:admin1_code":"7.0",
    "gn:admin2_code":"705",
    "gn:admin3_code":"70530.0",
    "gn:asciiname":"Haus",
    "gn:country_code":"AT",
    "gn:dem":891,
    "gn:feature_class":"P",
    "gn:feature_code":"PPL",
    "gn:name":"Haus",
    "gn:population":0,
    "gn:timezone":"Europe/Vienna",
    "iso:country":"AT",
    "name:ceb_x_preferred":[
        "Haus"
    ],
    "name:deu_x_preferred":[
        "Haus"
    ],
    "name:fin_x_preferred":[
        "Haus"
    ],
    "name:fra_x_preferred":[
        "Haus"
    ],
    "name:ita_x_preferred":[
        "Haus"
    ],
    "name:nds_x_preferred":[
        "Haus"
    ],
    "name:pol_x_preferred":[
        "Haus"
    ],
    "name:slv_x_preferred":[
        "Haus"
    ],
    "name:swe_x_preferred":[
        "Haus"
    ],
    "wof:name":"Haus",
    "wof:placetype":"locality"
},
  "geometry": {"coordinates":[12.06667,47.45],"type":"Point"}
}