{
  "type": "Feature",
  "properties": {
    "gn:admin1_code":"3.0",
    "gn:admin2_code":"313",
    "gn:admin3_code":"31302.0",
    "gn:asciiname":"Attenreith",
    "gn:country_code":"AT",
    "gn:dem":681,
    "gn:feature_class":"P",
    "gn:feature_code":"PPL",
    "gn:name":"Attenreith",
    "gn:population":96,
    "gn:timezone":"Europe/Vienna",
    "iso:country":"AT",
    "wof:name":"Attenreith",
    "wof:placetype":"locality",
    "wof:population":96
},
  "geometry": {"coordinates":[15.33476,48.46179],"type":"Point"}
}