{
  "type": "Feature",
  "properties": {
    "gn:admin1_code":"5.0",
    "gn:admin2_code":"503",
    "gn:admin3_code":"50326.0",
    "gn:asciiname":"Lindach",
    "gn:country_code":"AT",
    "gn:dem":425,
    "gn:feature_class":"P",
    "gn:feature_code":"PPL",
    "gn:name":"Lindach",
    "gn:population":0,
    "gn:timezone":"Europe/Vienna",
    "iso:country":"AT",
    "wof:name":"Lindach",
    "wof:placetype":"locality"
},
  "geometry": {"coordinates":[12.95,47.93778],"type":"Point"}
}