{
  "type": "Feature",
  "properties": {
    "gn:admin1_code":"4.0",
    "gn:admin2_code":"415",
    "gn:admin3_code":"41521.0",
    "gn:asciiname":"Hagleiten",
    "gn:country_code":"AT",
    "gn:dem":318,
    "gn:feature_class":"P",
    "gn:feature_code":"PPL",
    "gn:name":"Hagleiten",
    "gn:population":0,
    "gn:timezone":"Europe/Vienna",
    "iso:country":"AT",
    "wof:name":"Hagleiten",
    "wof:placetype":"locality"
},
  "geometry": {"coordinates":[14.37037,48.12061],"type":"Point"}
}