{
  "type": "Feature",
  "properties": {
    "gn:admin1_code":"6.0",
    "gn:admin2_code":"622",
    "gn:admin3_code":"62205.0",
    "gn:asciiname":"Tonleiten",
    "gn:country_code":"AT",
    "gn:dem":364,
    "gn:feature_class":"P",
    "gn:feature_code":"PPL",
    "gn:name":"Tonleiten",
    "gn:population":0,
    "gn:timezone":"Europe/Vienna",
    "iso:country":"AT",
    "wof:name":"Tonleiten",
    "wof:placetype":"locality"
},
  "geometry": {"coordinates":[16.01751,47.25276],"type":"Point"}
}