{
  "type": "Feature",
  "properties": {
    "gn:admin1_code":"04",
    "gn:admin2_code":"414.0",
    "gn:admin3_code":"41420.0",
    "gn:asciiname":"Steinerzaun",
    "gn:country_code":"AT",
    "gn:dem":554,
    "gn:feature_class":"P",
    "gn:feature_code":"PPL",
    "gn:name":"Steinerzaun",
    "gn:population":25,
    "gn:timezone":"Europe/Vienna",
    "iso:country":"AT",
    "wof:name":"Steinerzaun",
    "wof:placetype":"locality",
    "wof:population":25
},
  "geometry": {"coordinates":[13.61318,48.46012],"type":"Point"}
}