{
  "type": "Feature",
  "properties": {
    "gn:admin1_code":"07",
    "gn:admin2_code":"709.0",
    "gn:admin3_code":"70938.0",
    "gn:asciiname":"Rieder",
    "gn:country_code":"AT",
    "gn:dem":1106,
    "gn:feature_class":"P",
    "gn:feature_code":"PPL",
    "gn:name":"Rieder",
    "gn:population":0,
    "gn:timezone":"Europe/Vienna",
    "iso:country":"AT",
    "wof:name":"Rieder",
    "wof:placetype":"locality"
},
  "geometry": {"coordinates":[11.68333,47.26667],"type":"Point"}
}