{
  "type": "Feature",
  "properties": {
    "gn:admin1_code":"07",
    "gn:admin2_code":"709.0",
    "gn:admin3_code":"70938.0",
    "gn:asciiname":"Rieder",
    "gn:country_code":"AT",
    "gn:dem":1106,
    "gn:feature_class":"P",
    "gn:feature_code":"PPL",
    "gn:name":"Rieder",
    "gn:population":0,
    "gn:timezone":"Europe/Vienna",
    "iso:country":"AT",
    "name:bak_x_preferred":[
        "\u0420\u0438\u0434\u0435\u0440"
    ],
    "name:ceb_x_preferred":[
        "Rieder"
    ],
    "name:deu_x_preferred":[
        "Rieder"
    ],
    "name:epo_x_preferred":[
        "Rieder"
    ],
    "name:fas_x_preferred":[
        "\u0631\u0627\u06cc\u062f\u0631"
    ],
    "name:ita_x_preferred":[
        "Rieder"
    ],
    "name:kaz_x_preferred":[
        "\u0420\u0438\u0434\u0435\u0440"
    ],
    "name:kir_x_preferred":[
        "\u0420\u0438\u0434\u0435\u0440"
    ],
    "name:mkd_x_preferred":[
        "\u0420\u0438\u0434\u0435\u0440"
    ],
    "name:nld_x_preferred":[
        "Rieder"
    ],
    "name:pol_x_preferred":[
        "Rieder"
    ],
    "name:ron_x_preferred":[
        "Rieder"
    ],
    "name:rus_x_preferred":[
        "\u0420\u0438\u0434\u0435\u0440"
    ],
    "name:srp_x_preferred":[
        "\u0420\u0438\u0434\u0435\u0440"
    ],
    "name:uzb_x_preferred":[
        "Rieder"
    ],
    "name:vie_x_preferred":[
        "Rieder"
    ],
    "name:vol_x_preferred":[
        "Rieder"
    ],
    "name:war_x_preferred":[
        "Rieder"
    ],
    "wof:name":"Rieder",
    "wof:placetype":"locality"
},
  "geometry": {"coordinates":[11.68333,47.26667],"type":"Point"}
}