{
  "type": "Feature",
  "properties": {
    "gn:admin1_code":"2.0",
    "gn:admin2_code":"203",
    "gn:admin3_code":"20316.0",
    "gn:asciiname":"Bach",
    "gn:country_code":"AT",
    "gn:dem":714,
    "gn:feature_class":"P",
    "gn:feature_code":"PPL",
    "gn:name":"Bach",
    "gn:population":68,
    "gn:timezone":"Europe/Vienna",
    "iso:country":"AT",
    "wof:name":"Bach",
    "wof:placetype":"locality",
    "wof:population":68
},
  "geometry": {"coordinates":[13.52172,46.62006],"type":"Point"}
}