{
  "type": "Feature",
  "properties": {
    "iso:country":"AT",
    "name:deu_x_preferred":[
        "Haselstauden"
    ],
    "name:eng_x_preferred":[
        "Haselstauden"
    ],
    "name:fra_x_preferred":[
        "Haselstauden"
    ],
    "name:lat_x_preferred":[
        "Arborcoryli"
    ],
    "name:nld_x_preferred":[
        "Haselstauden"
    ],
    "qs:gn_adm0_cc":"AT",
    "qs:gn_fcode":"PPLX",
    "qs:gn_local":7872673,
    "qs:gn_nam_loc":"Dornbirn, Dornbirn, Vorarlberg, AT",
    "qs:gn_namadm1":"08",
    "qs:gn_name":"Haselstauden",
    "qs:local_max":922,
    "qs:local_sum":1738,
    "qs:localhoods":4,
    "qs:name":"Haselstauden",
    "qs:name_adm0":"\u00d6sterreich",
    "qs:name_adm1":"Vorarlberg",
    "qs:name_adm2":"Dornbirn",
    "qs:name_lau":"Dornbirn",
    "qs:name_local":"Dornbirn",
    "qs:photo_max":25,
    "qs:photo_sum":67,
    "qs:placetype":"Suburb",
    "qs:quad_count":20,
    "qs:woe_adm0":23424750,
    "qs:woe_adm1":2344715,
    "qs:woe_adm2":12591753,
    "qs:woe_lau":12675635,
    "qs:woe_local":12675635,
    "qs:woe_ver":"7.10.0",
    "wd:wordcount":76,
    "wof:lang":[
        "ger"
    ],
    "wof:name":"Haselstauden",
    "wof:placetype":"neighbourhood"
},
  "geometry": {"coordinates":[9.749833,47.431719],"type":"Point"}
}