{
  "type": "Feature",
  "properties": {
    "gn:admin1_code":"2.0",
    "gn:admin2_code":"207",
    "gn:admin3_code":"20721.0",
    "gn:asciiname":"Buchheim",
    "gn:country_code":"AT",
    "gn:dem":622,
    "gn:feature_class":"P",
    "gn:feature_code":"PPL",
    "gn:name":"Buchheim",
    "gn:population":84,
    "gn:timezone":"Europe/Vienna",
    "iso:country":"AT",
    "wof:name":"Buchheim",
    "wof:placetype":"locality",
    "wof:population":84
},
  "geometry": {"coordinates":[13.99361,46.56917],"type":"Point"}
}