{
  "type": "Feature",
  "properties": {
    "gn:admin1_code":"2.0",
    "gn:admin2_code":"207",
    "gn:admin3_code":"20721.0",
    "gn:asciiname":"Buchheim",
    "gn:country_code":"AT",
    "gn:dem":622,
    "gn:feature_class":"P",
    "gn:feature_code":"PPL",
    "gn:name":"Buchheim",
    "gn:population":84,
    "gn:timezone":"Europe/Vienna",
    "iso:country":"AT",
    "name:als_x_preferred":[
        "Buchheim"
    ],
    "name:ceb_x_preferred":[
        "Buchheim"
    ],
    "name:deu_x_preferred":[
        "Buchheim"
    ],
    "name:epo_x_preferred":[
        "Buchheim"
    ],
    "name:eus_x_preferred":[
        "Buchheim"
    ],
    "name:fas_x_preferred":[
        "\u0628\u0648\u062e\u0647\u0627\u06cc\u0645"
    ],
    "name:fra_x_preferred":[
        "Buchheim"
    ],
    "name:hun_x_preferred":[
        "Buchheim"
    ],
    "name:ita_x_preferred":[
        "Buchheim"
    ],
    "name:kaz_x_preferred":[
        "\u0411\u0443\u0445\u0433\u0430\u0439\u043c"
    ],
    "name:kir_x_preferred":[
        "\u0411\u0443\u0445\u0433\u0430\u0439\u043c"
    ],
    "name:lat_x_preferred":[
        "Buchheim"
    ],
    "name:lmo_x_preferred":[
        "Buchheim"
    ],
    "name:msa_x_preferred":[
        "Buchheim"
    ],
    "name:nld_x_preferred":[
        "Buchheim"
    ],
    "name:pol_x_preferred":[
        "Buchheim"
    ],
    "name:por_x_preferred":[
        "Buchheim"
    ],
    "name:ron_x_preferred":[
        "Buchheim"
    ],
    "name:rus_x_preferred":[
        "\u0411\u0443\u0445\u0445\u0430\u0439\u043c"
    ],
    "name:srp_x_preferred":[
        "\u0411\u0443\u0445\u0430\u0458\u043c"
    ],
    "name:uzb_x_preferred":[
        "Buchheim"
    ],
    "name:vie_x_preferred":[
        "Buchheim"
    ],
    "name:vol_x_preferred":[
        "Buchheim"
    ],
    "name:war_x_preferred":[
        "Buchheim"
    ],
    "name:zho_x_preferred":[
        "\u5e03\u8d6b\u6d77\u59c6"
    ],
    "wof:name":"Buchheim",
    "wof:placetype":"locality",
    "wof:population":84
},
  "geometry": {"coordinates":[13.99361,46.56917],"type":"Point"}
}