{
  "type": "Feature",
  "properties": {
    "gn:admin1_code":"3.0",
    "gn:admin2_code":"325",
    "gn:admin3_code":"32508.0",
    "gn:asciiname":"Nondorf",
    "gn:cc2":"AT",
    "gn:country_code":"AT",
    "gn:dem":720,
    "gn:feature_class":"P",
    "gn:feature_code":"PPL",
    "gn:name":"Nondorf",
    "gn:population":92,
    "gn:timezone":"Europe/Vienna",
    "iso:country":"AT",
    "name:und_x_variant":[
        "Nonndorf",
        "Nondorf"
    ],
    "wof:name":"Nondorf",
    "wof:placetype":"locality",
    "wof:population":92
},
  "geometry": {"coordinates":[14.88333,48.61667],"type":"Point"}
}