{
  "type": "Feature",
  "properties": {
    "gn:admin1_code":"04",
    "gn:admin2_code":"418.0",
    "gn:admin3_code":"41804.0",
    "gn:asciiname":"Schnadt",
    "gn:country_code":"AT",
    "gn:dem":384,
    "gn:feature_class":"P",
    "gn:feature_code":"PPL",
    "gn:name":"Schnadt",
    "gn:population":133,
    "gn:timezone":"Europe/Vienna",
    "iso:country":"AT",
    "wof:name":"Schnadt",
    "wof:placetype":"locality",
    "wof:population":133
},
  "geometry": {"coordinates":[14.00826,48.23108],"type":"Point"}
}