{
  "type": "Feature",
  "properties": {
    "gn:admin1_code":"06",
    "gn:admin2_code":"622.0",
    "gn:admin3_code":"62275.0",
    "gn:asciiname":"Praetis",
    "gn:country_code":"AT",
    "gn:dem":600,
    "gn:feature_class":"P",
    "gn:feature_code":"PPL",
    "gn:name":"Pr\u00e4tis",
    "gn:population":569,
    "gn:timezone":"Europe/Vienna",
    "iso:country":"AT",
    "wof:name":"Praetis",
    "wof:placetype":"locality",
    "wof:population":569
},
  "geometry": {"coordinates":[15.81216,47.34589],"type":"Point"}
}