{
  "type": "Feature",
  "properties": {
    "gn:admin1_code":"03",
    "gn:admin2_code":"321.0",
    "gn:admin3_code":"32131.0",
    "gn:asciiname":"Reichersberg",
    "gn:country_code":"AT",
    "gn:dem":250,
    "gn:feature_class":"P",
    "gn:feature_code":"PPL",
    "gn:name":"Reichersberg",
    "gn:population":171,
    "gn:timezone":"Europe/Vienna",
    "iso:country":"AT",
    "wof:name":"Reichersberg",
    "wof:placetype":"locality",
    "wof:population":171
},
  "geometry": {"coordinates":[16.07077,48.26137],"type":"Point"}
}