{
  "type": "Feature",
  "properties": {
    "gn:admin1_code":"03",
    "gn:admin2_code":"321.0",
    "gn:admin3_code":"32131.0",
    "gn:asciiname":"Reichersberg",
    "gn:country_code":"AT",
    "gn:dem":250,
    "gn:feature_class":"P",
    "gn:feature_code":"PPL",
    "gn:name":"Reichersberg",
    "gn:population":171,
    "gn:timezone":"Europe/Vienna",
    "iso:country":"AT",
    "name:ceb_x_preferred":[
        "Reichersberg"
    ],
    "name:deu_x_preferred":[
        "Reichersberg"
    ],
    "name:fas_x_preferred":[
        "\u0631\u0627\u06cc\u0634\u0631\u0633\u0628\u0631\u06af"
    ],
    "name:fra_x_preferred":[
        "Reichersberg"
    ],
    "name:hun_x_preferred":[
        "Reichersberg"
    ],
    "name:ita_x_preferred":[
        "Reichersberg"
    ],
    "name:kaz_x_preferred":[
        "\u0420\u0430\u0439\u0445\u0435\u0440\u0441\u0431\u0435\u0440\u0433"
    ],
    "name:nld_x_preferred":[
        "Reichersberg"
    ],
    "name:pol_x_preferred":[
        "Reichersberg"
    ],
    "name:por_x_preferred":[
        "Reichersberg"
    ],
    "name:rus_x_preferred":[
        "\u0420\u0430\u0439\u0445\u0435\u0440\u0441\u0431\u0435\u0440\u0433"
    ],
    "name:slk_x_preferred":[
        "Reichersberg"
    ],
    "name:spa_x_preferred":[
        "Reichersberg"
    ],
    "name:ukr_x_preferred":[
        "\u0420\u0430\u0439\u0445\u0435\u0440\u0441\u0431\u0435\u0440\u0433"
    ],
    "name:uzb_x_preferred":[
        "Reichersberg"
    ],
    "name:vie_x_preferred":[
        "Reichersberg"
    ],
    "name:vol_x_preferred":[
        "Reichersberg"
    ],
    "name:war_x_preferred":[
        "Reichersberg"
    ],
    "name:zho_x_preferred":[
        "\u8d56\u8c22\u65af\u8d1d\u683c"
    ],
    "wof:name":"Reichersberg",
    "wof:placetype":"locality",
    "wof:population":171
},
  "geometry": {"coordinates":[16.07077,48.26137],"type":"Point"}
}