{
  "type": "Feature",
  "properties": {
    "gn:admin1_code":"02",
    "gn:admin2_code":"209.0",
    "gn:admin3_code":"20905.0",
    "gn:asciiname":"Untergoesel",
    "gn:country_code":"AT",
    "gn:dem":693,
    "gn:feature_class":"P",
    "gn:feature_code":"PPL",
    "gn:name":"Unterg\u00f6sel",
    "gn:population":239,
    "gn:timezone":"Europe/Vienna",
    "iso:country":"AT",
    "wof:name":"Untergoesel",
    "wof:placetype":"locality",
    "wof:population":239
},
  "geometry": {"coordinates":[14.88333,46.86667],"type":"Point"}
}