{
  "type": "Feature",
  "properties": {
    "gn:admin1_code":"03",
    "gn:admin2_code":"319.0",
    "gn:admin3_code":"31938.0",
    "gn:asciiname":"Rammersdorf",
    "gn:country_code":"AT",
    "gn:dem":249,
    "gn:feature_class":"P",
    "gn:feature_code":"PPL",
    "gn:name":"Rammersdorf",
    "gn:population":49,
    "gn:timezone":"Europe/Vienna",
    "iso:country":"AT",
    "wof:name":"Rammersdorf",
    "wof:placetype":"locality",
    "wof:population":49
},
  "geometry": {"coordinates":[15.50094,48.15097],"type":"Point"}
}