{
  "type": "Feature",
  "properties": {
    "gn:admin1_code":"6.0",
    "gn:admin2_code":"623",
    "gn:admin3_code":"62389.0",
    "gn:asciiname":"Krottendorf im Sasstal",
    "gn:cc2":"AT",
    "gn:country_code":"AT",
    "gn:dem":315,
    "gn:feature_class":"P",
    "gn:feature_code":"PPL",
    "gn:name":"Krottendorf im Sasstal",
    "gn:population":0,
    "gn:timezone":"Europe/Vienna",
    "iso:country":"AT",
    "name:und_x_variant":[
        "Krottendorf",
        "Krottendorf im Sasstal"
    ],
    "wof:name":"Krottendorf im Sasstal",
    "wof:placetype":"locality"
},
  "geometry": {"coordinates":[15.71667,46.88333],"type":"Point"}
}