{
  "type": "Feature",
  "properties": {
    "gn:admin1_code":"4.0",
    "gn:admin2_code":"404",
    "gn:admin3_code":"40401.0",
    "gn:asciiname":"Schwaig",
    "gn:country_code":"AT",
    "gn:dem":381,
    "gn:feature_class":"P",
    "gn:feature_code":"PPL",
    "gn:name":"Schwaig",
    "gn:population":13,
    "gn:timezone":"Europe/Vienna",
    "iso:country":"AT",
    "wof:name":"Schwaig",
    "wof:placetype":"locality",
    "wof:population":13
},
  "geometry": {"coordinates":[13.26595,48.22462],"type":"Point"}
}