{
  "type": "Feature",
  "properties": {
    "gn:admin1_code":"4.0",
    "gn:admin2_code":"404",
    "gn:admin3_code":"40429.0",
    "gn:asciiname":"Mundenham",
    "gn:country_code":"AT",
    "gn:dem":512,
    "gn:feature_class":"P",
    "gn:feature_code":"PPL",
    "gn:name":"Mundenham",
    "gn:population":186,
    "gn:timezone":"Europe/Vienna",
    "iso:country":"AT",
    "wof:name":"Mundenham",
    "wof:placetype":"locality",
    "wof:population":186
},
  "geometry": {"coordinates":[13.12785,48.00669],"type":"Point"}
}