{
  "type": "Feature",
  "properties": {
    "gn:admin1_code":"2.0",
    "gn:admin2_code":"205",
    "gn:admin3_code":"20530.0",
    "gn:asciiname":"Krassnitz",
    "gn:country_code":"AT",
    "gn:dem":871,
    "gn:feature_class":"P",
    "gn:feature_code":"PPL",
    "gn:name":"Krassnitz",
    "gn:population":0,
    "gn:timezone":"Europe/Vienna",
    "iso:country":"AT",
    "wof:name":"Krassnitz",
    "wof:placetype":"locality"
},
  "geometry": {"coordinates":[14.33333,46.93333],"type":"Point"}
}