{
  "type": "Feature",
  "properties": {
    "gn:admin1_code":"06",
    "gn:admin2_code":"622.0",
    "gn:admin3_code":"62233.0",
    "gn:asciiname":"Schaueregg",
    "gn:country_code":"AT",
    "gn:dem":875,
    "gn:feature_class":"P",
    "gn:feature_code":"PPL",
    "gn:name":"Schaueregg",
    "gn:population":266,
    "gn:timezone":"Europe/Vienna",
    "iso:country":"AT",
    "wof:name":"Schaueregg",
    "wof:placetype":"locality",
    "wof:population":266
},
  "geometry": {"coordinates":[16.03333,47.48333],"type":"Point"}
}