{
  "type": "Feature",
  "properties": {
    "gn:admin1_code":"3.0",
    "gn:admin2_code":"312",
    "gn:admin3_code":"31215.0",
    "gn:asciiname":"Hatzenbach",
    "gn:country_code":"AT",
    "gn:dem":184,
    "gn:feature_class":"P",
    "gn:feature_code":"PPL",
    "gn:name":"Hatzenbach",
    "gn:population":147,
    "gn:timezone":"Europe/Vienna",
    "iso:country":"AT",
    "wof:name":"Hatzenbach",
    "wof:placetype":"locality",
    "wof:population":147
},
  "geometry": {"coordinates":[16.21667,48.43333],"type":"Point"}
}