{
  "type": "Feature",
  "properties": {
    "gn:admin1_code":"07",
    "gn:admin2_code":"703.0",
    "gn:admin3_code":"70333.0",
    "gn:asciiname":"Oberweg",
    "gn:country_code":"AT",
    "gn:dem":1642,
    "gn:feature_class":"P",
    "gn:feature_code":"PPL",
    "gn:name":"Oberweg",
    "gn:population":672,
    "gn:timezone":"Europe/Vienna",
    "iso:country":"AT",
    "name:ceb_x_preferred":[
        "Oberweg"
    ],
    "name:deu_x_preferred":[
        "Oberweg"
    ],
    "name:fas_x_preferred":[
        "\u0627\u0648\u0628\u0631\u0648\u06af"
    ],
    "name:fra_x_preferred":[
        "Oberweg"
    ],
    "name:ita_x_preferred":[
        "Oberweg"
    ],
    "name:nld_x_preferred":[
        "Oberweg"
    ],
    "name:rus_x_preferred":[
        "\u041e\u0431\u0435\u0440\u0432\u0435\u0433"
    ],
    "name:slk_x_preferred":[
        "Oberweg"
    ],
    "name:swe_x_preferred":[
        "Oberweg"
    ],
    "name:uzb_x_preferred":[
        "Oberweg"
    ],
    "name:vie_x_preferred":[
        "Oberweg"
    ],
    "name:vol_x_preferred":[
        "Oberweg"
    ],
    "name:war_x_preferred":[
        "Oberweg"
    ],
    "name:zho_x_preferred":[
        "\u4e0a\u97e6\u683c"
    ],
    "wof:name":"Oberweg",
    "wof:placetype":"locality",
    "wof:population":672
},
  "geometry": {"coordinates":[11.51667,47.13333],"type":"Point"}
}