{
  "type": "Feature",
  "properties": {
    "gn:admin1_code":"5.0",
    "gn:admin2_code":"504",
    "gn:admin3_code":"50416.0",
    "gn:asciiname":"Dorfwerfen",
    "gn:country_code":"AT",
    "gn:dem":681,
    "gn:feature_class":"P",
    "gn:feature_code":"PPL",
    "gn:name":"Dorfwerfen",
    "gn:population":773,
    "gn:timezone":"Europe/Vienna",
    "iso:country":"AT",
    "wof:name":"Dorfwerfen",
    "wof:placetype":"locality",
    "wof:population":773
},
  "geometry": {"coordinates":[13.20603,47.45872],"type":"Point"}
}