{
  "type": "Feature",
  "properties": {
    "gn:admin1_code":"02",
    "gn:admin2_code":"205.0",
    "gn:admin3_code":"20506.0",
    "gn:asciiname":"Weissberg",
    "gn:cc2":"AT",
    "gn:country_code":"AT",
    "gn:dem":799,
    "gn:feature_class":"P",
    "gn:feature_code":"PPL",
    "gn:name":"Wei\u00dfberg",
    "gn:population":27,
    "gn:timezone":"Europe/Vienna",
    "iso:country":"AT",
    "name:und_x_variant":[
        "Weisberg",
        "Wei\u00dfberg"
    ],
    "wof:name":"Weissberg",
    "wof:placetype":"locality",
    "wof:population":27
},
  "geometry": {"coordinates":[14.10778,46.90028],"type":"Point"}
}