{
  "type": "Feature",
  "properties": {
    "gn:admin1_code":"06",
    "gn:admin2_code":"623.0",
    "gn:admin3_code":"62377.0",
    "gn:asciiname":"Schroettenberg",
    "gn:country_code":"AT",
    "gn:dem":325,
    "gn:feature_class":"P",
    "gn:feature_code":"PPL",
    "gn:name":"Schr\u00f6ttenberg",
    "gn:population":0,
    "gn:timezone":"Europe/Vienna",
    "iso:country":"AT",
    "wof:name":"Schroettenberg",
    "wof:placetype":"locality"
},
  "geometry": {"coordinates":[15.81667,46.78333],"type":"Point"}
}