{
  "type": "Feature",
  "properties": {
    "gn:admin1_code":"04",
    "gn:admin2_code":"417.0",
    "gn:admin3_code":"41741.0",
    "gn:asciiname":"Powang",
    "gn:country_code":"AT",
    "gn:dem":613,
    "gn:feature_class":"P",
    "gn:feature_code":"PPL",
    "gn:name":"Powang",
    "gn:population":82,
    "gn:timezone":"Europe/Vienna",
    "iso:country":"AT",
    "wof:name":"Powang",
    "wof:placetype":"locality",
    "wof:population":82
},
  "geometry": {"coordinates":[13.42607,47.89551],"type":"Point"}
}