{
  "type": "Feature",
  "properties": {
    "gn:admin1_code":"3.0",
    "gn:admin2_code":"325",
    "gn:admin3_code":"32515.0",
    "gn:asciiname":"Grossreinprechts",
    "gn:country_code":"AT",
    "gn:dem":710,
    "gn:feature_class":"P",
    "gn:feature_code":"PPL",
    "gn:name":"Gro\u00dfreinprechts",
    "gn:population":0,
    "gn:timezone":"Europe/Vienna",
    "iso:country":"AT",
    "wof:name":"Grossreinprechts",
    "wof:placetype":"locality"
},
  "geometry": {"coordinates":[15.30813,48.47774],"type":"Point"}
}