{
  "type": "Feature",
  "properties": {
    "gn:admin1_code":"1.0",
    "gn:admin2_code":"108",
    "gn:admin3_code":"10809.0",
    "gn:asciiname":"Hochstrass",
    "gn:country_code":"AT",
    "gn:dem":420,
    "gn:feature_class":"P",
    "gn:feature_code":"PPL",
    "gn:name":"Hochstra\u00df",
    "gn:population":201,
    "gn:timezone":"Europe/Vienna",
    "iso:country":"AT",
    "wof:name":"Hochstrass",
    "wof:placetype":"locality",
    "wof:population":201
},
  "geometry": {"coordinates":[16.40469,47.42873],"type":"Point"}
}