{
  "type": "Feature",
  "properties": {
    "gn:admin1_code":"4.0",
    "gn:admin2_code":"417",
    "gn:admin3_code":"41718.0",
    "gn:asciiname":"Streit",
    "gn:country_code":"AT",
    "gn:dem":740,
    "gn:feature_class":"P",
    "gn:feature_code":"PPL",
    "gn:name":"Streit",
    "gn:population":25,
    "gn:timezone":"Europe/Vienna",
    "iso:country":"AT",
    "wof:name":"Streit",
    "wof:placetype":"locality",
    "wof:population":25
},
  "geometry": {"coordinates":[13.49035,47.85141],"type":"Point"}
}