{
  "type": "Feature",
  "properties": {
    "gn:admin1_code":"4.0",
    "gn:admin2_code":"417",
    "gn:admin3_code":"41718.0",
    "gn:asciiname":"Mahtbauer",
    "gn:country_code":"AT",
    "gn:dem":757,
    "gn:feature_class":"P",
    "gn:feature_code":"PPL",
    "gn:name":"Mahtbauer",
    "gn:population":0,
    "gn:timezone":"Europe/Vienna",
    "iso:country":"AT",
    "wof:name":"Mahtbauer",
    "wof:placetype":"locality"
},
  "geometry": {"coordinates":[13.50632,47.86731],"type":"Point"}
}