{
  "type": "Feature",
  "properties": {
    "gn:admin1_code":"2.0",
    "gn:admin2_code":"205",
    "gn:admin3_code":"20515.0",
    "gn:asciiname":"Puppitsch",
    "gn:country_code":"AT",
    "gn:dem":585,
    "gn:feature_class":"P",
    "gn:feature_code":"PPL",
    "gn:name":"Puppitsch",
    "gn:population":11,
    "gn:timezone":"Europe/Vienna",
    "iso:country":"AT",
    "wof:name":"Puppitsch",
    "wof:placetype":"locality",
    "wof:population":11
},
  "geometry": {"coordinates":[14.29982,46.75621],"type":"Point"}
}