{
  "type": "Feature",
  "properties": {
    "gn:admin1_code":"3.0",
    "gn:admin2_code":"315",
    "gn:admin3_code":"31537.0",
    "gn:asciiname":"Etzen",
    "gn:country_code":"AT",
    "gn:dem":261,
    "gn:feature_class":"P",
    "gn:feature_code":"PPL",
    "gn:name":"Etzen",
    "gn:population":60,
    "gn:timezone":"Europe/Vienna",
    "iso:country":"AT",
    "wof:name":"Etzen",
    "wof:placetype":"locality",
    "wof:population":60
},
  "geometry": {"coordinates":[15.25,48.11667],"type":"Point"}
}