{
  "type": "Feature",
  "properties": {
    "gn:admin1_code":"04",
    "gn:admin2_code":"409.0",
    "gn:admin3_code":"40915.0",
    "gn:asciiname":"Schweizersberg",
    "gn:country_code":"AT",
    "gn:dem":784,
    "gn:feature_class":"P",
    "gn:feature_code":"PPL",
    "gn:name":"Schweizersberg",
    "gn:population":525,
    "gn:timezone":"Europe/Vienna",
    "iso:country":"AT",
    "wof:name":"Schweizersberg",
    "wof:placetype":"locality",
    "wof:population":525
},
  "geometry": {"coordinates":[14.28197,47.716],"type":"Point"}
}