{
  "type": "Feature",
  "properties": {
    "gn:admin1_code":"01",
    "gn:admin2_code":"108.0",
    "gn:admin3_code":"10817.0",
    "gn:asciiname":"Steinbach im Burgenland",
    "gn:cc2":"AT",
    "gn:country_code":"AT",
    "gn:dem":407,
    "gn:feature_class":"P",
    "gn:feature_code":"PPL",
    "gn:name":"Steinbach im Burgenland",
    "gn:population":209,
    "gn:timezone":"Europe/Vienna",
    "iso:country":"AT",
    "name:hun_x_preferred":[
        "K\u0151patak"
    ],
    "name:und_x_variant":[
        "Steinbach",
        "Steinbach im Burgenland"
    ],
    "wof:name":"Steinbach im Burgenland",
    "wof:placetype":"locality",
    "wof:population":209
},
  "geometry": {"coordinates":[16.31663,47.47503],"type":"Point"}
}