{
  "type": "Feature",
  "properties": {
    "gn:admin1_code":"04",
    "gn:admin2_code":"406.0",
    "gn:admin3_code":"40618.0",
    "gn:asciiname":"Weinviertl",
    "gn:country_code":"AT",
    "gn:dem":848,
    "gn:feature_class":"P",
    "gn:feature_code":"PPL",
    "gn:name":"Weinviertl",
    "gn:population":0,
    "gn:timezone":"Europe/Vienna",
    "iso:country":"AT",
    "wof:name":"Weinviertl",
    "wof:placetype":"locality"
},
  "geometry": {"coordinates":[14.61096,48.52422],"type":"Point"}
}