{
  "type": "Feature",
  "properties": {
    "gn:admin1_code":"04",
    "gn:admin2_code":"416.0",
    "gn:admin3_code":"41623.0",
    "gn:asciiname":"Unterdreiegg",
    "gn:country_code":"AT",
    "gn:dem":772,
    "gn:feature_class":"P",
    "gn:feature_code":"PPL",
    "gn:name":"Unterdreiegg",
    "gn:population":0,
    "gn:timezone":"Europe/Vienna",
    "iso:country":"AT",
    "wof:name":"Unterdreiegg",
    "wof:placetype":"locality"
},
  "geometry": {"coordinates":[14.30351,48.4707],"type":"Point"}
}