{
  "type": "Feature",
  "properties": {
    "gn:admin1_code":"4.0",
    "gn:admin2_code":"414",
    "gn:admin3_code":"41429.0",
    "gn:asciiname":"Edt",
    "gn:country_code":"AT",
    "gn:dem":500,
    "gn:feature_class":"P",
    "gn:feature_code":"PPL",
    "gn:name":"Edt",
    "gn:population":13,
    "gn:timezone":"Europe/Vienna",
    "iso:country":"AT",
    "wof:name":"Edt",
    "wof:placetype":"locality",
    "wof:population":13
},
  "geometry": {"coordinates":[13.50056,48.51167],"type":"Point"}
}