{
  "type": "Feature",
  "properties": {
    "gn:admin1_code":"3.0",
    "gn:admin2_code":"309",
    "gn:admin3_code":"30902.0",
    "gn:asciiname":"Falkendorf",
    "gn:country_code":"AT",
    "gn:dem":561,
    "gn:feature_class":"P",
    "gn:feature_code":"PPL",
    "gn:name":"Falkendorf",
    "gn:population":36,
    "gn:timezone":"Europe/Vienna",
    "iso:country":"AT",
    "wof:name":"Falkendorf",
    "wof:placetype":"locality",
    "wof:population":36
},
  "geometry": {"coordinates":[15.08333,48.83333],"type":"Point"}
}