{
  "type": "Feature",
  "properties": {
    "gn:admin1_code":"4.0",
    "gn:admin2_code":"410",
    "gn:admin3_code":"41010.0",
    "gn:asciiname":"Gumpolding",
    "gn:country_code":"AT",
    "gn:dem":288,
    "gn:feature_class":"P",
    "gn:feature_code":"PPL",
    "gn:name":"Gumpolding",
    "gn:population":152,
    "gn:timezone":"Europe/Vienna",
    "iso:country":"AT",
    "wof:name":"Gumpolding",
    "wof:placetype":"locality",
    "wof:population":152
},
  "geometry": {"coordinates":[14.14524,48.26611],"type":"Point"}
}