{
  "type": "Feature",
  "properties": {
    "gn:admin1_code":"6.0",
    "gn:admin2_code":"620",
    "gn:admin3_code":"62008.0",
    "gn:asciiname":"Hart",
    "gn:country_code":"AT",
    "gn:dem":867,
    "gn:feature_class":"P",
    "gn:feature_code":"PPL",
    "gn:name":"Hart",
    "gn:population":0,
    "gn:timezone":"Europe/Vienna",
    "iso:country":"AT",
    "wof:name":"Hart",
    "wof:placetype":"locality"
},
  "geometry": {"coordinates":[14.75944,47.26639],"type":"Point"}
}