{
  "type": "Feature",
  "properties": {
    "gn:admin1_code":"03",
    "gn:admin2_code":"325.0",
    "gn:admin3_code":"32518.0",
    "gn:asciiname":"Oedwinkel",
    "gn:country_code":"AT",
    "gn:dem":798,
    "gn:feature_class":"P",
    "gn:feature_code":"PPL",
    "gn:name":"Oedwinkel",
    "gn:population":0,
    "gn:timezone":"Europe/Vienna",
    "iso:country":"AT",
    "wof:name":"Oedwinkel",
    "wof:placetype":"locality"
},
  "geometry": {"coordinates":[15.18333,48.45],"type":"Point"}
}