{
  "type": "Feature",
  "properties": {
    "gn:admin1_code":"2.0",
    "gn:admin2_code":"210",
    "gn:admin3_code":"21001.0",
    "gn:asciiname":"Sirnitz-Winkl",
    "gn:country_code":"AT",
    "gn:dem":1268,
    "gn:feature_class":"P",
    "gn:feature_code":"PPLL",
    "gn:name":"Sirnitz-Winkl",
    "gn:population":15,
    "gn:timezone":"Europe/Vienna",
    "iso:country":"AT",
    "wof:name":"Sirnitz-Winkl",
    "wof:placetype":"locality",
    "wof:population":15
},
  "geometry": {"coordinates":[13.99963,46.84924],"type":"Point"}
}