{
  "type": "Feature",
  "properties": {
    "gn:admin1_code":"06",
    "gn:admin2_code":"623.0",
    "gn:admin3_code":"62388.0",
    "gn:asciiname":"Troessing",
    "gn:country_code":"AT",
    "gn:dem":268,
    "gn:feature_class":"P",
    "gn:feature_code":"PPLA3",
    "gn:name":"Tr\u00f6ssing",
    "gn:population":0,
    "gn:timezone":"Europe/Vienna",
    "iso:country":"AT",
    "name:und_x_variant":[
        "Tr\u00f6ssing"
    ],
    "wof:name":"Troessing",
    "wof:placetype":"locality"
},
  "geometry": {"coordinates":[15.81667,46.81667],"type":"Point"}
}