{
  "type": "Feature",
  "properties": {
    "gn:admin1_code":"06",
    "gn:admin2_code":"623.0",
    "gn:admin3_code":"62388.0",
    "gn:asciiname":"Troessing",
    "gn:country_code":"AT",
    "gn:dem":268,
    "gn:feature_class":"P",
    "gn:feature_code":"PPLA3",
    "gn:name":"Tr\u00f6ssing",
    "gn:population":0,
    "gn:timezone":"Europe/Vienna",
    "iso:country":"AT",
    "name:ceb_x_preferred":[
        "Tr\u00f6ssing"
    ],
    "name:deu_x_preferred":[
        "Tr\u00f6ssing"
    ],
    "name:fas_x_preferred":[
        "\u062a\u0631\u0648\u0633\u06cc\u0646\u06af"
    ],
    "name:fra_x_preferred":[
        "Tr\u00f6ssing"
    ],
    "name:ita_x_preferred":[
        "Tr\u00f6ssing"
    ],
    "name:kaz_x_preferred":[
        "\u0422\u0440\u0451\u0441\u0441\u0438\u043d\u0433"
    ],
    "name:nld_x_preferred":[
        "Tr\u00f6ssing"
    ],
    "name:rus_x_preferred":[
        "\u0422\u0440\u0451\u0441\u0441\u0438\u043d\u0433"
    ],
    "name:slk_x_preferred":[
        "Tr\u00f6ssing"
    ],
    "name:swe_x_preferred":[
        "Tr\u00f6ssing"
    ],
    "name:und_x_variant":[
        "Tr\u00f6ssing"
    ],
    "name:uzb_x_preferred":[
        "Tr\u00f6ssing"
    ],
    "name:vie_x_preferred":[
        "Tr\u00f6ssing"
    ],
    "name:vol_x_preferred":[
        "Tr\u00f6ssing"
    ],
    "name:war_x_preferred":[
        "Tr\u00f6ssing"
    ],
    "name:zho_x_preferred":[
        "\u7279\u52d2\u8f9b"
    ],
    "wof:name":"Troessing",
    "wof:placetype":"locality"
},
  "geometry": {"coordinates":[15.81667,46.81667],"type":"Point"}
}