{
  "type": "Feature",
  "properties": {
    "gn:admin1_code":"7.0",
    "gn:admin2_code":"706",
    "gn:admin3_code":"70604.0",
    "gn:asciiname":"Niedergallmigg",
    "gn:country_code":"AT",
    "gn:dem":972,
    "gn:feature_class":"P",
    "gn:feature_code":"PPL",
    "gn:name":"Niedergallmigg",
    "gn:population":0,
    "gn:timezone":"Europe/Vienna",
    "iso:country":"AT",
    "wof:name":"Niedergallmigg",
    "wof:placetype":"locality"
},
  "geometry": {"coordinates":[10.63296,47.11062],"type":"Point"}
}