{
  "type": "Feature",
  "properties": {
    "gn:admin1_code":"4.0",
    "gn:admin2_code":"412",
    "gn:admin3_code":"41233.0",
    "gn:asciiname":"Murau",
    "gn:country_code":"AT",
    "gn:dem":385,
    "gn:feature_class":"P",
    "gn:feature_code":"PPL",
    "gn:name":"Murau",
    "gn:population":41,
    "gn:timezone":"Europe/Vienna",
    "iso:country":"AT",
    "name:bar_x_preferred":[
        "Murau"
    ],
    "name:bos_x_preferred":[
        "Murau"
    ],
    "name:bre_x_preferred":[
        "Murau"
    ],
    "name:bul_x_preferred":[
        "\u041c\u0443\u0440\u0430\u0443"
    ],
    "name:ceb_x_preferred":[
        "Murau"
    ],
    "name:ces_x_preferred":[
        "Murau"
    ],
    "name:deu_x_preferred":[
        "Murau"
    ],
    "name:epo_x_preferred":[
        "Murau"
    ],
    "name:fas_x_preferred":[
        "\u0645\u0648\u0631\u0648"
    ],
    "name:fra_x_preferred":[
        "Murau"
    ],
    "name:hun_x_preferred":[
        "Murau"
    ],
    "name:ita_x_preferred":[
        "Murau"
    ],
    "name:nld_x_preferred":[
        "Murau"
    ],
    "name:nno_x_preferred":[
        "Murau"
    ],
    "name:nor_x_preferred":[
        "Murau"
    ],
    "name:pol_x_preferred":[
        "Murau"
    ],
    "name:ron_x_preferred":[
        "Murau"
    ],
    "name:rus_x_preferred":[
        "\u041c\u0443\u0440\u0430\u0443"
    ],
    "name:slk_x_preferred":[
        "Murau"
    ],
    "name:slv_x_preferred":[
        "Murau"
    ],
    "name:spa_x_preferred":[
        "Murau"
    ],
    "name:srp_x_preferred":[
        "\u041c\u0443\u0440\u0430\u0443"
    ],
    "name:swe_x_preferred":[
        "Murau"
    ],
    "name:uzb_x_preferred":[
        "Murau"
    ],
    "name:vie_x_preferred":[
        "Murau"
    ],
    "name:vol_x_preferred":[
        "Murau"
    ],
    "name:war_x_preferred":[
        "Murau"
    ],
    "wof:name":"Murau",
    "wof:placetype":"locality",
    "wof:population":41
},
  "geometry": {"coordinates":[13.49559,48.27482],"type":"Point"}
}