{
  "type": "Feature",
  "properties": {
    "gn:admin1_code":"4.0",
    "gn:admin2_code":"408",
    "gn:admin3_code":"40817.0",
    "gn:asciiname":"Moosau",
    "gn:country_code":"AT",
    "gn:dem":447,
    "gn:feature_class":"P",
    "gn:feature_code":"PPL",
    "gn:name":"Moosau",
    "gn:population":32,
    "gn:timezone":"Europe/Vienna",
    "iso:country":"AT",
    "wof:name":"Moosau",
    "wof:placetype":"locality",
    "wof:population":32
},
  "geometry": {"coordinates":[13.78209,48.38014],"type":"Point"}
}