{
  "type": "Feature",
  "properties": {
    "gn:admin1_code":"3.0",
    "gn:admin2_code":"305",
    "gn:admin3_code":"30532.0",
    "gn:asciiname":"Neudorf",
    "gn:country_code":"AT",
    "gn:dem":361,
    "gn:feature_class":"P",
    "gn:feature_code":"PPL",
    "gn:name":"Neudorf",
    "gn:population":0,
    "gn:timezone":"Europe/Vienna",
    "iso:country":"AT",
    "wof:name":"Neudorf",
    "wof:placetype":"locality"
},
  "geometry": {"coordinates":[14.63333,48.03333],"type":"Point"}
}