{
  "type": "Feature",
  "properties": {
    "gn:admin1_code":"04",
    "gn:admin2_code":"409.0",
    "gn:admin3_code":"40907.0",
    "gn:asciiname":"Regau",
    "gn:country_code":"AT",
    "gn:dem":387,
    "gn:feature_class":"P",
    "gn:feature_code":"PPL",
    "gn:name":"Regau",
    "gn:population":0,
    "gn:timezone":"Europe/Vienna",
    "iso:country":"AT",
    "name:ara_x_preferred":[
        "\u0631\u064a\u063a\u0627\u0648"
    ],
    "name:bar_x_preferred":[
        "Regau"
    ],
    "name:ceb_x_preferred":[
        "Regau"
    ],
    "name:ces_x_preferred":[
        "Regau"
    ],
    "name:deu_x_preferred":[
        "Regau"
    ],
    "name:epo_x_preferred":[
        "Rega\u016d"
    ],
    "name:fas_x_preferred":[
        "\u0631\u06af\u0648"
    ],
    "name:fra_x_preferred":[
        "Regau"
    ],
    "name:hun_x_preferred":[
        "Regau"
    ],
    "name:ita_x_preferred":[
        "Regau"
    ],
    "name:kaz_x_preferred":[
        "\u0420\u0435\u0433\u0430\u0443"
    ],
    "name:lat_x_preferred":[
        "Repagovi"
    ],
    "name:nld_x_preferred":[
        "Regau"
    ],
    "name:nno_x_preferred":[
        "Regau"
    ],
    "name:pol_x_preferred":[
        "Regau"
    ],
    "name:por_x_preferred":[
        "Regau"
    ],
    "name:rus_x_preferred":[
        "\u0420\u0435\u0433\u0430\u0443"
    ],
    "name:scn_x_preferred":[
        "Regau"
    ],
    "name:slk_x_preferred":[
        "Regau"
    ],
    "name:spa_x_preferred":[
        "Regau"
    ],
    "name:swe_x_preferred":[
        "Regau"
    ],
    "name:uzb_x_preferred":[
        "Regau"
    ],
    "name:vol_x_preferred":[
        "Regau"
    ],
    "name:war_x_preferred":[
        "Regau"
    ],
    "wof:name":"Regau",
    "wof:placetype":"locality"
},
  "geometry": {"coordinates":[14.13743,48.07498],"type":"Point"}
}