{
  "type": "Feature",
  "properties": {
    "gn:admin1_code":"6.0",
    "gn:admin2_code":"610",
    "gn:admin3_code":"61032.0",
    "gn:asciiname":"Georgenberg",
    "gn:country_code":"AT",
    "gn:dem":357,
    "gn:feature_class":"P",
    "gn:feature_code":"PPL",
    "gn:name":"Georgenberg",
    "gn:population":0,
    "gn:timezone":"Europe/Vienna",
    "iso:country":"AT",
    "wof:name":"Georgenberg",
    "wof:placetype":"locality"
},
  "geometry": {"coordinates":[15.35,46.73333],"type":"Point"}
}