{
  "type": "Feature",
  "properties": {
    "gn:admin1_code":"3.0",
    "gn:admin2_code":"319",
    "gn:admin3_code":"31901.0",
    "gn:asciiname":"Hocheichberg",
    "gn:country_code":"AT",
    "gn:dem":294,
    "gn:feature_class":"P",
    "gn:feature_code":"PPL",
    "gn:name":"Hocheichberg",
    "gn:population":55,
    "gn:timezone":"Europe/Vienna",
    "iso:country":"AT",
    "wof:name":"Hocheichberg",
    "wof:placetype":"locality",
    "wof:population":55
},
  "geometry": {"coordinates":[15.89559,48.17244],"type":"Point"}
}