{
  "type": "Feature",
  "properties": {
    "gn:admin1_code":"3.0",
    "gn:admin2_code":"320",
    "gn:admin3_code":"32014.0",
    "gn:asciiname":"Duernbach",
    "gn:country_code":"AT",
    "gn:dem":280,
    "gn:feature_class":"P",
    "gn:feature_code":"PPLL",
    "gn:name":"D\u00fcrnbach",
    "gn:population":13,
    "gn:timezone":"Europe/Vienna",
    "iso:country":"AT",
    "wof:name":"Duernbach",
    "wof:placetype":"locality",
    "wof:population":13
},
  "geometry": {"coordinates":[15.02904,48.10921],"type":"Point"}
}