{
  "type": "Feature",
  "properties": {
    "gn:admin1_code":"2.0",
    "gn:admin2_code":"204",
    "gn:admin3_code":"20412.0",
    "gn:asciiname":"Leisbach",
    "gn:country_code":"AT",
    "gn:dem":560,
    "gn:feature_class":"P",
    "gn:feature_code":"PPL",
    "gn:name":"Leisbach",
    "gn:population":123,
    "gn:timezone":"Europe/Vienna",
    "iso:country":"AT",
    "wof:name":"Leisbach",
    "wof:placetype":"locality",
    "wof:population":123
},
  "geometry": {"coordinates":[14.23111,46.59417],"type":"Point"}
}