{
  "type": "Feature",
  "properties": {
    "gn:admin1_code":"3.0",
    "gn:admin2_code":"320",
    "gn:admin3_code":"32014.0",
    "gn:asciiname":"Zehethof",
    "gn:country_code":"AT",
    "gn:dem":342,
    "gn:feature_class":"P",
    "gn:feature_code":"PPLL",
    "gn:name":"Zehethof",
    "gn:population":189,
    "gn:timezone":"Europe/Vienna",
    "iso:country":"AT",
    "wof:name":"Zehethof",
    "wof:placetype":"locality",
    "wof:population":189
},
  "geometry": {"coordinates":[15.03449,48.08671],"type":"Point"}
}