{
  "type": "Feature",
  "properties": {
    "gn:country":"AT",
    "gn:fcode":"PPL",
    "gn:population":0,
    "iso:country":"AT",
    "name:ceb_x_preferred":[
        "Haus"
    ],
    "name:deu_x_preferred":[
        "Haus"
    ],
    "name:fin_x_preferred":[
        "Haus"
    ],
    "name:fra_x_preferred":[
        "Haus"
    ],
    "name:ita_x_preferred":[
        "Haus"
    ],
    "name:nds_x_preferred":[
        "Haus"
    ],
    "name:pol_x_preferred":[
        "Haus"
    ],
    "name:slv_x_preferred":[
        "Haus"
    ],
    "name:swe_x_preferred":[
        "Haus"
    ],
    "qs_pg:aaroncc":"AT",
    "qs_pg:gn_country":"AT",
    "qs_pg:gn_fcode":"PPL",
    "qs_pg:gn_pop":0,
    "qs_pg:name":"Haus",
    "qs_pg:name_adm0":"\u00d6sterreich",
    "qs_pg:name_adm1":"Tirol",
    "qs_pg:photos":35,
    "qs_pg:photos_1k":7,
    "qs_pg:photos_9k":1,
    "qs_pg:photos_9r":2,
    "qs_pg:photos_all":35,
    "qs_pg:photos_sr":2,
    "qs_pg:pop_sr":0,
    "qs_pg:qs_pg_placetype":"locality",
    "qs_pg:qs_pg_placetype_gp":"Town",
    "qs_pg:woe_adm0":23424750,
    "woe:adm0_id":23424750,
    "woe:name_adm0":"\u00d6sterreich",
    "woe:name_adm1":"Tirol",
    "woe:placetype":"Town",
    "wof:name":"Haus",
    "wof:placetype":"locality"
},
  "geometry": {"coordinates":[11.85,47.16667],"type":"Point"}
}