{
  "type": "Feature",
  "properties": {
    "gn:admin1_code":"4.0",
    "gn:admin2_code":"416",
    "gn:admin3_code":"41602.0",
    "gn:asciiname":"Niederwinkl",
    "gn:country_code":"AT",
    "gn:dem":626,
    "gn:feature_class":"P",
    "gn:feature_code":"PPL",
    "gn:name":"Niederwinkl",
    "gn:population":203,
    "gn:timezone":"Europe/Vienna",
    "iso:country":"AT",
    "wof:name":"Niederwinkl",
    "wof:placetype":"locality",
    "wof:population":203
},
  "geometry": {"coordinates":[14.34205,48.38219],"type":"Point"}
}