{
  "type": "Feature",
  "properties": {
    "gn:admin1_code":"4.0",
    "gn:admin2_code":"404",
    "gn:admin3_code":"40410.0",
    "gn:asciiname":"Bitzlthal",
    "gn:country_code":"AT",
    "gn:dem":442,
    "gn:feature_class":"P",
    "gn:feature_code":"PPL",
    "gn:name":"Bitzlthal",
    "gn:population":42,
    "gn:timezone":"Europe/Vienna",
    "iso:country":"AT",
    "wof:name":"Bitzlthal",
    "wof:placetype":"locality",
    "wof:population":42
},
  "geometry": {"coordinates":[12.92481,48.13734],"type":"Point"}
}