{
  "type": "Feature",
  "properties": {
    "gn:admin1_code":"3.0",
    "gn:admin2_code":"320",
    "gn:admin3_code":"32012.0",
    "gn:asciiname":"Mitteroed",
    "gn:country_code":"AT",
    "gn:dem":506,
    "gn:feature_class":"P",
    "gn:feature_code":"PPL",
    "gn:name":"Mitter\u00f6d",
    "gn:population":47,
    "gn:timezone":"Europe/Vienna",
    "iso:country":"AT",
    "wof:name":"Mitteroed",
    "wof:placetype":"locality",
    "wof:population":47
},
  "geometry": {"coordinates":[15.2389,48.02277],"type":"Point"}
}