{
  "type": "Feature",
  "properties": {
    "gn:admin1_code":"04",
    "gn:admin2_code":"413.0",
    "gn:admin3_code":"41340.0",
    "gn:asciiname":"Piberschlag",
    "gn:country_code":"AT",
    "gn:dem":698,
    "gn:feature_class":"P",
    "gn:feature_code":"PPL",
    "gn:name":"Piberschlag",
    "gn:population":0,
    "gn:timezone":"Europe/Vienna",
    "iso:country":"AT",
    "wof:name":"Piberschlag",
    "wof:placetype":"locality"
},
  "geometry": {"coordinates":[14.17442,48.56337],"type":"Point"}
}