{
  "type": "Feature",
  "properties": {
    "gn:admin1_code":"02",
    "gn:admin2_code":"204.0",
    "gn:admin3_code":"20416.0",
    "gn:asciiname":"Pugrad",
    "gn:cc2":"AT",
    "gn:country_code":"AT",
    "gn:dem":629,
    "gn:feature_class":"P",
    "gn:feature_code":"PPL",
    "gn:name":"Pugrad",
    "gn:population":177,
    "gn:timezone":"Europe/Vienna",
    "iso:country":"AT",
    "name:deu_x_preferred":[
        "Pugrad"
    ],
    "name:slv_x_preferred":[
        "Pograd"
    ],
    "name:und_x_variant":[
        "Pograd"
    ],
    "wof:name":"Pugrad",
    "wof:placetype":"locality",
    "wof:population":177
},
  "geometry": {"coordinates":[14.13889,46.54722],"type":"Point"}
}