{
  "type": "Feature",
  "properties": {
    "gn:admin1_code":"6.0",
    "gn:admin2_code":"621",
    "gn:admin3_code":"62141.0",
    "gn:asciiname":"Soelsnitz",
    "gn:country_code":"AT",
    "gn:dem":582,
    "gn:feature_class":"P",
    "gn:feature_code":"PPL",
    "gn:name":"S\u00f6lsnitz",
    "gn:population":114,
    "gn:timezone":"Europe/Vienna",
    "iso:country":"AT",
    "wof:name":"Soelsnitz",
    "wof:placetype":"locality",
    "wof:population":114
},
  "geometry": {"coordinates":[15.38846,47.4637],"type":"Point"}
}