{
  "type": "Feature",
  "properties": {
    "gn:admin1_code":"08",
    "gn:admin2_code":"801.0",
    "gn:admin3_code":"80124.0",
    "gn:asciiname":"Ischkarneialpe",
    "gn:country_code":"AT",
    "gn:dem":1529,
    "gn:feature_class":"P",
    "gn:feature_code":"PPLF",
    "gn:name":"Ischkarneialpe",
    "gn:population":0,
    "gn:timezone":"Europe/Vienna",
    "iso:country":"AT",
    "name:und_x_variant":[
        "Untere Isgarnei Alpe",
        "Iscarner Alpe",
        "Ischgarneialpe"
    ],
    "wof:name":"Ischkarneialpe",
    "wof:placetype":"locality"
},
  "geometry": {"coordinates":[10.00624,47.2546],"type":"Point"}
}