{
  "type": "Feature",
  "properties": {
    "gn:admin1_code":"02",
    "gn:admin2_code":"206.0",
    "gn:admin3_code":"20633.0",
    "gn:asciiname":"Sachsenweg",
    "gn:country_code":"AT",
    "gn:dem":578,
    "gn:feature_class":"P",
    "gn:feature_code":"PPL",
    "gn:name":"Sachsenweg",
    "gn:population":0,
    "gn:timezone":"Europe/Vienna",
    "iso:country":"AT",
    "wof:name":"Sachsenweg",
    "wof:placetype":"locality"
},
  "geometry": {"coordinates":[13.35,46.83333],"type":"Point"}
}