{
  "type": "Feature",
  "properties": {
    "gn:admin1_code":"4.0",
    "gn:admin2_code":"416",
    "gn:admin3_code":"41605.0",
    "gn:asciiname":"Innertreffling",
    "gn:country_code":"AT",
    "gn:dem":435,
    "gn:feature_class":"P",
    "gn:feature_code":"PPL",
    "gn:name":"Innertreffling",
    "gn:population":581,
    "gn:timezone":"Europe/Vienna",
    "iso:country":"AT",
    "wof:name":"Innertreffling",
    "wof:placetype":"locality",
    "wof:population":581
},
  "geometry": {"coordinates":[14.37613,48.34541],"type":"Point"}
}