{
  "type": "Feature",
  "properties": {
    "gn:admin1_code":"4.0",
    "gn:admin2_code":"405",
    "gn:admin3_code":"40510.0",
    "gn:asciiname":"Eben",
    "gn:country_code":"AT",
    "gn:dem":375,
    "gn:feature_class":"P",
    "gn:feature_code":"PPL",
    "gn:name":"Eben",
    "gn:population":17,
    "gn:timezone":"Europe/Vienna",
    "iso:country":"AT",
    "name:ces_x_preferred":[
        "Eben"
    ],
    "wof:name":"Eben",
    "wof:placetype":"locality",
    "wof:population":17
},
  "geometry": {"coordinates":[13.93444,48.2752],"type":"Point"}
}