{
  "type": "Feature",
  "properties": {
    "gn:admin1_code":"4.0",
    "gn:admin2_code":"405",
    "gn:admin3_code":"40509.0",
    "gn:asciiname":"Au bei hohen Steg",
    "gn:country_code":"AT",
    "gn:dem":262,
    "gn:feature_class":"P",
    "gn:feature_code":"PPL",
    "gn:name":"Au bei hohen Steg",
    "gn:population":60,
    "gn:timezone":"Europe/Vienna",
    "iso:country":"AT",
    "wof:name":"Au bei hohen Steg",
    "wof:placetype":"locality",
    "wof:population":60
},
  "geometry": {"coordinates":[14.02637,48.3255],"type":"Point"}
}