{
  "type": "Feature",
  "properties": {
    "gn:admin1_code":"4.0",
    "gn:admin2_code":"412",
    "gn:admin3_code":"41224.0",
    "gn:asciiname":"Minaberg",
    "gn:country_code":"AT",
    "gn:dem":348,
    "gn:feature_class":"P",
    "gn:feature_code":"PPL",
    "gn:name":"Minaberg",
    "gn:population":47,
    "gn:timezone":"Europe/Vienna",
    "iso:country":"AT",
    "wof:name":"Minaberg",
    "wof:placetype":"locality",
    "wof:population":47
},
  "geometry": {"coordinates":[13.37405,48.34159],"type":"Point"}
}