{
  "type": "Feature",
  "properties": {
    "gn:admin1_code":"03",
    "gn:admin2_code":"316.0",
    "gn:admin3_code":"31650.0",
    "gn:asciiname":"Patzmannsdorf",
    "gn:country_code":"AT",
    "gn:dem":235,
    "gn:feature_class":"P",
    "gn:feature_code":"PPL",
    "gn:name":"Patzmannsdorf",
    "gn:population":385,
    "gn:timezone":"Europe/Vienna",
    "iso:country":"AT",
    "wof:name":"Patzmannsdorf",
    "wof:placetype":"locality",
    "wof:population":385
},
  "geometry": {"coordinates":[16.26667,48.63333],"type":"Point"}
}