{
  "type": "Feature",
  "properties": {
    "gn:admin1_code":"4.0",
    "gn:admin2_code":"406",
    "gn:admin3_code":"40604.0",
    "gn:asciiname":"Oberaich",
    "gn:country_code":"AT",
    "gn:dem":469,
    "gn:feature_class":"P",
    "gn:feature_code":"PPL",
    "gn:name":"Oberaich",
    "gn:population":173,
    "gn:timezone":"Europe/Vienna",
    "iso:country":"AT",
    "wof:name":"Oberaich",
    "wof:placetype":"locality",
    "wof:population":173
},
  "geometry": {"coordinates":[14.50307,48.38293],"type":"Point"}
}