{
  "type": "Feature",
  "properties": {
    "gn:admin1_code":"4.0",
    "gn:admin2_code":"406",
    "gn:admin3_code":"40604.0",
    "gn:asciiname":"Oberaich",
    "gn:country_code":"AT",
    "gn:dem":469,
    "gn:feature_class":"P",
    "gn:feature_code":"PPL",
    "gn:name":"Oberaich",
    "gn:population":173,
    "gn:timezone":"Europe/Vienna",
    "iso:country":"AT",
    "name:ceb_x_preferred":[
        "Oberaich"
    ],
    "name:deu_x_preferred":[
        "Oberaich"
    ],
    "name:fas_x_preferred":[
        "\u0627\u0648\u0628\u0631\u0627\u06cc\u0634"
    ],
    "name:fra_x_preferred":[
        "Oberaich"
    ],
    "name:ita_x_preferred":[
        "Oberaich"
    ],
    "name:nld_x_preferred":[
        "Oberaich"
    ],
    "name:rus_x_preferred":[
        "\u041e\u0431\u0435\u0440\u0430\u0439\u0445"
    ],
    "name:slk_x_preferred":[
        "Oberaich"
    ],
    "name:spa_x_preferred":[
        "Oberaich"
    ],
    "name:swe_x_preferred":[
        "Oberaich"
    ],
    "name:ukr_x_preferred":[
        "\u041e\u0431\u0435\u0440\u0430\u0439\u0445"
    ],
    "name:uzb_x_preferred":[
        "Oberaich"
    ],
    "name:vie_x_preferred":[
        "Oberaich"
    ],
    "name:vol_x_preferred":[
        "Oberaich"
    ],
    "name:war_x_preferred":[
        "Oberaich"
    ],
    "name:zho_x_preferred":[
        "\u5965\u4f2f\u8d56\u5e0c"
    ],
    "wof:name":"Oberaich",
    "wof:placetype":"locality",
    "wof:population":173
},
  "geometry": {"coordinates":[14.50307,48.38293],"type":"Point"}
}