{
  "type": "Feature",
  "properties": {
    "gn:admin1_code":"03",
    "gn:admin2_code":"305.0",
    "gn:admin3_code":"30501.0",
    "gn:asciiname":"Purgstall",
    "gn:country_code":"AT",
    "gn:dem":344,
    "gn:feature_class":"P",
    "gn:feature_code":"PPL",
    "gn:name":"Purgstall",
    "gn:population":0,
    "gn:timezone":"Europe/Vienna",
    "iso:country":"AT",
    "wof:name":"Purgstall",
    "wof:placetype":"locality"
},
  "geometry": {"coordinates":[14.77065,48.02214],"type":"Point"}
}