{
  "type": "Feature",
  "properties": {
    "gn:admin1_code":"04",
    "gn:admin2_code":"413.0",
    "gn:admin3_code":"41313.0",
    "gn:asciiname":"Vorderschiffl",
    "gn:country_code":"AT",
    "gn:dem":725,
    "gn:feature_class":"P",
    "gn:feature_code":"PPL",
    "gn:name":"Vorderschiffl",
    "gn:population":49,
    "gn:timezone":"Europe/Vienna",
    "iso:country":"AT",
    "wof:name":"Vorderschiffl",
    "wof:placetype":"locality",
    "wof:population":49
},
  "geometry": {"coordinates":[13.8547,48.64023],"type":"Point"}
}