{
  "type": "Feature",
  "properties": {
    "gn:admin1_code":"4.0",
    "gn:admin2_code":"417",
    "gn:admin3_code":"41720.0",
    "gn:asciiname":"Lebertsham",
    "gn:country_code":"AT",
    "gn:dem":403,
    "gn:feature_class":"P",
    "gn:feature_code":"PPL",
    "gn:name":"Lebertsham",
    "gn:population":223,
    "gn:timezone":"Europe/Vienna",
    "iso:country":"AT",
    "wof:name":"Lebertsham",
    "wof:placetype":"locality",
    "wof:population":223
},
  "geometry": {"coordinates":[13.736,48.0494],"type":"Point"}
}