{
  "type": "Feature",
  "properties": {
    "gn:admin1_code":"03",
    "gn:admin2_code":"322.0",
    "gn:admin3_code":"32206.0",
    "gn:asciiname":"Steinwand",
    "gn:country_code":"AT",
    "gn:dem":618,
    "gn:feature_class":"P",
    "gn:feature_code":"PPL",
    "gn:name":"Steinwand",
    "gn:population":0,
    "gn:timezone":"Europe/Vienna",
    "iso:country":"AT",
    "name:ceb_x_preferred":[
        "Steinwand"
    ],
    "name:deu_x_preferred":[
        "Steinwand"
    ],
    "name:swe_x_preferred":[
        "Steinwand"
    ],
    "wof:name":"Steinwand",
    "wof:placetype":"locality"
},
  "geometry": {"coordinates":[15.18333,48.91667],"type":"Point"}
}