{
  "type": "Feature",
  "properties": {
    "gn:admin1_code":"01",
    "gn:admin2_code":"109.0",
    "gn:admin3_code":"10901.0",
    "gn:asciiname":"Sulzriegel",
    "gn:country_code":"AT",
    "gn:dem":366,
    "gn:feature_class":"P",
    "gn:feature_code":"PPL",
    "gn:name":"Sulzriegel",
    "gn:population":153,
    "gn:timezone":"Europe/Vienna",
    "iso:country":"AT",
    "wof:name":"Sulzriegel",
    "wof:placetype":"locality",
    "wof:population":153
},
  "geometry": {"coordinates":[16.23333,47.33333],"type":"Point"}
}