{
  "type": "Feature",
  "properties": {
    "gn:admin1_code":"6.0",
    "gn:admin2_code":"617",
    "gn:admin3_code":"61765.0",
    "gn:asciiname":"Fuenfing bei Sankt Ruprecht an der Raab",
    "gn:country_code":"AT",
    "gn:dem":472,
    "gn:feature_class":"P",
    "gn:feature_code":"PPL",
    "gn:name":"F\u00fcnfing bei Sankt Ruprecht an der Raab",
    "gn:population":866,
    "gn:timezone":"Europe/Vienna",
    "iso:country":"AT",
    "name:und_x_variant":[
        "F\u00fcnfing",
        "F\u00fcnfing bei Sankt Ruprecht an der Raab"
    ],
    "wof:name":"Fuenfing bei Sankt Ruprecht an der Raab",
    "wof:placetype":"locality",
    "wof:population":866
},
  "geometry": {"coordinates":[15.65,47.13333],"type":"Point"}
}