{
  "type": "Feature",
  "properties": {
    "gn:admin1_code":"06",
    "gn:admin2_code":"621.0",
    "gn:admin3_code":"62125.0",
    "gn:asciiname":"Zlatten",
    "gn:country_code":"AT",
    "gn:dem":485,
    "gn:feature_class":"P",
    "gn:feature_code":"PPL",
    "gn:name":"Zlatten",
    "gn:population":375,
    "gn:timezone":"Europe/Vienna",
    "iso:country":"AT",
    "wof:name":"Zlatten",
    "wof:placetype":"locality",
    "wof:population":375
},
  "geometry": {"coordinates":[15.31667,47.36667],"type":"Point"}
}