{
  "type": "Feature",
  "properties": {
    "gn:admin1_code":"3.0",
    "gn:admin2_code":"322",
    "gn:admin3_code":"32216.0",
    "gn:asciiname":"Koggendorf",
    "gn:country_code":"AT",
    "gn:dem":489,
    "gn:feature_class":"P",
    "gn:feature_code":"PPL",
    "gn:name":"Koggendorf",
    "gn:population":29,
    "gn:timezone":"Europe/Vienna",
    "iso:country":"AT",
    "wof:name":"Koggendorf",
    "wof:placetype":"locality",
    "wof:population":29
},
  "geometry": {"coordinates":[15.45,48.83333],"type":"Point"}
}