{
  "type": "Feature",
  "properties": {
    "gn:admin1_code":"2.0",
    "gn:admin2_code":"210",
    "gn:admin3_code":"21002.0",
    "gn:asciiname":"Klausen",
    "gn:country_code":"AT",
    "gn:dem":685,
    "gn:feature_class":"P",
    "gn:feature_code":"PPL",
    "gn:name":"Klausen",
    "gn:population":49,
    "gn:timezone":"Europe/Vienna",
    "iso:country":"AT",
    "wof:name":"Klausen",
    "wof:placetype":"locality",
    "wof:population":49
},
  "geometry": {"coordinates":[14.08014,46.68557],"type":"Point"}
}