{
  "type": "Feature",
  "properties": {
    "gn:admin1_code":"03",
    "gn:admin2_code":"309.0",
    "gn:admin3_code":"30904.0",
    "gn:asciiname":"Bergen",
    "gn:country_code":"AT",
    "gn:dem":608,
    "gn:feature_class":"P",
    "gn:feature_code":"PPL",
    "gn:name":"Bergen",
    "gn:population":0,
    "gn:timezone":"Europe/Vienna",
    "iso:country":"AT",
    "wof:name":"Bergen",
    "wof:placetype":"locality"
},
  "geometry": {"coordinates":[15.13333,48.91667],"type":"Point"}
}