{
  "type": "Feature",
  "properties": {
    "gn:admin1_code":"8.0",
    "gn:admin2_code":"801",
    "gn:admin3_code":"80109.0",
    "gn:asciiname":"Faschina",
    "gn:country_code":"AT",
    "gn:dem":1504,
    "gn:feature_class":"P",
    "gn:feature_code":"PPL",
    "gn:name":"Faschina",
    "gn:population":32,
    "gn:timezone":"Europe/Vienna",
    "iso:country":"AT",
    "wof:name":"Faschina",
    "wof:placetype":"locality",
    "wof:population":32
},
  "geometry": {"coordinates":[9.90619,47.27218],"type":"Point"}
}