{
  "type": "Feature",
  "properties": {
    "gn:admin1_code":"04",
    "gn:admin2_code":"408.0",
    "gn:admin3_code":"40834.0",
    "gn:asciiname":"Zupfing",
    "gn:country_code":"AT",
    "gn:dem":411,
    "gn:feature_class":"P",
    "gn:feature_code":"PPL",
    "gn:name":"Zupfing",
    "gn:population":41,
    "gn:timezone":"Europe/Vienna",
    "iso:country":"AT",
    "wof:name":"Zupfing",
    "wof:placetype":"locality",
    "wof:population":41
},
  "geometry": {"coordinates":[13.67094,48.24817],"type":"Point"}
}