{
  "type": "Feature",
  "properties": {
    "iso:country":"AT",
    "name:deu_x_preferred":[
        "Morzg"
    ],
    "name:eng_x_preferred":[
        "Morzg"
    ],
    "wof:name":"Morzg",
    "wof:placetype":"neighbourhood"
},
  "geometry": {"coordinates":[13.05507016439501,47.77139772497484],"type":"Point"}
}