{
  "type": "Feature",
  "properties": {
    "gn:admin1_code":"6.0",
    "gn:admin2_code":"612",
    "gn:admin3_code":"61253.0",
    "gn:asciiname":"Weng im Gesaeuse",
    "gn:country_code":"AT",
    "gn:dem":710,
    "gn:feature_class":"P",
    "gn:feature_code":"PPL",
    "gn:name":"Weng im Ges\u00e4use",
    "gn:population":548,
    "gn:timezone":"Europe/Vienna",
    "iso:country":"AT",
    "wof:name":"Weng im Gesaeuse",
    "wof:placetype":"locality",
    "wof:population":548
},
  "geometry": {"coordinates":[14.50388,47.602],"type":"Point"}
}