{
  "type": "Feature",
  "properties": {
    "gn:admin1_code":"03",
    "gn:admin2_code":"316.0",
    "gn:admin3_code":"31650.0",
    "gn:asciiname":"Stronegg",
    "gn:country_code":"AT",
    "gn:dem":274,
    "gn:feature_class":"P",
    "gn:feature_code":"PPL",
    "gn:name":"Stronegg",
    "gn:population":34,
    "gn:timezone":"Europe/Vienna",
    "iso:country":"AT",
    "wof:name":"Stronegg",
    "wof:placetype":"locality",
    "wof:population":34
},
  "geometry": {"coordinates":[16.31667,48.63333],"type":"Point"}
}