{
  "type": "Feature",
  "properties": {
    "gn:admin1_code":"2.0",
    "gn:admin2_code":"207",
    "gn:admin3_code":"20725.0",
    "gn:asciiname":"Aich",
    "gn:country_code":"AT",
    "gn:dem":524,
    "gn:feature_class":"P",
    "gn:feature_code":"PPL",
    "gn:name":"Aich",
    "gn:population":138,
    "gn:timezone":"Europe/Vienna",
    "iso:country":"AT",
    "name:ceb_x_preferred":[
        "Aich"
    ],
    "name:deu_x_preferred":[
        "Aich"
    ],
    "name:fra_x_preferred":[
        "Aich"
    ],
    "name:ita_x_preferred":[
        "Aich"
    ],
    "name:nld_x_preferred":[
        "Aich"
    ],
    "name:pol_x_preferred":[
        "Aich"
    ],
    "name:rus_x_preferred":[
        "\u0410\u0439\u0445"
    ],
    "name:swe_x_preferred":[
        "Aich"
    ],
    "wof:name":"Aich",
    "wof:placetype":"locality",
    "wof:population":138
},
  "geometry": {"coordinates":[14.05,46.58333],"type":"Point"}
}