{
  "type": "Feature",
  "properties": {
    "gn:admin1_code":"04",
    "gn:admin2_code":"409.0",
    "gn:admin3_code":"40903.0",
    "gn:asciiname":"Hinterberg",
    "gn:country_code":"AT",
    "gn:dem":655,
    "gn:feature_class":"P",
    "gn:feature_code":"PPL",
    "gn:name":"Hinterberg",
    "gn:population":139,
    "gn:timezone":"Europe/Vienna",
    "iso:country":"AT",
    "wof:name":"Hinterberg",
    "wof:placetype":"locality",
    "wof:population":139
},
  "geometry": {"coordinates":[14.12275,47.67458],"type":"Point"}
}