{
  "type": "Feature",
  "properties": {
    "gn:admin1_code":"3.0",
    "gn:admin2_code":"320",
    "gn:admin3_code":"32017.0",
    "gn:asciiname":"Muehling",
    "gn:country_code":"AT",
    "gn:dem":267,
    "gn:feature_class":"P",
    "gn:feature_code":"PPL",
    "gn:name":"M\u00fchling",
    "gn:population":587,
    "gn:timezone":"Europe/Vienna",
    "iso:country":"AT",
    "wof:name":"Muehling",
    "wof:placetype":"locality",
    "wof:population":587
},
  "geometry": {"coordinates":[15.13212,48.1017],"type":"Point"}
}