{
  "type": "Feature",
  "properties": {
    "gn:admin1_code":"4.0",
    "gn:admin2_code":"414",
    "gn:admin3_code":"41414.0",
    "gn:asciiname":"Grossprambach",
    "gn:country_code":"AT",
    "gn:dem":402,
    "gn:feature_class":"P",
    "gn:feature_code":"PPL",
    "gn:name":"Grossprambach",
    "gn:population":0,
    "gn:timezone":"Europe/Vienna",
    "iso:country":"AT",
    "wof:name":"Grossprambach",
    "wof:placetype":"locality"
},
  "geometry": {"coordinates":[13.63429,48.33777],"type":"Point"}
}