{
  "type": "Feature",
  "properties": {
    "gn:admin1_code":"6.0",
    "gn:admin2_code":"610",
    "gn:admin3_code":"61050.0",
    "gn:asciiname":"Oberlupitscheni",
    "gn:country_code":"AT",
    "gn:dem":378,
    "gn:feature_class":"P",
    "gn:feature_code":"PPL",
    "gn:name":"Oberlupitscheni",
    "gn:population":0,
    "gn:timezone":"Europe/Vienna",
    "iso:country":"AT",
    "wof:name":"Oberlupitscheni",
    "wof:placetype":"locality"
},
  "geometry": {"coordinates":[15.51667,46.73333],"type":"Point"}
}