{
  "type": "Feature",
  "properties": {
    "gn:admin1_code":"08",
    "gn:admin2_code":"801.0",
    "gn:admin3_code":"80113.0",
    "gn:asciiname":"Strass",
    "gn:country_code":"AT",
    "gn:dem":1445,
    "gn:feature_class":"P",
    "gn:feature_code":"PPL",
    "gn:name":"Strass",
    "gn:population":0,
    "gn:timezone":"Europe/Vienna",
    "iso:country":"AT",
    "wof:name":"Strass",
    "wof:placetype":"locality"
},
  "geometry": {"coordinates":[10.15,47.21667],"type":"Point"}
}