{
  "type": "Feature",
  "properties": {
    "gn:admin1_code":"3.0",
    "gn:admin2_code":"319",
    "gn:admin3_code":"31927.0",
    "gn:asciiname":"Mannersdorf",
    "gn:country_code":"AT",
    "gn:dem":261,
    "gn:feature_class":"P",
    "gn:feature_code":"PPL",
    "gn:name":"Mannersdorf",
    "gn:population":66,
    "gn:timezone":"Europe/Vienna",
    "iso:country":"AT",
    "wof:name":"Mannersdorf",
    "wof:placetype":"locality",
    "wof:population":66
},
  "geometry": {"coordinates":[15.89284,48.15818],"type":"Point"}
}