{
  "type": "Feature",
  "properties": {
    "gn:admin1_code":"2.0",
    "gn:admin2_code":"205",
    "gn:admin3_code":"20518.0",
    "gn:asciiname":"Moedring",
    "gn:country_code":"AT",
    "gn:dem":1123,
    "gn:feature_class":"P",
    "gn:feature_code":"PPL",
    "gn:name":"M\u00f6dring",
    "gn:population":57,
    "gn:timezone":"Europe/Vienna",
    "iso:country":"AT",
    "name:und_x_variant":[
        "M\u00f6dringer",
        "M\u00f6dring"
    ],
    "wof:name":"Moedring",
    "wof:placetype":"locality",
    "wof:population":57
},
  "geometry": {"coordinates":[14.15528,46.95472],"type":"Point"}
}