{
  "type": "Feature",
  "properties": {
    "gn:admin1_code":"3.0",
    "gn:admin2_code":"315",
    "gn:admin3_code":"31537.0",
    "gn:asciiname":"Kronberg",
    "gn:country_code":"AT",
    "gn:dem":299,
    "gn:feature_class":"P",
    "gn:feature_code":"PPL",
    "gn:name":"Kronberg",
    "gn:population":21,
    "gn:timezone":"Europe/Vienna",
    "iso:country":"AT",
    "wof:name":"Kronberg",
    "wof:placetype":"locality",
    "wof:population":21
},
  "geometry": {"coordinates":[15.23435,48.12574],"type":"Point"}
}