{
  "type": "Feature",
  "properties": {
    "gn:admin1_code":"3.0",
    "gn:admin2_code":"313",
    "gn:admin3_code":"31321.0",
    "gn:asciiname":"Kleinenzersdorf",
    "gn:country_code":"AT",
    "gn:dem":449,
    "gn:feature_class":"P",
    "gn:feature_code":"PPL",
    "gn:name":"Kleinenzersdorf",
    "gn:population":0,
    "gn:timezone":"Europe/Vienna",
    "iso:country":"AT",
    "wof:name":"Kleinenzersdorf",
    "wof:placetype":"locality"
},
  "geometry": {"coordinates":[15.45,48.61667],"type":"Point"}
}