{
  "type": "Feature",
  "properties": {
    "iso:country":"AT",
    "name:ceb_x_preferred":[
        "Ried-Kirchheim Airport"
    ],
    "name:deu_x_preferred":[
        "Ried-Kirchheim Airport"
    ],
    "name:deu_x_variant":[
        "Flugplatz Ried-Kirchheim"
    ],
    "name:eng_x_preferred":[
        "Ried-Kirchheim Airport"
    ],
    "name:eng_x_variant":[
        "LOLK",
        "Ried-Kirchheim airfield"
    ],
    "name:hun_x_preferred":[
        "Ried-Kirchheim rep\u00fcl\u0151t\u00e9r"
    ],
    "name:ron_x_preferred":[
        "Aeroportul Ried-Kirchheim"
    ],
    "name:swe_x_preferred":[
        "Ried-Kirchheim Airport"
    ],
    "oa:elevation_ft":"1378",
    "oa:type":"small_airport",
    "woe:hierarchy":{
        "country_id":23424750,
        "county_id":12591718,
        "localadmin_id":12674612,
        "planet_id":1,
        "state_id":2344711
    },
    "wof:name":"Sportflugplatz Ried-kirchheim",
    "wof:placetype":"campus"
},
  "geometry": {"coordinates":[13.3459,48.2122],"type":"Point"}
}