{
  "type": "Feature",
  "properties": {
    "gn:admin1_code":"03",
    "gn:admin2_code":"317.0",
    "gn:admin3_code":"31709.0",
    "gn:asciiname":"Thallern",
    "gn:country_code":"AT",
    "gn:dem":218,
    "gn:feature_class":"P",
    "gn:feature_code":"PPL",
    "gn:name":"Thallern",
    "gn:population":0,
    "gn:timezone":"Europe/Vienna",
    "iso:country":"AT",
    "wof:name":"Thallern",
    "wof:placetype":"locality"
},
  "geometry": {"coordinates":[16.2923,48.05261],"type":"Point"}
}