{
  "type": "Feature",
  "properties": {
    "gn:admin1_code":"3.0",
    "gn:admin2_code":"321",
    "gn:admin3_code":"32144.0",
    "gn:asciiname":"Gruental",
    "gn:country_code":"AT",
    "gn:dem":323,
    "gn:feature_class":"P",
    "gn:feature_code":"PPL",
    "gn:name":"Gr\u00fcntal",
    "gn:population":0,
    "gn:timezone":"Europe/Vienna",
    "iso:country":"AT",
    "wof:name":"Gruental",
    "wof:placetype":"locality"
},
  "geometry": {"coordinates":[16.28333,48.31667],"type":"Point"}
}