{
  "type": "Feature",
  "properties": {
    "gn:admin1_code":"7.0",
    "gn:admin2_code":"709",
    "gn:admin3_code":"70939.0",
    "gn:asciiname":"Astenberg",
    "gn:country_code":"AT",
    "gn:dem":722,
    "gn:feature_class":"P",
    "gn:feature_code":"PPL",
    "gn:name":"Astenberg",
    "gn:population":34,
    "gn:timezone":"Europe/Vienna",
    "iso:country":"AT",
    "wof:name":"Astenberg",
    "wof:placetype":"locality",
    "wof:population":34
},
  "geometry": {"coordinates":[11.79975,47.41659],"type":"Point"}
}