{
  "type": "Feature",
  "properties": {
    "gn:admin1_code":"02",
    "gn:admin2_code":"209.0",
    "gn:admin3_code":"20918.0",
    "gn:asciiname":"Zellbach",
    "gn:country_code":"AT",
    "gn:dem":579,
    "gn:feature_class":"P",
    "gn:feature_code":"PPL",
    "gn:name":"Zellbach",
    "gn:population":90,
    "gn:timezone":"Europe/Vienna",
    "iso:country":"AT",
    "wof:name":"Zellbach",
    "wof:placetype":"locality",
    "wof:population":90
},
  "geometry": {"coordinates":[14.813,46.71309],"type":"Point"}
}