{
  "type": "Feature",
  "properties": {
    "gn:admin1_code":"1.0",
    "gn:admin2_code":"104",
    "gn:admin3_code":"10417.0",
    "gn:asciiname":"Kroatisch Tschantschendorf",
    "gn:country_code":"AT",
    "gn:dem":244,
    "gn:feature_class":"P",
    "gn:feature_code":"PPL",
    "gn:name":"Kroatisch Tschantschendorf",
    "gn:population":95,
    "gn:timezone":"Europe/Vienna",
    "iso:country":"AT",
    "name:deu_x_preferred":[
        "Kroatisch Tschantschendorf"
    ],
    "name:hrv_x_preferred":[
        "Hrvatska \u010cen\u010da"
    ],
    "wof:name":"Kroatisch Tschantschendorf",
    "wof:placetype":"locality",
    "wof:population":95
},
  "geometry": {"coordinates":[16.28637,47.09742],"type":"Point"}
}