{
  "type": "Feature",
  "properties": {
    "gn:admin1_code":"3.0",
    "gn:admin2_code":"315",
    "gn:admin3_code":"31539.0",
    "gn:asciiname":"Sandeben",
    "gn:country_code":"AT",
    "gn:dem":265,
    "gn:feature_class":"P",
    "gn:feature_code":"PPL",
    "gn:name":"Sandeben",
    "gn:population":41,
    "gn:timezone":"Europe/Vienna",
    "iso:country":"AT",
    "wof:name":"Sandeben",
    "wof:placetype":"locality",
    "wof:population":41
},
  "geometry": {"coordinates":[15.3085,48.15472000000001],"type":"Point"}
}