{
  "type": "Feature",
  "properties": {
    "gn:admin1_code":"5.0",
    "gn:admin2_code":"506",
    "gn:admin3_code":"50613.0",
    "gn:asciiname":"Arndorf",
    "gn:country_code":"AT",
    "gn:dem":800,
    "gn:feature_class":"P",
    "gn:feature_code":"PPL",
    "gn:name":"Arndorf",
    "gn:population":1,
    "gn:timezone":"Europe/Vienna",
    "iso:country":"AT",
    "wof:name":"Arndorf",
    "wof:placetype":"locality",
    "wof:population":1
},
  "geometry": {"coordinates":[12.43333,47.28333],"type":"Point"}
}