{
  "type": "Feature",
  "properties": {
    "gn:admin1_code":"03",
    "gn:admin2_code":"312.0",
    "gn:admin3_code":"31226.0",
    "gn:asciiname":"Untermallebarn",
    "gn:country_code":"AT",
    "gn:dem":192,
    "gn:feature_class":"P",
    "gn:feature_code":"PPL",
    "gn:name":"Untermallebarn",
    "gn:population":299,
    "gn:timezone":"Europe/Vienna",
    "iso:country":"AT",
    "wof:name":"Untermallebarn",
    "wof:placetype":"locality",
    "wof:population":299
},
  "geometry": {"coordinates":[16.16667,48.45],"type":"Point"}
}