{
  "type": "Feature",
  "properties": {
    "gn:admin1_code":"03",
    "gn:admin2_code":"308.0",
    "gn:admin3_code":"30814.0",
    "gn:asciiname":"Stopfenreuth",
    "gn:country_code":"AT",
    "gn:dem":141,
    "gn:feature_class":"P",
    "gn:feature_code":"PPL",
    "gn:name":"Stopfenreuth",
    "gn:population":222,
    "gn:timezone":"Europe/Vienna",
    "iso:country":"AT",
    "wof:name":"Stopfenreuth",
    "wof:placetype":"locality",
    "wof:population":222
},
  "geometry": {"coordinates":[16.88332999999999,48.15],"type":"Point"}
}