{
  "type": "Feature",
  "properties": {
    "gn:gn_country":"AT",
    "gn:gn_fcode":"PPL",
    "gn:gn_pop":0,
    "iso:country":"AT",
    "name:deu_x_preferred":[
        "Rosenau am Hengstpa\u00df"
    ],
    "name:eng_x_preferred":[
        "Rosenau am Hengstpa\u00df"
    ],
    "name:fas_x_preferred":[
        "\u0631\u0648\u0632\u0646\u0648 \u0627\u0645 \u0647\u0646\u06af\u0634\u062a\u067e\u0627\u0633"
    ],
    "name:fra_x_preferred":[
        "Rosenau am Hengstpa\u00df"
    ],
    "name:hun_x_preferred":[
        "Rosenau am Hengstpa\u00df"
    ],
    "name:ita_x_preferred":[
        "Rosenau am Hengstpa\u00df"
    ],
    "name:jpn_x_preferred":[
        "\u30ed\u30fc\u30bc\u30ca\u30a6\u30fb\u30a2\u30e0\u30fb\u30d8\u30f3\u30af\u30b9\u30c8\u30d1\u30b9"
    ],
    "name:kaz_x_preferred":[
        "\u0420\u043e\u0437\u0435\u043d\u0430\u0443-\u0430\u043c-\u0425\u0435\u043d\u0433\u0441\u0442\u043f\u0430\u0441"
    ],
    "name:nld_x_preferred":[
        "Rosenau am Hengstpa\u00df"
    ],
    "name:pol_x_preferred":[
        "Rosenau am Hengstpa\u00df"
    ],
    "name:por_x_preferred":[
        "Rosenau am Hengstpa\u00df"
    ],
    "name:rus_x_preferred":[
        "\u0420\u043e\u0437\u0435\u043d\u0430\u0443-\u0430\u043c-\u0425\u0435\u043d\u0433\u0441\u0442\u043f\u0430\u0441"
    ],
    "name:slk_x_preferred":[
        "Rosenau am Hengstpa\u00df"
    ],
    "name:spa_x_preferred":[
        "Rosenau am Hengstpa\u00df"
    ],
    "name:unk_x_variant":[
        "Rosenau"
    ],
    "name:uzb_x_preferred":[
        "Rosenau am Hengstpa\u00df"
    ],
    "name:vie_x_preferred":[
        "Rosenau am Hengstpa\u00df"
    ],
    "name:vol_x_preferred":[
        "Rosenau am Hengstpa\u00df"
    ],
    "name:war_x_preferred":[
        "Rosenau am Hengstpa\u00df"
    ],
    "name:zho_x_preferred":[
        "Rosenau am Hengstpa\u00df"
    ],
    "qs_pg:aaroncc":"AT",
    "qs_pg:gn_country":"AT",
    "qs_pg:gn_fcode":"PPL",
    "qs_pg:gn_pop":0,
    "qs_pg:name":"Rosenau am Hengstpa\u00df",
    "qs_pg:name_adm0":"\u00d6sterreich",
    "qs_pg:name_adm1":"Ober\u00f6sterreich",
    "qs_pg:photos_9k":1,
    "qs_pg:photos_9r":1,
    "qs_pg:photos_all":1,
    "qs_pg:photos_sr":0,
    "qs_pg:pop_sr":0,
    "qs_pg:qs_pg_placetype":"locality",
    "qs_pg:qs_pg_placetype_gp":"Town",
    "qs_pg:woe_adm0":23424750,
    "woe:adm0_id":23424750,
    "woe:name_adm0":"\u00d6sterreich",
    "woe:name_adm1":"Ober\u00f6sterreich",
    "woe:placetype":"Town",
    "wof:name":"Rosenau am Hengstpa\u00df",
    "wof:placetype":"locality"
},
  "geometry": {"coordinates":[14.39252,47.71311],"type":"Point"}
}