{
  "type": "Feature",
  "properties": {
    "gn:admin1_code":"6.0",
    "gn:admin2_code":"623",
    "gn:admin3_code":"62384.0",
    "gn:asciiname":"Storchaberg",
    "gn:country_code":"AT",
    "gn:dem":327,
    "gn:feature_class":"P",
    "gn:feature_code":"PPL",
    "gn:name":"Storchaberg",
    "gn:population":0,
    "gn:timezone":"Europe/Vienna",
    "iso:country":"AT",
    "wof:name":"Storchaberg",
    "wof:placetype":"locality"
},
  "geometry": {"coordinates":[15.80722,46.96],"type":"Point"}
}