{
  "type": "Feature",
  "properties": {
    "gn:admin1_code":"05",
    "gn:admin2_code":"503.0",
    "gn:admin3_code":"50331.0",
    "gn:asciiname":"Wallsberg",
    "gn:country_code":"AT",
    "gn:dem":698,
    "gn:feature_class":"P",
    "gn:feature_code":"PPL",
    "gn:name":"Wallsberg",
    "gn:population":0,
    "gn:timezone":"Europe/Vienna",
    "iso:country":"AT",
    "wof:name":"Wallsberg",
    "wof:placetype":"locality"
},
  "geometry": {"coordinates":[13.15,47.96667],"type":"Point"}
}