{
  "type": "Feature",
  "properties": {
    "gn:admin1_code":"2.0",
    "gn:admin2_code":"204",
    "gn:admin3_code":"20414.0",
    "gn:asciiname":"Goeriach",
    "gn:country_code":"AT",
    "gn:dem":586,
    "gn:feature_class":"P",
    "gn:feature_code":"PPL",
    "gn:name":"G\u00f6riach",
    "gn:population":96,
    "gn:timezone":"Europe/Vienna",
    "iso:country":"AT",
    "wof:name":"Goeriach",
    "wof:placetype":"locality",
    "wof:population":96
},
  "geometry": {"coordinates":[14.2612,46.5564],"type":"Point"}
}