{
  "type": "Feature",
  "properties": {
    "gn:admin1_code":"5.0",
    "gn:admin2_code":"506",
    "gn:admin3_code":"50609.0",
    "gn:asciiname":"Sonnberg",
    "gn:country_code":"AT",
    "gn:dem":980,
    "gn:feature_class":"P",
    "gn:feature_code":"PPL",
    "gn:name":"Sonnberg",
    "gn:population":650,
    "gn:timezone":"Europe/Vienna",
    "iso:country":"AT",
    "wof:name":"Sonnberg",
    "wof:placetype":"locality",
    "wof:population":650
},
  "geometry": {"coordinates":[12.73333,47.45],"type":"Point"}
}