{
  "type": "Feature",
  "properties": {
    "gn:admin1_code":"03",
    "gn:admin2_code":"322.0",
    "gn:admin3_code":"32219.0",
    "gn:asciiname":"Sparbach",
    "gn:country_code":"AT",
    "gn:dem":547,
    "gn:feature_class":"P",
    "gn:feature_code":"PPL",
    "gn:name":"Sparbach",
    "gn:population":91,
    "gn:timezone":"Europe/Vienna",
    "iso:country":"AT",
    "wof:name":"Sparbach",
    "wof:placetype":"locality",
    "wof:population":91
},
  "geometry": {"coordinates":[15.21667,48.75],"type":"Point"}
}