{
  "type": "Feature",
  "properties": {
    "gn:admin1_code":"2.0",
    "gn:admin2_code":"210",
    "gn:admin3_code":"21002.0",
    "gn:asciiname":"Nassweg",
    "gn:country_code":"AT",
    "gn:dem":586,
    "gn:feature_class":"P",
    "gn:feature_code":"PPL",
    "gn:name":"Na\u00dfweg",
    "gn:population":57,
    "gn:timezone":"Europe/Vienna",
    "iso:country":"AT",
    "name:und_x_variant":[
        "Na\u00dfweg"
    ],
    "wof:name":"Nassweg",
    "wof:placetype":"locality",
    "wof:population":57
},
  "geometry": {"coordinates":[14.15267,46.69411],"type":"Point"}
}