{
  "type": "Feature",
  "properties": {
    "gn:country":"AT",
    "gn:fcode":"PPL",
    "gn:population":0,
    "iso:country":"AT",
    "name:bos_x_preferred":[
        "Riegersburg"
    ],
    "name:ceb_x_preferred":[
        "Riegersburg"
    ],
    "name:deu_x_preferred":[
        "Riegersburg"
    ],
    "name:epo_x_preferred":[
        "Riegersburg"
    ],
    "name:fas_x_preferred":[
        "\u0631\u0627\u06cc\u06af\u0631\u0633\u0628\u0648\u0631\u06af"
    ],
    "name:fra_x_preferred":[
        "Riegersburg"
    ],
    "name:hun_x_preferred":[
        "Riegersburg"
    ],
    "name:ita_x_preferred":[
        "Riegersburg"
    ],
    "name:kaz_x_preferred":[
        "\u0420\u0438\u0433\u0435\u0440\u0441\u0431\u0443\u0440\u0433"
    ],
    "name:nld_x_preferred":[
        "Riegersburg"
    ],
    "name:pol_x_preferred":[
        "Riegersburg"
    ],
    "name:rus_x_preferred":[
        "\u0420\u0438\u0433\u0435\u0440\u0441\u0431\u0443\u0440\u0433"
    ],
    "name:slk_x_preferred":[
        "Riegersburg"
    ],
    "name:slv_x_preferred":[
        "Riegersburg"
    ],
    "name:spa_x_preferred":[
        "Riegersburg"
    ],
    "name:swe_x_preferred":[
        "Riegersburg"
    ],
    "name:ukr_x_preferred":[
        "\u0420\u0456\u0433\u0435\u0440\u0441\u0431\u0443\u0440\u0433"
    ],
    "name:uzb_x_preferred":[
        "Riegersburg"
    ],
    "name:vie_x_preferred":[
        "Riegersburg"
    ],
    "name:vol_x_preferred":[
        "Riegersburg"
    ],
    "name:war_x_preferred":[
        "Riegersburg"
    ],
    "name:zho_x_preferred":[
        "\u91cc\u683c\u65af\u5821"
    ],
    "qs_pg:aaroncc":"AT",
    "qs_pg:gn_country":"AT",
    "qs_pg:gn_fcode":"PPL",
    "qs_pg:gn_pop":0,
    "qs_pg:name":"Riegersburg",
    "qs_pg:name_adm0":"\u00d6sterreich",
    "qs_pg:name_adm1":"Nieder\u00f6sterreich",
    "qs_pg:photos":10,
    "qs_pg:photos_1k":2,
    "qs_pg:photos_9k":1,
    "qs_pg:photos_9r":1,
    "qs_pg:photos_all":10,
    "qs_pg:photos_sr":1,
    "qs_pg:pop_sr":0,
    "qs_pg:qs_pg_placetype":"locality",
    "qs_pg:qs_pg_placetype_gp":"Town",
    "qs_pg:woe_adm0":23424750,
    "woe:adm0_id":23424750,
    "woe:name_adm0":"\u00d6sterreich",
    "woe:name_adm1":"Nieder\u00f6sterreich",
    "woe:placetype":"Town",
    "wof:name":"Riegersburg",
    "wof:placetype":"locality"
},
  "geometry": {"coordinates":[15.76667,48.85],"type":"Point"}
}