{
  "type": "Feature",
  "properties": {
    "iso:country":"AT",
    "name:ceb_x_preferred":[
        "Mauterndorf Airport"
    ],
    "name:deu_x_preferred":[
        "Mauterndorf Airport"
    ],
    "name:eng_x_preferred":[
        "Mauterndorf Airport"
    ],
    "name:hun_x_preferred":[
        "Mauterndorf  rep\u00fcl\u0151t\u00e9r"
    ],
    "name:ron_x_preferred":[
        "Aeroportul Mauterndorf"
    ],
    "name:swe_x_preferred":[
        "Mauterndorf Airport"
    ],
    "oa:elevation_ft":"3642",
    "oa:type":"small_airport",
    "woe:hierarchy":{
        "country_id":23424750,
        "county_id":12591728,
        "localadmin_id":12674708,
        "planet_id":1,
        "state_id":2344712
    },
    "wof:name":"Flugfeld Mauterndorf",
    "wof:placetype":"campus"
},
  "geometry": {"coordinates":[13.6959,47.132],"type":"Point"}
}