{
  "type": "Feature",
  "properties": {
    "gn:admin1_code":"5.0",
    "gn:admin2_code":"503",
    "gn:admin3_code":"50339.0",
    "gn:asciiname":"Bruderstall",
    "gn:country_code":"AT",
    "gn:dem":591,
    "gn:feature_class":"P",
    "gn:feature_code":"PPL",
    "gn:name":"Bruderstall",
    "gn:population":0,
    "gn:timezone":"Europe/Vienna",
    "iso:country":"AT",
    "wof:name":"Bruderstall",
    "wof:placetype":"locality"
},
  "geometry": {"coordinates":[13.0825,47.90444],"type":"Point"}
}