{
  "type": "Feature",
  "properties": {
    "gn:admin1_code":"2.0",
    "gn:admin2_code":"210",
    "gn:admin3_code":"21002.0",
    "gn:asciiname":"Buchscheiden",
    "gn:country_code":"AT",
    "gn:dem":528,
    "gn:feature_class":"P",
    "gn:feature_code":"PPL",
    "gn:name":"Buchscheiden",
    "gn:population":109,
    "gn:timezone":"Europe/Vienna",
    "iso:country":"AT",
    "wof:name":"Buchscheiden",
    "wof:placetype":"locality",
    "wof:population":109
},
  "geometry": {"coordinates":[14.08104,46.70604],"type":"Point"}
}