{
  "type": "Feature",
  "properties": {
    "gn:admin1_code":"07",
    "gn:admin2_code":"707.0",
    "gn:admin3_code":"70712.0",
    "gn:asciiname":"Peischlach",
    "gn:country_code":"AT",
    "gn:dem":990,
    "gn:feature_class":"P",
    "gn:feature_code":"PPL",
    "gn:name":"Peischlach",
    "gn:population":0,
    "gn:timezone":"Europe/Vienna",
    "iso:country":"AT",
    "wof:name":"Peischlach",
    "wof:placetype":"locality"
},
  "geometry": {"coordinates":[12.58333,46.93333],"type":"Point"}
}