{
  "type": "Feature",
  "properties": {
    "gn:admin1_code":"2.0",
    "gn:admin2_code":"203",
    "gn:admin3_code":"20305.0",
    "gn:asciiname":"Radnigforst",
    "gn:country_code":"AT",
    "gn:dem":715,
    "gn:feature_class":"P",
    "gn:feature_code":"PPL",
    "gn:name":"Radnigforst",
    "gn:population":9,
    "gn:timezone":"Europe/Vienna",
    "iso:country":"AT",
    "wof:name":"Radnigforst",
    "wof:placetype":"locality",
    "wof:population":9
},
  "geometry": {"coordinates":[13.37221,46.64139],"type":"Point"}
}