{
  "type": "Feature",
  "properties": {
    "gn:admin1_code":"01",
    "gn:admin2_code":"105.0",
    "gn:admin3_code":"10507.0",
    "gn:asciiname":"Kalchbergen",
    "gn:country_code":"AT",
    "gn:dem":273,
    "gn:feature_class":"P",
    "gn:feature_code":"PPL",
    "gn:name":"Kalchbergen",
    "gn:population":0,
    "gn:timezone":"Europe/Vienna",
    "iso:country":"AT",
    "wof:name":"Kalchbergen",
    "wof:placetype":"locality"
},
  "geometry": {"coordinates":[16.01667,46.85],"type":"Point"}
}