{
  "type": "Feature",
  "properties": {
    "gn:admin1_code":"2.0",
    "gn:admin2_code":"205",
    "gn:admin3_code":"20534.0",
    "gn:asciiname":"UEberfeld",
    "gn:country_code":"AT",
    "gn:dem":601,
    "gn:feature_class":"P",
    "gn:feature_code":"PPL",
    "gn:name":"\u00dcberfeld",
    "gn:population":492,
    "gn:timezone":"Europe/Vienna",
    "iso:country":"AT",
    "wof:name":"UEberfeld",
    "wof:placetype":"locality",
    "wof:population":492
},
  "geometry": {"coordinates":[14.36889,46.79972],"type":"Point"}
}