{
  "type": "Feature",
  "properties": {
    "gn:admin1_code":"02",
    "gn:admin2_code":"210.0",
    "gn:admin3_code":"21005.0",
    "gn:asciiname":"Tiffnerwinkl",
    "gn:cc2":"AT",
    "gn:country_code":"AT",
    "gn:dem":693,
    "gn:feature_class":"P",
    "gn:feature_code":"PPL",
    "gn:name":"Tiffnerwinkl",
    "gn:population":131,
    "gn:timezone":"Europe/Vienna",
    "iso:country":"AT",
    "name:und_x_variant":[
        "Tiffnerwinkel",
        "Tiffnerwinkl"
    ],
    "wof:name":"Tiffnerwinkl",
    "wof:placetype":"locality",
    "wof:population":131
},
  "geometry": {"coordinates":[14.03889,46.7275],"type":"Point"}
}