{
  "type": "Feature",
  "properties": {
    "gn:admin1_code":"5.0",
    "gn:admin2_code":"503",
    "gn:admin3_code":"50308.0",
    "gn:asciiname":"Ragging",
    "gn:country_code":"AT",
    "gn:dem":562,
    "gn:feature_class":"P",
    "gn:feature_code":"PPL",
    "gn:name":"Ragging",
    "gn:population":0,
    "gn:timezone":"Europe/Vienna",
    "iso:country":"AT",
    "name:hin_x_preferred":[
        "\u0930\u0948\u0917\u093f\u0902\u0917"
    ],
    "name:mal_x_preferred":[
        "\u0d31\u0d3e\u0d17\u0d3f\u0d19\u0d4d"
    ],
    "name:por_x_preferred":[
        "Ragging"
    ],
    "name:tam_x_preferred":[
        "\u0baa\u0b95\u0bbf\u0b9f\u0bbf\u0bb5\u0ba4\u0bc8"
    ],
    "name:tel_x_preferred":[
        "\u0c30\u0c4d\u0c2f\u0c3e\u0c17\u0c3f\u0c02\u0c17\u0c4d"
    ],
    "name:urd_x_preferred":[
        "\u0631\u06cc\u06af\u06cc\u0646\u06af"
    ],
    "wof:name":"Ragging",
    "wof:placetype":"locality"
},
  "geometry": {"coordinates":[13.04944,47.87556],"type":"Point"}
}