{
  "type": "Feature",
  "properties": {
    "gn:admin1_code":"5.0",
    "gn:admin2_code":"503",
    "gn:admin3_code":"50308.0",
    "gn:asciiname":"Ragging",
    "gn:country_code":"AT",
    "gn:dem":562,
    "gn:feature_class":"P",
    "gn:feature_code":"PPL",
    "gn:name":"Ragging",
    "gn:population":0,
    "gn:timezone":"Europe/Vienna",
    "iso:country":"AT",
    "wof:name":"Ragging",
    "wof:placetype":"locality"
},
  "geometry": {"coordinates":[13.04944,47.87556],"type":"Point"}
}