{
  "type": "Feature",
  "properties": {
    "gn:admin1_code":"08",
    "gn:admin2_code":"804.0",
    "gn:admin3_code":"80414.0",
    "gn:asciiname":"Reinberg",
    "gn:cc2":"AT",
    "gn:country_code":"AT",
    "gn:dem":706,
    "gn:feature_class":"P",
    "gn:feature_code":"PPL",
    "gn:name":"Reinberg",
    "gn:population":0,
    "gn:timezone":"Europe/Vienna",
    "iso:country":"AT",
    "name:deu_x_preferred":[
        "Reinberg"
    ],
    "name:epo_x_preferred":[
        "Reinberg"
    ],
    "name:fas_x_preferred":[
        "\u0631\u0627\u06cc\u0646\u0628\u0631\u06af"
    ],
    "name:mkd_x_preferred":[
        "\u0420\u0430\u0458\u043d\u0431\u0435\u0440\u0433"
    ],
    "name:nld_x_preferred":[
        "Reinberg"
    ],
    "name:ron_x_preferred":[
        "Reinberg"
    ],
    "name:rus_x_preferred":[
        "\u0420\u0430\u0439\u043d\u0431\u0435\u0440\u0433"
    ],
    "name:und_x_variant":[
        "Rainberg"
    ],
    "name:vol_x_preferred":[
        "Reinberg"
    ],
    "wof:name":"Reinberg",
    "wof:placetype":"locality"
},
  "geometry": {"coordinates":[9.66667,47.26667],"type":"Point"}
}