{
  "type": "Feature",
  "properties": {
    "gn:admin1_code":"08",
    "gn:admin2_code":"804.0",
    "gn:admin3_code":"80414.0",
    "gn:asciiname":"Reinberg",
    "gn:cc2":"AT",
    "gn:country_code":"AT",
    "gn:dem":706,
    "gn:feature_class":"P",
    "gn:feature_code":"PPL",
    "gn:name":"Reinberg",
    "gn:population":0,
    "gn:timezone":"Europe/Vienna",
    "iso:country":"AT",
    "name:und_x_variant":[
        "Rainberg",
        "Reinberg"
    ],
    "wof:name":"Reinberg",
    "wof:placetype":"locality"
},
  "geometry": {"coordinates":[9.66667,47.26667],"type":"Point"}
}