{
  "type": "Feature",
  "properties": {
    "gn:admin1_code":"6.0",
    "gn:admin2_code":"620",
    "gn:admin3_code":"62042.0",
    "gn:asciiname":"Grossprethal",
    "gn:country_code":"AT",
    "gn:dem":1280,
    "gn:feature_class":"P",
    "gn:feature_code":"PPL",
    "gn:name":"Gro\u00dfprethal",
    "gn:population":123,
    "gn:timezone":"Europe/Vienna",
    "iso:country":"AT",
    "wof:name":"Grossprethal",
    "wof:placetype":"locality",
    "wof:population":123
},
  "geometry": {"coordinates":[14.76282,47.04596],"type":"Point"}
}