{
  "type": "Feature",
  "properties": {
    "gn:admin1_code":"03",
    "gn:admin2_code":"305.0",
    "gn:admin3_code":"30514.0",
    "gn:asciiname":"Porstenberg",
    "gn:country_code":"AT",
    "gn:dem":364,
    "gn:feature_class":"P",
    "gn:feature_code":"PPL",
    "gn:name":"Porstenberg",
    "gn:population":150,
    "gn:timezone":"Europe/Vienna",
    "iso:country":"AT",
    "wof:name":"Porstenberg",
    "wof:placetype":"locality",
    "wof:population":150
},
  "geometry": {"coordinates":[14.53333,48.08333],"type":"Point"}
}