{
  "type": "Feature",
  "properties": {
    "gn:admin1_code":"6.0",
    "gn:admin2_code":"611",
    "gn:admin3_code":"61106.0",
    "gn:asciiname":"Liesing",
    "gn:country_code":"AT",
    "gn:dem":636,
    "gn:feature_class":"P",
    "gn:feature_code":"PPL",
    "gn:name":"Liesing",
    "gn:population":64,
    "gn:timezone":"Europe/Vienna",
    "iso:country":"AT",
    "wof:name":"Liesing",
    "wof:placetype":"locality",
    "wof:population":64
},
  "geometry": {"coordinates":[14.93333,47.38333],"type":"Point"}
}