{
  "type": "Feature",
  "properties": {
    "gn:admin1_code":"6.0",
    "gn:admin2_code":"611",
    "gn:admin3_code":"61106.0",
    "gn:asciiname":"Liesing",
    "gn:country_code":"AT",
    "gn:dem":636,
    "gn:feature_class":"P",
    "gn:feature_code":"PPL",
    "gn:name":"Liesing",
    "gn:population":64,
    "gn:timezone":"Europe/Vienna",
    "iso:country":"AT",
    "name:bar_x_preferred":[
        "Liesing"
    ],
    "name:bul_x_preferred":[
        "\u041b\u0438\u0437\u0438\u043d\u0433"
    ],
    "name:ceb_x_preferred":[
        "Gemeindebezirk Liesing"
    ],
    "name:ces_x_preferred":[
        "Liesing"
    ],
    "name:dan_x_preferred":[
        "Liesing"
    ],
    "name:deu_x_preferred":[
        "Liesing"
    ],
    "name:epo_x_preferred":[
        "Liesing"
    ],
    "name:est_x_preferred":[
        "Liesing"
    ],
    "name:fra_x_preferred":[
        "Liesing"
    ],
    "name:ita_x_preferred":[
        "Liesing"
    ],
    "name:kor_x_preferred":[
        "\ub9ac\uc9d5"
    ],
    "name:lat_x_preferred":[
        "Liesing"
    ],
    "name:ltz_x_preferred":[
        "Liesing"
    ],
    "name:pol_x_preferred":[
        "Liesing"
    ],
    "name:rus_x_preferred":[
        "\u041b\u0438\u0437\u0438\u043d\u0433"
    ],
    "name:slk_x_preferred":[
        "Liesing"
    ],
    "name:srp_x_preferred":[
        "\u041b\u0438\u0437\u0438\u043d\u0433"
    ],
    "name:swe_x_preferred":[
        "Gemeindebezirk Liesing"
    ],
    "name:tur_x_preferred":[
        "Liesing"
    ],
    "name:ukr_x_preferred":[
        "\u041b\u0456\u0437\u0456\u043d\u0433"
    ],
    "name:zho_x_preferred":[
        "\u5229\u8f9b"
    ],
    "wof:name":"Liesing",
    "wof:placetype":"locality",
    "wof:population":64
},
  "geometry": {"coordinates":[14.93333,47.38333],"type":"Point"}
}