{
  "type": "Feature",
  "properties": {
    "gn:country":"AT",
    "gn:fcode":"PPL",
    "gn:population":0,
    "iso:country":"AT",
    "name:bar_x_preferred":[
        "D\u00fcrnbeag"
    ],
    "name:ceb_x_preferred":[
        "D\u00fcrrnberg"
    ],
    "name:deu_x_preferred":[
        "D\u00fcrrnberg"
    ],
    "name:eng_x_preferred":[
        "D\u00fcrrnberg"
    ],
    "name:fas_x_preferred":[
        "\u062f\u0631\u0646\u0628\u0631\u06af"
    ],
    "name:fra_x_preferred":[
        "D\u00fcrrnberg"
    ],
    "name:hun_x_preferred":[
        "D\u00fcrrnberg"
    ],
    "name:ita_x_preferred":[
        "D\u00fcrrnberg"
    ],
    "name:nld_x_preferred":[
        "D\u00fcrrnberg"
    ],
    "name:spa_x_preferred":[
        "D\u00fcrrnberg"
    ],
    "name:swe_x_preferred":[
        "D\u00fcrrnberg"
    ],
    "name:und_x_variant":[
        "D\u00fcrnberg"
    ],
    "qs_pg:aaroncc":"AT",
    "qs_pg:gn_country":"AT",
    "qs_pg:gn_fcode":"PPL",
    "qs_pg:gn_pop":0,
    "qs_pg:name":"D\u00fcrrnberg",
    "qs_pg:name_adm0":"\u00d6sterreich",
    "qs_pg:name_adm1":"Salzburg",
    "qs_pg:photos":614,
    "qs_pg:photos_1k":124,
    "qs_pg:photos_9k":3,
    "qs_pg:photos_9r":5,
    "qs_pg:photos_all":614,
    "qs_pg:photos_sr":8,
    "qs_pg:pop_sr":0,
    "qs_pg:qs_pg_placetype":"locality",
    "qs_pg:qs_pg_placetype_gp":"Town",
    "qs_pg:woe_adm0":23424750,
    "woe:adm0_id":23424750,
    "woe:name_adm0":"\u00d6sterreich",
    "woe:name_adm1":"Salzburg",
    "woe:placetype":"Town",
    "wof:name":"D\u00fcrrnberg",
    "wof:placetype":"locality"
},
  "geometry": {"coordinates":[13.09004,47.6651],"type":"Point"}
}