{
  "type": "Feature",
  "properties": {
    "gn:admin1_code":"02",
    "gn:admin2_code":"206.0",
    "gn:admin3_code":"20638.0",
    "gn:asciiname":"Pirk",
    "gn:country_code":"AT",
    "gn:dem":1247,
    "gn:feature_class":"P",
    "gn:feature_code":"PPL",
    "gn:name":"Pirk",
    "gn:population":29,
    "gn:timezone":"Europe/Vienna",
    "iso:country":"AT",
    "wof:name":"Pirk",
    "wof:placetype":"locality",
    "wof:population":29
},
  "geometry": {"coordinates":[13.48333,46.86667],"type":"Point"}
}