{
  "type": "Feature",
  "properties": {
    "gn:admin1_code":"02",
    "gn:admin2_code":"206.0",
    "gn:admin3_code":"20638.0",
    "gn:asciiname":"Pirk",
    "gn:country_code":"AT",
    "gn:dem":1247,
    "gn:feature_class":"P",
    "gn:feature_code":"PPL",
    "gn:name":"Pirk",
    "gn:population":29,
    "gn:timezone":"Europe/Vienna",
    "iso:country":"AT",
    "name:ceb_x_preferred":[
        "Pirk"
    ],
    "name:dan_x_preferred":[
        "Pirk"
    ],
    "name:deu_x_preferred":[
        "Pirk"
    ],
    "name:epo_x_preferred":[
        "Pirk"
    ],
    "name:eus_x_preferred":[
        "Pirk"
    ],
    "name:fra_x_preferred":[
        "Pirk"
    ],
    "name:hun_x_preferred":[
        "Pirk"
    ],
    "name:hye_x_preferred":[
        "\u054a\u056b\u0580\u056f"
    ],
    "name:ind_x_preferred":[
        "Pirk"
    ],
    "name:ita_x_preferred":[
        "Pirk"
    ],
    "name:kaz_x_preferred":[
        "\u041f\u0438\u0440\u043a"
    ],
    "name:lmo_x_preferred":[
        "Pirk"
    ],
    "name:msa_x_preferred":[
        "Pirk"
    ],
    "name:nld_x_preferred":[
        "Pirk"
    ],
    "name:pol_x_preferred":[
        "Pirk"
    ],
    "name:por_x_preferred":[
        "Pirk"
    ],
    "name:ron_x_preferred":[
        "Pirk"
    ],
    "name:rus_x_preferred":[
        "\u041f\u0438\u0440\u043a"
    ],
    "name:spa_x_preferred":[
        "Pirk"
    ],
    "name:srp_x_preferred":[
        "\u041f\u0438\u0440\u043a"
    ],
    "name:ukr_x_preferred":[
        "\u041f\u0456\u0440\u043a"
    ],
    "name:uzb_x_preferred":[
        "Pirk"
    ],
    "name:vie_x_preferred":[
        "Pirk"
    ],
    "name:vol_x_preferred":[
        "Pirk"
    ],
    "name:war_x_preferred":[
        "Pirk"
    ],
    "name:zho_x_preferred":[
        "\u76ae\u5c14\u514b"
    ],
    "wof:name":"Pirk",
    "wof:placetype":"locality",
    "wof:population":29
},
  "geometry": {"coordinates":[13.48333,46.86667],"type":"Point"}
}