{
  "type": "Feature",
  "properties": {
    "gn:admin1_code":"3.0",
    "gn:admin2_code":"310",
    "gn:admin3_code":"31008.0",
    "gn:asciiname":"Bergau",
    "gn:country_code":"AT",
    "gn:dem":265,
    "gn:feature_class":"P",
    "gn:feature_code":"PPL",
    "gn:name":"Bergau",
    "gn:population":233,
    "gn:timezone":"Europe/Vienna",
    "iso:country":"AT",
    "wof:name":"Bergau",
    "wof:placetype":"locality",
    "wof:population":233
},
  "geometry": {"coordinates":[16.16667,48.51667],"type":"Point"}
}