{
  "type": "Feature",
  "properties": {
    "gn:admin1_code":"3.0",
    "gn:admin2_code":"315",
    "gn:admin3_code":"31534.0",
    "gn:asciiname":"Wachtberg",
    "gn:country_code":"AT",
    "gn:dem":676,
    "gn:feature_class":"P",
    "gn:feature_code":"PPL",
    "gn:name":"Wachtberg",
    "gn:population":13,
    "gn:timezone":"Europe/Vienna",
    "iso:country":"AT",
    "wof:name":"Wachtberg",
    "wof:placetype":"locality",
    "wof:population":13
},
  "geometry": {"coordinates":[15.18654,48.2993],"type":"Point"}
}