{
  "type": "Feature",
  "properties": {
    "gn:admin1_code":"4.0",
    "gn:admin2_code":"412",
    "gn:admin3_code":"41213.0",
    "gn:asciiname":"Reintal",
    "gn:country_code":"AT",
    "gn:dem":501,
    "gn:feature_class":"P",
    "gn:feature_code":"PPL",
    "gn:name":"Reintal",
    "gn:population":15,
    "gn:timezone":"Europe/Vienna",
    "iso:country":"AT",
    "name:ceb_x_preferred":[
        "Reintal"
    ],
    "name:deu_x_preferred":[
        "Reintal"
    ],
    "name:swe_x_preferred":[
        "Reintal"
    ],
    "wof:name":"Reintal",
    "wof:placetype":"locality",
    "wof:population":15
},
  "geometry": {"coordinates":[13.38924,48.15959],"type":"Point"}
}