{
  "type": "Feature",
  "properties": {
    "gn:gn_country":"AT",
    "gn:gn_fcode":"PPL",
    "gn:gn_pop":0,
    "iso:country":"AT",
    "name:bul_x_preferred":[
        "\u041c\u0438\u043b\u0449\u0430\u0442"
    ],
    "name:ceb_x_preferred":[
        "Millstatt"
    ],
    "name:fas_x_preferred":[
        "\u0645\u06cc\u0644\u0633\u062a\u0627\u062a"
    ],
    "name:fra_x_preferred":[
        "Millstatt"
    ],
    "name:fur_x_preferred":[
        "Millstatt"
    ],
    "name:kaz_x_preferred":[
        "\u041c\u0438\u043b\u044c\u0441\u0442\u0430\u0442"
    ],
    "name:nld_x_preferred":[
        "Millstatt"
    ],
    "name:nno_x_preferred":[
        "Millstatt"
    ],
    "name:por_x_preferred":[
        "Millstatt"
    ],
    "name:rus_x_preferred":[
        "\u041c\u0438\u043b\u043b\u044c\u0448\u0442\u0430\u0442\u0442-\u0430\u043c-\u0417\u0435"
    ],
    "name:swe_x_preferred":[
        "Millstatt"
    ],
    "name:unk_x_variant":[
        "Obermillstatt"
    ],
    "name:uzb_x_preferred":[
        "Millstatt"
    ],
    "name:vol_x_preferred":[
        "Millstatt"
    ],
    "name:war_x_preferred":[
        "Millstatt"
    ],
    "name:zho_x_preferred":[
        "\u7c73\u5c14\u65bd\u5854\u7279"
    ],
    "qs_pg:aaroncc":"AT",
    "qs_pg:gn_country":"AT",
    "qs_pg:gn_fcode":"PPL",
    "qs_pg:gn_pop":0,
    "qs_pg:name":"Millstatt",
    "qs_pg:name_adm0":"\u00d6sterreich",
    "qs_pg:name_adm1":"K\u00e4rnten",
    "qs_pg:photos":1164,
    "qs_pg:photos_1k":236,
    "qs_pg:photos_9k":5,
    "qs_pg:photos_9r":7,
    "qs_pg:photos_all":1164,
    "qs_pg:photos_sr":11,
    "qs_pg:pop_sr":0,
    "qs_pg:qs_pg_placetype":"locality",
    "qs_pg:qs_pg_placetype_gp":"Town",
    "qs_pg:woe_adm0":23424750,
    "woe:adm0_id":23424750,
    "woe:name_adm0":"\u00d6sterreich",
    "woe:name_adm1":"K\u00e4rnten",
    "woe:placetype":"Town",
    "wof:name":"Millstatt",
    "wof:placetype":"locality"
},
  "geometry": {"coordinates":[13.60194,46.81389],"type":"Point"}
}