{
  "type": "Feature",
  "properties": {
    "gn:admin1_code":"4.0",
    "gn:admin2_code":"408",
    "gn:admin3_code":"40829.0",
    "gn:asciiname":"Weidenau",
    "gn:country_code":"AT",
    "gn:dem":355,
    "gn:feature_class":"P",
    "gn:feature_code":"PPL",
    "gn:name":"Weidenau",
    "gn:population":4,
    "gn:timezone":"Europe/Vienna",
    "iso:country":"AT",
    "name:deu_x_preferred":[
        "Weidenau"
    ],
    "name:fra_x_preferred":[
        "Weidenau"
    ],
    "name:por_x_preferred":[
        "Weidenau"
    ],
    "wof:name":"Weidenau",
    "wof:placetype":"locality",
    "wof:population":4
},
  "geometry": {"coordinates":[13.77565,48.2416],"type":"Point"}
}