{
  "type": "Feature",
  "properties": {
    "gn:admin1_code":"7.0",
    "gn:admin2_code":"709",
    "gn:admin3_code":"70928.0",
    "gn:asciiname":"Tratzberg",
    "gn:country_code":"AT",
    "gn:dem":562,
    "gn:feature_class":"P",
    "gn:feature_code":"PPL",
    "gn:name":"Tratzberg",
    "gn:population":8,
    "gn:timezone":"Europe/Vienna",
    "iso:country":"AT",
    "wof:name":"Tratzberg",
    "wof:placetype":"locality",
    "wof:population":8
},
  "geometry": {"coordinates":[11.73949,47.38246],"type":"Point"}
}