{
  "type": "Feature",
  "properties": {
    "gn:admin1_code":"06",
    "gn:admin2_code":"610.0",
    "gn:admin3_code":"61013.0",
    "gn:asciiname":"Wippelsach",
    "gn:country_code":"AT",
    "gn:dem":291,
    "gn:feature_class":"P",
    "gn:feature_code":"PPL",
    "gn:name":"Wippelsach",
    "gn:population":0,
    "gn:timezone":"Europe/Vienna",
    "iso:country":"AT",
    "wof:name":"Wippelsach",
    "wof:placetype":"locality"
},
  "geometry": {"coordinates":[15.43333,46.75],"type":"Point"}
}