{
  "type": "Feature",
  "properties": {
    "gn:admin1_code":"6.0",
    "gn:admin2_code":"612",
    "gn:admin3_code":"61258.0",
    "gn:asciiname":"Lainbach",
    "gn:country_code":"AT",
    "gn:dem":553,
    "gn:feature_class":"P",
    "gn:feature_code":"PPL",
    "gn:name":"Lainbach",
    "gn:population":43,
    "gn:timezone":"Europe/Vienna",
    "iso:country":"AT",
    "wof:name":"Lainbach",
    "wof:placetype":"locality",
    "wof:population":43
},
  "geometry": {"coordinates":[14.76667,47.63333],"type":"Point"}
}