{
  "type": "Feature",
  "properties": {
    "gn:admin1_code":"04",
    "gn:admin2_code":"411.0",
    "gn:admin3_code":"41106.0",
    "gn:asciiname":"Standorf",
    "gn:country_code":"AT",
    "gn:dem":291,
    "gn:feature_class":"P",
    "gn:feature_code":"PPL",
    "gn:name":"Standorf",
    "gn:population":244,
    "gn:timezone":"Europe/Vienna",
    "iso:country":"AT",
    "wof:name":"Standorf",
    "wof:placetype":"locality",
    "wof:population":244
},
  "geometry": {"coordinates":[14.48547,48.29804],"type":"Point"}
}