{
  "type": "Feature",
  "properties": {
    "gn:country":"AT",
    "gn:fcode":"PPL",
    "gn:population":0,
    "iso:country":"AT",
    "name:ceb_x_preferred":[
        "Haugschlag"
    ],
    "name:ces_x_preferred":[
        "Haugschlag"
    ],
    "name:deu_x_preferred":[
        "Haugschlag"
    ],
    "name:epo_x_preferred":[
        "Haugschlag"
    ],
    "name:fas_x_preferred":[
        "\u0647\u0648\u06af\u0634\u0644\u0627\u06af"
    ],
    "name:fra_x_preferred":[
        "Haugschlag"
    ],
    "name:hun_x_preferred":[
        "Haugschlag"
    ],
    "name:ita_x_preferred":[
        "Haugschlag"
    ],
    "name:kaz_x_preferred":[
        "\u0419\u0435\u0442\u0446\u0435\u043b\u044c\u0441\u0434\u043e\u0440\u0444"
    ],
    "name:nld_x_preferred":[
        "Haugschlag"
    ],
    "name:pol_x_preferred":[
        "Haugschlag"
    ],
    "name:por_x_preferred":[
        "Haugschlag"
    ],
    "name:rus_x_preferred":[
        "\u0425\u0430\u0443\u0433\u0448\u043b\u0430\u0433"
    ],
    "name:slk_x_preferred":[
        "Haugschlag"
    ],
    "name:spa_x_preferred":[
        "Haugschlag"
    ],
    "name:swe_x_preferred":[
        "Haugschlag"
    ],
    "name:uzb_x_preferred":[
        "Haugschlag"
    ],
    "name:vie_x_preferred":[
        "Haugschlag"
    ],
    "name:vol_x_preferred":[
        "Haugschlag"
    ],
    "name:war_x_preferred":[
        "Haugschlag"
    ],
    "name:zho_x_preferred":[
        "\u8c6a\u683c\u65bd\u62c9\u683c"
    ],
    "qs_pg:aaroncc":"AT",
    "qs_pg:gn_country":"AT",
    "qs_pg:gn_fcode":"PPL",
    "qs_pg:gn_pop":0,
    "qs_pg:name":"Haugschlag",
    "qs_pg:name_adm0":"\u00d6sterreich",
    "qs_pg:name_adm1":"Nieder\u00f6sterreich",
    "qs_pg:photos":187,
    "qs_pg:photos_1k":38,
    "qs_pg:photos_9k":1,
    "qs_pg:photos_9r":4,
    "qs_pg:photos_all":187,
    "qs_pg:photos_sr":4,
    "qs_pg:pop_sr":0,
    "qs_pg:qs_pg_placetype":"locality",
    "qs_pg:qs_pg_placetype_gp":"Town",
    "qs_pg:woe_adm0":23424750,
    "woe:adm0_id":23424750,
    "woe:name_adm0":"\u00d6sterreich",
    "woe:name_adm1":"Nieder\u00f6sterreich",
    "woe:placetype":"Town",
    "wof:name":"Haugschlag",
    "wof:placetype":"locality"
},
  "geometry": {"coordinates":[15.18333,48.46667],"type":"Point"}
}