{
  "type": "Feature",
  "properties": {
    "gn:admin1_code":"5.0",
    "gn:admin2_code":"506",
    "gn:admin3_code":"50628.0",
    "gn:asciiname":"Prielau",
    "gn:country_code":"AT",
    "gn:dem":752,
    "gn:feature_class":"P",
    "gn:feature_code":"PPL",
    "gn:name":"Prielau",
    "gn:population":0,
    "gn:timezone":"Europe/Vienna",
    "iso:country":"AT",
    "wof:name":"Prielau",
    "wof:placetype":"locality"
},
  "geometry": {"coordinates":[12.79821,47.33917],"type":"Point"}
}