{
  "type": "Feature",
  "properties": {
    "gn:admin1_code":"05",
    "gn:admin2_code":"506.0",
    "gn:admin3_code":"50616.0",
    "gn:asciiname":"Wengerberg",
    "gn:country_code":"AT",
    "gn:dem":843,
    "gn:feature_class":"P",
    "gn:feature_code":"PPL",
    "gn:name":"Wengerberg",
    "gn:population":0,
    "gn:timezone":"Europe/Vienna",
    "iso:country":"AT",
    "wof:name":"Wengerberg",
    "wof:placetype":"locality"
},
  "geometry": {"coordinates":[12.72397,47.29524],"type":"Point"}
}