{
  "type": "Feature",
  "properties": {
    "gn:admin1_code":"6.0",
    "gn:admin2_code":"606",
    "gn:admin3_code":"60646.0",
    "gn:asciiname":"Hochgreit",
    "gn:country_code":"AT",
    "gn:dem":501,
    "gn:feature_class":"P",
    "gn:feature_code":"PPL",
    "gn:name":"Hochgreit",
    "gn:population":253,
    "gn:timezone":"Europe/Vienna",
    "iso:country":"AT",
    "wof:name":"Hochgreit",
    "wof:placetype":"locality",
    "wof:population":253
},
  "geometry": {"coordinates":[15.43333,47.13333],"type":"Point"}
}