{
  "type": "Feature",
  "properties": {
    "gn:admin1_code":"4.0",
    "gn:admin2_code":"416",
    "gn:admin3_code":"41607.0",
    "gn:asciiname":"Oberndorf",
    "gn:country_code":"AT",
    "gn:dem":335,
    "gn:feature_class":"P",
    "gn:feature_code":"PPL",
    "gn:name":"Oberndorf",
    "gn:population":0,
    "gn:timezone":"Europe/Vienna",
    "iso:country":"AT",
    "wof:name":"Oberndorf",
    "wof:placetype":"locality"
},
  "geometry": {"coordinates":[14.40565,48.35705],"type":"Point"}
}