{
  "type": "Feature",
  "properties": {
    "gn:admin1_code":"02",
    "gn:admin2_code":"202.0",
    "gn:admin3_code":"20201.0",
    "gn:asciiname":"Tschinowitsch",
    "gn:country_code":"AT",
    "gn:dem":552,
    "gn:feature_class":"P",
    "gn:feature_code":"PPL",
    "gn:name":"Tschinowitsch",
    "gn:population":295,
    "gn:timezone":"Europe/Vienna",
    "iso:country":"AT",
    "wof:name":"Tschinowitsch",
    "wof:placetype":"locality",
    "wof:population":295
},
  "geometry": {"coordinates":[13.85,46.58333],"type":"Point"}
}