{
  "type": "Feature",
  "properties": {
    "gn:gn_country":"AT",
    "gn:gn_fcode":"PPL",
    "gn:gn_pop":0,
    "iso:country":"AT",
    "name:ceb_x_preferred":[
        "Litzelsdorf"
    ],
    "name:ces_x_preferred":[
        "Litzelsdorf"
    ],
    "name:deu_x_preferred":[
        "Litzelsdorf"
    ],
    "name:epo_x_preferred":[
        "Litzelsdorf"
    ],
    "name:fas_x_preferred":[
        "\u0644\u06cc\u062a\u0633\u0644\u062f\u0648\u0631\u0641"
    ],
    "name:fra_x_preferred":[
        "Litzelsdorf"
    ],
    "name:hun_x_preferred":[
        "L\u0151d\u00f6s"
    ],
    "name:ita_x_preferred":[
        "Litzelsdorf"
    ],
    "name:kaz_x_preferred":[
        "\u041b\u0438\u0442\u0446\u0435\u043b\u044c\u0441\u0434\u043e\u0440\u0444"
    ],
    "name:nld_x_preferred":[
        "Litzelsdorf"
    ],
    "name:pol_x_preferred":[
        "Litzelsdorf"
    ],
    "name:por_x_preferred":[
        "Litzelsdorf"
    ],
    "name:rus_x_preferred":[
        "\u041b\u0438\u0442\u0446\u0435\u043b\u044c\u0441\u0434\u043e\u0440\u0444"
    ],
    "name:slk_x_preferred":[
        "Litzelsdorf"
    ],
    "name:spa_x_preferred":[
        "Litzelsdorf"
    ],
    "name:swe_x_preferred":[
        "Litzelsdorf"
    ],
    "name:ukr_x_preferred":[
        "\u041b\u0456\u0442\u0446\u0435\u043b\u044c\u0441\u0434\u043e\u0440\u0444"
    ],
    "name:unk_x_variant":[
        "Litzldorf"
    ],
    "name:uzb_x_preferred":[
        "Litzelsdorf"
    ],
    "name:vol_x_preferred":[
        "Litzelsdorf"
    ],
    "name:war_x_preferred":[
        "Litzelsdorf"
    ],
    "name:zho_x_preferred":[
        "\u5229\u7b56\u5c14\u65af\u591a\u592b"
    ],
    "qs_pg:aaroncc":"AT",
    "qs_pg:gn_country":"AT",
    "qs_pg:gn_fcode":"PPL",
    "qs_pg:gn_pop":0,
    "qs_pg:name":"Litzelsdorf",
    "qs_pg:name_adm0":"\u00d6sterreich",
    "qs_pg:name_adm1":"Salzburg",
    "qs_pg:photos_9k":1,
    "qs_pg:photos_9r":4,
    "qs_pg:photos_all":188,
    "qs_pg:photos_sr":0,
    "qs_pg:pop_sr":0,
    "qs_pg:qs_pg_placetype":"locality",
    "qs_pg:qs_pg_placetype_gp":"Town",
    "qs_pg:woe_adm0":23424750,
    "woe:adm0_id":23424750,
    "woe:name_adm0":"\u00d6sterreich",
    "woe:name_adm1":"Salzburg",
    "woe:placetype":"Town",
    "wof:name":"Litzelsdorf",
    "wof:placetype":"locality"
},
  "geometry": {"coordinates":[13.79728,47.13626],"type":"Point"}
}