{
  "type": "Feature",
  "properties": {
    "gn:admin1_code":"4.0",
    "gn:admin2_code":"414",
    "gn:admin3_code":"41409.0",
    "gn:asciiname":"Hoetzmannsdorf",
    "gn:country_code":"AT",
    "gn:dem":475,
    "gn:feature_class":"P",
    "gn:feature_code":"PPL",
    "gn:name":"H\u00f6tzmannsdorf",
    "gn:population":0,
    "gn:timezone":"Europe/Vienna",
    "iso:country":"AT",
    "wof:name":"Hoetzmannsdorf",
    "wof:placetype":"locality"
},
  "geometry": {"coordinates":[13.57601,48.54832],"type":"Point"}
}