{
  "type": "Feature",
  "properties": {
    "gn:admin1_code":"2.0",
    "gn:admin2_code":"210",
    "gn:admin3_code":"21009.0",
    "gn:asciiname":"Regin",
    "gn:country_code":"AT",
    "gn:dem":645,
    "gn:feature_class":"P",
    "gn:feature_code":"PPL",
    "gn:name":"Regin",
    "gn:population":16,
    "gn:timezone":"Europe/Vienna",
    "iso:country":"AT",
    "wof:name":"Regin",
    "wof:placetype":"locality",
    "wof:population":16
},
  "geometry": {"coordinates":[14.04967,46.71839],"type":"Point"}
}