{
  "type": "Feature",
  "properties": {
    "gn:admin1_code":"2.0",
    "gn:admin2_code":"210",
    "gn:admin3_code":"21009.0",
    "gn:asciiname":"Regin",
    "gn:country_code":"AT",
    "gn:dem":645,
    "gn:feature_class":"P",
    "gn:feature_code":"PPL",
    "gn:name":"Regin",
    "gn:population":16,
    "gn:timezone":"Europe/Vienna",
    "iso:country":"AT",
    "name:bul_x_preferred":[
        "\u0420\u0435\u0433\u0438\u043d"
    ],
    "name:dan_x_preferred":[
        "Regin"
    ],
    "name:deu_x_preferred":[
        "Reginn"
    ],
    "name:fas_x_preferred":[
        "\u0631\u06af\u06cc\u0646"
    ],
    "name:fin_x_preferred":[
        "Reginn"
    ],
    "name:fra_x_preferred":[
        "Regin"
    ],
    "name:ita_x_preferred":[
        "Reginn"
    ],
    "name:jpn_x_preferred":[
        "\u30ec\u30ae\u30f3"
    ],
    "name:nno_x_preferred":[
        "Regin"
    ],
    "name:nor_x_preferred":[
        "Regin"
    ],
    "name:pol_x_preferred":[
        "Regin"
    ],
    "name:por_x_preferred":[
        "Regin"
    ],
    "name:rus_x_preferred":[
        "\u0420\u0435\u0433\u0438\u043d"
    ],
    "name:spa_x_preferred":[
        "Regin"
    ],
    "name:swe_x_preferred":[
        "Regin"
    ],
    "name:ukr_x_preferred":[
        "\u0420\u0435\u0491\u0456\u043d"
    ],
    "wof:name":"Regin",
    "wof:placetype":"locality",
    "wof:population":16
},
  "geometry": {"coordinates":[14.04967,46.71839],"type":"Point"}
}