{
  "type": "Feature",
  "properties": {
    "gn:admin1_code":"04",
    "gn:admin2_code":"413.0",
    "gn:admin3_code":"41336.0",
    "gn:asciiname":"Simaden",
    "gn:country_code":"AT",
    "gn:dem":646,
    "gn:feature_class":"P",
    "gn:feature_code":"PPL",
    "gn:name":"Simaden",
    "gn:population":84,
    "gn:timezone":"Europe/Vienna",
    "iso:country":"AT",
    "wof:name":"Simaden",
    "wof:placetype":"locality",
    "wof:population":84
},
  "geometry": {"coordinates":[14.0837,48.48885],"type":"Point"}
}