{
  "type": "Feature",
  "properties": {
    "gn:admin1_code":"03",
    "gn:admin2_code":"325.0",
    "gn:admin3_code":"32509.0",
    "gn:asciiname":"Sproegnitz",
    "gn:country_code":"AT",
    "gn:dem":716,
    "gn:feature_class":"P",
    "gn:feature_code":"PPL",
    "gn:name":"Spr\u00f6gnitz",
    "gn:population":127,
    "gn:timezone":"Europe/Vienna",
    "iso:country":"AT",
    "wof:name":"Sproegnitz",
    "wof:placetype":"locality",
    "wof:population":127
},
  "geometry": {"coordinates":[15.23333,48.55],"type":"Point"}
}