{
  "type": "Feature",
  "properties": {
    "gn:admin1_code":"8.0",
    "gn:admin2_code":"801",
    "gn:admin3_code":"80103.0",
    "gn:asciiname":"Ausserbraz",
    "gn:country_code":"AT",
    "gn:dem":718,
    "gn:feature_class":"P",
    "gn:feature_code":"PPL",
    "gn:name":"Ausserbraz",
    "gn:population":1005,
    "gn:timezone":"Europe/Vienna",
    "iso:country":"AT",
    "wof:name":"Ausserbraz",
    "wof:placetype":"locality",
    "wof:population":1005
},
  "geometry": {"coordinates":[9.90066,47.14875],"type":"Point"}
}