{
  "type": "Feature",
  "properties": {
    "gn:gn_country":"AT",
    "gn:gn_fcode":"PPL",
    "gn:gn_pop":0,
    "iso:country":"AT",
    "name:ceb_x_preferred":[
        "Arnreit"
    ],
    "name:deu_x_preferred":[
        "Arnreit"
    ],
    "name:eng_x_preferred":[
        "Arnreit"
    ],
    "name:fas_x_preferred":[
        "\u0622\u0631\u0646\u0631\u0627\u06cc\u062a"
    ],
    "name:fra_x_preferred":[
        "Arnreit"
    ],
    "name:hun_x_preferred":[
        "Arnreit"
    ],
    "name:ita_x_preferred":[
        "Arnreit"
    ],
    "name:kaz_x_preferred":[
        "\u0410\u0440\u043d\u0440\u0430\u0439\u0442"
    ],
    "name:nld_x_preferred":[
        "Arnreit"
    ],
    "name:pol_x_preferred":[
        "Arnreit"
    ],
    "name:por_x_preferred":[
        "Arnreit"
    ],
    "name:rus_x_preferred":[
        "\u0410\u0440\u043d\u0440\u0430\u0439\u0442"
    ],
    "name:slk_x_preferred":[
        "Arnreit"
    ],
    "name:spa_x_preferred":[
        "Arnreit"
    ],
    "name:swe_x_preferred":[
        "Arnreit"
    ],
    "name:unk_x_variant":[
        "Arnreith"
    ],
    "name:uzb_x_preferred":[
        "Arnreit"
    ],
    "name:vol_x_preferred":[
        "Arnreit"
    ],
    "name:war_x_preferred":[
        "Arnreit"
    ],
    "name:zho_x_preferred":[
        "\u963f\u5c14\u6069\u96f7\u7279"
    ],
    "qs_pg:aaroncc":"AT",
    "qs_pg:gn_country":"AT",
    "qs_pg:gn_fcode":"PPL",
    "qs_pg:gn_pop":0,
    "qs_pg:name":"Arnreit",
    "qs_pg:name_adm0":"\u00d6sterreich",
    "qs_pg:name_adm1":"Ober\u00f6sterreich",
    "qs_pg:photos":9,
    "qs_pg:photos_1k":2,
    "qs_pg:photos_9k":1,
    "qs_pg:photos_9r":1,
    "qs_pg:photos_all":9,
    "qs_pg:photos_sr":1,
    "qs_pg:pop_sr":0,
    "qs_pg:qs_pg_placetype":"locality",
    "qs_pg:qs_pg_placetype_gp":"Town",
    "qs_pg:woe_adm0":23424750,
    "woe:adm0_id":23424750,
    "woe:name_adm0":"\u00d6sterreich",
    "woe:name_adm1":"Ober\u00f6sterreich",
    "woe:placetype":"Town",
    "wof:name":"Arnreit",
    "wof:placetype":"locality"
},
  "geometry": {"coordinates":[13.99487,48.52513],"type":"Point"}
}