{
  "type": "Feature",
  "properties": {
    "gn:admin1_code":"4.0",
    "gn:admin2_code":"416",
    "gn:admin3_code":"41625.0",
    "gn:asciiname":"Geierschlag",
    "gn:country_code":"AT",
    "gn:dem":806,
    "gn:feature_class":"P",
    "gn:feature_code":"PPL",
    "gn:name":"Geierschlag",
    "gn:population":0,
    "gn:timezone":"Europe/Vienna",
    "iso:country":"AT",
    "wof:name":"Geierschlag",
    "wof:placetype":"locality"
},
  "geometry": {"coordinates":[14.18455,48.54099],"type":"Point"}
}