{
  "type": "Feature",
  "properties": {
    "gn:admin1_code":"3.0",
    "gn:admin2_code":"315",
    "gn:admin3_code":"31511.0",
    "gn:asciiname":"Fahrenbach",
    "gn:country_code":"AT",
    "gn:dem":311,
    "gn:feature_class":"P",
    "gn:feature_code":"PPL",
    "gn:name":"Fahrenbach",
    "gn:population":5,
    "gn:timezone":"Europe/Vienna",
    "iso:country":"AT",
    "name:als_x_preferred":[
        "Fahrenbach"
    ],
    "name:deu_x_preferred":[
        "Fahrenbach"
    ],
    "name:epo_x_preferred":[
        "Fahrenbach"
    ],
    "name:eus_x_preferred":[
        "Fahrenbach"
    ],
    "name:fas_x_preferred":[
        "\u0641\u0627\u0631\u0646\u0628\u0627\u062e"
    ],
    "name:fra_x_preferred":[
        "Fahrenbach"
    ],
    "name:hun_x_preferred":[
        "Fahrenbach"
    ],
    "name:ita_x_preferred":[
        "Fahrenbach"
    ],
    "name:jpn_x_preferred":[
        "\u30d5\u30a1\u30fc\u30ec\u30f3\u30d0\u30c3\u30cf"
    ],
    "name:kaz_x_preferred":[
        "\u0424\u0430\u0440\u0435\u043d\u0431\u0430\u0445"
    ],
    "name:kir_x_preferred":[
        "\u0424\u0430\u0440\u0435\u043d\u0431\u0430\u0445"
    ],
    "name:lat_x_preferred":[
        "Fahrenbach"
    ],
    "name:lmo_x_preferred":[
        "Fahrenbach"
    ],
    "name:msa_x_preferred":[
        "Fahrenbach"
    ],
    "name:nld_x_preferred":[
        "Fahrenbach"
    ],
    "name:pol_x_preferred":[
        "Fahrenbach"
    ],
    "name:por_x_preferred":[
        "Fahrenbach"
    ],
    "name:ron_x_preferred":[
        "Fahrenbach"
    ],
    "name:rus_x_preferred":[
        "\u0424\u0430\u0440\u0435\u043d\u0431\u0430\u0445"
    ],
    "name:spa_x_preferred":[
        "Fahrenbach"
    ],
    "name:srp_x_preferred":[
        "\u0424\u0430\u0440\u0435\u043d\u0431\u0430\u0445"
    ],
    "name:ukr_x_preferred":[
        "\u0424\u0430\u0440\u0435\u043d\u0431\u0430\u0445"
    ],
    "name:urd_x_preferred":[
        "\u0641\u0627\u06c1\u0631\u06cc\u0646\u0628\u0627\u0686"
    ],
    "name:uzb_x_preferred":[
        "Fahrenbach"
    ],
    "name:vol_x_preferred":[
        "Fahrenbach"
    ],
    "name:war_x_preferred":[
        "Fahrenbach"
    ],
    "name:zho_x_preferred":[
        "\u6cd5\u4f26\u5df4\u8d6b"
    ],
    "wof:name":"Fahrenbach",
    "wof:placetype":"locality",
    "wof:population":5
},
  "geometry": {"coordinates":[15.0556,48.2032],"type":"Point"}
}