{
  "type": "Feature",
  "properties": {
    "gn:admin1_code":"3.0",
    "gn:admin2_code":"315",
    "gn:admin3_code":"31511.0",
    "gn:asciiname":"Fahrenbach",
    "gn:country_code":"AT",
    "gn:dem":311,
    "gn:feature_class":"P",
    "gn:feature_code":"PPL",
    "gn:name":"Fahrenbach",
    "gn:population":5,
    "gn:timezone":"Europe/Vienna",
    "iso:country":"AT",
    "wof:name":"Fahrenbach",
    "wof:placetype":"locality",
    "wof:population":5
},
  "geometry": {"coordinates":[15.0556,48.2032],"type":"Point"}
}