{
  "type": "Feature",
  "properties": {
    "gn:admin1_code":"4.0",
    "gn:admin2_code":"414",
    "gn:admin3_code":"41427.0",
    "gn:asciiname":"Kothau",
    "gn:country_code":"AT",
    "gn:dem":683,
    "gn:feature_class":"P",
    "gn:feature_code":"PPL",
    "gn:name":"Kothau",
    "gn:population":0,
    "gn:timezone":"Europe/Vienna",
    "iso:country":"AT",
    "wof:name":"Kothau",
    "wof:placetype":"locality"
},
  "geometry": {"coordinates":[13.65194,48.51833],"type":"Point"}
}