{
  "type": "Feature",
  "properties": {
    "iso:country":"AT",
    "qs:a0":"\u00d6sterreich",
    "qs:a1":"*Salzburg",
    "qs:a1r":"0",
    "qs:a2":"Sankt Johann im Pongau",
    "qs:adm0":"\u00d6sterreich",
    "qs:la":"Bischofshofen",
    "qs:la_lc":"*AT50404",
    "qs:level":"locality",
    "qs:loc":"Mitterbergh\u00fctten",
    "qs:loc_alt":"Mitterberghuetten",
    "qs:pop":0,
    "qs:type":"rural point-near-poly",
    "wof:name":"Mitterbergh\u00fctten",
    "wof:placetype":"locality"
},
  "geometry": {"coordinates":[13.215569,47.401722],"type":"Point"}
}