{
  "type": "Feature",
  "properties": {
    "gn:admin1_code":"1.0",
    "gn:admin2_code":"108",
    "gn:admin3_code":"10815.0",
    "gn:asciiname":"Kroatisch Minihof",
    "gn:country_code":"AT",
    "gn:dem":258,
    "gn:feature_class":"P",
    "gn:feature_code":"PPL",
    "gn:name":"Kroatisch Minihof",
    "gn:population":334,
    "gn:timezone":"Europe/Vienna",
    "iso:country":"AT",
    "name:deu_x_preferred":[
        "Kroatisch Minihof"
    ],
    "name:hrv_x_preferred":[
        "Mjenovo"
    ],
    "name:hun_x_preferred":[
        "Malomh\u00e1za"
    ],
    "name:und_x_variant":[
        "Minihof",
        "Kroatisch Minihof"
    ],
    "wof:name":"Kroatisch Minihof",
    "wof:placetype":"locality",
    "wof:population":334
},
  "geometry": {"coordinates":[16.64446,47.52549000000001],"type":"Point"}
}