{
  "type": "Feature",
  "properties": {
    "gn:admin1_code":"3.0",
    "gn:admin2_code":"325",
    "gn:admin3_code":"32530.0",
    "gn:asciiname":"Gradnitz",
    "gn:country_code":"AT",
    "gn:dem":613,
    "gn:feature_class":"P",
    "gn:feature_code":"PPL",
    "gn:name":"Gradnitz",
    "gn:population":122,
    "gn:timezone":"Europe/Vienna",
    "iso:country":"AT",
    "wof:name":"Gradnitz",
    "wof:placetype":"locality",
    "wof:population":122
},
  "geometry": {"coordinates":[15.14465,48.63081],"type":"Point"}
}