{
  "type": "Feature",
  "properties": {
    "gn:admin1_code":"2.0",
    "gn:admin2_code":"207",
    "gn:admin3_code":"20723.0",
    "gn:asciiname":"Gassen",
    "gn:country_code":"AT",
    "gn:dem":802,
    "gn:feature_class":"P",
    "gn:feature_code":"PPL",
    "gn:name":"Gassen",
    "gn:population":152,
    "gn:timezone":"Europe/Vienna",
    "iso:country":"AT",
    "wof:name":"Gassen",
    "wof:placetype":"locality",
    "wof:population":152
},
  "geometry": {"coordinates":[13.54917,46.72417],"type":"Point"}
}