{
  "type": "Feature",
  "properties": {
    "gn:admin1_code":"3.0",
    "gn:admin2_code":"316",
    "gn:admin3_code":"31630.0",
    "gn:asciiname":"Eggersdorf",
    "gn:country_code":"AT",
    "gn:dem":235,
    "gn:feature_class":"P",
    "gn:feature_code":"PPL",
    "gn:name":"Eggersdorf",
    "gn:population":100,
    "gn:timezone":"Europe/Vienna",
    "iso:country":"AT",
    "wof:name":"Eggersdorf",
    "wof:placetype":"locality",
    "wof:population":100
},
  "geometry": {"coordinates":[16.45,48.53333],"type":"Point"}
}