{
  "type": "Feature",
  "properties": {
    "gn:admin1_code":"07",
    "gn:admin2_code":"705.0",
    "gn:admin3_code":"70513.0",
    "gn:asciiname":"Zell",
    "gn:country_code":"AT",
    "gn:dem":516,
    "gn:feature_class":"P",
    "gn:feature_code":"PPL",
    "gn:name":"Zell",
    "gn:population":2551,
    "gn:timezone":"Europe/Vienna",
    "iso:country":"AT",
    "wof:name":"Zell",
    "wof:placetype":"locality",
    "wof:population":2551
},
  "geometry": {"coordinates":[12.15,47.58333],"type":"Point"}
}