{
  "type": "Feature",
  "properties": {
    "gn:admin1_code":"6.0",
    "gn:admin2_code":"611",
    "gn:admin3_code":"61115.0",
    "gn:asciiname":"Kaisersberg",
    "gn:country_code":"AT",
    "gn:dem":803,
    "gn:feature_class":"P",
    "gn:feature_code":"PPL",
    "gn:name":"Kaisersberg",
    "gn:population":383,
    "gn:timezone":"Europe/Vienna",
    "iso:country":"AT",
    "wof:name":"Kaisersberg",
    "wof:placetype":"locality",
    "wof:population":383
},
  "geometry": {"coordinates":[14.96667,47.33333],"type":"Point"}
}