{
  "type": "Feature",
  "properties": {
    "gn:admin1_code":"02",
    "gn:admin2_code":"208.0",
    "gn:admin3_code":"20801.0",
    "gn:asciiname":"Sankt Georgen",
    "gn:country_code":"AT",
    "gn:dem":515,
    "gn:feature_class":"P",
    "gn:feature_code":"PPL",
    "gn:name":"Sankt Georgen",
    "gn:population":39,
    "gn:timezone":"Europe/Vienna",
    "iso:country":"AT",
    "name:als_x_preferred":[
        "Sankt Georgen"
    ],
    "name:ceb_x_preferred":[
        "Sankt Georgen"
    ],
    "name:ces_x_preferred":[
        "Sankt Georgen"
    ],
    "name:deu_x_preferred":[
        "Sankt Georgen"
    ],
    "name:ita_x_preferred":[
        "Sankt Georgen"
    ],
    "name:nld_x_preferred":[
        "Sankt Georgen"
    ],
    "name:pol_x_preferred":[
        "Sankt Georgen"
    ],
    "name:rus_x_preferred":[
        "\u0421\u0430\u043d\u043a\u0442-\u0413\u0435\u043e\u0440\u0433\u0435\u043d"
    ],
    "name:swe_x_preferred":[
        "Sankt Georgen"
    ],
    "wof:name":"Sankt Georgen",
    "wof:placetype":"locality",
    "wof:population":39
},
  "geometry": {"coordinates":[14.81667,46.55],"type":"Point"}
}