{
  "type": "Feature",
  "properties": {
    "gn:admin1_code":"02",
    "gn:admin2_code":"208.0",
    "gn:admin3_code":"20801.0",
    "gn:asciiname":"Sankt Georgen",
    "gn:country_code":"AT",
    "gn:dem":515,
    "gn:feature_class":"P",
    "gn:feature_code":"PPL",
    "gn:name":"Sankt Georgen",
    "gn:population":39,
    "gn:timezone":"Europe/Vienna",
    "iso:country":"AT",
    "wof:name":"Sankt Georgen",
    "wof:placetype":"locality",
    "wof:population":39
},
  "geometry": {"coordinates":[14.81667,46.55],"type":"Point"}
}