{
  "type": "Feature",
  "properties": {
    "gn:admin1_code":"3.0",
    "gn:admin2_code":"325",
    "gn:admin3_code":"32508.0",
    "gn:asciiname":"Kinzenschlag",
    "gn:country_code":"AT",
    "gn:dem":797,
    "gn:feature_class":"P",
    "gn:feature_code":"PPL",
    "gn:name":"Kinzenschlag",
    "gn:population":46,
    "gn:timezone":"Europe/Vienna",
    "iso:country":"AT",
    "wof:name":"Kinzenschlag",
    "wof:placetype":"locality",
    "wof:population":46
},
  "geometry": {"coordinates":[14.93333,48.55],"type":"Point"}
}