{
  "type": "Feature",
  "properties": {
    "gn:admin1_code":"4.0",
    "gn:admin2_code":"408",
    "gn:admin3_code":"40812.0",
    "gn:asciiname":"Mairhof",
    "gn:country_code":"AT",
    "gn:dem":405,
    "gn:feature_class":"P",
    "gn:feature_code":"PPL",
    "gn:name":"Mairhof",
    "gn:population":12,
    "gn:timezone":"Europe/Vienna",
    "iso:country":"AT",
    "wof:name":"Mairhof",
    "wof:placetype":"locality",
    "wof:population":12
},
  "geometry": {"coordinates":[13.68176,48.27914000000001],"type":"Point"}
}