{
  "type": "Feature",
  "properties": {
    "gn:admin1_code":"2.0",
    "gn:admin2_code":"203",
    "gn:admin3_code":"20307.0",
    "gn:asciiname":"Gratzhof",
    "gn:country_code":"AT",
    "gn:dem":785,
    "gn:feature_class":"P",
    "gn:feature_code":"PPL",
    "gn:name":"Gratzhof",
    "gn:population":12,
    "gn:timezone":"Europe/Vienna",
    "iso:country":"AT",
    "wof:name":"Gratzhof",
    "wof:placetype":"locality",
    "wof:population":12
},
  "geometry": {"coordinates":[13.06219,46.64522],"type":"Point"}
}