{
  "type": "Feature",
  "properties": {
    "gn:admin1_code":"06",
    "gn:admin2_code":"611.0",
    "gn:admin3_code":"61106.0",
    "gn:asciiname":"Seiz",
    "gn:country_code":"AT",
    "gn:dem":820,
    "gn:feature_class":"P",
    "gn:feature_code":"PPL",
    "gn:name":"Seiz",
    "gn:population":267,
    "gn:timezone":"Europe/Vienna",
    "iso:country":"AT",
    "wof:name":"Seiz",
    "wof:placetype":"locality",
    "wof:population":267
},
  "geometry": {"coordinates":[14.91667,47.38333],"type":"Point"}
}