{
  "type": "Feature",
  "properties": {
    "gn:admin1_code":"3.0",
    "gn:admin2_code":"306",
    "gn:admin3_code":"30616.0",
    "gn:asciiname":"Grosskrottenbach",
    "gn:country_code":"AT",
    "gn:dem":393,
    "gn:feature_class":"P",
    "gn:feature_code":"PPL",
    "gn:name":"Grosskrottenbach",
    "gn:population":0,
    "gn:timezone":"Europe/Vienna",
    "iso:country":"AT",
    "wof:name":"Grosskrottenbach",
    "wof:placetype":"locality"
},
  "geometry": {"coordinates":[16.0112,48.07865],"type":"Point"}
}