{
  "type": "Feature",
  "properties": {
    "gn:admin1_code":"4.0",
    "gn:admin2_code":"417",
    "gn:admin3_code":"41716.0",
    "gn:asciiname":"Rothauptberg",
    "gn:country_code":"AT",
    "gn:dem":719,
    "gn:feature_class":"P",
    "gn:feature_code":"PPL",
    "gn:name":"Rothauptberg",
    "gn:population":49,
    "gn:timezone":"Europe/Vienna",
    "iso:country":"AT",
    "wof:name":"Rothauptberg",
    "wof:placetype":"locality",
    "wof:population":49
},
  "geometry": {"coordinates":[13.53005,48.07905],"type":"Point"}
}