{
  "type": "Feature",
  "properties": {
    "gn:admin1_code":"02",
    "gn:admin2_code":"210.0",
    "gn:admin3_code":"21003.0",
    "gn:asciiname":"Sankt Leonhard",
    "gn:country_code":"AT",
    "gn:dem":545,
    "gn:feature_class":"P",
    "gn:feature_code":"PPL",
    "gn:name":"Sankt Leonhard",
    "gn:population":116,
    "gn:timezone":"Europe/Vienna",
    "iso:country":"AT",
    "name:ceb_x_preferred":[
        "Sankt Leonhard"
    ],
    "name:deu_x_preferred":[
        "Sankt Leonhard"
    ],
    "name:ita_x_preferred":[
        "Sankt Leonhard"
    ],
    "name:nld_x_preferred":[
        "Sankt Leonhard"
    ],
    "name:pol_x_preferred":[
        "Sankt Leonhard"
    ],
    "name:swe_x_preferred":[
        "Sankt Leonhard"
    ],
    "wof:name":"Sankt Leonhard",
    "wof:placetype":"locality",
    "wof:population":116
},
  "geometry": {"coordinates":[14.25,46.73333],"type":"Point"}
}