{
  "type": "Feature",
  "properties": {
    "gn:admin1_code":"3.0",
    "gn:admin2_code":"325",
    "gn:admin3_code":"32520.0",
    "gn:asciiname":"Nondorf",
    "gn:country_code":"AT",
    "gn:dem":529,
    "gn:feature_class":"P",
    "gn:feature_code":"PPL",
    "gn:name":"Nondorf",
    "gn:population":58,
    "gn:timezone":"Europe/Vienna",
    "iso:country":"AT",
    "wof:name":"Nondorf",
    "wof:placetype":"locality",
    "wof:population":58
},
  "geometry": {"coordinates":[15.41667,48.61667],"type":"Point"}
}