{
  "type": "Feature",
  "properties": {
    "gn:admin1_code":"02",
    "gn:admin2_code":"208.0",
    "gn:admin3_code":"20815.0",
    "gn:asciiname":"Pfannsdorf",
    "gn:country_code":"AT",
    "gn:dem":552,
    "gn:feature_class":"P",
    "gn:feature_code":"PPL",
    "gn:name":"Pfannsdorf",
    "gn:population":84,
    "gn:timezone":"Europe/Vienna",
    "iso:country":"AT",
    "wof:name":"Pfannsdorf",
    "wof:placetype":"locality",
    "wof:population":84
},
  "geometry": {"coordinates":[14.63694,46.55528],"type":"Point"}
}