{
  "type": "Feature",
  "properties": {
    "gn:admin1_code":"06",
    "gn:admin2_code":"603.0",
    "gn:admin3_code":"60348.0",
    "gn:asciiname":"Waldkeuschler",
    "gn:country_code":"AT",
    "gn:dem":1057,
    "gn:feature_class":"P",
    "gn:feature_code":"PPL",
    "gn:name":"Waldkeuschler",
    "gn:population":0,
    "gn:timezone":"Europe/Vienna",
    "iso:country":"AT",
    "wof:name":"Waldkeuschler",
    "wof:placetype":"locality"
},
  "geometry": {"coordinates":[15.16667,46.95],"type":"Point"}
}