{
  "type": "Feature",
  "properties": {
    "gn:admin1_code":"03",
    "gn:admin2_code":"321.0",
    "gn:admin3_code":"32132.0",
    "gn:asciiname":"Thallern",
    "gn:country_code":"AT",
    "gn:dem":204,
    "gn:feature_class":"P",
    "gn:feature_code":"PPL",
    "gn:name":"Thallern",
    "gn:population":238,
    "gn:timezone":"Europe/Vienna",
    "iso:country":"AT",
    "wof:name":"Thallern",
    "wof:placetype":"locality",
    "wof:population":238
},
  "geometry": {"coordinates":[15.79473,48.3235],"type":"Point"}
}