{
  "type": "Feature",
  "properties": {
    "gn:admin1_code":"5.0",
    "gn:admin2_code":"506",
    "gn:admin3_code":"50606.0",
    "gn:asciiname":"Kaprun Werksiedlung",
    "gn:country_code":"AT",
    "gn:dem":1246,
    "gn:feature_class":"P",
    "gn:feature_code":"PPL",
    "gn:name":"Kaprun Werksiedlung",
    "gn:population":0,
    "gn:timezone":"Europe/Vienna",
    "iso:country":"AT",
    "wof:name":"Kaprun Werksiedlung",
    "wof:placetype":"locality"
},
  "geometry": {"coordinates":[12.75,47.25],"type":"Point"}
}