{
  "type": "Feature",
  "properties": {
    "gn:admin1_code":"2.0",
    "gn:admin2_code":"204",
    "gn:admin3_code":"20402.0",
    "gn:asciiname":"Rosenegg",
    "gn:country_code":"AT",
    "gn:dem":429,
    "gn:feature_class":"P",
    "gn:feature_code":"PPL",
    "gn:name":"Rosenegg",
    "gn:population":260,
    "gn:timezone":"Europe/Vienna",
    "iso:country":"AT",
    "wof:name":"Rosenegg",
    "wof:placetype":"locality",
    "wof:population":260
},
  "geometry": {"coordinates":[14.35535,46.61257],"type":"Point"}
}