{
  "type": "Feature",
  "properties": {
    "gn:admin1_code":"04",
    "gn:admin2_code":"416.0",
    "gn:admin3_code":"41613.0",
    "gn:asciiname":"Wildberg",
    "gn:country_code":"AT",
    "gn:dem":548,
    "gn:feature_class":"P",
    "gn:feature_code":"PPL",
    "gn:name":"Wildberg",
    "gn:population":123,
    "gn:timezone":"Europe/Vienna",
    "iso:country":"AT",
    "name:als_x_preferred":[
        "Wildberg"
    ],
    "name:ceb_x_preferred":[
        "Wildberg"
    ],
    "name:deu_x_preferred":[
        "Wildberg"
    ],
    "name:epo_x_preferred":[
        "Wildberg"
    ],
    "name:eus_x_preferred":[
        "Wildberg"
    ],
    "name:fra_x_preferred":[
        "Wildberg"
    ],
    "name:ita_x_preferred":[
        "Wildberg"
    ],
    "name:lmo_x_preferred":[
        "Wildberg"
    ],
    "name:mkd_x_preferred":[
        "\u0412\u0438\u043b\u0434\u0431\u0435\u0440\u0433"
    ],
    "name:nld_x_preferred":[
        "Wildberg"
    ],
    "name:pol_x_preferred":[
        "Wildberg"
    ],
    "name:por_x_preferred":[
        "Wildberg"
    ],
    "name:rus_x_preferred":[
        "\u0412\u0438\u043b\u044c\u0434\u0431\u0435\u0440\u0433"
    ],
    "name:srp_x_preferred":[
        "\u0412\u0438\u043b\u0434\u0431\u0435\u0440\u0433"
    ],
    "name:swe_x_preferred":[
        "Wildberg"
    ],
    "name:vol_x_preferred":[
        "Wildberg"
    ],
    "wof:name":"Wildberg",
    "wof:placetype":"locality",
    "wof:population":123
},
  "geometry": {"coordinates":[14.29673,48.40265],"type":"Point"}
}