{
  "type": "Feature",
  "properties": {
    "gn:admin1_code":"04",
    "gn:admin2_code":"416.0",
    "gn:admin3_code":"41613.0",
    "gn:asciiname":"Wildberg",
    "gn:country_code":"AT",
    "gn:dem":548,
    "gn:feature_class":"P",
    "gn:feature_code":"PPL",
    "gn:name":"Wildberg",
    "gn:population":123,
    "gn:timezone":"Europe/Vienna",
    "iso:country":"AT",
    "wof:name":"Wildberg",
    "wof:placetype":"locality",
    "wof:population":123
},
  "geometry": {"coordinates":[14.29673,48.40265],"type":"Point"}
}