{
  "type": "Feature",
  "properties": {
    "gn:admin1_code":"2.0",
    "gn:admin2_code":"207",
    "gn:admin3_code":"20703.0",
    "gn:asciiname":"Hundsdorf",
    "gn:country_code":"AT",
    "gn:dem":887,
    "gn:feature_class":"P",
    "gn:feature_code":"PPL",
    "gn:name":"Hundsdorf",
    "gn:population":145,
    "gn:timezone":"Europe/Vienna",
    "iso:country":"AT",
    "name:ara_x_preferred":[
        "\u0647\u0648\u0646\u062f\u0633\u062f\u0648\u0631\u0641"
    ],
    "name:ceb_x_preferred":[
        "Hundsdorf"
    ],
    "name:deu_x_preferred":[
        "Hundsdorf"
    ],
    "name:epo_x_preferred":[
        "Hundsdorf"
    ],
    "name:eus_x_preferred":[
        "Hundsdorf"
    ],
    "name:fas_x_preferred":[
        "\u0647\u0648\u0646\u062f\u0633\u062f\u0648\u0631\u0641"
    ],
    "name:fra_x_preferred":[
        "Hundsdorf"
    ],
    "name:hun_x_preferred":[
        "Hundsdorf"
    ],
    "name:ita_x_preferred":[
        "Hundsdorf"
    ],
    "name:kaz_x_preferred":[
        "\u0425\u0443\u043d\u0434\u0441\u0434\u043e\u0440\u0444"
    ],
    "name:kir_x_preferred":[
        "\u0425\u0443\u043d\u0434\u0441\u0434\u043e\u0440\u0444"
    ],
    "name:msa_x_preferred":[
        "Hundsdorf"
    ],
    "name:nld_x_preferred":[
        "Hundsdorf"
    ],
    "name:pol_x_preferred":[
        "Hundsdorf"
    ],
    "name:por_x_preferred":[
        "Hundsdorf"
    ],
    "name:ron_x_preferred":[
        "Hundsdorf"
    ],
    "name:rus_x_preferred":[
        "\u0425\u0443\u043d\u0434\u0441\u0434\u043e\u0440\u0444"
    ],
    "name:srp_x_preferred":[
        "\u0425\u0443\u043d\u0434\u0441\u0434\u043e\u0440\u0444"
    ],
    "name:ukr_x_preferred":[
        "\u0413\u0443\u043d\u0434\u0441\u0434\u043e\u0440\u0444"
    ],
    "name:uzb_x_preferred":[
        "Hundsdorf"
    ],
    "name:vol_x_preferred":[
        "Hundsdorf"
    ],
    "name:war_x_preferred":[
        "Hundsdorf"
    ],
    "name:zho_x_preferred":[
        "\u6d2a\u8328\u591a\u592b"
    ],
    "wof:name":"Hundsdorf",
    "wof:placetype":"locality",
    "wof:population":145
},
  "geometry": {"coordinates":[13.86526,46.72771],"type":"Point"}
}