{
  "type": "Feature",
  "properties": {
    "gn:admin1_code":"4.0",
    "gn:admin2_code":"414",
    "gn:admin3_code":"41404.0",
    "gn:asciiname":"Inding",
    "gn:country_code":"AT",
    "gn:dem":345,
    "gn:feature_class":"P",
    "gn:feature_code":"PPL",
    "gn:name":"Inding",
    "gn:population":35,
    "gn:timezone":"Europe/Vienna",
    "iso:country":"AT",
    "wof:name":"Inding",
    "wof:placetype":"locality",
    "wof:population":35
},
  "geometry": {"coordinates":[13.56133,48.39849],"type":"Point"}
}