{
  "type": "Feature",
  "properties": {
    "gn:admin1_code":"2.0",
    "gn:admin2_code":"203",
    "gn:admin3_code":"20305.0",
    "gn:asciiname":"Mellach",
    "gn:country_code":"AT",
    "gn:dem":676,
    "gn:feature_class":"P",
    "gn:feature_code":"PPL",
    "gn:name":"Mellach",
    "gn:population":34,
    "gn:timezone":"Europe/Vienna",
    "iso:country":"AT",
    "wof:name":"Mellach",
    "wof:placetype":"locality",
    "wof:population":34
},
  "geometry": {"coordinates":[13.41667,46.61667],"type":"Point"}
}