{
  "type": "Feature",
  "properties": {
    "gn:admin1_code":"4.0",
    "gn:admin2_code":"411",
    "gn:admin3_code":"41125.0",
    "gn:asciiname":"Gloxwald",
    "gn:country_code":"AT",
    "gn:dem":505,
    "gn:feature_class":"P",
    "gn:feature_code":"PPL",
    "gn:name":"Gloxwald",
    "gn:population":343,
    "gn:timezone":"Europe/Vienna",
    "iso:country":"AT",
    "wof:name":"Gloxwald",
    "wof:placetype":"locality",
    "wof:population":343
},
  "geometry": {"coordinates":[14.95643,48.23765],"type":"Point"}
}