{
  "type": "Feature",
  "properties": {
    "gn:admin1_code":"6.0",
    "gn:admin2_code":"620",
    "gn:admin3_code":"62044.0",
    "gn:asciiname":"Gfoellgraben",
    "gn:country_code":"AT",
    "gn:dem":1147,
    "gn:feature_class":"P",
    "gn:feature_code":"PPL",
    "gn:name":"Gf\u00f6llgraben",
    "gn:population":59,
    "gn:timezone":"Europe/Vienna",
    "iso:country":"AT",
    "wof:name":"Gfoellgraben",
    "wof:placetype":"locality",
    "wof:population":59
},
  "geometry": {"coordinates":[14.42778,47.23056],"type":"Point"}
}