{
  "type": "Feature",
  "properties": {
    "gn:admin1_code":"8.0",
    "gn:admin2_code":"802",
    "gn:admin3_code":"80207.0",
    "gn:asciiname":"Weissenreute",
    "gn:country_code":"AT",
    "gn:dem":494,
    "gn:feature_class":"P",
    "gn:feature_code":"PPL",
    "gn:name":"Wei\u00dfenreute",
    "gn:population":0,
    "gn:timezone":"Europe/Vienna",
    "iso:country":"AT",
    "wof:name":"Weissenreute",
    "wof:placetype":"locality"
},
  "geometry": {"coordinates":[9.75722,47.50111],"type":"Point"}
}