{
  "type": "Feature",
  "properties": {
    "gn:admin1_code":"06",
    "gn:admin2_code":"606.0",
    "gn:admin3_code":"60661.0",
    "gn:asciiname":"Stuhlsdorf",
    "gn:cc2":"AT",
    "gn:country_code":"AT",
    "gn:dem":408,
    "gn:feature_class":"P",
    "gn:feature_code":"PPL",
    "gn:name":"Stuhlsdorf",
    "gn:population":0,
    "gn:timezone":"Europe/Vienna",
    "iso:country":"AT",
    "name:und_x_variant":[
        "Stulsdorf",
        "Stuhlsdorf"
    ],
    "wof:name":"Stuhlsdorf",
    "wof:placetype":"locality"
},
  "geometry": {"coordinates":[15.61667,47.11667],"type":"Point"}
}