{
  "type": "Feature",
  "properties": {
    "gn:admin1_code":"4.0",
    "gn:admin2_code":"404",
    "gn:admin3_code":"40437.0",
    "gn:asciiname":"Kirchberg",
    "gn:country_code":"AT",
    "gn:dem":415,
    "gn:feature_class":"P",
    "gn:feature_code":"PPL",
    "gn:name":"Kirchberg",
    "gn:population":212,
    "gn:timezone":"Europe/Vienna",
    "iso:country":"AT",
    "wof:name":"Kirchberg",
    "wof:placetype":"locality",
    "wof:population":212
},
  "geometry": {"coordinates":[12.87606,48.00141],"type":"Point"}
}