{
  "type": "Feature",
  "properties": {
    "gn:admin1_code":"04",
    "gn:admin2_code":"413.0",
    "gn:admin3_code":"41313.0",
    "gn:asciiname":"Vorderschlag",
    "gn:country_code":"AT",
    "gn:dem":660,
    "gn:feature_class":"P",
    "gn:feature_code":"PPL",
    "gn:name":"Vorderschlag",
    "gn:population":10,
    "gn:timezone":"Europe/Vienna",
    "iso:country":"AT",
    "wof:name":"Vorderschlag",
    "wof:placetype":"locality",
    "wof:population":10
},
  "geometry": {"coordinates":[13.89633,48.64113],"type":"Point"}
}