{
  "type": "Feature",
  "properties": {
    "gn:admin1_code":"4.0",
    "gn:admin2_code":"403",
    "gn:admin3_code":"40301.0",
    "gn:asciiname":"Aschet",
    "gn:country_code":"AT",
    "gn:dem":313,
    "gn:feature_class":"P",
    "gn:feature_code":"PPL",
    "gn:name":"Aschet",
    "gn:population":0,
    "gn:timezone":"Europe/Vienna",
    "iso:country":"AT",
    "wof:name":"Aschet",
    "wof:placetype":"locality"
},
  "geometry": {"coordinates":[14.01667,48.15],"type":"Point"}
}