{
  "type": "Feature",
  "properties": {
    "gn:admin1_code":"6.0",
    "gn:admin2_code":"622",
    "gn:admin3_code":"62264.0",
    "gn:asciiname":"Leitersdorf bei Hartberg",
    "gn:cc2":"AT",
    "gn:country_code":"AT",
    "gn:dem":278,
    "gn:feature_class":"P",
    "gn:feature_code":"PPL",
    "gn:name":"Leitersdorf bei Hartberg",
    "gn:population":523,
    "gn:timezone":"Europe/Vienna",
    "iso:country":"AT",
    "name:und_x_variant":[
        "Leitersdorf",
        "Leitersdorf bei Hartberg"
    ],
    "wof:name":"Leitersdorf bei Hartberg",
    "wof:placetype":"locality",
    "wof:population":523
},
  "geometry": {"coordinates":[16.03333,47.15],"type":"Point"}
}