{
  "type": "Feature",
  "properties": {
    "gn:admin1_code":"06",
    "gn:admin2_code":"623.0",
    "gn:admin3_code":"62384.0",
    "gn:asciiname":"Koegerl",
    "gn:country_code":"AT",
    "gn:dem":337,
    "gn:feature_class":"P",
    "gn:feature_code":"PPL",
    "gn:name":"K\u00f6gerl",
    "gn:population":0,
    "gn:timezone":"Europe/Vienna",
    "iso:country":"AT",
    "wof:name":"Koegerl",
    "wof:placetype":"locality"
},
  "geometry": {"coordinates":[15.75,46.95],"type":"Point"}
}