{
  "type": "Feature",
  "properties": {
    "gn:admin1_code":"4.0",
    "gn:admin2_code":"414",
    "gn:admin3_code":"41430.0",
    "gn:asciiname":"Sienleiten",
    "gn:country_code":"AT",
    "gn:dem":443,
    "gn:feature_class":"P",
    "gn:feature_code":"PPL",
    "gn:name":"Sienleiten",
    "gn:population":8,
    "gn:timezone":"Europe/Vienna",
    "iso:country":"AT",
    "wof:name":"Sienleiten",
    "wof:placetype":"locality",
    "wof:population":8
},
  "geometry": {"coordinates":[13.56932,48.32156],"type":"Point"}
}