{
  "type": "Feature",
  "properties": {
    "gn:admin1_code":"4.0",
    "gn:admin2_code":"408",
    "gn:admin3_code":"40806.0",
    "gn:asciiname":"Buchleiten",
    "gn:country_code":"AT",
    "gn:dem":555,
    "gn:feature_class":"P",
    "gn:feature_code":"PPL",
    "gn:name":"Buchleiten",
    "gn:population":18,
    "gn:timezone":"Europe/Vienna",
    "iso:country":"AT",
    "wof:name":"Buchleiten",
    "wof:placetype":"locality",
    "wof:population":18
},
  "geometry": {"coordinates":[13.66476,48.14902],"type":"Point"}
}