{
  "type": "Feature",
  "properties": {
    "gn:admin1_code":"2.0",
    "gn:admin2_code":"203",
    "gn:admin3_code":"20307.0",
    "gn:asciiname":"Kreuzberg",
    "gn:country_code":"AT",
    "gn:dem":1364,
    "gn:feature_class":"P",
    "gn:feature_code":"PPL",
    "gn:name":"Kreuzberg",
    "gn:population":9,
    "gn:timezone":"Europe/Vienna",
    "iso:country":"AT",
    "wof:name":"Kreuzberg",
    "wof:placetype":"locality",
    "wof:population":9
},
  "geometry": {"coordinates":[12.96584,46.65223],"type":"Point"}
}