{
  "type": "Feature",
  "properties": {
    "gn:admin1_code":"03",
    "gn:admin2_code":"309.0",
    "gn:admin3_code":"30916.0",
    "gn:asciiname":"Schwarzenberg",
    "gn:country_code":"AT",
    "gn:dem":607,
    "gn:feature_class":"P",
    "gn:feature_code":"PPL",
    "gn:name":"Schwarzenberg",
    "gn:population":0,
    "gn:timezone":"Europe/Vienna",
    "iso:country":"AT",
    "name:als_x_preferred":[
        "Schwarzenberg"
    ],
    "name:ceb_x_preferred":[
        "Schwarzenberg"
    ],
    "name:ces_x_preferred":[
        "Schwarzenberg"
    ],
    "name:deu_x_preferred":[
        "Schwarzenberg"
    ],
    "name:epo_x_preferred":[
        "Schwarzenberg"
    ],
    "name:eus_x_preferred":[
        "Schwarzenberg"
    ],
    "name:fra_x_preferred":[
        "Schwarzenberg"
    ],
    "name:hun_x_preferred":[
        "Schwarzenberg"
    ],
    "name:ita_x_preferred":[
        "Schwarzenberg"
    ],
    "name:jpn_x_preferred":[
        "\u30b7\u30e5\u30f4\u30a1\u30eb\u30c4\u30a7\u30f3\u30d9\u30eb\u30af"
    ],
    "name:kor_x_preferred":[
        "\uc288\ubc14\ub974\uccb8\ubca0\ub974\ud06c"
    ],
    "name:mkd_x_preferred":[
        "\u0428\u0432\u0430\u0440\u0446\u0435\u043d\u0431\u0435\u0440\u0433"
    ],
    "name:nld_x_preferred":[
        "Schwarzenberg"
    ],
    "name:pol_x_preferred":[
        "Schwarzenberg"
    ],
    "name:por_x_preferred":[
        "Schwarzenberg"
    ],
    "name:rus_x_preferred":[
        "\u0428\u0432\u0430\u0440\u0446\u0435\u043d\u0431\u0435\u0440\u0433"
    ],
    "name:swe_x_preferred":[
        "Schwarzenberg"
    ],
    "name:ukr_x_preferred":[
        "\u0428\u0432\u0430\u0440\u0446\u0435\u043d\u0431\u0435\u0440\u0433"
    ],
    "name:vol_x_preferred":[
        "Schwarzenberg"
    ],
    "wof:name":"Schwarzenberg",
    "wof:placetype":"locality"
},
  "geometry": {"coordinates":[15.15,48.85],"type":"Point"}
}