{
  "type": "Feature",
  "properties": {
    "gn:admin1_code":"03",
    "gn:admin2_code":"309.0",
    "gn:admin3_code":"30916.0",
    "gn:asciiname":"Schwarzenberg",
    "gn:country_code":"AT",
    "gn:dem":607,
    "gn:feature_class":"P",
    "gn:feature_code":"PPL",
    "gn:name":"Schwarzenberg",
    "gn:population":0,
    "gn:timezone":"Europe/Vienna",
    "iso:country":"AT",
    "wof:name":"Schwarzenberg",
    "wof:placetype":"locality"
},
  "geometry": {"coordinates":[15.15,48.85],"type":"Point"}
}