{
  "type": "Feature",
  "properties": {
    "gn:admin1_code":"4.0",
    "gn:admin2_code":"412",
    "gn:admin3_code":"41216.0",
    "gn:asciiname":"Moosboeck",
    "gn:country_code":"AT",
    "gn:dem":441,
    "gn:feature_class":"P",
    "gn:feature_code":"PPL",
    "gn:name":"Moosb\u00f6ck",
    "gn:population":13,
    "gn:timezone":"Europe/Vienna",
    "iso:country":"AT",
    "wof:name":"Moosboeck",
    "wof:placetype":"locality",
    "wof:population":13
},
  "geometry": {"coordinates":[13.3919,48.28234000000001],"type":"Point"}
}