{
  "type": "Feature",
  "properties": {
    "gn:admin1_code":"3.0",
    "gn:admin2_code":"310",
    "gn:admin3_code":"31001.0",
    "gn:asciiname":"Am See",
    "gn:country_code":"AT",
    "gn:dem":194,
    "gn:feature_class":"P",
    "gn:feature_code":"PPLL",
    "gn:name":"Am See",
    "gn:population":0,
    "gn:timezone":"Europe/Vienna",
    "iso:country":"AT",
    "wof:name":"Am See",
    "wof:placetype":"locality"
},
  "geometry": {"coordinates":[16.10556,48.69972],"type":"Point"}
}