{
  "type": "Feature",
  "properties": {
    "gn:country":"AT",
    "gn:fcode":"PPL",
    "gn:population":0,
    "iso:country":"AT",
    "name:hrv_x_preferred":[
        "\u010cjeka"
    ],
    "name:hun_x_historical":[
        "Cs\u00e9ke"
    ],
    "name:hun_x_preferred":[
        "Csejke"
    ],
    "name:hun_x_variant":[
        "Cs\u00e9ke"
    ],
    "name:und_x_variant":[
        "Eisenberg"
    ],
    "qs_pg:aaroncc":"AT",
    "qs_pg:gn_country":"AT",
    "qs_pg:gn_fcode":"PPL",
    "qs_pg:gn_pop":0,
    "qs_pg:name":"Eisenberg an der Pinka",
    "qs_pg:name_adm0":"\u00d6sterreich",
    "qs_pg:name_adm1":"Burgenland",
    "qs_pg:photos_9k":1,
    "qs_pg:photos_9r":1,
    "qs_pg:photos_all":1,
    "qs_pg:photos_sr":0,
    "qs_pg:pop_sr":0,
    "qs_pg:qs_pg_placetype":"locality",
    "qs_pg:qs_pg_placetype_gp":"Town",
    "qs_pg:woe_adm0":23424750,
    "woe:adm0_id":23424750,
    "woe:name_adm0":"\u00d6sterreich",
    "woe:name_adm1":"Burgenland",
    "woe:placetype":"Town",
    "wof:name":"Eisenberg an der Pinka",
    "wof:placetype":"locality"
},
  "geometry": {"coordinates":[16.42602,47.18032],"type":"Point"}
}