{
  "type": "Feature",
  "properties": {
    "gn:admin1_code":"04",
    "gn:admin2_code":"407.0",
    "gn:admin3_code":"40703.0",
    "gn:asciiname":"Sulzbach",
    "gn:country_code":"AT",
    "gn:dem":473,
    "gn:feature_class":"P",
    "gn:feature_code":"PPL",
    "gn:name":"Sulzbach",
    "gn:population":671,
    "gn:timezone":"Europe/Vienna",
    "iso:country":"AT",
    "wof:name":"Sulzbach",
    "wof:placetype":"locality",
    "wof:population":671
},
  "geometry": {"coordinates":[13.61953,47.69561],"type":"Point"}
}