{
  "type": "Feature",
  "properties": {
    "gn:admin1_code":"05",
    "gn:admin2_code":"505.0",
    "gn:admin3_code":"50506.0",
    "gn:asciiname":"Stein",
    "gn:country_code":"AT",
    "gn:dem":1091,
    "gn:feature_class":"P",
    "gn:feature_code":"PPL",
    "gn:name":"Stein",
    "gn:population":0,
    "gn:timezone":"Europe/Vienna",
    "iso:country":"AT",
    "wof:name":"Stein",
    "wof:placetype":"locality"
},
  "geometry": {"coordinates":[13.83333,47.06667],"type":"Point"}
}