{
  "type": "Feature",
  "properties": {
    "gn:admin1_code":"03",
    "gn:admin2_code":"320.0",
    "gn:admin3_code":"32018.0",
    "gn:asciiname":"Unterstampfing",
    "gn:country_code":"AT",
    "gn:dem":285,
    "gn:feature_class":"P",
    "gn:feature_code":"PPL",
    "gn:name":"Unterstampfing",
    "gn:population":0,
    "gn:timezone":"Europe/Vienna",
    "iso:country":"AT",
    "wof:name":"Unterstampfing",
    "wof:placetype":"locality"
},
  "geometry": {"coordinates":[15.0853,48.07254],"type":"Point"}
}