{
  "type": "Feature",
  "properties": {
    "gn:admin1_code":"4.0",
    "gn:admin2_code":"408",
    "gn:admin3_code":"40823.0",
    "gn:asciiname":"Lamperstorf",
    "gn:country_code":"AT",
    "gn:dem":417,
    "gn:feature_class":"P",
    "gn:feature_code":"PPL",
    "gn:name":"Lamperstorf",
    "gn:population":15,
    "gn:timezone":"Europe/Vienna",
    "iso:country":"AT",
    "wof:name":"Lamperstorf",
    "wof:placetype":"locality",
    "wof:population":15
},
  "geometry": {"coordinates":[13.68025,48.21355],"type":"Point"}
}