{
  "type": "Feature",
  "properties": {
    "gn:admin1_code":"06",
    "gn:admin2_code":"620.0",
    "gn:admin3_code":"62008.0",
    "gn:asciiname":"Puchschachen",
    "gn:country_code":"AT",
    "gn:dem":906,
    "gn:feature_class":"P",
    "gn:feature_code":"PPL",
    "gn:name":"Puchschachen",
    "gn:population":163,
    "gn:timezone":"Europe/Vienna",
    "iso:country":"AT",
    "wof:name":"Puchschachen",
    "wof:placetype":"locality",
    "wof:population":163
},
  "geometry": {"coordinates":[14.71129,47.27705],"type":"Point"}
}