{
  "type": "Feature",
  "properties": {
    "gn:admin1_code":"2.0",
    "gn:admin2_code":"205",
    "gn:admin3_code":"20534.0",
    "gn:asciiname":"Foebing",
    "gn:country_code":"AT",
    "gn:dem":767,
    "gn:feature_class":"P",
    "gn:feature_code":"PPL",
    "gn:name":"F\u00f6bing",
    "gn:population":14,
    "gn:timezone":"Europe/Vienna",
    "iso:country":"AT",
    "wof:name":"Foebing",
    "wof:placetype":"locality",
    "wof:population":14
},
  "geometry": {"coordinates":[14.30306,46.83722],"type":"Point"}
}