{
  "type": "Feature",
  "properties": {
    "gn:admin1_code":"4.0",
    "gn:admin2_code":"412",
    "gn:admin3_code":"41204.0",
    "gn:asciiname":"Eichetsham",
    "gn:country_code":"AT",
    "gn:dem":498,
    "gn:feature_class":"P",
    "gn:feature_code":"PPL",
    "gn:name":"Eichetsham",
    "gn:population":29,
    "gn:timezone":"Europe/Vienna",
    "iso:country":"AT",
    "wof:name":"Eichetsham",
    "wof:placetype":"locality",
    "wof:population":29
},
  "geometry": {"coordinates":[13.54052,48.17356],"type":"Point"}
}