{
  "type": "Feature",
  "properties": {
    "gn:admin1_code":"2.0",
    "gn:admin2_code":"202",
    "gn:admin3_code":"20201.0",
    "gn:asciiname":"Drautschen",
    "gn:country_code":"AT",
    "gn:dem":521,
    "gn:feature_class":"P",
    "gn:feature_code":"PPL",
    "gn:name":"Drautschen",
    "gn:population":354,
    "gn:timezone":"Europe/Vienna",
    "iso:country":"AT",
    "wof:name":"Drautschen",
    "wof:placetype":"locality",
    "wof:population":354
},
  "geometry": {"coordinates":[13.91779,46.62091],"type":"Point"}
}