{
  "type": "Feature",
  "properties": {
    "gn:admin1_code":"02",
    "gn:admin2_code":"201.0",
    "gn:admin3_code":"20101.0",
    "gn:asciiname":"Poppichl",
    "gn:country_code":"AT",
    "gn:dem":450,
    "gn:feature_class":"P",
    "gn:feature_code":"PPL",
    "gn:name":"Poppichl",
    "gn:population":0,
    "gn:timezone":"Europe/Vienna",
    "iso:country":"AT",
    "wof:name":"Poppichl",
    "wof:placetype":"locality"
},
  "geometry": {"coordinates":[14.30222,46.66417],"type":"Point"}
}