{
  "type": "Feature",
  "properties": {
    "gn:admin1_code":"2.0",
    "gn:admin2_code":"205",
    "gn:admin3_code":"20518.0",
    "gn:asciiname":"Moedring-Sonnseite",
    "gn:country_code":"AT",
    "gn:dem":1344,
    "gn:feature_class":"P",
    "gn:feature_code":"PPL",
    "gn:name":"M\u00f6dring-Sonnseite",
    "gn:population":0,
    "gn:timezone":"Europe/Vienna",
    "iso:country":"AT",
    "name:und_x_variant":[
        "Sonnseite",
        "M\u00f6dring-Sonnseite"
    ],
    "wof:name":"Moedring-Sonnseite",
    "wof:placetype":"locality"
},
  "geometry": {"coordinates":[14.15,46.95],"type":"Point"}
}