{
  "type": "Feature",
  "properties": {
    "gn:admin1_code":"03",
    "gn:admin2_code":"313.0",
    "gn:admin3_code":"31311.0",
    "gn:asciiname":"Reisling",
    "gn:country_code":"AT",
    "gn:dem":588,
    "gn:feature_class":"P",
    "gn:feature_code":"PPL",
    "gn:name":"Reisling",
    "gn:population":59,
    "gn:timezone":"Europe/Vienna",
    "iso:country":"AT",
    "wof:name":"Reisling",
    "wof:placetype":"locality",
    "wof:population":59
},
  "geometry": {"coordinates":[15.41667,48.51667],"type":"Point"}
}