{
  "type": "Feature",
  "properties": {
    "gn:admin1_code":"04",
    "gn:admin2_code":"406.0",
    "gn:admin3_code":"40605.0",
    "gn:asciiname":"Thierberg",
    "gn:country_code":"AT",
    "gn:dem":697,
    "gn:feature_class":"P",
    "gn:feature_code":"PPL",
    "gn:name":"Thierberg",
    "gn:population":97,
    "gn:timezone":"Europe/Vienna",
    "iso:country":"AT",
    "name:deu_x_preferred":[
        "Thierberg"
    ],
    "name:fra_x_preferred":[
        "Thierberg"
    ],
    "name:nld_x_preferred":[
        "Thierberg"
    ],
    "wof:name":"Thierberg",
    "wof:placetype":"locality",
    "wof:population":97
},
  "geometry": {"coordinates":[14.38591,48.51666],"type":"Point"}
}