{
  "type": "Feature",
  "properties": {
    "gn:admin1_code":"6.0",
    "gn:admin2_code":"611",
    "gn:admin3_code":"61120.0",
    "gn:asciiname":"Goessgraben",
    "gn:country_code":"AT",
    "gn:dem":966,
    "gn:feature_class":"P",
    "gn:feature_code":"PPL",
    "gn:name":"G\u00f6ssgraben",
    "gn:population":0,
    "gn:timezone":"Europe/Vienna",
    "iso:country":"AT",
    "wof:name":"Goessgraben",
    "wof:placetype":"locality"
},
  "geometry": {"coordinates":[14.93333,47.46667],"type":"Point"}
}