{
  "type": "Feature",
  "properties": {
    "gn:admin1_code":"3.0",
    "gn:admin2_code":"320",
    "gn:admin3_code":"32014.0",
    "gn:asciiname":"Windpassing",
    "gn:country_code":"AT",
    "gn:dem":425,
    "gn:feature_class":"P",
    "gn:feature_code":"PPLL",
    "gn:name":"Windpassing",
    "gn:population":47,
    "gn:timezone":"Europe/Vienna",
    "iso:country":"AT",
    "wof:name":"Windpassing",
    "wof:placetype":"locality",
    "wof:population":47
},
  "geometry": {"coordinates":[15.0608,48.05043],"type":"Point"}
}