{
  "type": "Feature",
  "properties": {
    "gn:admin1_code":"4.0",
    "gn:admin2_code":"416",
    "gn:admin3_code":"41603.0",
    "gn:asciiname":"Elmegg",
    "gn:country_code":"AT",
    "gn:dem":722,
    "gn:feature_class":"P",
    "gn:feature_code":"PPL",
    "gn:name":"Elmegg",
    "gn:population":23,
    "gn:timezone":"Europe/Vienna",
    "iso:country":"AT",
    "wof:name":"Elmegg",
    "wof:placetype":"locality",
    "wof:population":23
},
  "geometry": {"coordinates":[14.30695,48.48948],"type":"Point"}
}