{
  "type": "Feature",
  "properties": {
    "iso:country":"AT",
    "name:ceb_x_preferred":[
        "Grins"
    ],
    "name:ces_x_preferred":[
        "Grins"
    ],
    "name:deu_x_preferred":[
        "Grins"
    ],
    "name:eng_x_preferred":[
        "Innerdorf"
    ],
    "name:eng_x_variant":[
        "Grins"
    ],
    "name:est_x_preferred":[
        "Grins"
    ],
    "name:fas_x_preferred":[
        "\u06af\u0631\u0627\u06cc\u0646\u0633"
    ],
    "name:fra_x_preferred":[
        "Grins"
    ],
    "name:hun_x_preferred":[
        "Grins"
    ],
    "name:ita_x_preferred":[
        "Grins"
    ],
    "name:jpn_x_preferred":[
        "\u30b0\u30ea\u30f3\u30b9"
    ],
    "name:kaz_x_preferred":[
        "\u0413\u0440\u0438\u043d\u0441"
    ],
    "name:lmo_x_preferred":[
        "Grins"
    ],
    "name:nld_x_preferred":[
        "Grins"
    ],
    "name:pol_x_preferred":[
        "Grins"
    ],
    "name:rus_x_preferred":[
        "\u0413\u0440\u0438\u043d\u0441"
    ],
    "name:slk_x_preferred":[
        "Grins"
    ],
    "name:spa_x_preferred":[
        "Grins"
    ],
    "name:swe_x_preferred":[
        "Grins"
    ],
    "name:ukr_x_preferred":[
        "\u0413\u0440\u0456\u043d\u0441"
    ],
    "name:uzb_x_preferred":[
        "Grins"
    ],
    "name:vol_x_preferred":[
        "Grins"
    ],
    "name:war_x_preferred":[
        "Grins"
    ],
    "name:zho_x_preferred":[
        "\u683c\u6797\u65af"
    ],
    "name:zho_x_variant":[
        "Grins"
    ],
    "qs:a0":"\u00d6sterreich",
    "qs:a1":"*Tirol",
    "qs:a1r":"0",
    "qs:a2":"Landeck",
    "qs:adm0":"\u00d6sterreich",
    "qs:la_lc":"*",
    "qs:level":"locality",
    "qs:loc":"Grins",
    "qs:loc_alt":"Grins",
    "qs:pop":0,
    "qs:type":"buffered point",
    "wd:wordcount":109,
    "wof:lang":[
        "ger"
    ],
    "wof:name":"Grins",
    "wof:placetype":"locality"
},
  "geometry": {"coordinates":[10.514008,47.150666],"type":"Point"}
}