{
  "type": "Feature",
  "properties": {
    "gn:admin1_code":"03",
    "gn:admin2_code":"309.0",
    "gn:admin3_code":"30910.0",
    "gn:asciiname":"Weikertschlag",
    "gn:country_code":"AT",
    "gn:dem":784,
    "gn:feature_class":"P",
    "gn:feature_code":"PPL",
    "gn:name":"Weikertschlag",
    "gn:population":65,
    "gn:timezone":"Europe/Vienna",
    "iso:country":"AT",
    "wof:name":"Weikertschlag",
    "wof:placetype":"locality",
    "wof:population":65
},
  "geometry": {"coordinates":[14.85,48.61667],"type":"Point"}
}