{
  "type": "Feature",
  "properties": {
    "gn:admin1_code":"04",
    "gn:admin2_code":"406.0",
    "gn:admin3_code":"40625.0",
    "gn:asciiname":"Windgfoell",
    "gn:country_code":"AT",
    "gn:dem":770,
    "gn:feature_class":"P",
    "gn:feature_code":"PPL",
    "gn:name":"Windgf\u00f6ll",
    "gn:population":73,
    "gn:timezone":"Europe/Vienna",
    "iso:country":"AT",
    "wof:name":"Windgfoell",
    "wof:placetype":"locality",
    "wof:population":73
},
  "geometry": {"coordinates":[14.70735,48.49778],"type":"Point"}
}