{
  "type": "Feature",
  "properties": {
    "gn:admin1_code":"4.0",
    "gn:admin2_code":"405",
    "gn:admin3_code":"40501.0",
    "gn:asciiname":"Langsiedlung",
    "gn:country_code":"AT",
    "gn:dem":294,
    "gn:feature_class":"P",
    "gn:feature_code":"PPL",
    "gn:name":"Langsiedlung",
    "gn:population":0,
    "gn:timezone":"Europe/Vienna",
    "iso:country":"AT",
    "wof:name":"Langsiedlung",
    "wof:placetype":"locality"
},
  "geometry": {"coordinates":[14.15111,48.28889],"type":"Point"}
}