{
  "type": "Feature",
  "properties": {
    "gn:admin1_code":"3.0",
    "gn:admin2_code":"320",
    "gn:admin3_code":"32008.0",
    "gn:asciiname":"Hoefl",
    "gn:country_code":"AT",
    "gn:dem":341,
    "gn:feature_class":"P",
    "gn:feature_code":"PPL",
    "gn:name":"H\u00f6fl",
    "gn:population":39,
    "gn:timezone":"Europe/Vienna",
    "iso:country":"AT",
    "wof:name":"Hoefl",
    "wof:placetype":"locality",
    "wof:population":39
},
  "geometry": {"coordinates":[15.10989,48.05898],"type":"Point"}
}