{
  "type": "Feature",
  "properties": {
    "gn:admin1_code":"4.0",
    "gn:admin2_code":"407",
    "gn:admin3_code":"40718.0",
    "gn:asciiname":"Muehlbachberg",
    "gn:country_code":"AT",
    "gn:dem":617,
    "gn:feature_class":"P",
    "gn:feature_code":"PPL",
    "gn:name":"M\u00fchlbachberg",
    "gn:population":0,
    "gn:timezone":"Europe/Vienna",
    "iso:country":"AT",
    "wof:name":"Muehlbachberg",
    "wof:placetype":"locality"
},
  "geometry": {"coordinates":[13.75,47.85],"type":"Point"}
}