{
  "type": "Feature",
  "properties": {
    "iso:country":"AT",
    "name:deu_x_preferred":[
        "Malta"
    ],
    "name:eng_x_preferred":[
        "Malta"
    ],
    "name:fra_x_preferred":[
        "Malta"
    ],
    "name:fur_x_preferred":[
        "Malta"
    ],
    "name:hun_x_preferred":[
        "Malta"
    ],
    "name:ita_x_preferred":[
        "Malta"
    ],
    "name:kaz_x_preferred":[
        "\u041c\u0430\u043b\u044c\u0442\u0430"
    ],
    "name:nld_x_preferred":[
        "Malta in K\u00e4rnten"
    ],
    "name:pol_x_preferred":[
        "Malta"
    ],
    "name:por_x_preferred":[
        "Malta"
    ],
    "name:rus_x_preferred":[
        "\u041c\u0430\u043b\u044c\u0442\u0430"
    ],
    "name:slk_x_preferred":[
        "Malta"
    ],
    "name:swe_x_preferred":[
        "Malta"
    ],
    "name:uzb_x_preferred":[
        "Malta"
    ],
    "name:vol_x_preferred":[
        "Malta"
    ],
    "name:war_x_preferred":[
        "Malta"
    ],
    "qs_pg:aaroncc":"AT",
    "qs_pg:name":"Malta",
    "qs_pg:name_adm0":"\u00d6sterreich",
    "qs_pg:name_adm1":"K\u00e4rnten",
    "qs_pg:photos":271,
    "qs_pg:photos_1k":55,
    "qs_pg:photos_9k":1,
    "qs_pg:photos_9r":4,
    "qs_pg:photos_all":271,
    "qs_pg:photos_sr":5,
    "qs_pg:pop_sr":0,
    "qs_pg:qs_pg_placetype":"locality",
    "qs_pg:qs_pg_placetype_gp":"Town",
    "qs_pg:woe_adm0":23424750,
    "woe:adm0_id":23424750,
    "woe:name_adm0":"\u00d6sterreich",
    "woe:name_adm1":"K\u00e4rnten",
    "woe:placetype":"Town",
    "wof:name":"Malta",
    "wof:placetype":"locality"
},
  "geometry": {"coordinates":[13.506402,46.96151],"type":"Point"}
}