{
  "type": "Feature",
  "properties": {
    "gn:admin1_code":"4.0",
    "gn:admin2_code":"416",
    "gn:admin3_code":"41627.0",
    "gn:asciiname":"Langzwettl",
    "gn:cc2":"AT",
    "gn:country_code":"AT",
    "gn:dem":725,
    "gn:feature_class":"P",
    "gn:feature_code":"PPL",
    "gn:name":"Langzwettl",
    "gn:population":220,
    "gn:timezone":"Europe/Vienna",
    "iso:country":"AT",
    "name:und_x_variant":[
        "Langenzwettl",
        "Langzwettl"
    ],
    "wof:name":"Langzwettl",
    "wof:placetype":"locality",
    "wof:population":220
},
  "geometry": {"coordinates":[14.27819,48.48322],"type":"Point"}
}