{
  "type": "Feature",
  "properties": {
    "gn:admin1_code":"8.0",
    "gn:admin2_code":"802",
    "gn:admin3_code":"80238.0",
    "gn:asciiname":"Glafberg",
    "gn:country_code":"AT",
    "gn:dem":811,
    "gn:feature_class":"P",
    "gn:feature_code":"PPL",
    "gn:name":"Glafberg",
    "gn:population":0,
    "gn:timezone":"Europe/Vienna",
    "iso:country":"AT",
    "wof:name":"Glafberg",
    "wof:placetype":"locality"
},
  "geometry": {"coordinates":[9.94861,47.5325],"type":"Point"}
}