{
  "type": "Feature",
  "properties": {
    "gn:admin1_code":"4.0",
    "gn:admin2_code":"408",
    "gn:admin3_code":"40826.0",
    "gn:asciiname":"Naichet",
    "gn:country_code":"AT",
    "gn:dem":415,
    "gn:feature_class":"P",
    "gn:feature_code":"PPL",
    "gn:name":"Naichet",
    "gn:population":15,
    "gn:timezone":"Europe/Vienna",
    "iso:country":"AT",
    "wof:name":"Naichet",
    "wof:placetype":"locality",
    "wof:population":15
},
  "geometry": {"coordinates":[13.8635,48.28291],"type":"Point"}
}