{
  "type": "Feature",
  "properties": {
    "gn:admin1_code":"02",
    "gn:admin2_code":"207.0",
    "gn:admin3_code":"20722.0",
    "gn:asciiname":"Sankt Peter",
    "gn:country_code":"AT",
    "gn:dem":482,
    "gn:feature_class":"P",
    "gn:feature_code":"PPL",
    "gn:name":"Sankt Peter",
    "gn:population":103,
    "gn:timezone":"Europe/Vienna",
    "iso:country":"AT",
    "wof:name":"Sankt Peter",
    "wof:placetype":"locality",
    "wof:population":103
},
  "geometry": {"coordinates":[14.04222,46.55358],"type":"Point"}
}