{
  "type": "Feature",
  "properties": {
    "gn:admin1_code":"02",
    "gn:admin2_code":"207.0",
    "gn:admin3_code":"20722.0",
    "gn:asciiname":"Sankt Peter",
    "gn:country_code":"AT",
    "gn:dem":482,
    "gn:feature_class":"P",
    "gn:feature_code":"PPL",
    "gn:name":"Sankt Peter",
    "gn:population":103,
    "gn:timezone":"Europe/Vienna",
    "iso:country":"AT",
    "name:ceb_x_preferred":[
        "Sankt Peter"
    ],
    "name:ces_x_preferred":[
        "Sankt Peter"
    ],
    "name:deu_x_preferred":[
        "Sankt Peter"
    ],
    "name:fra_x_preferred":[
        "Sankt Peter"
    ],
    "name:ita_x_preferred":[
        "Sankt Peter"
    ],
    "name:nld_x_preferred":[
        "Sankt Peter"
    ],
    "name:pol_x_preferred":[
        "Sankt Peter"
    ],
    "name:por_x_preferred":[
        "Sankt Peter"
    ],
    "name:rus_x_preferred":[
        "\u0421\u0430\u043d\u043a\u0442-\u041f\u0435\u0442\u0435\u0440"
    ],
    "name:sco_x_preferred":[
        "Sankt Peter"
    ],
    "name:swe_x_preferred":[
        "Sankt Peter"
    ],
    "wof:name":"Sankt Peter",
    "wof:placetype":"locality",
    "wof:population":103
},
  "geometry": {"coordinates":[14.04222,46.55358],"type":"Point"}
}