{
  "type": "Feature",
  "properties": {
    "gn:admin1_code":"4.0",
    "gn:admin2_code":"410",
    "gn:admin3_code":"41012.0",
    "gn:asciiname":"Friesenegg",
    "gn:country_code":"AT",
    "gn:dem":362,
    "gn:feature_class":"P",
    "gn:feature_code":"PPL",
    "gn:name":"Friesenegg",
    "gn:population":69,
    "gn:timezone":"Europe/Vienna",
    "iso:country":"AT",
    "wof:name":"Friesenegg",
    "wof:placetype":"locality",
    "wof:population":69
},
  "geometry": {"coordinates":[14.24558,48.30187],"type":"Point"}
}