{
  "type": "Feature",
  "properties": {
    "iso:country":"AT",
    "name:ceb_x_preferred":[
        "Rieden"
    ],
    "name:deu_x_preferred":[
        "Rieden"
    ],
    "name:eng_x_preferred":[
        "Rieden Ortsteil"
    ],
    "name:eng_x_variant":[
        "Rieden Ortsteil"
    ],
    "name:epo_x_preferred":[
        "Rieden"
    ],
    "name:fas_x_preferred":[
        "\u0631\u06cc\u062f\u0646"
    ],
    "name:fra_x_preferred":[
        "Rieden"
    ],
    "name:hbs_x_preferred":[
        "Rieden"
    ],
    "name:hye_x_preferred":[
        "\u054c\u056b\u0564\u0565\u0576"
    ],
    "name:ita_x_preferred":[
        "Rieden"
    ],
    "name:jpn_x_preferred":[
        "\u30ea\u30fc\u30c7\u30f3"
    ],
    "name:lmo_x_preferred":[
        "Rieden"
    ],
    "name:nld_x_preferred":[
        "Rieden"
    ],
    "name:pol_x_preferred":[
        "Rieden"
    ],
    "name:por_x_preferred":[
        "Rieden"
    ],
    "name:rus_x_preferred":[
        "\u0420\u0438\u0434\u0435\u043d"
    ],
    "name:spa_x_preferred":[
        "Rieden"
    ],
    "name:srp_x_preferred":[
        "\u0420\u0438\u0434\u0435\u043d"
    ],
    "name:swe_x_preferred":[
        "Rieden"
    ],
    "name:vol_x_preferred":[
        "Rieden"
    ],
    "name:zho_x_preferred":[
        "\u91cc\u767b"
    ],
    "qs:gn_adm0_cc":"AT",
    "qs:gn_fcode":"PPLX",
    "qs:gn_local":2772827,
    "qs:gn_nam_loc":"lauterach",
    "qs:gn_namadm1":"08",
    "qs:gn_name":"Rieden",
    "qs:local_max":118,
    "qs:local_sum":118,
    "qs:localhoods":1,
    "qs:name":"Rieden",
    "qs:name_adm0":"\u00d6sterreich",
    "qs:name_adm1":"Vorarlberg",
    "qs:name_adm2":"Bregenz",
    "qs:name_en":"Rieden Ortsteil",
    "qs:name_lau":"Lauterach",
    "qs:name_local":"Lauterach",
    "qs:photo_max":43,
    "qs:photo_sum":118,
    "qs:placetype":"Suburb",
    "qs:quad_count":31,
    "qs:woe_adm0":23424750,
    "qs:woe_adm1":2344715,
    "qs:woe_adm2":12591750,
    "qs:woe_lau":12675662,
    "qs:woe_local":12675662,
    "qs:woe_ver":"7.10.0",
    "wof:lang":[
        "ger"
    ],
    "wof:name":"Rieden",
    "wof:placetype":"neighbourhood"
},
  "geometry": {"coordinates":[9.748853,47.488865],"type":"Point"}
}