{
  "type": "Feature",
  "properties": {
    "gn:admin1_code":"2.0",
    "gn:admin2_code":"205",
    "gn:admin3_code":"20531.0",
    "gn:asciiname":"Koetschendorf",
    "gn:country_code":"AT",
    "gn:dem":1112,
    "gn:feature_class":"P",
    "gn:feature_code":"PPL",
    "gn:name":"K\u00f6tschendorf",
    "gn:population":69,
    "gn:timezone":"Europe/Vienna",
    "iso:country":"AT",
    "wof:name":"Koetschendorf",
    "wof:placetype":"locality",
    "wof:population":69
},
  "geometry": {"coordinates":[14.16667,46.81667],"type":"Point"}
}