{
  "type": "Feature",
  "properties": {
    "gn:admin1_code":"4.0",
    "gn:admin2_code":"409",
    "gn:admin3_code":"40908.0",
    "gn:asciiname":"Seebach",
    "gn:country_code":"AT",
    "gn:dem":582,
    "gn:feature_class":"P",
    "gn:feature_code":"PPL",
    "gn:name":"Seebach",
    "gn:population":0,
    "gn:timezone":"Europe/Vienna",
    "iso:country":"AT",
    "wof:name":"Seebach",
    "wof:placetype":"locality"
},
  "geometry": {"coordinates":[14.1405,47.9097],"type":"Point"}
}