{
  "type": "Feature",
  "properties": {
    "gn:admin1_code":"2.0",
    "gn:admin2_code":"208",
    "gn:admin3_code":"20806.0",
    "gn:asciiname":"Nageltschach",
    "gn:country_code":"AT",
    "gn:dem":426,
    "gn:feature_class":"P",
    "gn:feature_code":"PPL",
    "gn:name":"Nageltschach",
    "gn:population":0,
    "gn:timezone":"Europe/Vienna",
    "iso:country":"AT",
    "wof:name":"Nageltschach",
    "wof:placetype":"locality"
},
  "geometry": {"coordinates":[14.51028,46.57528],"type":"Point"}
}