{
  "type": "Feature",
  "properties": {
    "gn:admin1_code":"4.0",
    "gn:admin2_code":"409",
    "gn:admin3_code":"40920.0",
    "gn:asciiname":"Dorngraben",
    "gn:country_code":"AT",
    "gn:dem":422,
    "gn:feature_class":"P",
    "gn:feature_code":"PPL",
    "gn:name":"Dorngraben",
    "gn:population":0,
    "gn:timezone":"Europe/Vienna",
    "iso:country":"AT",
    "wof:name":"Dorngraben",
    "wof:placetype":"locality"
},
  "geometry": {"coordinates":[14.2533,47.92152],"type":"Point"}
}