{
  "type": "Feature",
  "properties": {
    "gn:admin1_code":"03",
    "gn:admin2_code":"318.0",
    "gn:admin3_code":"31821.0",
    "gn:asciiname":"Pettenbach",
    "gn:country_code":"AT",
    "gn:dem":497,
    "gn:feature_class":"P",
    "gn:feature_code":"PPL",
    "gn:name":"Pettenbach",
    "gn:population":172,
    "gn:timezone":"Europe/Vienna",
    "iso:country":"AT",
    "name:ceb_x_preferred":[
        "Pettenbach"
    ],
    "name:deu_x_preferred":[
        "Pettenbach"
    ],
    "name:fas_x_preferred":[
        "\u067e\u062a\u0646\u0628\u0627\u062e"
    ],
    "name:fra_x_preferred":[
        "Pettenbach"
    ],
    "name:hun_x_preferred":[
        "Pettenbach"
    ],
    "name:ita_x_preferred":[
        "Pettenbach"
    ],
    "name:kaz_x_preferred":[
        "\u041f\u0435\u0442\u0442\u0435\u043d\u0431\u0430\u0445"
    ],
    "name:nld_x_preferred":[
        "Pettenbach"
    ],
    "name:nno_x_preferred":[
        "Pettenbach"
    ],
    "name:pol_x_preferred":[
        "Pettenbach"
    ],
    "name:por_x_preferred":[
        "Pettenbach"
    ],
    "name:rus_x_preferred":[
        "\u041f\u0435\u0442\u0442\u0435\u043d\u0431\u0430\u0445"
    ],
    "name:slk_x_preferred":[
        "Pettenbach"
    ],
    "name:spa_x_preferred":[
        "Pettenbach"
    ],
    "name:swe_x_preferred":[
        "Pettenbach"
    ],
    "name:uzb_x_preferred":[
        "Pettenbach"
    ],
    "name:vie_x_preferred":[
        "Pettenbach"
    ],
    "name:vol_x_preferred":[
        "Pettenbach"
    ],
    "name:war_x_preferred":[
        "Pettenbach"
    ],
    "name:zho_x_preferred":[
        "\u4f69\u6ed5\u5df4\u8d6b"
    ],
    "wof:name":"Pettenbach",
    "wof:placetype":"locality",
    "wof:population":172
},
  "geometry": {"coordinates":[15.89275,47.67625],"type":"Point"}
}