{
  "type": "Feature",
  "properties": {
    "gn:admin1_code":"06",
    "gn:admin2_code":"606.0",
    "gn:admin3_code":"60613.0",
    "gn:asciiname":"Worth",
    "gn:country_code":"AT",
    "gn:dem":401,
    "gn:feature_class":"P",
    "gn:feature_code":"PPL",
    "gn:name":"W\u00f6rth",
    "gn:population":0,
    "gn:timezone":"Europe/Vienna",
    "iso:country":"AT",
    "wof:name":"Worth",
    "wof:placetype":"locality"
},
  "geometry": {"coordinates":[15.33333,47.16667],"type":"Point"}
}