{
  "type": "Feature",
  "properties": {
    "gn:admin1_code":"06",
    "gn:admin2_code":"606.0",
    "gn:admin3_code":"60613.0",
    "gn:asciiname":"Worth",
    "gn:country_code":"AT",
    "gn:dem":401,
    "gn:feature_class":"P",
    "gn:feature_code":"PPL",
    "gn:name":"W\u00f6rth",
    "gn:population":0,
    "gn:timezone":"Europe/Vienna",
    "iso:country":"AT",
    "name:ceb_x_preferred":[
        "Worth"
    ],
    "name:deu_x_preferred":[
        "Worth"
    ],
    "name:fin_x_preferred":[
        "Worth"
    ],
    "name:fra_x_preferred":[
        "Worth"
    ],
    "name:ita_x_preferred":[
        "Worth"
    ],
    "name:nds_x_preferred":[
        "Worth"
    ],
    "name:nld_x_preferred":[
        "Worth"
    ],
    "name:pol_x_preferred":[
        "Worth"
    ],
    "name:por_x_preferred":[
        "Worth"
    ],
    "name:rus_x_preferred":[
        "\u0423\u043e\u0440\u0442"
    ],
    "name:srp_x_preferred":[
        "\u0412\u043e\u0440\u0442"
    ],
    "name:swe_x_preferred":[
        "Worth"
    ],
    "name:ukr_x_preferred":[
        "\u0412\u043e\u0440\u0442"
    ],
    "name:vol_x_preferred":[
        "Worth"
    ],
    "wof:name":"Worth",
    "wof:placetype":"locality"
},
  "geometry": {"coordinates":[15.33333,47.16667],"type":"Point"}
}