{
  "type": "Feature",
  "properties": {
    "gn:admin1_code":"4.0",
    "gn:admin2_code":"407",
    "gn:admin3_code":"40713.0",
    "gn:asciiname":"Penesdorf",
    "gn:country_code":"AT",
    "gn:dem":443,
    "gn:feature_class":"P",
    "gn:feature_code":"PPL",
    "gn:name":"Penesdorf",
    "gn:population":27,
    "gn:timezone":"Europe/Vienna",
    "iso:country":"AT",
    "wof:name":"Penesdorf",
    "wof:placetype":"locality",
    "wof:population":27
},
  "geometry": {"coordinates":[13.77857,47.99957],"type":"Point"}
}