{
  "type": "Feature",
  "properties": {
    "gn:admin1_code":"4.0",
    "gn:admin2_code":"418",
    "gn:admin3_code":"41823.0",
    "gn:asciiname":"Schauersberg",
    "gn:country_code":"AT",
    "gn:dem":317,
    "gn:feature_class":"P",
    "gn:feature_code":"PPL",
    "gn:name":"Schauersberg",
    "gn:population":392,
    "gn:timezone":"Europe/Vienna",
    "iso:country":"AT",
    "wof:name":"Schauersberg",
    "wof:placetype":"locality",
    "wof:population":392
},
  "geometry": {"coordinates":[14.00293,48.13897],"type":"Point"}
}