{
  "type": "Feature",
  "properties": {
    "gn:admin1_code":"06",
    "gn:admin2_code":"611.0",
    "gn:admin3_code":"61120.0",
    "gn:asciiname":"Schardorf",
    "gn:cc2":"AT",
    "gn:country_code":"AT",
    "gn:dem":776,
    "gn:feature_class":"P",
    "gn:feature_code":"PPL",
    "gn:name":"Schardorf",
    "gn:population":248,
    "gn:timezone":"Europe/Vienna",
    "iso:country":"AT",
    "name:und_x_variant":[
        "Scharsdorf",
        "Schardorf"
    ],
    "wof:name":"Schardorf",
    "wof:placetype":"locality",
    "wof:population":248
},
  "geometry": {"coordinates":[14.95952,47.41807],"type":"Point"}
}