{
  "type": "Feature",
  "properties": {
    "gn:admin1_code":"04",
    "gn:admin2_code":"416.0",
    "gn:admin3_code":"41615.0",
    "gn:asciiname":"Oberwaldschlag",
    "gn:country_code":"AT",
    "gn:dem":771,
    "gn:feature_class":"P",
    "gn:feature_code":"PPL",
    "gn:name":"Oberwaldschlag",
    "gn:population":103,
    "gn:timezone":"Europe/Vienna",
    "iso:country":"AT",
    "wof:name":"Oberwaldschlag",
    "wof:placetype":"locality",
    "wof:population":103
},
  "geometry": {"coordinates":[14.21536,48.49704000000001],"type":"Point"}
}