{
  "type": "Feature",
  "properties": {
    "gn:admin1_code":"3.0",
    "gn:admin2_code":"315",
    "gn:admin3_code":"31539.0",
    "gn:asciiname":"Grimmegg",
    "gn:country_code":"AT",
    "gn:dem":276,
    "gn:feature_class":"P",
    "gn:feature_code":"PPL",
    "gn:name":"Grimmegg",
    "gn:population":76,
    "gn:timezone":"Europe/Vienna",
    "iso:country":"AT",
    "wof:name":"Grimmegg",
    "wof:placetype":"locality",
    "wof:population":76
},
  "geometry": {"coordinates":[15.31048,48.12537],"type":"Point"}
}