{
  "type": "Feature",
  "properties": {
    "gn:admin1_code":"03",
    "gn:admin2_code":"325.0",
    "gn:admin3_code":"32508.0",
    "gn:asciiname":"Wendelgraben",
    "gn:country_code":"AT",
    "gn:dem":652,
    "gn:feature_class":"P",
    "gn:feature_code":"PPL",
    "gn:name":"Wendelgraben",
    "gn:population":41,
    "gn:timezone":"Europe/Vienna",
    "iso:country":"AT",
    "wof:name":"Wendelgraben",
    "wof:placetype":"locality",
    "wof:population":41
},
  "geometry": {"coordinates":[14.99805,48.61975],"type":"Point"}
}