{
  "type": "Feature",
  "properties": {
    "gn:admin1_code":"06",
    "gn:admin2_code":"612.0",
    "gn:admin3_code":"61260.0",
    "gn:asciiname":"Tunzendorf",
    "gn:country_code":"AT",
    "gn:dem":1107,
    "gn:feature_class":"P",
    "gn:feature_code":"PPL",
    "gn:name":"Tunzendorf",
    "gn:population":0,
    "gn:timezone":"Europe/Vienna",
    "iso:country":"AT",
    "wof:name":"Tunzendorf",
    "wof:placetype":"locality"
},
  "geometry": {"coordinates":[13.91667,47.41667],"type":"Point"}
}