{
  "type": "Feature",
  "properties": {
    "gn:admin1_code":"4.0",
    "gn:admin2_code":"404",
    "gn:admin3_code":"40405.0",
    "gn:asciiname":"Harham",
    "gn:country_code":"AT",
    "gn:dem":416,
    "gn:feature_class":"P",
    "gn:feature_code":"PPL",
    "gn:name":"Harham",
    "gn:population":40,
    "gn:timezone":"Europe/Vienna",
    "iso:country":"AT",
    "wof:name":"Harham",
    "wof:placetype":"locality",
    "wof:population":40
},
  "geometry": {"coordinates":[13.13115,48.20814],"type":"Point"}
}