{
  "type": "Feature",
  "properties": {
    "gn:admin1_code":"07",
    "gn:admin2_code":"708.0",
    "gn:admin3_code":"70836.0",
    "gn:asciiname":"Weissenbach am Lech",
    "gn:cc2":"AT",
    "gn:country_code":"AT",
    "gn:dem":882,
    "gn:feature_class":"P",
    "gn:feature_code":"PPL",
    "gn:name":"Weissenbach am Lech",
    "gn:population":0,
    "gn:timezone":"Europe/Vienna",
    "iso:country":"AT",
    "name:und_x_variant":[
        "Weissenbach",
        "Weissenbach am Lech",
        "Wei\u00dfenbach am Lech"
    ],
    "wof:name":"Weissenbach am Lech",
    "wof:placetype":"locality"
},
  "geometry": {"coordinates":[10.64071,47.44162],"type":"Point"}
}