{
  "type": "Feature",
  "properties": {
    "gn:admin1_code":"4.0",
    "gn:admin2_code":"417",
    "gn:admin3_code":"41705.0",
    "gn:asciiname":"Hongar",
    "gn:country_code":"AT",
    "gn:dem":860,
    "gn:feature_class":"P",
    "gn:feature_code":"PPL",
    "gn:name":"Hongar",
    "gn:population":0,
    "gn:timezone":"Europe/Vienna",
    "iso:country":"AT",
    "wof:name":"Hongar",
    "wof:placetype":"locality"
},
  "geometry": {"coordinates":[13.68665,47.92255],"type":"Point"}
}