{
  "type": "Feature",
  "properties": {
    "gn:admin1_code":"5.0",
    "gn:admin2_code":"503",
    "gn:admin3_code":"50327.0",
    "gn:asciiname":"Potzelsberg",
    "gn:country_code":"AT",
    "gn:dem":594,
    "gn:feature_class":"P",
    "gn:feature_code":"PPL",
    "gn:name":"P\u00f6tzelsberg",
    "gn:population":0,
    "gn:timezone":"Europe/Vienna",
    "iso:country":"AT",
    "wof:name":"Potzelsberg",
    "wof:placetype":"locality"
},
  "geometry": {"coordinates":[13.06,47.93472],"type":"Point"}
}