{
  "type": "Feature",
  "properties": {
    "gn:admin1_code":"4.0",
    "gn:admin2_code":"408",
    "gn:admin3_code":"40807.0",
    "gn:asciiname":"Zeisserding",
    "gn:country_code":"AT",
    "gn:dem":554,
    "gn:feature_class":"P",
    "gn:feature_code":"PPL",
    "gn:name":"Zei\u00dferding",
    "gn:population":22,
    "gn:timezone":"Europe/Vienna",
    "iso:country":"AT",
    "wof:name":"Zeisserding",
    "wof:placetype":"locality",
    "wof:population":22
},
  "geometry": {"coordinates":[13.63451,48.17075],"type":"Point"}
}