{
  "type": "Feature",
  "properties": {
    "gn:admin1_code":"3.0",
    "gn:admin2_code":"313",
    "gn:admin3_code":"31355.0",
    "gn:asciiname":"Buchberger Waldhuetten",
    "gn:country_code":"AT",
    "gn:dem":396,
    "gn:feature_class":"P",
    "gn:feature_code":"PPL",
    "gn:name":"Buchberger Waldh\u00fctten",
    "gn:population":35,
    "gn:timezone":"Europe/Vienna",
    "iso:country":"AT",
    "wof:name":"Buchberger Waldhuetten",
    "wof:placetype":"locality",
    "wof:population":35
},
  "geometry": {"coordinates":[15.63333,48.55],"type":"Point"}
}