{
  "type": "Feature",
  "properties": {
    "gn:admin1_code":"5.0",
    "gn:admin2_code":"503",
    "gn:admin3_code":"50337.0",
    "gn:asciiname":"Irlach",
    "gn:country_code":"AT",
    "gn:dem":583,
    "gn:feature_class":"P",
    "gn:feature_code":"PPL",
    "gn:name":"Irlach",
    "gn:population":0,
    "gn:timezone":"Europe/Vienna",
    "iso:country":"AT",
    "wof:name":"Irlach",
    "wof:placetype":"locality"
},
  "geometry": {"coordinates":[13.229,47.85015],"type":"Point"}
}