{
  "type": "Feature",
  "properties": {
    "gn:admin1_code":"02",
    "gn:admin2_code":"205.0",
    "gn:admin3_code":"20504.0",
    "gn:asciiname":"Sankt Oswald",
    "gn:country_code":"AT",
    "gn:dem":893,
    "gn:feature_class":"P",
    "gn:feature_code":"PPL",
    "gn:name":"Sankt Oswald",
    "gn:population":91,
    "gn:timezone":"Europe/Vienna",
    "iso:country":"AT",
    "name:ceb_x_preferred":[
        "Sankt Oswald"
    ],
    "name:deu_x_preferred":[
        "Sankt Oswald"
    ],
    "name:ita_x_preferred":[
        "Sankt Oswald"
    ],
    "name:nld_x_preferred":[
        "Sankt Oswald"
    ],
    "name:pol_x_preferred":[
        "Sankt Oswald"
    ],
    "name:swe_x_preferred":[
        "Sankt Oswald"
    ],
    "wof:name":"Sankt Oswald",
    "wof:placetype":"locality",
    "wof:population":91
},
  "geometry": {"coordinates":[14.58333,46.81667],"type":"Point"}
}