{
  "type": "Feature",
  "properties": {
    "gn:admin1_code":"6.0",
    "gn:admin2_code":"617",
    "gn:admin3_code":"61729.0",
    "gn:asciiname":"Hohenkogl",
    "gn:country_code":"AT",
    "gn:dem":564,
    "gn:feature_class":"P",
    "gn:feature_code":"PPL",
    "gn:name":"Hohenkogl",
    "gn:population":298,
    "gn:timezone":"Europe/Vienna",
    "iso:country":"AT",
    "wof:name":"Hohenkogl",
    "wof:placetype":"locality",
    "wof:population":298
},
  "geometry": {"coordinates":[15.59793,47.18516],"type":"Point"}
}