{
  "type": "Feature",
  "properties": {
    "gn:admin1_code":"02",
    "gn:admin2_code":"204.0",
    "gn:admin3_code":"20418.0",
    "gn:asciiname":"Willersdorf",
    "gn:country_code":"AT",
    "gn:dem":486,
    "gn:feature_class":"P",
    "gn:feature_code":"PPL",
    "gn:name":"Willersdorf",
    "gn:population":29,
    "gn:timezone":"Europe/Vienna",
    "iso:country":"AT",
    "wof:name":"Willersdorf",
    "wof:placetype":"locality",
    "wof:population":29
},
  "geometry": {"coordinates":[14.38333,46.71667],"type":"Point"}
}