{
  "type": "Feature",
  "properties": {
    "gn:admin1_code":"7.0",
    "gn:admin2_code":"705",
    "gn:admin3_code":"70512.0",
    "gn:asciiname":"Achenrain",
    "gn:country_code":"AT",
    "gn:dem":517,
    "gn:feature_class":"P",
    "gn:feature_code":"PPL",
    "gn:name":"Achenrain",
    "gn:population":0,
    "gn:timezone":"Europe/Vienna",
    "iso:country":"AT",
    "wof:name":"Achenrain",
    "wof:placetype":"locality"
},
  "geometry": {"coordinates":[11.88068,47.44864000000001],"type":"Point"}
}