{
  "type": "Feature",
  "properties": {
    "gn:admin1_code":"4.0",
    "gn:admin2_code":"410",
    "gn:admin3_code":"41020.0",
    "gn:asciiname":"Kurzenkirchen",
    "gn:country_code":"AT",
    "gn:dem":303,
    "gn:feature_class":"P",
    "gn:feature_code":"PPL",
    "gn:name":"Kurzenkirchen",
    "gn:population":113,
    "gn:timezone":"Europe/Vienna",
    "iso:country":"AT",
    "wof:name":"Kurzenkirchen",
    "wof:placetype":"locality",
    "wof:population":113
},
  "geometry": {"coordinates":[14.29424,48.16603],"type":"Point"}
}