{
  "type": "Feature",
  "properties": {
    "gn:admin1_code":"4.0",
    "gn:admin2_code":"412",
    "gn:admin3_code":"41223.0",
    "gn:asciiname":"Ecklham",
    "gn:country_code":"AT",
    "gn:dem":521,
    "gn:feature_class":"P",
    "gn:feature_code":"PPL",
    "gn:name":"Ecklham",
    "gn:population":5,
    "gn:timezone":"Europe/Vienna",
    "iso:country":"AT",
    "wof:name":"Ecklham",
    "wof:placetype":"locality",
    "wof:population":5
},
  "geometry": {"coordinates":[13.4825,48.14556],"type":"Point"}
}