{
  "type": "Feature",
  "properties": {
    "gn:admin1_code":"04",
    "gn:admin2_code":"407.0",
    "gn:admin3_code":"40719.0",
    "gn:asciiname":"Wahl",
    "gn:country_code":"AT",
    "gn:dem":588,
    "gn:feature_class":"P",
    "gn:feature_code":"PPL",
    "gn:name":"Wahl",
    "gn:population":0,
    "gn:timezone":"Europe/Vienna",
    "iso:country":"AT",
    "wof:name":"Wahl",
    "wof:placetype":"locality"
},
  "geometry": {"coordinates":[13.93333,47.93333],"type":"Point"}
}