{
  "type": "Feature",
  "properties": {
    "gn:admin1_code":"4.0",
    "gn:admin2_code":"418",
    "gn:admin3_code":"41815.0",
    "gn:asciiname":"Arbing",
    "gn:country_code":"AT",
    "gn:dem":382,
    "gn:feature_class":"P",
    "gn:feature_code":"PPL",
    "gn:name":"Arbing",
    "gn:population":24,
    "gn:timezone":"Europe/Vienna",
    "iso:country":"AT",
    "name:ceb_x_preferred":[
        "Arbing"
    ],
    "name:deu_x_preferred":[
        "Arbing"
    ],
    "name:fas_x_preferred":[
        "\u0622\u0631\u0628\u06cc\u0646\u06af"
    ],
    "name:fra_x_preferred":[
        "Arbing"
    ],
    "name:hun_x_preferred":[
        "Arbing"
    ],
    "name:ita_x_preferred":[
        "Arbing"
    ],
    "name:kaz_x_preferred":[
        "\u0410\u0440\u0431\u0438\u043d\u0433"
    ],
    "name:nld_x_preferred":[
        "Arbing"
    ],
    "name:pol_x_preferred":[
        "Arbing"
    ],
    "name:por_x_preferred":[
        "Arbing"
    ],
    "name:rus_x_preferred":[
        "\u0410\u0440\u0431\u0438\u043d\u0433"
    ],
    "name:slk_x_preferred":[
        "Arbing"
    ],
    "name:spa_x_preferred":[
        "Arbing"
    ],
    "name:swe_x_preferred":[
        "Arbing"
    ],
    "name:uzb_x_preferred":[
        "Arbing"
    ],
    "name:vie_x_preferred":[
        "Arbing"
    ],
    "name:vol_x_preferred":[
        "Arbing"
    ],
    "name:war_x_preferred":[
        "Arbing"
    ],
    "name:zho_x_preferred":[
        "\u963f\u5c14\u5bbe"
    ],
    "wof:name":"Arbing",
    "wof:placetype":"locality",
    "wof:population":24
},
  "geometry": {"coordinates":[13.86148,48.1233],"type":"Point"}
}