{
  "type": "Feature",
  "properties": {
    "gn:admin1_code":"3.0",
    "gn:admin2_code":"319",
    "gn:admin3_code":"31934.0",
    "gn:asciiname":"Blindorf",
    "gn:country_code":"AT",
    "gn:dem":301,
    "gn:feature_class":"P",
    "gn:feature_code":"PPL",
    "gn:name":"Blindorf",
    "gn:population":28,
    "gn:timezone":"Europe/Vienna",
    "iso:country":"AT",
    "wof:name":"Blindorf",
    "wof:placetype":"locality",
    "wof:population":28
},
  "geometry": {"coordinates":[15.66942,48.16872],"type":"Point"}
}