{
  "type": "Feature",
  "properties": {
    "gn:admin1_code":"6.0",
    "gn:admin2_code":"621",
    "gn:admin3_code":"62138.0",
    "gn:asciiname":"Draiach",
    "gn:country_code":"AT",
    "gn:dem":805,
    "gn:feature_class":"P",
    "gn:feature_code":"PPL",
    "gn:name":"Draiach",
    "gn:population":0,
    "gn:timezone":"Europe/Vienna",
    "iso:country":"AT",
    "wof:name":"Draiach",
    "wof:placetype":"locality"
},
  "geometry": {"coordinates":[15.28333,47.55],"type":"Point"}
}