{
  "type": "Feature",
  "properties": {
    "gn:admin1_code":"6.0",
    "gn:admin2_code":"614",
    "gn:admin3_code":"61444.0",
    "gn:asciiname":"Innere Fessnach",
    "gn:country_code":"AT",
    "gn:dem":1047,
    "gn:feature_class":"P",
    "gn:feature_code":"PPL",
    "gn:name":"Innere Fessnach",
    "gn:population":0,
    "gn:timezone":"Europe/Vienna",
    "iso:country":"AT",
    "wof:name":"Innere Fessnach",
    "wof:placetype":"locality"
},
  "geometry": {"coordinates":[14.45,47.15],"type":"Point"}
}