{
  "type": "Feature",
  "properties": {
    "gn:admin1_code":"6.0",
    "gn:admin2_code":"610",
    "gn:admin3_code":"61050.0",
    "gn:asciiname":"Sulz",
    "gn:country_code":"AT",
    "gn:dem":387,
    "gn:feature_class":"P",
    "gn:feature_code":"PPL",
    "gn:name":"Sulz",
    "gn:population":0,
    "gn:timezone":"Europe/Vienna",
    "iso:country":"AT",
    "name:als_x_preferred":[
        "Sulz"
    ],
    "name:ceb_x_preferred":[
        "Sulz"
    ],
    "name:deu_x_preferred":[
        "Sulz"
    ],
    "name:epo_x_preferred":[
        "Sulz"
    ],
    "name:fra_x_preferred":[
        "Sulz"
    ],
    "name:ita_x_preferred":[
        "Sulz"
    ],
    "name:nld_x_preferred":[
        "Sulz"
    ],
    "name:pol_x_preferred":[
        "Sulz"
    ],
    "name:por_x_preferred":[
        "Sulz"
    ],
    "name:rus_x_preferred":[
        "\u0417\u0443\u043b\u044c\u0446"
    ],
    "name:swe_x_preferred":[
        "Sulz"
    ],
    "name:ukr_x_preferred":[
        "\u0417\u0443\u043b\u044c\u0446"
    ],
    "name:vol_x_preferred":[
        "Sulz"
    ],
    "wof:name":"Sulz",
    "wof:placetype":"locality"
},
  "geometry": {"coordinates":[15.55814,46.67594],"type":"Point"}
}