{
  "type": "Feature",
  "properties": {
    "gn:admin1_code":"4.0",
    "gn:admin2_code":"417",
    "gn:admin3_code":"41705.0",
    "gn:asciiname":"Lixlberg",
    "gn:country_code":"AT",
    "gn:dem":599,
    "gn:feature_class":"P",
    "gn:feature_code":"PPL",
    "gn:name":"Lixlberg",
    "gn:population":0,
    "gn:timezone":"Europe/Vienna",
    "iso:country":"AT",
    "wof:name":"Lixlberg",
    "wof:placetype":"locality"
},
  "geometry": {"coordinates":[13.67755,47.93296],"type":"Point"}
}