{
  "type": "Feature",
  "properties": {
    "gn:admin1_code":"03",
    "gn:admin2_code":"319.0",
    "gn:admin3_code":"31934.0",
    "gn:asciiname":"Wald",
    "gn:country_code":"AT",
    "gn:dem":335,
    "gn:feature_class":"P",
    "gn:feature_code":"PPL",
    "gn:name":"Wald",
    "gn:population":219,
    "gn:timezone":"Europe/Vienna",
    "iso:country":"AT",
    "wof:name":"Wald",
    "wof:placetype":"locality",
    "wof:population":219
},
  "geometry": {"coordinates":[15.69637,48.12439000000001],"type":"Point"}
}