{
  "type": "Feature",
  "properties": {
    "gn:admin1_code":"6.0",
    "gn:admin2_code":"606",
    "gn:admin3_code":"60665.0",
    "gn:asciiname":"Hoellberg",
    "gn:country_code":"AT",
    "gn:dem":387,
    "gn:feature_class":"P",
    "gn:feature_code":"PPL",
    "gn:name":"H\u00f6llberg",
    "gn:population":231,
    "gn:timezone":"Europe/Vienna",
    "iso:country":"AT",
    "wof:name":"Hoellberg",
    "wof:placetype":"locality",
    "wof:population":231
},
  "geometry": {"coordinates":[15.28333,47.01667],"type":"Point"}
}