{
  "type": "Feature",
  "properties": {
    "gn:admin1_code":"04",
    "gn:admin2_code":"405.0",
    "gn:admin3_code":"40507.0",
    "gn:asciiname":"Polsenz",
    "gn:country_code":"AT",
    "gn:dem":270,
    "gn:feature_class":"P",
    "gn:feature_code":"PPL",
    "gn:name":"Polsenz",
    "gn:population":61,
    "gn:timezone":"Europe/Vienna",
    "iso:country":"AT",
    "wof:name":"Polsenz",
    "wof:placetype":"locality",
    "wof:population":61
},
  "geometry": {"coordinates":[14.00778,48.30018],"type":"Point"}
}