{
  "type": "Feature",
  "properties": {
    "gn:admin1_code":"04",
    "gn:admin2_code":"409.0",
    "gn:admin3_code":"40902.0",
    "gn:asciiname":"Wagenhub",
    "gn:country_code":"AT",
    "gn:dem":494,
    "gn:feature_class":"P",
    "gn:feature_code":"PPL",
    "gn:name":"Wagenhub",
    "gn:population":493,
    "gn:timezone":"Europe/Vienna",
    "iso:country":"AT",
    "wof:name":"Wagenhub",
    "wof:placetype":"locality",
    "wof:population":493
},
  "geometry": {"coordinates":[14.22987,47.96119],"type":"Point"}
}