{
  "type": "Feature",
  "properties": {
    "gn:admin1_code":"2.0",
    "gn:admin2_code":"203",
    "gn:admin3_code":"20321.0",
    "gn:asciiname":"Guggenberg",
    "gn:country_code":"AT",
    "gn:dem":1626,
    "gn:feature_class":"P",
    "gn:feature_code":"PPL",
    "gn:name":"Guggenberg",
    "gn:population":21,
    "gn:timezone":"Europe/Vienna",
    "iso:country":"AT",
    "wof:name":"Guggenberg",
    "wof:placetype":"locality",
    "wof:population":21
},
  "geometry": {"coordinates":[12.71667,46.71667],"type":"Point"}
}