{
  "type": "Feature",
  "properties": {
    "gn:admin1_code":"2.0",
    "gn:admin2_code":"208",
    "gn:admin3_code":"20804.0",
    "gn:asciiname":"Stoper",
    "gn:country_code":"AT",
    "gn:dem":893,
    "gn:feature_class":"P",
    "gn:feature_code":"PPL",
    "gn:name":"Stoper",
    "gn:population":0,
    "gn:timezone":"Europe/Vienna",
    "iso:country":"AT",
    "wof:name":"Stoper",
    "wof:placetype":"locality"
},
  "geometry": {"coordinates":[14.6325,46.4925],"type":"Point"}
}