{
  "type": "Feature",
  "properties": {
    "gn:admin1_code":"04",
    "gn:admin2_code":"409.0",
    "gn:admin3_code":"40915.0",
    "gn:asciiname":"Veichltal",
    "gn:country_code":"AT",
    "gn:dem":646,
    "gn:feature_class":"P",
    "gn:feature_code":"PPL",
    "gn:name":"Veichltal",
    "gn:population":0,
    "gn:timezone":"Europe/Vienna",
    "iso:country":"AT",
    "wof:name":"Veichltal",
    "wof:placetype":"locality"
},
  "geometry": {"coordinates":[14.32776,47.74105],"type":"Point"}
}