{
  "type": "Feature",
  "properties": {
    "gn:admin1_code":"6.0",
    "gn:admin2_code":"617",
    "gn:admin3_code":"61708.0",
    "gn:asciiname":"Oberdissau",
    "gn:country_code":"AT",
    "gn:dem":876,
    "gn:feature_class":"P",
    "gn:feature_code":"PPL",
    "gn:name":"Oberdissau",
    "gn:population":0,
    "gn:timezone":"Europe/Vienna",
    "iso:country":"AT",
    "wof:name":"Oberdissau",
    "wof:placetype":"locality"
},
  "geometry": {"coordinates":[15.65,47.45],"type":"Point"}
}