{
  "type": "Feature",
  "properties": {
    "gn:admin1_code":"4.0",
    "gn:admin2_code":"417",
    "gn:admin3_code":"41737.0",
    "gn:asciiname":"Woerzing",
    "gn:country_code":"AT",
    "gn:dem":509,
    "gn:feature_class":"P",
    "gn:feature_code":"PPL",
    "gn:name":"W\u00f6rzing",
    "gn:population":40,
    "gn:timezone":"Europe/Vienna",
    "iso:country":"AT",
    "wof:name":"Woerzing",
    "wof:placetype":"locality",
    "wof:population":40
},
  "geometry": {"coordinates":[13.62682,47.93866],"type":"Point"}
}