{
  "type": "Feature",
  "properties": {
    "gn:admin1_code":"03",
    "gn:admin2_code":"314.0",
    "gn:admin3_code":"31414.0",
    "gn:asciiname":"Schildbachhofe",
    "gn:country_code":"AT",
    "gn:dem":540,
    "gn:feature_class":"P",
    "gn:feature_code":"PPL",
    "gn:name":"Schildbachh\u00f6fe",
    "gn:population":0,
    "gn:timezone":"Europe/Vienna",
    "iso:country":"AT",
    "wof:name":"Schildbachhofe",
    "wof:placetype":"locality"
},
  "geometry": {"coordinates":[15.48333,47.91667],"type":"Point"}
}