{
  "type": "Feature",
  "properties": {
    "gn:admin1_code":"2.0",
    "gn:admin2_code":"204",
    "gn:admin3_code":"20416.0",
    "gn:asciiname":"Lukowitz",
    "gn:country_code":"AT",
    "gn:dem":654,
    "gn:feature_class":"P",
    "gn:feature_code":"PPL",
    "gn:name":"Lukowitz",
    "gn:population":120,
    "gn:timezone":"Europe/Vienna",
    "iso:country":"AT",
    "name:deu_x_preferred":[
        "Lukowitz"
    ],
    "name:slv_x_preferred":[
        "Kovi\u010de"
    ],
    "wof:name":"Lukowitz",
    "wof:placetype":"locality",
    "wof:population":120
},
  "geometry": {"coordinates":[14.09979,46.55389],"type":"Point"}
}