{
  "type": "Feature",
  "properties": {
    "gn:admin1_code":"2.0",
    "gn:admin2_code":"210",
    "gn:admin3_code":"21010.0",
    "gn:asciiname":"Jeinitz",
    "gn:country_code":"AT",
    "gn:dem":864,
    "gn:feature_class":"P",
    "gn:feature_code":"PPL",
    "gn:name":"Jeinitz",
    "gn:population":29,
    "gn:timezone":"Europe/Vienna",
    "iso:country":"AT",
    "wof:name":"Jeinitz",
    "wof:placetype":"locality",
    "wof:population":29
},
  "geometry": {"coordinates":[14.11992,46.77497],"type":"Point"}
}