{
  "type": "Feature",
  "properties": {
    "gn:admin1_code":"4.0",
    "gn:admin2_code":"403",
    "gn:admin3_code":"40301.0",
    "gn:asciiname":"Oberhart",
    "gn:country_code":"AT",
    "gn:dem":314,
    "gn:feature_class":"P",
    "gn:feature_code":"PPL",
    "gn:name":"Oberhart",
    "gn:population":1059,
    "gn:timezone":"Europe/Vienna",
    "iso:country":"AT",
    "wof:name":"Oberhart",
    "wof:placetype":"locality",
    "wof:population":1059
},
  "geometry": {"coordinates":[14.05,48.18333],"type":"Point"}
}