{
  "type": "Feature",
  "properties": {
    "gn:admin1_code":"4.0",
    "gn:admin2_code":"408",
    "gn:admin3_code":"40804.0",
    "gn:asciiname":"Gferedt",
    "gn:country_code":"AT",
    "gn:dem":419,
    "gn:feature_class":"P",
    "gn:feature_code":"PPL",
    "gn:name":"Gferedt",
    "gn:population":3,
    "gn:timezone":"Europe/Vienna",
    "iso:country":"AT",
    "wof:name":"Gferedt",
    "wof:placetype":"locality",
    "wof:population":3
},
  "geometry": {"coordinates":[13.80951,48.38174],"type":"Point"}
}