{
  "type": "Feature",
  "properties": {
    "gn:admin1_code":"6.0",
    "gn:admin2_code":"623",
    "gn:admin3_code":"62379.0",
    "gn:asciiname":"Kleinwalkersdorf",
    "gn:country_code":"AT",
    "gn:dem":325,
    "gn:feature_class":"P",
    "gn:feature_code":"PPL",
    "gn:name":"Kleinwalkersdorf",
    "gn:population":0,
    "gn:timezone":"Europe/Vienna",
    "iso:country":"AT",
    "wof:name":"Kleinwalkersdorf",
    "wof:placetype":"locality"
},
  "geometry": {"coordinates":[15.86667,46.98333],"type":"Point"}
}