{
  "type": "Feature",
  "properties": {
    "iso:country":"AT",
    "name:deu_x_preferred":[
        "Grabenbauernsiedlung"
    ],
    "name:eng_x_preferred":[
        "Grabenbauernsiedlung"
    ],
    "wof:name":"Grabenbauernsiedlung",
    "wof:placetype":"neighbourhood"
},
  "geometry": {"coordinates":[13.0389325128719,47.827920153363],"type":"Point"}
}