{
  "type": "Feature",
  "properties": {
    "gn:admin1_code":"4.0",
    "gn:admin2_code":"406",
    "gn:admin3_code":"40617.0",
    "gn:asciiname":"Langfirling",
    "gn:country_code":"AT",
    "gn:dem":839,
    "gn:feature_class":"P",
    "gn:feature_code":"PPL",
    "gn:name":"Langfirling",
    "gn:population":95,
    "gn:timezone":"Europe/Vienna",
    "iso:country":"AT",
    "wof:name":"Langfirling",
    "wof:placetype":"locality",
    "wof:population":95
},
  "geometry": {"coordinates":[14.70211,48.45795],"type":"Point"}
}