{
  "type": "Feature",
  "properties": {
    "iso:country":"AT",
    "name:deu_x_preferred":[
        "Glanhofen"
    ],
    "name:eng_x_preferred":[
        "Glanhofen"
    ],
    "wof:name":"Glanhofen",
    "wof:placetype":"neighbourhood"
},
  "geometry": {"coordinates":[13.00481479703609,47.79914856293976],"type":"Point"}
}