{
  "type": "Feature",
  "properties": {
    "gn:admin1_code":"2.0",
    "gn:admin2_code":"210",
    "gn:admin3_code":"21005.0",
    "gn:asciiname":"Grilzgraben",
    "gn:cc2":"AT",
    "gn:country_code":"AT",
    "gn:dem":1065,
    "gn:feature_class":"P",
    "gn:feature_code":"PPL",
    "gn:name":"Grilzgraben",
    "gn:population":15,
    "gn:timezone":"Europe/Vienna",
    "iso:country":"AT",
    "name:und_x_variant":[
        "Grilzberg",
        "Grilzgraben"
    ],
    "wof:name":"Grilzgraben",
    "wof:placetype":"locality",
    "wof:population":15
},
  "geometry": {"coordinates":[13.99139,46.73028],"type":"Point"}
}