{
  "type": "Feature",
  "properties": {
    "gn:admin1_code":"02",
    "gn:admin2_code":"209.0",
    "gn:admin3_code":"20909.0",
    "gn:asciiname":"Unterpudlach",
    "gn:country_code":"AT",
    "gn:dem":417,
    "gn:feature_class":"P",
    "gn:feature_code":"PPL",
    "gn:name":"Unterpudlach",
    "gn:population":0,
    "gn:timezone":"Europe/Vienna",
    "iso:country":"AT",
    "wof:name":"Unterpudlach",
    "wof:placetype":"locality"
},
  "geometry": {"coordinates":[14.93333,46.65],"type":"Point"}
}