{
  "type": "Feature",
  "properties": {
    "gn:admin1_code":"3.0",
    "gn:admin2_code":"321",
    "gn:admin3_code":"32142.0",
    "gn:asciiname":"Kirchbach",
    "gn:country_code":"AT",
    "gn:dem":369,
    "gn:feature_class":"P",
    "gn:feature_code":"PPL",
    "gn:name":"Kirchbach",
    "gn:population":521,
    "gn:timezone":"Europe/Vienna",
    "iso:country":"AT",
    "name:ceb_x_preferred":[
        "Kirchbach"
    ],
    "name:deu_x_preferred":[
        "Kirchbach"
    ],
    "name:fra_x_preferred":[
        "Kirchbach"
    ],
    "name:ita_x_preferred":[
        "Kirchbach"
    ],
    "name:pol_x_preferred":[
        "Kirchbach"
    ],
    "name:rus_x_preferred":[
        "\u041a\u0438\u0440\u0445\u0431\u0430\u0445"
    ],
    "name:swe_x_preferred":[
        "Kirchbach"
    ],
    "wof:name":"Kirchbach",
    "wof:placetype":"locality",
    "wof:population":521
},
  "geometry": {"coordinates":[16.19755,48.28583],"type":"Point"}
}