{
  "type": "Feature",
  "properties": {
    "gn:admin1_code":"2.0",
    "gn:admin2_code":"206",
    "gn:admin3_code":"20604.0",
    "gn:asciiname":"Drassnitz",
    "gn:country_code":"AT",
    "gn:dem":1202,
    "gn:feature_class":"P",
    "gn:feature_code":"PPL",
    "gn:name":"Drassnitz",
    "gn:population":0,
    "gn:timezone":"Europe/Vienna",
    "iso:country":"AT",
    "wof:name":"Drassnitz",
    "wof:placetype":"locality"
},
  "geometry": {"coordinates":[13.08806,46.765],"type":"Point"}
}