{
  "type": "Feature",
  "properties": {
    "gn:admin1_code":"05",
    "gn:admin2_code":"503.0",
    "gn:admin3_code":"50337.0",
    "gn:asciiname":"Obervetterbach",
    "gn:country_code":"AT",
    "gn:dem":561,
    "gn:feature_class":"P",
    "gn:feature_code":"PPL",
    "gn:name":"Obervetterbach",
    "gn:population":0,
    "gn:timezone":"Europe/Vienna",
    "iso:country":"AT",
    "wof:name":"Obervetterbach",
    "wof:placetype":"locality"
},
  "geometry": {"coordinates":[13.28333,47.83333],"type":"Point"}
}