{
  "type": "Feature",
  "properties": {
    "gn:admin1_code":"05",
    "gn:admin2_code":"506.0",
    "gn:admin3_code":"50613.0",
    "gn:asciiname":"Rettenbach",
    "gn:country_code":"AT",
    "gn:dem":800,
    "gn:feature_class":"P",
    "gn:feature_code":"PPL",
    "gn:name":"Rettenbach",
    "gn:population":310,
    "gn:timezone":"Europe/Vienna",
    "iso:country":"AT",
    "wof:name":"Rettenbach",
    "wof:placetype":"locality",
    "wof:population":310
},
  "geometry": {"coordinates":[12.43333,47.28333],"type":"Point"}
}