{
  "type": "Feature",
  "properties": {
    "gn:admin1_code":"03",
    "gn:admin2_code":"319.0",
    "gn:admin3_code":"31949.0",
    "gn:asciiname":"Hochbuch",
    "gn:country_code":"AT",
    "gn:dem":326,
    "gn:feature_class":"P",
    "gn:feature_code":"PPL",
    "gn:name":"Hochbuch",
    "gn:population":0,
    "gn:timezone":"Europe/Vienna",
    "iso:country":"AT",
    "wof:name":"Hochbuch",
    "wof:placetype":"locality"
},
  "geometry": {"coordinates":[16.1493,48.22239],"type":"Point"}
}