{
  "type": "Feature",
  "properties": {
    "gn:admin1_code":"4.0",
    "gn:admin2_code":"414",
    "gn:admin3_code":"41426.0",
    "gn:asciiname":"Maad",
    "gn:country_code":"AT",
    "gn:dem":374,
    "gn:feature_class":"P",
    "gn:feature_code":"PPL",
    "gn:name":"Maad",
    "gn:population":56,
    "gn:timezone":"Europe/Vienna",
    "iso:country":"AT",
    "wof:name":"Maad",
    "wof:placetype":"locality",
    "wof:population":56
},
  "geometry": {"coordinates":[13.51172,48.38539],"type":"Point"}
}