{
  "type": "Feature",
  "properties": {
    "gn:admin1_code":"04",
    "gn:admin2_code":"405.0",
    "gn:admin3_code":"40510.0",
    "gn:asciiname":"Pernau",
    "gn:country_code":"AT",
    "gn:dem":369,
    "gn:feature_class":"P",
    "gn:feature_code":"PPL",
    "gn:name":"Pernau",
    "gn:population":20,
    "gn:timezone":"Europe/Vienna",
    "iso:country":"AT",
    "wof:name":"Pernau",
    "wof:placetype":"locality",
    "wof:population":20
},
  "geometry": {"coordinates":[13.92431,48.28074],"type":"Point"}
}