{
  "type": "Feature",
  "properties": {
    "gn:admin1_code":"7.0",
    "gn:admin2_code":"703",
    "gn:admin3_code":"70356.0",
    "gn:asciiname":"Kapfers",
    "gn:country_code":"AT",
    "gn:dem":924,
    "gn:feature_class":"P",
    "gn:feature_code":"PPL",
    "gn:name":"Kapfers",
    "gn:population":150,
    "gn:timezone":"Europe/Vienna",
    "iso:country":"AT",
    "wof:name":"Kapfers",
    "wof:placetype":"locality",
    "wof:population":150
},
  "geometry": {"coordinates":[11.36667,47.16667],"type":"Point"}
}