{
  "type": "Feature",
  "properties": {
    "gn:admin1_code":"01",
    "gn:admin2_code":"109.0",
    "gn:admin3_code":"10926.0",
    "gn:asciiname":"Podler",
    "gn:country_code":"AT",
    "gn:dem":332,
    "gn:feature_class":"P",
    "gn:feature_code":"PPL",
    "gn:name":"Podler",
    "gn:population":72,
    "gn:timezone":"Europe/Vienna",
    "iso:country":"AT",
    "name:deu_x_preferred":[
        "Podler"
    ],
    "name:hrv_x_preferred":[
        "Poljanci"
    ],
    "wof:name":"Podler",
    "wof:placetype":"locality",
    "wof:population":72
},
  "geometry": {"coordinates":[16.33333,47.28333],"type":"Point"}
}