{
  "type": "Feature",
  "properties": {
    "gn:admin1_code":"03",
    "gn:admin2_code":"319.0",
    "gn:admin3_code":"31910.0",
    "gn:asciiname":"Wimpassing an der Pielach",
    "gn:cc2":"AT",
    "gn:country_code":"AT",
    "gn:dem":418,
    "gn:feature_class":"P",
    "gn:feature_code":"PPL",
    "gn:name":"Wimpassing an der Pielach",
    "gn:population":455,
    "gn:timezone":"Europe/Vienna",
    "iso:country":"AT",
    "name:und_x_variant":[
        "Wimpassing",
        "Wimpassing an der Pielach"
    ],
    "wof:name":"Wimpassing an der Pielach",
    "wof:placetype":"locality",
    "wof:population":455
},
  "geometry": {"coordinates":[15.48333,48.23333],"type":"Point"}
}