{
  "type": "Feature",
  "properties": {
    "gn:admin1_code":"05",
    "gn:admin2_code":"503.0",
    "gn:admin3_code":"50330.0",
    "gn:asciiname":"Poellach",
    "gn:country_code":"AT",
    "gn:dem":742,
    "gn:feature_class":"P",
    "gn:feature_code":"PPL",
    "gn:name":"P\u00f6llach",
    "gn:population":654,
    "gn:timezone":"Europe/Vienna",
    "iso:country":"AT",
    "wof:name":"Poellach",
    "wof:placetype":"locality",
    "wof:population":654
},
  "geometry": {"coordinates":[13.35,47.78333],"type":"Point"}
}