{
  "type": "Feature",
  "properties": {
    "gn:admin1_code":"4.0",
    "gn:admin2_code":"406",
    "gn:admin3_code":"40602.0",
    "gn:asciiname":"Heinrichschlag",
    "gn:country_code":"AT",
    "gn:dem":854,
    "gn:feature_class":"P",
    "gn:feature_code":"PPL",
    "gn:name":"Heinrichschlag",
    "gn:population":98,
    "gn:timezone":"Europe/Vienna",
    "iso:country":"AT",
    "wof:name":"Heinrichschlag",
    "wof:placetype":"locality",
    "wof:population":98
},
  "geometry": {"coordinates":[14.56289,48.54264000000001],"type":"Point"}
}