{
  "type": "Feature",
  "properties": {
    "gn:admin1_code":"7.0",
    "gn:admin2_code":"706",
    "gn:admin3_code":"70617.0",
    "gn:asciiname":"Eggele",
    "gn:country_code":"AT",
    "gn:dem":1525,
    "gn:feature_class":"P",
    "gn:feature_code":"PPL",
    "gn:name":"Eggele",
    "gn:population":0,
    "gn:timezone":"Europe/Vienna",
    "iso:country":"AT",
    "wof:name":"Eggele",
    "wof:placetype":"locality"
},
  "geometry": {"coordinates":[10.58333,46.98333],"type":"Point"}
}