{
  "type": "Feature",
  "properties": {
    "gn:admin1_code":"8.0",
    "gn:admin2_code":"802",
    "gn:admin3_code":"80228.0",
    "gn:asciiname":"Westegg",
    "gn:country_code":"AT",
    "gn:dem":1084,
    "gn:feature_class":"P",
    "gn:feature_code":"PPL",
    "gn:name":"Westegg",
    "gn:population":0,
    "gn:timezone":"Europe/Vienna",
    "iso:country":"AT",
    "wof:name":"Westegg",
    "wof:placetype":"locality"
},
  "geometry": {"coordinates":[10.19944,47.36528],"type":"Point"}
}