{
  "type": "Feature",
  "properties": {
    "iso:country":"AT",
    "name:deu_x_preferred":[
        "Webling"
    ],
    "name:eng_x_preferred":[
        "Webling"
    ],
    "wof:name":"Webling",
    "wof:placetype":"neighbourhood"
},
  "geometry": {"coordinates":[15.38957320550318,47.03250606959976],"type":"Point"}
}