{
  "type": "Feature",
  "properties": {
    "gn:admin1_code":"4.0",
    "gn:admin2_code":"406",
    "gn:admin3_code":"40623.0",
    "gn:asciiname":"Freudenthal",
    "gn:country_code":"AT",
    "gn:dem":701,
    "gn:feature_class":"P",
    "gn:feature_code":"PPL",
    "gn:name":"Freudenthal",
    "gn:population":90,
    "gn:timezone":"Europe/Vienna",
    "iso:country":"AT",
    "wof:name":"Freudenthal",
    "wof:placetype":"locality",
    "wof:population":90
},
  "geometry": {"coordinates":[14.43552,48.53332],"type":"Point"}
}