{
  "type": "Feature",
  "properties": {
    "gn:admin1_code":"04",
    "gn:admin2_code":"404.0",
    "gn:admin3_code":"40424.0",
    "gn:asciiname":"Winden",
    "gn:country_code":"AT",
    "gn:dem":397,
    "gn:feature_class":"P",
    "gn:feature_code":"PPL",
    "gn:name":"Winden",
    "gn:population":24,
    "gn:timezone":"Europe/Vienna",
    "iso:country":"AT",
    "name:ceb_x_preferred":[
        "Winden"
    ],
    "name:deu_x_preferred":[
        "Winden"
    ],
    "name:epo_x_preferred":[
        "Winden"
    ],
    "name:fra_x_preferred":[
        "Winden"
    ],
    "name:ita_x_preferred":[
        "Winden"
    ],
    "name:nld_x_preferred":[
        "Winden"
    ],
    "name:pol_x_preferred":[
        "Winden"
    ],
    "name:rus_x_preferred":[
        "\u0412\u0438\u043d\u0434\u0435\u043d"
    ],
    "name:srp_x_preferred":[
        "\u0412\u0438\u043d\u0434\u0438"
    ],
    "name:swe_x_preferred":[
        "Winden"
    ],
    "wof:name":"Winden",
    "wof:placetype":"locality",
    "wof:population":24
},
  "geometry": {"coordinates":[13.146,48.21901],"type":"Point"}
}