{
  "type": "Feature",
  "properties": {
    "gn:admin1_code":"04",
    "gn:admin2_code":"404.0",
    "gn:admin3_code":"40424.0",
    "gn:asciiname":"Winden",
    "gn:country_code":"AT",
    "gn:dem":397,
    "gn:feature_class":"P",
    "gn:feature_code":"PPL",
    "gn:name":"Winden",
    "gn:population":24,
    "gn:timezone":"Europe/Vienna",
    "iso:country":"AT",
    "wof:name":"Winden",
    "wof:placetype":"locality",
    "wof:population":24
},
  "geometry": {"coordinates":[13.146,48.21901],"type":"Point"}
}