{
  "type": "Feature",
  "properties": {
    "iso:country":"AT",
    "name:deu_x_preferred":[
        "Austra\u00dfensiedlung"
    ],
    "name:eng_x_preferred":[
        "Austrassensiedlung"
    ],
    "wof:name":"Austrassensiedlung",
    "wof:placetype":"neighbourhood"
},
  "geometry": {"coordinates":[13.036872575312,47.82177330636958],"type":"Point"}
}