{
  "type": "Feature",
  "properties": {
    "gn:admin1_code":"7.0",
    "gn:admin2_code":"707",
    "gn:admin3_code":"70719.0",
    "gn:asciiname":"Nussdorfer Berg",
    "gn:country_code":"AT",
    "gn:dem":1101,
    "gn:feature_class":"P",
    "gn:feature_code":"PPLL",
    "gn:name":"Nu\u00dfdorfer Berg",
    "gn:population":95,
    "gn:timezone":"Europe/Vienna",
    "iso:country":"AT",
    "wof:name":"Nussdorfer Berg",
    "wof:placetype":"locality",
    "wof:population":95
},
  "geometry": {"coordinates":[12.81083,46.84381],"type":"Point"}
}