{
  "type": "Feature",
  "properties": {
    "gn:admin1_code":"06",
    "gn:admin2_code":"620.0",
    "gn:admin3_code":"62044.0",
    "gn:asciiname":"Wenischgraben",
    "gn:country_code":"AT",
    "gn:dem":1162,
    "gn:feature_class":"P",
    "gn:feature_code":"PPLL",
    "gn:name":"Wenischgraben",
    "gn:population":0,
    "gn:timezone":"Europe/Vienna",
    "iso:country":"AT",
    "wof:name":"Wenischgraben",
    "wof:placetype":"locality"
},
  "geometry": {"coordinates":[14.51667,47.28333],"type":"Point"}
}