{
  "type": "Feature",
  "properties": {
    "gn:admin1_code":"04",
    "gn:admin2_code":"418.0",
    "gn:admin3_code":"41816.0",
    "gn:asciiname":"Winkeln",
    "gn:country_code":"AT",
    "gn:dem":317,
    "gn:feature_class":"P",
    "gn:feature_code":"PPL",
    "gn:name":"Winkeln",
    "gn:population":0,
    "gn:timezone":"Europe/Vienna",
    "iso:country":"AT",
    "wof:name":"Winkeln",
    "wof:placetype":"locality"
},
  "geometry": {"coordinates":[13.92612,48.21655],"type":"Point"}
}