{
  "type": "Feature",
  "properties": {
    "gn:admin1_code":"4.0",
    "gn:admin2_code":"407",
    "gn:admin3_code":"40711.0",
    "gn:asciiname":"Aichberg",
    "gn:country_code":"AT",
    "gn:dem":443,
    "gn:feature_class":"P",
    "gn:feature_code":"PPL",
    "gn:name":"Aichberg",
    "gn:population":0,
    "gn:timezone":"Europe/Vienna",
    "iso:country":"AT",
    "wof:name":"Aichberg",
    "wof:placetype":"locality"
},
  "geometry": {"coordinates":[13.80466,47.99529],"type":"Point"}
}