{
  "type": "Feature",
  "properties": {
    "gn:gn_country":"AT",
    "gn:gn_fcode":"PPL",
    "gn:gn_pop":0,
    "iso:country":"AT",
    "name:als_x_preferred":[
        "Kaisers"
    ],
    "name:ceb_x_preferred":[
        "Kaisers"
    ],
    "name:ces_x_preferred":[
        "Kaisers"
    ],
    "name:deu_x_preferred":[
        "Kaisers"
    ],
    "name:est_x_preferred":[
        "Kaisers"
    ],
    "name:fas_x_preferred":[
        "\u06a9\u0627\u06cc\u0632\u0631\u0633"
    ],
    "name:fra_x_preferred":[
        "Kaisers"
    ],
    "name:hun_x_preferred":[
        "Kaisers"
    ],
    "name:ita_x_preferred":[
        "Kaisers"
    ],
    "name:kaz_x_preferred":[
        "\u041a\u0430\u0439\u0437\u0435\u0440\u0441"
    ],
    "name:lmo_x_preferred":[
        "Kaisers"
    ],
    "name:nld_x_preferred":[
        "Kaisers"
    ],
    "name:pol_x_preferred":[
        "Kaisers"
    ],
    "name:rus_x_preferred":[
        "\u041a\u0430\u0439\u0437\u0435\u0440\u0441"
    ],
    "name:slk_x_preferred":[
        "Kaisers"
    ],
    "name:spa_x_preferred":[
        "Kaisers"
    ],
    "name:swe_x_preferred":[
        "Kaisers"
    ],
    "name:ukr_x_preferred":[
        "\u041a\u0430\u0439\u0437\u0435\u0440\u0441"
    ],
    "name:uzb_x_preferred":[
        "Kaisers"
    ],
    "name:vol_x_preferred":[
        "Kaisers"
    ],
    "name:war_x_preferred":[
        "Kaisers"
    ],
    "name:zho_x_preferred":[
        "\u51ef\u745f\u5c14\u65af"
    ],
    "qs_pg:aaroncc":"AT",
    "qs_pg:gn_country":"AT",
    "qs_pg:gn_fcode":"PPL",
    "qs_pg:gn_pop":0,
    "qs_pg:name":"Kaisers",
    "qs_pg:name_adm0":"\u00d6sterreich",
    "qs_pg:name_adm1":"Tirol",
    "qs_pg:photos":51,
    "qs_pg:photos_1k":10,
    "qs_pg:photos_9k":1,
    "qs_pg:photos_9r":2,
    "qs_pg:photos_all":51,
    "qs_pg:photos_sr":2,
    "qs_pg:pop_sr":0,
    "qs_pg:qs_pg_placetype":"locality",
    "qs_pg:qs_pg_placetype_gp":"Town",
    "qs_pg:woe_adm0":23424750,
    "woe:adm0_id":23424750,
    "woe:name_adm0":"\u00d6sterreich",
    "woe:name_adm1":"Tirol",
    "woe:placetype":"Town",
    "wof:name":"Kaisers",
    "wof:placetype":"locality"
},
  "geometry": {"coordinates":[11.01667,46.98333],"type":"Point"}
}