{
  "type": "Feature",
  "properties": {
    "gn:admin1_code":"4.0",
    "gn:admin2_code":"409",
    "gn:admin3_code":"40913.0",
    "gn:asciiname":"Grossendorf",
    "gn:country_code":"AT",
    "gn:dem":413,
    "gn:feature_class":"P",
    "gn:feature_code":"PPL",
    "gn:name":"Grossendorf",
    "gn:population":0,
    "gn:timezone":"Europe/Vienna",
    "iso:country":"AT",
    "name:und_x_variant":[
        "Gro\u00dfendorf"
    ],
    "wof:name":"Grossendorf",
    "wof:placetype":"locality"
},
  "geometry": {"coordinates":[14.05,48.05],"type":"Point"}
}