{
  "type": "Feature",
  "properties": {
    "gn:admin1_code":"02",
    "gn:admin2_code":"204.0",
    "gn:admin3_code":"20441.0",
    "gn:asciiname":"Ravna",
    "gn:country_code":"AT",
    "gn:dem":1022,
    "gn:feature_class":"P",
    "gn:feature_code":"PPL",
    "gn:name":"Ravna",
    "gn:population":0,
    "gn:timezone":"Europe/Vienna",
    "iso:country":"AT",
    "name:bos_x_preferred":[
        "Ravna"
    ],
    "name:bul_x_preferred":[
        "\u0420\u0430\u0432\u043d\u0430"
    ],
    "name:ceb_x_preferred":[
        "Ravna"
    ],
    "name:fra_x_preferred":[
        "Ravna"
    ],
    "name:hrv_x_preferred":[
        "Ravna"
    ],
    "name:ron_x_preferred":[
        "Ravna"
    ],
    "name:rus_x_preferred":[
        "\u0420\u0430\u0432\u043d\u0430"
    ],
    "name:slv_x_preferred":[
        "Ravna"
    ],
    "name:srp_x_preferred":[
        "\u0420\u0430\u0432\u043d\u0430"
    ],
    "name:swe_x_preferred":[
        "Ravna"
    ],
    "name:ukr_x_preferred":[
        "\u0420\u0430\u0432\u043d\u0430"
    ],
    "wof:name":"Ravna",
    "wof:placetype":"locality"
},
  "geometry": {"coordinates":[14.36667,46.46667],"type":"Point"}
}