{
  "type": "Feature",
  "properties": {
    "gn:admin1_code":"04",
    "gn:admin2_code":"407.0",
    "gn:admin3_code":"40718.0",
    "gn:asciiname":"Winkl",
    "gn:country_code":"AT",
    "gn:dem":482,
    "gn:feature_class":"P",
    "gn:feature_code":"PPL",
    "gn:name":"Winkl",
    "gn:population":0,
    "gn:timezone":"Europe/Vienna",
    "iso:country":"AT",
    "wof:name":"Winkl",
    "wof:placetype":"locality"
},
  "geometry": {"coordinates":[13.7751,47.84865],"type":"Point"}
}