{
  "type": "Feature",
  "properties": {
    "gn:admin1_code":"03",
    "gn:admin2_code":"318.0",
    "gn:admin3_code":"31839.0",
    "gn:asciiname":"Pottschach",
    "gn:country_code":"AT",
    "gn:dem":402,
    "gn:feature_class":"P",
    "gn:feature_code":"PPL",
    "gn:name":"Pottschach",
    "gn:population":4826,
    "gn:timezone":"Europe/Vienna",
    "iso:country":"AT",
    "wof:name":"Pottschach",
    "wof:placetype":"locality",
    "wof:population":4826
},
  "geometry": {"coordinates":[16.00725,47.69856],"type":"Point"}
}