{
  "type": "Feature",
  "properties": {
    "gn:admin1_code":"4.0",
    "gn:admin2_code":"417",
    "gn:admin3_code":"41709.0",
    "gn:asciiname":"Oberfeitzing",
    "gn:country_code":"AT",
    "gn:dem":646,
    "gn:feature_class":"P",
    "gn:feature_code":"PPL",
    "gn:name":"Oberfeitzing",
    "gn:population":16,
    "gn:timezone":"Europe/Vienna",
    "iso:country":"AT",
    "wof:name":"Oberfeitzing",
    "wof:placetype":"locality",
    "wof:population":16
},
  "geometry": {"coordinates":[13.50623,48.09935],"type":"Point"}
}