{
  "type": "Feature",
  "properties": {
    "iso:country":"AT",
    "name:deu_x_preferred":[
        "\u00c4u\u00dferer Stein"
    ],
    "name:eng_x_preferred":[
        "Aeusserer Stein"
    ],
    "wof:name":"Aeusserer Stein",
    "wof:placetype":"neighbourhood"
},
  "geometry": {"coordinates":[13.05471106237586,47.79951371134855],"type":"Point"}
}