{
  "type": "Feature",
  "properties": {
    "gn:admin1_code":"4.0",
    "gn:admin2_code":"405",
    "gn:admin3_code":"40510.0",
    "gn:asciiname":"Valtau",
    "gn:country_code":"AT",
    "gn:dem":357,
    "gn:feature_class":"P",
    "gn:feature_code":"PPL",
    "gn:name":"Valtau",
    "gn:population":58,
    "gn:timezone":"Europe/Vienna",
    "iso:country":"AT",
    "wof:name":"Valtau",
    "wof:placetype":"locality",
    "wof:population":58
},
  "geometry": {"coordinates":[13.90491,48.27497],"type":"Point"}
}