{
  "type": "Feature",
  "properties": {
    "gn:admin1_code":"4.0",
    "gn:admin2_code":"413",
    "gn:admin3_code":"41319.0",
    "gn:asciiname":"Damreith",
    "gn:country_code":"AT",
    "gn:dem":545,
    "gn:feature_class":"P",
    "gn:feature_code":"PPL",
    "gn:name":"Damreith",
    "gn:population":67,
    "gn:timezone":"Europe/Vienna",
    "iso:country":"AT",
    "wof:name":"Damreith",
    "wof:placetype":"locality",
    "wof:population":67
},
  "geometry": {"coordinates":[14.03478,48.60102],"type":"Point"}
}