{
  "type": "Feature",
  "properties": {
    "gn:admin1_code":"2.0",
    "gn:admin2_code":"205",
    "gn:admin3_code":"20527.0",
    "gn:asciiname":"Baardorf",
    "gn:country_code":"AT",
    "gn:dem":549,
    "gn:feature_class":"P",
    "gn:feature_code":"PPL",
    "gn:name":"Baardorf",
    "gn:population":4,
    "gn:timezone":"Europe/Vienna",
    "iso:country":"AT",
    "wof:name":"Baardorf",
    "wof:placetype":"locality",
    "wof:population":4
},
  "geometry": {"coordinates":[14.35596,46.74024],"type":"Point"}
}