{
  "type": "Feature",
  "properties": {
    "iso:country":"AT",
    "name:deu_x_colloquial":[
        "Kleinmuenchen",
        "Kleinmunchen"
    ],
    "name:deu_x_preferred":[
        "\u00d6FB Frauen Bundesliga"
    ],
    "name:deu_x_variant":[
        "Kleinm\u00fcnchen"
    ],
    "name:fra_x_preferred":[
        "Championnat d'Autriche de football f\u00e9minin"
    ],
    "name:ita_x_preferred":[
        "\u00d6FB-Frauenliga"
    ],
    "name:por_x_preferred":[
        "Campeonato Austr\u00edaco de Futebol Feminino"
    ],
    "name:rus_x_preferred":[
        "\u0427\u0435\u043c\u043f\u0438\u043e\u043d\u0430\u0442 \u0410\u0432\u0441\u0442\u0440\u0438\u0438 \u043f\u043e \u0444\u0443\u0442\u0431\u043e\u043b\u0443 \u0441\u0440\u0435\u0434\u0438 \u0436\u0435\u043d\u0449\u0438\u043d"
    ],
    "qs:gn_fcode":"PPLX",
    "qs:gn_local":0,
    "qs:gn_nam_loc":"Linz, Linz Stadt, Ober\u00f6sterreich, AT",
    "qs:gn_namadm1":"04",
    "qs:gn_name":"Kleinm\u00fcnchen",
    "qs:local_max":22933,
    "qs:local_sum":38224,
    "qs:localhoods":15,
    "qs:name":"Kleinm\u00fcnchen",
    "qs:name_adm0":"\u00d6sterreich",
    "qs:name_adm1":"Ober\u00f6sterreich",
    "qs:name_adm2":"Linz Stadt",
    "qs:name_lau":"Linz",
    "qs:name_local":"Linz",
    "qs:photo_max":77,
    "qs:photo_sum":424,
    "qs:placetype":"Suburb",
    "qs:quad_count":26,
    "qs:woe_adm0":23424750,
    "qs:woe_adm1":2344711,
    "qs:woe_adm2":12591722,
    "qs:woe_lau":12674377,
    "qs:woe_local":12674377,
    "qs:woe_ver":"7.10.0",
    "wof:lang":[
        "ger"
    ],
    "wof:name":"Kleinm\u00fcnchen",
    "wof:placetype":"neighbourhood"
},
  "geometry": {"coordinates":[14.318965,48.25542],"type":"Point"}
}