{
  "type": "Feature",
  "properties": {
    "gn:admin1_code":"3.0",
    "gn:admin2_code":"309",
    "gn:admin3_code":"30909.0",
    "gn:asciiname":"Eichberg",
    "gn:country_code":"AT",
    "gn:dem":512,
    "gn:feature_class":"P",
    "gn:feature_code":"PPL",
    "gn:name":"Eichberg",
    "gn:population":289,
    "gn:timezone":"Europe/Vienna",
    "iso:country":"AT",
    "wof:name":"Eichberg",
    "wof:placetype":"locality",
    "wof:population":289
},
  "geometry": {"coordinates":[14.91667,48.73333],"type":"Point"}
}