{
  "type": "Feature",
  "properties": {
    "gn:admin1_code":"3.0",
    "gn:admin2_code":"325",
    "gn:admin3_code":"32508.0",
    "gn:asciiname":"Josefsdorf",
    "gn:country_code":"AT",
    "gn:dem":677,
    "gn:feature_class":"P",
    "gn:feature_code":"PPL",
    "gn:name":"Josefsdorf",
    "gn:population":32,
    "gn:timezone":"Europe/Vienna",
    "iso:country":"AT",
    "wof:name":"Josefsdorf",
    "wof:placetype":"locality",
    "wof:population":32
},
  "geometry": {"coordinates":[15.06667,48.56667],"type":"Point"}
}