{
  "type": "Feature",
  "properties": {
    "gn:country":"AT",
    "gn:fcode":"PPL",
    "gn:population":0,
    "iso:country":"AT",
    "name:ceb_x_preferred":[
        "Mallnitz"
    ],
    "name:deu_x_preferred":[
        "Mallnitz"
    ],
    "name:eng_x_preferred":[
        "Mallnitz"
    ],
    "name:epo_x_preferred":[
        "Mallnitz"
    ],
    "name:fas_x_preferred":[
        "\u0645\u0627\u0644\u0646\u06cc\u062a\u0633"
    ],
    "name:fra_x_preferred":[
        "Mallnitz"
    ],
    "name:fur_x_preferred":[
        "Mallnitz"
    ],
    "name:hun_x_preferred":[
        "Mallnitz"
    ],
    "name:ind_x_preferred":[
        "Mallnitz"
    ],
    "name:ita_x_preferred":[
        "Mallnitz"
    ],
    "name:kaz_x_preferred":[
        "\u041c\u0430\u043b\u044c\u043d\u0438\u0446"
    ],
    "name:mkd_x_preferred":[
        "\u041c\u0430\u043b\u043d\u0438\u0446"
    ],
    "name:nld_x_preferred":[
        "Mallnitz"
    ],
    "name:pol_x_preferred":[
        "Mallnitz"
    ],
    "name:por_x_preferred":[
        "Mallnitz"
    ],
    "name:rus_x_preferred":[
        "\u041c\u0430\u043b\u044c\u043d\u0438\u0446"
    ],
    "name:slk_x_preferred":[
        "Mallnitz"
    ],
    "name:spa_x_preferred":[
        "Mallnitz"
    ],
    "name:swe_x_preferred":[
        "Mallnitz"
    ],
    "name:uzb_x_preferred":[
        "Mallnitz"
    ],
    "name:vol_x_preferred":[
        "Mallnitz"
    ],
    "name:war_x_preferred":[
        "Mallnitz"
    ],
    "name:zho_x_preferred":[
        "\u9a6c\u5c14\u5c3c\u8328"
    ],
    "name:zho_x_variant":[
        "Mallnitz"
    ],
    "qs_pg:aaroncc":"AT",
    "qs_pg:gn_country":"AT",
    "qs_pg:gn_fcode":"PPL",
    "qs_pg:gn_pop":0,
    "qs_pg:name":"Mallnitz",
    "qs_pg:name_adm0":"\u00d6sterreich",
    "qs_pg:name_adm1":"K\u00e4rnten",
    "qs_pg:photos":185,
    "qs_pg:photos_1k":37,
    "qs_pg:photos_9k":1,
    "qs_pg:photos_9r":4,
    "qs_pg:photos_all":185,
    "qs_pg:photos_sr":4,
    "qs_pg:pop_sr":0,
    "qs_pg:qs_pg_placetype":"locality",
    "qs_pg:qs_pg_placetype_gp":"Town",
    "qs_pg:woe_adm0":23424750,
    "woe:adm0_id":23424750,
    "woe:name_adm0":"\u00d6sterreich",
    "woe:name_adm1":"K\u00e4rnten",
    "woe:placetype":"Town",
    "wof:name":"Mallnitz",
    "wof:placetype":"locality"
},
  "geometry": {"coordinates":[13.1678,46.99173],"type":"Point"}
}