{
  "type": "Feature",
  "properties": {
    "gn:admin1_code":"3.0",
    "gn:admin2_code":"322",
    "gn:admin3_code":"32219.0",
    "gn:asciiname":"Kleingloms",
    "gn:country_code":"AT",
    "gn:dem":532,
    "gn:feature_class":"P",
    "gn:feature_code":"PPL",
    "gn:name":"Kleingloms",
    "gn:population":42,
    "gn:timezone":"Europe/Vienna",
    "iso:country":"AT",
    "wof:name":"Kleingloms",
    "wof:placetype":"locality",
    "wof:population":42
},
  "geometry": {"coordinates":[15.16195,48.74416],"type":"Point"}
}