{
  "type": "Feature",
  "properties": {
    "gn:admin1_code":"02",
    "gn:admin2_code":"209.0",
    "gn:admin3_code":"20909.0",
    "gn:asciiname":"Unterholz",
    "gn:country_code":"AT",
    "gn:dem":403,
    "gn:feature_class":"P",
    "gn:feature_code":"PPL",
    "gn:name":"Unterholz",
    "gn:population":47,
    "gn:timezone":"Europe/Vienna",
    "iso:country":"AT",
    "wof:name":"Unterholz",
    "wof:placetype":"locality",
    "wof:population":47
},
  "geometry": {"coordinates":[14.93333,46.68333],"type":"Point"}
}