{
  "type": "Feature",
  "properties": {
    "gn:admin1_code":"3.0",
    "gn:admin2_code":"325",
    "gn:admin3_code":"32508.0",
    "gn:asciiname":"Griesbach",
    "gn:country_code":"AT",
    "gn:dem":770,
    "gn:feature_class":"P",
    "gn:feature_code":"PPL",
    "gn:name":"Griesbach",
    "gn:population":247,
    "gn:timezone":"Europe/Vienna",
    "iso:country":"AT",
    "name:als_x_preferred":[
        "Griesbach"
    ],
    "name:ceb_x_preferred":[
        "Griesbach"
    ],
    "name:deu_x_preferred":[
        "Griesbach"
    ],
    "name:fra_x_preferred":[
        "Griesbach"
    ],
    "name:pol_x_preferred":[
        "Griesbach"
    ],
    "name:por_x_preferred":[
        "Griesbach"
    ],
    "name:rus_x_preferred":[
        "\u0413\u0440\u0438\u0441\u0431\u0430\u0445"
    ],
    "name:swe_x_preferred":[
        "Griesbach"
    ],
    "wof:name":"Griesbach",
    "wof:placetype":"locality",
    "wof:population":247
},
  "geometry": {"coordinates":[14.94879,48.52473],"type":"Point"}
}