{
  "type": "Feature",
  "properties": {
    "gn:admin1_code":"4.0",
    "gn:admin2_code":"408",
    "gn:admin3_code":"40812.0",
    "gn:asciiname":"Kallhamerdorf",
    "gn:country_code":"AT",
    "gn:dem":403,
    "gn:feature_class":"P",
    "gn:feature_code":"PPL",
    "gn:name":"Kallhamerdorf",
    "gn:population":51,
    "gn:timezone":"Europe/Vienna",
    "iso:country":"AT",
    "wof:name":"Kallhamerdorf",
    "wof:placetype":"locality",
    "wof:population":51
},
  "geometry": {"coordinates":[13.70978,48.28656],"type":"Point"}
}