{
  "type": "Feature",
  "properties": {
    "gn:admin1_code":"3.0",
    "gn:admin2_code":"312",
    "gn:admin3_code":"31235.0",
    "gn:asciiname":"Foehrenhain",
    "gn:country_code":"AT",
    "gn:dem":181,
    "gn:feature_class":"P",
    "gn:feature_code":"PPL",
    "gn:name":"F\u00f6hrenhain",
    "gn:population":0,
    "gn:timezone":"Europe/Vienna",
    "iso:country":"AT",
    "wof:name":"Foehrenhain",
    "wof:placetype":"locality"
},
  "geometry": {"coordinates":[16.45,48.31667],"type":"Point"}
}