{
  "type": "Feature",
  "properties": {
    "gn:country":"AT",
    "gn:fcode":"ADM3",
    "gn:population":0,
    "iso:country":"AT",
    "name:bar_x_preferred":[
        "Thiasee"
    ],
    "name:cat_x_preferred":[
        "Thiersee"
    ],
    "name:ceb_x_preferred":[
        "Thiersee"
    ],
    "name:che_x_preferred":[
        "\u0422\u0438\u0440\u0437\u0435"
    ],
    "name:deu_x_preferred":[
        "Thiersee"
    ],
    "name:eng_x_preferred":[
        "Thiersee"
    ],
    "name:est_x_preferred":[
        "Thiersee"
    ],
    "name:fas_x_preferred":[
        "\u062a\u0627\u06cc\u0631\u0633\u06cc"
    ],
    "name:fra_x_preferred":[
        "Thiersee"
    ],
    "name:hun_x_preferred":[
        "Thiersee"
    ],
    "name:ind_x_preferred":[
        "Thiersee"
    ],
    "name:ita_x_preferred":[
        "Thiersee"
    ],
    "name:kaz_x_preferred":[
        "\u0422\u0438\u0440\u0437\u0435\u0435"
    ],
    "name:lld_x_preferred":[
        "Thiersee"
    ],
    "name:lmo_x_preferred":[
        "Thiersee"
    ],
    "name:nld_x_preferred":[
        "Thiersee"
    ],
    "name:nno_x_preferred":[
        "Thiersee"
    ],
    "name:nob_x_preferred":[
        "Thiersee"
    ],
    "name:pol_x_preferred":[
        "Thiersee"
    ],
    "name:por_x_preferred":[
        "Thiersee"
    ],
    "name:rus_x_preferred":[
        "\u0422\u0438\u0440\u0437\u0435\u0435"
    ],
    "name:rus_x_variant":[
        "\u0422\u0438\u0440\u0437\u0435"
    ],
    "name:slk_x_preferred":[
        "Thiersee"
    ],
    "name:spa_x_preferred":[
        "Thiersee"
    ],
    "name:swe_x_preferred":[
        "Thiersee"
    ],
    "name:tat_x_preferred":[
        "\u0422\u0438\u0440\u0437\u0435"
    ],
    "name:ukr_x_preferred":[
        "\u0422\u0456\u0440\u0437\u0435"
    ],
    "name:uzb_x_preferred":[
        "Thiersee"
    ],
    "name:vec_x_preferred":[
        "Thiersee"
    ],
    "name:vol_x_preferred":[
        "Thiersee"
    ],
    "name:war_x_preferred":[
        "Thiersee"
    ],
    "name:zho_x_preferred":[
        "\u8482\u5c14\u585e"
    ],
    "qs_pg:aaroncc":"AT",
    "qs_pg:gn_country":"AT",
    "qs_pg:gn_fcode":"ADM3",
    "qs_pg:gn_pop":0,
    "qs_pg:name":"Thiersee",
    "qs_pg:name_adm0":"\u00d6sterreich",
    "qs_pg:name_adm1":"Tirol",
    "qs_pg:photos":146,
    "qs_pg:photos_1k":30,
    "qs_pg:photos_9k":1,
    "qs_pg:photos_9r":3,
    "qs_pg:photos_all":146,
    "qs_pg:photos_sr":3,
    "qs_pg:pop_sr":0,
    "qs_pg:qs_pg_placetype":"locality",
    "qs_pg:qs_pg_placetype_gp":"Town",
    "qs_pg:woe_adm0":23424750,
    "woe:adm0_id":23424750,
    "woe:name_adm0":"\u00d6sterreich",
    "woe:name_adm1":"Tirol",
    "woe:placetype":"Town",
    "wof:name":"Thiersee",
    "wof:placetype":"locality",
    "wof:population":2989
},
  "geometry": {"coordinates":[12.08333,47.58333],"type":"Point"}
}