{
  "type": "Feature",
  "properties": {
    "gn:admin1_code":"2.0",
    "gn:admin2_code":"205",
    "gn:admin3_code":"20531.0",
    "gn:asciiname":"Sadin",
    "gn:country_code":"AT",
    "gn:dem":818,
    "gn:feature_class":"P",
    "gn:feature_code":"PPLL",
    "gn:name":"Sadin",
    "gn:population":24,
    "gn:timezone":"Europe/Vienna",
    "iso:country":"AT",
    "wof:name":"Sadin",
    "wof:placetype":"locality",
    "wof:population":24
},
  "geometry": {"coordinates":[14.18528,46.86083],"type":"Point"}
}