{
  "type": "Feature",
  "properties": {
    "gn:admin1_code":"6.0",
    "gn:admin2_code":"616",
    "gn:admin3_code":"61625.0",
    "gn:asciiname":"Lobmingberg",
    "gn:country_code":"AT",
    "gn:dem":567,
    "gn:feature_class":"P",
    "gn:feature_code":"PPL",
    "gn:name":"Lobmingberg",
    "gn:population":0,
    "gn:timezone":"Europe/Vienna",
    "iso:country":"AT",
    "wof:name":"Lobmingberg",
    "wof:placetype":"locality"
},
  "geometry": {"coordinates":[15.16667,47.06667],"type":"Point"}
}