{
  "type": "Feature",
  "properties": {
    "gn:admin1_code":"06",
    "gn:admin2_code":"617.0",
    "gn:admin3_code":"61758.0",
    "gn:asciiname":"Oberreith",
    "gn:country_code":"AT",
    "gn:dem":808,
    "gn:feature_class":"P",
    "gn:feature_code":"PPL",
    "gn:name":"Oberreith",
    "gn:population":0,
    "gn:timezone":"Europe/Vienna",
    "iso:country":"AT",
    "wof:name":"Oberreith",
    "wof:placetype":"locality"
},
  "geometry": {"coordinates":[15.43333,47.28333],"type":"Point"}
}