{
  "type": "Feature",
  "properties": {
    "gn:admin1_code":"03",
    "gn:admin2_code":"318.0",
    "gn:admin3_code":"31810.0",
    "gn:asciiname":"Weissenbach",
    "gn:country_code":"AT",
    "gn:dem":494,
    "gn:feature_class":"P",
    "gn:feature_code":"PPL",
    "gn:name":"Weissenbach",
    "gn:population":0,
    "gn:timezone":"Europe/Vienna",
    "iso:country":"AT",
    "wof:name":"Weissenbach",
    "wof:placetype":"locality"
},
  "geometry": {"coordinates":[15.91318,47.66053],"type":"Point"}
}