{
  "type": "Feature",
  "properties": {
    "gn:admin1_code":"4.0",
    "gn:admin2_code":"410",
    "gn:admin3_code":"41015.0",
    "gn:asciiname":"Obere Au",
    "gn:country_code":"AT",
    "gn:dem":324,
    "gn:feature_class":"P",
    "gn:feature_code":"PPL",
    "gn:name":"Obere Au",
    "gn:population":0,
    "gn:timezone":"Europe/Vienna",
    "iso:country":"AT",
    "wof:name":"Obere Au",
    "wof:placetype":"locality"
},
  "geometry": {"coordinates":[14.35269,48.15927],"type":"Point"}
}