{
  "type": "Feature",
  "properties": {
    "gn:admin1_code":"4.0",
    "gn:admin2_code":"418",
    "gn:admin3_code":"41821.0",
    "gn:asciiname":"Hummelberg",
    "gn:country_code":"AT",
    "gn:dem":402,
    "gn:feature_class":"P",
    "gn:feature_code":"PPL",
    "gn:name":"Hummelberg",
    "gn:population":89,
    "gn:timezone":"Europe/Vienna",
    "iso:country":"AT",
    "wof:name":"Hummelberg",
    "wof:placetype":"locality",
    "wof:population":89
},
  "geometry": {"coordinates":[13.94414,48.07332],"type":"Point"}
}