{
  "type": "Feature",
  "properties": {
    "gn:admin1_code":"4.0",
    "gn:admin2_code":"417",
    "gn:admin3_code":"41716.0",
    "gn:asciiname":"Froschern",
    "gn:country_code":"AT",
    "gn:dem":601,
    "gn:feature_class":"P",
    "gn:feature_code":"PPL",
    "gn:name":"Froschern",
    "gn:population":21,
    "gn:timezone":"Europe/Vienna",
    "iso:country":"AT",
    "wof:name":"Froschern",
    "wof:placetype":"locality",
    "wof:population":21
},
  "geometry": {"coordinates":[13.54696,48.06549],"type":"Point"}
}