{
  "type": "Feature",
  "properties": {
    "gn:admin1_code":"06",
    "gn:admin2_code":"623.0",
    "gn:admin3_code":"62368.0",
    "gn:asciiname":"Kreuzberg",
    "gn:country_code":"AT",
    "gn:dem":254,
    "gn:feature_class":"P",
    "gn:feature_code":"PPL",
    "gn:name":"Kreuzberg",
    "gn:population":0,
    "gn:timezone":"Europe/Vienna",
    "iso:country":"AT",
    "name:bar_x_preferred":[
        "Kreizberg"
    ],
    "name:ben_x_preferred":[
        "\u0995\u09cd\u09b0\u09af\u09bc\u09c7\u09ce\u09b8\u09ac\u09c7\u09b0\u09cd\u0997"
    ],
    "name:bre_x_preferred":[
        "Kreuzberg"
    ],
    "name:cat_x_preferred":[
        "Kreuzberg"
    ],
    "name:cym_x_preferred":[
        "Kreuzberg"
    ],
    "name:dan_x_preferred":[
        "Kreuzberg"
    ],
    "name:deu_x_preferred":[
        "Berlin-Kreuzberg"
    ],
    "name:ell_x_preferred":[
        "\u039a\u03c1\u03cc\u03b9\u03c4\u03c3\u03bc\u03c0\u03b5\u03c1\u03b3\u03ba"
    ],
    "name:epo_x_preferred":[
        "Kreuzberg"
    ],
    "name:est_x_preferred":[
        "Kreuzberg"
    ],
    "name:fas_x_preferred":[
        "\u06a9\u0631\u0648\u06cc\u062a\u0633\u0628\u0631\u06af"
    ],
    "name:fin_x_preferred":[
        "Kreuzberg"
    ],
    "name:fra_x_preferred":[
        "Berlin-Kreuzberg"
    ],
    "name:heb_x_preferred":[
        "\u05e7\u05e8\u05d5\u05d9\u05e6\u05d1\u05e8\u05d2"
    ],
    "name:ita_x_preferred":[
        "Kreuzberg"
    ],
    "name:lat_x_preferred":[
        "Mons Crucis"
    ],
    "name:mkd_x_preferred":[
        "\u041a\u0440\u043e\u0458\u0446\u0431\u0435\u0440\u0433"
    ],
    "name:nld_x_preferred":[
        "Berlin-Kreuzberg"
    ],
    "name:nor_x_preferred":[
        "Kreuzberg"
    ],
    "name:pol_x_preferred":[
        "Kreuzberg"
    ],
    "name:rus_x_preferred":[
        "\u041a\u0440\u043e\u0439\u0446\u0431\u0435\u0440\u0433"
    ],
    "name:spa_x_preferred":[
        "Kreuzberg"
    ],
    "name:swe_x_preferred":[
        "Kreuzberg"
    ],
    "name:tur_x_preferred":[
        "Kreuzberg"
    ],
    "name:zho_x_preferred":[
        "\u514b\u7f57\u4f0a\u8328\u8d1d\u683c"
    ],
    "wof:name":"Kreuzberg",
    "wof:placetype":"locality"
},
  "geometry": {"coordinates":[15.93333,46.76667],"type":"Point"}
}