{
  "type": "Feature",
  "properties": {
    "gn:admin1_code":"4.0",
    "gn:admin2_code":"413",
    "gn:admin3_code":"41317.0",
    "gn:asciiname":"Lengau",
    "gn:country_code":"AT",
    "gn:dem":819,
    "gn:feature_class":"P",
    "gn:feature_code":"PPL",
    "gn:name":"Lengau",
    "gn:population":71,
    "gn:timezone":"Europe/Vienna",
    "iso:country":"AT",
    "wof:name":"Lengau",
    "wof:placetype":"locality",
    "wof:population":71
},
  "geometry": {"coordinates":[13.86157,48.60136],"type":"Point"}
}