{
  "type": "Feature",
  "properties": {
    "gn:admin1_code":"4.0",
    "gn:admin2_code":"413",
    "gn:admin3_code":"41317.0",
    "gn:asciiname":"Lengau",
    "gn:country_code":"AT",
    "gn:dem":819,
    "gn:feature_class":"P",
    "gn:feature_code":"PPL",
    "gn:name":"Lengau",
    "gn:population":71,
    "gn:timezone":"Europe/Vienna",
    "iso:country":"AT",
    "name:ceb_x_preferred":[
        "Lengau"
    ],
    "name:deu_x_preferred":[
        "Lengau"
    ],
    "name:fas_x_preferred":[
        "\u0644\u0646\u06af\u0648"
    ],
    "name:fra_x_preferred":[
        "Lengau"
    ],
    "name:fur_x_preferred":[
        "Lengau"
    ],
    "name:hun_x_preferred":[
        "Lengau"
    ],
    "name:ita_x_preferred":[
        "Lengau"
    ],
    "name:kaz_x_preferred":[
        "\u041b\u0435\u043d\u0433\u0430\u0443"
    ],
    "name:nld_x_preferred":[
        "Lengau"
    ],
    "name:pol_x_preferred":[
        "Lengau"
    ],
    "name:por_x_preferred":[
        "Lengau"
    ],
    "name:rus_x_preferred":[
        "\u041b\u0435\u043d\u0433\u0430\u0443"
    ],
    "name:slk_x_preferred":[
        "Lengau"
    ],
    "name:spa_x_preferred":[
        "Lengau"
    ],
    "name:swe_x_preferred":[
        "Lengau"
    ],
    "name:uzb_x_preferred":[
        "Lengau"
    ],
    "name:vie_x_preferred":[
        "Lengau"
    ],
    "name:vol_x_preferred":[
        "Lengau"
    ],
    "name:war_x_preferred":[
        "Lengau"
    ],
    "wof:name":"Lengau",
    "wof:placetype":"locality",
    "wof:population":71
},
  "geometry": {"coordinates":[13.86157,48.60136],"type":"Point"}
}