{
  "type": "Feature",
  "properties": {
    "gn:admin1_code":"4.0",
    "gn:admin2_code":"404",
    "gn:admin3_code":"40407.0",
    "gn:asciiname":"Holz",
    "gn:country_code":"AT",
    "gn:dem":558,
    "gn:feature_class":"P",
    "gn:feature_code":"PPL",
    "gn:name":"Holz",
    "gn:population":17,
    "gn:timezone":"Europe/Vienna",
    "iso:country":"AT",
    "wof:name":"Holz",
    "wof:placetype":"locality",
    "wof:population":17
},
  "geometry": {"coordinates":[13.06759,48.06595],"type":"Point"}
}