{
  "type": "Feature",
  "properties": {
    "gn:admin1_code":"4.0",
    "gn:admin2_code":"408",
    "gn:admin3_code":"40834.0",
    "gn:asciiname":"Unterhoeglham",
    "gn:country_code":"AT",
    "gn:dem":412,
    "gn:feature_class":"P",
    "gn:feature_code":"PPL",
    "gn:name":"Unterh\u00f6glham",
    "gn:population":25,
    "gn:timezone":"Europe/Vienna",
    "iso:country":"AT",
    "wof:name":"Unterhoeglham",
    "wof:placetype":"locality",
    "wof:population":25
},
  "geometry": {"coordinates":[13.68047,48.25788],"type":"Point"}
}