{
  "type": "Feature",
  "properties": {
    "gn:admin1_code":"6.0",
    "gn:admin2_code":"623",
    "gn:admin3_code":"62388.0",
    "gn:asciiname":"Dietersdorf am Gnasbach",
    "gn:cc2":"AT",
    "gn:country_code":"AT",
    "gn:dem":277,
    "gn:feature_class":"P",
    "gn:feature_code":"PPLA3",
    "gn:name":"Dietersdorf am Gnasbach",
    "gn:population":365,
    "gn:timezone":"Europe/Vienna",
    "iso:country":"AT",
    "name:und_x_variant":[
        "Dietersdorf",
        "Dietersdorf am Gnasbach"
    ],
    "wof:name":"Dietersdorf am Gnasbach",
    "wof:placetype":"locality",
    "wof:population":365
},
  "geometry": {"coordinates":[15.81167,46.80917],"type":"Point"}
}