{
  "type": "Feature",
  "properties": {
    "gn:admin1_code":"6.0",
    "gn:admin2_code":"623",
    "gn:admin3_code":"62388.0",
    "gn:asciiname":"Dietersdorf am Gnasbach",
    "gn:cc2":"AT",
    "gn:country_code":"AT",
    "gn:dem":277,
    "gn:feature_class":"P",
    "gn:feature_code":"PPLA3",
    "gn:name":"Dietersdorf am Gnasbach",
    "gn:population":365,
    "gn:timezone":"Europe/Vienna",
    "iso:country":"AT",
    "name:ceb_x_preferred":[
        "Dietersdorf am Gnasbach"
    ],
    "name:deu_x_preferred":[
        "Dietersdorf am Gnasbach"
    ],
    "name:fas_x_preferred":[
        "\u062f\u0627\u06cc\u062a\u0631\u0633\u062f\u0648\u0631\u0641 \u0627\u0645 \u06af\u0646\u0627\u0633\u0628\u0627\u062e"
    ],
    "name:fra_x_preferred":[
        "Dietersdorf am Gnasbach"
    ],
    "name:ita_x_preferred":[
        "Dietersdorf am Gnasbach"
    ],
    "name:kaz_x_preferred":[
        "\u0414\u0438\u0442\u0435\u0440\u0441\u0434\u043e\u0440\u0444-\u0430\u043c-\u0413\u043d\u0430\u0441\u0431\u0430\u0445"
    ],
    "name:nld_x_preferred":[
        "Dietersdorf am Gnasbach"
    ],
    "name:rus_x_preferred":[
        "\u0414\u0438\u0442\u0435\u0440\u0441\u0434\u043e\u0440\u0444-\u0430\u043c-\u0413\u043d\u0430\u0441\u0431\u0430\u0445"
    ],
    "name:slk_x_preferred":[
        "Dietersdorf am Gnasbach"
    ],
    "name:swe_x_preferred":[
        "Dietersdorf am Gnasbach"
    ],
    "name:und_x_variant":[
        "Dietersdorf",
        "Dietersdorf am Gnasbach"
    ],
    "name:uzb_x_preferred":[
        "Dietersdorf am Gnasbach"
    ],
    "name:vie_x_preferred":[
        "Dietersdorf am Gnasbach"
    ],
    "name:vol_x_preferred":[
        "Dietersdorf am Gnasbach"
    ],
    "name:war_x_preferred":[
        "Dietersdorf am Gnasbach"
    ],
    "name:zho_x_preferred":[
        "\u683c\u7eb3\u65af\u5df4\u8d6b\u6cb3\u7554\u8fea\u7279\u5c14\u65af\u591a\u592b"
    ],
    "wof:name":"Dietersdorf am Gnasbach",
    "wof:placetype":"locality",
    "wof:population":365
},
  "geometry": {"coordinates":[15.81167,46.80917],"type":"Point"}
}