{
  "type": "Feature",
  "properties": {
    "gn:admin1_code":"3.0",
    "gn:admin2_code":"319",
    "gn:admin3_code":"31934.0",
    "gn:asciiname":"Brunn",
    "gn:country_code":"AT",
    "gn:dem":302,
    "gn:feature_class":"P",
    "gn:feature_code":"PPL",
    "gn:name":"Brunn",
    "gn:population":110,
    "gn:timezone":"Europe/Vienna",
    "iso:country":"AT",
    "wof:name":"Brunn",
    "wof:placetype":"locality",
    "wof:population":110
},
  "geometry": {"coordinates":[15.65535,48.16712],"type":"Point"}
}