{
  "type": "Feature",
  "properties": {
    "gn:admin1_code":"6.0",
    "gn:admin2_code":"622",
    "gn:admin3_code":"62233.0",
    "gn:asciiname":"Sparberegg",
    "gn:country_code":"AT",
    "gn:dem":708,
    "gn:feature_class":"P",
    "gn:feature_code":"PPL",
    "gn:name":"Sparberegg",
    "gn:population":177,
    "gn:timezone":"Europe/Vienna",
    "iso:country":"AT",
    "wof:name":"Sparberegg",
    "wof:placetype":"locality",
    "wof:population":177
},
  "geometry": {"coordinates":[16.11703,47.42588],"type":"Point"}
}