{
  "type": "Feature",
  "properties": {
    "gn:admin1_code":"6.0",
    "gn:admin2_code":"603",
    "gn:admin3_code":"60305.0",
    "gn:asciiname":"Krottendorf an der Lassnitz",
    "gn:cc2":"AT",
    "gn:country_code":"AT",
    "gn:dem":308,
    "gn:feature_class":"P",
    "gn:feature_code":"PPL",
    "gn:name":"Krottendorf an der Lassnitz",
    "gn:population":0,
    "gn:timezone":"Europe/Vienna",
    "iso:country":"AT",
    "name:und_x_variant":[
        "Krottendorf",
        "Krottendorf an der La\u00dfnitz"
    ],
    "wof:name":"Krottendorf an der Lassnitz",
    "wof:placetype":"locality"
},
  "geometry": {"coordinates":[15.27553,46.82115],"type":"Point"}
}