{
  "type": "Feature",
  "properties": {
    "gn:admin1_code":"5.0",
    "gn:admin2_code":"506",
    "gn:admin3_code":"50622.0",
    "gn:asciiname":"Amoos",
    "gn:country_code":"AT",
    "gn:dem":1334,
    "gn:feature_class":"P",
    "gn:feature_code":"PPL",
    "gn:name":"Amoos",
    "gn:population":0,
    "gn:timezone":"Europe/Vienna",
    "iso:country":"AT",
    "wof:name":"Amoos",
    "wof:placetype":"locality"
},
  "geometry": {"coordinates":[12.99331,47.32184],"type":"Point"}
}