{
  "type": "Feature",
  "properties": {
    "gn:admin1_code":"1.0",
    "gn:admin2_code":"107",
    "gn:admin3_code":"10701.0",
    "gn:asciiname":"Albrechtsfeld",
    "gn:country_code":"AT",
    "gn:dem":120,
    "gn:feature_class":"P",
    "gn:feature_code":"PPL",
    "gn:name":"Albrechtsfeld",
    "gn:population":0,
    "gn:timezone":"Europe/Vienna",
    "iso:country":"AT",
    "wof:name":"Albrechtsfeld",
    "wof:placetype":"locality"
},
  "geometry": {"coordinates":[17.01667,47.81667],"type":"Point"}
}