{
  "type": "Feature",
  "properties": {
    "gn:admin1_code":"2.0",
    "gn:admin2_code":"203",
    "gn:admin3_code":"20307.0",
    "gn:asciiname":"Plon",
    "gn:country_code":"AT",
    "gn:dem":1024,
    "gn:feature_class":"P",
    "gn:feature_code":"PPL",
    "gn:name":"Plon",
    "gn:population":13,
    "gn:timezone":"Europe/Vienna",
    "iso:country":"AT",
    "wof:name":"Plon",
    "wof:placetype":"locality",
    "wof:population":13
},
  "geometry": {"coordinates":[13.03438,46.6775],"type":"Point"}
}