{
  "type": "Feature",
  "properties": {
    "gn:admin1_code":"4.0",
    "gn:admin2_code":"412",
    "gn:admin3_code":"41231.0",
    "gn:asciiname":"Brandstaetten",
    "gn:country_code":"AT",
    "gn:dem":491,
    "gn:feature_class":"P",
    "gn:feature_code":"PPL",
    "gn:name":"Brandst\u00e4tten",
    "gn:population":35,
    "gn:timezone":"Europe/Vienna",
    "iso:country":"AT",
    "wof:name":"Brandstaetten",
    "wof:placetype":"locality",
    "wof:population":35
},
  "geometry": {"coordinates":[13.55,48.28333],"type":"Point"}
}