{
  "type": "Feature",
  "properties": {
    "gn:admin1_code":"6.0",
    "gn:admin2_code":"612",
    "gn:admin3_code":"61257.0",
    "gn:asciiname":"Furrach",
    "gn:country_code":"AT",
    "gn:dem":1080,
    "gn:feature_class":"P",
    "gn:feature_code":"PPL",
    "gn:name":"Furrach",
    "gn:population":49,
    "gn:timezone":"Europe/Vienna",
    "iso:country":"AT",
    "wof:name":"Furrach",
    "wof:placetype":"locality",
    "wof:population":49
},
  "geometry": {"coordinates":[14.15,47.43333],"type":"Point"}
}