{
  "type": "Feature",
  "properties": {
    "gn:admin1_code":"3.0",
    "gn:admin2_code":"313",
    "gn:admin3_code":"31330.0",
    "gn:asciiname":"Elsarn am Jauerling",
    "gn:cc2":"AT",
    "gn:country_code":"AT",
    "gn:dem":558,
    "gn:feature_class":"P",
    "gn:feature_code":"PPL",
    "gn:name":"Elsarn am Jauerling",
    "gn:population":154,
    "gn:timezone":"Europe/Vienna",
    "iso:country":"AT",
    "name:und_x_variant":[
        "Elsarn",
        "Elsarn am Jauerling"
    ],
    "wof:name":"Elsarn am Jauerling",
    "wof:placetype":"locality",
    "wof:population":154
},
  "geometry": {"coordinates":[15.36667,48.36667],"type":"Point"}
}