{
  "type": "Feature",
  "properties": {
    "gn:admin1_code":"03",
    "gn:admin2_code":"322.0",
    "gn:admin3_code":"32219.0",
    "gn:asciiname":"Stoies",
    "gn:country_code":"AT",
    "gn:dem":570,
    "gn:feature_class":"P",
    "gn:feature_code":"PPL",
    "gn:name":"Stoies",
    "gn:population":17,
    "gn:timezone":"Europe/Vienna",
    "iso:country":"AT",
    "wof:name":"Stoies",
    "wof:placetype":"locality",
    "wof:population":17
},
  "geometry": {"coordinates":[15.20289,48.78129000000001],"type":"Point"}
}