{
  "type": "Feature",
  "properties": {
    "gn:admin1_code":"7.0",
    "gn:admin2_code":"709",
    "gn:admin3_code":"70939.0",
    "gn:asciiname":"Ehrenstall",
    "gn:country_code":"AT",
    "gn:dem":613,
    "gn:feature_class":"P",
    "gn:feature_code":"PPL",
    "gn:name":"Ehrenstall",
    "gn:population":3,
    "gn:timezone":"Europe/Vienna",
    "iso:country":"AT",
    "wof:name":"Ehrenstall",
    "wof:placetype":"locality",
    "wof:population":3
},
  "geometry": {"coordinates":[11.78404,47.4021],"type":"Point"}
}