{
  "type": "Feature",
  "properties": {
    "gn:admin1_code":"06",
    "gn:admin2_code":"610.0",
    "gn:admin3_code":"61047.0",
    "gn:asciiname":"Wurzing",
    "gn:country_code":"AT",
    "gn:dem":320,
    "gn:feature_class":"P",
    "gn:feature_code":"PPL",
    "gn:name":"Wurzing",
    "gn:population":0,
    "gn:timezone":"Europe/Vienna",
    "iso:country":"AT",
    "wof:name":"Wurzing",
    "wof:placetype":"locality"
},
  "geometry": {"coordinates":[15.51667,46.88333],"type":"Point"}
}