{
  "type": "Feature",
  "properties": {
    "gn:admin1_code":"03",
    "gn:admin2_code":"325.0",
    "gn:admin3_code":"32530.0",
    "gn:asciiname":"Ritzmannshof",
    "gn:country_code":"AT",
    "gn:dem":622,
    "gn:feature_class":"P",
    "gn:feature_code":"PPL",
    "gn:name":"Ritzmannshof",
    "gn:population":5,
    "gn:timezone":"Europe/Vienna",
    "iso:country":"AT",
    "wof:name":"Ritzmannshof",
    "wof:placetype":"locality",
    "wof:population":5
},
  "geometry": {"coordinates":[15.15169,48.65627],"type":"Point"}
}