{
  "type": "Feature",
  "properties": {
    "gn:admin1_code":"3.0",
    "gn:admin2_code":"305",
    "gn:admin3_code":"30531.0",
    "gn:asciiname":"Kirchdorf",
    "gn:country_code":"AT",
    "gn:dem":265,
    "gn:feature_class":"P",
    "gn:feature_code":"PPL",
    "gn:name":"Kirchdorf",
    "gn:population":0,
    "gn:timezone":"Europe/Vienna",
    "iso:country":"AT",
    "wof:name":"Kirchdorf",
    "wof:placetype":"locality"
},
  "geometry": {"coordinates":[14.53333,48.16667],"type":"Point"}
}