{
  "type": "Feature",
  "properties": {
    "gn:admin1_code":"3.0",
    "gn:admin2_code":"305",
    "gn:admin3_code":"30531.0",
    "gn:asciiname":"Kirchdorf",
    "gn:country_code":"AT",
    "gn:dem":265,
    "gn:feature_class":"P",
    "gn:feature_code":"PPL",
    "gn:name":"Kirchdorf",
    "gn:population":0,
    "gn:timezone":"Europe/Vienna",
    "iso:country":"AT",
    "name:als_x_preferred":[
        "Kirchdorf"
    ],
    "name:ceb_x_preferred":[
        "Kirchdorf"
    ],
    "name:dan_x_preferred":[
        "Kirchdorf"
    ],
    "name:deu_x_preferred":[
        "Kirchdorf"
    ],
    "name:epo_x_preferred":[
        "Kirchdorf"
    ],
    "name:fra_x_preferred":[
        "Kirchdorf"
    ],
    "name:hye_x_preferred":[
        "\u053f\u056b\u0580\u056d\u0564\u0578\u0580\u0586"
    ],
    "name:ita_x_preferred":[
        "Kirchdorf"
    ],
    "name:lmo_x_preferred":[
        "Kirchdorf"
    ],
    "name:nld_x_preferred":[
        "Kirchdorf"
    ],
    "name:pol_x_preferred":[
        "Kirchdorf"
    ],
    "name:por_x_preferred":[
        "Kirchdorf"
    ],
    "name:rus_x_preferred":[
        "\u041a\u0438\u0440\u0445\u0434\u043e\u0440\u0444"
    ],
    "name:spa_x_preferred":[
        "Kirchdorf"
    ],
    "name:swe_x_preferred":[
        "Kirchdorf"
    ],
    "name:vol_x_preferred":[
        "Kirchdorf"
    ],
    "wof:name":"Kirchdorf",
    "wof:placetype":"locality"
},
  "geometry": {"coordinates":[14.53333,48.16667],"type":"Point"}
}