{
  "type": "Feature",
  "properties": {
    "gn:admin1_code":"6.0",
    "gn:admin2_code":"620",
    "gn:admin3_code":"62046.0",
    "gn:asciiname":"Kroisbach",
    "gn:country_code":"AT",
    "gn:dem":644,
    "gn:feature_class":"P",
    "gn:feature_code":"PPL",
    "gn:name":"Kroisbach",
    "gn:population":68,
    "gn:timezone":"Europe/Vienna",
    "iso:country":"AT",
    "wof:name":"Kroisbach",
    "wof:placetype":"locality",
    "wof:population":68
},
  "geometry": {"coordinates":[14.86042,47.22193],"type":"Point"}
}