{
  "type": "Feature",
  "properties": {
    "gn:admin1_code":"3.0",
    "gn:admin2_code":"315",
    "gn:admin3_code":"31514.0",
    "gn:asciiname":"Glosbach",
    "gn:country_code":"AT",
    "gn:dem":469,
    "gn:feature_class":"P",
    "gn:feature_code":"PPL",
    "gn:name":"Glosbach",
    "gn:population":26,
    "gn:timezone":"Europe/Vienna",
    "iso:country":"AT",
    "wof:name":"Glosbach",
    "wof:placetype":"locality",
    "wof:population":26
},
  "geometry": {"coordinates":[15.37897,48.05755],"type":"Point"}
}