{
  "type": "Feature",
  "properties": {
    "gn:admin1_code":"5.0",
    "gn:admin2_code":"502",
    "gn:admin3_code":"50211.0",
    "gn:asciiname":"Oberlangenberg",
    "gn:country_code":"AT",
    "gn:dem":831,
    "gn:feature_class":"P",
    "gn:feature_code":"PPL",
    "gn:name":"Oberlangenberg",
    "gn:population":509,
    "gn:timezone":"Europe/Vienna",
    "iso:country":"AT",
    "wof:name":"Oberlangenberg",
    "wof:placetype":"locality",
    "wof:population":509
},
  "geometry": {"coordinates":[13.18866,47.63601],"type":"Point"}
}