{
  "type": "Feature",
  "properties": {
    "gn:admin1_code":"06",
    "gn:admin2_code":"612.0",
    "gn:admin3_code":"61222.0",
    "gn:asciiname":"Fuchslucken",
    "gn:country_code":"AT",
    "gn:dem":823,
    "gn:feature_class":"P",
    "gn:feature_code":"PPL",
    "gn:name":"Fuchslucken",
    "gn:population":63,
    "gn:timezone":"Europe/Vienna",
    "iso:country":"AT",
    "wof:name":"Fuchslucken",
    "wof:placetype":"locality",
    "wof:population":63
},
  "geometry": {"coordinates":[14.21667,47.55],"type":"Point"}
}