{
  "type": "Feature",
  "properties": {
    "gn:admin1_code":"5.0",
    "gn:admin2_code":"503",
    "gn:admin3_code":"50303.0",
    "gn:asciiname":"Siggerwiesen",
    "gn:country_code":"AT",
    "gn:dem":417,
    "gn:feature_class":"P",
    "gn:feature_code":"PPL",
    "gn:name":"Siggerwiesen",
    "gn:population":0,
    "gn:timezone":"Europe/Vienna",
    "iso:country":"AT",
    "wof:name":"Siggerwiesen",
    "wof:placetype":"locality"
},
  "geometry": {"coordinates":[13.01278,47.86139],"type":"Point"}
}