{
  "type": "Feature",
  "properties": {
    "gn:admin1_code":"06",
    "gn:admin2_code":"620.0",
    "gn:admin3_code":"62040.0",
    "gn:asciiname":"Reifling",
    "gn:country_code":"AT",
    "gn:dem":1187,
    "gn:feature_class":"P",
    "gn:feature_code":"PPLA3",
    "gn:name":"Reifling",
    "gn:population":60,
    "gn:timezone":"Europe/Vienna",
    "iso:country":"AT",
    "wof:name":"Reifling",
    "wof:placetype":"locality",
    "wof:population":60
},
  "geometry": {"coordinates":[14.66667,47.13333],"type":"Point"}
}