{
  "type": "Feature",
  "properties": {
    "gn:admin1_code":"06",
    "gn:admin2_code":"620.0",
    "gn:admin3_code":"62040.0",
    "gn:asciiname":"Reifling",
    "gn:country_code":"AT",
    "gn:dem":1187,
    "gn:feature_class":"P",
    "gn:feature_code":"PPLA3",
    "gn:name":"Reifling",
    "gn:population":60,
    "gn:timezone":"Europe/Vienna",
    "iso:country":"AT",
    "name:ceb_x_preferred":[
        "Reifling"
    ],
    "name:deu_x_preferred":[
        "Reifling"
    ],
    "name:fas_x_preferred":[
        "\u0631\u0627\u06cc\u0641\u0644\u06cc\u0646\u06af"
    ],
    "name:fra_x_preferred":[
        "Reifling"
    ],
    "name:ita_x_preferred":[
        "Reifling"
    ],
    "name:kaz_x_preferred":[
        "\u0420\u0430\u0439\u0444\u043b\u0438\u043d\u0433"
    ],
    "name:nld_x_preferred":[
        "Reifling"
    ],
    "name:rus_x_preferred":[
        "\u0420\u0430\u0439\u0444\u043b\u0438\u043d\u0433"
    ],
    "name:slk_x_preferred":[
        "Reifling"
    ],
    "name:swe_x_preferred":[
        "Reifling"
    ],
    "name:uzb_x_preferred":[
        "Reifling"
    ],
    "name:vie_x_preferred":[
        "Reifling"
    ],
    "name:vol_x_preferred":[
        "Reifling"
    ],
    "name:war_x_preferred":[
        "Reifling"
    ],
    "name:zho_x_preferred":[
        "\u8d56\u592b\u7075"
    ],
    "wof:name":"Reifling",
    "wof:placetype":"locality",
    "wof:population":60
},
  "geometry": {"coordinates":[14.66667,47.13333],"type":"Point"}
}