{
  "type": "Feature",
  "properties": {
    "gn:admin1_code":"04",
    "gn:admin2_code":"413.0",
    "gn:admin3_code":"41314.0",
    "gn:asciiname":"Witzersdorf",
    "gn:country_code":"AT",
    "gn:dem":543,
    "gn:feature_class":"P",
    "gn:feature_code":"PPL",
    "gn:name":"Witzersdorf",
    "gn:population":36,
    "gn:timezone":"Europe/Vienna",
    "iso:country":"AT",
    "wof:name":"Witzersdorf",
    "wof:placetype":"locality",
    "wof:population":36
},
  "geometry": {"coordinates":[13.94796,48.43575],"type":"Point"}
}