{
  "type": "Feature",
  "properties": {
    "gn:admin1_code":"4.0",
    "gn:admin2_code":"418",
    "gn:admin3_code":"41821.0",
    "gn:asciiname":"Hammersedt",
    "gn:country_code":"AT",
    "gn:dem":384,
    "gn:feature_class":"P",
    "gn:feature_code":"PPL",
    "gn:name":"Hammersedt",
    "gn:population":59,
    "gn:timezone":"Europe/Vienna",
    "iso:country":"AT",
    "wof:name":"Hammersedt",
    "wof:placetype":"locality",
    "wof:population":59
},
  "geometry": {"coordinates":[14.01701,48.08163],"type":"Point"}
}