{
  "type": "Feature",
  "properties": {
    "gn:admin1_code":"4.0",
    "gn:admin2_code":"412",
    "gn:admin3_code":"41218.0",
    "gn:asciiname":"Bergetsedt",
    "gn:country_code":"AT",
    "gn:dem":518,
    "gn:feature_class":"P",
    "gn:feature_code":"PPL",
    "gn:name":"Bergetsedt",
    "gn:population":30,
    "gn:timezone":"Europe/Vienna",
    "iso:country":"AT",
    "wof:name":"Bergetsedt",
    "wof:placetype":"locality",
    "wof:population":30
},
  "geometry": {"coordinates":[13.43761,48.17416],"type":"Point"}
}