{
  "type": "Feature",
  "properties": {
    "gn:admin1_code":"5.0",
    "gn:admin2_code":"506",
    "gn:admin3_code":"50622.0",
    "gn:asciiname":"Holzlehen",
    "gn:country_code":"AT",
    "gn:dem":1196,
    "gn:feature_class":"P",
    "gn:feature_code":"PPL",
    "gn:name":"Holzlehen",
    "gn:population":0,
    "gn:timezone":"Europe/Vienna",
    "iso:country":"AT",
    "wof:name":"Holzlehen",
    "wof:placetype":"locality"
},
  "geometry": {"coordinates":[12.95202,47.30321],"type":"Point"}
}