{
  "type": "Feature",
  "properties": {
    "gn:admin1_code":"7.0",
    "gn:admin2_code":"708",
    "gn:admin3_code":"70822.0",
    "gn:asciiname":"Oberpinswang",
    "gn:country_code":"AT",
    "gn:dem":817,
    "gn:feature_class":"P",
    "gn:feature_code":"PPL",
    "gn:name":"Oberpinswang",
    "gn:population":0,
    "gn:timezone":"Europe/Vienna",
    "iso:country":"AT",
    "wof:name":"Oberpinswang",
    "wof:placetype":"locality"
},
  "geometry": {"coordinates":[10.68333,47.53333],"type":"Point"}
}