{
  "type": "Feature",
  "properties": {
    "gn:admin1_code":"3.0",
    "gn:admin2_code":"321",
    "gn:admin3_code":"32139.0",
    "gn:asciiname":"Grub",
    "gn:country_code":"AT",
    "gn:dem":212,
    "gn:feature_class":"P",
    "gn:feature_code":"PPL",
    "gn:name":"Grub",
    "gn:population":7,
    "gn:timezone":"Europe/Vienna",
    "iso:country":"AT",
    "name:ceb_x_preferred":[
        "Grub"
    ],
    "name:deu_x_preferred":[
        "Grub"
    ],
    "name:epo_x_preferred":[
        "Grub"
    ],
    "name:fra_x_preferred":[
        "Grub"
    ],
    "name:ita_x_preferred":[
        "Grub"
    ],
    "name:nld_x_preferred":[
        "Grub"
    ],
    "name:pol_x_preferred":[
        "Grub"
    ],
    "name:por_x_preferred":[
        "Grub"
    ],
    "name:ron_x_preferred":[
        "Grub"
    ],
    "name:rus_x_preferred":[
        "\u0413\u0440\u0443\u0431"
    ],
    "name:spa_x_preferred":[
        "Grub"
    ],
    "name:srp_x_preferred":[
        "\u0413\u0440\u0443\u0431"
    ],
    "name:swe_x_preferred":[
        "Grub"
    ],
    "name:vol_x_preferred":[
        "Grub"
    ],
    "wof:name":"Grub",
    "wof:placetype":"locality",
    "wof:population":7
},
  "geometry": {"coordinates":[15.86958,48.26617],"type":"Point"}
}