{
  "type": "Feature",
  "properties": {
    "gn:admin1_code":"2.0",
    "gn:admin2_code":"203",
    "gn:admin3_code":"20321.0",
    "gn:asciiname":"Frohn",
    "gn:country_code":"AT",
    "gn:dem":1362,
    "gn:feature_class":"P",
    "gn:feature_code":"PPL",
    "gn:name":"Frohn",
    "gn:population":27,
    "gn:timezone":"Europe/Vienna",
    "iso:country":"AT",
    "wof:name":"Frohn",
    "wof:placetype":"locality",
    "wof:population":27
},
  "geometry": {"coordinates":[12.76611,46.69472],"type":"Point"}
}