{
  "type": "Feature",
  "properties": {
    "gn:admin1_code":"06",
    "gn:admin2_code":"603.0",
    "gn:admin3_code":"60305.0",
    "gn:asciiname":"Zeierling",
    "gn:country_code":"AT",
    "gn:dem":368,
    "gn:feature_class":"P",
    "gn:feature_code":"PPL",
    "gn:name":"Zeierling",
    "gn:population":450,
    "gn:timezone":"Europe/Vienna",
    "iso:country":"AT",
    "wof:name":"Zeierling",
    "wof:placetype":"locality",
    "wof:population":450
},
  "geometry": {"coordinates":[15.26667,46.83333],"type":"Point"}
}