{
  "type": "Feature",
  "properties": {
    "gn:admin1_code":"6.0",
    "gn:admin2_code":"620",
    "gn:admin3_code":"62042.0",
    "gn:asciiname":"Baernthal",
    "gn:country_code":"AT",
    "gn:dem":1343,
    "gn:feature_class":"P",
    "gn:feature_code":"PPL",
    "gn:name":"B\u00e4rnthal",
    "gn:population":21,
    "gn:timezone":"Europe/Vienna",
    "iso:country":"AT",
    "wof:name":"Baernthal",
    "wof:placetype":"locality",
    "wof:population":21
},
  "geometry": {"coordinates":[14.63333,47.03333],"type":"Point"}
}