{
  "type": "Feature",
  "properties": {
    "gn:admin1_code":"6.0",
    "gn:admin2_code":"622",
    "gn:admin3_code":"62205.0",
    "gn:asciiname":"Mitterndorf",
    "gn:country_code":"AT",
    "gn:dem":368,
    "gn:feature_class":"P",
    "gn:feature_code":"PPL",
    "gn:name":"Mitterndorf",
    "gn:population":73,
    "gn:timezone":"Europe/Vienna",
    "iso:country":"AT",
    "wof:name":"Mitterndorf",
    "wof:placetype":"locality",
    "wof:population":73
},
  "geometry": {"coordinates":[16.04266,47.21572000000001],"type":"Point"}
}