{
  "type": "Feature",
  "properties": {
    "gn:admin1_code":"3.0",
    "gn:admin2_code":"309",
    "gn:admin3_code":"30909.0",
    "gn:asciiname":"Hoermanns bei Weitra",
    "gn:cc2":"AT",
    "gn:country_code":"AT",
    "gn:dem":593,
    "gn:feature_class":"P",
    "gn:feature_code":"PPL",
    "gn:name":"H\u00f6rmanns bei Weitra",
    "gn:population":221,
    "gn:timezone":"Europe/Vienna",
    "iso:country":"AT",
    "name:und_x_variant":[
        "H\u00f6rmanns",
        "H\u00f6rmanns bei Weitra"
    ],
    "wof:name":"Hoermanns bei Weitra",
    "wof:placetype":"locality",
    "wof:population":221
},
  "geometry": {"coordinates":[14.96667,48.71667],"type":"Point"}
}