{
  "type": "Feature",
  "properties": {
    "gn:admin1_code":"4.0",
    "gn:admin2_code":"406",
    "gn:admin3_code":"40617.0",
    "gn:asciiname":"Attenedt",
    "gn:country_code":"AT",
    "gn:dem":788,
    "gn:feature_class":"P",
    "gn:feature_code":"PPL",
    "gn:name":"Attenedt",
    "gn:population":0,
    "gn:timezone":"Europe/Vienna",
    "iso:country":"AT",
    "wof:name":"Attenedt",
    "wof:placetype":"locality"
},
  "geometry": {"coordinates":[14.70915,48.45038],"type":"Point"}
}