{
  "type": "Feature",
  "properties": {
    "gn:admin1_code":"4.0",
    "gn:admin2_code":"413",
    "gn:admin3_code":"41339.0",
    "gn:asciiname":"Oberhaag",
    "gn:country_code":"AT",
    "gn:dem":845,
    "gn:feature_class":"P",
    "gn:feature_code":"PPL",
    "gn:name":"Oberhaag",
    "gn:population":0,
    "gn:timezone":"Europe/Vienna",
    "iso:country":"AT",
    "wof:name":"Oberhaag",
    "wof:placetype":"locality"
},
  "geometry": {"coordinates":[14.00697,48.65469],"type":"Point"}
}