{
  "type": "Feature",
  "properties": {
    "gn:admin1_code":"4.0",
    "gn:admin2_code":"413",
    "gn:admin3_code":"41339.0",
    "gn:asciiname":"Oberhaag",
    "gn:country_code":"AT",
    "gn:dem":845,
    "gn:feature_class":"P",
    "gn:feature_code":"PPL",
    "gn:name":"Oberhaag",
    "gn:population":0,
    "gn:timezone":"Europe/Vienna",
    "iso:country":"AT",
    "name:ceb_x_preferred":[
        "Oberhaag"
    ],
    "name:deu_x_preferred":[
        "Oberhaag"
    ],
    "name:epo_x_preferred":[
        "Oberhaag"
    ],
    "name:fas_x_preferred":[
        "\u0627\u0648\u0628\u0631\u0647\u0627\u06af"
    ],
    "name:fra_x_preferred":[
        "Oberhaag"
    ],
    "name:hun_x_preferred":[
        "Oberhaag"
    ],
    "name:ita_x_preferred":[
        "Oberhaag"
    ],
    "name:nld_x_preferred":[
        "Oberhaag"
    ],
    "name:pol_x_preferred":[
        "Oberhaag"
    ],
    "name:rus_x_preferred":[
        "\u041e\u0431\u0435\u0440\u0445\u0430\u0433"
    ],
    "name:slk_x_preferred":[
        "Oberhaag"
    ],
    "name:spa_x_preferred":[
        "Oberhaag"
    ],
    "name:swe_x_preferred":[
        "Oberhaag"
    ],
    "name:uzb_x_preferred":[
        "Oberhaag"
    ],
    "name:vie_x_preferred":[
        "Oberhaag"
    ],
    "name:vol_x_preferred":[
        "Oberhaag"
    ],
    "name:war_x_preferred":[
        "Oberhaag"
    ],
    "name:zho_x_preferred":[
        "\u4e0a\u54c8\u683c"
    ],
    "wof:name":"Oberhaag",
    "wof:placetype":"locality"
},
  "geometry": {"coordinates":[14.00697,48.65469],"type":"Point"}
}