{
  "type": "Feature",
  "properties": {
    "gn:admin1_code":"06",
    "gn:admin2_code":"623.0",
    "gn:admin3_code":"62381.0",
    "gn:asciiname":"Zerlach",
    "gn:country_code":"AT",
    "gn:dem":336,
    "gn:feature_class":"P",
    "gn:feature_code":"PPLA3",
    "gn:name":"Zerlach",
    "gn:population":361,
    "gn:timezone":"Europe/Vienna",
    "iso:country":"AT",
    "wof:name":"Zerlach",
    "wof:placetype":"locality",
    "wof:population":361
},
  "geometry": {"coordinates":[15.65093,46.94593],"type":"Point"}
}