{
  "type": "Feature",
  "properties": {
    "gn:admin1_code":"06",
    "gn:admin2_code":"623.0",
    "gn:admin3_code":"62381.0",
    "gn:asciiname":"Zerlach",
    "gn:country_code":"AT",
    "gn:dem":336,
    "gn:feature_class":"P",
    "gn:feature_code":"PPLA3",
    "gn:name":"Zerlach",
    "gn:population":361,
    "gn:timezone":"Europe/Vienna",
    "iso:country":"AT",
    "name:ceb_x_preferred":[
        "Zerlach"
    ],
    "name:deu_x_preferred":[
        "Zerlach"
    ],
    "name:fas_x_preferred":[
        "\u0633\u0631\u0644\u0627\u062e"
    ],
    "name:fra_x_preferred":[
        "Zerlach"
    ],
    "name:ita_x_preferred":[
        "Zerlach"
    ],
    "name:kaz_x_preferred":[
        "\u0426\u0435\u0440\u043b\u0430\u0445"
    ],
    "name:nld_x_preferred":[
        "Zerlach"
    ],
    "name:rus_x_preferred":[
        "\u0426\u0435\u0440\u043b\u0430\u0445"
    ],
    "name:slk_x_preferred":[
        "Zerlach"
    ],
    "name:swe_x_preferred":[
        "Zerlach"
    ],
    "name:uzb_x_preferred":[
        "Zerlach"
    ],
    "name:vie_x_preferred":[
        "Zerlach"
    ],
    "name:vol_x_preferred":[
        "Zerlach"
    ],
    "name:war_x_preferred":[
        "Zerlach"
    ],
    "name:zho_x_preferred":[
        "\u91c7\u62c9\u8d6b"
    ],
    "wof:name":"Zerlach",
    "wof:placetype":"locality",
    "wof:population":361
},
  "geometry": {"coordinates":[15.65093,46.94593],"type":"Point"}
}