{
  "type": "Feature",
  "properties": {
    "gn:admin1_code":"6.0",
    "gn:admin2_code":"622",
    "gn:admin3_code":"62271.0",
    "gn:asciiname":"Aschau",
    "gn:country_code":"AT",
    "gn:dem":285,
    "gn:feature_class":"P",
    "gn:feature_code":"PPL",
    "gn:name":"Aschau",
    "gn:population":0,
    "gn:timezone":"Europe/Vienna",
    "iso:country":"AT",
    "name:ceb_x_preferred":[
        "Aschau"
    ],
    "name:deu_x_preferred":[
        "Aschau"
    ],
    "name:epo_x_preferred":[
        "Aschau"
    ],
    "name:fra_x_preferred":[
        "Aschau"
    ],
    "name:ita_x_preferred":[
        "Aschau"
    ],
    "name:nld_x_preferred":[
        "Aschau"
    ],
    "name:pol_x_preferred":[
        "Aschau"
    ],
    "name:ron_x_preferred":[
        "Aschau"
    ],
    "name:swe_x_preferred":[
        "Aschau"
    ],
    "wof:name":"Aschau",
    "wof:placetype":"locality"
},
  "geometry": {"coordinates":[15.91667,47.08333],"type":"Point"}
}