{
  "type": "Feature",
  "properties": {
    "gn:admin1_code":"4.0",
    "gn:admin2_code":"410",
    "gn:admin3_code":"41022.0",
    "gn:asciiname":"Hoef",
    "gn:country_code":"AT",
    "gn:dem":279,
    "gn:feature_class":"P",
    "gn:feature_code":"PPL",
    "gn:name":"H\u00f6f",
    "gn:population":198,
    "gn:timezone":"Europe/Vienna",
    "iso:country":"AT",
    "wof:name":"Hoef",
    "wof:placetype":"locality",
    "wof:population":198
},
  "geometry": {"coordinates":[14.17631,48.32122],"type":"Point"}
}