{
  "type": "Feature",
  "properties": {
    "gn:admin1_code":"6.0",
    "gn:admin2_code":"603",
    "gn:admin3_code":"60345.0",
    "gn:asciiname":"Sankt Oswald ob Eibiswald",
    "gn:country_code":"AT",
    "gn:dem":754,
    "gn:feature_class":"P",
    "gn:feature_code":"PPLA3",
    "gn:name":"Sankt Oswald ob Eibiswald",
    "gn:population":292,
    "gn:timezone":"Europe/Vienna",
    "iso:country":"AT",
    "wof:name":"Sankt Oswald ob Eibiswald",
    "wof:placetype":"locality",
    "wof:population":292
},
  "geometry": {"coordinates":[15.14667,46.70833],"type":"Point"}
}