{
  "type": "Feature",
  "properties": {
    "gn:admin1_code":"6.0",
    "gn:admin2_code":"603",
    "gn:admin3_code":"60345.0",
    "gn:asciiname":"Sankt Oswald ob Eibiswald",
    "gn:country_code":"AT",
    "gn:dem":754,
    "gn:feature_class":"P",
    "gn:feature_code":"PPLA3",
    "gn:name":"Sankt Oswald ob Eibiswald",
    "gn:population":292,
    "gn:timezone":"Europe/Vienna",
    "iso:country":"AT",
    "name:ceb_x_preferred":[
        "Sankt Oswald ob Eibiswald"
    ],
    "name:deu_x_preferred":[
        "Sankt Oswald ob Eibiswald"
    ],
    "name:fas_x_preferred":[
        "\u0632\u0627\u0646\u06a9\u062a \u0627\u0648\u0633\u0648\u0627\u0644\u062f \u0627\u0648\u0628 \u0622\u06cc\u0628\u06cc\u0633\u0648\u0627\u0644\u062f"
    ],
    "name:fra_x_preferred":[
        "Sankt Oswald ob Eibiswald"
    ],
    "name:ita_x_preferred":[
        "Sankt Oswald ob Eibiswald"
    ],
    "name:nld_x_preferred":[
        "Sankt Oswald ob Eibiswald"
    ],
    "name:slk_x_preferred":[
        "Sankt Oswald ob Eibiswald"
    ],
    "name:swe_x_preferred":[
        "Sankt Oswald ob Eibiswald"
    ],
    "name:uzb_x_preferred":[
        "Sankt Oswald ob Eibiswald"
    ],
    "name:vie_x_preferred":[
        "Sankt Oswald ob Eibiswald"
    ],
    "name:vol_x_preferred":[
        "Sankt Oswald ob Eibiswald"
    ],
    "name:war_x_preferred":[
        "Sankt Oswald ob Eibiswald"
    ],
    "wof:name":"Sankt Oswald ob Eibiswald",
    "wof:placetype":"locality",
    "wof:population":292
},
  "geometry": {"coordinates":[15.14667,46.70833],"type":"Point"}
}