{
  "type": "Feature",
  "properties": {
    "gn:admin1_code":"4.0",
    "gn:admin2_code":"415",
    "gn:admin3_code":"41513.0",
    "gn:asciiname":"Bradern",
    "gn:country_code":"AT",
    "gn:dem":377,
    "gn:feature_class":"P",
    "gn:feature_code":"PPL",
    "gn:name":"Bradern",
    "gn:population":0,
    "gn:timezone":"Europe/Vienna",
    "iso:country":"AT",
    "wof:name":"Bradern",
    "wof:placetype":"locality"
},
  "geometry": {"coordinates":[14.16667,48.05],"type":"Point"}
}