{
  "type": "Feature",
  "properties": {
    "iso:country":"AT",
    "name:deu_x_preferred":[
        "Altmaxglan"
    ],
    "name:eng_x_preferred":[
        "Altmaxglan"
    ],
    "wof:name":"Altmaxglan",
    "wof:placetype":"neighbourhood"
},
  "geometry": {"coordinates":[13.01339787020234,47.80341487363341],"type":"Point"}
}