{
  "type": "Feature",
  "properties": {
    "gn:admin1_code":"3.0",
    "gn:admin2_code":"305",
    "gn:admin3_code":"30511.0",
    "gn:asciiname":"Ferndorf",
    "gn:country_code":"AT",
    "gn:dem":455,
    "gn:feature_class":"P",
    "gn:feature_code":"PPL",
    "gn:name":"Ferndorf",
    "gn:population":0,
    "gn:timezone":"Europe/Vienna",
    "iso:country":"AT",
    "name:ceb_x_preferred":[
        "Ferndorf"
    ],
    "name:deu_x_preferred":[
        "Ferndorf"
    ],
    "name:epo_x_preferred":[
        "Ferndorf"
    ],
    "name:fas_x_preferred":[
        "\u0641\u0631\u0646\u062f\u0648\u0631\u0641"
    ],
    "name:fra_x_preferred":[
        "Ferndorf"
    ],
    "name:fur_x_preferred":[
        "Ferndorf"
    ],
    "name:hun_x_preferred":[
        "Ferndorf"
    ],
    "name:ita_x_preferred":[
        "Ferndorf"
    ],
    "name:kaz_x_preferred":[
        "\u0424\u0435\u0440\u043d\u0434\u043e\u0440\u0444"
    ],
    "name:nld_x_preferred":[
        "Ferndorf"
    ],
    "name:pol_x_preferred":[
        "Ferndorf"
    ],
    "name:por_x_preferred":[
        "Ferndorf"
    ],
    "name:rus_x_preferred":[
        "\u0424\u0435\u0440\u043d\u0434\u043e\u0440\u0444"
    ],
    "name:slk_x_preferred":[
        "Ferndorf"
    ],
    "name:slv_x_preferred":[
        "Perja vas"
    ],
    "name:spa_x_preferred":[
        "Ferndorf"
    ],
    "name:ukr_x_preferred":[
        "\u0424\u0435\u0440\u043d\u0434\u043e\u0440\u0444"
    ],
    "name:uzb_x_preferred":[
        "Ferndorf"
    ],
    "name:vie_x_preferred":[
        "Ferndorf"
    ],
    "name:vol_x_preferred":[
        "Ferndorf"
    ],
    "name:war_x_preferred":[
        "Ferndorf"
    ],
    "name:zho_x_preferred":[
        "\u8d39\u6069\u591a\u592b"
    ],
    "wof:name":"Ferndorf",
    "wof:placetype":"locality"
},
  "geometry": {"coordinates":[14.92235,48.04383],"type":"Point"}
}