{
  "type": "Feature",
  "properties": {
    "gn:admin1_code":"3.0",
    "gn:admin2_code":"305",
    "gn:admin3_code":"30511.0",
    "gn:asciiname":"Ferndorf",
    "gn:country_code":"AT",
    "gn:dem":455,
    "gn:feature_class":"P",
    "gn:feature_code":"PPL",
    "gn:name":"Ferndorf",
    "gn:population":0,
    "gn:timezone":"Europe/Vienna",
    "iso:country":"AT",
    "wof:name":"Ferndorf",
    "wof:placetype":"locality"
},
  "geometry": {"coordinates":[14.92235,48.04383],"type":"Point"}
}