{
  "type": "Feature",
  "properties": {
    "gn:admin1_code":"05",
    "gn:admin2_code":"503.0",
    "gn:admin3_code":"50322.0",
    "gn:asciiname":"Sankt Alban",
    "gn:country_code":"AT",
    "gn:dem":486,
    "gn:feature_class":"P",
    "gn:feature_code":"PPL",
    "gn:name":"Sankt Alban",
    "gn:population":61,
    "gn:timezone":"Europe/Vienna",
    "iso:country":"AT",
    "wof:name":"Sankt Alban",
    "wof:placetype":"locality",
    "wof:population":61
},
  "geometry": {"coordinates":[12.98333,47.98333],"type":"Point"}
}