{
  "type": "Feature",
  "properties": {
    "gn:admin1_code":"3.0",
    "gn:admin2_code":"321",
    "gn:admin3_code":"32135.0",
    "gn:asciiname":"Neuaigen",
    "gn:country_code":"AT",
    "gn:dem":181,
    "gn:feature_class":"P",
    "gn:feature_code":"PPL",
    "gn:name":"Neuaigen",
    "gn:population":478,
    "gn:timezone":"Europe/Vienna",
    "iso:country":"AT",
    "wof:name":"Neuaigen",
    "wof:placetype":"locality",
    "wof:population":478
},
  "geometry": {"coordinates":[16.01667,48.35],"type":"Point"}
}