{
  "type": "Feature",
  "properties": {
    "gn:admin1_code":"02",
    "gn:admin2_code":"209.0",
    "gn:admin3_code":"20923.0",
    "gn:asciiname":"Reinfelsdorf",
    "gn:country_code":"AT",
    "gn:dem":451,
    "gn:feature_class":"P",
    "gn:feature_code":"PPL",
    "gn:name":"Reinfelsdorf",
    "gn:population":63,
    "gn:timezone":"Europe/Vienna",
    "iso:country":"AT",
    "wof:name":"Reinfelsdorf",
    "wof:placetype":"locality",
    "wof:population":63
},
  "geometry": {"coordinates":[14.81667,46.81667],"type":"Point"}
}