{
  "type": "Feature",
  "properties": {
    "gn:admin1_code":"03",
    "gn:admin2_code":"313.0",
    "gn:admin3_code":"31326.0",
    "gn:asciiname":"Wiesmannsreith",
    "gn:country_code":"AT",
    "gn:dem":745,
    "gn:feature_class":"P",
    "gn:feature_code":"PPL",
    "gn:name":"Wiesmannsreith",
    "gn:population":30,
    "gn:timezone":"Europe/Vienna",
    "iso:country":"AT",
    "wof:name":"Wiesmannsreith",
    "wof:placetype":"locality",
    "wof:population":30
},
  "geometry": {"coordinates":[15.35841,48.3269],"type":"Point"}
}