{
  "type": "Feature",
  "properties": {
    "gn:admin1_code":"2.0",
    "gn:admin2_code":"208",
    "gn:admin3_code":"20813.0",
    "gn:asciiname":"Horzach I",
    "gn:country_code":"AT",
    "gn:dem":442,
    "gn:feature_class":"P",
    "gn:feature_code":"PPL",
    "gn:name":"Horzach I",
    "gn:population":44,
    "gn:timezone":"Europe/Vienna",
    "iso:country":"AT",
    "wof:name":"Horzach I",
    "wof:placetype":"locality",
    "wof:population":44
},
  "geometry": {"coordinates":[14.5901,46.62097],"type":"Point"}
}