{
  "type": "Feature",
  "properties": {
    "gn:admin1_code":"4.0",
    "gn:admin2_code":"417",
    "gn:admin3_code":"41708.0",
    "gn:asciiname":"Unterholzing",
    "gn:country_code":"AT",
    "gn:dem":527,
    "gn:feature_class":"P",
    "gn:feature_code":"PPL",
    "gn:name":"Unterholzing",
    "gn:population":8,
    "gn:timezone":"Europe/Vienna",
    "iso:country":"AT",
    "wof:name":"Unterholzing",
    "wof:placetype":"locality",
    "wof:population":8
},
  "geometry": {"coordinates":[13.43654,48.01513],"type":"Point"}
}