{
  "type": "Feature",
  "properties": {
    "gn:admin1_code":"4.0",
    "gn:admin2_code":"412",
    "gn:admin3_code":"41204.0",
    "gn:asciiname":"Illing",
    "gn:country_code":"AT",
    "gn:dem":622,
    "gn:feature_class":"P",
    "gn:feature_code":"PPL",
    "gn:name":"Illing",
    "gn:population":33,
    "gn:timezone":"Europe/Vienna",
    "iso:country":"AT",
    "wof:name":"Illing",
    "wof:placetype":"locality",
    "wof:population":33
},
  "geometry": {"coordinates":[13.55129,48.12302],"type":"Point"}
}