{
  "type": "Feature",
  "properties": {
    "gn:admin1_code":"6.0",
    "gn:admin2_code":"623",
    "gn:admin3_code":"62381.0",
    "gn:asciiname":"Doerfla",
    "gn:country_code":"AT",
    "gn:dem":329,
    "gn:feature_class":"P",
    "gn:feature_code":"PPL",
    "gn:name":"D\u00f6rfla",
    "gn:population":476,
    "gn:timezone":"Europe/Vienna",
    "iso:country":"AT",
    "wof:name":"Doerfla",
    "wof:placetype":"locality",
    "wof:population":476
},
  "geometry": {"coordinates":[15.6725,46.93806],"type":"Point"}
}