{
  "type": "Feature",
  "properties": {
    "gn:gn_country":"AT",
    "gn:gn_fcode":"PPLA3",
    "gn:gn_pop":0,
    "gn:population":1166,
    "iso:country":"AT",
    "name:chi_x_preferred":[
        "\u54c8\u5ef7"
    ],
    "name:cze_x_preferred":[
        "Hatting"
    ],
    "name:dut_x_preferred":[
        "Hatting"
    ],
    "name:eng_x_preferred":[
        "Hatting"
    ],
    "name:fre_x_preferred":[
        "Hatting"
    ],
    "name:ger_x_preferred":[
        "Hatting"
    ],
    "name:hun_x_preferred":[
        "Hatting"
    ],
    "name:ita_x_preferred":[
        "Hatting"
    ],
    "name:kaz_x_preferred":[
        "\u0425\u0430\u0442\u0442\u0438\u043d\u0433"
    ],
    "name:lmo_x_preferred":[
        "Hatting"
    ],
    "name:pol_x_preferred":[
        "Hatting"
    ],
    "name:rus_x_preferred":[
        "\u0425\u0430\u0442\u0442\u0438\u043d\u0433"
    ],
    "name:slo_x_preferred":[
        "Hatting"
    ],
    "name:swe_x_preferred":[
        "Hatting"
    ],
    "name:ukr_x_preferred":[
        "\u0413\u0430\u0442\u0442\u0456\u043d\u0433"
    ],
    "name:uzb_x_preferred":[
        "Hatting"
    ],
    "name:vol_x_preferred":[
        "Hatting"
    ],
    "name:war_x_preferred":[
        "Hatting"
    ],
    "qs_pg:aaroncc":"AT",
    "qs_pg:gn_country":"AT",
    "qs_pg:gn_fcode":"PPLA3",
    "qs_pg:gn_pop":0,
    "qs_pg:name":"Hatting",
    "qs_pg:name_adm0":"\u00d6sterreich",
    "qs_pg:name_adm1":"Tirol",
    "qs_pg:photos":163,
    "qs_pg:photos_1k":33,
    "qs_pg:photos_9k":1,
    "qs_pg:photos_9r":4,
    "qs_pg:photos_all":163,
    "qs_pg:photos_sr":4,
    "qs_pg:pop_sr":0,
    "qs_pg:qs_pg_placetype":"locality",
    "qs_pg:qs_pg_placetype_gp":"Town",
    "qs_pg:woe_adm0":23424750,
    "woe:adm0_id":23424750,
    "woe:name_adm0":"\u00d6sterreich",
    "woe:name_adm1":"Tirol",
    "woe:placetype":"Town",
    "wof:name":"Hatting",
    "wof:placetype":"locality",
    "wof:population":1166
},
  "geometry": {"coordinates":[11.16667,47.28333],"type":"Point"}
}