{
  "type": "Feature",
  "properties": {
    "gn:admin1_code":"04",
    "gn:admin2_code":"409.0",
    "gn:admin3_code":"40901.0",
    "gn:asciiname":"Pieglmoos",
    "gn:country_code":"AT",
    "gn:dem":630,
    "gn:feature_class":"P",
    "gn:feature_code":"PPL",
    "gn:name":"Pieglmoos",
    "gn:population":0,
    "gn:timezone":"Europe/Vienna",
    "iso:country":"AT",
    "wof:name":"Pieglmoos",
    "wof:placetype":"locality"
},
  "geometry": {"coordinates":[14.34707,47.70199],"type":"Point"}
}