{
  "type": "Feature",
  "properties": {
    "gn:admin1_code":"6.0",
    "gn:admin2_code":"606",
    "gn:admin3_code":"60662.0",
    "gn:asciiname":"Gnaning",
    "gn:country_code":"AT",
    "gn:dem":365,
    "gn:feature_class":"P",
    "gn:feature_code":"PPL",
    "gn:name":"Gnaning",
    "gn:population":424,
    "gn:timezone":"Europe/Vienna",
    "iso:country":"AT",
    "wof:name":"Gnaning",
    "wof:placetype":"locality",
    "wof:population":424
},
  "geometry": {"coordinates":[15.53333,46.96667],"type":"Point"}
}