{
  "type": "Feature",
  "properties": {
    "gn:admin1_code":"4.0",
    "gn:admin2_code":"408",
    "gn:admin3_code":"40801.0",
    "gn:asciiname":"Himmelreich",
    "gn:country_code":"AT",
    "gn:dem":440,
    "gn:feature_class":"P",
    "gn:feature_code":"PPL",
    "gn:name":"Himmelreich",
    "gn:population":31,
    "gn:timezone":"Europe/Vienna",
    "iso:country":"AT",
    "wof:name":"Himmelreich",
    "wof:placetype":"locality",
    "wof:population":31
},
  "geometry": {"coordinates":[13.72853,48.17874000000001],"type":"Point"}
}