{
  "type": "Feature",
  "properties": {
    "gn:admin1_code":"6.0",
    "gn:admin2_code":"603",
    "gn:admin3_code":"60305.0",
    "gn:asciiname":"Lassnitz",
    "gn:country_code":"AT",
    "gn:dem":341,
    "gn:feature_class":"P",
    "gn:feature_code":"PPL",
    "gn:name":"Lassnitz",
    "gn:population":966,
    "gn:timezone":"Europe/Vienna",
    "iso:country":"AT",
    "name:und_x_variant":[
        "La\u00dfnitz",
        "Lassnitz"
    ],
    "wof:name":"Lassnitz",
    "wof:placetype":"locality",
    "wof:population":966
},
  "geometry": {"coordinates":[15.25,46.81667],"type":"Point"}
}