{
  "type": "Feature",
  "properties": {
    "gn:admin1_code":"3.0",
    "gn:admin2_code":"315",
    "gn:admin3_code":"31551.0",
    "gn:asciiname":"Hinterleiten",
    "gn:country_code":"AT",
    "gn:dem":463,
    "gn:feature_class":"P",
    "gn:feature_code":"PPLL",
    "gn:name":"Hinterleiten",
    "gn:population":18,
    "gn:timezone":"Europe/Vienna",
    "iso:country":"AT",
    "wof:name":"Hinterleiten",
    "wof:placetype":"locality",
    "wof:population":18
},
  "geometry": {"coordinates":[15.3455,48.0494],"type":"Point"}
}