{
  "type": "Feature",
  "properties": {
    "gn:admin1_code":"02",
    "gn:admin2_code":"204.0",
    "gn:admin3_code":"20409.0",
    "gn:asciiname":"Sankt Johann",
    "gn:country_code":"AT",
    "gn:dem":443,
    "gn:feature_class":"P",
    "gn:feature_code":"PPL",
    "gn:name":"Sankt Johann",
    "gn:population":0,
    "gn:timezone":"Europe/Vienna",
    "iso:country":"AT",
    "wof:name":"Sankt Johann",
    "wof:placetype":"locality"
},
  "geometry": {"coordinates":[14.46771,46.64546],"type":"Point"}
}