{
  "type": "Feature",
  "properties": {
    "gn:admin1_code":"8.0",
    "gn:admin2_code":"804",
    "gn:admin3_code":"80404.0",
    "gn:asciiname":"Levis",
    "gn:country_code":"AT",
    "gn:dem":450,
    "gn:feature_class":"P",
    "gn:feature_code":"PPL",
    "gn:name":"Levis",
    "gn:population":0,
    "gn:timezone":"Europe/Vienna",
    "iso:country":"AT",
    "name:cat_x_preferred":[
        "Levis"
    ],
    "name:ceb_x_preferred":[
        "Levis"
    ],
    "name:deu_x_preferred":[
        "Levis"
    ],
    "name:hye_x_preferred":[
        "\u053c\u0587\u056b\u057d"
    ],
    "name:ita_x_preferred":[
        "Levis"
    ],
    "name:lit_x_preferred":[
        "Levis"
    ],
    "name:nld_x_preferred":[
        "Levis"
    ],
    "name:oci_x_preferred":[
        "Levis"
    ],
    "name:rus_x_preferred":[
        "\u041b\u0435\u0432\u0438\u0441"
    ],
    "name:spa_x_preferred":[
        "Levis"
    ],
    "name:swe_x_preferred":[
        "Levis"
    ],
    "name:war_x_preferred":[
        "Levis"
    ],
    "wof:name":"Levis",
    "wof:placetype":"locality"
},
  "geometry": {"coordinates":[9.60926,47.2483],"type":"Point"}
}