{
  "type": "Feature",
  "properties": {
    "gn:admin1_code":"8.0",
    "gn:admin2_code":"804",
    "gn:admin3_code":"80404.0",
    "gn:asciiname":"Levis",
    "gn:country_code":"AT",
    "gn:dem":450,
    "gn:feature_class":"P",
    "gn:feature_code":"PPL",
    "gn:name":"Levis",
    "gn:population":0,
    "gn:timezone":"Europe/Vienna",
    "iso:country":"AT",
    "wof:name":"Levis",
    "wof:placetype":"locality"
},
  "geometry": {"coordinates":[9.60926,47.2483],"type":"Point"}
}