{
  "type": "Feature",
  "properties": {
    "iso:country":"AT",
    "name:deu_x_preferred":[
        "Gries"
    ],
    "name:eng_x_preferred":[
        "Gries"
    ],
    "wof:name":"Gries",
    "wof:placetype":"neighbourhood"
},
  "geometry": {"coordinates":[15.42716235250327,47.06291035624034],"type":"Point"}
}