{
  "type": "Feature",
  "properties": {
    "gn:admin1_code":"2.0",
    "gn:admin2_code":"205",
    "gn:admin3_code":"20513.0",
    "gn:asciiname":"Dulberg",
    "gn:country_code":"AT",
    "gn:dem":959,
    "gn:feature_class":"P",
    "gn:feature_code":"PPL",
    "gn:name":"Dulberg",
    "gn:population":0,
    "gn:timezone":"Europe/Vienna",
    "iso:country":"AT",
    "wof:name":"Dulberg",
    "wof:placetype":"locality"
},
  "geometry": {"coordinates":[14.55,46.85],"type":"Point"}
}