{
  "type": "Feature",
  "properties": {
    "gn:admin1_code":"06",
    "gn:admin2_code":"606.0",
    "gn:admin3_code":"60642.0",
    "gn:asciiname":"Rinnegg",
    "gn:country_code":"AT",
    "gn:dem":679,
    "gn:feature_class":"P",
    "gn:feature_code":"PPL",
    "gn:name":"Rinnegg",
    "gn:population":541,
    "gn:timezone":"Europe/Vienna",
    "iso:country":"AT",
    "name:und_x_variant":[
        "Rinegg"
    ],
    "wof:name":"Rinnegg",
    "wof:placetype":"locality",
    "wof:population":541
},
  "geometry": {"coordinates":[15.48809,47.16196],"type":"Point"}
}