{
  "type": "Feature",
  "properties": {
    "gn:admin1_code":"2.0",
    "gn:admin2_code":"203",
    "gn:admin3_code":"20321.0",
    "gn:asciiname":"Mattling",
    "gn:country_code":"AT",
    "gn:dem":1144,
    "gn:feature_class":"P",
    "gn:feature_code":"PPL",
    "gn:name":"Mattling",
    "gn:population":20,
    "gn:timezone":"Europe/Vienna",
    "iso:country":"AT",
    "wof:name":"Mattling",
    "wof:placetype":"locality",
    "wof:population":20
},
  "geometry": {"coordinates":[12.86833,46.68806],"type":"Point"}
}