{
  "type": "Feature",
  "properties": {
    "gn:admin1_code":"8.0",
    "gn:admin2_code":"801",
    "gn:admin3_code":"80120.0",
    "gn:asciiname":"Aussersiggam",
    "gn:country_code":"AT",
    "gn:dem":908,
    "gn:feature_class":"P",
    "gn:feature_code":"PPL",
    "gn:name":"Aussersiggam",
    "gn:population":0,
    "gn:timezone":"Europe/Vienna",
    "iso:country":"AT",
    "wof:name":"Aussersiggam",
    "wof:placetype":"locality"
},
  "geometry": {"coordinates":[9.97331,47.02366],"type":"Point"}
}