{
  "type": "Feature",
  "properties": {
    "gn:admin1_code":"4.0",
    "gn:admin2_code":"406",
    "gn:admin3_code":"40627.0",
    "gn:asciiname":"Erdleiten",
    "gn:country_code":"AT",
    "gn:dem":598,
    "gn:feature_class":"P",
    "gn:feature_code":"PPL",
    "gn:name":"Erdleiten",
    "gn:population":141,
    "gn:timezone":"Europe/Vienna",
    "iso:country":"AT",
    "wof:name":"Erdleiten",
    "wof:placetype":"locality",
    "wof:population":141
},
  "geometry": {"coordinates":[14.63333,48.36667],"type":"Point"}
}