{
  "type": "Feature",
  "properties": {
    "gn:gn_country":"AT",
    "gn:gn_fcode":"PPL",
    "gn:gn_pop":0,
    "iso:country":"AT",
    "name:ceb_x_preferred":[
        "Nu\u00dfdorf am Attersee"
    ],
    "name:deu_x_preferred":[
        "Nu\u00dfdorf am Attersee"
    ],
    "name:eng_x_preferred":[
        "Nu\u00dfdorf am Attersee"
    ],
    "name:fas_x_preferred":[
        "\u0646\u0648\u0633\u062f\u0648\u0631\u0641 \u0627\u0645 \u0627\u062a\u0631\u0632\u06cc"
    ],
    "name:fra_x_preferred":[
        "Nu\u00dfdorf am Attersee"
    ],
    "name:hun_x_preferred":[
        "Nu\u00dfdorf am Attersee"
    ],
    "name:ita_x_preferred":[
        "Nu\u00dfdorf am Attersee"
    ],
    "name:kaz_x_preferred":[
        "\u041d\u0443\u0441\u0434\u043e\u0440\u0444-\u0430\u043c-\u0410\u0442\u0442\u0435\u0440\u0437\u0435\u0435"
    ],
    "name:nld_x_preferred":[
        "Nu\u00dfdorf am Attersee"
    ],
    "name:pol_x_preferred":[
        "Nu\u00dfdorf am Attersee"
    ],
    "name:por_x_preferred":[
        "Nu\u00dfdorf am Attersee"
    ],
    "name:rus_x_preferred":[
        "\u041d\u0443\u0441\u0434\u043e\u0440\u0444-\u0430\u043c-\u0410\u0442\u0442\u0435\u0440\u0437\u0435\u0435"
    ],
    "name:slk_x_preferred":[
        "Nu\u00dfdorf am Attersee"
    ],
    "name:spa_x_preferred":[
        "Nu\u00dfdorf am Attersee"
    ],
    "name:swe_x_preferred":[
        "Nu\u00dfdorf am Attersee"
    ],
    "name:unk_x_variant":[
        "Nussdorf"
    ],
    "name:uzb_x_preferred":[
        "Nu\u00dfdorf am Attersee"
    ],
    "name:vie_x_preferred":[
        "Nu\u00dfdorf am Attersee"
    ],
    "name:vol_x_preferred":[
        "Nu\u00dfdorf am Attersee"
    ],
    "name:war_x_preferred":[
        "Nu\u00dfdorf am Attersee"
    ],
    "name:zho_x_preferred":[
        "\u963f\u7279\u6e56\u7554\u52aa\u65af\u591a\u592b"
    ],
    "qs_pg:aaroncc":"AT",
    "qs_pg:gn_country":"AT",
    "qs_pg:gn_fcode":"PPL",
    "qs_pg:gn_pop":0,
    "qs_pg:name":"Nu\u00dfdorf am Attersee",
    "qs_pg:name_adm0":"\u00d6sterreich",
    "qs_pg:name_adm1":"Ober\u00f6sterreich",
    "qs_pg:photos":30,
    "qs_pg:photos_1k":6,
    "qs_pg:photos_9k":1,
    "qs_pg:photos_9r":2,
    "qs_pg:photos_all":30,
    "qs_pg:photos_sr":2,
    "qs_pg:pop_sr":0,
    "qs_pg:qs_pg_placetype":"locality",
    "qs_pg:qs_pg_placetype_gp":"Town",
    "qs_pg:woe_adm0":23424750,
    "woe:adm0_id":23424750,
    "woe:name_adm0":"\u00d6sterreich",
    "woe:name_adm1":"Ober\u00f6sterreich",
    "woe:placetype":"Town",
    "wof:name":"Nu\u00dfdorf am Attersee",
    "wof:placetype":"locality"
},
  "geometry": {"coordinates":[13.51667,47.88333],"type":"Point"}
}