{
  "type": "Feature",
  "properties": {
    "gn:admin1_code":"3.0",
    "gn:admin2_code":"309",
    "gn:admin3_code":"30925.0",
    "gn:asciiname":"Kibitzhauser",
    "gn:country_code":"AT",
    "gn:dem":556,
    "gn:feature_class":"P",
    "gn:feature_code":"PPL",
    "gn:name":"Kibitzh\u00e4user",
    "gn:population":0,
    "gn:timezone":"Europe/Vienna",
    "iso:country":"AT",
    "wof:name":"Kibitzhauser",
    "wof:placetype":"locality"
},
  "geometry": {"coordinates":[15.05,48.93333],"type":"Point"}
}