{
  "type": "Feature",
  "properties": {
    "gn:admin1_code":"06",
    "gn:admin2_code":"617.0",
    "gn:admin3_code":"61746.0",
    "gn:asciiname":"Sommerberg",
    "gn:country_code":"AT",
    "gn:dem":421,
    "gn:feature_class":"P",
    "gn:feature_code":"PPL",
    "gn:name":"Sommerberg",
    "gn:population":0,
    "gn:timezone":"Europe/Vienna",
    "iso:country":"AT",
    "wof:name":"Sommerberg",
    "wof:placetype":"locality"
},
  "geometry": {"coordinates":[15.78333,47.05],"type":"Point"}
}