{
  "type": "Feature",
  "properties": {
    "gn:admin1_code":"4.0",
    "gn:admin2_code":"408",
    "gn:admin3_code":"40809.0",
    "gn:asciiname":"Gotthaming",
    "gn:country_code":"AT",
    "gn:dem":448,
    "gn:feature_class":"P",
    "gn:feature_code":"PPL",
    "gn:name":"Gotthaming",
    "gn:population":29,
    "gn:timezone":"Europe/Vienna",
    "iso:country":"AT",
    "wof:name":"Gotthaming",
    "wof:placetype":"locality",
    "wof:population":29
},
  "geometry": {"coordinates":[13.63742,48.21086],"type":"Point"}
}