{
  "type": "Feature",
  "properties": {
    "gn:country":"AT",
    "gn:fcode":"PPL",
    "gn:population":0,
    "iso:country":"AT",
    "name:ceb_x_preferred":[
        "Oberloisdorf"
    ],
    "name:deu_x_preferred":[
        "Oberloisdorf"
    ],
    "name:epo_x_preferred":[
        "Oberloisdorf"
    ],
    "name:fas_x_preferred":[
        "\u0627\u0648\u0628\u0631\u0644\u0648\u0627\u0633\u062f\u0648\u0631\u0641"
    ],
    "name:fra_x_preferred":[
        "Oberloisdorf"
    ],
    "name:hrv_x_preferred":[
        "Nadrlo\u0161trof"
    ],
    "name:hun_x_preferred":[
        "Fels\u0151l\u00e1szl\u00f3"
    ],
    "name:ita_x_preferred":[
        "Oberloisdorf"
    ],
    "name:kaz_x_preferred":[
        "\u041e\u0431\u0435\u0440\u043b\u043e\u0439\u0441\u0434\u043e\u0440\u0444"
    ],
    "name:nld_x_preferred":[
        "Oberloisdorf"
    ],
    "name:pol_x_preferred":[
        "Oberloisdorf"
    ],
    "name:por_x_preferred":[
        "Oberloisdorf"
    ],
    "name:rus_x_preferred":[
        "\u041e\u0431\u0435\u0440\u043b\u043e\u0439\u0441\u0434\u043e\u0440\u0444"
    ],
    "name:slk_x_preferred":[
        "Oberloisdorf"
    ],
    "name:spa_x_preferred":[
        "Oberloisdorf"
    ],
    "name:swe_x_preferred":[
        "Oberloisdorf"
    ],
    "name:ukr_x_preferred":[
        "\u041e\u0431\u0435\u0440\u043b\u043e\u0439\u0441\u0434\u043e\u0440\u0444"
    ],
    "name:uzb_x_preferred":[
        "Oberloisdorf"
    ],
    "name:vol_x_preferred":[
        "Oberloisdorf"
    ],
    "name:war_x_preferred":[
        "Oberloisdorf"
    ],
    "name:zho_x_preferred":[
        "\u4e0a\u6d1b\u4f0a\u65af\u591a\u592b"
    ],
    "qs_pg:aaroncc":"AT",
    "qs_pg:gn_country":"AT",
    "qs_pg:gn_fcode":"PPL",
    "qs_pg:gn_pop":0,
    "qs_pg:name":"Oberloisdorf",
    "qs_pg:name_adm0":"\u00d6sterreich",
    "qs_pg:name_adm1":"Burgenland",
    "qs_pg:photos_9r":0,
    "qs_pg:photos_sr":0,
    "qs_pg:pop_sr":0,
    "qs_pg:qs_pg_placetype":"locality",
    "qs_pg:qs_pg_placetype_gp":"Town",
    "qs_pg:woe_adm0":23424750,
    "woe:adm0_id":23424750,
    "woe:name_adm0":"\u00d6sterreich",
    "woe:name_adm1":"Burgenland",
    "woe:placetype":"Town",
    "wof:name":"Oberloisdorf",
    "wof:placetype":"locality"
},
  "geometry": {"coordinates":[16.51667,48.36667],"type":"Point"}
}