{
  "type": "Feature",
  "properties": {
    "gn:admin1_code":"6.0",
    "gn:admin2_code":"620",
    "gn:admin3_code":"62034.0",
    "gn:asciiname":"Duernberg",
    "gn:country_code":"AT",
    "gn:dem":911,
    "gn:feature_class":"P",
    "gn:feature_code":"PPL",
    "gn:name":"D\u00fcrnberg",
    "gn:population":187,
    "gn:timezone":"Europe/Vienna",
    "iso:country":"AT",
    "wof:name":"Duernberg",
    "wof:placetype":"locality",
    "wof:population":187
},
  "geometry": {"coordinates":[14.78333,47.28333],"type":"Point"}
}