{
  "type": "Feature",
  "properties": {
    "gn:admin1_code":"6.0",
    "gn:admin2_code":"612",
    "gn:admin3_code":"61206.0",
    "gn:asciiname":"Frauenberg",
    "gn:cc2":"AT",
    "gn:country_code":"AT",
    "gn:dem":624,
    "gn:feature_class":"P",
    "gn:feature_code":"PPL",
    "gn:name":"Frauenberg",
    "gn:population":290,
    "gn:timezone":"Europe/Vienna",
    "iso:country":"AT",
    "name:rus_x_preferred":[
        "\u0420\u043e\u043c\u0440\u043e\u0434"
    ],
    "name:und_x_variant":[
        "Frauenberg bei Admont",
        "Frauenberg"
    ],
    "wof:name":"Frauenberg",
    "wof:placetype":"locality",
    "wof:population":290
},
  "geometry": {"coordinates":[14.38333,47.58333],"type":"Point"}
}