{
  "type": "Feature",
  "properties": {
    "gn:admin1_code":"3.0",
    "gn:admin2_code":"321",
    "gn:admin3_code":"32104.0",
    "gn:asciiname":"Ebersdorf",
    "gn:country_code":"AT",
    "gn:dem":195,
    "gn:feature_class":"P",
    "gn:feature_code":"PPL",
    "gn:name":"Ebersdorf",
    "gn:population":59,
    "gn:timezone":"Europe/Vienna",
    "iso:country":"AT",
    "name:ceb_x_preferred":[
        "Ebersdorf"
    ],
    "name:deu_x_preferred":[
        "Ebersdorf"
    ],
    "name:epo_x_preferred":[
        "Ebersdorf"
    ],
    "name:fra_x_preferred":[
        "Ebersdorf"
    ],
    "name:ita_x_preferred":[
        "Ebersdorf"
    ],
    "name:jpn_x_preferred":[
        "\u30a8\u30fc\u30d0\u30fc\u30b9\u30c9\u30eb\u30d5"
    ],
    "name:kaz_x_preferred":[
        "\u042d\u0431\u0435\u0440\u0441\u0434\u043e\u0440\u0444"
    ],
    "name:nld_x_preferred":[
        "Ebersdorf"
    ],
    "name:pol_x_preferred":[
        "Ebersdorf"
    ],
    "name:rus_x_preferred":[
        "\u042d\u0431\u0435\u0440\u0441\u0434\u043e\u0440\u0444"
    ],
    "name:srp_x_preferred":[
        "\u0415\u0431\u0435\u0440\u0441\u0434\u043e\u0440\u0444"
    ],
    "name:swe_x_preferred":[
        "Ebersdorf"
    ],
    "name:vol_x_preferred":[
        "Ebersdorf"
    ],
    "wof:name":"Ebersdorf",
    "wof:placetype":"locality",
    "wof:population":59
},
  "geometry": {"coordinates":[15.8634,48.28399],"type":"Point"}
}