{
  "type": "Feature",
  "properties": {
    "gn:admin1_code":"3.0",
    "gn:admin2_code":"321",
    "gn:admin3_code":"32104.0",
    "gn:asciiname":"Ebersdorf",
    "gn:country_code":"AT",
    "gn:dem":195,
    "gn:feature_class":"P",
    "gn:feature_code":"PPL",
    "gn:name":"Ebersdorf",
    "gn:population":59,
    "gn:timezone":"Europe/Vienna",
    "iso:country":"AT",
    "wof:name":"Ebersdorf",
    "wof:placetype":"locality",
    "wof:population":59
},
  "geometry": {"coordinates":[15.8634,48.28399],"type":"Point"}
}