{
  "type": "Feature",
  "properties": {
    "gn:admin1_code":"03",
    "gn:admin2_code":"323.0",
    "gn:admin3_code":"32317.0",
    "gn:asciiname":"Thal",
    "gn:country_code":"AT",
    "gn:dem":677,
    "gn:feature_class":"P",
    "gn:feature_code":"PPL",
    "gn:name":"Thal",
    "gn:population":90,
    "gn:timezone":"Europe/Vienna",
    "iso:country":"AT",
    "name:als_x_preferred":[
        "Thal"
    ],
    "name:ceb_x_preferred":[
        "Thal"
    ],
    "name:deu_x_preferred":[
        "Thal"
    ],
    "name:epo_x_preferred":[
        "Thal"
    ],
    "name:fra_x_preferred":[
        "Thal"
    ],
    "name:ita_x_preferred":[
        "Thal"
    ],
    "name:nld_x_preferred":[
        "Thal"
    ],
    "name:pol_x_preferred":[
        "Thal"
    ],
    "name:spa_x_preferred":[
        "Thal"
    ],
    "name:swe_x_preferred":[
        "Thal"
    ],
    "name:vol_x_preferred":[
        "Thal"
    ],
    "wof:name":"Thal",
    "wof:placetype":"locality",
    "wof:population":90
},
  "geometry": {"coordinates":[16.25,47.55],"type":"Point"}
}