{
  "type": "Feature",
  "properties": {
    "gn:admin1_code":"04",
    "gn:admin2_code":"405.0",
    "gn:admin3_code":"40512.0",
    "gn:asciiname":"Woegern",
    "gn:country_code":"AT",
    "gn:dem":523,
    "gn:feature_class":"P",
    "gn:feature_code":"PPL",
    "gn:name":"W\u00f6gern",
    "gn:population":82,
    "gn:timezone":"Europe/Vienna",
    "iso:country":"AT",
    "wof:name":"Woegern",
    "wof:placetype":"locality",
    "wof:population":82
},
  "geometry": {"coordinates":[13.95,48.36667],"type":"Point"}
}