{
  "type": "Feature",
  "properties": {
    "gn:admin1_code":"5.0",
    "gn:admin2_code":"503",
    "gn:admin3_code":"50304.0",
    "gn:asciiname":"Unter-Hopfling",
    "gn:country_code":"AT",
    "gn:dem":585,
    "gn:feature_class":"P",
    "gn:feature_code":"PPL",
    "gn:name":"Unter-H\u00f6pfling",
    "gn:population":0,
    "gn:timezone":"Europe/Vienna",
    "iso:country":"AT",
    "wof:name":"Unter-Hopfling",
    "wof:placetype":"locality"
},
  "geometry": {"coordinates":[13.05333,47.99417],"type":"Point"}
}