{
  "type": "Feature",
  "properties": {
    "gn:admin1_code":"06",
    "gn:admin2_code":"610.0",
    "gn:admin3_code":"61027.0",
    "gn:asciiname":"Oedt",
    "gn:country_code":"AT",
    "gn:dem":284,
    "gn:feature_class":"P",
    "gn:feature_code":"PPL",
    "gn:name":"Oedt",
    "gn:population":182,
    "gn:timezone":"Europe/Vienna",
    "iso:country":"AT",
    "wof:name":"Oedt",
    "wof:placetype":"locality",
    "wof:population":182
},
  "geometry": {"coordinates":[15.55,46.85],"type":"Point"}
}