{
  "type": "Feature",
  "properties": {
    "gn:admin1_code":"2.0",
    "gn:admin2_code":"207",
    "gn:admin3_code":"20723.0",
    "gn:asciiname":"Drussnitz",
    "gn:country_code":"AT",
    "gn:dem":1568,
    "gn:feature_class":"P",
    "gn:feature_code":"PPL",
    "gn:name":"Drussnitz",
    "gn:population":0,
    "gn:timezone":"Europe/Vienna",
    "iso:country":"AT",
    "wof:name":"Drussnitz",
    "wof:placetype":"locality"
},
  "geometry": {"coordinates":[13.51889,46.74611],"type":"Point"}
}