{
  "type": "Feature",
  "properties": {
    "gn:admin1_code":"3.0",
    "gn:admin2_code":"325",
    "gn:admin3_code":"32502.0",
    "gn:asciiname":"Grossschonberg",
    "gn:cc2":"AT",
    "gn:country_code":"AT",
    "gn:dem":970,
    "gn:feature_class":"P",
    "gn:feature_code":"PPL",
    "gn:name":"Grosssch\u00f6nberg",
    "gn:population":0,
    "gn:timezone":"Europe/Vienna",
    "iso:country":"AT",
    "name:und_x_variant":[
        "Sch\u00f6nberg",
        "Grosssch\u00f6nberg"
    ],
    "wof:name":"Grossschonberg",
    "wof:placetype":"locality"
},
  "geometry": {"coordinates":[14.88333,48.46667],"type":"Point"}
}