{
  "type": "Feature",
  "properties": {
    "gn:admin1_code":"3.0",
    "gn:admin2_code":"319",
    "gn:admin3_code":"31927.0",
    "gn:asciiname":"Oberkuehberg",
    "gn:country_code":"AT",
    "gn:dem":444,
    "gn:feature_class":"P",
    "gn:feature_code":"PPL",
    "gn:name":"Oberk\u00fchberg",
    "gn:population":42,
    "gn:timezone":"Europe/Vienna",
    "iso:country":"AT",
    "wof:name":"Oberkuehberg",
    "wof:placetype":"locality",
    "wof:population":42
},
  "geometry": {"coordinates":[15.8816,48.12772],"type":"Point"}
}