{
  "type": "Feature",
  "properties": {
    "gn:admin1_code":"5.0",
    "gn:admin2_code":"506",
    "gn:admin3_code":"50620.0",
    "gn:asciiname":"Gumping",
    "gn:country_code":"AT",
    "gn:dem":629,
    "gn:feature_class":"P",
    "gn:feature_code":"PPL",
    "gn:name":"Gumping",
    "gn:population":53,
    "gn:timezone":"Europe/Vienna",
    "iso:country":"AT",
    "wof:name":"Gumping",
    "wof:placetype":"locality",
    "wof:population":53
},
  "geometry": {"coordinates":[12.69917,47.57994],"type":"Point"}
}