{
  "type": "Feature",
  "properties": {
    "gn:admin1_code":"03",
    "gn:admin2_code":"325.0",
    "gn:admin3_code":"32528.0",
    "gn:asciiname":"Prettlers",
    "gn:country_code":"AT",
    "gn:dem":878,
    "gn:feature_class":"P",
    "gn:feature_code":"PPL",
    "gn:name":"Prettlers",
    "gn:population":0,
    "gn:timezone":"Europe/Vienna",
    "iso:country":"AT",
    "wof:name":"Prettlers",
    "wof:placetype":"locality"
},
  "geometry": {"coordinates":[15.08333,48.41667],"type":"Point"}
}