{
  "type": "Feature",
  "properties": {
    "gn:admin1_code":"3.0",
    "gn:admin2_code":"320",
    "gn:admin3_code":"32005.0",
    "gn:asciiname":"Ahorn",
    "gn:country_code":"AT",
    "gn:dem":901,
    "gn:feature_class":"P",
    "gn:feature_code":"PPL",
    "gn:name":"Ahorn",
    "gn:population":0,
    "gn:timezone":"Europe/Vienna",
    "iso:country":"AT",
    "name:als_x_preferred":[
        "Ahorn"
    ],
    "name:ceb_x_preferred":[
        "Ahorn"
    ],
    "name:ces_x_preferred":[
        "Ahorn"
    ],
    "name:deu_x_preferred":[
        "Ahorn"
    ],
    "name:epo_x_preferred":[
        "Ahorn"
    ],
    "name:eus_x_preferred":[
        "Ahorn"
    ],
    "name:fra_x_preferred":[
        "Ahorn"
    ],
    "name:hun_x_preferred":[
        "Ahorn"
    ],
    "name:ita_x_preferred":[
        "Ahorn"
    ],
    "name:jpn_x_preferred":[
        "\u30a2\u30db\u30eb\u30f3"
    ],
    "name:lmo_x_preferred":[
        "Ahorn"
    ],
    "name:nld_x_preferred":[
        "Ahorn"
    ],
    "name:pms_x_preferred":[
        "Ahorn"
    ],
    "name:pol_x_preferred":[
        "Ahorn"
    ],
    "name:por_x_preferred":[
        "Ahorn"
    ],
    "name:rus_x_preferred":[
        "\u0410\u0445\u043e\u0440\u043d"
    ],
    "name:srp_x_preferred":[
        "\u0410\u0445\u043e\u0440\u043d"
    ],
    "name:swe_x_preferred":[
        "Ahorn"
    ],
    "name:vol_x_preferred":[
        "Ahorn"
    ],
    "wof:name":"Ahorn",
    "wof:placetype":"locality"
},
  "geometry": {"coordinates":[14.96667,47.85],"type":"Point"}
}