{
  "type": "Feature",
  "properties": {
    "gn:admin1_code":"3.0",
    "gn:admin2_code":"320",
    "gn:admin3_code":"32005.0",
    "gn:asciiname":"Ahorn",
    "gn:country_code":"AT",
    "gn:dem":901,
    "gn:feature_class":"P",
    "gn:feature_code":"PPL",
    "gn:name":"Ahorn",
    "gn:population":0,
    "gn:timezone":"Europe/Vienna",
    "iso:country":"AT",
    "wof:name":"Ahorn",
    "wof:placetype":"locality"
},
  "geometry": {"coordinates":[14.96667,47.85],"type":"Point"}
}