{
  "type": "Feature",
  "properties": {
    "gn:admin1_code":"4.0",
    "gn:admin2_code":"414",
    "gn:admin3_code":"41409.0",
    "gn:asciiname":"Rauhegg",
    "gn:country_code":"AT",
    "gn:dem":495,
    "gn:feature_class":"P",
    "gn:feature_code":"PPL",
    "gn:name":"Rauhegg",
    "gn:population":0,
    "gn:timezone":"Europe/Vienna",
    "iso:country":"AT",
    "wof:name":"Rauhegg",
    "wof:placetype":"locality"
},
  "geometry": {"coordinates":[13.61944,48.54556],"type":"Point"}
}