{
  "type": "Feature",
  "properties": {
    "gn:admin1_code":"03",
    "gn:admin2_code":"309.0",
    "gn:admin3_code":"30909.0",
    "gn:asciiname":"Reinpolz",
    "gn:country_code":"AT",
    "gn:dem":585,
    "gn:feature_class":"P",
    "gn:feature_code":"PPL",
    "gn:name":"Reinpolz",
    "gn:population":49,
    "gn:timezone":"Europe/Vienna",
    "iso:country":"AT",
    "wof:name":"Reinpolz",
    "wof:placetype":"locality",
    "wof:population":49
},
  "geometry": {"coordinates":[14.85,48.76667],"type":"Point"}
}