{
  "type": "Feature",
  "properties": {
    "iso:country":"AT",
    "name:bar_x_preferred":[
        "Traunkircha"
    ],
    "name:ceb_x_preferred":[
        "Traunkirchen"
    ],
    "name:deu_x_preferred":[
        "Traunkirchen"
    ],
    "name:eng_x_preferred":[
        "Traunkirchen"
    ],
    "name:fas_x_preferred":[
        "\u062a\u0631\u0648\u0646\u06a9\u06cc\u0631\u0634\u0646"
    ],
    "name:fra_x_preferred":[
        "Traunkirchen"
    ],
    "name:fur_x_preferred":[
        "Traunkirchen"
    ],
    "name:hun_x_preferred":[
        "Traunkirchen"
    ],
    "name:ita_x_preferred":[
        "Traunkirchen"
    ],
    "name:kaz_x_preferred":[
        "\u0422\u0440\u0430\u0443\u043d\u043a\u0438\u0440\u0445\u0435\u043d"
    ],
    "name:nld_x_preferred":[
        "Traunkirchen"
    ],
    "name:pol_x_preferred":[
        "Traunkirchen"
    ],
    "name:por_x_preferred":[
        "Traunkirchen"
    ],
    "name:rus_x_preferred":[
        "\u0422\u0440\u0430\u0443\u043d\u043a\u0438\u0440\u0445\u0435\u043d"
    ],
    "name:slk_x_preferred":[
        "Traunkirchen"
    ],
    "name:spa_x_preferred":[
        "Traunkirchen"
    ],
    "name:swe_x_preferred":[
        "Traunkirchen"
    ],
    "name:ukr_x_preferred":[
        "\u0422\u0440\u0430\u0443\u043d\u043a\u0456\u0440\u0445\u0435\u043d"
    ],
    "name:uzb_x_preferred":[
        "Traunkirchen"
    ],
    "name:vie_x_preferred":[
        "Traunkirchen"
    ],
    "name:vol_x_preferred":[
        "Traunkirchen"
    ],
    "name:war_x_preferred":[
        "Traunkirchen"
    ],
    "name:zho_x_preferred":[
        "\u7279\u52b3\u6069\u57fa\u5174"
    ],
    "qs:a0":"\u00d6sterreich",
    "qs:a1":"*Ober\u00f6sterreich",
    "qs:a1r":"0",
    "qs:a2":"Gmunden",
    "qs:adm0":"\u00d6sterreich",
    "qs:la_lc":"*",
    "qs:level":"locality",
    "qs:loc":"Traunkirchen",
    "qs:loc_alt":"Traunkirchen",
    "qs:pop":0,
    "qs:type":"buffered point",
    "wd:wordcount":65,
    "wof:name":"Traunkirchen",
    "wof:placetype":"locality"
},
  "geometry": {"coordinates":[13.785123,47.843289],"type":"Point"}
}