{
  "type": "Feature",
  "properties": {
    "gn:admin1_code":"6.0",
    "gn:admin2_code":"610",
    "gn:admin3_code":"61008.0",
    "gn:asciiname":"Neudorf an der Mur",
    "gn:cc2":"AT",
    "gn:country_code":"AT",
    "gn:dem":287,
    "gn:feature_class":"P",
    "gn:feature_code":"PPL",
    "gn:name":"Neudorf an der Mur",
    "gn:population":342,
    "gn:timezone":"Europe/Vienna",
    "iso:country":"AT",
    "name:und_x_variant":[
        "Neudorf",
        "Neudorf an der Mur"
    ],
    "wof:name":"Neudorf an der Mur",
    "wof:placetype":"locality",
    "wof:population":342
},
  "geometry": {"coordinates":[15.595,46.79194],"type":"Point"}
}