{
  "type": "Feature",
  "properties": {
    "gn:admin1_code":"7.0",
    "gn:admin2_code":"704",
    "gn:admin3_code":"70406.0",
    "gn:asciiname":"Penningberg",
    "gn:country_code":"AT",
    "gn:dem":937,
    "gn:feature_class":"P",
    "gn:feature_code":"PPL",
    "gn:name":"Penningberg",
    "gn:population":900,
    "gn:timezone":"Europe/Vienna",
    "iso:country":"AT",
    "wof:name":"Penningberg",
    "wof:placetype":"locality",
    "wof:population":900
},
  "geometry": {"coordinates":[12.12543,47.42196],"type":"Point"}
}