{
  "type": "Feature",
  "properties": {
    "gn:admin1_code":"6.0",
    "gn:admin2_code":"603",
    "gn:admin3_code":"60344.0",
    "gn:asciiname":"Furth",
    "gn:country_code":"AT",
    "gn:dem":370,
    "gn:feature_class":"P",
    "gn:feature_code":"PPL",
    "gn:name":"Furth",
    "gn:population":130,
    "gn:timezone":"Europe/Vienna",
    "iso:country":"AT",
    "name:cat_x_preferred":[
        "Furth"
    ],
    "name:ceb_x_preferred":[
        "Furth"
    ],
    "name:deu_x_preferred":[
        "Furth"
    ],
    "name:epo_x_preferred":[
        "Furth"
    ],
    "name:fra_x_preferred":[
        "Furth"
    ],
    "name:ita_x_preferred":[
        "Furth"
    ],
    "name:nld_x_preferred":[
        "Furth"
    ],
    "name:pol_x_preferred":[
        "Furth"
    ],
    "name:rus_x_preferred":[
        "\u0424\u0443\u0440\u0442"
    ],
    "name:srp_x_preferred":[
        "\u0424\u0443\u0440\u0442"
    ],
    "name:swe_x_preferred":[
        "Furth"
    ],
    "wof:name":"Furth",
    "wof:placetype":"locality",
    "wof:population":130
},
  "geometry": {"coordinates":[15.23333,46.85],"type":"Point"}
}