{
  "type": "Feature",
  "properties": {
    "iso:country":"AT",
    "name:ceb_x_preferred":[
        "Brixen im Thale"
    ],
    "name:ces_x_preferred":[
        "Brixen im Thale"
    ],
    "name:deu_x_preferred":[
        "Brixen im Thale"
    ],
    "name:eng_x_preferred":[
        "Brixen im Thale"
    ],
    "name:est_x_preferred":[
        "Brixen im Thale"
    ],
    "name:fas_x_preferred":[
        "\u0628\u0631\u06cc\u06a9\u0633\u0646 \u0627\u06cc\u0645 \u062a\u0627\u0644\u0647"
    ],
    "name:fra_x_preferred":[
        "Brixen im Thale"
    ],
    "name:heb_x_preferred":[
        "\u05d1\u05e8\u05d9\u05e7\u05e1\u05df \u05d0\u05dd \u05d8\u05d0\u05dc\u05d4"
    ],
    "name:hun_x_preferred":[
        "Brixen im Thale"
    ],
    "name:ita_x_preferred":[
        "Brixen im Thale"
    ],
    "name:jpn_x_preferred":[
        "\u30d6\u30ea\u30af\u30bb\u30f3\u30fb\u30a4\u30e0\u30fb\u30bf\u30fc\u30ec"
    ],
    "name:kaz_x_preferred":[
        "\u0411\u0440\u0438\u043a\u0441\u0435\u043d-\u0438\u043c-\u0422\u0430\u043b\u0435"
    ],
    "name:lmo_x_preferred":[
        "Brixen im Thale"
    ],
    "name:nld_x_preferred":[
        "Brixen im Thale"
    ],
    "name:nno_x_preferred":[
        "Brixen im Thale"
    ],
    "name:nob_x_preferred":[
        "Brixen im Thale"
    ],
    "name:pol_x_preferred":[
        "Brixen im Thale"
    ],
    "name:ron_x_preferred":[
        "Brixen im Thale"
    ],
    "name:rus_x_preferred":[
        "\u0411\u0440\u0438\u043a\u0441\u0435\u043d-\u0438\u043c-\u0422\u0430\u043b\u0435"
    ],
    "name:slk_x_preferred":[
        "Brixen im Thale"
    ],
    "name:slv_x_preferred":[
        "Brixen im Thale"
    ],
    "name:spa_x_preferred":[
        "Brixen im Thale"
    ],
    "name:swe_x_preferred":[
        "Brixen im Thale"
    ],
    "name:ukr_x_preferred":[
        "\u0411\u0440\u0456\u043a\u0441\u0435\u043d-\u0456\u043c-\u0422\u0430\u043b\u0435"
    ],
    "name:uzb_x_preferred":[
        "Brixen im Thale"
    ],
    "name:vol_x_preferred":[
        "Brixen im Thale"
    ],
    "name:war_x_preferred":[
        "Brixen im Thale"
    ],
    "name:zho_x_preferred":[
        "Brixen im Thale"
    ],
    "qs_pg:aaroncc":"AT",
    "qs_pg:name":"Brixen im Thale",
    "qs_pg:name_adm0":"\u00d6sterreich",
    "qs_pg:name_adm1":"Tirol",
    "qs_pg:photos":253,
    "qs_pg:photos_1k":51,
    "qs_pg:photos_9k":1,
    "qs_pg:photos_9r":4,
    "qs_pg:photos_all":253,
    "qs_pg:photos_sr":5,
    "qs_pg:pop_sr":0,
    "qs_pg:qs_pg_placetype":"locality",
    "qs_pg:qs_pg_placetype_gp":"Town",
    "qs_pg:woe_adm0":23424750,
    "woe:adm0_id":23424750,
    "woe:name_adm0":"\u00d6sterreich",
    "woe:name_adm1":"Tirol",
    "woe:placetype":"Town",
    "wof:name":"Brixen im Thale",
    "wof:placetype":"locality"
},
  "geometry": {"coordinates":[12.234134,47.466333],"type":"Point"}
}