{
  "type": "Feature",
  "properties": {
    "gn:admin1_code":"2.0",
    "gn:admin2_code":"205",
    "gn:admin3_code":"20520.0",
    "gn:asciiname":"Bergwerksgraben",
    "gn:country_code":"AT",
    "gn:dem":703,
    "gn:feature_class":"P",
    "gn:feature_code":"PPLL",
    "gn:name":"Bergwerksgraben",
    "gn:population":35,
    "gn:timezone":"Europe/Vienna",
    "iso:country":"AT",
    "wof:name":"Bergwerksgraben",
    "wof:placetype":"locality",
    "wof:population":35
},
  "geometry": {"coordinates":[14.37528,46.85056],"type":"Point"}
}