{
  "type": "Feature",
  "properties": {
    "gn:admin1_code":"03",
    "gn:admin2_code":"309.0",
    "gn:admin3_code":"30932.0",
    "gn:asciiname":"Zeil",
    "gn:country_code":"AT",
    "gn:dem":665,
    "gn:feature_class":"P",
    "gn:feature_code":"PPL",
    "gn:name":"Zeil",
    "gn:population":117,
    "gn:timezone":"Europe/Vienna",
    "iso:country":"AT",
    "name:ara_x_preferred":[
        "\u0632\u0627\u064a\u0644"
    ],
    "name:ces_x_preferred":[
        "Zeil"
    ],
    "name:deu_x_preferred":[
        "Zeil"
    ],
    "name:fin_x_preferred":[
        "Zeil"
    ],
    "name:fra_x_preferred":[
        "Zeil"
    ],
    "name:hye_x_preferred":[
        "\u0551\u0561\u0575\u056c"
    ],
    "name:ita_x_preferred":[
        "Zeil"
    ],
    "name:nld_x_preferred":[
        "Zeil"
    ],
    "name:nor_x_preferred":[
        "Zeil"
    ],
    "name:pol_x_preferred":[
        "Zeil"
    ],
    "name:por_x_preferred":[
        "Zeil"
    ],
    "name:rus_x_preferred":[
        "\u0426\u0430\u0439\u043b\u044c"
    ],
    "name:spa_x_preferred":[
        "Zeil"
    ],
    "name:zho_x_preferred":[
        "\u91c7\u5c14\u5927\u8857"
    ],
    "wof:name":"Zeil",
    "wof:placetype":"locality",
    "wof:population":117
},
  "geometry": {"coordinates":[14.85,48.65],"type":"Point"}
}