{
  "type": "Feature",
  "properties": {
    "gn:admin1_code":"3.0",
    "gn:admin2_code":"301",
    "gn:admin3_code":"30101.0",
    "gn:asciiname":"Alauntal",
    "gn:cc2":"AT",
    "gn:country_code":"AT",
    "gn:dem":295,
    "gn:feature_class":"P",
    "gn:feature_code":"PPL",
    "gn:name":"Alauntal",
    "gn:population":0,
    "gn:timezone":"Europe/Vienna",
    "iso:country":"AT",
    "name:und_x_variant":[
        "Alaunthal"
    ],
    "wof:name":"Alauntal",
    "wof:placetype":"locality"
},
  "geometry": {"coordinates":[15.57587,48.41872],"type":"Point"}
}