{
  "type": "Feature",
  "properties": {
    "gn:admin1_code":"3.0",
    "gn:admin2_code":"321",
    "gn:admin3_code":"32114.0",
    "gn:asciiname":"Engelmannsbrunn",
    "gn:country_code":"AT",
    "gn:dem":246,
    "gn:feature_class":"P",
    "gn:feature_code":"PPL",
    "gn:name":"Engelmannsbrunn",
    "gn:population":297,
    "gn:timezone":"Europe/Vienna",
    "iso:country":"AT",
    "wof:name":"Engelmannsbrunn",
    "wof:placetype":"locality",
    "wof:population":297
},
  "geometry": {"coordinates":[15.88333,48.45],"type":"Point"}
}