{
  "type": "Feature",
  "properties": {
    "gn:admin1_code":"03",
    "gn:admin2_code":"315.0",
    "gn:admin3_code":"31524.0",
    "gn:asciiname":"Pielachberg",
    "gn:country_code":"AT",
    "gn:dem":233,
    "gn:feature_class":"P",
    "gn:feature_code":"PPL",
    "gn:name":"Pielachberg",
    "gn:population":453,
    "gn:timezone":"Europe/Vienna",
    "iso:country":"AT",
    "wof:name":"Pielachberg",
    "wof:placetype":"locality",
    "wof:population":453
},
  "geometry": {"coordinates":[15.36846,48.23148],"type":"Point"}
}