{
  "type": "Feature",
  "properties": {
    "gn:admin1_code":"2.0",
    "gn:admin2_code":"204",
    "gn:admin3_code":"20441.0",
    "gn:asciiname":"Kobla",
    "gn:country_code":"AT",
    "gn:dem":975,
    "gn:feature_class":"P",
    "gn:feature_code":"PPL",
    "gn:name":"Kobla",
    "gn:population":0,
    "gn:timezone":"Europe/Vienna",
    "iso:country":"AT",
    "wof:name":"Kobla",
    "wof:placetype":"locality"
},
  "geometry": {"coordinates":[14.38194,46.46889],"type":"Point"}
}