{
  "type": "Feature",
  "properties": {
    "gn:admin1_code":"4.0",
    "gn:admin2_code":"404",
    "gn:admin3_code":"40405.0",
    "gn:asciiname":"Tal",
    "gn:country_code":"AT",
    "gn:dem":423,
    "gn:feature_class":"P",
    "gn:feature_code":"PPL",
    "gn:name":"Tal",
    "gn:population":12,
    "gn:timezone":"Europe/Vienna",
    "iso:country":"AT",
    "wof:name":"Tal",
    "wof:placetype":"locality",
    "wof:population":12
},
  "geometry": {"coordinates":[13.09729,48.18566],"type":"Point"}
}