{
  "type": "Feature",
  "properties": {
    "gn:admin1_code":"8.0",
    "gn:admin2_code":"802",
    "gn:admin3_code":"80232.0",
    "gn:asciiname":"Enge Vorsaess",
    "gn:country_code":"AT",
    "gn:dem":703,
    "gn:elevation":"700.0",
    "gn:feature_class":"P",
    "gn:feature_code":"PPLF",
    "gn:name":"Enge Vors\u00e4\u00df",
    "gn:population":0,
    "gn:timezone":"Europe/Vienna",
    "iso:country":"AT",
    "wof:name":"Enge Vorsaess",
    "wof:placetype":"locality"
},
  "geometry": {"coordinates":[9.91063,47.34327],"type":"Point"}
}