{
  "type": "Feature",
  "properties": {
    "gn:admin1_code":"4.0",
    "gn:admin2_code":"406",
    "gn:admin3_code":"40621.0",
    "gn:asciiname":"Landshut",
    "gn:country_code":"AT",
    "gn:dem":860,
    "gn:feature_class":"P",
    "gn:feature_code":"PPL",
    "gn:name":"Landshut",
    "gn:population":174,
    "gn:timezone":"Europe/Vienna",
    "iso:country":"AT",
    "wof:name":"Landshut",
    "wof:placetype":"locality",
    "wof:population":174
},
  "geometry": {"coordinates":[14.80433,48.45391],"type":"Point"}
}