{
  "type": "Feature",
  "properties": {
    "gn:admin1_code":"2.0",
    "gn:admin2_code":"209",
    "gn:admin3_code":"20909.0",
    "gn:asciiname":"Hart",
    "gn:country_code":"AT",
    "gn:dem":425,
    "gn:feature_class":"P",
    "gn:feature_code":"PPL",
    "gn:name":"Hart",
    "gn:population":134,
    "gn:timezone":"Europe/Vienna",
    "iso:country":"AT",
    "wof:name":"Hart",
    "wof:placetype":"locality",
    "wof:population":134
},
  "geometry": {"coordinates":[14.91667,46.66667],"type":"Point"}
}