{
  "type": "Feature",
  "properties": {
    "gn:admin1_code":"4.0",
    "gn:admin2_code":"412",
    "gn:admin3_code":"41201.0",
    "gn:asciiname":"Stelzerberg",
    "gn:country_code":"AT",
    "gn:dem":473,
    "gn:feature_class":"P",
    "gn:feature_code":"PPL",
    "gn:name":"Stelzerberg",
    "gn:population":0,
    "gn:timezone":"Europe/Vienna",
    "iso:country":"AT",
    "wof:name":"Stelzerberg",
    "wof:placetype":"locality"
},
  "geometry": {"coordinates":[13.52606,48.27368],"type":"Point"}
}