{
  "type": "Feature",
  "properties": {
    "gn:admin1_code":"03",
    "gn:admin2_code":"311.0",
    "gn:admin3_code":"31130.0",
    "gn:asciiname":"Sitzenhart",
    "gn:country_code":"AT",
    "gn:dem":282,
    "gn:feature_class":"P",
    "gn:feature_code":"PPL",
    "gn:name":"Sitzenhart",
    "gn:population":0,
    "gn:timezone":"Europe/Vienna",
    "iso:country":"AT",
    "wof:name":"Sitzenhart",
    "wof:placetype":"locality"
},
  "geometry": {"coordinates":[15.88333,48.61667],"type":"Point"}
}