{
  "type": "Feature",
  "properties": {
    "gn:admin1_code":"8.0",
    "gn:admin2_code":"802",
    "gn:admin3_code":"80226.0",
    "gn:asciiname":"Hofen",
    "gn:country_code":"AT",
    "gn:dem":415,
    "gn:feature_class":"P",
    "gn:feature_code":"PPL",
    "gn:name":"Hofen",
    "gn:population":0,
    "gn:timezone":"Europe/Vienna",
    "iso:country":"AT",
    "wof:name":"Hofen",
    "wof:placetype":"locality"
},
  "geometry": {"coordinates":[9.75,47.53333],"type":"Point"}
}