{
  "type": "Feature",
  "properties": {
    "gn:admin1_code":"03",
    "gn:admin2_code":"319.0",
    "gn:admin3_code":"31934.0",
    "gn:asciiname":"Wieden",
    "gn:country_code":"AT",
    "gn:dem":326,
    "gn:feature_class":"P",
    "gn:feature_code":"PPL",
    "gn:name":"Wieden",
    "gn:population":23,
    "gn:timezone":"Europe/Vienna",
    "iso:country":"AT",
    "name:bar_x_preferred":[
        "Wiedn"
    ],
    "name:bul_x_preferred":[
        "\u0412\u0438\u0434\u0435\u043d"
    ],
    "name:ceb_x_preferred":[
        "Gemeindebezirk Wieden"
    ],
    "name:ces_x_preferred":[
        "Wieden"
    ],
    "name:dan_x_preferred":[
        "Wieden"
    ],
    "name:deu_x_preferred":[
        "Wieden"
    ],
    "name:est_x_preferred":[
        "Wieden"
    ],
    "name:fin_x_preferred":[
        "Wieden"
    ],
    "name:fra_x_preferred":[
        "Wieden"
    ],
    "name:ita_x_preferred":[
        "Wieden"
    ],
    "name:jpn_x_preferred":[
        "\u30f4\u30a3\u30fc\u30c7\u30f3"
    ],
    "name:lat_x_preferred":[
        "Wieden"
    ],
    "name:ltz_x_preferred":[
        "Wieden"
    ],
    "name:mkd_x_preferred":[
        "\u0412\u0438\u0434\u0435\u043d"
    ],
    "name:nld_x_preferred":[
        "Wieden"
    ],
    "name:nor_x_preferred":[
        "Wieden"
    ],
    "name:pol_x_preferred":[
        "Wieden"
    ],
    "name:por_x_preferred":[
        "Wieden"
    ],
    "name:rus_x_preferred":[
        "\u0412\u0438\u0434\u0435\u043d"
    ],
    "name:slk_x_preferred":[
        "Wieden"
    ],
    "name:spa_x_preferred":[
        "Wieden"
    ],
    "name:srp_x_preferred":[
        "\u0412\u0438\u0434\u0435\u043d"
    ],
    "name:swe_x_preferred":[
        "Gemeindebezirk Wieden"
    ],
    "name:tur_x_preferred":[
        "Wieden"
    ],
    "name:ukr_x_preferred":[
        "\u0412\u0456\u0434\u0435\u043d"
    ],
    "wof:name":"Wieden",
    "wof:placetype":"locality",
    "wof:population":23
},
  "geometry": {"coordinates":[15.67389,48.15372],"type":"Point"}
}