{
  "type": "Feature",
  "properties": {
    "gn:admin1_code":"03",
    "gn:admin2_code":"319.0",
    "gn:admin3_code":"31934.0",
    "gn:asciiname":"Wieden",
    "gn:country_code":"AT",
    "gn:dem":326,
    "gn:feature_class":"P",
    "gn:feature_code":"PPL",
    "gn:name":"Wieden",
    "gn:population":23,
    "gn:timezone":"Europe/Vienna",
    "iso:country":"AT",
    "wof:name":"Wieden",
    "wof:placetype":"locality",
    "wof:population":23
},
  "geometry": {"coordinates":[15.67389,48.15372],"type":"Point"}
}