{
  "type": "Feature",
  "properties": {
    "iso:country":"AT",
    "qs_pg:aaroncc":"AT",
    "qs_pg:name":"Gr\u00fcner Baum",
    "qs_pg:name_adm0":"\u00d6sterreich",
    "qs_pg:name_adm1":"Salzburg",
    "qs_pg:photos":9,
    "qs_pg:photos_1k":2,
    "qs_pg:photos_9k":1,
    "qs_pg:photos_9r":1,
    "qs_pg:photos_all":9,
    "qs_pg:photos_sr":1,
    "qs_pg:pop_sr":0,
    "qs_pg:qs_pg_placetype":"locality",
    "qs_pg:qs_pg_placetype_gp":"Town",
    "qs_pg:woe_adm0":23424750,
    "woe:adm0_id":23424750,
    "woe:name_adm0":"\u00d6sterreich",
    "woe:name_adm1":"Salzburg",
    "woe:placetype":"Town",
    "wof:name":"Gr\u00fcner Baum",
    "wof:placetype":"locality"
},
  "geometry": {"coordinates":[13.160591,47.127465],"type":"Point"}
}