{
  "type": "Feature",
  "properties": {
    "gn:admin1_code":"04",
    "gn:admin2_code":"408.0",
    "gn:admin3_code":"40831.0",
    "gn:asciiname":"Oberwegbach",
    "gn:country_code":"AT",
    "gn:dem":372,
    "gn:feature_class":"P",
    "gn:feature_code":"PPL",
    "gn:name":"Oberwegbach",
    "gn:population":52,
    "gn:timezone":"Europe/Vienna",
    "iso:country":"AT",
    "wof:name":"Oberwegbach",
    "wof:placetype":"locality",
    "wof:population":52
},
  "geometry": {"coordinates":[13.8547,48.31751],"type":"Point"}
}