{
  "type": "Feature",
  "properties": {
    "gn:admin1_code":"4.0",
    "gn:admin2_code":"405",
    "gn:admin3_code":"40509.0",
    "gn:asciiname":"Woerth",
    "gn:country_code":"AT",
    "gn:dem":264,
    "gn:feature_class":"P",
    "gn:feature_code":"PPL",
    "gn:name":"W\u00f6rth",
    "gn:population":192,
    "gn:timezone":"Europe/Vienna",
    "iso:country":"AT",
    "wof:name":"Woerth",
    "wof:placetype":"locality",
    "wof:population":192
},
  "geometry": {"coordinates":[14.028,48.31374],"type":"Point"}
}