{
  "type": "Feature",
  "properties": {
    "gn:admin1_code":"4.0",
    "gn:admin2_code":"404",
    "gn:admin3_code":"40419.0",
    "gn:asciiname":"Oberhaft",
    "gn:country_code":"AT",
    "gn:dem":502,
    "gn:feature_class":"P",
    "gn:feature_code":"PPL",
    "gn:name":"Oberhaft",
    "gn:population":67,
    "gn:timezone":"Europe/Vienna",
    "iso:country":"AT",
    "wof:name":"Oberhaft",
    "wof:placetype":"locality",
    "wof:population":67
},
  "geometry": {"coordinates":[13.19578,48.02785],"type":"Point"}
}