{
  "type": "Feature",
  "properties": {
    "gn:admin1_code":"02",
    "gn:admin2_code":"208.0",
    "gn:admin3_code":"20817.0",
    "gn:asciiname":"Sankt Georgen am Weinberge",
    "gn:cc2":"AT",
    "gn:country_code":"AT",
    "gn:dem":690,
    "gn:feature_class":"P",
    "gn:feature_code":"PPL",
    "gn:name":"Sankt Georgen am Weinberge",
    "gn:population":0,
    "gn:timezone":"Europe/Vienna",
    "iso:country":"AT",
    "name:und_x_variant":[
        "Sankt Georgen",
        "Sankt Georgen am Weinberge"
    ],
    "wof:name":"Sankt Georgen am Weinberge",
    "wof:placetype":"locality"
},
  "geometry": {"coordinates":[14.55,46.68333],"type":"Point"}
}