{
  "type": "Feature",
  "properties": {
    "gn:admin1_code":"4.0",
    "gn:admin2_code":"414",
    "gn:admin3_code":"41406.0",
    "gn:asciiname":"Hackledt",
    "gn:country_code":"AT",
    "gn:dem":353,
    "gn:feature_class":"P",
    "gn:feature_code":"PPL",
    "gn:name":"Hackledt",
    "gn:population":133,
    "gn:timezone":"Europe/Vienna",
    "iso:country":"AT",
    "wof:name":"Hackledt",
    "wof:placetype":"locality",
    "wof:population":133
},
  "geometry": {"coordinates":[13.44718,48.3514],"type":"Point"}
}