{
  "type": "Feature",
  "properties": {
    "gn:admin1_code":"4.0",
    "gn:admin2_code":"410",
    "gn:admin3_code":"41004.0",
    "gn:asciiname":"Hundsfussberg",
    "gn:country_code":"AT",
    "gn:dem":359,
    "gn:feature_class":"P",
    "gn:feature_code":"PPL",
    "gn:name":"Hundsfussberg",
    "gn:population":0,
    "gn:timezone":"Europe/Vienna",
    "iso:country":"AT",
    "wof:name":"Hundsfussberg",
    "wof:placetype":"locality"
},
  "geometry": {"coordinates":[14.14026,48.12508],"type":"Point"}
}