{
  "type": "Feature",
  "properties": {
    "gn:admin1_code":"07",
    "gn:admin2_code":"704.0",
    "gn:admin3_code":"70419.0",
    "gn:asciiname":"Strub",
    "gn:country_code":"AT",
    "gn:dem":751,
    "gn:feature_class":"P",
    "gn:feature_code":"PPL",
    "gn:name":"Strub",
    "gn:population":0,
    "gn:timezone":"Europe/Vienna",
    "iso:country":"AT",
    "wof:name":"Strub",
    "wof:placetype":"locality"
},
  "geometry": {"coordinates":[12.61667,47.58333],"type":"Point"}
}