{
  "type": "Feature",
  "properties": {
    "gn:admin1_code":"06",
    "gn:admin2_code":"623.0",
    "gn:admin3_code":"62384.0",
    "gn:asciiname":"Brandlegg",
    "gn:country_code":"AT",
    "gn:dem":351,
    "gn:feature_class":"P",
    "gn:feature_code":"PPL",
    "gn:name":"Brandlegg",
    "gn:population":0,
    "gn:timezone":"Europe/Vienna",
    "iso:country":"AT",
    "wof:name":"Brandlegg",
    "wof:placetype":"locality"
},
  "geometry": {"coordinates":[15.83333,46.93333],"type":"Point"}
}