{
  "type": "Feature",
  "properties": {
    "gn:admin1_code":"4.0",
    "gn:admin2_code":"414",
    "gn:admin3_code":"41414.0",
    "gn:asciiname":"Bruendl",
    "gn:country_code":"AT",
    "gn:dem":384,
    "gn:feature_class":"P",
    "gn:feature_code":"PPL",
    "gn:name":"Br\u00fcndl",
    "gn:population":125,
    "gn:timezone":"Europe/Vienna",
    "iso:country":"AT",
    "wof:name":"Bruendl",
    "wof:placetype":"locality",
    "wof:population":125
},
  "geometry": {"coordinates":[13.64897,48.36053],"type":"Point"}
}