{
  "type": "Feature",
  "properties": {
    "gn:admin1_code":"7.0",
    "gn:admin2_code":"705",
    "gn:admin3_code":"70511.0",
    "gn:asciiname":"Kastengstatt",
    "gn:country_code":"AT",
    "gn:dem":504,
    "gn:feature_class":"P",
    "gn:feature_code":"PPL",
    "gn:name":"Kastengstatt",
    "gn:population":0,
    "gn:timezone":"Europe/Vienna",
    "iso:country":"AT",
    "wof:name":"Kastengstatt",
    "wof:placetype":"locality"
},
  "geometry": {"coordinates":[12.07209,47.50143],"type":"Point"}
}