{
  "type": "Feature",
  "properties": {
    "gn:admin1_code":"04",
    "gn:admin2_code":"404.0",
    "gn:admin3_code":"40423.0",
    "gn:asciiname":"Obersunzing",
    "gn:country_code":"AT",
    "gn:dem":336,
    "gn:feature_class":"P",
    "gn:feature_code":"PPL",
    "gn:name":"Obersunzing",
    "gn:population":10,
    "gn:timezone":"Europe/Vienna",
    "iso:country":"AT",
    "wof:name":"Obersunzing",
    "wof:placetype":"locality",
    "wof:population":10
},
  "geometry": {"coordinates":[13.17887,48.28828],"type":"Point"}
}