{
  "type": "Feature",
  "properties": {
    "gn:admin1_code":"4.0",
    "gn:admin2_code":"416",
    "gn:admin3_code":"41601.0",
    "gn:asciiname":"Greifenberg",
    "gn:country_code":"AT",
    "gn:dem":501,
    "gn:feature_class":"P",
    "gn:feature_code":"PPL",
    "gn:name":"Greifenberg",
    "gn:population":6,
    "gn:timezone":"Europe/Vienna",
    "iso:country":"AT",
    "name:ara_x_preferred":[
        "\u063a\u0631\u0622\u064a\u0641\u064a\u0646\u0628\u064a\u0631\u063a"
    ],
    "name:ceb_x_preferred":[
        "Greifenberg"
    ],
    "name:ces_x_preferred":[
        "Greifenberg"
    ],
    "name:dan_x_preferred":[
        "Greifenberg"
    ],
    "name:deu_x_preferred":[
        "Greifenberg"
    ],
    "name:epo_x_preferred":[
        "Greifenberg"
    ],
    "name:eus_x_preferred":[
        "Greifenberg"
    ],
    "name:fas_x_preferred":[
        "\u06af\u0631\u0627\u06cc\u0641\u0646\u0628\u0631\u06af"
    ],
    "name:fra_x_preferred":[
        "Greifenberg"
    ],
    "name:hun_x_preferred":[
        "Greifenberg"
    ],
    "name:hye_x_preferred":[
        "\u0533\u0580\u0561\u0575\u0586\u0565\u0576\u0562\u0565\u0580\u0563"
    ],
    "name:ita_x_preferred":[
        "Greifenberg"
    ],
    "name:jpn_x_preferred":[
        "\u30b0\u30e9\u30a4\u30d5\u30a7\u30f3\u30d9\u30eb\u30af"
    ],
    "name:lmo_x_preferred":[
        "Greifenberg"
    ],
    "name:msa_x_preferred":[
        "Greifenberg"
    ],
    "name:nld_x_preferred":[
        "Greifenberg"
    ],
    "name:pol_x_preferred":[
        "Greifenberg"
    ],
    "name:por_x_preferred":[
        "Greifenberg"
    ],
    "name:ron_x_preferred":[
        "Greifenberg"
    ],
    "name:rus_x_preferred":[
        "\u0413\u0440\u0430\u0439\u0444\u0435\u043d\u0431\u0435\u0440\u0433"
    ],
    "name:spa_x_preferred":[
        "Greifenberg"
    ],
    "name:srp_x_preferred":[
        "\u0413\u0440\u0430\u0458\u0444\u0435\u043d\u0431\u0435\u0440\u0433"
    ],
    "name:swe_x_preferred":[
        "Greifenberg"
    ],
    "name:ukr_x_preferred":[
        "\u0413\u0440\u0430\u0439\u0444\u0435\u043d\u0431\u0435\u0440\u0433"
    ],
    "name:uzb_x_preferred":[
        "Greifenberg"
    ],
    "name:vie_x_preferred":[
        "Greifenberg"
    ],
    "name:vol_x_preferred":[
        "Greifenberg"
    ],
    "name:war_x_preferred":[
        "Greifenberg"
    ],
    "name:zho_x_preferred":[
        "\u683c\u8d56\u82ac\u8d1d\u683c"
    ],
    "wof:name":"Greifenberg",
    "wof:placetype":"locality",
    "wof:population":6
},
  "geometry": {"coordinates":[14.45869,48.38749],"type":"Point"}
}