{
  "type": "Feature",
  "properties": {
    "gn:admin1_code":"4.0",
    "gn:admin2_code":"416",
    "gn:admin3_code":"41601.0",
    "gn:asciiname":"Greifenberg",
    "gn:country_code":"AT",
    "gn:dem":501,
    "gn:feature_class":"P",
    "gn:feature_code":"PPL",
    "gn:name":"Greifenberg",
    "gn:population":6,
    "gn:timezone":"Europe/Vienna",
    "iso:country":"AT",
    "wof:name":"Greifenberg",
    "wof:placetype":"locality",
    "wof:population":6
},
  "geometry": {"coordinates":[14.45869,48.38749],"type":"Point"}
}