{
  "type": "Feature",
  "properties": {
    "gn:admin1_code":"4.0",
    "gn:admin2_code":"404",
    "gn:admin3_code":"40427.0",
    "gn:asciiname":"Eisenhub",
    "gn:country_code":"AT",
    "gn:dem":411,
    "gn:feature_class":"P",
    "gn:feature_code":"PPL",
    "gn:name":"Eisenhub",
    "gn:population":19,
    "gn:timezone":"Europe/Vienna",
    "iso:country":"AT",
    "wof:name":"Eisenhub",
    "wof:placetype":"locality",
    "wof:population":19
},
  "geometry": {"coordinates":[13.01691,48.1911],"type":"Point"}
}