{
  "type": "Feature",
  "properties": {
    "gn:admin1_code":"2.0",
    "gn:admin2_code":"205",
    "gn:admin3_code":"20506.0",
    "gn:asciiname":"Lassenberg",
    "gn:country_code":"AT",
    "gn:dem":783,
    "gn:feature_class":"P",
    "gn:feature_code":"PPL",
    "gn:name":"Lassenberg",
    "gn:population":29,
    "gn:timezone":"Europe/Vienna",
    "iso:country":"AT",
    "wof:name":"Lassenberg",
    "wof:placetype":"locality",
    "wof:population":29
},
  "geometry": {"coordinates":[14.13333,46.86667],"type":"Point"}
}