{
  "type": "Feature",
  "properties": {
    "gn:country":"AT",
    "gn:fcode":"PPL",
    "gn:population":0,
    "iso:country":"AT",
    "name:ceb_x_preferred":[
        "Lauterbach"
    ],
    "name:chv_x_preferred":[
        "\u041b\u0430\u0443\u0442\u0435\u0440\u0431\u0430\u0445"
    ],
    "name:deu_x_preferred":[
        "Lauterbach"
    ],
    "name:epo_x_preferred":[
        "Lauterbach"
    ],
    "name:fra_x_preferred":[
        "Lauterbach"
    ],
    "name:heb_x_preferred":[
        "\u05dc\u05d5\u05d9\u05d8\u05e8\u05d1\u05da"
    ],
    "name:hun_x_preferred":[
        "Lauterbach"
    ],
    "name:ita_x_preferred":[
        "Lauterbach"
    ],
    "name:jpn_x_preferred":[
        "\u30e9\u30a6\u30bf\u30fc\u30d0\u30c3\u30cf"
    ],
    "name:nld_x_preferred":[
        "Lauterbach"
    ],
    "name:nor_x_preferred":[
        "Lauterbach"
    ],
    "name:pol_x_preferred":[
        "Lauterbach"
    ],
    "name:ron_x_preferred":[
        "Lauterbach"
    ],
    "name:rus_x_preferred":[
        "\u041b\u0430\u0443\u0442\u0435\u0440\u0431\u0430\u0445"
    ],
    "name:srp_x_preferred":[
        "\u041b\u0430\u0443\u0442\u0435\u0440\u0431\u0430\u0445"
    ],
    "name:swe_x_preferred":[
        "Lauterbach"
    ],
    "name:vol_x_preferred":[
        "Lauterbach"
    ],
    "qs_pg:aaroncc":"AT",
    "qs_pg:gn_country":"AT",
    "qs_pg:gn_fcode":"PPL",
    "qs_pg:gn_pop":0,
    "qs_pg:name":"Lauterbach",
    "qs_pg:name_adm0":"\u00d6sterreich",
    "qs_pg:name_adm1":"Nieder\u00f6sterreich",
    "qs_pg:photos_9r":0,
    "qs_pg:photos_sr":0,
    "qs_pg:pop_sr":0,
    "qs_pg:qs_pg_placetype":"locality",
    "qs_pg:qs_pg_placetype_gp":"Town",
    "qs_pg:woe_adm0":23424750,
    "woe:adm0_id":23424750,
    "woe:name_adm0":"\u00d6sterreich",
    "woe:name_adm1":"Nieder\u00f6sterreich",
    "woe:placetype":"Town",
    "wof:name":"Lauterbach",
    "wof:placetype":"locality"
},
  "geometry": {"coordinates":[14.76667,48.68333],"type":"Point"}
}