{
  "type": "Feature",
  "properties": {
    "gn:admin1_code":"3.0",
    "gn:admin2_code":"308",
    "gn:admin3_code":"30831.0",
    "gn:asciiname":"Breitstetten",
    "gn:country_code":"AT",
    "gn:dem":147,
    "gn:feature_class":"P",
    "gn:feature_code":"PPL",
    "gn:name":"Breitstetten",
    "gn:population":457,
    "gn:timezone":"Europe/Vienna",
    "iso:country":"AT",
    "wof:name":"Breitstetten",
    "wof:placetype":"locality",
    "wof:population":457
},
  "geometry": {"coordinates":[16.70832,48.19424],"type":"Point"}
}