{
  "type": "Feature",
  "properties": {
    "iso:country":"AT",
    "name:deu_x_preferred":[
        "Wasserfeldsiedlung"
    ],
    "name:eng_x_preferred":[
        "Wasserfeldsiedlung"
    ],
    "wof:name":"Wasserfeldsiedlung",
    "wof:placetype":"neighbourhood"
},
  "geometry": {"coordinates":[13.03465528141072,47.82585527814302],"type":"Point"}
}