{
  "type": "Feature",
  "properties": {
    "gn:admin1_code":"02",
    "gn:admin2_code":"207.0",
    "gn:admin3_code":"20719.0",
    "gn:asciiname":"Semering",
    "gn:country_code":"AT",
    "gn:dem":771,
    "gn:feature_class":"P",
    "gn:feature_code":"PPL",
    "gn:name":"Semering",
    "gn:population":85,
    "gn:timezone":"Europe/Vienna",
    "iso:country":"AT",
    "wof:name":"Semering",
    "wof:placetype":"locality",
    "wof:population":85
},
  "geometry": {"coordinates":[13.58253,46.61183],"type":"Point"}
}