{
  "type": "Feature",
  "properties": {
    "gn:admin1_code":"4.0",
    "gn:admin2_code":"413",
    "gn:admin3_code":"41317.0",
    "gn:asciiname":"Fuchsoedt",
    "gn:country_code":"AT",
    "gn:dem":613,
    "gn:feature_class":"P",
    "gn:feature_code":"PPL",
    "gn:name":"Fuchs\u00f6dt",
    "gn:population":58,
    "gn:timezone":"Europe/Vienna",
    "iso:country":"AT",
    "wof:name":"Fuchsoedt",
    "wof:placetype":"locality",
    "wof:population":58
},
  "geometry": {"coordinates":[13.80827,48.59035],"type":"Point"}
}