{
  "type": "Feature",
  "properties": {
    "gn:admin1_code":"4.0",
    "gn:admin2_code":"418",
    "gn:admin3_code":"41816.0",
    "gn:asciiname":"Oberthambach",
    "gn:country_code":"AT",
    "gn:dem":329,
    "gn:feature_class":"P",
    "gn:feature_code":"PPL",
    "gn:name":"Oberthambach",
    "gn:population":31,
    "gn:timezone":"Europe/Vienna",
    "iso:country":"AT",
    "wof:name":"Oberthambach",
    "wof:placetype":"locality",
    "wof:population":31
},
  "geometry": {"coordinates":[13.91273,48.20466],"type":"Point"}
}