{
  "type": "Feature",
  "properties": {
    "gn:admin1_code":"04",
    "gn:admin2_code":"408.0",
    "gn:admin3_code":"40813.0",
    "gn:asciiname":"See",
    "gn:country_code":"AT",
    "gn:dem":438,
    "gn:feature_class":"P",
    "gn:feature_code":"PPL",
    "gn:name":"See",
    "gn:population":169,
    "gn:timezone":"Europe/Vienna",
    "iso:country":"AT",
    "name:ceb_x_preferred":[
        "See"
    ],
    "name:deu_x_preferred":[
        "See"
    ],
    "name:fra_x_preferred":[
        "See"
    ],
    "name:nds_x_preferred":[
        "See"
    ],
    "name:nld_x_preferred":[
        "See"
    ],
    "name:pol_x_preferred":[
        "See"
    ],
    "name:por_x_preferred":[
        "See"
    ],
    "name:swe_x_preferred":[
        "See"
    ],
    "wof:name":"See",
    "wof:placetype":"locality",
    "wof:population":169
},
  "geometry": {"coordinates":[13.86706,48.1686],"type":"Point"}
}