{
  "type": "Feature",
  "properties": {
    "gn:admin1_code":"4.0",
    "gn:admin2_code":"418",
    "gn:admin3_code":"41808.0",
    "gn:asciiname":"Kranzl am Eck",
    "gn:country_code":"AT",
    "gn:dem":382,
    "gn:feature_class":"P",
    "gn:feature_code":"PPL",
    "gn:name":"Kranzl am Eck",
    "gn:population":6,
    "gn:timezone":"Europe/Vienna",
    "iso:country":"AT",
    "wof:name":"Kranzl am Eck",
    "wof:placetype":"locality",
    "wof:population":6
},
  "geometry": {"coordinates":[13.89637,48.14026],"type":"Point"}
}