{
  "type": "Feature",
  "properties": {
    "gn:admin1_code":"02",
    "gn:admin2_code":"207.0",
    "gn:admin3_code":"20711.0",
    "gn:asciiname":"Outschena",
    "gn:country_code":"AT",
    "gn:dem":870,
    "gn:feature_class":"P",
    "gn:feature_code":"PPL",
    "gn:name":"Outschena",
    "gn:population":20,
    "gn:timezone":"Europe/Vienna",
    "iso:country":"AT",
    "wof:name":"Outschena",
    "wof:placetype":"locality",
    "wof:population":20
},
  "geometry": {"coordinates":[13.91994,46.53926],"type":"Point"}
}