{
  "type": "Feature",
  "properties": {
    "gn:admin1_code":"6.0",
    "gn:admin2_code":"603",
    "gn:admin3_code":"60345.0",
    "gn:asciiname":"Kornriegl",
    "gn:country_code":"AT",
    "gn:dem":585,
    "gn:feature_class":"P",
    "gn:feature_code":"PPL",
    "gn:name":"Kornriegl",
    "gn:population":31,
    "gn:timezone":"Europe/Vienna",
    "iso:country":"AT",
    "wof:name":"Kornriegl",
    "wof:placetype":"locality",
    "wof:population":31
},
  "geometry": {"coordinates":[15.25868,46.65874],"type":"Point"}
}