{
  "type": "Feature",
  "properties": {
    "gn:admin1_code":"6.0",
    "gn:admin2_code":"614",
    "gn:admin3_code":"61425.0",
    "gn:asciiname":"Laasen",
    "gn:country_code":"AT",
    "gn:dem":1196,
    "gn:feature_class":"P",
    "gn:feature_code":"PPL",
    "gn:name":"Laasen",
    "gn:population":0,
    "gn:timezone":"Europe/Vienna",
    "iso:country":"AT",
    "wof:name":"Laasen",
    "wof:placetype":"locality"
},
  "geometry": {"coordinates":[14.22222,47.15333],"type":"Point"}
}