{
  "type": "Feature",
  "properties": {
    "gn:admin1_code":"04",
    "gn:admin2_code":"414.0",
    "gn:admin3_code":"41407.0",
    "gn:asciiname":"Stadl",
    "gn:country_code":"AT",
    "gn:dem":719,
    "gn:feature_class":"P",
    "gn:feature_code":"PPL",
    "gn:name":"Stadl",
    "gn:population":189,
    "gn:timezone":"Europe/Vienna",
    "iso:country":"AT",
    "wof:name":"Stadl",
    "wof:placetype":"locality",
    "wof:population":189
},
  "geometry": {"coordinates":[13.68347,48.49306],"type":"Point"}
}