{
  "type": "Feature",
  "properties": {
    "gn:admin1_code":"4.0",
    "gn:admin2_code":"413",
    "gn:admin3_code":"41306.0",
    "gn:asciiname":"Woegerstorf",
    "gn:country_code":"AT",
    "gn:dem":619,
    "gn:feature_class":"P",
    "gn:feature_code":"PPL",
    "gn:name":"W\u00f6gerstorf",
    "gn:population":30,
    "gn:timezone":"Europe/Vienna",
    "iso:country":"AT",
    "wof:name":"Woegerstorf",
    "wof:placetype":"locality",
    "wof:population":30
},
  "geometry": {"coordinates":[13.87337,48.52996],"type":"Point"}
}