{
  "type": "Feature",
  "properties": {
    "gn:admin1_code":"3.0",
    "gn:admin2_code":"315",
    "gn:admin3_code":"31540.0",
    "gn:asciiname":"Mehlberg",
    "gn:country_code":"AT",
    "gn:dem":283,
    "gn:feature_class":"P",
    "gn:feature_code":"PPL",
    "gn:name":"Mehlberg",
    "gn:population":0,
    "gn:timezone":"Europe/Vienna",
    "iso:country":"AT",
    "wof:name":"Mehlberg",
    "wof:placetype":"locality"
},
  "geometry": {"coordinates":[15.01667,48.15],"type":"Point"}
}