{
  "type": "Feature",
  "properties": {
    "gn:admin1_code":"3.0",
    "gn:admin2_code":"319",
    "gn:admin3_code":"31901.0",
    "gn:asciiname":"Maiss",
    "gn:country_code":"AT",
    "gn:dem":459,
    "gn:feature_class":"P",
    "gn:feature_code":"PPL",
    "gn:name":"Mai\u00df",
    "gn:population":215,
    "gn:timezone":"Europe/Vienna",
    "iso:country":"AT",
    "name:deu_x_preferred":[
        "Maiss"
    ],
    "wof:name":"Maiss",
    "wof:placetype":"locality",
    "wof:population":215
},
  "geometry": {"coordinates":[15.93533,48.14135],"type":"Point"}
}