{
  "type": "Feature",
  "properties": {
    "gn:admin1_code":"7.0",
    "gn:admin2_code":"709",
    "gn:admin3_code":"70939.0",
    "gn:asciiname":"Dikat",
    "gn:country_code":"AT",
    "gn:dem":592,
    "gn:feature_class":"P",
    "gn:feature_code":"PPL",
    "gn:name":"Dikat",
    "gn:population":107,
    "gn:timezone":"Europe/Vienna",
    "iso:country":"AT",
    "wof:name":"Dikat",
    "wof:placetype":"locality",
    "wof:population":107
},
  "geometry": {"coordinates":[11.80708,47.40901],"type":"Point"}
}