{
  "type": "Feature",
  "properties": {
    "gn:admin1_code":"4.0",
    "gn:admin2_code":"408",
    "gn:admin3_code":"40822.0",
    "gn:asciiname":"Wimm",
    "gn:country_code":"AT",
    "gn:dem":447,
    "gn:feature_class":"P",
    "gn:feature_code":"PPL",
    "gn:name":"Wimm",
    "gn:population":14,
    "gn:timezone":"Europe/Vienna",
    "iso:country":"AT",
    "wof:name":"Wimm",
    "wof:placetype":"locality",
    "wof:population":14
},
  "geometry": {"coordinates":[13.6006,48.24345],"type":"Point"}
}