{
  "type": "Feature",
  "properties": {
    "gn:admin1_code":"07",
    "gn:admin2_code":"707.0",
    "gn:admin3_code":"70725.0",
    "gn:asciiname":"Unterleibnig",
    "gn:country_code":"AT",
    "gn:dem":1031,
    "gn:feature_class":"P",
    "gn:feature_code":"PPL",
    "gn:name":"Unterleibnig",
    "gn:population":0,
    "gn:timezone":"Europe/Vienna",
    "iso:country":"AT",
    "wof:name":"Unterleibnig",
    "wof:placetype":"locality"
},
  "geometry": {"coordinates":[12.63889,46.90583],"type":"Point"}
}