{
  "type": "Feature",
  "properties": {
    "gn:admin1_code":"1.0",
    "gn:admin2_code":"108",
    "gn:admin3_code":"10804.0",
    "gn:asciiname":"Grosswarasdorf",
    "gn:country_code":"AT",
    "gn:dem":237,
    "gn:feature_class":"P",
    "gn:feature_code":"PPL",
    "gn:name":"Grosswarasdorf",
    "gn:population":527,
    "gn:timezone":"Europe/Vienna",
    "iso:country":"AT",
    "name:ceb_x_preferred":[
        "Grosswarasdorf"
    ],
    "name:deu_x_preferred":[
        "Grosswarasdorf"
    ],
    "name:deu_x_variant":[
        "Gro\u00dfwarasdorf"
    ],
    "name:epo_x_preferred":[
        "Gro\u00dfwarasdorf"
    ],
    "name:fas_x_preferred":[
        "\u06af\u0631\u0648\u0633\u0648\u0627\u0631\u0627\u0633\u062f\u0648\u0631\u0641"
    ],
    "name:fra_x_preferred":[
        "Gro\u00dfwarasdorf"
    ],
    "name:hrv_x_preferred":[
        "Veliki Bori\u0161tof"
    ],
    "name:hun_x_preferred":[
        "Szabadb\u00e1r\u00e1nd"
    ],
    "name:ita_x_preferred":[
        "Gro\u00dfwarasdorf"
    ],
    "name:kaz_x_preferred":[
        "\u0413\u0440\u043e\u0441\u0432\u0430\u0440\u0430\u0441\u0434\u043e\u0440\u0444"
    ],
    "name:nld_x_preferred":[
        "Gro\u00dfwarasdorf"
    ],
    "name:pol_x_preferred":[
        "Gro\u00dfwarasdorf"
    ],
    "name:por_x_preferred":[
        "Gro\u00dfwarasdorf"
    ],
    "name:rus_x_preferred":[
        "\u0413\u0440\u043e\u0441\u0432\u0430\u0440\u0430\u0441\u0434\u043e\u0440\u0444"
    ],
    "name:slk_x_preferred":[
        "Gro\u00dfwarasdorf"
    ],
    "name:spa_x_preferred":[
        "Gro\u00dfwarasdorf"
    ],
    "name:ukr_x_preferred":[
        "\u0413\u0440\u043e\u0441\u0432\u0430\u0440\u0430\u0441\u0434\u043e\u0440\u0444"
    ],
    "name:und_x_variant":[
        "Gro\u00dfwarasdorf"
    ],
    "name:uzb_x_preferred":[
        "Gro\u00dfwarasdorf"
    ],
    "name:vol_x_preferred":[
        "Gro\u00dfwarasdorf"
    ],
    "name:war_x_preferred":[
        "Gro\u00dfwarasdorf"
    ],
    "name:zho_x_preferred":[
        "\u5927\u74e6\u62c9\u65af\u591a\u592b"
    ],
    "wof:name":"Grosswarasdorf",
    "wof:placetype":"locality",
    "wof:population":527
},
  "geometry": {"coordinates":[16.55305,47.53906],"type":"Point"}
}