{
  "type": "Feature",
  "properties": {
    "gn:admin1_code":"1.0",
    "gn:admin2_code":"108",
    "gn:admin3_code":"10804.0",
    "gn:asciiname":"Grosswarasdorf",
    "gn:country_code":"AT",
    "gn:dem":237,
    "gn:feature_class":"P",
    "gn:feature_code":"PPL",
    "gn:name":"Grosswarasdorf",
    "gn:population":527,
    "gn:timezone":"Europe/Vienna",
    "iso:country":"AT",
    "name:deu_x_preferred":[
        "Grosswarasdorf"
    ],
    "name:hrv_x_preferred":[
        "Veliki Bori\u0161tof"
    ],
    "name:hun_x_preferred":[
        "Szabadb\u00e1r\u00e1nd"
    ],
    "name:und_x_variant":[
        "Gro\u00dfwarasdorf"
    ],
    "wof:name":"Grosswarasdorf",
    "wof:placetype":"locality",
    "wof:population":527
},
  "geometry": {"coordinates":[16.55305,47.53906],"type":"Point"}
}