{
  "type": "Feature",
  "properties": {
    "iso:country":"AT",
    "name:deu_x_preferred":[
        "Liefering-Lehenau"
    ],
    "name:eng_x_preferred":[
        "Liefering-Lehenau"
    ],
    "wof:name":"Liefering-Lehenau",
    "wof:placetype":"neighbourhood"
},
  "geometry": {"coordinates":[13.0235258965385,47.8191702814763],"type":"Point"}
}