{
  "type": "Feature",
  "properties": {
    "gn:admin1_code":"2.0",
    "gn:admin2_code":"205",
    "gn:admin3_code":"20534.0",
    "gn:asciiname":"Steinbruecken",
    "gn:country_code":"AT",
    "gn:dem":515,
    "gn:feature_class":"P",
    "gn:feature_code":"PPL",
    "gn:name":"Steinbr\u00fccken",
    "gn:population":5,
    "gn:timezone":"Europe/Vienna",
    "iso:country":"AT",
    "wof:name":"Steinbruecken",
    "wof:placetype":"locality",
    "wof:population":5
},
  "geometry": {"coordinates":[14.3896,46.79906],"type":"Point"}
}