{
  "type": "Feature",
  "properties": {
    "iso:country":"AT",
    "wof:name":"Schottenviertel",
    "wof:placetype":"neighbourhood"
},
  "geometry": {"coordinates":[16.36269377117759,48.21112194583544],"type":"Point"}
}