{
  "type": "Feature",
  "properties": {
    "gn:admin1_code":"2.0",
    "gn:admin2_code":"210",
    "gn:admin3_code":"21008.0",
    "gn:asciiname":"Agsdorf",
    "gn:country_code":"AT",
    "gn:dem":572,
    "gn:feature_class":"P",
    "gn:feature_code":"PPL",
    "gn:name":"Agsdorf",
    "gn:population":356,
    "gn:timezone":"Europe/Vienna",
    "iso:country":"AT",
    "wof:name":"Agsdorf",
    "wof:placetype":"locality",
    "wof:population":356
},
  "geometry": {"coordinates":[14.15,46.73333],"type":"Point"}
}