{
  "type": "Feature",
  "properties": {
    "gn:admin1_code":"3.0",
    "gn:admin2_code":"316",
    "gn:admin3_code":"31634.0",
    "gn:asciiname":"Kirchstetten",
    "gn:country_code":"AT",
    "gn:dem":240,
    "gn:feature_class":"P",
    "gn:feature_code":"PPL",
    "gn:name":"Kirchstetten",
    "gn:population":129,
    "gn:timezone":"Europe/Vienna",
    "iso:country":"AT",
    "wof:name":"Kirchstetten",
    "wof:placetype":"locality",
    "wof:population":129
},
  "geometry": {"coordinates":[16.51667,48.73333],"type":"Point"}
}