{
  "type": "Feature",
  "properties": {
    "gn:admin1_code":"03",
    "gn:admin2_code":"313.0",
    "gn:admin3_code":"31330.0",
    "gn:asciiname":"Viessling",
    "gn:country_code":"AT",
    "gn:dem":558,
    "gn:feature_class":"P",
    "gn:feature_code":"PPL",
    "gn:name":"Viessling",
    "gn:population":0,
    "gn:timezone":"Europe/Vienna",
    "iso:country":"AT",
    "wof:name":"Viessling",
    "wof:placetype":"locality"
},
  "geometry": {"coordinates":[15.36667,48.36667],"type":"Point"}
}