{
  "type": "Feature",
  "properties": {
    "gn:admin1_code":"4.0",
    "gn:admin2_code":"411",
    "gn:admin3_code":"41118.0",
    "gn:asciiname":"Marwach",
    "gn:country_code":"AT",
    "gn:dem":320,
    "gn:feature_class":"P",
    "gn:feature_code":"PPL",
    "gn:name":"Marwach",
    "gn:population":136,
    "gn:timezone":"Europe/Vienna",
    "iso:country":"AT",
    "wof:name":"Marwach",
    "wof:placetype":"locality",
    "wof:population":136
},
  "geometry": {"coordinates":[14.53899,48.2917],"type":"Point"}
}