{
  "type": "Feature",
  "properties": {
    "gn:admin1_code":"3.0",
    "gn:admin2_code":"325",
    "gn:admin3_code":"32519.0",
    "gn:asciiname":"Kleinpertenschlag",
    "gn:country_code":"AT",
    "gn:dem":910,
    "gn:feature_class":"P",
    "gn:feature_code":"PPL",
    "gn:name":"Kleinpertenschlag",
    "gn:population":136,
    "gn:timezone":"Europe/Vienna",
    "iso:country":"AT",
    "wof:name":"Kleinpertenschlag",
    "wof:placetype":"locality",
    "wof:population":136
},
  "geometry": {"coordinates":[14.96667,48.43333],"type":"Point"}
}