{
  "type": "Feature",
  "properties": {
    "gn:admin1_code":"03",
    "gn:admin2_code":"317.0",
    "gn:admin3_code":"31703.0",
    "gn:asciiname":"Breitenfurt-Ost",
    "gn:country_code":"AT",
    "gn:dem":283,
    "gn:feature_class":"P",
    "gn:feature_code":"PPL",
    "gn:name":"Breitenfurt-Ost",
    "gn:population":0,
    "gn:timezone":"Europe/Vienna",
    "iso:country":"AT",
    "wof:name":"Breitenfurt-Ost",
    "wof:placetype":"locality"
},
  "geometry": {"coordinates":[16.19436,48.13579],"type":"Point"}
}