{
  "type": "Feature",
  "properties": {
    "gn:admin1_code":"04",
    "gn:admin2_code":"404.0",
    "gn:admin3_code":"40417.0",
    "gn:asciiname":"Oichten",
    "gn:country_code":"AT",
    "gn:dem":519,
    "gn:feature_class":"P",
    "gn:feature_code":"PPL",
    "gn:name":"Oichten",
    "gn:population":0,
    "gn:timezone":"Europe/Vienna",
    "iso:country":"AT",
    "wof:name":"Oichten",
    "wof:placetype":"locality"
},
  "geometry": {"coordinates":[13.06667,48.03333],"type":"Point"}
}