{
  "type": "Feature",
  "properties": {
    "gn:admin1_code":"4.0",
    "gn:admin2_code":"417",
    "gn:admin3_code":"41752.0",
    "gn:asciiname":"Vornholz",
    "gn:country_code":"AT",
    "gn:dem":515,
    "gn:feature_class":"P",
    "gn:feature_code":"PPL",
    "gn:name":"Vornholz",
    "gn:population":60,
    "gn:timezone":"Europe/Vienna",
    "iso:country":"AT",
    "name:ceb_x_preferred":[
        "Vornholz"
    ],
    "name:deu_x_preferred":[
        "Vornholz"
    ],
    "name:fas_x_preferred":[
        "\u0641\u0631\u0646\u0647\u0648\u0644\u062a\u0633"
    ],
    "name:fra_x_preferred":[
        "Vornholz"
    ],
    "name:ita_x_preferred":[
        "Vornholz"
    ],
    "name:kaz_x_preferred":[
        "\u0424\u043e\u0440\u043d\u0445\u043e\u043b\u044c\u0446"
    ],
    "name:nld_x_preferred":[
        "Vornholz"
    ],
    "name:rus_x_preferred":[
        "\u0424\u043e\u0440\u043d\u0445\u043e\u043b\u044c\u0446"
    ],
    "name:slk_x_preferred":[
        "Vornholz"
    ],
    "name:swe_x_preferred":[
        "Vornholz"
    ],
    "name:uzb_x_preferred":[
        "Vornholz"
    ],
    "name:vie_x_preferred":[
        "Vornholz"
    ],
    "name:vol_x_preferred":[
        "Vornholz"
    ],
    "name:war_x_preferred":[
        "Vornholz"
    ],
    "name:zho_x_preferred":[
        "\u798f\u6069\u970d\u5c14\u8328"
    ],
    "wof:name":"Vornholz",
    "wof:placetype":"locality",
    "wof:population":60
},
  "geometry": {"coordinates":[13.6024,48.05293],"type":"Point"}
}