{
  "type": "Feature",
  "properties": {
    "gn:admin1_code":"2.0",
    "gn:admin2_code":"206",
    "gn:admin3_code":"20643.0",
    "gn:asciiname":"Goeriach",
    "gn:country_code":"AT",
    "gn:dem":865,
    "gn:feature_class":"P",
    "gn:feature_code":"PPL",
    "gn:name":"G\u00f6riach",
    "gn:population":284,
    "gn:timezone":"Europe/Vienna",
    "iso:country":"AT",
    "wof:name":"Goeriach",
    "wof:placetype":"locality",
    "wof:population":284
},
  "geometry": {"coordinates":[13.38722,46.85694],"type":"Point"}
}