{
  "type": "Feature",
  "properties": {
    "gn:admin1_code":"03",
    "gn:admin2_code":"318.0",
    "gn:admin3_code":"31832.0",
    "gn:asciiname":"Ofenbach",
    "gn:country_code":"AT",
    "gn:dem":444,
    "gn:feature_class":"P",
    "gn:feature_code":"PPL",
    "gn:name":"Ofenbach",
    "gn:population":0,
    "gn:timezone":"Europe/Vienna",
    "iso:country":"AT",
    "wof:name":"Ofenbach",
    "wof:placetype":"locality"
},
  "geometry": {"coordinates":[16.15,47.65],"type":"Point"}
}