{
  "type": "Feature",
  "properties": {
    "gn:admin1_code":"6.0",
    "gn:admin2_code":"612",
    "gn:admin3_code":"61252.0",
    "gn:asciiname":"Maitschern",
    "gn:country_code":"AT",
    "gn:dem":714,
    "gn:feature_class":"P",
    "gn:feature_code":"PPL",
    "gn:name":"Maitschern",
    "gn:population":405,
    "gn:timezone":"Europe/Vienna",
    "iso:country":"AT",
    "wof:name":"Maitschern",
    "wof:placetype":"locality",
    "wof:population":405
},
  "geometry": {"coordinates":[14.13333,47.55],"type":"Point"}
}