{
  "type": "Feature",
  "properties": {
    "gn:admin1_code":"2.0",
    "gn:admin2_code":"208",
    "gn:admin3_code":"20812.0",
    "gn:asciiname":"Draugegend",
    "gn:cc2":"AT",
    "gn:country_code":"AT",
    "gn:dem":458,
    "gn:feature_class":"P",
    "gn:feature_code":"PPL",
    "gn:name":"Draugegend",
    "gn:population":0,
    "gn:timezone":"Europe/Vienna",
    "iso:country":"AT",
    "name:deu_x_preferred":[
        "Draugegend"
    ],
    "name:slv_x_preferred":[
        "Pri Dravi"
    ],
    "name:und_x_variant":[
        "Pri Dravi"
    ],
    "wof:name":"Draugegend",
    "wof:placetype":"locality"
},
  "geometry": {"coordinates":[14.83333,46.65],"type":"Point"}
}