{
  "type": "Feature",
  "properties": {
    "gn:admin1_code":"07",
    "gn:admin2_code":"706.0",
    "gn:admin3_code":"70609.0",
    "gn:asciiname":"Ulmich",
    "gn:country_code":"AT",
    "gn:dem":1620,
    "gn:feature_class":"P",
    "gn:feature_code":"PPL",
    "gn:name":"Ulmich",
    "gn:population":0,
    "gn:timezone":"Europe/Vienna",
    "iso:country":"AT",
    "wof:name":"Ulmich",
    "wof:placetype":"locality"
},
  "geometry": {"coordinates":[10.33333,47.05],"type":"Point"}
}