{
  "type": "Feature",
  "properties": {
    "gn:admin1_code":"04",
    "gn:admin2_code":"416.0",
    "gn:admin3_code":"41618.0",
    "gn:asciiname":"Unterpuchenau",
    "gn:country_code":"AT",
    "gn:dem":483,
    "gn:feature_class":"P",
    "gn:feature_code":"PPL",
    "gn:name":"Unterpuchenau",
    "gn:population":690,
    "gn:timezone":"Europe/Vienna",
    "iso:country":"AT",
    "wof:name":"Unterpuchenau",
    "wof:placetype":"locality",
    "wof:population":690
},
  "geometry": {"coordinates":[14.2345,48.32812],"type":"Point"}
}