{
  "type": "Feature",
  "properties": {
    "gn:admin1_code":"6.0",
    "gn:admin2_code":"622",
    "gn:admin3_code":"62205.0",
    "gn:asciiname":"Noiberg",
    "gn:country_code":"AT",
    "gn:dem":361,
    "gn:feature_class":"P",
    "gn:feature_code":"PPL",
    "gn:name":"Noiberg",
    "gn:population":0,
    "gn:timezone":"Europe/Vienna",
    "iso:country":"AT",
    "wof:name":"Noiberg",
    "wof:placetype":"locality"
},
  "geometry": {"coordinates":[16.00822,47.24274000000001],"type":"Point"}
}