{
  "type": "Feature",
  "properties": {
    "gn:admin1_code":"4.0",
    "gn:admin2_code":"417",
    "gn:admin3_code":"41748.0",
    "gn:asciiname":"Steinwand",
    "gn:country_code":"AT",
    "gn:dem":536,
    "gn:feature_class":"P",
    "gn:feature_code":"PPL",
    "gn:name":"Steinwand",
    "gn:population":62,
    "gn:timezone":"Europe/Vienna",
    "iso:country":"AT",
    "name:ceb_x_preferred":[
        "Steinwand"
    ],
    "name:deu_x_preferred":[
        "Steinwand"
    ],
    "name:swe_x_preferred":[
        "Steinwand"
    ],
    "wof:name":"Steinwand",
    "wof:placetype":"locality",
    "wof:population":62
},
  "geometry": {"coordinates":[13.40924,47.96981],"type":"Point"}
}