{
  "type": "Feature",
  "properties": {
    "gn:admin1_code":"5.0",
    "gn:admin2_code":"506",
    "gn:admin3_code":"50602.0",
    "gn:asciiname":"Furstau",
    "gn:country_code":"AT",
    "gn:dem":773,
    "gn:feature_class":"P",
    "gn:feature_code":"PPL",
    "gn:name":"F\u00fcrstau",
    "gn:population":0,
    "gn:timezone":"Europe/Vienna",
    "iso:country":"AT",
    "wof:name":"Furstau",
    "wof:placetype":"locality"
},
  "geometry": {"coordinates":[12.88333,47.28333],"type":"Point"}
}