{
  "type": "Feature",
  "properties": {
    "gn:admin1_code":"6.0",
    "gn:admin2_code":"621",
    "gn:admin3_code":"62143.0",
    "gn:asciiname":"Lambach",
    "gn:country_code":"AT",
    "gn:dem":668,
    "gn:feature_class":"P",
    "gn:feature_code":"PPL",
    "gn:name":"Lambach",
    "gn:population":137,
    "gn:timezone":"Europe/Vienna",
    "iso:country":"AT",
    "name:ces_x_preferred":[
        "Lambach"
    ],
    "name:dan_x_preferred":[
        "Lambach"
    ],
    "name:deu_x_preferred":[
        "Lambach"
    ],
    "name:fas_x_preferred":[
        "\u0644\u0627\u0645\u0628\u0627\u062e"
    ],
    "name:fin_x_preferred":[
        "Lambach"
    ],
    "name:fra_x_preferred":[
        "Lambach"
    ],
    "name:hun_x_preferred":[
        "Lambach"
    ],
    "name:ind_x_preferred":[
        "Lambach"
    ],
    "name:ita_x_preferred":[
        "Lambach"
    ],
    "name:kaz_x_preferred":[
        "\u041b\u0430\u043c\u0431\u0430\u0445"
    ],
    "name:nld_x_preferred":[
        "Lambach"
    ],
    "name:nor_x_preferred":[
        "Lambach"
    ],
    "name:pol_x_preferred":[
        "Lambach"
    ],
    "name:por_x_preferred":[
        "Lambach"
    ],
    "name:rus_x_preferred":[
        "\u041b\u0430\u043c\u0431\u0430\u0445"
    ],
    "name:slk_x_preferred":[
        "Lambach"
    ],
    "name:spa_x_preferred":[
        "Lambach"
    ],
    "name:ukr_x_preferred":[
        "\u041b\u0430\u043c\u0431\u0430\u0445"
    ],
    "name:uzb_x_preferred":[
        "Lambach"
    ],
    "name:vol_x_preferred":[
        "Lambach"
    ],
    "name:war_x_preferred":[
        "Lambach"
    ],
    "wof:name":"Lambach",
    "wof:placetype":"locality",
    "wof:population":137
},
  "geometry": {"coordinates":[15.66408,47.60415],"type":"Point"}
}