{
  "type": "Feature",
  "properties": {
    "gn:admin1_code":"6.0",
    "gn:admin2_code":"621",
    "gn:admin3_code":"62143.0",
    "gn:asciiname":"Lambach",
    "gn:country_code":"AT",
    "gn:dem":668,
    "gn:feature_class":"P",
    "gn:feature_code":"PPL",
    "gn:name":"Lambach",
    "gn:population":137,
    "gn:timezone":"Europe/Vienna",
    "iso:country":"AT",
    "wof:name":"Lambach",
    "wof:placetype":"locality",
    "wof:population":137
},
  "geometry": {"coordinates":[15.66408,47.60415],"type":"Point"}
}