{
  "type": "Feature",
  "properties": {
    "gn:admin1_code":"4.0",
    "gn:admin2_code":"407",
    "gn:admin3_code":"40713.0",
    "gn:asciiname":"Obernathal",
    "gn:country_code":"AT",
    "gn:dem":461,
    "gn:feature_class":"P",
    "gn:feature_code":"PPL",
    "gn:name":"Obernathal",
    "gn:population":28,
    "gn:timezone":"Europe/Vienna",
    "iso:country":"AT",
    "wof:name":"Obernathal",
    "wof:placetype":"locality",
    "wof:population":28
},
  "geometry": {"coordinates":[13.78269,47.97728],"type":"Point"}
}