{
  "type": "Feature",
  "properties": {
    "gn:gn_country":"AT",
    "gn:gn_fcode":"PPL",
    "gn:gn_pop":0,
    "iso:country":"AT",
    "name:ceb_x_preferred":[
        "Zell am Moos"
    ],
    "name:deu_x_preferred":[
        "Zell am Moos"
    ],
    "name:eng_x_preferred":[
        "Zell am Moos"
    ],
    "name:fas_x_preferred":[
        "\u0633\u0644 \u0627\u0645 \u0645\u0648\u0633"
    ],
    "name:fra_x_preferred":[
        "Zell am Moos"
    ],
    "name:hun_x_preferred":[
        "Zell am Moos"
    ],
    "name:ita_x_preferred":[
        "Zell am Moos"
    ],
    "name:kaz_x_preferred":[
        "\u0426\u0435\u043b\u043b\u044c-\u043d\u0430-\u041c\u043e\u0441\u0435"
    ],
    "name:nld_x_preferred":[
        "Zell am Moos"
    ],
    "name:pol_x_preferred":[
        "Zell am Moos"
    ],
    "name:por_x_preferred":[
        "Zell am Moos"
    ],
    "name:rus_x_preferred":[
        "\u0426\u0435\u043b\u043b\u044c-\u043d\u0430-\u041c\u043e\u0441\u0435"
    ],
    "name:slk_x_preferred":[
        "Zell am Moos"
    ],
    "name:spa_x_preferred":[
        "Zell am Moos"
    ],
    "name:swe_x_preferred":[
        "Zell am Moos"
    ],
    "name:uzb_x_preferred":[
        "Zell am Moos"
    ],
    "name:vie_x_preferred":[
        "Zell am Moos"
    ],
    "name:vol_x_preferred":[
        "Zell am Moos"
    ],
    "name:war_x_preferred":[
        "Zell am Moos"
    ],
    "name:zho_x_preferred":[
        "Zell am Moos"
    ],
    "qs_pg:aaroncc":"AT",
    "qs_pg:gn_country":"AT",
    "qs_pg:gn_fcode":"PPL",
    "qs_pg:gn_pop":0,
    "qs_pg:name":"Zell am Moos",
    "qs_pg:name_adm0":"\u00d6sterreich",
    "qs_pg:name_adm1":"Ober\u00f6sterreich",
    "qs_pg:photos":123,
    "qs_pg:photos_1k":25,
    "qs_pg:photos_9k":1,
    "qs_pg:photos_9r":3,
    "qs_pg:photos_all":123,
    "qs_pg:photos_sr":3,
    "qs_pg:pop_sr":0,
    "qs_pg:qs_pg_placetype":"locality",
    "qs_pg:qs_pg_placetype_gp":"Town",
    "qs_pg:woe_adm0":23424750,
    "woe:adm0_id":23424750,
    "woe:name_adm0":"\u00d6sterreich",
    "woe:name_adm1":"Ober\u00f6sterreich",
    "woe:placetype":"Town",
    "wof:name":"Zell am Moos",
    "wof:placetype":"locality"
},
  "geometry": {"coordinates":[13.51667,47.86667],"type":"Point"}
}