{
  "type": "Feature",
  "properties": {
    "gn:admin1_code":"7.0",
    "gn:admin2_code":"705",
    "gn:admin3_code":"70527.0",
    "gn:asciiname":"Jochberg",
    "gn:country_code":"AT",
    "gn:dem":825,
    "gn:feature_class":"P",
    "gn:feature_code":"PPL",
    "gn:name":"Jochberg",
    "gn:population":0,
    "gn:timezone":"Europe/Vienna",
    "iso:country":"AT",
    "name:ceb_x_preferred":[
        "Jochberg"
    ],
    "name:deu_x_preferred":[
        "Jochberg"
    ],
    "name:ita_x_preferred":[
        "Jochberg"
    ],
    "name:pol_x_preferred":[
        "Jochberg"
    ],
    "name:swe_x_preferred":[
        "Jochberg"
    ],
    "wof:name":"Jochberg",
    "wof:placetype":"locality"
},
  "geometry": {"coordinates":[12.03333,47.58333],"type":"Point"}
}