{
  "type": "Feature",
  "properties": {
    "gn:admin1_code":"3.0",
    "gn:admin2_code":"319",
    "gn:admin3_code":"31901.0",
    "gn:asciiname":"Hart",
    "gn:country_code":"AT",
    "gn:dem":418,
    "gn:feature_class":"P",
    "gn:feature_code":"PPL",
    "gn:name":"Hart",
    "gn:population":81,
    "gn:timezone":"Europe/Vienna",
    "iso:country":"AT",
    "wof:name":"Hart",
    "wof:placetype":"locality",
    "wof:population":81
},
  "geometry": {"coordinates":[15.92546,48.16929],"type":"Point"}
}