{
  "type": "Feature",
  "properties": {
    "gn:admin1_code":"3.0",
    "gn:admin2_code":"307",
    "gn:admin3_code":"30731.0",
    "gn:asciiname":"Neu-Reisenberg",
    "gn:country_code":"AT",
    "gn:dem":176,
    "gn:feature_class":"P",
    "gn:feature_code":"PPL",
    "gn:name":"Neu-Reisenberg",
    "gn:population":0,
    "gn:timezone":"Europe/Vienna",
    "iso:country":"AT",
    "wof:name":"Neu-Reisenberg",
    "wof:placetype":"locality"
},
  "geometry": {"coordinates":[16.49583,48.0225],"type":"Point"}
}