{
  "type": "Feature",
  "properties": {
    "gn:country":"AT",
    "gn:fcode":"PPL",
    "gn:population":0,
    "iso:country":"AT",
    "name:cat_x_preferred":[
        "Pulkau"
    ],
    "name:ceb_x_preferred":[
        "Pulkau"
    ],
    "name:ces_x_preferred":[
        "Pulkau"
    ],
    "name:deu_x_preferred":[
        "Pulkau"
    ],
    "name:eng_x_preferred":[
        "Pulkau"
    ],
    "name:epo_x_preferred":[
        "Pulkau"
    ],
    "name:fas_x_preferred":[
        "\u067e\u0648\u0644\u06a9\u0648"
    ],
    "name:fra_x_preferred":[
        "Pulkau"
    ],
    "name:hun_x_preferred":[
        "Pulkau"
    ],
    "name:ita_x_preferred":[
        "Pulkau"
    ],
    "name:kaz_x_preferred":[
        "\u041f\u0443\u043b\u044c\u043a\u0430\u0443"
    ],
    "name:nld_x_preferred":[
        "Pulkau"
    ],
    "name:pol_x_preferred":[
        "Pulkau"
    ],
    "name:por_x_preferred":[
        "Pulkau"
    ],
    "name:rus_x_preferred":[
        "\u041f\u0443\u043b\u044c\u043a\u0430\u0443"
    ],
    "name:slk_x_preferred":[
        "Pulkau"
    ],
    "name:slv_x_preferred":[
        "Pulkava"
    ],
    "name:spa_x_preferred":[
        "Pulkau"
    ],
    "name:swe_x_preferred":[
        "Pulkau"
    ],
    "name:uzb_x_preferred":[
        "Pulkau"
    ],
    "name:vie_x_preferred":[
        "Pulkau"
    ],
    "name:vol_x_preferred":[
        "Pulkau"
    ],
    "name:war_x_preferred":[
        "Pulkau"
    ],
    "name:zho_x_preferred":[
        "\u666e\u5c14\u8003"
    ],
    "qs_pg:aaroncc":"AT",
    "qs_pg:gn_country":"AT",
    "qs_pg:gn_fcode":"PPL",
    "qs_pg:gn_pop":0,
    "qs_pg:name":"Pulkau",
    "qs_pg:name_adm0":"\u00d6sterreich",
    "qs_pg:name_adm1":"Nieder\u00f6sterreich",
    "qs_pg:photos":328,
    "qs_pg:photos_1k":66,
    "qs_pg:photos_9k":1,
    "qs_pg:photos_9r":5,
    "qs_pg:photos_all":328,
    "qs_pg:photos_sr":5,
    "qs_pg:pop_sr":0,
    "qs_pg:qs_pg_placetype":"locality",
    "qs_pg:qs_pg_placetype_gp":"Town",
    "qs_pg:woe_adm0":23424750,
    "woe:adm0_id":23424750,
    "woe:name_adm0":"\u00d6sterreich",
    "woe:name_adm1":"Nieder\u00f6sterreich",
    "woe:placetype":"Town",
    "wof:name":"Pulkau",
    "wof:placetype":"locality"
},
  "geometry": {"coordinates":[15.84306,48.70667],"type":"Point"}
}