{
  "type": "Feature",
  "properties": {
    "iso:country":"AT",
    "qs_pg:aaroncc":"AT",
    "qs_pg:name":"St. Gallenkirch",
    "qs_pg:name_adm0":"\u00d6sterreich",
    "qs_pg:name_adm1":"Vorarlberg",
    "qs_pg:photos":135,
    "qs_pg:photos_1k":27,
    "qs_pg:photos_9k":1,
    "qs_pg:photos_9r":3,
    "qs_pg:photos_all":135,
    "qs_pg:photos_sr":3,
    "qs_pg:pop_sr":0,
    "qs_pg:qs_pg_placetype":"locality",
    "qs_pg:qs_pg_placetype_gp":"Town",
    "qs_pg:woe_adm0":23424750,
    "woe:adm0_id":23424750,
    "woe:name_adm0":"\u00d6sterreich",
    "woe:name_adm1":"Vorarlberg",
    "woe:placetype":"Town",
    "wof:name":"St. Gallenkirch",
    "wof:placetype":"locality"
},
  "geometry": {"coordinates":[9.969189,47.023221],"type":"Point"}
}