{
  "type": "Feature",
  "properties": {
    "gn:admin1_code":"04",
    "gn:admin2_code":"413.0",
    "gn:admin3_code":"41343.0",
    "gn:asciiname":"Rudolfing",
    "gn:country_code":"AT",
    "gn:dem":597,
    "gn:feature_class":"P",
    "gn:feature_code":"PPL",
    "gn:name":"Rudolfing",
    "gn:population":118,
    "gn:timezone":"Europe/Vienna",
    "iso:country":"AT",
    "wof:name":"Rudolfing",
    "wof:placetype":"locality",
    "wof:population":118
},
  "geometry": {"coordinates":[13.96259,48.6506],"type":"Point"}
}