{
  "type": "Feature",
  "properties": {
    "gn:admin1_code":"06",
    "gn:admin2_code":"623.0",
    "gn:admin3_code":"62387.0",
    "gn:asciiname":"Risola",
    "gn:country_code":"AT",
    "gn:dem":291,
    "gn:feature_class":"P",
    "gn:feature_code":"PPL",
    "gn:name":"Risola",
    "gn:population":74,
    "gn:timezone":"Europe/Vienna",
    "iso:country":"AT",
    "wof:name":"Risola",
    "wof:placetype":"locality",
    "wof:population":74
},
  "geometry": {"coordinates":[15.96667,46.81667],"type":"Point"}
}