{
  "type": "Feature",
  "properties": {
    "gn:admin1_code":"4.0",
    "gn:admin2_code":"417",
    "gn:admin3_code":"41709.0",
    "gn:asciiname":"Hoblschlag",
    "gn:country_code":"AT",
    "gn:dem":717,
    "gn:feature_class":"P",
    "gn:feature_code":"PPL",
    "gn:name":"Hoblschlag",
    "gn:population":52,
    "gn:timezone":"Europe/Vienna",
    "iso:country":"AT",
    "wof:name":"Hoblschlag",
    "wof:placetype":"locality",
    "wof:population":52
},
  "geometry": {"coordinates":[13.51868,48.10179],"type":"Point"}
}