{
  "type": "Feature",
  "properties": {
    "gn:admin1_code":"04",
    "gn:admin2_code":"413.0",
    "gn:admin3_code":"41304.0",
    "gn:asciiname":"Unteredt",
    "gn:country_code":"AT",
    "gn:dem":539,
    "gn:feature_class":"P",
    "gn:feature_code":"PPL",
    "gn:name":"Unteredt",
    "gn:population":42,
    "gn:timezone":"Europe/Vienna",
    "iso:country":"AT",
    "wof:name":"Unteredt",
    "wof:placetype":"locality",
    "wof:population":42
},
  "geometry": {"coordinates":[13.93805,48.46262],"type":"Point"}
}