{
  "type": "Feature",
  "properties": {
    "gn:admin1_code":"03",
    "gn:admin2_code":"319.0",
    "gn:admin3_code":"31918.0",
    "gn:asciiname":"Tradigist Dorf",
    "gn:country_code":"AT",
    "gn:dem":385,
    "gn:feature_class":"P",
    "gn:feature_code":"PPL",
    "gn:name":"Tradigist Dorf",
    "gn:population":0,
    "gn:timezone":"Europe/Vienna",
    "iso:country":"AT",
    "name:und_x_variant":[
        "Tradigistdorf"
    ],
    "wof:name":"Tradigist Dorf",
    "wof:placetype":"locality"
},
  "geometry": {"coordinates":[15.46188,48.03138],"type":"Point"}
}