{
  "type": "Feature",
  "properties": {
    "gn:admin1_code":"5.0",
    "gn:admin2_code":"503",
    "gn:admin3_code":"50335.0",
    "gn:asciiname":"Ausserroid",
    "gn:country_code":"AT",
    "gn:dem":555,
    "gn:feature_class":"P",
    "gn:feature_code":"PPL",
    "gn:name":"Ausserroid",
    "gn:population":0,
    "gn:timezone":"Europe/Vienna",
    "iso:country":"AT",
    "wof:name":"Ausserroid",
    "wof:placetype":"locality"
},
  "geometry": {"coordinates":[13.29114,47.98119000000001],"type":"Point"}
}