{
  "type": "Feature",
  "properties": {
    "gn:admin1_code":"02",
    "gn:admin2_code":"203.0",
    "gn:admin3_code":"20306.0",
    "gn:asciiname":"Unterdoebernitzen",
    "gn:country_code":"AT",
    "gn:dem":621,
    "gn:feature_class":"P",
    "gn:feature_code":"PPL",
    "gn:name":"Unterd\u00f6bernitzen",
    "gn:population":24,
    "gn:timezone":"Europe/Vienna",
    "iso:country":"AT",
    "wof:name":"Unterdoebernitzen",
    "wof:placetype":"locality",
    "wof:population":24
},
  "geometry": {"coordinates":[13.19072,46.62987],"type":"Point"}
}