{
  "type": "Feature",
  "properties": {
    "gn:admin1_code":"02",
    "gn:admin2_code":"207.0",
    "gn:admin3_code":"20711.0",
    "gn:asciiname":"Susalitsch",
    "gn:country_code":"AT",
    "gn:dem":627,
    "gn:feature_class":"P",
    "gn:feature_code":"PPL",
    "gn:name":"Susalitsch",
    "gn:population":98,
    "gn:timezone":"Europe/Vienna",
    "iso:country":"AT",
    "wof:name":"Susalitsch",
    "wof:placetype":"locality",
    "wof:population":98
},
  "geometry": {"coordinates":[13.83818,46.55104],"type":"Point"}
}