{
  "type": "Feature",
  "properties": {
    "gn:admin1_code":"4.0",
    "gn:admin2_code":"414",
    "gn:admin3_code":"41410.0",
    "gn:asciiname":"Ausserhareth",
    "gn:country_code":"AT",
    "gn:dem":491,
    "gn:feature_class":"P",
    "gn:feature_code":"PPL",
    "gn:name":"Au\u00dferhareth",
    "gn:population":0,
    "gn:timezone":"Europe/Vienna",
    "iso:country":"AT",
    "wof:name":"Ausserhareth",
    "wof:placetype":"locality"
},
  "geometry": {"coordinates":[13.52917,48.54167],"type":"Point"}
}