{
  "type": "Feature",
  "properties": {
    "gn:admin1_code":"06",
    "gn:admin2_code":"623.0",
    "gn:admin3_code":"62378.0",
    "gn:asciiname":"Hirzenriegel",
    "gn:country_code":"AT",
    "gn:dem":337,
    "gn:feature_class":"P",
    "gn:feature_code":"PPL",
    "gn:name":"Hirzenriegel",
    "gn:population":0,
    "gn:timezone":"Europe/Vienna",
    "iso:country":"AT",
    "wof:name":"Hirzenriegel",
    "wof:placetype":"locality"
},
  "geometry": {"coordinates":[16.05,46.91667],"type":"Point"}
}