{
  "type": "Feature",
  "properties": {
    "gn:admin1_code":"4.0",
    "gn:admin2_code":"408",
    "gn:admin3_code":"40811.0",
    "gn:asciiname":"Panbruck",
    "gn:country_code":"AT",
    "gn:dem":400,
    "gn:feature_class":"P",
    "gn:feature_code":"PPL",
    "gn:name":"Panbruck",
    "gn:population":22,
    "gn:timezone":"Europe/Vienna",
    "iso:country":"AT",
    "wof:name":"Panbruck",
    "wof:placetype":"locality",
    "wof:population":22
},
  "geometry": {"coordinates":[13.71566,48.2169],"type":"Point"}
}