{
  "type": "Feature",
  "properties": {
    "iso:country":"AT",
    "name:deu_x_preferred":[
        "Ro\u00dfegg"
    ],
    "name:eng_x_preferred":[
        "Rossegg"
    ],
    "wof:name":"Rossegg",
    "wof:placetype":"neighbourhood"
},
  "geometry": {"coordinates":[15.43343973876215,47.12244700936579],"type":"Point"}
}