{
  "type": "Feature",
  "properties": {
    "gn:admin1_code":"4.0",
    "gn:admin2_code":"406",
    "gn:admin3_code":"40610.0",
    "gn:asciiname":"Leopoldschlag Dorf",
    "gn:country_code":"AT",
    "gn:dem":676,
    "gn:feature_class":"P",
    "gn:feature_code":"PPL",
    "gn:name":"Leopoldschlag Dorf",
    "gn:population":0,
    "gn:timezone":"Europe/Vienna",
    "iso:country":"AT",
    "wof:name":"Leopoldschlag Dorf",
    "wof:placetype":"locality"
},
  "geometry": {"coordinates":[14.48539,48.61282],"type":"Point"}
}