{
  "type": "Feature",
  "properties": {
    "gn:admin1_code":"4.0",
    "gn:admin2_code":"417",
    "gn:admin3_code":"41709.0",
    "gn:asciiname":"Ottigen",
    "gn:country_code":"AT",
    "gn:dem":649,
    "gn:feature_class":"P",
    "gn:feature_code":"PPL",
    "gn:name":"Ottigen",
    "gn:population":5,
    "gn:timezone":"Europe/Vienna",
    "iso:country":"AT",
    "wof:name":"Ottigen",
    "wof:placetype":"locality",
    "wof:population":5
},
  "geometry": {"coordinates":[13.5182,48.08897],"type":"Point"}
}