{
  "type": "Feature",
  "properties": {
    "gn:admin1_code":"04",
    "gn:admin2_code":"407.0",
    "gn:admin3_code":"40703.0",
    "gn:asciiname":"Koesslbach",
    "gn:country_code":"AT",
    "gn:dem":693,
    "gn:feature_class":"P",
    "gn:feature_code":"PPL",
    "gn:name":"K\u00f6\u00dflbach",
    "gn:population":85,
    "gn:timezone":"Europe/Vienna",
    "iso:country":"AT",
    "wof:name":"Koesslbach",
    "wof:placetype":"locality",
    "wof:population":85
},
  "geometry": {"coordinates":[13.66667,47.73333],"type":"Point"}
}