{
  "type": "Feature",
  "properties": {
    "gn:admin1_code":"6.0",
    "gn:admin2_code":"603",
    "gn:admin3_code":"60345.0",
    "gn:asciiname":"Laaken",
    "gn:country_code":"AT",
    "gn:dem":1150,
    "gn:feature_class":"P",
    "gn:feature_code":"PPL",
    "gn:name":"Laaken",
    "gn:population":13,
    "gn:timezone":"Europe/Vienna",
    "iso:country":"AT",
    "wof:name":"Laaken",
    "wof:placetype":"locality",
    "wof:population":13
},
  "geometry": {"coordinates":[15.08333,46.65],"type":"Point"}
}