{
  "type": "Feature",
  "properties": {
    "gn:country":"AT",
    "gn:fcode":"PPL",
    "gn:population":0,
    "iso:country":"AT",
    "name:als_x_preferred":[
        "Stein"
    ],
    "name:ara_x_preferred":[
        "\u0634\u062a\u0627\u064a\u0646"
    ],
    "name:ceb_x_preferred":[
        "Stein"
    ],
    "name:ces_x_preferred":[
        "Stein"
    ],
    "name:dan_x_preferred":[
        "Stein"
    ],
    "name:deu_x_preferred":[
        "Stein"
    ],
    "name:epo_x_preferred":[
        "Stein"
    ],
    "name:eus_x_preferred":[
        "Stein"
    ],
    "name:fas_x_preferred":[
        "\u0627\u0634\u062a\u0627\u06cc\u0646"
    ],
    "name:fin_x_preferred":[
        "Stein"
    ],
    "name:fra_x_preferred":[
        "Stein"
    ],
    "name:frr_x_preferred":[
        "Stian"
    ],
    "name:heb_x_preferred":[
        "\u05e9\u05d8\u05d9\u05d9\u05df"
    ],
    "name:ita_x_preferred":[
        "Stein"
    ],
    "name:jpn_x_preferred":[
        "\u30b7\u30e5\u30bf\u30a4\u30f3"
    ],
    "name:kor_x_preferred":[
        "\uc288\ud0c0\uc778"
    ],
    "name:lmo_x_preferred":[
        "Stein"
    ],
    "name:mkd_x_preferred":[
        "\u0428\u0442\u0430\u0458\u043d"
    ],
    "name:nld_x_preferred":[
        "Stein"
    ],
    "name:nor_x_preferred":[
        "Stein"
    ],
    "name:pol_x_preferred":[
        "Stein"
    ],
    "name:por_x_preferred":[
        "Stein"
    ],
    "name:ron_x_preferred":[
        "Stein"
    ],
    "name:rus_x_preferred":[
        "\u0421\u0442\u0435\u0439\u043d"
    ],
    "name:sco_x_preferred":[
        "Stein"
    ],
    "name:slk_x_preferred":[
        "Stein"
    ],
    "name:spa_x_preferred":[
        "Stein"
    ],
    "name:srp_x_preferred":[
        "\u0428\u0442\u0430\u0458\u043d"
    ],
    "name:swe_x_preferred":[
        "Stein"
    ],
    "name:ukr_x_preferred":[
        "\u0421\u0442\u0435\u0439\u043d"
    ],
    "name:vol_x_preferred":[
        "Stein"
    ],
    "qs_pg:aaroncc":"AT",
    "qs_pg:gn_country":"AT",
    "qs_pg:gn_fcode":"PPL",
    "qs_pg:gn_pop":0,
    "qs_pg:name":"Stein",
    "qs_pg:name_adm0":"Italia",
    "qs_pg:name_adm1":"Trentino-Alto Adige",
    "qs_pg:photos":22,
    "qs_pg:photos_1k":4,
    "qs_pg:photos_9k":1,
    "qs_pg:photos_9r":1,
    "qs_pg:photos_all":22,
    "qs_pg:photos_sr":1,
    "qs_pg:pop_sr":0,
    "qs_pg:qs_pg_placetype":"locality",
    "qs_pg:qs_pg_placetype_gp":"Town",
    "qs_pg:woe_adm0":23424853,
    "woe:adm0_id":23424853,
    "woe:name_adm0":"Italia",
    "woe:name_adm1":"Trentino-Alto Adige",
    "woe:placetype":"Town",
    "wof:name":"Stein",
    "wof:placetype":"locality"
},
  "geometry": {"coordinates":[12.41667,47.01667],"type":"Point"}
}