{
  "type": "Feature",
  "properties": {
    "gn:admin1_code":"3.0",
    "gn:admin2_code":"319",
    "gn:admin3_code":"31912.0",
    "gn:asciiname":"Adletzberg",
    "gn:country_code":"AT",
    "gn:dem":208,
    "gn:feature_class":"P",
    "gn:feature_code":"PPL",
    "gn:name":"Adletzberg",
    "gn:population":81,
    "gn:timezone":"Europe/Vienna",
    "iso:country":"AT",
    "wof:name":"Adletzberg",
    "wof:placetype":"locality",
    "wof:population":81
},
  "geometry": {"coordinates":[15.81379,48.29987],"type":"Point"}
}