{
  "type": "Feature",
  "properties": {
    "gn:admin1_code":"7.0",
    "gn:admin2_code":"707",
    "gn:admin3_code":"70712.0",
    "gn:asciiname":"Glor-Berg",
    "gn:country_code":"AT",
    "gn:dem":1438,
    "gn:feature_class":"P",
    "gn:feature_code":"PPLL",
    "gn:name":"Glor-Berg",
    "gn:population":58,
    "gn:timezone":"Europe/Vienna",
    "iso:country":"AT",
    "wof:name":"Glor-Berg",
    "wof:placetype":"locality",
    "wof:population":58
},
  "geometry": {"coordinates":[12.65483,47.00414],"type":"Point"}
}