{
  "type": "Feature",
  "properties": {
    "gn:admin1_code":"3.0",
    "gn:admin2_code":"320",
    "gn:admin3_code":"32001.0",
    "gn:asciiname":"Mitterau",
    "gn:country_code":"AT",
    "gn:dem":515,
    "gn:feature_class":"P",
    "gn:feature_code":"PPL",
    "gn:name":"Mitterau",
    "gn:population":0,
    "gn:timezone":"Europe/Vienna",
    "iso:country":"AT",
    "wof:name":"Mitterau",
    "wof:placetype":"locality"
},
  "geometry": {"coordinates":[15.06723,47.90334],"type":"Point"}
}