{
  "type": "Feature",
  "properties": {
    "gn:admin1_code":"06",
    "gn:admin2_code":"621.0",
    "gn:admin3_code":"62139.0",
    "gn:asciiname":"Pischk",
    "gn:country_code":"AT",
    "gn:dem":572,
    "gn:feature_class":"P",
    "gn:feature_code":"PPL",
    "gn:name":"Pischk",
    "gn:population":230,
    "gn:timezone":"Europe/Vienna",
    "iso:country":"AT",
    "wof:name":"Pischk",
    "wof:placetype":"locality",
    "wof:population":230
},
  "geometry": {"coordinates":[15.28333,47.41667],"type":"Point"}
}