{
  "type": "Feature",
  "properties": {
    "gn:admin1_code":"7.0",
    "gn:admin2_code":"705",
    "gn:admin3_code":"70505.0",
    "gn:asciiname":"Kleinsoell",
    "gn:country_code":"AT",
    "gn:dem":607,
    "gn:feature_class":"P",
    "gn:feature_code":"PPL",
    "gn:name":"Kleins\u00f6ll",
    "gn:population":512,
    "gn:timezone":"Europe/Vienna",
    "iso:country":"AT",
    "wof:name":"Kleinsoell",
    "wof:placetype":"locality",
    "wof:population":512
},
  "geometry": {"coordinates":[11.99209,47.48513],"type":"Point"}
}