{
  "type": "Feature",
  "properties": {
    "gn:admin1_code":"8.0",
    "gn:admin2_code":"801",
    "gn:admin3_code":"80118.0",
    "gn:asciiname":"Marul",
    "gn:country_code":"AT",
    "gn:dem":997,
    "gn:feature_class":"P",
    "gn:feature_code":"PPL",
    "gn:name":"Marul",
    "gn:population":150,
    "gn:timezone":"Europe/Vienna",
    "iso:country":"AT",
    "name:bul_x_preferred":[
        "\u041c\u0430\u0440\u0443\u043b"
    ],
    "name:ceb_x_preferred":[
        "Marul"
    ],
    "name:fra_x_preferred":[
        "Maroul"
    ],
    "name:mkd_x_preferred":[
        "\u041c\u0430\u0440\u0443\u043b"
    ],
    "name:sqi_x_preferred":[
        "Marulli"
    ],
    "name:srp_x_preferred":[
        "\u041c\u0430\u0440\u0443\u0459"
    ],
    "name:swe_x_preferred":[
        "Marul"
    ],
    "wof:name":"Marul",
    "wof:placetype":"locality",
    "wof:population":150
},
  "geometry": {"coordinates":[9.8616,47.20138],"type":"Point"}
}