{
  "type": "Feature",
  "properties": {
    "gn:admin1_code":"06",
    "gn:admin2_code":"606.0",
    "gn:admin3_code":"60651.0",
    "gn:asciiname":"Waldstein",
    "gn:country_code":"AT",
    "gn:dem":521,
    "gn:feature_class":"P",
    "gn:feature_code":"PPL",
    "gn:name":"Waldstein",
    "gn:population":0,
    "gn:timezone":"Europe/Vienna",
    "iso:country":"AT",
    "name:als_x_preferred":[
        "Waldstein"
    ],
    "name:ceb_x_preferred":[
        "Waldstein"
    ],
    "name:ces_x_preferred":[
        "Vald\u0161tejn"
    ],
    "name:deu_x_preferred":[
        "Waldstein"
    ],
    "name:fin_x_preferred":[
        "Waldstein"
    ],
    "name:jpn_x_preferred":[
        "\u30f4\u30a1\u30eb\u30c8\u30b7\u30e5\u30bf\u30a4\u30f3"
    ],
    "name:pol_x_preferred":[
        "Waldstein"
    ],
    "name:swe_x_preferred":[
        "Waldstein"
    ],
    "wof:name":"Waldstein",
    "wof:placetype":"locality"
},
  "geometry": {"coordinates":[15.26667,47.21667],"type":"Point"}
}