{
  "type": "Feature",
  "properties": {
    "gn:admin1_code":"06",
    "gn:admin2_code":"606.0",
    "gn:admin3_code":"60651.0",
    "gn:asciiname":"Waldstein",
    "gn:country_code":"AT",
    "gn:dem":521,
    "gn:feature_class":"P",
    "gn:feature_code":"PPL",
    "gn:name":"Waldstein",
    "gn:population":0,
    "gn:timezone":"Europe/Vienna",
    "iso:country":"AT",
    "wof:name":"Waldstein",
    "wof:placetype":"locality"
},
  "geometry": {"coordinates":[15.26667,47.21667],"type":"Point"}
}