{
  "type": "Feature",
  "properties": {
    "gn:admin1_code":"04",
    "gn:admin2_code":"412.0",
    "gn:admin3_code":"41220.0",
    "gn:asciiname":"Osternach",
    "gn:country_code":"AT",
    "gn:dem":359,
    "gn:feature_class":"P",
    "gn:feature_code":"PPL",
    "gn:name":"Osternach",
    "gn:population":206,
    "gn:timezone":"Europe/Vienna",
    "iso:country":"AT",
    "wof:name":"Osternach",
    "wof:placetype":"locality",
    "wof:population":206
},
  "geometry": {"coordinates":[13.45207,48.3124],"type":"Point"}
}