{
  "type": "Feature",
  "properties": {
    "gn:admin1_code":"06",
    "gn:admin2_code":"620.0",
    "gn:admin3_code":"62021.0",
    "gn:asciiname":"Zistl",
    "gn:cc2":"AT",
    "gn:country_code":"AT",
    "gn:dem":948,
    "gn:feature_class":"P",
    "gn:feature_code":"PPL",
    "gn:name":"Zistl",
    "gn:population":0,
    "gn:timezone":"Europe/Vienna",
    "iso:country":"AT",
    "name:und_x_variant":[
        "Zistl Wirtshaus",
        "Zistl"
    ],
    "wof:name":"Zistl",
    "wof:placetype":"locality"
},
  "geometry": {"coordinates":[14.45417,47.30444],"type":"Point"}
}