{
  "type": "Feature",
  "properties": {
    "gn:admin1_code":"04",
    "gn:admin2_code":"409.0",
    "gn:admin3_code":"40921.0",
    "gn:asciiname":"Mitterkrotzen",
    "gn:country_code":"AT",
    "gn:dem":785,
    "gn:feature_class":"P",
    "gn:feature_code":"PPL",
    "gn:name":"Mitterkrotzen",
    "gn:population":0,
    "gn:timezone":"Europe/Vienna",
    "iso:country":"AT",
    "wof:name":"Mitterkrotzen",
    "wof:placetype":"locality"
},
  "geometry": {"coordinates":[14.21667,47.71667],"type":"Point"}
}