{
  "type": "Feature",
  "properties": {
    "gn:admin1_code":"2.0",
    "gn:admin2_code":"204",
    "gn:admin3_code":"20409.0",
    "gn:asciiname":"Werda",
    "gn:country_code":"AT",
    "gn:dem":433,
    "gn:feature_class":"P",
    "gn:feature_code":"PPL",
    "gn:name":"Werda",
    "gn:population":10,
    "gn:timezone":"Europe/Vienna",
    "iso:country":"AT",
    "wof:name":"Werda",
    "wof:placetype":"locality",
    "wof:population":10
},
  "geometry": {"coordinates":[14.46346,46.62952],"type":"Point"}
}