{
  "type": "Feature",
  "properties": {
    "gn:admin1_code":"3.0",
    "gn:admin2_code":"322",
    "gn:admin3_code":"32220.0",
    "gn:asciiname":"Goetzles",
    "gn:country_code":"AT",
    "gn:dem":603,
    "gn:feature_class":"P",
    "gn:feature_code":"PPL",
    "gn:name":"G\u00f6tzles",
    "gn:population":52,
    "gn:timezone":"Europe/Vienna",
    "iso:country":"AT",
    "wof:name":"Goetzles",
    "wof:placetype":"locality",
    "wof:population":52
},
  "geometry": {"coordinates":[15.35,48.78333],"type":"Point"}
}