{
  "type": "Feature",
  "properties": {
    "gn:admin1_code":"06",
    "gn:admin2_code":"611.0",
    "gn:admin3_code":"61120.0",
    "gn:asciiname":"Putzenberg",
    "gn:country_code":"AT",
    "gn:dem":736,
    "gn:feature_class":"P",
    "gn:feature_code":"PPL",
    "gn:name":"Putzenberg",
    "gn:population":64,
    "gn:timezone":"Europe/Vienna",
    "iso:country":"AT",
    "wof:name":"Putzenberg",
    "wof:placetype":"locality",
    "wof:population":64
},
  "geometry": {"coordinates":[14.96814,47.42592],"type":"Point"}
}