{
  "type": "Feature",
  "properties": {
    "gn:admin1_code":"3.0",
    "gn:admin2_code":"310",
    "gn:admin3_code":"31009.0",
    "gn:asciiname":"Mittergrabern",
    "gn:country_code":"AT",
    "gn:dem":249,
    "gn:feature_class":"P",
    "gn:feature_code":"PPL",
    "gn:name":"Mittergrabern",
    "gn:population":326,
    "gn:timezone":"Europe/Vienna",
    "iso:country":"AT",
    "wof:name":"Mittergrabern",
    "wof:placetype":"locality",
    "wof:population":326
},
  "geometry": {"coordinates":[16.01667,48.61667],"type":"Point"}
}