{
  "type": "Feature",
  "properties": {
    "gn:admin1_code":"4.0",
    "gn:admin2_code":"418",
    "gn:admin3_code":"41822.0",
    "gn:asciiname":"Fierling",
    "gn:country_code":"AT",
    "gn:dem":382,
    "gn:feature_class":"P",
    "gn:feature_code":"PPL",
    "gn:name":"Fierling",
    "gn:population":0,
    "gn:timezone":"Europe/Vienna",
    "iso:country":"AT",
    "wof:name":"Fierling",
    "wof:placetype":"locality"
},
  "geometry": {"coordinates":[14.03333,48.11667],"type":"Point"}
}