{
  "type": "Feature",
  "properties": {
    "gn:admin1_code":"7.0",
    "gn:admin2_code":"703",
    "gn:admin3_code":"70360.0",
    "gn:asciiname":"Kleinvolderberg",
    "gn:country_code":"AT",
    "gn:dem":963,
    "gn:feature_class":"P",
    "gn:feature_code":"PPL",
    "gn:name":"Kleinvolderberg",
    "gn:population":0,
    "gn:timezone":"Europe/Vienna",
    "iso:country":"AT",
    "wof:name":"Kleinvolderberg",
    "wof:placetype":"locality"
},
  "geometry": {"coordinates":[11.55,47.26667],"type":"Point"}
}