{
  "type": "Feature",
  "properties": {
    "gn:admin1_code":"2.0",
    "gn:admin2_code":"205",
    "gn:admin3_code":"20534.0",
    "gn:asciiname":"Gassing",
    "gn:country_code":"AT",
    "gn:dem":651,
    "gn:feature_class":"P",
    "gn:feature_code":"PPL",
    "gn:name":"Gassing",
    "gn:population":78,
    "gn:timezone":"Europe/Vienna",
    "iso:country":"AT",
    "name:deu_x_preferred":[
        "Gassing"
    ],
    "name:nds_x_preferred":[
        "Gassing"
    ],
    "wof:name":"Gassing",
    "wof:placetype":"locality",
    "wof:population":78
},
  "geometry": {"coordinates":[14.35149,46.78784],"type":"Point"}
}