{
  "type": "Feature",
  "properties": {
    "gn:admin1_code":"4.0",
    "gn:admin2_code":"417",
    "gn:admin3_code":"41729.0",
    "gn:asciiname":"Oberegg",
    "gn:country_code":"AT",
    "gn:dem":641,
    "gn:feature_class":"P",
    "gn:feature_code":"PPL",
    "gn:name":"Oberegg",
    "gn:population":50,
    "gn:timezone":"Europe/Vienna",
    "iso:country":"AT",
    "name:als_x_preferred":[
        "Oberegg"
    ],
    "name:ceb_x_preferred":[
        "Oberegg"
    ],
    "name:deu_x_preferred":[
        "Oberegg"
    ],
    "name:epo_x_preferred":[
        "Oberegg"
    ],
    "name:pol_x_preferred":[
        "Oberegg"
    ],
    "name:swe_x_preferred":[
        "Oberegg"
    ],
    "wof:name":"Oberegg",
    "wof:placetype":"locality",
    "wof:population":50
},
  "geometry": {"coordinates":[13.43971,48.08657],"type":"Point"}
}