{
  "type": "Feature",
  "properties": {
    "gn:admin1_code":"4.0",
    "gn:admin2_code":"417",
    "gn:admin3_code":"41726.0",
    "gn:asciiname":"Schachen",
    "gn:country_code":"AT",
    "gn:dem":596,
    "gn:feature_class":"P",
    "gn:feature_code":"PPL",
    "gn:name":"Schachen",
    "gn:population":30,
    "gn:timezone":"Europe/Vienna",
    "iso:country":"AT",
    "wof:name":"Schachen",
    "wof:placetype":"locality",
    "wof:population":30
},
  "geometry": {"coordinates":[13.32015,48.00939],"type":"Point"}
}