{
  "type": "Feature",
  "properties": {
    "gn:admin1_code":"03",
    "gn:admin2_code":"309.0",
    "gn:admin3_code":"30925.0",
    "gn:asciiname":"Reitzenschlag",
    "gn:country_code":"AT",
    "gn:dem":591,
    "gn:feature_class":"P",
    "gn:feature_code":"PPL",
    "gn:name":"Reitzenschlag",
    "gn:population":140,
    "gn:timezone":"Europe/Vienna",
    "iso:country":"AT",
    "wof:name":"Reitzenschlag",
    "wof:placetype":"locality",
    "wof:population":140
},
  "geometry": {"coordinates":[15.08333,48.95],"type":"Point"}
}