{
  "type": "Feature",
  "properties": {
    "gn:admin1_code":"4.0",
    "gn:admin2_code":"413",
    "gn:admin3_code":"41322.0",
    "gn:asciiname":"Lampersdorf",
    "gn:country_code":"AT",
    "gn:dem":606,
    "gn:feature_class":"P",
    "gn:feature_code":"PPL",
    "gn:name":"Lampersdorf",
    "gn:population":39,
    "gn:timezone":"Europe/Vienna",
    "iso:country":"AT",
    "wof:name":"Lampersdorf",
    "wof:placetype":"locality",
    "wof:population":39
},
  "geometry": {"coordinates":[13.90556,48.47591],"type":"Point"}
}