{
  "type": "Feature",
  "properties": {
    "gn:admin1_code":"6.0",
    "gn:admin2_code":"603",
    "gn:admin3_code":"60345.0",
    "gn:asciiname":"Kornriegel",
    "gn:country_code":"AT",
    "gn:dem":822,
    "gn:feature_class":"P",
    "gn:feature_code":"PPL",
    "gn:name":"Kornriegel",
    "gn:population":0,
    "gn:timezone":"Europe/Vienna",
    "iso:country":"AT",
    "wof:name":"Kornriegel",
    "wof:placetype":"locality"
},
  "geometry": {"coordinates":[15.25,46.65],"type":"Point"}
}