{
  "type": "Feature",
  "properties": {
    "gn:gn_country":"AT",
    "gn:gn_fcode":"PPLA3",
    "gn:gn_pop":0,
    "iso:country":"AT",
    "name:ces_x_preferred":[
        "Leutschach"
    ],
    "name:deu_x_preferred":[
        "Leutschach"
    ],
    "name:eng_x_preferred":[
        "Leutschach"
    ],
    "name:fra_x_preferred":[
        "Leutschach"
    ],
    "name:hun_x_preferred":[
        "Leutschach"
    ],
    "name:ita_x_preferred":[
        "Leutschach"
    ],
    "name:nld_x_preferred":[
        "Leutschach"
    ],
    "name:pol_x_preferred":[
        "Leutschach"
    ],
    "name:rus_x_preferred":[
        "\u041b\u043e\u0439\u0447\u0430\u0445"
    ],
    "name:slk_x_preferred":[
        "Leutschach"
    ],
    "name:slv_x_preferred":[
        "Lu\u010dane"
    ],
    "name:swe_x_preferred":[
        "Leutschach"
    ],
    "name:uzb_x_preferred":[
        "Leutschach"
    ],
    "name:vie_x_preferred":[
        "Leutschach"
    ],
    "name:vol_x_preferred":[
        "Leutschach"
    ],
    "name:war_x_preferred":[
        "Leutschach"
    ],
    "name:zho_x_preferred":[
        "\u6d1b\u4f0a\u67e5\u8d6b"
    ],
    "name:zho_x_variant":[
        "Leutschach"
    ],
    "qs_pg:aaroncc":"AT",
    "qs_pg:gn_country":"AT",
    "qs_pg:gn_fcode":"PPLA3",
    "qs_pg:gn_pop":0,
    "qs_pg:name":"Leutschach",
    "qs_pg:name_adm0":"\u00d6sterreich",
    "qs_pg:name_adm1":"Steiermark",
    "qs_pg:photos":81,
    "qs_pg:photos_1k":16,
    "qs_pg:photos_9k":1,
    "qs_pg:photos_9r":3,
    "qs_pg:photos_all":81,
    "qs_pg:photos_sr":3,
    "qs_pg:pop_sr":0,
    "qs_pg:qs_pg_placetype":"locality",
    "qs_pg:qs_pg_placetype_gp":"Town",
    "qs_pg:woe_adm0":23424750,
    "woe:adm0_id":23424750,
    "woe:name_adm0":"\u00d6sterreich",
    "woe:name_adm1":"Steiermark",
    "woe:placetype":"Town",
    "wof:name":"Leutschach",
    "wof:placetype":"locality"
},
  "geometry": {"coordinates":[15.46889,46.66722],"type":"Point"}
}