{
  "type": "Feature",
  "properties": {
    "gn:admin1_code":"1.0",
    "gn:admin2_code":"109",
    "gn:admin3_code":"10924.0",
    "gn:asciiname":"Glashuetten bei Schlaining",
    "gn:country_code":"AT",
    "gn:dem":593,
    "gn:feature_class":"P",
    "gn:feature_code":"PPL",
    "gn:name":"Glash\u00fctten bei Schlaining",
    "gn:population":116,
    "gn:timezone":"Europe/Vienna",
    "iso:country":"AT",
    "name:deu_x_preferred":[
        "Glash\u00fctten bei Schlaining"
    ],
    "name:epo_x_preferred":[
        "Glash\u00fctten bei Schlaining"
    ],
    "name:hun_x_preferred":[
        "Szal\u00f3nakhuta"
    ],
    "name:und_x_variant":[
        "Glash\u00fctten",
        "Glash\u00fctten bei Schlaining"
    ],
    "wof:name":"Glashuetten bei Schlaining",
    "wof:placetype":"locality",
    "wof:population":116
},
  "geometry": {"coordinates":[16.33333,47.35],"type":"Point"}
}