{
  "type": "Feature",
  "properties": {
    "gn:admin1_code":"4.0",
    "gn:admin2_code":"412",
    "gn:admin3_code":"41221.0",
    "gn:asciiname":"Hochkuchl",
    "gn:country_code":"AT",
    "gn:dem":590,
    "gn:feature_class":"P",
    "gn:feature_code":"PPL",
    "gn:name":"Hochkuchl",
    "gn:population":39,
    "gn:timezone":"Europe/Vienna",
    "iso:country":"AT",
    "wof:name":"Hochkuchl",
    "wof:placetype":"locality",
    "wof:population":39
},
  "geometry": {"coordinates":[13.504,48.15486],"type":"Point"}
}