{
  "type": "Feature",
  "properties": {
    "gn:admin1_code":"6.0",
    "gn:admin2_code":"617",
    "gn:admin3_code":"61751.0",
    "gn:asciiname":"Raas",
    "gn:country_code":"AT",
    "gn:dem":552,
    "gn:feature_class":"P",
    "gn:feature_code":"PPL",
    "gn:name":"Raas",
    "gn:population":184,
    "gn:timezone":"Europe/Vienna",
    "iso:country":"AT",
    "name:ceb_x_preferred":[
        "Raas"
    ],
    "name:swe_x_preferred":[
        "Raas"
    ],
    "wof:name":"Raas",
    "wof:placetype":"locality",
    "wof:population":184
},
  "geometry": {"coordinates":[15.64865,47.23321],"type":"Point"}
}