{
  "type": "Feature",
  "properties": {
    "gn:gn_country":"AT",
    "gn:gn_fcode":"PPL",
    "gn:gn_pop":460,
    "gn:population":460,
    "iso:country":"AT",
    "name:ceb_x_preferred":[
        "Pertisau"
    ],
    "name:deu_x_preferred":[
        "Pertisau"
    ],
    "name:eng_x_preferred":[
        "Pertisau"
    ],
    "name:fra_x_preferred":[
        "Pertisau"
    ],
    "name:ltz_x_preferred":[
        "Pertisau"
    ],
    "name:nld_x_preferred":[
        "Pertisau"
    ],
    "name:pol_x_preferred":[
        "Grossheimschuh"
    ],
    "name:rus_x_preferred":[
        "\u041f\u0435\u0440\u0442\u0438\u0437\u0430\u0443"
    ],
    "name:swe_x_preferred":[
        "Pertisau"
    ],
    "qs_pg:aaroncc":"AT",
    "qs_pg:gn_country":"AT",
    "qs_pg:gn_fcode":"PPL",
    "qs_pg:gn_pop":460,
    "qs_pg:name":"Pertisau",
    "qs_pg:name_adm0":"\u00d6sterreich",
    "qs_pg:name_adm1":"Tirol",
    "qs_pg:photos":1206,
    "qs_pg:photos_1k":244,
    "qs_pg:photos_9k":5,
    "qs_pg:photos_9r":7,
    "qs_pg:photos_all":1206,
    "qs_pg:photos_sr":11,
    "qs_pg:pop_sr":2,
    "qs_pg:qs_pg_placetype":"locality",
    "qs_pg:qs_pg_placetype_gp":"Town",
    "qs_pg:woe_adm0":23424750,
    "woe:adm0_id":23424750,
    "woe:name_adm0":"\u00d6sterreich",
    "woe:name_adm1":"Tirol",
    "woe:placetype":"Town",
    "wof:name":"Pertisau",
    "wof:placetype":"locality",
    "wof:population":460
},
  "geometry": {"coordinates":[11.69486,47.44057],"type":"Point"}
}