{
  "type": "Feature",
  "properties": {
    "gn:admin1_code":"03",
    "gn:admin2_code":"321.0",
    "gn:admin3_code":"32144.0",
    "gn:asciiname":"Steinriegl",
    "gn:country_code":"AT",
    "gn:dem":354,
    "gn:feature_class":"P",
    "gn:feature_code":"PPL",
    "gn:name":"Steinriegl",
    "gn:population":0,
    "gn:timezone":"Europe/Vienna",
    "iso:country":"AT",
    "wof:name":"Steinriegl",
    "wof:placetype":"locality"
},
  "geometry": {"coordinates":[16.23333,48.26667],"type":"Point"}
}