{
  "type": "Feature",
  "properties": {
    "gn:admin1_code":"5.0",
    "gn:admin2_code":"503",
    "gn:admin3_code":"50302.0",
    "gn:asciiname":"Pomed",
    "gn:country_code":"AT",
    "gn:dem":643,
    "gn:feature_class":"P",
    "gn:feature_code":"PPL",
    "gn:name":"Pomed",
    "gn:population":0,
    "gn:timezone":"Europe/Vienna",
    "iso:country":"AT",
    "wof:name":"Pomed",
    "wof:placetype":"locality"
},
  "geometry": {"coordinates":[13.00833,47.91083],"type":"Point"}
}