{
  "type": "Feature",
  "properties": {
    "gn:admin1_code":"4.0",
    "gn:admin2_code":"414",
    "gn:admin3_code":"41419.0",
    "gn:asciiname":"Kleinwiesenhart",
    "gn:country_code":"AT",
    "gn:dem":347,
    "gn:feature_class":"P",
    "gn:feature_code":"PPL",
    "gn:name":"Kleinwiesenhart",
    "gn:population":51,
    "gn:timezone":"Europe/Vienna",
    "iso:country":"AT",
    "wof:name":"Kleinwiesenhart",
    "wof:placetype":"locality",
    "wof:population":51
},
  "geometry": {"coordinates":[13.45568,48.3688],"type":"Point"}
}