{
  "type": "Feature",
  "properties": {
    "gn:admin1_code":"03",
    "gn:admin2_code":"315.0",
    "gn:admin3_code":"31539.0",
    "gn:asciiname":"Seimetzbach",
    "gn:cc2":"AT",
    "gn:country_code":"AT",
    "gn:dem":297,
    "gn:feature_class":"P",
    "gn:feature_code":"PPL",
    "gn:name":"Seimetzbach",
    "gn:population":45,
    "gn:timezone":"Europe/Vienna",
    "iso:country":"AT",
    "name:und_x_variant":[
        "Seimetzback",
        "Seimetsbach"
    ],
    "wof:name":"Seimetzbach",
    "wof:placetype":"locality",
    "wof:population":45
},
  "geometry": {"coordinates":[15.34206,48.15567],"type":"Point"}
}