{
  "type": "Feature",
  "properties": {
    "gn:admin1_code":"04",
    "gn:admin2_code":"408.0",
    "gn:admin3_code":"40832.0",
    "gn:asciiname":"Parzham",
    "gn:country_code":"AT",
    "gn:dem":293,
    "gn:feature_class":"P",
    "gn:feature_code":"PPL",
    "gn:name":"Parzham",
    "gn:population":26,
    "gn:timezone":"Europe/Vienna",
    "iso:country":"AT",
    "wof:name":"Parzham",
    "wof:placetype":"locality",
    "wof:population":26
},
  "geometry": {"coordinates":[13.95942,48.23914],"type":"Point"}
}