{
  "type": "Feature",
  "properties": {
    "gn:admin1_code":"5.0",
    "gn:admin2_code":"505",
    "gn:admin3_code":"50515.0",
    "gn:asciiname":"Gries",
    "gn:country_code":"AT",
    "gn:dem":1245,
    "gn:feature_class":"P",
    "gn:feature_code":"PPL",
    "gn:name":"Gries",
    "gn:population":0,
    "gn:timezone":"Europe/Vienna",
    "iso:country":"AT",
    "name:cat_x_preferred":[
        "Gries"
    ],
    "name:ceb_x_preferred":[
        "Gries"
    ],
    "name:deu_x_preferred":[
        "Gries"
    ],
    "name:fra_x_preferred":[
        "Gries"
    ],
    "name:ita_x_preferred":[
        "Gries"
    ],
    "name:nld_x_preferred":[
        "Gries"
    ],
    "name:pol_x_preferred":[
        "Gries"
    ],
    "name:vol_x_preferred":[
        "Gries"
    ],
    "wof:name":"Gries",
    "wof:placetype":"locality"
},
  "geometry": {"coordinates":[13.46667,47.16667],"type":"Point"}
}