{
  "type": "Feature",
  "properties": {
    "gn:admin1_code":"4.0",
    "gn:admin2_code":"404",
    "gn:admin3_code":"40405.0",
    "gn:asciiname":"Frieseneck",
    "gn:country_code":"AT",
    "gn:dem":417,
    "gn:feature_class":"P",
    "gn:feature_code":"PPL",
    "gn:name":"Frieseneck",
    "gn:population":13,
    "gn:timezone":"Europe/Vienna",
    "iso:country":"AT",
    "wof:name":"Frieseneck",
    "wof:placetype":"locality",
    "wof:population":13
},
  "geometry": {"coordinates":[13.06468,48.17765],"type":"Point"}
}