{
  "type": "Feature",
  "properties": {
    "gn:admin1_code":"4.0",
    "gn:admin2_code":"409",
    "gn:admin3_code":"40912.0",
    "gn:asciiname":"Pratsdorf",
    "gn:country_code":"AT",
    "gn:dem":554,
    "gn:feature_class":"P",
    "gn:feature_code":"PPL",
    "gn:name":"Pratsdorf",
    "gn:population":521,
    "gn:timezone":"Europe/Vienna",
    "iso:country":"AT",
    "wof:name":"Pratsdorf",
    "wof:placetype":"locality",
    "wof:population":521
},
  "geometry": {"coordinates":[14.04619,47.95521],"type":"Point"}
}