{
  "type": "Feature",
  "properties": {
    "gn:admin1_code":"03",
    "gn:admin2_code":"319.0",
    "gn:admin3_code":"31947.0",
    "gn:asciiname":"Wielandsberg",
    "gn:country_code":"AT",
    "gn:dem":343,
    "gn:feature_class":"P",
    "gn:feature_code":"PPL",
    "gn:name":"Wielandsberg",
    "gn:population":0,
    "gn:timezone":"Europe/Vienna",
    "iso:country":"AT",
    "wof:name":"Wielandsberg",
    "wof:placetype":"locality"
},
  "geometry": {"coordinates":[15.56488,48.11626],"type":"Point"}
}