{
  "type": "Feature",
  "properties": {
    "gn:admin1_code":"04",
    "gn:admin2_code":"416.0",
    "gn:admin3_code":"41605.0",
    "gn:asciiname":"Zinngiessing",
    "gn:country_code":"AT",
    "gn:dem":415,
    "gn:feature_class":"P",
    "gn:feature_code":"PPL",
    "gn:name":"Zinngiessing",
    "gn:population":0,
    "gn:timezone":"Europe/Vienna",
    "iso:country":"AT",
    "wof:name":"Zinngiessing",
    "wof:placetype":"locality"
},
  "geometry": {"coordinates":[14.36857,48.34456],"type":"Point"}
}