{
  "type": "Feature",
  "properties": {
    "gn:admin1_code":"3.0",
    "gn:admin2_code":"319",
    "gn:admin3_code":"31918.0",
    "gn:asciiname":"Kirchberggegend",
    "gn:country_code":"AT",
    "gn:dem":550,
    "gn:feature_class":"P",
    "gn:feature_code":"PPL",
    "gn:name":"Kirchberggegend",
    "gn:population":241,
    "gn:timezone":"Europe/Vienna",
    "iso:country":"AT",
    "wof:name":"Kirchberggegend",
    "wof:placetype":"locality",
    "wof:population":241
},
  "geometry": {"coordinates":[15.40712,48.04894],"type":"Point"}
}