{
  "type": "Feature",
  "properties": {
    "iso:country":"AT",
    "name:deu_x_preferred":[
        "Glasenbach"
    ],
    "name:unk_x_variant":[
        "Glasenbach"
    ],
    "qs:gn_adm0_cc":"AT",
    "qs:gn_fcode":"PPL",
    "qs:gn_local":2780113,
    "qs:gn_nam_loc":"elsbethen",
    "qs:gn_namadm1":"05",
    "qs:gn_name":"Glasenbach",
    "qs:local_max":337,
    "qs:local_sum":337,
    "qs:localhoods":1,
    "qs:name":"Glasenbach",
    "qs:name_adm0":"\u00d6sterreich",
    "qs:name_adm1":"Salzburg",
    "qs:name_adm2":"Salzburg-Umgebung",
    "qs:name_lau":"Elsbethen",
    "qs:name_local":"Elsbethen",
    "qs:photo_max":218,
    "qs:photo_sum":337,
    "qs:placetype":"Suburb",
    "qs:quad_count":25,
    "qs:woe_adm0":23424750,
    "qs:woe_adm1":2344712,
    "qs:woe_adm2":12591721,
    "qs:woe_lau":12674739,
    "qs:woe_local":12674739,
    "qs:woe_ver":"7.10.0",
    "wof:lang":[
        "ger"
    ],
    "wof:name":"Glasenbach",
    "wof:placetype":"neighbourhood"
},
  "geometry": {"coordinates":[13.083743,47.768629],"type":"Point"}
}