{
  "type": "Feature",
  "properties": {
    "gn:admin1_code":"3.0",
    "gn:admin2_code":"319",
    "gn:admin3_code":"31930.0",
    "gn:asciiname":"Fugging",
    "gn:country_code":"AT",
    "gn:dem":271,
    "gn:feature_class":"P",
    "gn:feature_code":"PPL",
    "gn:name":"Fugging",
    "gn:population":96,
    "gn:timezone":"Europe/Vienna",
    "iso:country":"AT",
    "name:deu_x_preferred":[
        "Fugging"
    ],
    "name:fas_x_preferred":[
        "\u0641\u0648\u06af\u06cc\u0646\u06af"
    ],
    "name:fra_x_preferred":[
        "Fugging"
    ],
    "wof:name":"Fugging",
    "wof:placetype":"locality",
    "wof:population":96
},
  "geometry": {"coordinates":[15.63372,48.28788],"type":"Point"}
}