{
  "type": "Feature",
  "properties": {
    "gn:admin1_code":"04",
    "gn:admin2_code":"404.0",
    "gn:admin3_code":"40440.0",
    "gn:asciiname":"Sankt Veit im Innkreis",
    "gn:cc2":"AT",
    "gn:country_code":"AT",
    "gn:dem":412,
    "gn:feature_class":"P",
    "gn:feature_code":"PPL",
    "gn:name":"Sankt Veit im Innkreis",
    "gn:population":179,
    "gn:timezone":"Europe/Vienna",
    "iso:country":"AT",
    "name:und_x_variant":[
        "Sankt Veit im Innkreise",
        "Sankt Veit",
        "Sankt Veit im Innkreis"
    ],
    "wof:name":"Sankt Veit im Innkreis",
    "wof:placetype":"locality",
    "wof:population":179
},
  "geometry": {"coordinates":[13.27475,48.20832],"type":"Point"}
}