{
  "type": "Feature",
  "properties": {
    "gn:admin1_code":"04",
    "gn:admin2_code":"404.0",
    "gn:admin3_code":"40440.0",
    "gn:asciiname":"Sankt Veit im Innkreis",
    "gn:cc2":"AT",
    "gn:country_code":"AT",
    "gn:dem":412,
    "gn:feature_class":"P",
    "gn:feature_code":"PPL",
    "gn:name":"Sankt Veit im Innkreis",
    "gn:population":179,
    "gn:timezone":"Europe/Vienna",
    "iso:country":"AT",
    "name:ceb_x_preferred":[
        "Sankt Veit im Innkreis"
    ],
    "name:deu_x_preferred":[
        "St. Veit im Innkreis"
    ],
    "name:fas_x_preferred":[
        "\u0632\u0627\u0646\u06a9\u062a \u0648\u0627\u06cc\u062a \u0627\u06cc\u0645 \u0627\u06cc\u0646\u06a9\u0631\u0627\u06cc\u0633"
    ],
    "name:fra_x_preferred":[
        "Sankt Veit im Innkreis"
    ],
    "name:fur_x_preferred":[
        "Sankt Veit im Innkreis"
    ],
    "name:hun_x_preferred":[
        "Sankt Veit im Innkreis"
    ],
    "name:ita_x_preferred":[
        "Sankt Veit im Innkreis"
    ],
    "name:nld_x_preferred":[
        "Sankt Veit im Innkreis"
    ],
    "name:pol_x_preferred":[
        "St. Veit im Innkreis"
    ],
    "name:por_x_preferred":[
        "Sankt Veit im Innkreis"
    ],
    "name:slk_x_preferred":[
        "Sankt Veit im Innkreis"
    ],
    "name:spa_x_preferred":[
        "Sankt Veit im Innkreis"
    ],
    "name:swe_x_preferred":[
        "Sankt Veit im Innkreis"
    ],
    "name:und_x_variant":[
        "Sankt Veit im Innkreise",
        "Sankt Veit"
    ],
    "name:uzb_x_preferred":[
        "Sankt Veit im Innkreis"
    ],
    "name:vie_x_preferred":[
        "Sankt Veit im Innkreis"
    ],
    "name:vol_x_preferred":[
        "Sankt Veit im Innkreis"
    ],
    "name:war_x_preferred":[
        "Sankt Veit im Innkreis"
    ],
    "wof:name":"Sankt Veit im Innkreis",
    "wof:placetype":"locality",
    "wof:population":179
},
  "geometry": {"coordinates":[13.27475,48.20832],"type":"Point"}
}