{
  "type": "Feature",
  "properties": {
    "gn:admin1_code":"4.0",
    "gn:admin2_code":"418",
    "gn:admin3_code":"41807.0",
    "gn:asciiname":"Hafeld",
    "gn:country_code":"AT",
    "gn:dem":339,
    "gn:feature_class":"P",
    "gn:feature_code":"PPL",
    "gn:name":"Hafeld",
    "gn:population":462,
    "gn:timezone":"Europe/Vienna",
    "iso:country":"AT",
    "wof:name":"Hafeld",
    "wof:placetype":"locality",
    "wof:population":462
},
  "geometry": {"coordinates":[13.91667,48.08333],"type":"Point"}
}