{
  "type": "Feature",
  "properties": {
    "gn:admin1_code":"4.0",
    "gn:admin2_code":"417",
    "gn:admin3_code":"41708.0",
    "gn:asciiname":"Fachberg",
    "gn:country_code":"AT",
    "gn:dem":660,
    "gn:feature_class":"P",
    "gn:feature_code":"PPL",
    "gn:name":"Fachberg",
    "gn:population":7,
    "gn:timezone":"Europe/Vienna",
    "iso:country":"AT",
    "wof:name":"Fachberg",
    "wof:placetype":"locality",
    "wof:population":7
},
  "geometry": {"coordinates":[13.43096,48.03296],"type":"Point"}
}