{
  "type": "Feature",
  "properties": {
    "gn:admin1_code":"2.0",
    "gn:admin2_code":"207",
    "gn:admin3_code":"20722.0",
    "gn:asciiname":"Dragositschach",
    "gn:country_code":"AT",
    "gn:dem":476,
    "gn:feature_class":"P",
    "gn:feature_code":"PPL",
    "gn:name":"Dragositschach",
    "gn:population":56,
    "gn:timezone":"Europe/Vienna",
    "iso:country":"AT",
    "wof:name":"Dragositschach",
    "wof:placetype":"locality",
    "wof:population":56
},
  "geometry": {"coordinates":[14.08585,46.5391],"type":"Point"}
}