{
  "type": "Feature",
  "properties": {
    "gn:admin1_code":"7.0",
    "gn:admin2_code":"707",
    "gn:admin3_code":"70705.0",
    "gn:asciiname":"Klausen",
    "gn:country_code":"AT",
    "gn:dem":1116,
    "gn:feature_class":"P",
    "gn:feature_code":"PPLL",
    "gn:name":"Klausen",
    "gn:population":36,
    "gn:timezone":"Europe/Vienna",
    "iso:country":"AT",
    "wof:name":"Klausen",
    "wof:placetype":"locality",
    "wof:population":36
},
  "geometry": {"coordinates":[12.66466,46.79031],"type":"Point"}
}