{
  "type": "Feature",
  "properties": {
    "gn:admin1_code":"4.0",
    "gn:admin2_code":"414",
    "gn:admin3_code":"41408.0",
    "gn:asciiname":"Matzing",
    "gn:country_code":"AT",
    "gn:dem":474,
    "gn:feature_class":"P",
    "gn:feature_code":"PPL",
    "gn:name":"Matzing",
    "gn:population":89,
    "gn:timezone":"Europe/Vienna",
    "iso:country":"AT",
    "wof:name":"Matzing",
    "wof:placetype":"locality",
    "wof:population":89
},
  "geometry": {"coordinates":[13.68613,48.3845],"type":"Point"}
}