{
  "type": "Feature",
  "properties": {
    "gn:admin1_code":"4.0",
    "gn:admin2_code":"412",
    "gn:admin3_code":"41204.0",
    "gn:asciiname":"Am Sportplatz",
    "gn:country_code":"AT",
    "gn:dem":556,
    "gn:feature_class":"P",
    "gn:feature_code":"PPL",
    "gn:name":"Am Sportplatz",
    "gn:population":97,
    "gn:timezone":"Europe/Vienna",
    "iso:country":"AT",
    "wof:name":"Am Sportplatz",
    "wof:placetype":"locality",
    "wof:population":97
},
  "geometry": {"coordinates":[13.56803,48.14965],"type":"Point"}
}