{
  "type": "Feature",
  "properties": {
    "gn:admin1_code":"3.0",
    "gn:admin2_code":"305",
    "gn:admin3_code":"30510.0",
    "gn:asciiname":"Hinterleiten",
    "gn:country_code":"AT",
    "gn:dem":702,
    "gn:feature_class":"P",
    "gn:feature_code":"PPL",
    "gn:name":"Hinterleiten",
    "gn:population":0,
    "gn:timezone":"Europe/Vienna",
    "iso:country":"AT",
    "wof:name":"Hinterleiten",
    "wof:placetype":"locality"
},
  "geometry": {"coordinates":[14.61353,47.96205],"type":"Point"}
}