{
  "type": "Feature",
  "properties": {
    "gn:admin1_code":"7.0",
    "gn:admin2_code":"707",
    "gn:admin3_code":"70726.0",
    "gn:asciiname":"Feld",
    "gn:country_code":"AT",
    "gn:dem":1308,
    "gn:feature_class":"P",
    "gn:feature_code":"PPL",
    "gn:name":"Feld",
    "gn:population":0,
    "gn:timezone":"Europe/Vienna",
    "iso:country":"AT",
    "wof:name":"Feld",
    "wof:placetype":"locality"
},
  "geometry": {"coordinates":[12.38333,46.91667],"type":"Point"}
}