{
  "type": "Feature",
  "properties": {
    "gn:gn_country":"AT",
    "gn:gn_fcode":"PPLA3",
    "gn:gn_pop":0,
    "iso:country":"AT",
    "name:deu_x_preferred":[
        "Hollersbach im Pinzgau"
    ],
    "name:eng_x_preferred":[
        "Hollersbach im Pinzgau"
    ],
    "name:fra_x_preferred":[
        "Hollersbach im Pinzgau"
    ],
    "name:hun_x_preferred":[
        "Hollersbach im Pinzgau"
    ],
    "name:ita_x_preferred":[
        "Hollersbach im Pinzgau"
    ],
    "name:kaz_x_preferred":[
        "\u0425\u043e\u043b\u043b\u0435\u0440\u0441\u0431\u0430\u0445"
    ],
    "name:nld_x_preferred":[
        "Hollersbach im Pinzgau"
    ],
    "name:pol_x_preferred":[
        "Hollersbach im Pinzgau"
    ],
    "name:ron_x_preferred":[
        "Hollersbach im Pinzgau"
    ],
    "name:rus_x_preferred":[
        "\u0425\u043e\u043b\u043b\u0435\u0440\u0441\u0431\u0430\u0445"
    ],
    "name:slk_x_preferred":[
        "Hollersbach im Pinzgau"
    ],
    "name:swe_x_preferred":[
        "Hollersbach im Pinzgau"
    ],
    "name:ukr_x_preferred":[
        "\u0413\u043e\u043b\u043b\u0435\u0440\u0441\u0431\u0430\u0445-\u0456\u043c-\u041f\u0456\u043d\u0446\u0433\u0430\u0443"
    ],
    "name:unk_x_variant":[
        "Hollersbach"
    ],
    "name:uzb_x_preferred":[
        "Hollersbach im Pinzgau"
    ],
    "name:vie_x_preferred":[
        "Hollersbach im Pinzgau"
    ],
    "name:vol_x_preferred":[
        "Hollersbach im Pinzgau"
    ],
    "name:war_x_preferred":[
        "Hollersbach im Pinzgau"
    ],
    "name:zho_x_preferred":[
        "Hollersbach im Pinzgau"
    ],
    "qs_pg:aaroncc":"AT",
    "qs_pg:gn_country":"AT",
    "qs_pg:gn_fcode":"PPLA3",
    "qs_pg:gn_pop":0,
    "qs_pg:name":"Hollersbach im Pinzgau",
    "qs_pg:name_adm0":"\u00d6sterreich",
    "qs_pg:name_adm1":"Salzburg",
    "qs_pg:photos":160,
    "qs_pg:photos_1k":32,
    "qs_pg:photos_9k":1,
    "qs_pg:photos_9r":4,
    "qs_pg:photos_all":160,
    "qs_pg:photos_sr":4,
    "qs_pg:pop_sr":0,
    "qs_pg:qs_pg_placetype":"locality",
    "qs_pg:qs_pg_placetype_gp":"Town",
    "qs_pg:woe_adm0":23424750,
    "woe:adm0_id":23424750,
    "woe:name_adm0":"\u00d6sterreich",
    "woe:name_adm1":"Salzburg",
    "woe:placetype":"Town",
    "wof:name":"Hollersbach im Pinzgau",
    "wof:placetype":"locality"
},
  "geometry": {"coordinates":[12.41667,47.26667],"type":"Point"}
}