{
  "type": "Feature",
  "properties": {
    "gn:admin1_code":"2.0",
    "gn:admin2_code":"206",
    "gn:admin3_code":"20619.0",
    "gn:asciiname":"Maltaberg",
    "gn:country_code":"AT",
    "gn:dem":1363,
    "gn:feature_class":"P",
    "gn:feature_code":"PPL",
    "gn:name":"Maltaberg",
    "gn:population":68,
    "gn:timezone":"Europe/Vienna",
    "iso:country":"AT",
    "wof:name":"Maltaberg",
    "wof:placetype":"locality",
    "wof:population":68
},
  "geometry": {"coordinates":[13.51667,46.96667],"type":"Point"}
}