{
  "type": "Feature",
  "properties": {
    "gn:admin1_code":"3.0",
    "gn:admin2_code":"325",
    "gn:admin3_code":"32519.0",
    "gn:asciiname":"Marchstein",
    "gn:country_code":"AT",
    "gn:dem":861,
    "gn:feature_class":"P",
    "gn:feature_code":"PPL",
    "gn:name":"Marchstein",
    "gn:population":19,
    "gn:timezone":"Europe/Vienna",
    "iso:country":"AT",
    "wof:name":"Marchstein",
    "wof:placetype":"locality",
    "wof:population":19
},
  "geometry": {"coordinates":[14.95797,48.39248],"type":"Point"}
}