{
  "type": "Feature",
  "properties": {
    "gn:admin1_code":"4.0",
    "gn:admin2_code":"417",
    "gn:admin3_code":"41740.0",
    "gn:asciiname":"Kienklause",
    "gn:country_code":"AT",
    "gn:dem":630,
    "gn:feature_class":"P",
    "gn:feature_code":"PPL",
    "gn:name":"Kienklause",
    "gn:population":6,
    "gn:timezone":"Europe/Vienna",
    "iso:country":"AT",
    "wof:name":"Kienklause",
    "wof:placetype":"locality",
    "wof:population":6
},
  "geometry": {"coordinates":[13.58627,47.84783],"type":"Point"}
}