{
  "type": "Feature",
  "properties": {
    "gn:admin1_code":"4.0",
    "gn:admin2_code":"411",
    "gn:admin3_code":"41123.0",
    "gn:asciiname":"Eizendorf",
    "gn:country_code":"AT",
    "gn:dem":233,
    "gn:feature_class":"P",
    "gn:feature_code":"PPL",
    "gn:name":"Eizendorf",
    "gn:population":2,
    "gn:timezone":"Europe/Vienna",
    "iso:country":"AT",
    "wof:name":"Eizendorf",
    "wof:placetype":"locality",
    "wof:population":2
},
  "geometry": {"coordinates":[14.77155,48.19424],"type":"Point"}
}