{
  "type": "Feature",
  "properties": {
    "gn:admin1_code":"7.0",
    "gn:admin2_code":"705",
    "gn:admin3_code":"70508.0",
    "gn:asciiname":"Buchberg am Kaiser",
    "gn:country_code":"AT",
    "gn:dem":684,
    "gn:feature_class":"P",
    "gn:feature_code":"PPL",
    "gn:name":"Buchberg am Kaiser",
    "gn:population":0,
    "gn:timezone":"Europe/Vienna",
    "iso:country":"AT",
    "name:und_x_variant":[
        "Schwaig",
        "Buchberg",
        "Buchberg am Kaiser"
    ],
    "wof:name":"Buchberg am Kaiser",
    "wof:placetype":"locality"
},
  "geometry": {"coordinates":[12.2428,47.62948],"type":"Point"}
}