{
  "type": "Feature",
  "properties": {
    "gn:admin1_code":"4.0",
    "gn:admin2_code":"410",
    "gn:admin3_code":"41010.0",
    "gn:asciiname":"Kirchberg",
    "gn:country_code":"AT",
    "gn:dem":356,
    "gn:feature_class":"P",
    "gn:feature_code":"PPL",
    "gn:name":"Kirchberg",
    "gn:population":322,
    "gn:timezone":"Europe/Vienna",
    "iso:country":"AT",
    "wof:name":"Kirchberg",
    "wof:placetype":"locality",
    "wof:population":322
},
  "geometry": {"coordinates":[14.15846,48.2644],"type":"Point"}
}