{
  "type": "Feature",
  "properties": {
    "gn:admin1_code":"4.0",
    "gn:admin2_code":"410",
    "gn:admin3_code":"41010.0",
    "gn:asciiname":"Kirchberg",
    "gn:country_code":"AT",
    "gn:dem":356,
    "gn:feature_class":"P",
    "gn:feature_code":"PPL",
    "gn:name":"Kirchberg",
    "gn:population":322,
    "gn:timezone":"Europe/Vienna",
    "iso:country":"AT",
    "name:als_x_preferred":[
        "Kirchberg"
    ],
    "name:bre_x_preferred":[
        "Kirchberg"
    ],
    "name:ceb_x_preferred":[
        "Kirchberg"
    ],
    "name:ces_x_preferred":[
        "Kirchberg"
    ],
    "name:deu_x_preferred":[
        "Kirchberg"
    ],
    "name:epo_x_preferred":[
        "Kirchberg"
    ],
    "name:fas_x_preferred":[
        "\u06a9\u06cc\u0631\u0634\u0628\u0631\u06af"
    ],
    "name:fra_x_preferred":[
        "Kirchberg"
    ],
    "name:hun_x_preferred":[
        "Kirchberg"
    ],
    "name:ita_x_preferred":[
        "Kirchberg"
    ],
    "name:jpn_x_preferred":[
        "\u30ad\u30eb\u30d2\u30d9\u30eb\u30af"
    ],
    "name:lmo_x_preferred":[
        "Kirchberg"
    ],
    "name:nld_x_preferred":[
        "Kirchberg"
    ],
    "name:oci_x_preferred":[
        "Kirchberg"
    ],
    "name:pms_x_preferred":[
        "Kirchberg"
    ],
    "name:pol_x_preferred":[
        "Kirchberg"
    ],
    "name:por_x_preferred":[
        "Kirchberg"
    ],
    "name:ron_x_preferred":[
        "Kirchberg"
    ],
    "name:rus_x_preferred":[
        "\u041a\u0438\u0440\u0445\u0431\u0435\u0440\u0433"
    ],
    "name:spa_x_preferred":[
        "Kirchberg"
    ],
    "name:swe_x_preferred":[
        "Kirchberg"
    ],
    "name:vol_x_preferred":[
        "Kirchberg"
    ],
    "wof:name":"Kirchberg",
    "wof:placetype":"locality",
    "wof:population":322
},
  "geometry": {"coordinates":[14.15846,48.2644],"type":"Point"}
}