{
  "type": "Feature",
  "properties": {
    "gn:admin1_code":"3.0",
    "gn:admin2_code":"321",
    "gn:admin3_code":"32132.0",
    "gn:asciiname":"Neustift",
    "gn:country_code":"AT",
    "gn:dem":188,
    "gn:feature_class":"P",
    "gn:feature_code":"PPLL",
    "gn:name":"Neustift",
    "gn:population":96,
    "gn:timezone":"Europe/Vienna",
    "iso:country":"AT",
    "wof:name":"Neustift",
    "wof:placetype":"locality",
    "wof:population":96
},
  "geometry": {"coordinates":[15.81231,48.32501],"type":"Point"}
}