{
  "type": "Feature",
  "properties": {
    "gn:admin1_code":"4.0",
    "gn:admin2_code":"410",
    "gn:admin3_code":"41005.0",
    "gn:asciiname":"Kristein",
    "gn:country_code":"AT",
    "gn:dem":248,
    "gn:feature_class":"P",
    "gn:feature_code":"PPL",
    "gn:name":"Kristein",
    "gn:population":797,
    "gn:timezone":"Europe/Vienna",
    "iso:country":"AT",
    "wof:name":"Kristein",
    "wof:placetype":"locality",
    "wof:population":797
},
  "geometry": {"coordinates":[14.45,48.21667],"type":"Point"}
}