{
  "type": "Feature",
  "properties": {
    "gn:admin1_code":"03",
    "gn:admin2_code":"320.0",
    "gn:admin3_code":"32015.0",
    "gn:asciiname":"Pyhrafeld",
    "gn:cc2":"AT",
    "gn:country_code":"AT",
    "gn:dem":437,
    "gn:feature_class":"P",
    "gn:feature_code":"PPL",
    "gn:name":"Pyhrafeld",
    "gn:population":33,
    "gn:timezone":"Europe/Vienna",
    "iso:country":"AT",
    "name:und_x_variant":[
        "Pyrafeld",
        "Pyhrafeld"
    ],
    "wof:name":"Pyhrafeld",
    "wof:placetype":"locality",
    "wof:population":33
},
  "geometry": {"coordinates":[14.98333,48.05],"type":"Point"}
}