{
  "type": "Feature",
  "properties": {
    "gn:admin1_code":"6.0",
    "gn:admin2_code":"610",
    "gn:admin3_code":"61017.0",
    "gn:asciiname":"Kehlsdorf",
    "gn:country_code":"AT",
    "gn:dem":284,
    "gn:feature_class":"P",
    "gn:feature_code":"PPL",
    "gn:name":"Kehlsdorf",
    "gn:population":123,
    "gn:timezone":"Europe/Vienna",
    "iso:country":"AT",
    "wof:name":"Kehlsdorf",
    "wof:placetype":"locality",
    "wof:population":123
},
  "geometry": {"coordinates":[15.48333,46.86667],"type":"Point"}
}