{
  "type": "Feature",
  "properties": {
    "gn:admin1_code":"4.0",
    "gn:admin2_code":"416",
    "gn:admin3_code":"41606.0",
    "gn:asciiname":"Oberhart",
    "gn:country_code":"AT",
    "gn:dem":388,
    "gn:feature_class":"P",
    "gn:feature_code":"PPL",
    "gn:name":"Oberhart",
    "gn:population":159,
    "gn:timezone":"Europe/Vienna",
    "iso:country":"AT",
    "wof:name":"Oberhart",
    "wof:placetype":"locality",
    "wof:population":159
},
  "geometry": {"coordinates":[14.08971,48.35893],"type":"Point"}
}