{
  "type": "Feature",
  "properties": {
    "gn:admin1_code":"04",
    "gn:admin2_code":"409.0",
    "gn:admin3_code":"40904.0",
    "gn:asciiname":"Wanzbach",
    "gn:country_code":"AT",
    "gn:dem":417,
    "gn:feature_class":"P",
    "gn:feature_code":"PPL",
    "gn:name":"Wanzbach",
    "gn:population":0,
    "gn:timezone":"Europe/Vienna",
    "iso:country":"AT",
    "wof:name":"Wanzbach",
    "wof:placetype":"locality"
},
  "geometry": {"coordinates":[14.08293,47.93538],"type":"Point"}
}