{
  "type": "Feature",
  "properties": {
    "gn:admin1_code":"3.0",
    "gn:admin2_code":"315",
    "gn:admin3_code":"31546.0",
    "gn:asciiname":"Eitenthal",
    "gn:country_code":"AT",
    "gn:dem":395,
    "gn:feature_class":"P",
    "gn:feature_code":"PPL",
    "gn:name":"Eitenthal",
    "gn:population":0,
    "gn:timezone":"Europe/Vienna",
    "iso:country":"AT",
    "wof:name":"Eitenthal",
    "wof:placetype":"locality"
},
  "geometry": {"coordinates":[15.26667,48.26667],"type":"Point"}
}