{
  "type": "Feature",
  "properties": {
    "gn:admin1_code":"6.0",
    "gn:admin2_code":"610",
    "gn:admin3_code":"61052.0",
    "gn:asciiname":"Krottendorf",
    "gn:country_code":"AT",
    "gn:dem":350,
    "gn:feature_class":"P",
    "gn:feature_code":"PPL",
    "gn:name":"Krottendorf",
    "gn:population":0,
    "gn:timezone":"Europe/Vienna",
    "iso:country":"AT",
    "name:ceb_x_preferred":[
        "Krottendorf"
    ],
    "name:deu_x_preferred":[
        "Krottendorf"
    ],
    "name:fas_x_preferred":[
        "\u06a9\u0631\u0648\u062a\u0646\u062f\u0648\u0631\u0641"
    ],
    "name:fra_x_preferred":[
        "Krottendorf"
    ],
    "name:hun_x_preferred":[
        "Krottendorf"
    ],
    "name:ita_x_preferred":[
        "Krottendorf"
    ],
    "name:nld_x_preferred":[
        "Krottendorf"
    ],
    "name:rus_x_preferred":[
        "\u041a\u0440\u043e\u0442\u0442\u0435\u043d\u0434\u043e\u0440\u0444"
    ],
    "name:slk_x_preferred":[
        "Krottendorf"
    ],
    "name:swe_x_preferred":[
        "Krottendorf"
    ],
    "name:uzb_x_preferred":[
        "Krottendorf"
    ],
    "name:vie_x_preferred":[
        "Krottendorf"
    ],
    "name:vol_x_preferred":[
        "Krottendorf"
    ],
    "name:war_x_preferred":[
        "Krottendorf"
    ],
    "name:zho_x_preferred":[
        "\u514b\u7f57\u6ed5\u591a\u592b"
    ],
    "wof:name":"Krottendorf",
    "wof:placetype":"locality"
},
  "geometry": {"coordinates":[15.53299,46.94001],"type":"Point"}
}