{
  "type": "Feature",
  "properties": {
    "gn:admin1_code":"4.0",
    "gn:admin2_code":"404",
    "gn:admin3_code":"40432.0",
    "gn:asciiname":"Siegerting",
    "gn:country_code":"AT",
    "gn:dem":474,
    "gn:feature_class":"P",
    "gn:feature_code":"PPL",
    "gn:name":"Siegerting",
    "gn:population":134,
    "gn:timezone":"Europe/Vienna",
    "iso:country":"AT",
    "wof:name":"Siegerting",
    "wof:placetype":"locality",
    "wof:population":134
},
  "geometry": {"coordinates":[13.10296,48.14278],"type":"Point"}
}