{
  "type": "Feature",
  "properties": {
    "gn:admin1_code":"03",
    "gn:admin2_code":"321.0",
    "gn:admin3_code":"32114.0",
    "gn:asciiname":"Oberstockstall",
    "gn:country_code":"AT",
    "gn:dem":247,
    "gn:feature_class":"P",
    "gn:feature_code":"PPL",
    "gn:name":"Oberstockstall",
    "gn:population":212,
    "gn:timezone":"Europe/Vienna",
    "iso:country":"AT",
    "wof:name":"Oberstockstall",
    "wof:placetype":"locality",
    "wof:population":212
},
  "geometry": {"coordinates":[15.91667,48.45],"type":"Point"}
}