{
  "type": "Feature",
  "properties": {
    "gn:admin1_code":"4.0",
    "gn:admin2_code":"413",
    "gn:admin3_code":"41344.0",
    "gn:asciiname":"Autengrub",
    "gn:country_code":"AT",
    "gn:dem":639,
    "gn:feature_class":"P",
    "gn:feature_code":"PPL",
    "gn:name":"Autengrub",
    "gn:population":13,
    "gn:timezone":"Europe/Vienna",
    "iso:country":"AT",
    "wof:name":"Autengrub",
    "wof:placetype":"locality",
    "wof:population":13
},
  "geometry": {"coordinates":[13.97873,48.5469],"type":"Point"}
}