{
  "type": "Feature",
  "properties": {
    "gn:admin1_code":"07",
    "gn:admin2_code":"703.0",
    "gn:admin3_code":"70333.0",
    "gn:asciiname":"Tienzens",
    "gn:country_code":"AT",
    "gn:dem":1107,
    "gn:feature_class":"P",
    "gn:feature_code":"PPL",
    "gn:name":"Tienzens",
    "gn:population":0,
    "gn:timezone":"Europe/Vienna",
    "iso:country":"AT",
    "wof:name":"Tienzens",
    "wof:placetype":"locality"
},
  "geometry": {"coordinates":[11.46667,47.11667],"type":"Point"}
}