{
  "type": "Feature",
  "properties": {
    "gn:admin1_code":"6.0",
    "gn:admin2_code":"620",
    "gn:admin3_code":"62043.0",
    "gn:asciiname":"Goetzendorf",
    "gn:country_code":"AT",
    "gn:dem":829,
    "gn:feature_class":"P",
    "gn:feature_code":"PPL",
    "gn:name":"G\u00f6tzendorf",
    "gn:population":96,
    "gn:timezone":"Europe/Vienna",
    "iso:country":"AT",
    "wof:name":"Goetzendorf",
    "wof:placetype":"locality",
    "wof:population":96
},
  "geometry": {"coordinates":[14.55,47.23333],"type":"Point"}
}