{
  "type": "Feature",
  "properties": {
    "gn:admin1_code":"4.0",
    "gn:admin2_code":"407",
    "gn:admin3_code":"40713.0",
    "gn:asciiname":"Hafendorf",
    "gn:country_code":"AT",
    "gn:dem":481,
    "gn:feature_class":"P",
    "gn:feature_code":"PPL",
    "gn:name":"Hafendorf",
    "gn:population":43,
    "gn:timezone":"Europe/Vienna",
    "iso:country":"AT",
    "wof:name":"Hafendorf",
    "wof:placetype":"locality",
    "wof:population":43
},
  "geometry": {"coordinates":[13.76381,47.96458],"type":"Point"}
}