{
  "type": "Feature",
  "properties": {
    "gn:admin1_code":"07",
    "gn:admin2_code":"706.0",
    "gn:admin3_code":"70620.0",
    "gn:asciiname":"Sankt Christina",
    "gn:country_code":"AT",
    "gn:dem":1034,
    "gn:feature_class":"P",
    "gn:feature_code":"PPL",
    "gn:name":"Sankt Christina",
    "gn:population":0,
    "gn:timezone":"Europe/Vienna",
    "iso:country":"AT",
    "wof:name":"Sankt Christina",
    "wof:placetype":"locality"
},
  "geometry": {"coordinates":[10.63333,47.03333],"type":"Point"}
}