{
  "type": "Feature",
  "properties": {
    "gn:admin1_code":"4.0",
    "gn:admin2_code":"406",
    "gn:admin3_code":"40611.0",
    "gn:asciiname":"Eibenberg",
    "gn:country_code":"AT",
    "gn:dem":971,
    "gn:feature_class":"P",
    "gn:feature_code":"PPL",
    "gn:name":"Eibenberg",
    "gn:population":45,
    "gn:timezone":"Europe/Vienna",
    "iso:country":"AT",
    "wof:name":"Eibenberg",
    "wof:placetype":"locality",
    "wof:population":45
},
  "geometry": {"coordinates":[14.75593,48.51376],"type":"Point"}
}