{
  "type": "Feature",
  "properties": {
    "gn:admin1_code":"04",
    "gn:admin2_code":"416.0",
    "gn:admin3_code":"41613.0",
    "gn:asciiname":"Rohrach",
    "gn:country_code":"AT",
    "gn:dem":809,
    "gn:feature_class":"P",
    "gn:feature_code":"PPL",
    "gn:name":"Rohrach",
    "gn:population":87,
    "gn:timezone":"Europe/Vienna",
    "iso:country":"AT",
    "name:ceb_x_preferred":[
        "Rohrach"
    ],
    "name:deu_x_preferred":[
        "Rohrach"
    ],
    "name:rus_x_preferred":[
        "\u0420\u043e\u0440\u0430\u0445"
    ],
    "name:swe_x_preferred":[
        "Rohrach"
    ],
    "wof:name":"Rohrach",
    "wof:placetype":"locality",
    "wof:population":87
},
  "geometry": {"coordinates":[14.26858,48.40556],"type":"Point"}
}