{
  "type": "Feature",
  "properties": {
    "gn:admin1_code":"08",
    "gn:admin2_code":"801.0",
    "gn:admin3_code":"80128.0",
    "gn:asciiname":"Rodund",
    "gn:country_code":"AT",
    "gn:dem":752,
    "gn:feature_class":"P",
    "gn:feature_code":"PPL",
    "gn:name":"Rodund",
    "gn:population":0,
    "gn:timezone":"Europe/Vienna",
    "iso:country":"AT",
    "wof:name":"Rodund",
    "wof:placetype":"locality"
},
  "geometry": {"coordinates":[9.88333,47.08333],"type":"Point"}
}