{
  "type": "Feature",
  "properties": {
    "gn:admin1_code":"7.0",
    "gn:admin2_code":"703",
    "gn:admin3_code":"70314.0",
    "gn:asciiname":"Juifenau",
    "gn:country_code":"AT",
    "gn:dem":1353,
    "gn:elevation":"1381.0",
    "gn:feature_class":"P",
    "gn:feature_code":"PPL",
    "gn:name":"Juifenau",
    "gn:population":0,
    "gn:timezone":"Europe/Vienna",
    "iso:country":"AT",
    "wof:name":"Juifenau",
    "wof:placetype":"locality"
},
  "geometry": {"coordinates":[11.14795,47.17857],"type":"Point"}
}