{
  "type": "Feature",
  "properties": {
    "gn:admin1_code":"06",
    "gn:admin2_code":"610.0",
    "gn:admin3_code":"61058.0",
    "gn:asciiname":"Strass in Steiermark",
    "gn:cc2":"AT",
    "gn:country_code":"AT",
    "gn:dem":255,
    "gn:feature_class":"P",
    "gn:feature_code":"PPLA3",
    "gn:name":"Stra\u00df in Steiermark",
    "gn:population":1552,
    "gn:timezone":"Europe/Vienna",
    "iso:country":"AT",
    "name:ceb_x_preferred":[
        "Stra\u00df in Steiermark"
    ],
    "name:deu_x_preferred":[
        "Stra\u00df in Steiermark"
    ],
    "name:epo_x_preferred":[
        "Stra\u00df"
    ],
    "name:fas_x_preferred":[
        "\u0627\u0634\u062a\u0631\u0627\u0633 \u0627\u06cc\u0646 \u0627\u0634\u062a\u0627\u06cc\u0631\u0645\u0627\u0631\u06a9"
    ],
    "name:fra_x_preferred":[
        "Stra\u00df in Steiermark"
    ],
    "name:hun_x_preferred":[
        "Stra\u00df in Steiermark"
    ],
    "name:ita_x_preferred":[
        "Stra\u00df in Steiermark"
    ],
    "name:kaz_x_preferred":[
        "\u0428\u0442\u0440\u0430\u0441"
    ],
    "name:nld_x_preferred":[
        "Stra\u00df in Steiermark"
    ],
    "name:pol_x_preferred":[
        "Stra\u00df in Steiermark"
    ],
    "name:rus_x_preferred":[
        "\u0428\u0442\u0440\u0430\u0441-\u0438\u043d-\u0428\u0442\u0430\u0439\u0435\u0440\u043c\u0430\u0440\u043a"
    ],
    "name:slk_x_preferred":[
        "Stra\u00df in Steiermark"
    ],
    "name:spa_x_preferred":[
        "Stra\u00df in Steiermark"
    ],
    "name:swe_x_preferred":[
        "Stra\u00df in Steiermark"
    ],
    "name:und_x_variant":[
        "Strass",
        "Stra\u00df in Steiermark"
    ],
    "name:uzb_x_preferred":[
        "Stra\u00df in Steiermark"
    ],
    "name:vie_x_preferred":[
        "Stra\u00df in Steiermark"
    ],
    "name:vol_x_preferred":[
        "Stra\u00df in Steiermark"
    ],
    "name:war_x_preferred":[
        "Stra\u00df in Steiermark"
    ],
    "name:zho_x_preferred":[
        "\u65bd\u6cf0\u5c14\u9a6c\u514b\u5730\u533a\u65bd\u7279\u62c9\u65af"
    ],
    "wof:name":"Strass in Steiermark",
    "wof:placetype":"locality",
    "wof:population":1552
},
  "geometry": {"coordinates":[15.62444,46.72722],"type":"Point"}
}