{
  "type": "Feature",
  "properties": {
    "gn:admin1_code":"4.0",
    "gn:admin2_code":"405",
    "gn:admin3_code":"40509.0",
    "gn:asciiname":"Auhof",
    "gn:country_code":"AT",
    "gn:dem":263,
    "gn:feature_class":"P",
    "gn:feature_code":"PPL",
    "gn:name":"Auhof",
    "gn:population":17,
    "gn:timezone":"Europe/Vienna",
    "iso:country":"AT",
    "wof:name":"Auhof",
    "wof:placetype":"locality",
    "wof:population":17
},
  "geometry": {"coordinates":[14.03872,48.31916],"type":"Point"}
}