{
  "type": "Feature",
  "properties": {
    "gn:admin1_code":"04",
    "gn:admin2_code":"417.0",
    "gn:admin3_code":"41747.0",
    "gn:asciiname":"Zeiling",
    "gn:country_code":"AT",
    "gn:dem":466,
    "gn:feature_class":"P",
    "gn:feature_code":"PPL",
    "gn:name":"Zeiling",
    "gn:population":0,
    "gn:timezone":"Europe/Vienna",
    "iso:country":"AT",
    "wof:name":"Zeiling",
    "wof:placetype":"locality"
},
  "geometry": {"coordinates":[13.52666,48.01795],"type":"Point"}
}