{
  "type": "Feature",
  "properties": {
    "gn:admin1_code":"03",
    "gn:admin2_code":"306.0",
    "gn:admin3_code":"30602.0",
    "gn:asciiname":"Sankt Corona am Schoepfl",
    "gn:cc2":"AT",
    "gn:country_code":"AT",
    "gn:dem":542,
    "gn:elevation":"580.0",
    "gn:feature_class":"P",
    "gn:feature_code":"PPL",
    "gn:name":"Sankt Corona am Sch\u00f6pfl",
    "gn:population":332,
    "gn:timezone":"Europe/Vienna",
    "iso:country":"AT",
    "name:und_x_variant":[
        "Sankt Corona"
    ],
    "wof:name":"Sankt Corona am Schoepfl",
    "wof:placetype":"locality",
    "wof:population":332
},
  "geometry": {"coordinates":[15.92726,48.06248],"type":"Point"}
}