{
  "type": "Feature",
  "properties": {
    "iso:country":"AT",
    "name:chi_x_preferred":[
        "Donnersbachwald"
    ],
    "name:dut_x_preferred":[
        "Donnersbachwald"
    ],
    "name:eng_x_preferred":[
        "Donnersbachwald"
    ],
    "name:fre_x_preferred":[
        "Donnersbachwald"
    ],
    "name:ger_x_preferred":[
        "Donnersbachwald"
    ],
    "name:hun_x_preferred":[
        "Donnersbachwald"
    ],
    "name:ita_x_preferred":[
        "Donnersbachwald"
    ],
    "name:kaz_x_preferred":[
        "\u0414\u043e\u043d\u043d\u0435\u0440\u0441\u0431\u0430\u0445\u0432\u0430\u043b\u044c\u0434"
    ],
    "name:rus_x_preferred":[
        "\u0414\u043e\u043d\u043d\u0435\u0440\u0441\u0431\u0430\u0445\u0432\u0430\u043b\u044c\u0434"
    ],
    "name:slo_x_preferred":[
        "Donnersbachwald"
    ],
    "name:swe_x_preferred":[
        "Donnersbachwald"
    ],
    "name:uzb_x_preferred":[
        "Donnersbachwald"
    ],
    "name:vie_x_preferred":[
        "Donnersbachwald"
    ],
    "name:vol_x_preferred":[
        "Donnersbachwald"
    ],
    "name:war_x_preferred":[
        "Donnersbachwald"
    ],
    "qs_pg:aaroncc":"AT",
    "qs_pg:name":"Donnersbachwald",
    "qs_pg:name_adm0":"\u00d6sterreich",
    "qs_pg:name_adm1":"Steiermark",
    "qs_pg:photos":91,
    "qs_pg:photos_1k":18,
    "qs_pg:photos_9k":1,
    "qs_pg:photos_9r":3,
    "qs_pg:photos_all":91,
    "qs_pg:photos_sr":3,
    "qs_pg:pop_sr":0,
    "qs_pg:qs_pg_placetype":"locality",
    "qs_pg:qs_pg_placetype_gp":"Town",
    "qs_pg:woe_adm0":23424750,
    "woe:adm0_id":23424750,
    "woe:name_adm0":"\u00d6sterreich",
    "woe:name_adm1":"Steiermark",
    "woe:placetype":"Town",
    "wof:name":"Donnersbachwald",
    "wof:placetype":"locality"
},
  "geometry": {"coordinates":[14.105758,47.373825],"type":"Point"}
}