{
  "type": "Feature",
  "properties": {
    "gn:admin1_code":"4.0",
    "gn:admin2_code":"415",
    "gn:admin3_code":"41508.0",
    "gn:asciiname":"Plattenberg",
    "gn:country_code":"AT",
    "gn:dem":676,
    "gn:feature_class":"P",
    "gn:feature_code":"PPL",
    "gn:name":"Plattenberg",
    "gn:population":0,
    "gn:timezone":"Europe/Vienna",
    "iso:country":"AT",
    "name:ceb_x_preferred":[
        "Plattenberg"
    ],
    "name:ita_x_preferred":[
        "Plattenberg"
    ],
    "name:nno_x_preferred":[
        "Plattenberg"
    ],
    "name:pol_x_preferred":[
        "Plattenberg"
    ],
    "wof:name":"Plattenberg",
    "wof:placetype":"locality"
},
  "geometry": {"coordinates":[14.4841,47.94797],"type":"Point"}
}