{
  "type": "Feature",
  "properties": {
    "gn:admin1_code":"5.0",
    "gn:admin2_code":"503",
    "gn:admin3_code":"50329.0",
    "gn:asciiname":"Irlach",
    "gn:country_code":"AT",
    "gn:dem":395,
    "gn:feature_class":"P",
    "gn:feature_code":"PPL",
    "gn:name":"Irlach",
    "gn:population":239,
    "gn:timezone":"Europe/Vienna",
    "iso:country":"AT",
    "wof:name":"Irlach",
    "wof:placetype":"locality",
    "wof:population":239
},
  "geometry": {"coordinates":[12.88167,47.98889000000001],"type":"Point"}
}