{
  "type": "Feature",
  "properties": {
    "gn:admin1_code":"7.0",
    "gn:admin2_code":"705",
    "gn:admin3_code":"70530.0",
    "gn:asciiname":"Esbaum",
    "gn:country_code":"AT",
    "gn:dem":873,
    "gn:feature_class":"P",
    "gn:feature_code":"PPL",
    "gn:name":"Esbaum",
    "gn:population":0,
    "gn:timezone":"Europe/Vienna",
    "iso:country":"AT",
    "wof:name":"Esbaum",
    "wof:placetype":"locality"
},
  "geometry": {"coordinates":[12.05,47.46667],"type":"Point"}
}