{
  "type": "Feature",
  "properties": {
    "gn:admin1_code":"4.0",
    "gn:admin2_code":"416",
    "gn:admin3_code":"41613.0",
    "gn:asciiname":"Riedl",
    "gn:country_code":"AT",
    "gn:dem":627,
    "gn:feature_class":"P",
    "gn:feature_code":"PPL",
    "gn:name":"Riedl",
    "gn:population":242,
    "gn:timezone":"Europe/Vienna",
    "iso:country":"AT",
    "wof:name":"Riedl",
    "wof:placetype":"locality",
    "wof:population":242
},
  "geometry": {"coordinates":[14.28778,48.39333],"type":"Point"}
}