{
  "type": "Feature",
  "properties": {
    "gn:admin1_code":"3.0",
    "gn:admin2_code":"321",
    "gn:admin3_code":"32131.0",
    "gn:asciiname":"Kreuth",
    "gn:country_code":"AT",
    "gn:dem":247,
    "gn:feature_class":"P",
    "gn:feature_code":"PPL",
    "gn:name":"Kreuth",
    "gn:population":167,
    "gn:timezone":"Europe/Vienna",
    "iso:country":"AT",
    "wof:name":"Kreuth",
    "wof:placetype":"locality",
    "wof:population":167
},
  "geometry": {"coordinates":[16.00674,48.22822],"type":"Point"}
}