{
  "type": "Feature",
  "properties": {
    "gn:admin1_code":"4.0",
    "gn:admin2_code":"408",
    "gn:admin3_code":"40824.0",
    "gn:asciiname":"Miniberg",
    "gn:country_code":"AT",
    "gn:dem":522,
    "gn:feature_class":"P",
    "gn:feature_code":"PPL",
    "gn:name":"Miniberg",
    "gn:population":7,
    "gn:timezone":"Europe/Vienna",
    "iso:country":"AT",
    "wof:name":"Miniberg",
    "wof:placetype":"locality",
    "wof:population":7
},
  "geometry": {"coordinates":[13.83822,48.38786],"type":"Point"}
}