{
  "type": "Feature",
  "properties": {
    "gn:admin1_code":"4.0",
    "gn:admin2_code":"406",
    "gn:admin3_code":"40608.0",
    "gn:asciiname":"Ebrixedt",
    "gn:country_code":"AT",
    "gn:dem":698,
    "gn:feature_class":"P",
    "gn:feature_code":"PPL",
    "gn:name":"Ebrixedt",
    "gn:population":85,
    "gn:timezone":"Europe/Vienna",
    "iso:country":"AT",
    "wof:name":"Ebrixedt",
    "wof:placetype":"locality",
    "wof:population":85
},
  "geometry": {"coordinates":[14.85673,48.39311],"type":"Point"}
}