{
  "type": "Feature",
  "properties": {
    "gn:admin1_code":"04",
    "gn:admin2_code":"407.0",
    "gn:admin3_code":"40702.0",
    "gn:asciiname":"Riedln",
    "gn:country_code":"AT",
    "gn:dem":647,
    "gn:feature_class":"P",
    "gn:feature_code":"PPL",
    "gn:name":"Riedln",
    "gn:population":56,
    "gn:timezone":"Europe/Vienna",
    "iso:country":"AT",
    "wof:name":"Riedln",
    "wof:placetype":"locality",
    "wof:population":56
},
  "geometry": {"coordinates":[13.63935,47.6411],"type":"Point"}
}