{
  "type": "Feature",
  "properties": {
    "gn:admin1_code":"06",
    "gn:admin2_code":"617.0",
    "gn:admin3_code":"61763.0",
    "gn:asciiname":"Untersattl",
    "gn:country_code":"AT",
    "gn:dem":705,
    "gn:feature_class":"P",
    "gn:feature_code":"PPL",
    "gn:name":"Untersattl",
    "gn:population":0,
    "gn:timezone":"Europe/Vienna",
    "iso:country":"AT",
    "wof:name":"Untersattl",
    "wof:placetype":"locality"
},
  "geometry": {"coordinates":[15.53333,47.26667],"type":"Point"}
}