{
  "type": "Feature",
  "properties": {
    "gn:admin1_code":"04",
    "gn:admin2_code":"417.0",
    "gn:admin3_code":"41748.0",
    "gn:asciiname":"Weissenkirchen im Attergau",
    "gn:cc2":"AT",
    "gn:country_code":"AT",
    "gn:dem":735,
    "gn:feature_class":"P",
    "gn:feature_code":"PPL",
    "gn:name":"Weissenkirchen im Attergau",
    "gn:population":0,
    "gn:timezone":"Europe/Vienna",
    "iso:country":"AT",
    "name:bar_x_preferred":[
        "Wei\u00dfkira im Attagau"
    ],
    "name:ceb_x_preferred":[
        "Wei\u00dfenkirchen im Attergau"
    ],
    "name:ces_x_preferred":[
        "Wei\u00dfenkirchen im Attergau"
    ],
    "name:deu_x_preferred":[
        "Wei\u00dfenkirchen im Attergau"
    ],
    "name:fas_x_preferred":[
        "\u0648\u0627\u06cc\u0633\u0646\u06a9\u06cc\u0631\u0634\u0646 \u0627\u06cc\u0645 \u0622\u062a\u0631\u06af\u0648"
    ],
    "name:fra_x_preferred":[
        "Wei\u00dfenkirchen im Attergau"
    ],
    "name:hun_x_preferred":[
        "Wei\u00dfenkirchen im Attergau"
    ],
    "name:ita_x_preferred":[
        "Wei\u00dfenkirchen im Attergau"
    ],
    "name:kaz_x_preferred":[
        "\u0412\u0430\u0439\u0441\u0435\u043d\u043a\u0438\u0440\u0445\u0435\u043d"
    ],
    "name:nld_x_preferred":[
        "Wei\u00dfenkirchen im Attergau"
    ],
    "name:pol_x_preferred":[
        "Wei\u00dfenkirchen im Attergau"
    ],
    "name:por_x_preferred":[
        "Wei\u00dfenkirchen im Attergau"
    ],
    "name:rus_x_preferred":[
        "\u0412\u0430\u0439\u0441\u0435\u043d\u043a\u0438\u0440\u0445\u0435\u043d-\u0438\u043c-\u0410\u0442\u0442\u0435\u0440\u0433\u0430\u0443"
    ],
    "name:slk_x_preferred":[
        "Wei\u00dfenkirchen im Attergau"
    ],
    "name:spa_x_preferred":[
        "Wei\u00dfenkirchen im Attergau"
    ],
    "name:swe_x_preferred":[
        "Wei\u00dfenkirchen im Attergau"
    ],
    "name:und_x_variant":[
        "Weissenkirchen",
        "Weissenkirchen im Attergau"
    ],
    "name:uzb_x_preferred":[
        "Wei\u00dfenkirchen im Attergau"
    ],
    "name:vie_x_preferred":[
        "Wei\u00dfenkirchen im Attergau"
    ],
    "name:vol_x_preferred":[
        "Wei\u00dfenkirchen im Attergau"
    ],
    "name:war_x_preferred":[
        "Wei\u00dfenkirchen im Attergau"
    ],
    "name:zho_x_preferred":[
        "\u963f\u7279\u9ad8\u5730\u533a\u9b4f\u68ee\u57fa\u5174"
    ],
    "wof:name":"Weissenkirchen im Attergau",
    "wof:placetype":"locality"
},
  "geometry": {"coordinates":[13.38333,47.93333],"type":"Point"}
}