{
  "type": "Feature",
  "properties": {
    "gn:admin1_code":"04",
    "gn:admin2_code":"417.0",
    "gn:admin3_code":"41748.0",
    "gn:asciiname":"Weissenkirchen im Attergau",
    "gn:cc2":"AT",
    "gn:country_code":"AT",
    "gn:dem":735,
    "gn:feature_class":"P",
    "gn:feature_code":"PPL",
    "gn:name":"Weissenkirchen im Attergau",
    "gn:population":0,
    "gn:timezone":"Europe/Vienna",
    "iso:country":"AT",
    "name:und_x_variant":[
        "Weissenkirchen",
        "Weissenkirchen im Attergau"
    ],
    "wof:name":"Weissenkirchen im Attergau",
    "wof:placetype":"locality"
},
  "geometry": {"coordinates":[13.38333,47.93333],"type":"Point"}
}