{
  "type": "Feature",
  "properties": {
    "gn:admin1_code":"7.0",
    "gn:admin2_code":"707",
    "gn:admin3_code":"70705.0",
    "gn:asciiname":"Oberthal",
    "gn:country_code":"AT",
    "gn:dem":982,
    "gn:feature_class":"P",
    "gn:feature_code":"PPL",
    "gn:name":"Oberthal",
    "gn:population":91,
    "gn:timezone":"Europe/Vienna",
    "iso:country":"AT",
    "name:als_x_preferred":[
        "Oberthal"
    ],
    "name:cat_x_preferred":[
        "Oberthal"
    ],
    "name:ceb_x_preferred":[
        "Oberthal"
    ],
    "name:deu_x_preferred":[
        "Oberthal"
    ],
    "name:epo_x_preferred":[
        "Oberthal"
    ],
    "name:eus_x_preferred":[
        "Oberthal"
    ],
    "name:fra_x_preferred":[
        "Oberthal"
    ],
    "name:ita_x_preferred":[
        "Oberthal"
    ],
    "name:nld_x_preferred":[
        "Oberthal"
    ],
    "name:pol_x_preferred":[
        "Oberthal"
    ],
    "name:rus_x_preferred":[
        "\u041e\u0431\u0435\u0440\u0442\u0430\u043b\u044c"
    ],
    "name:swe_x_preferred":[
        "Oberthal"
    ],
    "name:vol_x_preferred":[
        "Oberthal"
    ],
    "wof:name":"Oberthal",
    "wof:placetype":"locality",
    "wof:population":91
},
  "geometry": {"coordinates":[12.64814,46.78989],"type":"Point"}
}