{
  "type": "Feature",
  "properties": {
    "gn:admin1_code":"06",
    "gn:admin2_code":"623.0",
    "gn:admin3_code":"62377.0",
    "gn:asciiname":"Murkreis",
    "gn:country_code":"AT",
    "gn:dem":235,
    "gn:feature_class":"P",
    "gn:feature_code":"PPL",
    "gn:name":"Murkreis",
    "gn:population":0,
    "gn:timezone":"Europe/Vienna",
    "iso:country":"AT",
    "wof:name":"Murkreis",
    "wof:placetype":"locality"
},
  "geometry": {"coordinates":[15.88333,46.75],"type":"Point"}
}