{
  "type": "Feature",
  "properties": {
    "gn:admin1_code":"7.0",
    "gn:admin2_code":"702",
    "gn:admin3_code":"70223.0",
    "gn:asciiname":"Niederthei",
    "gn:country_code":"AT",
    "gn:dem":1649,
    "gn:feature_class":"P",
    "gn:feature_code":"PPL",
    "gn:name":"Niederthei",
    "gn:population":0,
    "gn:timezone":"Europe/Vienna",
    "iso:country":"AT",
    "wof:name":"Niederthei",
    "wof:placetype":"locality"
},
  "geometry": {"coordinates":[10.95,47.13333],"type":"Point"}
}