{
  "type": "Feature",
  "properties": {
    "gn:admin1_code":"8.0",
    "gn:admin2_code":"802",
    "gn:admin3_code":"80227.0",
    "gn:asciiname":"Hauser",
    "gn:country_code":"AT",
    "gn:dem":1252,
    "gn:elevation":"1252.0",
    "gn:feature_class":"P",
    "gn:feature_code":"PPLF",
    "gn:name":"Hauser",
    "gn:population":0,
    "gn:timezone":"Europe/Vienna",
    "iso:country":"AT",
    "name:pol_x_preferred":[
        "Hauser"
    ],
    "name:und_x_variant":[
        "Huser"
    ],
    "wof:name":"Hauser",
    "wof:placetype":"locality"
},
  "geometry": {"coordinates":[9.82498,47.31341],"type":"Point"}
}