{
  "type": "Feature",
  "properties": {
    "gn:admin1_code":"4.0",
    "gn:admin2_code":"412",
    "gn:admin3_code":"41233.0",
    "gn:asciiname":"Strass",
    "gn:country_code":"AT",
    "gn:dem":444,
    "gn:feature_class":"P",
    "gn:feature_code":"PPLL",
    "gn:name":"Stra\u00df",
    "gn:population":21,
    "gn:timezone":"Europe/Vienna",
    "iso:country":"AT",
    "wof:name":"Strass",
    "wof:placetype":"locality",
    "wof:population":21
},
  "geometry": {"coordinates":[13.5022,48.25977],"type":"Point"}
}