{
  "type": "Feature",
  "properties": {
    "gn:admin1_code":"4.0",
    "gn:admin2_code":"404",
    "gn:admin3_code":"40409.0",
    "gn:asciiname":"Brunn",
    "gn:country_code":"AT",
    "gn:dem":463,
    "gn:feature_class":"P",
    "gn:feature_code":"PPL",
    "gn:name":"Brunn",
    "gn:population":34,
    "gn:timezone":"Europe/Vienna",
    "iso:country":"AT",
    "wof:name":"Brunn",
    "wof:placetype":"locality",
    "wof:population":34
},
  "geometry": {"coordinates":[12.91966,48.06707],"type":"Point"}
}