{
  "type": "Feature",
  "properties": {
    "gn:admin1_code":"6.0",
    "gn:admin2_code":"610",
    "gn:admin3_code":"61052.0",
    "gn:asciiname":"Kleinfelgitsch",
    "gn:country_code":"AT",
    "gn:dem":358,
    "gn:feature_class":"P",
    "gn:feature_code":"PPL",
    "gn:name":"Kleinfelgitsch",
    "gn:population":0,
    "gn:timezone":"Europe/Vienna",
    "iso:country":"AT",
    "wof:name":"Kleinfelgitsch",
    "wof:placetype":"locality"
},
  "geometry": {"coordinates":[15.58333,46.95],"type":"Point"}
}