{
  "type": "Feature",
  "properties": {
    "gn:admin1_code":"02",
    "gn:admin2_code":"206.0",
    "gn:admin3_code":"20644.0",
    "gn:asciiname":"Penk",
    "gn:country_code":"AT",
    "gn:dem":944,
    "gn:feature_class":"P",
    "gn:feature_code":"PPL",
    "gn:name":"Penk",
    "gn:population":277,
    "gn:timezone":"Europe/Vienna",
    "iso:country":"AT",
    "name:deu_x_preferred":[
        "Penk"
    ],
    "name:fra_x_preferred":[
        "Penk"
    ],
    "name:nds_x_preferred":[
        "Penk"
    ],
    "wof:name":"Penk",
    "wof:placetype":"locality",
    "wof:population":277
},
  "geometry": {"coordinates":[13.27083,46.90333],"type":"Point"}
}