{
  "type": "Feature",
  "properties": {
    "gn:admin1_code":"4.0",
    "gn:admin2_code":"404",
    "gn:admin3_code":"40406.0",
    "gn:asciiname":"Hoetzenau",
    "gn:country_code":"AT",
    "gn:dem":524,
    "gn:feature_class":"P",
    "gn:feature_code":"PPL",
    "gn:name":"H\u00f6tzenau",
    "gn:population":3,
    "gn:timezone":"Europe/Vienna",
    "iso:country":"AT",
    "wof:name":"Hoetzenau",
    "wof:placetype":"locality",
    "wof:population":3
},
  "geometry": {"coordinates":[12.98524,48.08224000000001],"type":"Point"}
}