{
  "type": "Feature",
  "properties": {
    "gn:gn_country":"AT",
    "gn:gn_fcode":"PPL",
    "gn:gn_pop":0,
    "iso:country":"AT",
    "name:ceb_x_preferred":[
        "Preding"
    ],
    "name:deu_x_preferred":[
        "Preding"
    ],
    "name:epo_x_preferred":[
        "Preding"
    ],
    "name:fas_x_preferred":[
        "\u067e\u0631\u06cc\u062f\u06cc\u0646\u06af"
    ],
    "name:fra_x_preferred":[
        "Preding"
    ],
    "name:hun_x_preferred":[
        "Preding"
    ],
    "name:ita_x_preferred":[
        "Preding"
    ],
    "name:kaz_x_preferred":[
        "\u041f\u0440\u0435\u0434\u0438\u043d\u0433"
    ],
    "name:nld_x_preferred":[
        "Preding"
    ],
    "name:pol_x_preferred":[
        "Preding"
    ],
    "name:rus_x_preferred":[
        "\u041f\u0440\u0435\u0434\u0438\u043d\u0433"
    ],
    "name:slk_x_preferred":[
        "Preding"
    ],
    "name:spa_x_preferred":[
        "Preding"
    ],
    "name:swe_x_preferred":[
        "Preding"
    ],
    "name:uzb_x_preferred":[
        "Preding"
    ],
    "name:vie_x_preferred":[
        "Preding"
    ],
    "name:vol_x_preferred":[
        "Preding"
    ],
    "name:war_x_preferred":[
        "Preding"
    ],
    "name:zho_x_preferred":[
        "\u666e\u96f7\u4e01"
    ],
    "qs_pg:aaroncc":"AT",
    "qs_pg:gn_country":"AT",
    "qs_pg:gn_fcode":"PPL",
    "qs_pg:gn_pop":0,
    "qs_pg:name":"Preding",
    "qs_pg:name_adm0":"\u00d6sterreich",
    "qs_pg:name_adm1":"Steiermark",
    "qs_pg:photos":4,
    "qs_pg:photos_1k":1,
    "qs_pg:photos_9k":1,
    "qs_pg:photos_9r":1,
    "qs_pg:photos_all":4,
    "qs_pg:photos_sr":1,
    "qs_pg:pop_sr":0,
    "qs_pg:qs_pg_placetype":"locality",
    "qs_pg:qs_pg_placetype_gp":"Town",
    "qs_pg:woe_adm0":23424750,
    "woe:adm0_id":23424750,
    "woe:name_adm0":"\u00d6sterreich",
    "woe:name_adm1":"Steiermark",
    "woe:placetype":"Town",
    "wof:name":"Preding",
    "wof:placetype":"locality"
},
  "geometry": {"coordinates":[15.65,47.18333],"type":"Point"}
}