{
  "type": "Feature",
  "properties": {
    "gn:admin1_code":"6.0",
    "gn:admin2_code":"606",
    "gn:admin3_code":"60645.0",
    "gn:asciiname":"Mitterdorf am Trotsch",
    "gn:country_code":"AT",
    "gn:dem":856,
    "gn:feature_class":"P",
    "gn:feature_code":"PPL",
    "gn:name":"Mitterdorf am Tr\u00f6tsch",
    "gn:population":0,
    "gn:timezone":"Europe/Vienna",
    "iso:country":"AT",
    "wof:name":"Mitterdorf am Trotsch",
    "wof:placetype":"locality"
},
  "geometry": {"coordinates":[15.36667,47.25],"type":"Point"}
}