{
  "type": "Feature",
  "properties": {
    "gn:admin1_code":"06",
    "gn:admin2_code":"612.0",
    "gn:admin3_code":"61215.0",
    "gn:asciiname":"Rosslern",
    "gn:country_code":"AT",
    "gn:dem":732,
    "gn:feature_class":"P",
    "gn:feature_code":"PPL",
    "gn:name":"R\u00f6sslern",
    "gn:population":0,
    "gn:timezone":"Europe/Vienna",
    "iso:country":"AT",
    "wof:name":"Rosslern",
    "wof:placetype":"locality"
},
  "geometry": {"coordinates":[13.85,47.63333],"type":"Point"}
}