{
  "type": "Feature",
  "properties": {
    "gn:admin1_code":"06",
    "gn:admin2_code":"623.0",
    "gn:admin3_code":"62375.0",
    "gn:asciiname":"Sulz",
    "gn:country_code":"AT",
    "gn:dem":309,
    "gn:feature_class":"P",
    "gn:feature_code":"PPL",
    "gn:name":"Sulz",
    "gn:population":0,
    "gn:timezone":"Europe/Vienna",
    "iso:country":"AT",
    "wof:name":"Sulz",
    "wof:placetype":"locality"
},
  "geometry": {"coordinates":[15.89861,46.86944],"type":"Point"}
}