{
  "type": "Feature",
  "properties": {
    "gn:admin1_code":"06",
    "gn:admin2_code":"623.0",
    "gn:admin3_code":"62388.0",
    "gn:asciiname":"Wiersdorf",
    "gn:country_code":"AT",
    "gn:dem":283,
    "gn:feature_class":"P",
    "gn:feature_code":"PPL",
    "gn:name":"Wiersdorf",
    "gn:population":158,
    "gn:timezone":"Europe/Vienna",
    "iso:country":"AT",
    "name:ceb_x_preferred":[
        "Wiersdorf"
    ],
    "name:deu_x_preferred":[
        "Wiersdorf"
    ],
    "name:epo_x_preferred":[
        "Wiersdorf"
    ],
    "name:eus_x_preferred":[
        "Wiersdorf"
    ],
    "name:fas_x_preferred":[
        "\u0648\u06cc\u0631\u0633\u062f\u0648\u0631\u0641"
    ],
    "name:fra_x_preferred":[
        "Wiersdorf"
    ],
    "name:hun_x_preferred":[
        "Wiersdorf"
    ],
    "name:ita_x_preferred":[
        "Wiersdorf"
    ],
    "name:kaz_x_preferred":[
        "\u0412\u0438\u0440\u0441\u0434\u043e\u0440\u0444"
    ],
    "name:kir_x_preferred":[
        "\u0412\u0438\u0440\u0441\u0434\u043e\u0440\u0444"
    ],
    "name:msa_x_preferred":[
        "Wiersdorf"
    ],
    "name:nld_x_preferred":[
        "Wiersdorf"
    ],
    "name:pol_x_preferred":[
        "Wiersdorf"
    ],
    "name:por_x_preferred":[
        "Wiersdorf"
    ],
    "name:ron_x_preferred":[
        "Wiersdorf"
    ],
    "name:rus_x_preferred":[
        "\u0412\u0438\u0440\u0441\u0434\u043e\u0440\u0444"
    ],
    "name:spa_x_preferred":[
        "Wiersdorf"
    ],
    "name:srp_x_preferred":[
        "\u0412\u0438\u0440\u0441\u0434\u043e\u0440\u0444"
    ],
    "name:ukr_x_preferred":[
        "\u0412\u0456\u0440\u0441\u0434\u043e\u0440\u0444"
    ],
    "name:uzb_x_preferred":[
        "Wiersdorf"
    ],
    "name:vie_x_preferred":[
        "Wiersdorf"
    ],
    "name:vol_x_preferred":[
        "Wiersdorf"
    ],
    "name:war_x_preferred":[
        "Wiersdorf"
    ],
    "name:zho_x_preferred":[
        "\u7ef4\u5c14\u65af\u591a\u592b"
    ],
    "wof:name":"Wiersdorf",
    "wof:placetype":"locality",
    "wof:population":158
},
  "geometry": {"coordinates":[15.75583,46.825],"type":"Point"}
}