{
  "type": "Feature",
  "properties": {
    "gn:admin1_code":"06",
    "gn:admin2_code":"623.0",
    "gn:admin3_code":"62388.0",
    "gn:asciiname":"Wiersdorf",
    "gn:country_code":"AT",
    "gn:dem":283,
    "gn:feature_class":"P",
    "gn:feature_code":"PPL",
    "gn:name":"Wiersdorf",
    "gn:population":158,
    "gn:timezone":"Europe/Vienna",
    "iso:country":"AT",
    "wof:name":"Wiersdorf",
    "wof:placetype":"locality",
    "wof:population":158
},
  "geometry": {"coordinates":[15.75583,46.825],"type":"Point"}
}