{
  "type": "Feature",
  "properties": {
    "gn:admin1_code":"3.0",
    "gn:admin2_code":"316",
    "gn:admin3_code":"31604.0",
    "gn:asciiname":"Muhlberg",
    "gn:country_code":"AT",
    "gn:dem":180,
    "gn:feature_class":"P",
    "gn:feature_code":"PPLL",
    "gn:name":"M\u00fchlberg",
    "gn:population":0,
    "gn:timezone":"Europe/Vienna",
    "iso:country":"AT",
    "wof:name":"Muhlberg",
    "wof:placetype":"locality"
},
  "geometry": {"coordinates":[16.82389,48.67444],"type":"Point"}
}