{
  "type": "Feature",
  "properties": {
    "gn:admin1_code":"06",
    "gn:admin2_code":"611.0",
    "gn:admin3_code":"61105.0",
    "gn:asciiname":"Sonnberg",
    "gn:country_code":"AT",
    "gn:dem":810,
    "gn:feature_class":"P",
    "gn:feature_code":"PPL",
    "gn:name":"Sonnberg",
    "gn:population":86,
    "gn:timezone":"Europe/Vienna",
    "iso:country":"AT",
    "wof:name":"Sonnberg",
    "wof:placetype":"locality",
    "wof:population":86
},
  "geometry": {"coordinates":[14.73333,47.43333],"type":"Point"}
}