{
  "type": "Feature",
  "properties": {
    "gn:admin1_code":"4.0",
    "gn:admin2_code":"414",
    "gn:admin3_code":"41410.0",
    "gn:asciiname":"Hanzing",
    "gn:country_code":"AT",
    "gn:dem":439,
    "gn:feature_class":"P",
    "gn:feature_code":"PPL",
    "gn:name":"Hanzing",
    "gn:population":44,
    "gn:timezone":"Europe/Vienna",
    "iso:country":"AT",
    "wof:name":"Hanzing",
    "wof:placetype":"locality",
    "wof:population":44
},
  "geometry": {"coordinates":[13.48765,48.54937],"type":"Point"}
}