{
  "type": "Feature",
  "properties": {
    "gn:admin1_code":"5.0",
    "gn:admin2_code":"503",
    "gn:admin3_code":"50320.0",
    "gn:asciiname":"Helming",
    "gn:country_code":"AT",
    "gn:dem":594,
    "gn:feature_class":"P",
    "gn:feature_code":"PPL",
    "gn:name":"Helming",
    "gn:population":272,
    "gn:timezone":"Europe/Vienna",
    "iso:country":"AT",
    "wof:name":"Helming",
    "wof:placetype":"locality",
    "wof:population":272
},
  "geometry": {"coordinates":[13.15,47.93333],"type":"Point"}
}