{
  "type": "Feature",
  "properties": {
    "gn:admin1_code":"7.0",
    "gn:admin2_code":"708",
    "gn:admin3_code":"70831.0",
    "gn:asciiname":"Duernau",
    "gn:country_code":"AT",
    "gn:dem":1120,
    "gn:feature_class":"P",
    "gn:feature_code":"PPL",
    "gn:name":"D\u00fcrnau",
    "gn:population":0,
    "gn:timezone":"Europe/Vienna",
    "iso:country":"AT",
    "name:und_x_variant":[
        "D\u00fcrrnau",
        "D\u00fcrnau"
    ],
    "wof:name":"Duernau",
    "wof:placetype":"locality"
},
  "geometry": {"coordinates":[10.31667,47.25],"type":"Point"}
}