{
  "type": "Feature",
  "properties": {
    "gn:admin1_code":"01",
    "gn:admin2_code":"104.0",
    "gn:admin3_code":"10416.0",
    "gn:asciiname":"Sumetendorf",
    "gn:country_code":"AT",
    "gn:dem":214,
    "gn:feature_class":"P",
    "gn:feature_code":"PPL",
    "gn:name":"Sumetendorf",
    "gn:population":50,
    "gn:timezone":"Europe/Vienna",
    "iso:country":"AT",
    "name:hun_x_preferred":[
        "Szombatfa"
    ],
    "wof:name":"Sumetendorf",
    "wof:placetype":"locality",
    "wof:population":50
},
  "geometry": {"coordinates":[16.39349,47.04451],"type":"Point"}
}