{
  "type": "Feature",
  "properties": {
    "gn:admin1_code":"05",
    "gn:admin2_code":"506.0",
    "gn:admin3_code":"50624.0",
    "gn:asciiname":"Pirtendorf",
    "gn:country_code":"AT",
    "gn:dem":775,
    "gn:feature_class":"P",
    "gn:feature_code":"PPL",
    "gn:name":"Pirtendorf",
    "gn:population":0,
    "gn:timezone":"Europe/Vienna",
    "iso:country":"AT",
    "wof:name":"Pirtendorf",
    "wof:placetype":"locality"
},
  "geometry": {"coordinates":[12.55,47.28333],"type":"Point"}
}