{
  "type": "Feature",
  "properties": {
    "gn:admin1_code":"2.0",
    "gn:admin2_code":"203",
    "gn:admin3_code":"20320.0",
    "gn:asciiname":"Liesch",
    "gn:country_code":"AT",
    "gn:dem":663,
    "gn:feature_class":"P",
    "gn:feature_code":"PPL",
    "gn:name":"Liesch",
    "gn:population":0,
    "gn:timezone":"Europe/Vienna",
    "iso:country":"AT",
    "wof:name":"Liesch",
    "wof:placetype":"locality"
},
  "geometry": {"coordinates":[13.33333,46.65],"type":"Point"}
}