{
  "type": "Feature",
  "properties": {
    "gn:admin1_code":"4.0",
    "gn:admin2_code":"417",
    "gn:admin3_code":"41722.0",
    "gn:asciiname":"Hagleithen",
    "gn:country_code":"AT",
    "gn:dem":508,
    "gn:feature_class":"P",
    "gn:feature_code":"PPL",
    "gn:name":"Hagleithen",
    "gn:population":86,
    "gn:timezone":"Europe/Vienna",
    "iso:country":"AT",
    "wof:name":"Hagleithen",
    "wof:placetype":"locality",
    "wof:population":86
},
  "geometry": {"coordinates":[13.64609,48.0884],"type":"Point"}
}