{
  "type": "Feature",
  "properties": {
    "gn:admin1_code":"6.0",
    "gn:admin2_code":"616",
    "gn:admin3_code":"61612.0",
    "gn:asciiname":"Grusser",
    "gn:country_code":"AT",
    "gn:dem":637,
    "gn:feature_class":"P",
    "gn:feature_code":"PPL",
    "gn:name":"Gr\u00fcsser",
    "gn:population":0,
    "gn:timezone":"Europe/Vienna",
    "iso:country":"AT",
    "wof:name":"Grusser",
    "wof:placetype":"locality"
},
  "geometry": {"coordinates":[15.20833,46.96583],"type":"Point"}
}