{
  "type": "Feature",
  "properties": {
    "gn:admin1_code":"4.0",
    "gn:admin2_code":"404",
    "gn:admin3_code":"40444.0",
    "gn:asciiname":"Ascherdorf",
    "gn:country_code":"AT",
    "gn:dem":423,
    "gn:feature_class":"P",
    "gn:feature_code":"PPL",
    "gn:name":"Ascherdorf",
    "gn:population":19,
    "gn:timezone":"Europe/Vienna",
    "iso:country":"AT",
    "wof:name":"Ascherdorf",
    "wof:placetype":"locality",
    "wof:population":19
},
  "geometry": {"coordinates":[13.21818,48.18958],"type":"Point"}
}