{
  "type": "Feature",
  "properties": {
    "gn:admin1_code":"4.0",
    "gn:admin2_code":"414",
    "gn:admin3_code":"41420.0",
    "gn:asciiname":"Ginzlberg",
    "gn:country_code":"AT",
    "gn:dem":526,
    "gn:feature_class":"P",
    "gn:feature_code":"PPL",
    "gn:name":"Ginzlberg",
    "gn:population":26,
    "gn:timezone":"Europe/Vienna",
    "iso:country":"AT",
    "wof:name":"Ginzlberg",
    "wof:placetype":"locality",
    "wof:population":26
},
  "geometry": {"coordinates":[13.59306,48.50667],"type":"Point"}
}