{
  "type": "Feature",
  "properties": {
    "gn:admin1_code":"04",
    "gn:admin2_code":"416.0",
    "gn:admin3_code":"41626.0",
    "gn:asciiname":"Purwoerth",
    "gn:country_code":"AT",
    "gn:dem":259,
    "gn:feature_class":"P",
    "gn:feature_code":"PPL",
    "gn:name":"Purw\u00f6rth",
    "gn:population":0,
    "gn:timezone":"Europe/Vienna",
    "iso:country":"AT",
    "wof:name":"Purwoerth",
    "wof:placetype":"locality"
},
  "geometry": {"coordinates":[14.12756,48.32829],"type":"Point"}
}