{
  "type": "Feature",
  "properties": {
    "gn:admin1_code":"2.0",
    "gn:admin2_code":"204",
    "gn:admin3_code":"20403.0",
    "gn:asciiname":"Muschkau",
    "gn:cc2":"AT",
    "gn:country_code":"AT",
    "gn:dem":591,
    "gn:feature_class":"P",
    "gn:feature_code":"PPL",
    "gn:name":"Muschkau",
    "gn:population":0,
    "gn:timezone":"Europe/Vienna",
    "iso:country":"AT",
    "name:deu_x_preferred":[
        "Muschkau"
    ],
    "name:slv_x_preferred":[
        "Mu\u0161kava"
    ],
    "wof:name":"Muschkau",
    "wof:placetype":"locality"
},
  "geometry": {"coordinates":[14.17614,46.54747],"type":"Point"}
}