{
  "type": "Feature",
  "properties": {
    "gn:admin1_code":"06",
    "gn:admin2_code":"623.0",
    "gn:admin3_code":"62390.0",
    "gn:asciiname":"Sulzbach",
    "gn:country_code":"AT",
    "gn:dem":256,
    "gn:feature_class":"P",
    "gn:feature_code":"PPL",
    "gn:name":"Sulzbach",
    "gn:population":83,
    "gn:timezone":"Europe/Vienna",
    "iso:country":"AT",
    "name:als_x_preferred":[
        "Sulzbach"
    ],
    "name:bul_x_preferred":[
        "\u0417\u0443\u043b\u0446\u0431\u0430\u0445"
    ],
    "name:cat_x_preferred":[
        "Sulzbach"
    ],
    "name:ceb_x_preferred":[
        "Sulzbach"
    ],
    "name:deu_x_preferred":[
        "Sulzbach"
    ],
    "name:epo_x_preferred":[
        "Sulzbach"
    ],
    "name:fra_x_preferred":[
        "Sulzbach"
    ],
    "name:ita_x_preferred":[
        "Sulzbach"
    ],
    "name:kaz_x_preferred":[
        "\u0417\u0443\u043b\u044c\u0446\u0431\u0430\u0445"
    ],
    "name:nld_x_preferred":[
        "Sulzbach"
    ],
    "name:pol_x_preferred":[
        "Sulzbach"
    ],
    "name:por_x_preferred":[
        "Sulzbach"
    ],
    "name:rus_x_preferred":[
        "\u0417\u0443\u043b\u044c\u0446\u0431\u0430\u0445"
    ],
    "name:spa_x_preferred":[
        "Sulzbach"
    ],
    "name:srp_x_preferred":[
        "\u0417\u0443\u043b\u0446\u0431\u0430\u0445"
    ],
    "name:swe_x_preferred":[
        "Sulzbach"
    ],
    "name:vol_x_preferred":[
        "Sulzbach"
    ],
    "wof:name":"Sulzbach",
    "wof:placetype":"locality",
    "wof:population":83
},
  "geometry": {"coordinates":[15.89639,46.805],"type":"Point"}
}