{
  "type": "Feature",
  "properties": {
    "gn:admin1_code":"3.0",
    "gn:admin2_code":"320",
    "gn:admin3_code":"32018.0",
    "gn:asciiname":"Keppelberg",
    "gn:country_code":"AT",
    "gn:dem":302,
    "gn:feature_class":"P",
    "gn:feature_code":"PPL",
    "gn:name":"Keppelberg",
    "gn:population":18,
    "gn:timezone":"Europe/Vienna",
    "iso:country":"AT",
    "wof:name":"Keppelberg",
    "wof:placetype":"locality",
    "wof:population":18
},
  "geometry": {"coordinates":[15.05706,48.10766],"type":"Point"}
}