{
  "type": "Feature",
  "properties": {
    "gn:country":"AT",
    "gn:fcode":"PPL",
    "gn:population":0,
    "iso:country":"AT",
    "name:ceb_x_preferred":[
        "Asparn an der Zaya"
    ],
    "name:ces_x_preferred":[
        "Asparn an der Zaya"
    ],
    "name:deu_x_preferred":[
        "Asparn an der Zaya"
    ],
    "name:epo_x_preferred":[
        "Asparn an der Zaya"
    ],
    "name:fas_x_preferred":[
        "\u0622\u0634\u067e\u0627\u0631\u0646 \u0622\u0646\u062f\u0631 \u0633\u0627\u06cc\u0627"
    ],
    "name:fra_x_preferred":[
        "Asparn an der Zaya"
    ],
    "name:hun_x_preferred":[
        "Asparn an der Zaya"
    ],
    "name:ita_x_preferred":[
        "Asparn an der Zaya"
    ],
    "name:nld_x_preferred":[
        "Asparn an der Zaya"
    ],
    "name:pol_x_preferred":[
        "Asparn an der Zaya"
    ],
    "name:por_x_preferred":[
        "Asparn an der Zaya"
    ],
    "name:slk_x_preferred":[
        "Asparn an der Zaya"
    ],
    "name:spa_x_preferred":[
        "Asparn an der Zaya"
    ],
    "name:swe_x_preferred":[
        "Asparn an der Zaya"
    ],
    "name:uzb_x_preferred":[
        "Asparn an der Zaya"
    ],
    "name:vie_x_preferred":[
        "Asparn an der Zaya"
    ],
    "name:vol_x_preferred":[
        "Asparn an der Zaya"
    ],
    "name:war_x_preferred":[
        "Asparn an der Zaya"
    ],
    "qs_pg:aaroncc":"AT",
    "qs_pg:gn_country":"AT",
    "qs_pg:gn_fcode":"PPL",
    "qs_pg:gn_pop":0,
    "qs_pg:name":"Asparn an der Zaya",
    "qs_pg:name_adm0":"\u00d6sterreich",
    "qs_pg:name_adm1":"Nieder\u00f6sterreich",
    "qs_pg:photos":29,
    "qs_pg:photos_1k":6,
    "qs_pg:photos_9k":1,
    "qs_pg:photos_9r":2,
    "qs_pg:photos_all":29,
    "qs_pg:photos_sr":2,
    "qs_pg:pop_sr":0,
    "qs_pg:qs_pg_placetype":"locality",
    "qs_pg:qs_pg_placetype_gp":"Town",
    "qs_pg:woe_adm0":23424750,
    "woe:adm0_id":23424750,
    "woe:name_adm0":"\u00d6sterreich",
    "woe:name_adm1":"Nieder\u00f6sterreich",
    "woe:placetype":"Town",
    "wof:name":"Asparn an der Zaya",
    "wof:placetype":"locality"
},
  "geometry": {"coordinates":[16.00914,48.31905],"type":"Point"}
}