{
  "type": "Feature",
  "properties": {
    "gn:admin1_code":"3.0",
    "gn:admin2_code":"319",
    "gn:admin3_code":"31927.0",
    "gn:asciiname":"Aschberg",
    "gn:country_code":"AT",
    "gn:dem":397,
    "gn:feature_class":"P",
    "gn:feature_code":"PPL",
    "gn:name":"Aschberg",
    "gn:population":42,
    "gn:timezone":"Europe/Vienna",
    "iso:country":"AT",
    "wof:name":"Aschberg",
    "wof:placetype":"locality",
    "wof:population":42
},
  "geometry": {"coordinates":[15.87808,48.15389],"type":"Point"}
}