{
  "type": "Feature",
  "properties": {
    "gn:admin1_code":"3.0",
    "gn:admin2_code":"315",
    "gn:admin3_code":"31514.0",
    "gn:asciiname":"Panschach",
    "gn:country_code":"AT",
    "gn:dem":387,
    "gn:feature_class":"P",
    "gn:feature_code":"PPL",
    "gn:name":"Panschach",
    "gn:population":46,
    "gn:timezone":"Europe/Vienna",
    "iso:country":"AT",
    "wof:name":"Panschach",
    "wof:placetype":"locality",
    "wof:population":46
},
  "geometry": {"coordinates":[15.39996,48.08232],"type":"Point"}
}