{
  "type": "Feature",
  "properties": {
    "gn:admin1_code":"6.0",
    "gn:admin2_code":"621",
    "gn:admin3_code":"62140.0",
    "gn:asciiname":"Diemlach",
    "gn:country_code":"AT",
    "gn:dem":493,
    "gn:feature_class":"P",
    "gn:feature_code":"PPL",
    "gn:name":"Diemlach",
    "gn:population":1976,
    "gn:timezone":"Europe/Vienna",
    "iso:country":"AT",
    "wof:name":"Diemlach",
    "wof:placetype":"locality",
    "wof:population":1976
},
  "geometry": {"coordinates":[15.2746,47.4361],"type":"Point"}
}