{
  "type": "Feature",
  "properties": {
    "gn:admin1_code":"4.0",
    "gn:admin2_code":"408",
    "gn:admin3_code":"40827.0",
    "gn:asciiname":"Mitterndorf",
    "gn:country_code":"AT",
    "gn:dem":372,
    "gn:feature_class":"P",
    "gn:feature_code":"PPL",
    "gn:name":"Mitterndorf",
    "gn:population":29,
    "gn:timezone":"Europe/Vienna",
    "iso:country":"AT",
    "wof:name":"Mitterndorf",
    "wof:placetype":"locality",
    "wof:population":29
},
  "geometry": {"coordinates":[13.87376,48.20969],"type":"Point"}
}