{
  "type": "Feature",
  "properties": {
    "gn:admin1_code":"4.0",
    "gn:admin2_code":"417",
    "gn:admin3_code":"41706.0",
    "gn:asciiname":"Woetzing",
    "gn:country_code":"AT",
    "gn:dem":546,
    "gn:feature_class":"P",
    "gn:feature_code":"PPL",
    "gn:name":"W\u00f6tzing",
    "gn:population":61,
    "gn:timezone":"Europe/Vienna",
    "iso:country":"AT",
    "wof:name":"Woetzing",
    "wof:placetype":"locality",
    "wof:population":61
},
  "geometry": {"coordinates":[13.48211,47.94903],"type":"Point"}
}