{
  "type": "Feature",
  "properties": {
    "gn:admin1_code":"07",
    "gn:admin2_code":"708.0",
    "gn:admin3_code":"70835.0",
    "gn:asciiname":"Winkl",
    "gn:country_code":"AT",
    "gn:dem":919,
    "gn:feature_class":"P",
    "gn:feature_code":"PPL",
    "gn:name":"Winkl",
    "gn:population":179,
    "gn:timezone":"Europe/Vienna",
    "iso:country":"AT",
    "wof:name":"Winkl",
    "wof:placetype":"locality",
    "wof:population":179
},
  "geometry": {"coordinates":[10.68214,47.48461],"type":"Point"}
}