{
  "type": "Feature",
  "properties": {
    "gn:admin1_code":"4.0",
    "gn:admin2_code":"408",
    "gn:admin3_code":"40833.0",
    "gn:asciiname":"Grolzham",
    "gn:country_code":"AT",
    "gn:dem":485,
    "gn:feature_class":"P",
    "gn:feature_code":"PPL",
    "gn:name":"Grolzham",
    "gn:population":114,
    "gn:timezone":"Europe/Vienna",
    "iso:country":"AT",
    "wof:name":"Grolzham",
    "wof:placetype":"locality",
    "wof:population":114
},
  "geometry": {"coordinates":[13.66064,48.17192],"type":"Point"}
}