{
  "type": "Feature",
  "properties": {
    "iso:country":"AT",
    "qs_pg:aaroncc":"AT",
    "qs_pg:name":"Patriasdorf",
    "qs_pg:name_adm0":"\u00d6sterreich",
    "qs_pg:name_adm1":"Tirol",
    "qs_pg:photos":32,
    "qs_pg:photos_1k":6,
    "qs_pg:photos_9k":1,
    "qs_pg:photos_9r":2,
    "qs_pg:photos_all":32,
    "qs_pg:photos_sr":2,
    "qs_pg:pop_sr":0,
    "qs_pg:qs_pg_placetype":"locality",
    "qs_pg:qs_pg_placetype_gp":"Town",
    "qs_pg:woe_adm0":23424750,
    "woe:adm0_id":23424750,
    "woe:name_adm0":"\u00d6sterreich",
    "woe:name_adm1":"Tirol",
    "woe:placetype":"Town",
    "wof:name":"Patriasdorf",
    "wof:placetype":"locality"
},
  "geometry": {"coordinates":[12.751178,46.830662],"type":"Point"}
}