{
  "type": "Feature",
  "properties": {
    "gn:admin1_code":"4.0",
    "gn:admin2_code":"408",
    "gn:admin3_code":"40812.0",
    "gn:asciiname":"Guettling",
    "gn:country_code":"AT",
    "gn:dem":422,
    "gn:feature_class":"P",
    "gn:feature_code":"PPL",
    "gn:name":"G\u00fcttling",
    "gn:population":74,
    "gn:timezone":"Europe/Vienna",
    "iso:country":"AT",
    "wof:name":"Guettling",
    "wof:placetype":"locality",
    "wof:population":74
},
  "geometry": {"coordinates":[13.6827,48.29364],"type":"Point"}
}