{
  "type": "Feature",
  "properties": {
    "gn:admin1_code":"4.0",
    "gn:admin2_code":"414",
    "gn:admin3_code":"41416.0",
    "gn:asciiname":"Vormarkt",
    "gn:country_code":"AT",
    "gn:dem":370,
    "gn:feature_class":"P",
    "gn:feature_code":"PPL",
    "gn:name":"Vormarkt",
    "gn:population":178,
    "gn:timezone":"Europe/Vienna",
    "iso:country":"AT",
    "wof:name":"Vormarkt",
    "wof:placetype":"locality",
    "wof:population":178
},
  "geometry": {"coordinates":[13.62944,48.30435],"type":"Point"}
}