{
  "type": "Feature",
  "properties": {
    "gn:admin1_code":"2.0",
    "gn:admin2_code":"205",
    "gn:admin3_code":"20534.0",
    "gn:asciiname":"Grassen",
    "gn:country_code":"AT",
    "gn:dem":729,
    "gn:feature_class":"P",
    "gn:feature_code":"PPL",
    "gn:name":"Grassen",
    "gn:population":14,
    "gn:timezone":"Europe/Vienna",
    "iso:country":"AT",
    "name:ara_x_preferred":[
        "\u063a\u0631\u0627\u0633\u064a\u0646"
    ],
    "name:ceb_x_preferred":[
        "Grassen"
    ],
    "name:deu_x_preferred":[
        "Grassen"
    ],
    "name:fra_x_preferred":[
        "Grassen"
    ],
    "name:nno_x_preferred":[
        "Grassen"
    ],
    "name:swe_x_preferred":[
        "Grassen"
    ],
    "wof:name":"Grassen",
    "wof:placetype":"locality",
    "wof:population":14
},
  "geometry": {"coordinates":[14.34531,46.79166],"type":"Point"}
}