{
  "type": "Feature",
  "properties": {
    "gn:admin1_code":"3.0",
    "gn:admin2_code":"325",
    "gn:admin3_code":"32508.0",
    "gn:asciiname":"Egres",
    "gn:country_code":"AT",
    "gn:dem":704,
    "gn:feature_class":"P",
    "gn:feature_code":"PPL",
    "gn:name":"Egres",
    "gn:population":67,
    "gn:timezone":"Europe/Vienna",
    "iso:country":"AT",
    "wof:name":"Egres",
    "wof:placetype":"locality",
    "wof:population":67
},
  "geometry": {"coordinates":[14.96667,48.55],"type":"Point"}
}