{
  "type": "Feature",
  "properties": {
    "gn:admin1_code":"3.0",
    "gn:admin2_code":"315",
    "gn:admin3_code":"31542.0",
    "gn:asciiname":"Hub",
    "gn:country_code":"AT",
    "gn:dem":317,
    "gn:feature_class":"P",
    "gn:feature_code":"PPL",
    "gn:name":"Hub",
    "gn:population":65,
    "gn:timezone":"Europe/Vienna",
    "iso:country":"AT",
    "wof:name":"Hub",
    "wof:placetype":"locality",
    "wof:population":65
},
  "geometry": {"coordinates":[15.36198,48.24197],"type":"Point"}
}