{
  "type": "Feature",
  "properties": {
    "gn:admin1_code":"1.0",
    "gn:admin2_code":"105",
    "gn:admin3_code":"10509.0",
    "gn:asciiname":"Doiber",
    "gn:country_code":"AT",
    "gn:dem":244,
    "gn:feature_class":"P",
    "gn:feature_code":"PPL",
    "gn:name":"Doiber",
    "gn:population":235,
    "gn:timezone":"Europe/Vienna",
    "iso:country":"AT",
    "wof:name":"Doiber",
    "wof:placetype":"locality",
    "wof:population":235
},
  "geometry": {"coordinates":[16.11528,46.92222],"type":"Point"}
}