{
  "type": "Feature",
  "properties": {
    "gn:admin1_code":"03",
    "gn:admin2_code":"309.0",
    "gn:admin3_code":"30903.0",
    "gn:asciiname":"Waldhauseln",
    "gn:country_code":"AT",
    "gn:dem":562,
    "gn:feature_class":"P",
    "gn:feature_code":"PPLL",
    "gn:name":"Waldh\u00e4useln",
    "gn:population":0,
    "gn:timezone":"Europe/Vienna",
    "iso:country":"AT",
    "wof:name":"Waldhauseln",
    "wof:placetype":"locality"
},
  "geometry": {"coordinates":[15.01667,48.81667],"type":"Point"}
}