{
  "type": "Feature",
  "properties": {
    "iso:country":"AT",
    "name:deu_x_preferred":[
        "Teichhof"
    ],
    "name:eng_x_preferred":[
        "Teichhof"
    ],
    "wof:name":"Teichhof",
    "wof:placetype":"neighbourhood"
},
  "geometry": {"coordinates":[15.4873926456693,47.09953790844372],"type":"Point"}
}