{
  "type": "Feature",
  "properties": {
    "gn:admin1_code":"3.0",
    "gn:admin2_code":"307",
    "gn:admin3_code":"30726.0",
    "gn:asciiname":"Gallbrunn",
    "gn:country_code":"AT",
    "gn:dem":160,
    "gn:feature_class":"P",
    "gn:feature_code":"PPL",
    "gn:name":"Gallbrunn",
    "gn:population":733,
    "gn:timezone":"Europe/Vienna",
    "iso:country":"AT",
    "wof:name":"Gallbrunn",
    "wof:placetype":"locality",
    "wof:population":733
},
  "geometry": {"coordinates":[16.63332999999999,48.05],"type":"Point"}
}