{
  "type": "Feature",
  "properties": {
    "gn:admin1_code":"2.0",
    "gn:admin2_code":"210",
    "gn:admin3_code":"21001.0",
    "gn:asciiname":"Grillenberg",
    "gn:country_code":"AT",
    "gn:dem":871,
    "gn:feature_class":"P",
    "gn:feature_code":"PPL",
    "gn:name":"Grillenberg",
    "gn:population":78,
    "gn:timezone":"Europe/Vienna",
    "iso:country":"AT",
    "name:ceb_x_preferred":[
        "Grillenberg"
    ],
    "name:deu_x_preferred":[
        "Grillenberg"
    ],
    "name:swe_x_preferred":[
        "Grillenberg"
    ],
    "wof:name":"Grillenberg",
    "wof:placetype":"locality",
    "wof:population":78
},
  "geometry": {"coordinates":[14.05389,46.81694],"type":"Point"}
}