{
  "type": "Feature",
  "properties": {
    "gn:admin1_code":"5.0",
    "gn:admin2_code":"503",
    "gn:admin3_code":"50322.0",
    "gn:asciiname":"Ausserfuert",
    "gn:country_code":"AT",
    "gn:dem":435,
    "gn:feature_class":"P",
    "gn:feature_code":"PPL",
    "gn:name":"Ausserf\u00fcrt",
    "gn:population":24,
    "gn:timezone":"Europe/Vienna",
    "iso:country":"AT",
    "wof:name":"Ausserfuert",
    "wof:placetype":"locality",
    "wof:population":24
},
  "geometry": {"coordinates":[12.95571,48.02994],"type":"Point"}
}