{
  "type": "Feature",
  "properties": {
    "gn:admin1_code":"2.0",
    "gn:admin2_code":"205",
    "gn:admin3_code":"20531.0",
    "gn:asciiname":"Grabenig",
    "gn:country_code":"AT",
    "gn:dem":808,
    "gn:feature_class":"P",
    "gn:feature_code":"PPL",
    "gn:name":"Grabenig",
    "gn:population":50,
    "gn:timezone":"Europe/Vienna",
    "iso:country":"AT",
    "wof:name":"Grabenig",
    "wof:placetype":"locality",
    "wof:population":50
},
  "geometry": {"coordinates":[14.21333,46.88861],"type":"Point"}
}