{
  "type": "Feature",
  "properties": {
    "gn:admin1_code":"04",
    "gn:admin2_code":"412.0",
    "gn:admin3_code":"41232.0",
    "gn:asciiname":"Walchshausen",
    "gn:country_code":"AT",
    "gn:dem":446,
    "gn:feature_class":"P",
    "gn:feature_code":"PPL",
    "gn:name":"Walchshausen",
    "gn:population":48,
    "gn:timezone":"Europe/Vienna",
    "iso:country":"AT",
    "wof:name":"Walchshausen",
    "wof:placetype":"locality",
    "wof:population":48
},
  "geometry": {"coordinates":[13.50932,48.24274000000001],"type":"Point"}
}