{
  "type": "Feature",
  "properties": {
    "gn:admin1_code":"03",
    "gn:admin2_code":"319.0",
    "gn:admin3_code":"31952.0",
    "gn:asciiname":"Dambach",
    "gn:country_code":"AT",
    "gn:dem":316,
    "gn:feature_class":"P",
    "gn:feature_code":"PPL",
    "gn:name":"Dambach",
    "gn:population":0,
    "gn:timezone":"Europe/Vienna",
    "iso:country":"AT",
    "name:cat_x_preferred":[
        "Dambach"
    ],
    "name:ceb_x_preferred":[
        "Dambach"
    ],
    "name:deu_x_preferred":[
        "Dambach"
    ],
    "name:fra_x_preferred":[
        "Dambach"
    ],
    "name:ita_x_preferred":[
        "Dambach"
    ],
    "name:nld_x_preferred":[
        "Dambach"
    ],
    "name:pol_x_preferred":[
        "Dambach"
    ],
    "name:por_x_preferred":[
        "Dambach"
    ],
    "name:swe_x_preferred":[
        "Dambach"
    ],
    "name:vol_x_preferred":[
        "Dambach"
    ],
    "wof:name":"Dambach",
    "wof:placetype":"locality"
},
  "geometry": {"coordinates":[16.14716,48.18246],"type":"Point"}
}