{
  "type": "Feature",
  "properties": {
    "gn:admin1_code":"04",
    "gn:admin2_code":"415.0",
    "gn:admin3_code":"41506.0",
    "gn:asciiname":"Pesendorf",
    "gn:country_code":"AT",
    "gn:dem":401,
    "gn:feature_class":"P",
    "gn:feature_code":"PPL",
    "gn:name":"Pesendorf",
    "gn:population":357,
    "gn:timezone":"Europe/Vienna",
    "iso:country":"AT",
    "wof:name":"Pesendorf",
    "wof:placetype":"locality",
    "wof:population":357
},
  "geometry": {"coordinates":[14.38454,48.01433],"type":"Point"}
}