{
  "type": "Feature",
  "properties": {
    "gn:admin1_code":"6.0",
    "gn:admin2_code":"606",
    "gn:admin3_code":"60626.0",
    "gn:asciiname":"Frindorf",
    "gn:country_code":"AT",
    "gn:dem":457,
    "gn:feature_class":"P",
    "gn:feature_code":"PPL",
    "gn:name":"Frindorf",
    "gn:population":0,
    "gn:timezone":"Europe/Vienna",
    "iso:country":"AT",
    "wof:name":"Frindorf",
    "wof:placetype":"locality"
},
  "geometry": {"coordinates":[15.55,47.15],"type":"Point"}
}