{
  "type": "Feature",
  "properties": {
    "gn:admin1_code":"4.0",
    "gn:admin2_code":"418",
    "gn:admin3_code":"41813.0",
    "gn:asciiname":"Hofern",
    "gn:country_code":"AT",
    "gn:dem":386,
    "gn:feature_class":"P",
    "gn:feature_code":"PPL",
    "gn:name":"Hofern",
    "gn:population":76,
    "gn:timezone":"Europe/Vienna",
    "iso:country":"AT",
    "wof:name":"Hofern",
    "wof:placetype":"locality",
    "wof:population":76
},
  "geometry": {"coordinates":[13.82235,48.08863],"type":"Point"}
}