{
  "type": "Feature",
  "properties": {
    "gn:admin1_code":"3.0",
    "gn:admin2_code":"319",
    "gn:admin3_code":"31948.0",
    "gn:asciiname":"Landersdorf",
    "gn:country_code":"AT",
    "gn:dem":393,
    "gn:feature_class":"P",
    "gn:feature_code":"PPL",
    "gn:name":"Landersdorf",
    "gn:population":322,
    "gn:timezone":"Europe/Vienna",
    "iso:country":"AT",
    "wof:name":"Landersdorf",
    "wof:placetype":"locality",
    "wof:population":322
},
  "geometry": {"coordinates":[15.57587,48.31488],"type":"Point"}
}