{
  "type": "Feature",
  "properties": {
    "gn:admin1_code":"4.0",
    "gn:admin2_code":"407",
    "gn:admin3_code":"40715.0",
    "gn:asciiname":"Asang",
    "gn:country_code":"AT",
    "gn:dem":390,
    "gn:feature_class":"P",
    "gn:feature_code":"PPL",
    "gn:name":"Asang",
    "gn:population":0,
    "gn:timezone":"Europe/Vienna",
    "iso:country":"AT",
    "wof:name":"Asang",
    "wof:placetype":"locality"
},
  "geometry": {"coordinates":[13.84726,48.05109],"type":"Point"}
}