{
  "type": "Feature",
  "properties": {
    "gn:admin1_code":"4.0",
    "gn:admin2_code":"407",
    "gn:admin3_code":"40710.0",
    "gn:asciiname":"kasberg",
    "gn:country_code":"AT",
    "gn:dem":491,
    "gn:feature_class":"P",
    "gn:feature_code":"PPL",
    "gn:name":"kasberg",
    "gn:population":0,
    "gn:timezone":"Europe/Vienna",
    "iso:country":"AT",
    "wof:name":"kasberg",
    "wof:placetype":"locality"
},
  "geometry": {"coordinates":[13.91273,47.95872],"type":"Point"}
}