{
  "type": "Feature",
  "properties": {
    "gn:admin1_code":"4.0",
    "gn:admin2_code":"414",
    "gn:admin3_code":"41404.0",
    "gn:asciiname":"Kalling",
    "gn:country_code":"AT",
    "gn:dem":335,
    "gn:feature_class":"P",
    "gn:feature_code":"PPL",
    "gn:name":"Kalling",
    "gn:population":98,
    "gn:timezone":"Europe/Vienna",
    "iso:country":"AT",
    "wof:name":"Kalling",
    "wof:placetype":"locality",
    "wof:population":98
},
  "geometry": {"coordinates":[13.56417,48.40704],"type":"Point"}
}