{
  "type": "Feature",
  "properties": {
    "gn:admin1_code":"01",
    "gn:admin2_code":"109.0",
    "gn:admin3_code":"10923.0",
    "gn:asciiname":"Schoenau",
    "gn:country_code":"AT",
    "gn:dem":450,
    "gn:feature_class":"P",
    "gn:feature_code":"PPL",
    "gn:name":"Sch\u00f6nau",
    "gn:population":0,
    "gn:timezone":"Europe/Vienna",
    "iso:country":"AT",
    "wof:name":"Schoenau",
    "wof:placetype":"locality"
},
  "geometry": {"coordinates":[16.28333,47.33333],"type":"Point"}
}