{
  "type": "Feature",
  "properties": {
    "gn:admin1_code":"02",
    "gn:admin2_code":"205.0",
    "gn:admin3_code":"20501.0",
    "gn:asciiname":"Toescheldorf",
    "gn:country_code":"AT",
    "gn:dem":735,
    "gn:feature_class":"P",
    "gn:feature_code":"PPL",
    "gn:name":"T\u00f6scheldorf",
    "gn:population":5,
    "gn:timezone":"Europe/Vienna",
    "iso:country":"AT",
    "wof:name":"Toescheldorf",
    "wof:placetype":"locality",
    "wof:population":5
},
  "geometry": {"coordinates":[14.46667,46.88333],"type":"Point"}
}