{
  "type": "Feature",
  "properties": {
    "gn:admin1_code":"05",
    "gn:admin2_code":"503.0",
    "gn:admin3_code":"50335.0",
    "gn:asciiname":"Stockham",
    "gn:country_code":"AT",
    "gn:dem":595,
    "gn:feature_class":"P",
    "gn:feature_code":"PPL",
    "gn:name":"Stockham",
    "gn:population":69,
    "gn:timezone":"Europe/Vienna",
    "iso:country":"AT",
    "name:deu_x_preferred":[
        "Stockham"
    ],
    "wof:name":"Stockham",
    "wof:placetype":"locality",
    "wof:population":69
},
  "geometry": {"coordinates":[13.31101,47.96728],"type":"Point"}
}