{
  "type": "Feature",
  "properties": {
    "gn:admin1_code":"3.0",
    "gn:admin2_code":"313",
    "gn:admin3_code":"31350.0",
    "gn:asciiname":"Himberg",
    "gn:country_code":"AT",
    "gn:dem":706,
    "gn:feature_class":"P",
    "gn:feature_code":"PPL",
    "gn:name":"Himberg",
    "gn:population":67,
    "gn:timezone":"Europe/Vienna",
    "iso:country":"AT",
    "wof:name":"Himberg",
    "wof:placetype":"locality",
    "wof:population":67
},
  "geometry": {"coordinates":[15.38333,48.41667],"type":"Point"}
}