{
  "type": "Feature",
  "properties": {
    "gn:admin1_code":"2.0",
    "gn:admin2_code":"210",
    "gn:admin3_code":"21005.0",
    "gn:asciiname":"Fresen",
    "gn:country_code":"AT",
    "gn:dem":772,
    "gn:feature_class":"P",
    "gn:feature_code":"PPLA3",
    "gn:name":"Fresen",
    "gn:population":7,
    "gn:timezone":"Europe/Vienna",
    "iso:country":"AT",
    "wof:name":"Fresen",
    "wof:placetype":"locality",
    "wof:population":7
},
  "geometry": {"coordinates":[14.04513,46.70516],"type":"Point"}
}