{
  "type": "Feature",
  "properties": {
    "gn:admin1_code":"5.0",
    "gn:admin2_code":"503",
    "gn:admin3_code":"50338.0",
    "gn:asciiname":"Walserberg",
    "gn:country_code":"AT",
    "gn:dem":439,
    "gn:feature_class":"P",
    "gn:feature_code":"PPL",
    "gn:name":"Walserberg",
    "gn:population":879,
    "gn:timezone":"Europe/Vienna",
    "iso:country":"AT",
    "wof:name":"Walserberg",
    "wof:placetype":"locality",
    "wof:population":879
},
  "geometry": {"coordinates":[12.9575,47.77389],"type":"Point"}
}