{
  "type": "Feature",
  "properties": {
    "gn:admin1_code":"4.0",
    "gn:admin2_code":"417",
    "gn:admin3_code":"41723.0",
    "gn:asciiname":"Weixlbaum",
    "gn:country_code":"AT",
    "gn:dem":541,
    "gn:feature_class":"P",
    "gn:feature_code":"PPL",
    "gn:name":"Weixlbaum",
    "gn:population":15,
    "gn:timezone":"Europe/Vienna",
    "iso:country":"AT",
    "wof:name":"Weixlbaum",
    "wof:placetype":"locality",
    "wof:population":15
},
  "geometry": {"coordinates":[13.49263,48.01264000000001],"type":"Point"}
}