{
  "type": "Feature",
  "properties": {
    "gn:admin1_code":"04",
    "gn:admin2_code":"408.0",
    "gn:admin3_code":"40811.0",
    "gn:asciiname":"Stroetting",
    "gn:country_code":"AT",
    "gn:dem":379,
    "gn:feature_class":"P",
    "gn:feature_code":"PPL",
    "gn:name":"Str\u00f6tting",
    "gn:population":73,
    "gn:timezone":"Europe/Vienna",
    "iso:country":"AT",
    "wof:name":"Stroetting",
    "wof:placetype":"locality",
    "wof:population":73
},
  "geometry": {"coordinates":[13.73214,48.22347],"type":"Point"}
}