{
  "type": "Feature",
  "properties": {
    "gn:admin1_code":"5.0",
    "gn:admin2_code":"506",
    "gn:admin3_code":"50628.0",
    "gn:asciiname":"Schuettdorf",
    "gn:country_code":"AT",
    "gn:dem":755,
    "gn:feature_class":"P",
    "gn:feature_code":"PPL",
    "gn:name":"Sch\u00fcttdorf",
    "gn:population":0,
    "gn:timezone":"Europe/Vienna",
    "iso:country":"AT",
    "wof:name":"Schuettdorf",
    "wof:placetype":"locality"
},
  "geometry": {"coordinates":[12.79581,47.30356],"type":"Point"}
}