{
  "type": "Feature",
  "properties": {
    "gn:admin1_code":"2.0",
    "gn:admin2_code":"210",
    "gn:admin3_code":"21002.0",
    "gn:asciiname":"Dietrichstein",
    "gn:country_code":"AT",
    "gn:dem":651,
    "gn:feature_class":"P",
    "gn:feature_code":"PPL",
    "gn:name":"Dietrichstein",
    "gn:population":5,
    "gn:timezone":"Europe/Vienna",
    "iso:country":"AT",
    "name:bul_x_preferred":[
        "\u0414\u0438\u0442\u0440\u0438\u0445\u0449\u0430\u0439\u043d"
    ],
    "name:ces_x_preferred":[
        "Ditrich\u0161tejnov\u00e9"
    ],
    "name:deu_x_preferred":[
        "Dietrichstein"
    ],
    "name:fra_x_preferred":[
        "Dietrichstein"
    ],
    "name:ita_x_preferred":[
        "Dietrichstein"
    ],
    "name:nld_x_preferred":[
        "Dietrichstein"
    ],
    "name:rus_x_preferred":[
        "\u0414\u0438\u0442\u0440\u0438\u0445\u0448\u0442\u0435\u0439\u043d\u044b"
    ],
    "name:spa_x_preferred":[
        "Dietrichstein"
    ],
    "name:zho_x_preferred":[
        "\u8fea\u7279\u91cc\u5e0c\u65bd\u6cf0\u56e0\u4eb2\u738b"
    ],
    "wof:name":"Dietrichstein",
    "wof:placetype":"locality",
    "wof:population":5
},
  "geometry": {"coordinates":[14.12962,46.72698],"type":"Point"}
}