{
  "type": "Feature",
  "properties": {
    "gn:admin1_code":"2.0",
    "gn:admin2_code":"210",
    "gn:admin3_code":"21002.0",
    "gn:asciiname":"Dietrichstein",
    "gn:country_code":"AT",
    "gn:dem":651,
    "gn:feature_class":"P",
    "gn:feature_code":"PPL",
    "gn:name":"Dietrichstein",
    "gn:population":5,
    "gn:timezone":"Europe/Vienna",
    "iso:country":"AT",
    "wof:name":"Dietrichstein",
    "wof:placetype":"locality",
    "wof:population":5
},
  "geometry": {"coordinates":[14.12962,46.72698],"type":"Point"}
}