{
  "type": "Feature",
  "properties": {
    "gn:admin1_code":"4.0",
    "gn:admin2_code":"405",
    "gn:admin3_code":"40505.0",
    "gn:asciiname":"Linetshub",
    "gn:country_code":"AT",
    "gn:dem":496,
    "gn:feature_class":"P",
    "gn:feature_code":"PPL",
    "gn:name":"Linetshub",
    "gn:population":23,
    "gn:timezone":"Europe/Vienna",
    "iso:country":"AT",
    "wof:name":"Linetshub",
    "wof:placetype":"locality",
    "wof:population":23
},
  "geometry": {"coordinates":[13.89075,48.42242],"type":"Point"}
}