{
  "type": "Feature",
  "properties": {
    "gn:admin1_code":"6.0",
    "gn:admin2_code":"606",
    "gn:admin3_code":"60664.0",
    "gn:asciiname":"Greith",
    "gn:country_code":"AT",
    "gn:dem":474,
    "gn:feature_class":"P",
    "gn:feature_code":"PPL",
    "gn:name":"Greith",
    "gn:population":0,
    "gn:timezone":"Europe/Vienna",
    "iso:country":"AT",
    "wof:name":"Greith",
    "wof:placetype":"locality"
},
  "geometry": {"coordinates":[15.28333,47.11667],"type":"Point"}
}