{
  "type": "Feature",
  "properties": {
    "gn:country":"AT",
    "gn:fcode":"PPLA3",
    "gn:population":0,
    "iso:country":"AT",
    "name:ceb_x_preferred":[
        "Schmirn"
    ],
    "name:deu_x_preferred":[
        "Schmirn"
    ],
    "name:eng_x_preferred":[
        "Schmirn"
    ],
    "name:est_x_preferred":[
        "Schmirn"
    ],
    "name:fas_x_preferred":[
        "\u0627\u0634\u0645\u06cc\u0631\u0646"
    ],
    "name:fra_x_preferred":[
        "Schmirn"
    ],
    "name:hun_x_preferred":[
        "Schmirn"
    ],
    "name:ita_x_preferred":[
        "Schmirn"
    ],
    "name:kaz_x_preferred":[
        "\u0428\u043c\u0438\u0440\u043d"
    ],
    "name:lmo_x_preferred":[
        "Schmirn"
    ],
    "name:nld_x_preferred":[
        "Schmirn"
    ],
    "name:pol_x_preferred":[
        "Schmirn"
    ],
    "name:rus_x_preferred":[
        "\u0428\u043c\u0438\u0440\u043d"
    ],
    "name:slk_x_preferred":[
        "Schmirn"
    ],
    "name:spa_x_preferred":[
        "Schmirn"
    ],
    "name:swe_x_preferred":[
        "Schmirn"
    ],
    "name:ukr_x_preferred":[
        "\u0428\u043c\u0456\u0440\u043d"
    ],
    "name:uzb_x_preferred":[
        "Schmirn"
    ],
    "name:vol_x_preferred":[
        "Schmirn"
    ],
    "name:war_x_preferred":[
        "Schmirn"
    ],
    "name:zho_x_preferred":[
        "\u65bd\u7c73\u6069"
    ],
    "qs_pg:aaroncc":"AT",
    "qs_pg:gn_country":"AT",
    "qs_pg:gn_fcode":"PPLA3",
    "qs_pg:gn_pop":0,
    "qs_pg:name":"Schmirn",
    "qs_pg:name_adm0":"\u00d6sterreich",
    "qs_pg:name_adm1":"Tirol",
    "qs_pg:photos":9,
    "qs_pg:photos_1k":2,
    "qs_pg:photos_9k":1,
    "qs_pg:photos_9r":1,
    "qs_pg:photos_all":9,
    "qs_pg:photos_sr":1,
    "qs_pg:pop_sr":0,
    "qs_pg:qs_pg_placetype":"locality",
    "qs_pg:qs_pg_placetype_gp":"Town",
    "qs_pg:woe_adm0":23424750,
    "woe:adm0_id":23424750,
    "woe:name_adm0":"\u00d6sterreich",
    "woe:name_adm1":"Tirol",
    "woe:placetype":"Town",
    "wof:name":"Schmirn",
    "wof:placetype":"locality"
},
  "geometry": {"coordinates":[11.56667,47.08333],"type":"Point"}
}