{
  "type": "Feature",
  "properties": {
    "gn:admin1_code":"6.0",
    "gn:admin2_code":"603",
    "gn:admin3_code":"60346.0",
    "gn:asciiname":"Lebing",
    "gn:country_code":"AT",
    "gn:dem":314,
    "gn:feature_class":"P",
    "gn:feature_code":"PPL",
    "gn:name":"Lebing",
    "gn:population":199,
    "gn:timezone":"Europe/Vienna",
    "iso:country":"AT",
    "wof:name":"Lebing",
    "wof:placetype":"locality",
    "wof:population":199
},
  "geometry": {"coordinates":[15.29083,46.82306],"type":"Point"}
}