{
  "type": "Feature",
  "properties": {
    "gn:admin1_code":"4.0",
    "gn:admin2_code":"404",
    "gn:admin3_code":"40436.0",
    "gn:asciiname":"Obereck",
    "gn:country_code":"AT",
    "gn:dem":567,
    "gn:feature_class":"P",
    "gn:feature_code":"PPL",
    "gn:name":"Obereck",
    "gn:population":157,
    "gn:timezone":"Europe/Vienna",
    "iso:country":"AT",
    "wof:name":"Obereck",
    "wof:placetype":"locality",
    "wof:population":157
},
  "geometry": {"coordinates":[13.27663,48.13132],"type":"Point"}
}