{
  "type": "Feature",
  "properties": {
    "gn:admin1_code":"06",
    "gn:admin2_code":"623.0",
    "gn:admin3_code":"62378.0",
    "gn:asciiname":"Kloechigraben",
    "gn:country_code":"AT",
    "gn:dem":361,
    "gn:feature_class":"P",
    "gn:feature_code":"PPL",
    "gn:name":"Kl\u00f6chigraben",
    "gn:population":0,
    "gn:timezone":"Europe/Vienna",
    "iso:country":"AT",
    "wof:name":"Kloechigraben",
    "wof:placetype":"locality"
},
  "geometry": {"coordinates":[16.03333,46.96667],"type":"Point"}
}