{
  "type": "Feature",
  "properties": {
    "gn:admin1_code":"04",
    "gn:admin2_code":"418.0",
    "gn:admin3_code":"41804.0",
    "gn:asciiname":"Radlach",
    "gn:country_code":"AT",
    "gn:dem":358,
    "gn:feature_class":"P",
    "gn:feature_code":"PPL",
    "gn:name":"Radlach",
    "gn:population":81,
    "gn:timezone":"Europe/Vienna",
    "iso:country":"AT",
    "wof:name":"Radlach",
    "wof:placetype":"locality",
    "wof:population":81
},
  "geometry": {"coordinates":[14.00568,48.21421],"type":"Point"}
}