{
  "type": "Feature",
  "properties": {
    "iso:country":"AT",
    "name:ceb_x_preferred":[
        "Enzersdorf an der Fischa"
    ],
    "name:deu_x_preferred":[
        "Enzersdorf an der Fischa"
    ],
    "name:eng_x_preferred":[
        "Enzersdorf"
    ],
    "name:eng_x_variant":[
        "Enzersdorf an der Fischa"
    ],
    "name:epo_x_preferred":[
        "Enzersdorf an der Fischa"
    ],
    "name:fas_x_preferred":[
        "\u0622\u0646\u062a\u0633\u0631\u0633\u062f\u0648\u0631\u0641 \u0622\u0646\u062f\u0631 \u0641\u06cc\u0634\u0627"
    ],
    "name:fra_x_preferred":[
        "Enzersdorf an der Fischa"
    ],
    "name:hun_x_preferred":[
        "Enzersdorf an der Fischa"
    ],
    "name:ita_x_preferred":[
        "Enzersdorf an der Fischa"
    ],
    "name:kaz_x_preferred":[
        "\u042d\u043d\u0446\u0435\u0440\u0441\u0434\u043e\u0440\u0444-\u0430\u043d-\u0434\u0435\u0440-\u0424\u0438\u0448\u0430"
    ],
    "name:nld_x_preferred":[
        "Enzersdorf an der Fischa"
    ],
    "name:pol_x_preferred":[
        "Enzersdorf an der Fischa"
    ],
    "name:por_x_preferred":[
        "Enzersdorf an der Fischa"
    ],
    "name:rus_x_preferred":[
        "\u042d\u043d\u0446\u0435\u0440\u0441\u0434\u043e\u0440\u0444-\u0430\u043d-\u0434\u0435\u0440-\u0424\u0438\u0448\u0430"
    ],
    "name:slk_x_preferred":[
        "Enzersdorf an der Fischa"
    ],
    "name:spa_x_preferred":[
        "Enzersdorf an der Fischa"
    ],
    "name:swe_x_preferred":[
        "Enzersdorf an der Fischa"
    ],
    "name:uzb_x_preferred":[
        "Enzersdorf an der Fischa"
    ],
    "name:vie_x_preferred":[
        "Enzersdorf an der Fischa"
    ],
    "name:vol_x_preferred":[
        "Enzersdorf an der Fischa"
    ],
    "name:war_x_preferred":[
        "Enzersdorf an der Fischa"
    ],
    "name:zho_x_preferred":[
        "\u83f2\u6c99\u6cb3\u7554\u6069\u7b56\u5c14\u65af\u591a\u592b"
    ],
    "name:zho_x_variant":[
        "Enzersdorf an der Fischa"
    ],
    "qs:a0":"\u00d6sterreich",
    "qs:a1":"*Nieder\u00f6sterreich",
    "qs:a1r":"0",
    "qs:a2":"Bruck an der Leitha",
    "qs:adm0":"\u00d6sterreich",
    "qs:la_lc":"*",
    "qs:level":"locality",
    "qs:loc":"Enzersdorf an der Fischa",
    "qs:loc_alt":"Enzersdorf an der Fischa",
    "qs:pop":0,
    "qs:type":"buffered point",
    "wd:wordcount":51,
    "wof:lang":[
        "ger"
    ],
    "wof:name":"Enzersdorf an der Fischa",
    "wof:placetype":"locality"
},
  "geometry": {"coordinates":[16.614192,48.084],"type":"Point"}
}