{
  "type": "Feature",
  "properties": {
    "gn:admin1_code":"04",
    "gn:admin2_code":"418.0",
    "gn:admin3_code":"41824.0",
    "gn:asciiname":"Schimpelsberg",
    "gn:country_code":"AT",
    "gn:dem":336,
    "gn:feature_class":"P",
    "gn:feature_code":"PPL",
    "gn:name":"Schimpelsberg",
    "gn:population":277,
    "gn:timezone":"Europe/Vienna",
    "iso:country":"AT",
    "wof:name":"Schimpelsberg",
    "wof:placetype":"locality",
    "wof:population":277
},
  "geometry": {"coordinates":[14.1164,48.16053],"type":"Point"}
}