{
  "type": "Feature",
  "properties": {
    "gn:admin1_code":"8.0",
    "gn:admin2_code":"801",
    "gn:admin3_code":"80108.0",
    "gn:asciiname":"Ausserwald",
    "gn:cc2":"AT",
    "gn:country_code":"AT",
    "gn:dem":1088,
    "gn:feature_class":"P",
    "gn:feature_code":"PPL",
    "gn:name":"Ausserwald",
    "gn:population":0,
    "gn:timezone":"Europe/Vienna",
    "iso:country":"AT",
    "name:und_x_variant":[
        "Ausser Wald am Arlberg",
        "Ausserwald"
    ],
    "wof:name":"Ausserwald",
    "wof:placetype":"locality"
},
  "geometry": {"coordinates":[10.03333,47.13333],"type":"Point"}
}