{
  "type": "Feature",
  "properties": {
    "gn:admin1_code":"4.0",
    "gn:admin2_code":"412",
    "gn:admin3_code":"41231.0",
    "gn:asciiname":"Vicht",
    "gn:country_code":"AT",
    "gn:dem":503,
    "gn:feature_class":"P",
    "gn:feature_code":"PPL",
    "gn:name":"Vicht",
    "gn:population":0,
    "gn:timezone":"Europe/Vienna",
    "iso:country":"AT",
    "wof:name":"Vicht",
    "wof:placetype":"locality"
},
  "geometry": {"coordinates":[13.55786,48.28179],"type":"Point"}
}