{
  "type": "Feature",
  "properties": {
    "gn:admin1_code":"04",
    "gn:admin2_code":"404.0",
    "gn:admin3_code":"40435.0",
    "gn:asciiname":"Sankt Georgen am Fillmannsbach",
    "gn:country_code":"AT",
    "gn:dem":449,
    "gn:feature_class":"P",
    "gn:feature_code":"PPLA3",
    "gn:name":"Sankt Georgen am Fillmannsbach",
    "gn:population":96,
    "gn:timezone":"Europe/Vienna",
    "iso:country":"AT",
    "name:ceb_x_preferred":[
        "Sankt Georgen am Fillmannsbach"
    ],
    "name:deu_x_preferred":[
        "St. Georgen am Fillmannsbach"
    ],
    "name:fas_x_preferred":[
        "\u0632\u0627\u0646\u06a9\u062a \u06af\u0648\u0631\u06af\u0646 \u0627\u0645 \u0641\u06cc\u0644\u0645\u0627\u0646\u0633\u0628\u0627\u062e"
    ],
    "name:fra_x_preferred":[
        "Sankt Georgen am Fillmannsbach"
    ],
    "name:fur_x_preferred":[
        "Sankt Georgen am Fillmannsbach"
    ],
    "name:hun_x_preferred":[
        "Sankt Georgen am Fillmannsbach"
    ],
    "name:ita_x_preferred":[
        "Sankt Georgen am Fillmannsbach"
    ],
    "name:nld_x_preferred":[
        "Sankt Georgen am Fillmannsbach"
    ],
    "name:pol_x_preferred":[
        "St. Georgen am Fillmannsbach"
    ],
    "name:por_x_preferred":[
        "Sankt Georgen am Fillmannsbach"
    ],
    "name:slk_x_preferred":[
        "Sankt Georgen am Fillmannsbach"
    ],
    "name:spa_x_preferred":[
        "Sankt Georgen am Fillmannsbach"
    ],
    "name:swe_x_preferred":[
        "Sankt Georgen am Fillmannsbach"
    ],
    "name:und_x_variant":[
        "Sankt Georgen",
        "Sankt Georgen am Fillmannsbach"
    ],
    "name:uzb_x_preferred":[
        "Sankt Georgen am Fillmannsbach"
    ],
    "name:vie_x_preferred":[
        "Sankt Georgen am Fillmannsbach"
    ],
    "name:vol_x_preferred":[
        "Sankt Georgen am Fillmannsbach"
    ],
    "name:war_x_preferred":[
        "Sankt Georgen am Fillmannsbach"
    ],
    "wof:name":"Sankt Georgen am Fillmannsbach",
    "wof:placetype":"locality",
    "wof:population":96
},
  "geometry": {"coordinates":[13.00811,48.1256],"type":"Point"}
}