{
  "type": "Feature",
  "properties": {
    "gn:admin1_code":"03",
    "gn:admin2_code":"323.0",
    "gn:admin3_code":"32302.0",
    "gn:asciiname":"Wenigreith",
    "gn:country_code":"AT",
    "gn:dem":655,
    "gn:feature_class":"P",
    "gn:feature_code":"PPL",
    "gn:name":"Wenigreith",
    "gn:population":14,
    "gn:timezone":"Europe/Vienna",
    "iso:country":"AT",
    "wof:name":"Wenigreith",
    "wof:placetype":"locality",
    "wof:population":14
},
  "geometry": {"coordinates":[16.23333,47.46667],"type":"Point"}
}