{
  "type": "Feature",
  "properties": {
    "gn:country":"AT",
    "gn:fcode":"PPL",
    "gn:population":3121,
    "iso:country":"AT",
    "name:cat_x_preferred":[
        "St. Florian am Inn"
    ],
    "name:ceb_x_preferred":[
        "Sankt Florian am Inn"
    ],
    "name:cym_x_preferred":[
        "Sankt Florian am Inn"
    ],
    "name:deu_x_preferred":[
        "St. Florian am Inn"
    ],
    "name:eng_x_preferred":[
        "Sankt Florian am Inn"
    ],
    "name:epo_x_preferred":[
        "Sankt Florian am Inn"
    ],
    "name:fas_x_preferred":[
        "\u0632\u0627\u0646\u06a9\u062a \u0641\u0644\u0648\u0631\u06cc\u0627\u0646 \u0627\u0645\u200c\u0627\u06cc\u0646"
    ],
    "name:fra_x_preferred":[
        "Sankt Florian am Inn"
    ],
    "name:hun_x_preferred":[
        "Sankt Florian am Inn"
    ],
    "name:ita_x_preferred":[
        "Sankt Florian am Inn"
    ],
    "name:kaz_x_preferred":[
        "\u0421\u0430\u043d\u043a\u0442-\u0424\u043b\u043e\u0440\u0438\u0430\u043d-\u043d\u0430-\u0418\u043d\u043d\u0435"
    ],
    "name:lld_x_preferred":[
        "Sankt Florian am Inn"
    ],
    "name:nld_x_preferred":[
        "Sankt Florian am Inn"
    ],
    "name:nob_x_preferred":[
        "St. Florian am Inn"
    ],
    "name:pol_x_preferred":[
        "St. Florian am Inn"
    ],
    "name:por_x_preferred":[
        "Sankt Florian am Inn"
    ],
    "name:ron_x_preferred":[
        "Sankt Florian am Inn"
    ],
    "name:rus_x_preferred":[
        "\u0421\u0430\u043d\u043a\u0442-\u0424\u043b\u043e\u0440\u0438\u0430\u043d-\u0430\u043c-\u0418\u043d\u043d"
    ],
    "name:slk_x_preferred":[
        "Sankt Florian am Inn"
    ],
    "name:spa_x_preferred":[
        "Sankt Florian am Inn"
    ],
    "name:swe_x_preferred":[
        "Sankt Florian am Inn"
    ],
    "name:und_x_variant":[
        "Sankt Florian"
    ],
    "name:uzb_x_preferred":[
        "Sankt Florian am Inn"
    ],
    "name:vec_x_preferred":[
        "Sankt Florian am Inn"
    ],
    "name:vie_x_preferred":[
        "Sankt Florian am Inn"
    ],
    "name:vol_x_preferred":[
        "Sankt Florian am Inn"
    ],
    "name:war_x_preferred":[
        "Sankt Florian am Inn"
    ],
    "name:zho_x_preferred":[
        "\u56e0\u6cb3\u7554\u5723\u5f17\u6d1b\u91cc\u5b89"
    ],
    "qs_pg:aaroncc":"AT",
    "qs_pg:gn_country":"AT",
    "qs_pg:gn_fcode":"PPL",
    "qs_pg:gn_pop":3121,
    "qs_pg:name":"Sankt Florian am Inn",
    "qs_pg:photos_9r":0,
    "qs_pg:photos_sr":0,
    "qs_pg:pop_sr":4,
    "qs_pg:qs_pg_placetype":"locality",
    "wof:name":"Sankt Florian am Inn",
    "wof:placetype":"locality",
    "wof:population":3121
},
  "geometry": {"coordinates":[13.44263,48.44122],"type":"Point"}
}