{
  "type": "Feature",
  "properties": {
    "gn:admin1_code":"6.0",
    "gn:admin2_code":"621",
    "gn:admin3_code":"62138.0",
    "gn:asciiname":"Doerflach",
    "gn:country_code":"AT",
    "gn:dem":787,
    "gn:feature_class":"P",
    "gn:feature_code":"PPL",
    "gn:name":"D\u00f6rflach",
    "gn:population":200,
    "gn:timezone":"Europe/Vienna",
    "iso:country":"AT",
    "wof:name":"Doerflach",
    "wof:placetype":"locality",
    "wof:population":200
},
  "geometry": {"coordinates":[15.26611,47.55029],"type":"Point"}
}