{
  "type": "Feature",
  "properties": {
    "gn:admin1_code":"04",
    "gn:admin2_code":"413.0",
    "gn:admin3_code":"41322.0",
    "gn:asciiname":"Weikersdorf",
    "gn:cc2":"AT",
    "gn:country_code":"AT",
    "gn:dem":533,
    "gn:feature_class":"P",
    "gn:feature_code":"PPL",
    "gn:name":"Weikersdorf",
    "gn:population":78,
    "gn:timezone":"Europe/Vienna",
    "iso:country":"AT",
    "name:und_x_variant":[
        "Weikerstorf",
        "Weikersdorf"
    ],
    "wof:name":"Weikersdorf",
    "wof:placetype":"locality",
    "wof:population":78
},
  "geometry": {"coordinates":[13.88002,48.45499],"type":"Point"}
}