{
  "type": "Feature",
  "properties": {
    "gn:admin1_code":"6.0",
    "gn:admin2_code":"610",
    "gn:admin3_code":"61024.0",
    "gn:asciiname":"Unterhaag",
    "gn:country_code":"AT",
    "gn:dem":314,
    "gn:feature_class":"P",
    "gn:feature_code":"PPL",
    "gn:name":"Unterhaag",
    "gn:population":0,
    "gn:timezone":"Europe/Vienna",
    "iso:country":"AT",
    "wof:name":"Unterhaag",
    "wof:placetype":"locality"
},
  "geometry": {"coordinates":[15.35331,46.68648],"type":"Point"}
}