{
  "type": "Feature",
  "properties": {
    "gn:admin1_code":"07",
    "gn:admin2_code":"703.0",
    "gn:admin3_code":"70356.0",
    "gn:asciiname":"Ploeven",
    "gn:country_code":"AT",
    "gn:dem":1151,
    "gn:feature_class":"P",
    "gn:feature_code":"PPL",
    "gn:name":"Pl\u00f6ven",
    "gn:population":277,
    "gn:timezone":"Europe/Vienna",
    "iso:country":"AT",
    "wof:name":"Ploeven",
    "wof:placetype":"locality",
    "wof:population":277
},
  "geometry": {"coordinates":[11.35,47.16667],"type":"Point"}
}