{
  "type": "Feature",
  "properties": {
    "gn:admin1_code":"4.0",
    "gn:admin2_code":"405",
    "gn:admin3_code":"40505.0",
    "gn:asciiname":"Starz",
    "gn:country_code":"AT",
    "gn:dem":514,
    "gn:feature_class":"P",
    "gn:feature_code":"PPL",
    "gn:name":"Starz",
    "gn:population":4,
    "gn:timezone":"Europe/Vienna",
    "iso:country":"AT",
    "name:ara_x_preferred":[
        "\u0633\u062a\u0627\u0631\u0632"
    ],
    "name:aze_x_preferred":[
        "Starz"
    ],
    "name:deu_x_preferred":[
        "Starz"
    ],
    "name:fas_x_preferred":[
        "\u0627\u0633\u062a\u0627\u0631\u0632"
    ],
    "name:fra_x_preferred":[
        "Starz"
    ],
    "name:heb_x_preferred":[
        "Starz"
    ],
    "name:hye_x_preferred":[
        "Starz"
    ],
    "name:ita_x_preferred":[
        "Starz"
    ],
    "name:jpn_x_preferred":[
        "Starz"
    ],
    "name:kor_x_preferred":[
        "\uc2a4\ud0c0\uc988"
    ],
    "name:lmo_x_preferred":[
        "Starz"
    ],
    "name:pol_x_preferred":[
        "Starz"
    ],
    "name:por_x_preferred":[
        "Starz"
    ],
    "name:rus_x_preferred":[
        "Starz"
    ],
    "name:spa_x_preferred":[
        "Starz"
    ],
    "name:swe_x_preferred":[
        "Starz"
    ],
    "name:tur_x_preferred":[
        "Starz"
    ],
    "name:zho_x_preferred":[
        "Starz"
    ],
    "wof:name":"Starz",
    "wof:placetype":"locality",
    "wof:population":4
},
  "geometry": {"coordinates":[13.90908,48.43732],"type":"Point"}
}