{
  "type": "Feature",
  "properties": {
    "gn:admin1_code":"7.0",
    "gn:admin2_code":"707",
    "gn:admin3_code":"70723.0",
    "gn:asciiname":"Oberbichl",
    "gn:country_code":"AT",
    "gn:dem":1354,
    "gn:feature_class":"P",
    "gn:feature_code":"PPL",
    "gn:name":"Oberbichl",
    "gn:population":0,
    "gn:timezone":"Europe/Vienna",
    "iso:country":"AT",
    "wof:name":"Oberbichl",
    "wof:placetype":"locality"
},
  "geometry": {"coordinates":[12.36667,47.01667],"type":"Point"}
}