{
  "type": "Feature",
  "properties": {
    "gn:admin1_code":"3.0",
    "gn:admin2_code":"320",
    "gn:admin3_code":"32014.0",
    "gn:asciiname":"Knolling",
    "gn:country_code":"AT",
    "gn:dem":321,
    "gn:feature_class":"P",
    "gn:feature_code":"PPL",
    "gn:name":"Knolling",
    "gn:population":131,
    "gn:timezone":"Europe/Vienna",
    "iso:country":"AT",
    "wof:name":"Knolling",
    "wof:placetype":"locality",
    "wof:population":131
},
  "geometry": {"coordinates":[15.05,48.08333],"type":"Point"}
}