{
  "type": "Feature",
  "properties": {
    "gn:admin1_code":"3.0",
    "gn:admin2_code":"305",
    "gn:admin3_code":"30532.0",
    "gn:asciiname":"Bubendorf",
    "gn:country_code":"AT",
    "gn:dem":319,
    "gn:feature_class":"P",
    "gn:feature_code":"PPL",
    "gn:name":"Bubendorf",
    "gn:population":0,
    "gn:timezone":"Europe/Vienna",
    "iso:country":"AT",
    "wof:name":"Bubendorf",
    "wof:placetype":"locality"
},
  "geometry": {"coordinates":[14.65,48.05],"type":"Point"}
}