{
  "type": "Feature",
  "properties": {
    "gn:admin1_code":"3.0",
    "gn:admin2_code":"305",
    "gn:admin3_code":"30532.0",
    "gn:asciiname":"Bubendorf",
    "gn:country_code":"AT",
    "gn:dem":319,
    "gn:feature_class":"P",
    "gn:feature_code":"PPL",
    "gn:name":"Bubendorf",
    "gn:population":0,
    "gn:timezone":"Europe/Vienna",
    "iso:country":"AT",
    "name:als_x_preferred":[
        "Bubendorf"
    ],
    "name:ast_x_preferred":[
        "Bubendorf"
    ],
    "name:ceb_x_preferred":[
        "Bubendorf"
    ],
    "name:deu_x_preferred":[
        "Bubendorf"
    ],
    "name:epo_x_preferred":[
        "Bubendorf"
    ],
    "name:eus_x_preferred":[
        "Bubendorf"
    ],
    "name:fra_x_preferred":[
        "Bubendorf"
    ],
    "name:ita_x_preferred":[
        "Bubendorf"
    ],
    "name:kaz_x_preferred":[
        "\u0411\u0443\u0431\u0435\u043d\u0434\u043e\u0440\u0444"
    ],
    "name:lmo_x_preferred":[
        "Bubendorf"
    ],
    "name:msa_x_preferred":[
        "Bubendorf"
    ],
    "name:nld_x_preferred":[
        "Bubendorf"
    ],
    "name:nno_x_preferred":[
        "Bubendorf"
    ],
    "name:pms_x_preferred":[
        "Bubendorf"
    ],
    "name:por_x_preferred":[
        "Bubendorf"
    ],
    "name:rus_x_preferred":[
        "\u0411\u0443\u0431\u0435\u043d\u0434\u043e\u0440\u0444"
    ],
    "name:spa_x_preferred":[
        "Bubendorf"
    ],
    "name:sqi_x_preferred":[
        "Bubendorf"
    ],
    "name:swe_x_preferred":[
        "Bubendorf"
    ],
    "name:uzb_x_preferred":[
        "Bubendorf"
    ],
    "name:vol_x_preferred":[
        "Bubendorf"
    ],
    "name:war_x_preferred":[
        "Bubendorf"
    ],
    "name:zho_x_preferred":[
        "\u5e03\u672c\u591a\u592b"
    ],
    "wof:name":"Bubendorf",
    "wof:placetype":"locality"
},
  "geometry": {"coordinates":[14.65,48.05],"type":"Point"}
}