{
  "type": "Feature",
  "properties": {
    "gn:admin1_code":"04",
    "gn:admin2_code":"411.0",
    "gn:admin3_code":"41110.0",
    "gn:asciiname":"Statzing",
    "gn:country_code":"AT",
    "gn:dem":295,
    "gn:feature_class":"P",
    "gn:feature_code":"PPL",
    "gn:name":"Statzing",
    "gn:population":612,
    "gn:timezone":"Europe/Vienna",
    "iso:country":"AT",
    "wof:name":"Statzing",
    "wof:placetype":"locality",
    "wof:population":612
},
  "geometry": {"coordinates":[14.4296,48.27485],"type":"Point"}
}