{
  "type": "Feature",
  "properties": {
    "gn:admin1_code":"02",
    "gn:admin2_code":"204.0",
    "gn:admin3_code":"20428.0",
    "gn:asciiname":"Sankt Margareten im Rosental",
    "gn:country_code":"AT",
    "gn:dem":570,
    "gn:feature_class":"P",
    "gn:feature_code":"PPLA3",
    "gn:name":"Sankt Margareten im Rosental",
    "gn:population":268,
    "gn:timezone":"Europe/Vienna",
    "iso:country":"AT",
    "name:rus_x_preferred":[
        "\u0421\u0430\u043d\u043a\u0442-\u041c\u0430\u0440\u0433\u0430\u0440\u0435\u0442\u0435\u043d (\u0420\u043e\u0437\u0435\u043d\u0442\u0430\u043b\u044c)"
    ],
    "name:und_x_variant":[
        "Sankt Margarethen im Rosenthale",
        "Sankt Margarethen",
        "Sankt Margarethen im Rosental",
        "Sankt Margareten im Rosental"
    ],
    "wof:name":"Sankt Margareten im Rosental",
    "wof:placetype":"locality",
    "wof:population":268
},
  "geometry": {"coordinates":[14.42444,46.54417],"type":"Point"}
}