{
  "type": "Feature",
  "properties": {
    "gn:admin1_code":"02",
    "gn:admin2_code":"204.0",
    "gn:admin3_code":"20428.0",
    "gn:asciiname":"Sankt Margareten im Rosental",
    "gn:country_code":"AT",
    "gn:dem":570,
    "gn:feature_class":"P",
    "gn:feature_code":"PPLA3",
    "gn:name":"Sankt Margareten im Rosental",
    "gn:population":268,
    "gn:timezone":"Europe/Vienna",
    "iso:country":"AT",
    "name:ceb_x_preferred":[
        "Sankt Margareten im Rosental"
    ],
    "name:deu_x_preferred":[
        "Sankt Margareten im Rosental"
    ],
    "name:epo_x_preferred":[
        "Sankt Margareten im Rosental"
    ],
    "name:fas_x_preferred":[
        "\u0632\u0627\u0646\u06a9\u062a \u0645\u0627\u0631\u06af\u0627\u0631\u062a\u0646 \u0627\u06cc\u0645 \u0631\u0648\u0632\u0646\u062a\u0627\u0644"
    ],
    "name:fra_x_preferred":[
        "Sankt Margareten im Rosental"
    ],
    "name:fur_x_preferred":[
        "Sankt Margareten im Rosental"
    ],
    "name:hun_x_preferred":[
        "Sankt Margareten im Rosental"
    ],
    "name:ita_x_preferred":[
        "Sankt Margareten im Rosental"
    ],
    "name:nld_x_preferred":[
        "Sankt Margareten im Rosental"
    ],
    "name:pol_x_preferred":[
        "St. Margareten im Rosental"
    ],
    "name:por_x_preferred":[
        "Sankt Margareten im Rosental"
    ],
    "name:rus_x_preferred":[
        "\u0421\u0430\u043d\u043a\u0442-\u041c\u0430\u0440\u0433\u0430\u0440\u0435\u0442\u0435\u043d (\u0420\u043e\u0437\u0435\u043d\u0442\u0430\u043b\u044c)"
    ],
    "name:slk_x_preferred":[
        "St. Margareten im Rosental"
    ],
    "name:slv_x_preferred":[
        "\u0160marjeta v Ro\u017eu"
    ],
    "name:spa_x_preferred":[
        "St. Margareten im Rosental"
    ],
    "name:swe_x_preferred":[
        "Sankt Margareten im Rosental"
    ],
    "name:und_x_variant":[
        "Sankt Margarethen im Rosenthale",
        "Sankt Margarethen",
        "Sankt Margarethen im Rosental",
        "Sankt Margareten im Rosental"
    ],
    "name:uzb_x_preferred":[
        "Sankt Margareten im Rosental"
    ],
    "name:vol_x_preferred":[
        "Sankt Margareten im Rosental"
    ],
    "name:war_x_preferred":[
        "Sankt Margareten im Rosental"
    ],
    "wof:name":"Sankt Margareten im Rosental",
    "wof:placetype":"locality",
    "wof:population":268
},
  "geometry": {"coordinates":[14.42444,46.54417],"type":"Point"}
}