{
  "type": "Feature",
  "properties": {
    "gn:admin1_code":"4.0",
    "gn:admin2_code":"414",
    "gn:admin3_code":"41406.0",
    "gn:asciiname":"Edenaichet",
    "gn:country_code":"AT",
    "gn:dem":410,
    "gn:feature_class":"P",
    "gn:feature_code":"PPL",
    "gn:name":"Edenaichet",
    "gn:population":173,
    "gn:timezone":"Europe/Vienna",
    "iso:country":"AT",
    "wof:name":"Edenaichet",
    "wof:placetype":"locality",
    "wof:population":173
},
  "geometry": {"coordinates":[13.47018,48.33857],"type":"Point"}
}