{
  "type": "Feature",
  "properties": {
    "gn:admin1_code":"07",
    "gn:admin2_code":"707.0",
    "gn:admin3_code":"70717.0",
    "gn:asciiname":"Prossegg",
    "gn:country_code":"AT",
    "gn:dem":990,
    "gn:feature_class":"P",
    "gn:feature_code":"PPL",
    "gn:name":"Prossegg",
    "gn:population":0,
    "gn:timezone":"Europe/Vienna",
    "iso:country":"AT",
    "wof:name":"Prossegg",
    "wof:placetype":"locality"
},
  "geometry": {"coordinates":[12.53333,47.01667],"type":"Point"}
}