{
  "type": "Feature",
  "properties": {
    "gn:admin1_code":"4.0",
    "gn:admin2_code":"417",
    "gn:admin3_code":"41702.0",
    "gn:asciiname":"Winterleithen",
    "gn:country_code":"AT",
    "gn:dem":583,
    "gn:feature_class":"P",
    "gn:feature_code":"PPL",
    "gn:name":"Winterleithen",
    "gn:population":0,
    "gn:timezone":"Europe/Vienna",
    "iso:country":"AT",
    "wof:name":"Winterleithen",
    "wof:placetype":"locality"
},
  "geometry": {"coordinates":[13.51009,47.89776],"type":"Point"}
}