{
  "type": "Feature",
  "properties": {
    "gn:country":"AT",
    "gn:fcode":"PPL",
    "gn:population":0,
    "iso:country":"AT",
    "qs_pg:aaroncc":"AT",
    "qs_pg:gn_country":"AT",
    "qs_pg:gn_fcode":"PPL",
    "qs_pg:gn_pop":0,
    "qs_pg:name":"Umlberg",
    "qs_pg:name_adm0":"\u00d6sterreich",
    "qs_pg:name_adm1":"Tirol",
    "qs_pg:photos":55,
    "qs_pg:photos_1k":11,
    "qs_pg:photos_9k":1,
    "qs_pg:photos_9r":2,
    "qs_pg:photos_all":55,
    "qs_pg:photos_sr":2,
    "qs_pg:pop_sr":0,
    "qs_pg:qs_pg_placetype":"locality",
    "qs_pg:qs_pg_placetype_gp":"Town",
    "qs_pg:woe_adm0":23424750,
    "woe:adm0_id":23424750,
    "woe:name_adm0":"\u00d6sterreich",
    "woe:name_adm1":"Tirol",
    "woe:placetype":"Town",
    "wof:name":"Umlberg",
    "wof:placetype":"locality"
},
  "geometry": {"coordinates":[11.63333,47.33333],"type":"Point"}
}