{
  "type": "Feature",
  "properties": {
    "gn:admin1_code":"4.0",
    "gn:admin2_code":"408",
    "gn:admin3_code":"40828.0",
    "gn:asciiname":"Untwuesten",
    "gn:country_code":"AT",
    "gn:dem":416,
    "gn:feature_class":"P",
    "gn:feature_code":"PPL",
    "gn:name":"Untw\u00fcsten",
    "gn:population":20,
    "gn:timezone":"Europe/Vienna",
    "iso:country":"AT",
    "wof:name":"Untwuesten",
    "wof:placetype":"locality",
    "wof:population":20
},
  "geometry": {"coordinates":[13.73373,48.3524],"type":"Point"}
}