{
  "type": "Feature",
  "properties": {
    "gn:admin1_code":"05",
    "gn:admin2_code":"504.0",
    "gn:admin3_code":"50413.0",
    "gn:asciiname":"Wolfau",
    "gn:country_code":"AT",
    "gn:dem":1096,
    "gn:feature_class":"P",
    "gn:feature_code":"PPL",
    "gn:name":"Wolfau",
    "gn:population":0,
    "gn:timezone":"Europe/Vienna",
    "iso:country":"AT",
    "name:ceb_x_preferred":[
        "Wolfau"
    ],
    "name:ces_x_preferred":[
        "Wolfau"
    ],
    "name:deu_x_preferred":[
        "Wolfau"
    ],
    "name:epo_x_preferred":[
        "Wolfau"
    ],
    "name:fas_x_preferred":[
        "\u0648\u0644\u0641\u0648"
    ],
    "name:fra_x_preferred":[
        "Wolfau"
    ],
    "name:hun_x_preferred":[
        "Vasfarkasfalva"
    ],
    "name:ita_x_preferred":[
        "Wolfau"
    ],
    "name:kaz_x_preferred":[
        "\u0412\u043e\u043b\u044c\u0444\u0430\u0443"
    ],
    "name:nld_x_preferred":[
        "Wolfau"
    ],
    "name:pol_x_preferred":[
        "Wolfau"
    ],
    "name:por_x_preferred":[
        "Wolfau"
    ],
    "name:rus_x_preferred":[
        "\u0412\u043e\u043b\u044c\u0444\u0430\u0443"
    ],
    "name:slk_x_preferred":[
        "Wolfau"
    ],
    "name:spa_x_preferred":[
        "Wolfau"
    ],
    "name:swe_x_preferred":[
        "Wolfau"
    ],
    "name:ukr_x_preferred":[
        "\u0412\u043e\u043b\u044c\u0444\u0430\u0443"
    ],
    "name:uzb_x_preferred":[
        "Wolfau"
    ],
    "name:vol_x_preferred":[
        "Wolfau"
    ],
    "name:war_x_preferred":[
        "Wolfau"
    ],
    "name:zho_x_preferred":[
        "\u6c83\u5c14\u798f"
    ],
    "wof:name":"Wolfau",
    "wof:placetype":"locality"
},
  "geometry": {"coordinates":[13.25,47.16667],"type":"Point"}
}