{
  "type": "Feature",
  "properties": {
    "gn:admin1_code":"05",
    "gn:admin2_code":"504.0",
    "gn:admin3_code":"50413.0",
    "gn:asciiname":"Wolfau",
    "gn:country_code":"AT",
    "gn:dem":1096,
    "gn:feature_class":"P",
    "gn:feature_code":"PPL",
    "gn:name":"Wolfau",
    "gn:population":0,
    "gn:timezone":"Europe/Vienna",
    "iso:country":"AT",
    "wof:name":"Wolfau",
    "wof:placetype":"locality"
},
  "geometry": {"coordinates":[13.25,47.16667],"type":"Point"}
}