{
  "type": "Feature",
  "properties": {
    "gn:admin1_code":"4.0",
    "gn:admin2_code":"408",
    "gn:admin3_code":"40821.0",
    "gn:asciiname":"Aigen",
    "gn:country_code":"AT",
    "gn:dem":383,
    "gn:feature_class":"P",
    "gn:feature_code":"PPL",
    "gn:name":"Aigen",
    "gn:population":96,
    "gn:timezone":"Europe/Vienna",
    "iso:country":"AT",
    "name:deu_x_preferred":[
        "Aigen"
    ],
    "name:fra_x_preferred":[
        "Aigen"
    ],
    "name:ita_x_preferred":[
        "Aigen"
    ],
    "name:pol_x_preferred":[
        "Aigen"
    ],
    "name:rus_x_preferred":[
        "\u0410\u0439\u0433\u0435\u043d"
    ],
    "wof:name":"Aigen",
    "wof:placetype":"locality",
    "wof:population":96
},
  "geometry": {"coordinates":[13.86698,48.26377],"type":"Point"}
}