{
  "type": "Feature",
  "properties": {
    "gn:admin1_code":"4.0",
    "gn:admin2_code":"409",
    "gn:admin3_code":"40907.0",
    "gn:asciiname":"Guntendorf",
    "gn:country_code":"AT",
    "gn:dem":450,
    "gn:feature_class":"P",
    "gn:feature_code":"PPL",
    "gn:name":"Guntendorf",
    "gn:population":0,
    "gn:timezone":"Europe/Vienna",
    "iso:country":"AT",
    "wof:name":"Guntendorf",
    "wof:placetype":"locality"
},
  "geometry": {"coordinates":[14.13333,48.03333],"type":"Point"}
}