{
  "type": "Feature",
  "properties": {
    "gn:admin1_code":"6.0",
    "gn:admin2_code":"622",
    "gn:admin3_code":"62266.0",
    "gn:asciiname":"Maieregg",
    "gn:country_code":"AT",
    "gn:dem":401,
    "gn:feature_class":"P",
    "gn:feature_code":"PPL",
    "gn:name":"Maieregg",
    "gn:population":0,
    "gn:timezone":"Europe/Vienna",
    "iso:country":"AT",
    "wof:name":"Maieregg",
    "wof:placetype":"locality"
},
  "geometry": {"coordinates":[15.88333,47.18333],"type":"Point"}
}