{
  "type": "Feature",
  "properties": {
    "gn:admin1_code":"4.0",
    "gn:admin2_code":"408",
    "gn:admin3_code":"40819.0",
    "gn:asciiname":"Spielmannsberg",
    "gn:country_code":"AT",
    "gn:dem":502,
    "gn:feature_class":"P",
    "gn:feature_code":"PPL",
    "gn:name":"Spielmannsberg",
    "gn:population":0,
    "gn:timezone":"Europe/Vienna",
    "iso:country":"AT",
    "wof:name":"Spielmannsberg",
    "wof:placetype":"locality"
},
  "geometry": {"coordinates":[13.77643,48.36634],"type":"Point"}
}