{
  "type": "Feature",
  "properties": {
    "gn:admin1_code":"4.0",
    "gn:admin2_code":"412",
    "gn:admin3_code":"41214.0",
    "gn:asciiname":"Langdorf",
    "gn:country_code":"AT",
    "gn:dem":428,
    "gn:feature_class":"P",
    "gn:feature_code":"PPL",
    "gn:name":"Langdorf",
    "gn:population":72,
    "gn:timezone":"Europe/Vienna",
    "iso:country":"AT",
    "wof:name":"Langdorf",
    "wof:placetype":"locality",
    "wof:population":72
},
  "geometry": {"coordinates":[13.40195,48.22427],"type":"Point"}
}