{
  "type": "Feature",
  "properties": {
    "gn:admin1_code":"4.0",
    "gn:admin2_code":"405",
    "gn:admin3_code":"40508.0",
    "gn:asciiname":"Oberdoppl",
    "gn:country_code":"AT",
    "gn:dem":381,
    "gn:feature_class":"P",
    "gn:feature_code":"PPL",
    "gn:name":"Oberdoppl",
    "gn:population":24,
    "gn:timezone":"Europe/Vienna",
    "iso:country":"AT",
    "wof:name":"Oberdoppl",
    "wof:placetype":"locality",
    "wof:population":24
},
  "geometry": {"coordinates":[13.91187,48.3005],"type":"Point"}
}