{
  "type": "Feature",
  "properties": {
    "gn:admin1_code":"2.0",
    "gn:admin2_code":"209",
    "gn:admin3_code":"20911.0",
    "gn:asciiname":"Oberauerling",
    "gn:country_code":"AT",
    "gn:dem":1123,
    "gn:feature_class":"P",
    "gn:feature_code":"PPL",
    "gn:name":"Oberauerling",
    "gn:population":55,
    "gn:timezone":"Europe/Vienna",
    "iso:country":"AT",
    "wof:name":"Oberauerling",
    "wof:placetype":"locality",
    "wof:population":55
},
  "geometry": {"coordinates":[14.95,46.96667],"type":"Point"}
}