{
  "type": "Feature",
  "properties": {
    "gn:admin1_code":"4.0",
    "gn:admin2_code":"414",
    "gn:admin3_code":"41424.0",
    "gn:asciiname":"Grubmuehle",
    "gn:country_code":"AT",
    "gn:dem":339,
    "gn:feature_class":"P",
    "gn:feature_code":"PPL",
    "gn:name":"Grubm\u00fchle",
    "gn:population":0,
    "gn:timezone":"Europe/Vienna",
    "iso:country":"AT",
    "wof:name":"Grubmuehle",
    "wof:placetype":"locality"
},
  "geometry": {"coordinates":[13.58249,48.39818],"type":"Point"}
}