{
  "type": "Feature",
  "properties": {
    "gn:admin1_code":"6.0",
    "gn:admin2_code":"614",
    "gn:admin3_code":"61445.0",
    "gn:asciiname":"Predlitzwinkel",
    "gn:country_code":"AT",
    "gn:dem":1377,
    "gn:feature_class":"P",
    "gn:feature_code":"PPLL",
    "gn:name":"Predlitzwinkel",
    "gn:population":0,
    "gn:timezone":"Europe/Vienna",
    "iso:country":"AT",
    "wof:name":"Predlitzwinkel",
    "wof:placetype":"locality"
},
  "geometry": {"coordinates":[13.89194,47.02917],"type":"Point"}
}