{
  "type": "Feature",
  "properties": {
    "iso:country":"AT",
    "name:deu_x_preferred":[
        "Krottendorf"
    ],
    "name:eng_x_preferred":[
        "Krottendorf"
    ],
    "wof:name":"Krottendorf",
    "wof:placetype":"neighbourhood"
},
  "geometry": {"coordinates":[15.39692331340483,47.04885654694899],"type":"Point"}
}