{
  "type": "Feature",
  "properties": {
    "gn:admin1_code":"4.0",
    "gn:admin2_code":"412",
    "gn:admin3_code":"41209.0",
    "gn:asciiname":"Obermauer",
    "gn:country_code":"AT",
    "gn:dem":467,
    "gn:feature_class":"P",
    "gn:feature_code":"PPL",
    "gn:name":"Obermauer",
    "gn:population":14,
    "gn:timezone":"Europe/Vienna",
    "iso:country":"AT",
    "wof:name":"Obermauer",
    "wof:placetype":"locality",
    "wof:population":14
},
  "geometry": {"coordinates":[13.57635,48.2241],"type":"Point"}
}