{
  "type": "Feature",
  "properties": {
    "gn:admin1_code":"3.0",
    "gn:admin2_code":"323",
    "gn:admin3_code":"32315.0",
    "gn:asciiname":"Buchegg",
    "gn:country_code":"AT",
    "gn:dem":595,
    "gn:feature_class":"P",
    "gn:feature_code":"PPL",
    "gn:name":"Buchegg",
    "gn:population":0,
    "gn:timezone":"Europe/Vienna",
    "iso:country":"AT",
    "wof:name":"Buchegg",
    "wof:placetype":"locality"
},
  "geometry": {"coordinates":[16.21667,47.48333],"type":"Point"}
}