{
  "type": "Feature",
  "properties": {
    "gn:admin1_code":"07",
    "gn:admin2_code":"705.0",
    "gn:admin3_code":"70529.0",
    "gn:asciiname":"Oed",
    "gn:country_code":"AT",
    "gn:dem":765,
    "gn:feature_class":"P",
    "gn:feature_code":"PPL",
    "gn:name":"Oed",
    "gn:population":234,
    "gn:timezone":"Europe/Vienna",
    "iso:country":"AT",
    "wof:name":"Oed",
    "wof:placetype":"locality",
    "wof:population":234
},
  "geometry": {"coordinates":[12.31667,47.63333],"type":"Point"}
}