{
  "type": "Feature",
  "properties": {
    "gn:admin1_code":"2.0",
    "gn:admin2_code":"206",
    "gn:admin3_code":"20636.0",
    "gn:asciiname":"Latzendorf",
    "gn:country_code":"AT",
    "gn:dem":795,
    "gn:feature_class":"P",
    "gn:feature_code":"PPL",
    "gn:name":"Latzendorf",
    "gn:population":170,
    "gn:timezone":"Europe/Vienna",
    "iso:country":"AT",
    "wof:name":"Latzendorf",
    "wof:placetype":"locality",
    "wof:population":170
},
  "geometry": {"coordinates":[13.01528,46.88028],"type":"Point"}
}