{
  "type": "Feature",
  "properties": {
    "gn:admin1_code":"2.0",
    "gn:admin2_code":"201",
    "gn:admin3_code":"20101.0",
    "gn:asciiname":"Karnberg",
    "gn:country_code":"AT",
    "gn:dem":636,
    "gn:feature_class":"P",
    "gn:feature_code":"PPL",
    "gn:name":"Karnberg",
    "gn:population":0,
    "gn:timezone":"Europe/Vienna",
    "iso:country":"AT",
    "wof:name":"Karnberg",
    "wof:placetype":"locality"
},
  "geometry": {"coordinates":[14.2909,46.71168],"type":"Point"}
}