{
  "type": "Feature",
  "properties": {
    "gn:admin1_code":"3.0",
    "gn:admin2_code":"308",
    "gn:admin3_code":"30859.0",
    "gn:asciiname":"Velm",
    "gn:country_code":"AT",
    "gn:dem":164,
    "gn:feature_class":"P",
    "gn:feature_code":"PPL",
    "gn:name":"Velm",
    "gn:population":280,
    "gn:timezone":"Europe/Vienna",
    "iso:country":"AT",
    "name:ceb_x_preferred":[
        "Velm"
    ],
    "name:fra_x_preferred":[
        "Velm"
    ],
    "name:lim_x_preferred":[
        "Vallem"
    ],
    "name:nld_x_preferred":[
        "Velm"
    ],
    "name:swe_x_preferred":[
        "Velm"
    ],
    "wof:name":"Velm",
    "wof:placetype":"locality",
    "wof:population":280
},
  "geometry": {"coordinates":[16.78056,48.46694],"type":"Point"}
}