{
  "type": "Feature",
  "properties": {
    "iso:country":"AT",
    "name:cat_x_preferred":[
        "Furth"
    ],
    "name:ceb_x_preferred":[
        "Furth"
    ],
    "name:deu_x_preferred":[
        "Furth"
    ],
    "name:epo_x_preferred":[
        "Furth"
    ],
    "name:fra_x_preferred":[
        "Furth"
    ],
    "name:ita_x_preferred":[
        "Furth"
    ],
    "name:nld_x_preferred":[
        "Furth"
    ],
    "name:pol_x_preferred":[
        "Furth"
    ],
    "name:rus_x_preferred":[
        "\u0424\u0443\u0440\u0442"
    ],
    "name:srp_x_preferred":[
        "\u0424\u0443\u0440\u0442"
    ],
    "name:swe_x_preferred":[
        "Furth"
    ],
    "name:zho_x_preferred":[
        "\u5bcc\u5c14\u7279"
    ],
    "qs:gn_fcode":"PPLX",
    "qs:gn_local":0,
    "qs:gn_nam_loc":"Linz, Linz Stadt, Ober\u00f6sterreich, AT",
    "qs:gn_namadm1":"04",
    "qs:gn_name":"Furth",
    "qs:local_max":22933,
    "qs:local_sum":38224,
    "qs:localhoods":15,
    "qs:name":"Furth",
    "qs:name_adm0":"\u00d6sterreich",
    "qs:name_adm1":"Ober\u00f6sterreich",
    "qs:name_adm2":"Linz Stadt",
    "qs:name_lau":"Linz",
    "qs:name_local":"Linz",
    "qs:photo_max":375,
    "qs:photo_sum":1508,
    "qs:placetype":"Suburb",
    "qs:quad_count":41,
    "qs:woe_adm0":23424750,
    "qs:woe_adm1":2344711,
    "qs:woe_adm2":12591722,
    "qs:woe_lau":12674377,
    "qs:woe_local":12674377,
    "qs:woe_ver":"7.10.0",
    "wof:lang":[
        "ger"
    ],
    "wof:name":"Furth",
    "wof:placetype":"neighbourhood"
},
  "geometry": {"coordinates":[14.316725,48.332974],"type":"Point"}
}