{
  "type": "Feature",
  "properties": {
    "gn:admin1_code":"04",
    "gn:admin2_code":"413.0",
    "gn:admin3_code":"41334.0",
    "gn:asciiname":"Uttendorf",
    "gn:country_code":"AT",
    "gn:dem":633,
    "gn:feature_class":"P",
    "gn:feature_code":"PPL",
    "gn:name":"Uttendorf",
    "gn:population":42,
    "gn:timezone":"Europe/Vienna",
    "iso:country":"AT",
    "wof:name":"Uttendorf",
    "wof:placetype":"locality",
    "wof:population":42
},
  "geometry": {"coordinates":[14.11563,48.52814],"type":"Point"}
}