{
  "type": "Feature",
  "properties": {
    "gn:admin1_code":"04",
    "gn:admin2_code":"413.0",
    "gn:admin3_code":"41334.0",
    "gn:asciiname":"Uttendorf",
    "gn:country_code":"AT",
    "gn:dem":633,
    "gn:feature_class":"P",
    "gn:feature_code":"PPL",
    "gn:name":"Uttendorf",
    "gn:population":42,
    "gn:timezone":"Europe/Vienna",
    "iso:country":"AT",
    "name:bar_x_preferred":[
        "Uatndorf"
    ],
    "name:ceb_x_preferred":[
        "Uttendorf"
    ],
    "name:deu_x_preferred":[
        "Uttendorf"
    ],
    "name:epo_x_preferred":[
        "Uttendorf"
    ],
    "name:fas_x_preferred":[
        "\u0627\u0648\u062a\u0646\u062f\u0648\u0631\u0641"
    ],
    "name:fra_x_preferred":[
        "Uttendorf"
    ],
    "name:hun_x_preferred":[
        "Uttendorf"
    ],
    "name:ita_x_preferred":[
        "Uttendorf"
    ],
    "name:kaz_x_preferred":[
        "\u0423\u0442\u0442\u0435\u043d\u0434\u043e\u0440\u0444"
    ],
    "name:nld_x_preferred":[
        "Uttendorf"
    ],
    "name:nno_x_preferred":[
        "Uttendorf"
    ],
    "name:pol_x_preferred":[
        "Uttendorf"
    ],
    "name:rus_x_preferred":[
        "\u0423\u0442\u0442\u0435\u043d\u0434\u043e\u0440\u0444"
    ],
    "name:slk_x_preferred":[
        "Uttendorf"
    ],
    "name:spa_x_preferred":[
        "Uttendorf"
    ],
    "name:swe_x_preferred":[
        "Uttendorf"
    ],
    "name:ukr_x_preferred":[
        "\u0423\u0442\u0442\u0435\u043d\u0434\u043e\u0440\u0444"
    ],
    "name:uzb_x_preferred":[
        "Uttendorf"
    ],
    "name:vol_x_preferred":[
        "Uttendorf"
    ],
    "name:war_x_preferred":[
        "Uttendorf"
    ],
    "name:zho_x_preferred":[
        "\u4e4c\u6ed5\u591a\u592b"
    ],
    "wof:name":"Uttendorf",
    "wof:placetype":"locality",
    "wof:population":42
},
  "geometry": {"coordinates":[14.11563,48.52814],"type":"Point"}
}