{
  "type": "Feature",
  "properties": {
    "gn:admin1_code":"3.0",
    "gn:admin2_code":"325",
    "gn:admin3_code":"32515.0",
    "gn:asciiname":"Hoerans",
    "gn:country_code":"AT",
    "gn:dem":706,
    "gn:feature_class":"P",
    "gn:feature_code":"PPL",
    "gn:name":"H\u00f6rans",
    "gn:population":14,
    "gn:timezone":"Europe/Vienna",
    "iso:country":"AT",
    "wof:name":"Hoerans",
    "wof:placetype":"locality",
    "wof:population":14
},
  "geometry": {"coordinates":[15.29648,48.45747],"type":"Point"}
}