{
  "type": "Feature",
  "properties": {
    "gn:admin1_code":"6.0",
    "gn:admin2_code":"617",
    "gn:admin3_code":"61710.0",
    "gn:asciiname":"Lebing",
    "gn:country_code":"AT",
    "gn:dem":463,
    "gn:feature_class":"P",
    "gn:feature_code":"PPL",
    "gn:name":"Lebing",
    "gn:population":434,
    "gn:timezone":"Europe/Vienna",
    "iso:country":"AT",
    "wof:name":"Lebing",
    "wof:placetype":"locality",
    "wof:population":434
},
  "geometry": {"coordinates":[15.73333,47.25],"type":"Point"}
}