{
  "type": "Feature",
  "properties": {
    "gn:admin1_code":"3.0",
    "gn:admin2_code":"319",
    "gn:admin3_code":"31946.0",
    "gn:asciiname":"Obermoos",
    "gn:country_code":"AT",
    "gn:dem":259,
    "gn:feature_class":"P",
    "gn:feature_code":"PPL",
    "gn:name":"Obermoos",
    "gn:population":10,
    "gn:timezone":"Europe/Vienna",
    "iso:country":"AT",
    "wof:name":"Obermoos",
    "wof:placetype":"locality",
    "wof:population":10
},
  "geometry": {"coordinates":[15.81667,48.25],"type":"Point"}
}