{
  "type": "Feature",
  "properties": {
    "gn:admin1_code":"4.0",
    "gn:admin2_code":"404",
    "gn:admin3_code":"40404.0",
    "gn:asciiname":"Blankenbach",
    "gn:country_code":"AT",
    "gn:dem":350,
    "gn:feature_class":"P",
    "gn:feature_code":"PPL",
    "gn:name":"Blankenbach",
    "gn:population":99,
    "gn:timezone":"Europe/Vienna",
    "iso:country":"AT",
    "name:bar_x_preferred":[
        "Blankenbach"
    ],
    "name:ceb_x_preferred":[
        "Blankenbach"
    ],
    "name:dan_x_preferred":[
        "Blankenbach"
    ],
    "name:deu_x_preferred":[
        "Blankenbach"
    ],
    "name:epo_x_preferred":[
        "Blankenbach"
    ],
    "name:eus_x_preferred":[
        "Blankenbach"
    ],
    "name:fas_x_preferred":[
        "\u0628\u0644\u0627\u0646\u06a9\u0646\u0628\u0627\u062e"
    ],
    "name:fra_x_preferred":[
        "Blankenbach"
    ],
    "name:hun_x_preferred":[
        "Blankenbach"
    ],
    "name:hye_x_preferred":[
        "\u0532\u056c\u0561\u0576\u056f\u0565\u0576\u0562\u0561\u056d"
    ],
    "name:ind_x_preferred":[
        "Blankenbach"
    ],
    "name:ita_x_preferred":[
        "Blankenbach"
    ],
    "name:jpn_x_preferred":[
        "\u30d6\u30e9\u30f3\u30b1\u30f3\u30d0\u30c3\u30cf"
    ],
    "name:kaz_x_preferred":[
        "\u0411\u043b\u0430\u043d\u043a\u0435\u043d\u0431\u0430\u0445"
    ],
    "name:kir_x_preferred":[
        "\u0411\u043b\u0430\u043d\u043a\u0435\u043d\u0431\u0430\u0445"
    ],
    "name:lat_x_preferred":[
        "Blankenbach"
    ],
    "name:lmo_x_preferred":[
        "Blankenbach"
    ],
    "name:msa_x_preferred":[
        "Blankenbach"
    ],
    "name:nld_x_preferred":[
        "Blankenbach"
    ],
    "name:pol_x_preferred":[
        "Blankenbach"
    ],
    "name:por_x_preferred":[
        "Blankenbach"
    ],
    "name:ron_x_preferred":[
        "Blankenbach"
    ],
    "name:rus_x_preferred":[
        "\u0411\u043b\u0430\u043d\u043a\u0435\u043d\u0431\u0430\u0445"
    ],
    "name:spa_x_preferred":[
        "Blankenbach"
    ],
    "name:srp_x_preferred":[
        "\u0411\u043b\u0430\u043d\u043a\u0435\u043d\u0431\u0430\u0445"
    ],
    "name:ukr_x_preferred":[
        "\u0411\u043b\u0430\u043d\u043a\u0435\u043d\u0431\u0430\u0445"
    ],
    "name:uzb_x_preferred":[
        "Blankenbach"
    ],
    "name:vol_x_preferred":[
        "Blankenbach"
    ],
    "name:war_x_preferred":[
        "Blankenbach"
    ],
    "name:zho_x_preferred":[
        "\u5e03\u5170\u80af\u5df4\u8d6b"
    ],
    "wof:name":"Blankenbach",
    "wof:placetype":"locality",
    "wof:population":99
},
  "geometry": {"coordinates":[12.99468,48.22433],"type":"Point"}
}