{
  "type": "Feature",
  "properties": {
    "gn:admin1_code":"4.0",
    "gn:admin2_code":"404",
    "gn:admin3_code":"40404.0",
    "gn:asciiname":"Blankenbach",
    "gn:country_code":"AT",
    "gn:dem":350,
    "gn:feature_class":"P",
    "gn:feature_code":"PPL",
    "gn:name":"Blankenbach",
    "gn:population":99,
    "gn:timezone":"Europe/Vienna",
    "iso:country":"AT",
    "wof:name":"Blankenbach",
    "wof:placetype":"locality",
    "wof:population":99
},
  "geometry": {"coordinates":[12.99468,48.22433],"type":"Point"}
}