{
  "type": "Feature",
  "properties": {
    "gn:admin1_code":"6.0",
    "gn:admin2_code":"606",
    "gn:admin3_code":"60663.0",
    "gn:asciiname":"Gamsgraben",
    "gn:country_code":"AT",
    "gn:dem":585,
    "gn:feature_class":"P",
    "gn:feature_code":"PPL",
    "gn:name":"Gamsgraben",
    "gn:population":35,
    "gn:timezone":"Europe/Vienna",
    "iso:country":"AT",
    "wof:name":"Gamsgraben",
    "wof:placetype":"locality",
    "wof:population":35
},
  "geometry": {"coordinates":[15.26667,47.28333],"type":"Point"}
}