{
  "type": "Feature",
  "properties": {
    "gn:admin1_code":"04",
    "gn:admin2_code":"406.0",
    "gn:admin3_code":"40611.0",
    "gn:asciiname":"Schoeneben",
    "gn:country_code":"AT",
    "gn:dem":885,
    "gn:feature_class":"P",
    "gn:feature_code":"PPL",
    "gn:name":"Sch\u00f6neben",
    "gn:population":167,
    "gn:timezone":"Europe/Vienna",
    "iso:country":"AT",
    "wof:name":"Schoeneben",
    "wof:placetype":"locality",
    "wof:population":167
},
  "geometry": {"coordinates":[14.73919,48.54786],"type":"Point"}
}