{
  "type": "Feature",
  "properties": {
    "gn:admin1_code":"2.0",
    "gn:admin2_code":"205",
    "gn:admin3_code":"20513.0",
    "gn:asciiname":"Gruenburg",
    "gn:country_code":"AT",
    "gn:dem":1002,
    "gn:feature_class":"P",
    "gn:feature_code":"PPL",
    "gn:name":"Gr\u00fcnburg",
    "gn:population":10,
    "gn:timezone":"Europe/Vienna",
    "iso:country":"AT",
    "wof:name":"Gruenburg",
    "wof:placetype":"locality",
    "wof:population":10
},
  "geometry": {"coordinates":[14.57401,46.85236],"type":"Point"}
}