{
  "type": "Feature",
  "properties": {
    "gn:admin1_code":"6.0",
    "gn:admin2_code":"612",
    "gn:admin3_code":"61264.0",
    "gn:asciiname":"Wolfsbachau",
    "gn:country_code":"AT",
    "gn:dem":491,
    "gn:feature_class":"P",
    "gn:feature_code":"PPL",
    "gn:name":"Wolfsbachau",
    "gn:population":19,
    "gn:timezone":"Europe/Vienna",
    "iso:country":"AT",
    "wof:name":"Wolfsbachau",
    "wof:placetype":"locality",
    "wof:population":19
},
  "geometry": {"coordinates":[14.67597,47.70864],"type":"Point"}
}