{
  "type": "Feature",
  "properties": {
    "gn:admin1_code":"04",
    "gn:admin2_code":"404.0",
    "gn:admin3_code":"40401.0",
    "gn:asciiname":"Stern",
    "gn:country_code":"AT",
    "gn:dem":428,
    "gn:feature_class":"P",
    "gn:feature_code":"PPL",
    "gn:name":"Stern",
    "gn:population":112,
    "gn:timezone":"Europe/Vienna",
    "iso:country":"AT",
    "wof:name":"Stern",
    "wof:placetype":"locality",
    "wof:population":112
},
  "geometry": {"coordinates":[13.21667,48.21667],"type":"Point"}
}