{
  "type": "Feature",
  "properties": {
    "gn:admin1_code":"04",
    "gn:admin2_code":"404.0",
    "gn:admin3_code":"40401.0",
    "gn:asciiname":"Stern",
    "gn:country_code":"AT",
    "gn:dem":428,
    "gn:feature_class":"P",
    "gn:feature_code":"PPL",
    "gn:name":"Stern",
    "gn:population":112,
    "gn:timezone":"Europe/Vienna",
    "iso:country":"AT",
    "name:arg_x_preferred":[
        "Popa"
    ],
    "name:aze_x_preferred":[
        "G\u0259mi sar\u011f\u0131s\u0131"
    ],
    "name:bel_x_preferred":[
        "\u041a\u0430\u0440\u043c\u0430"
    ],
    "name:bul_x_preferred":[
        "\u041a\u044a\u0440\u043c\u0430"
    ],
    "name:cat_x_preferred":[
        "Popa"
    ],
    "name:dan_x_preferred":[
        "Agter"
    ],
    "name:deu_x_preferred":[
        "Heck"
    ],
    "name:ell_x_preferred":[
        "\u03a0\u03c1\u03cd\u03bc\u03bd\u03b7"
    ],
    "name:epo_x_preferred":[
        "Pobo"
    ],
    "name:est_x_preferred":[
        "Ahter"
    ],
    "name:eus_x_preferred":[
        "Txopa"
    ],
    "name:fra_x_preferred":[
        "Poupe"
    ],
    "name:glg_x_preferred":[
        "Popa"
    ],
    "name:hrv_x_preferred":[
        "Krma"
    ],
    "name:ido_x_preferred":[
        "Pupo"
    ],
    "name:ind_x_preferred":[
        "Buritan"
    ],
    "name:isl_x_preferred":[
        "Skutur"
    ],
    "name:ita_x_preferred":[
        "Poppa"
    ],
    "name:msa_x_preferred":[
        "Buritan"
    ],
    "name:nor_x_preferred":[
        "Akterspeil"
    ],
    "name:oci_x_preferred":[
        "Popa"
    ],
    "name:pol_x_preferred":[
        "Rufa"
    ],
    "name:por_x_preferred":[
        "Popa"
    ],
    "name:ron_x_preferred":[
        "Pup\u0103"
    ],
    "name:rus_x_preferred":[
        "\u041a\u043e\u0440\u043c\u0430"
    ],
    "name:slk_x_preferred":[
        "Korma"
    ],
    "name:slv_x_preferred":[
        "Krma"
    ],
    "name:spa_x_preferred":[
        "Popa"
    ],
    "name:srp_x_preferred":[
        "\u041a\u0440\u043c\u0430"
    ],
    "name:swa_x_preferred":[
        "Tezi"
    ],
    "name:swe_x_preferred":[
        "Akter"
    ],
    "name:tur_x_preferred":[
        "Pupa"
    ],
    "name:ukr_x_preferred":[
        "\u041a\u043e\u0440\u043c\u0430"
    ],
    "wof:name":"Stern",
    "wof:placetype":"locality",
    "wof:population":112
},
  "geometry": {"coordinates":[13.21667,48.21667],"type":"Point"}
}