{
  "type": "Feature",
  "properties": {
    "gn:admin1_code":"03",
    "gn:admin2_code":"316.0",
    "gn:admin3_code":"31630.0",
    "gn:asciiname":"Puerstendorf",
    "gn:country_code":"AT",
    "gn:dem":260,
    "gn:feature_class":"P",
    "gn:feature_code":"PPL",
    "gn:name":"P\u00fcrstendorf",
    "gn:population":81,
    "gn:timezone":"Europe/Vienna",
    "iso:country":"AT",
    "wof:name":"Puerstendorf",
    "wof:placetype":"locality",
    "wof:population":81
},
  "geometry": {"coordinates":[16.41667,48.53333],"type":"Point"}
}