{
  "type": "Feature",
  "properties": {
    "gn:admin1_code":"4.0",
    "gn:admin2_code":"408",
    "gn:admin3_code":"40806.0",
    "gn:asciiname":"Holzing",
    "gn:country_code":"AT",
    "gn:dem":525,
    "gn:feature_class":"P",
    "gn:feature_code":"PPL",
    "gn:name":"Holzing",
    "gn:population":42,
    "gn:timezone":"Europe/Vienna",
    "iso:country":"AT",
    "wof:name":"Holzing",
    "wof:placetype":"locality",
    "wof:population":42
},
  "geometry": {"coordinates":[13.68055,48.15501],"type":"Point"}
}