{
  "type": "Feature",
  "properties": {
    "iso:country":"AT",
    "name:deu_x_preferred":[
        "\u00c4u\u00dferer Muelln"
    ],
    "name:eng_x_preferred":[
        "Aeusserer M\u00fclln"
    ],
    "wof:name":"Aeusserer M\u00fclln",
    "wof:placetype":"neighbourhood"
},
  "geometry": {"coordinates":[13.03056401653483,47.8031266204341],"type":"Point"}
}