{
  "type": "Feature",
  "properties": {
    "gn:admin1_code":"03",
    "gn:admin2_code":"305.0",
    "gn:admin3_code":"30542.0",
    "gn:asciiname":"Rudersberg",
    "gn:country_code":"AT",
    "gn:dem":389,
    "gn:feature_class":"P",
    "gn:feature_code":"PPL",
    "gn:name":"Rudersberg",
    "gn:population":0,
    "gn:timezone":"Europe/Vienna",
    "iso:country":"AT",
    "name:als_x_preferred":[
        "Rudersberg"
    ],
    "name:ceb_x_preferred":[
        "Rudersberg"
    ],
    "name:deu_x_preferred":[
        "Rudersberg"
    ],
    "name:epo_x_preferred":[
        "Rudersberg"
    ],
    "name:eus_x_preferred":[
        "Rudersberg"
    ],
    "name:fas_x_preferred":[
        "\u0631\u0648\u062f\u0631\u0633\u0628\u0631\u06af"
    ],
    "name:fra_x_preferred":[
        "Rudersberg"
    ],
    "name:hun_x_preferred":[
        "Rudersberg"
    ],
    "name:ita_x_preferred":[
        "Rudersberg"
    ],
    "name:jpn_x_preferred":[
        "\u30eb\u30fc\u30c0\u30fc\u30b9\u30d9\u30eb\u30af"
    ],
    "name:lat_x_preferred":[
        "Rudersberg"
    ],
    "name:lmo_x_preferred":[
        "Rudersberg"
    ],
    "name:msa_x_preferred":[
        "Rudersberg"
    ],
    "name:nld_x_preferred":[
        "Rudersberg"
    ],
    "name:pol_x_preferred":[
        "Rudersberg"
    ],
    "name:por_x_preferred":[
        "Rudersberg"
    ],
    "name:ron_x_preferred":[
        "Rudersberg"
    ],
    "name:rus_x_preferred":[
        "\u0420\u0443\u0434\u0435\u0440\u0441\u0431\u0435\u0440\u0433"
    ],
    "name:srp_x_preferred":[
        "\u0420\u0443\u0434\u0435\u0440\u0441\u0431\u0435\u0440\u0433"
    ],
    "name:swe_x_preferred":[
        "Rudersberg"
    ],
    "name:ukr_x_preferred":[
        "\u0420\u0443\u0434\u0435\u0440\u0441\u0431\u0435\u0440\u0433"
    ],
    "name:uzb_x_preferred":[
        "Rudersberg"
    ],
    "name:vie_x_preferred":[
        "Rudersberg"
    ],
    "name:vol_x_preferred":[
        "Rudersberg"
    ],
    "name:war_x_preferred":[
        "Rudersberg"
    ],
    "name:zho_x_preferred":[
        "\u9c81\u5fb7\u65af\u8d1d\u683c"
    ],
    "wof:name":"Rudersberg",
    "wof:placetype":"locality"
},
  "geometry": {"coordinates":[14.68333,48.08333],"type":"Point"}
}