{
  "type": "Feature",
  "properties": {
    "gn:admin1_code":"6.0",
    "gn:admin2_code":"621",
    "gn:admin3_code":"62135.0",
    "gn:asciiname":"Au",
    "gn:country_code":"AT",
    "gn:dem":841,
    "gn:feature_class":"P",
    "gn:feature_code":"PPL",
    "gn:name":"Au",
    "gn:population":0,
    "gn:timezone":"Europe/Vienna",
    "iso:country":"AT",
    "name:cat_x_preferred":[
        "Au"
    ],
    "name:est_x_preferred":[
        "Au"
    ],
    "name:hun_x_preferred":[
        "Au"
    ],
    "wof:name":"Au",
    "wof:placetype":"locality"
},
  "geometry": {"coordinates":[15.33333,47.56667],"type":"Point"}
}