{
  "type": "Feature",
  "properties": {
    "gn:admin1_code":"06",
    "gn:admin2_code":"623.0",
    "gn:admin3_code":"62390.0",
    "gn:asciiname":"Himberg",
    "gn:country_code":"AT",
    "gn:dem":248,
    "gn:feature_class":"P",
    "gn:feature_code":"PPL",
    "gn:name":"Himberg",
    "gn:population":0,
    "gn:timezone":"Europe/Vienna",
    "iso:country":"AT",
    "name:ceb_x_preferred":[
        "Himberg"
    ],
    "name:deu_x_preferred":[
        "Himberg"
    ],
    "name:epo_x_preferred":[
        "Himberg"
    ],
    "name:fas_x_preferred":[
        "\u0647\u06cc\u0645\u0628\u0631\u06af"
    ],
    "name:fra_x_preferred":[
        "Himberg"
    ],
    "name:hun_x_preferred":[
        "Himberg"
    ],
    "name:ita_x_preferred":[
        "Himberg"
    ],
    "name:kaz_x_preferred":[
        "\u0425\u0438\u043c\u0431\u0435\u0440\u0433"
    ],
    "name:nld_x_preferred":[
        "Himberg"
    ],
    "name:nno_x_preferred":[
        "Himberg"
    ],
    "name:pol_x_preferred":[
        "Himberg"
    ],
    "name:por_x_preferred":[
        "Himberg"
    ],
    "name:rus_x_preferred":[
        "\u0425\u0438\u043c\u0431\u0435\u0440\u0433"
    ],
    "name:slk_x_preferred":[
        "Himberg"
    ],
    "name:spa_x_preferred":[
        "Himberg"
    ],
    "name:swe_x_preferred":[
        "Himberg"
    ],
    "name:uzb_x_preferred":[
        "Himberg"
    ],
    "name:vie_x_preferred":[
        "Himberg"
    ],
    "name:vol_x_preferred":[
        "Himberg"
    ],
    "name:war_x_preferred":[
        "Himberg"
    ],
    "name:zho_x_preferred":[
        "\u6b23\u8d1d\u683c"
    ],
    "wof:name":"Himberg",
    "wof:placetype":"locality"
},
  "geometry": {"coordinates":[15.88333,46.81667],"type":"Point"}
}