{
  "type": "Feature",
  "properties": {
    "gn:admin1_code":"2.0",
    "gn:admin2_code":"205",
    "gn:admin3_code":"20520.0",
    "gn:asciiname":"Drasenberg",
    "gn:country_code":"AT",
    "gn:dem":673,
    "gn:feature_class":"P",
    "gn:feature_code":"PPL",
    "gn:name":"Drasenberg",
    "gn:population":35,
    "gn:timezone":"Europe/Vienna",
    "iso:country":"AT",
    "wof:name":"Drasenberg",
    "wof:placetype":"locality",
    "wof:population":35
},
  "geometry": {"coordinates":[14.38333,46.83333],"type":"Point"}
}