{
  "type": "Feature",
  "properties": {
    "gn:admin1_code":"4.0",
    "gn:admin2_code":"408",
    "gn:admin3_code":"40828.0",
    "gn:asciiname":"Parz am OEhlstampf",
    "gn:country_code":"AT",
    "gn:dem":395,
    "gn:feature_class":"P",
    "gn:feature_code":"PPL",
    "gn:name":"Parz am \u00d6hlstampf",
    "gn:population":25,
    "gn:timezone":"Europe/Vienna",
    "iso:country":"AT",
    "wof:name":"Parz am OEhlstampf",
    "wof:placetype":"locality",
    "wof:population":25
},
  "geometry": {"coordinates":[13.74111,48.35209],"type":"Point"}
}