{
  "type": "Feature",
  "properties": {
    "gn:admin1_code":"3.0",
    "gn:admin2_code":"316",
    "gn:admin3_code":"31629.0",
    "gn:asciiname":"Ruhhof",
    "gn:country_code":"AT",
    "gn:dem":180,
    "gn:feature_class":"P",
    "gn:feature_code":"PPLL",
    "gn:name":"Ruhhof",
    "gn:population":6,
    "gn:timezone":"Europe/Vienna",
    "iso:country":"AT",
    "wof:name":"Ruhhof",
    "wof:placetype":"locality",
    "wof:population":6
},
  "geometry": {"coordinates":[16.41512,48.74326],"type":"Point"}
}