{
  "type": "Feature",
  "properties": {
    "gn:admin1_code":"4.0",
    "gn:admin2_code":"414",
    "gn:admin3_code":"41423.0",
    "gn:asciiname":"Pyret",
    "gn:country_code":"AT",
    "gn:dem":309,
    "gn:feature_class":"P",
    "gn:feature_code":"PPL",
    "gn:name":"Pyret",
    "gn:population":0,
    "gn:timezone":"Europe/Vienna",
    "iso:country":"AT",
    "wof:name":"Pyret",
    "wof:placetype":"locality"
},
  "geometry": {"coordinates":[13.44694,48.5425],"type":"Point"}
}