{
  "type": "Feature",
  "properties": {
    "gn:admin1_code":"4.0",
    "gn:admin2_code":"417",
    "gn:admin3_code":"41741.0",
    "gn:asciiname":"Angermair",
    "gn:country_code":"AT",
    "gn:dem":613,
    "gn:feature_class":"P",
    "gn:feature_code":"PPL",
    "gn:name":"Angermair",
    "gn:population":0,
    "gn:timezone":"Europe/Vienna",
    "iso:country":"AT",
    "wof:name":"Angermair",
    "wof:placetype":"locality"
},
  "geometry": {"coordinates":[13.44778,47.90064],"type":"Point"}
}