{
  "type": "Feature",
  "properties": {
    "gn:admin1_code":"03",
    "gn:admin2_code":"325.0",
    "gn:admin3_code":"32525.0",
    "gn:asciiname":"Vierlings",
    "gn:country_code":"AT",
    "gn:dem":619,
    "gn:feature_class":"P",
    "gn:feature_code":"PPL",
    "gn:name":"Vierlings",
    "gn:population":17,
    "gn:timezone":"Europe/Vienna",
    "iso:country":"AT",
    "wof:name":"Vierlings",
    "wof:placetype":"locality",
    "wof:population":17
},
  "geometry": {"coordinates":[14.9967,48.6677],"type":"Point"}
}