{
  "type": "Feature",
  "properties": {
    "gn:admin1_code":"07",
    "gn:admin2_code":"702.0",
    "gn:admin3_code":"70220.0",
    "gn:asciiname":"Rettenbach",
    "gn:cc2":"AT",
    "gn:country_code":"AT",
    "gn:dem":2006,
    "gn:feature_class":"P",
    "gn:feature_code":"PPL",
    "gn:name":"Rettenbach",
    "gn:population":0,
    "gn:timezone":"Europe/Vienna",
    "iso:country":"AT",
    "name:ceb_x_preferred":[
        "Rettenbach"
    ],
    "name:deu_x_preferred":[
        "Rettenbach"
    ],
    "name:epo_x_preferred":[
        "Rettenbach"
    ],
    "name:fra_x_preferred":[
        "Rettenbach"
    ],
    "name:hye_x_preferred":[
        "\u054c\u0565\u0569\u0565\u0576\u0562\u0561\u056d"
    ],
    "name:ita_x_preferred":[
        "Rettenbach"
    ],
    "name:lmo_x_preferred":[
        "Rettenbach"
    ],
    "name:nld_x_preferred":[
        "Rettenbach"
    ],
    "name:pol_x_preferred":[
        "Rettenbach"
    ],
    "name:ron_x_preferred":[
        "Rettenbach"
    ],
    "name:rus_x_preferred":[
        "\u0420\u0435\u0442\u0442\u0435\u043d\u0431\u0430\u0445"
    ],
    "name:srp_x_preferred":[
        "\u0420\u0435\u0442\u0435\u043d\u0431\u0430\u0445"
    ],
    "name:swe_x_preferred":[
        "Rettenbach"
    ],
    "name:und_x_variant":[
        "Rettenbachl"
    ],
    "wof:name":"Rettenbach",
    "wof:placetype":"locality"
},
  "geometry": {"coordinates":[10.98333,46.96667],"type":"Point"}
}