{
  "type": "Feature",
  "properties": {
    "gn:admin1_code":"03",
    "gn:admin2_code":"320.0",
    "gn:admin3_code":"32018.0",
    "gn:asciiname":"Zarnsdorf",
    "gn:country_code":"AT",
    "gn:dem":290,
    "gn:feature_class":"P",
    "gn:feature_code":"PPL",
    "gn:name":"Zarnsdorf",
    "gn:population":438,
    "gn:timezone":"Europe/Vienna",
    "iso:country":"AT",
    "wof:name":"Zarnsdorf",
    "wof:placetype":"locality",
    "wof:population":438
},
  "geometry": {"coordinates":[15.08333,48.08333],"type":"Point"}
}