{
  "type": "Feature",
  "properties": {
    "gn:admin1_code":"7.0",
    "gn:admin2_code":"706",
    "gn:admin3_code":"70611.0",
    "gn:asciiname":"Platz",
    "gn:country_code":"AT",
    "gn:dem":1245,
    "gn:feature_class":"P",
    "gn:feature_code":"PPL",
    "gn:name":"Platz",
    "gn:population":0,
    "gn:timezone":"Europe/Vienna",
    "iso:country":"AT",
    "wof:name":"Platz",
    "wof:placetype":"locality"
},
  "geometry": {"coordinates":[10.75287,47.05352],"type":"Point"}
}