{
  "type": "Feature",
  "properties": {
    "gn:admin1_code":"4.0",
    "gn:admin2_code":"414",
    "gn:admin3_code":"41416.0",
    "gn:asciiname":"Puchet",
    "gn:country_code":"AT",
    "gn:dem":434,
    "gn:feature_class":"P",
    "gn:feature_code":"PPL",
    "gn:name":"Puchet",
    "gn:population":0,
    "gn:timezone":"Europe/Vienna",
    "iso:country":"AT",
    "wof:name":"Puchet",
    "wof:placetype":"locality"
},
  "geometry": {"coordinates":[13.66382,48.29267],"type":"Point"}
}