{
  "type": "Feature",
  "properties": {
    "gn:admin1_code":"4.0",
    "gn:admin2_code":"417",
    "gn:admin3_code":"41744.0",
    "gn:asciiname":"Kellner",
    "gn:country_code":"AT",
    "gn:dem":500,
    "gn:feature_class":"P",
    "gn:feature_code":"PPL",
    "gn:name":"Kellner",
    "gn:population":59,
    "gn:timezone":"Europe/Vienna",
    "iso:country":"AT",
    "wof:name":"Kellner",
    "wof:placetype":"locality",
    "wof:population":59
},
  "geometry": {"coordinates":[13.60391,48.0453],"type":"Point"}
}