{
  "type": "Feature",
  "properties": {
    "gn:admin1_code":"7.0",
    "gn:admin2_code":"707",
    "gn:admin3_code":"70705.0",
    "gn:asciiname":"Oberassling",
    "gn:country_code":"AT",
    "gn:dem":1045,
    "gn:feature_class":"P",
    "gn:feature_code":"PPL",
    "gn:name":"Oberassling",
    "gn:population":179,
    "gn:timezone":"Europe/Vienna",
    "iso:country":"AT",
    "wof:name":"Oberassling",
    "wof:placetype":"locality",
    "wof:population":179
},
  "geometry": {"coordinates":[12.63333,46.78333],"type":"Point"}
}