{
  "type": "Feature",
  "properties": {
    "gn:admin1_code":"05",
    "gn:admin2_code":"505.0",
    "gn:admin3_code":"50503.0",
    "gn:asciiname":"Tscharra",
    "gn:country_code":"AT",
    "gn:dem":1328,
    "gn:feature_class":"P",
    "gn:feature_code":"PPL",
    "gn:name":"Tscharra",
    "gn:population":0,
    "gn:timezone":"Europe/Vienna",
    "iso:country":"AT",
    "wof:name":"Tscharra",
    "wof:placetype":"locality"
},
  "geometry": {"coordinates":[13.73333,47.18333],"type":"Point"}
}