{
  "type": "Feature",
  "properties": {
    "gn:admin1_code":"3.0",
    "gn:admin2_code":"319",
    "gn:admin3_code":"31926.0",
    "gn:asciiname":"Altanzing",
    "gn:country_code":"AT",
    "gn:dem":233,
    "gn:feature_class":"P",
    "gn:feature_code":"PPL",
    "gn:name":"Altanzing",
    "gn:population":0,
    "gn:timezone":"Europe/Vienna",
    "iso:country":"AT",
    "wof:name":"Altanzing",
    "wof:placetype":"locality"
},
  "geometry": {"coordinates":[15.87396,48.22078],"type":"Point"}
}