{
  "type": "Feature",
  "properties": {
    "gn:admin1_code":"04",
    "gn:admin2_code":"407.0",
    "gn:admin3_code":"40720.0",
    "gn:asciiname":"Weidach",
    "gn:country_code":"AT",
    "gn:dem":421,
    "gn:feature_class":"P",
    "gn:feature_code":"PPL",
    "gn:name":"Weidach",
    "gn:population":0,
    "gn:timezone":"Europe/Vienna",
    "iso:country":"AT",
    "wof:name":"Weidach",
    "wof:placetype":"locality"
},
  "geometry": {"coordinates":[13.91041,47.99434],"type":"Point"}
}