{
  "type": "Feature",
  "properties": {
    "gn:admin1_code":"02",
    "gn:admin2_code":"201.0",
    "gn:admin3_code":"20101.0",
    "gn:asciiname":"Ponfeld",
    "gn:country_code":"AT",
    "gn:dem":535,
    "gn:feature_class":"P",
    "gn:feature_code":"PPL",
    "gn:name":"Ponfeld",
    "gn:population":0,
    "gn:timezone":"Europe/Vienna",
    "iso:country":"AT",
    "wof:name":"Ponfeld",
    "wof:placetype":"locality"
},
  "geometry": {"coordinates":[14.23333,46.66667],"type":"Point"}
}