{
  "type": "Feature",
  "properties": {
    "gn:admin1_code":"4.0",
    "gn:admin2_code":"414",
    "gn:admin3_code":"41429.0",
    "gn:asciiname":"Hofoetz",
    "gn:country_code":"AT",
    "gn:dem":312,
    "gn:feature_class":"P",
    "gn:feature_code":"PPL",
    "gn:name":"Hof\u00f6tz",
    "gn:population":24,
    "gn:timezone":"Europe/Vienna",
    "iso:country":"AT",
    "wof:name":"Hofoetz",
    "wof:placetype":"locality",
    "wof:population":24
},
  "geometry": {"coordinates":[13.45611,48.51861],"type":"Point"}
}