{
  "type": "Feature",
  "properties": {
    "gn:admin1_code":"4.0",
    "gn:admin2_code":"413",
    "gn:admin3_code":"41329.0",
    "gn:asciiname":"Grub",
    "gn:country_code":"AT",
    "gn:dem":561,
    "gn:feature_class":"P",
    "gn:feature_code":"PPL",
    "gn:name":"Grub",
    "gn:population":100,
    "gn:timezone":"Europe/Vienna",
    "iso:country":"AT",
    "wof:name":"Grub",
    "wof:placetype":"locality",
    "wof:population":100
},
  "geometry": {"coordinates":[13.75651,48.52019],"type":"Point"}
}