{
  "type": "Feature",
  "properties": {
    "gn:admin1_code":"4.0",
    "gn:admin2_code":"413",
    "gn:admin3_code":"41329.0",
    "gn:asciiname":"Grub",
    "gn:country_code":"AT",
    "gn:dem":561,
    "gn:feature_class":"P",
    "gn:feature_code":"PPL",
    "gn:name":"Grub",
    "gn:population":100,
    "gn:timezone":"Europe/Vienna",
    "iso:country":"AT",
    "name:ceb_x_preferred":[
        "Grub"
    ],
    "name:deu_x_preferred":[
        "Grub"
    ],
    "name:epo_x_preferred":[
        "Grub"
    ],
    "name:fra_x_preferred":[
        "Grub"
    ],
    "name:ita_x_preferred":[
        "Grub"
    ],
    "name:nld_x_preferred":[
        "Grub"
    ],
    "name:pol_x_preferred":[
        "Grub"
    ],
    "name:por_x_preferred":[
        "Grub"
    ],
    "name:ron_x_preferred":[
        "Grub"
    ],
    "name:rus_x_preferred":[
        "\u0413\u0440\u0443\u0431"
    ],
    "name:spa_x_preferred":[
        "Grub"
    ],
    "name:srp_x_preferred":[
        "\u0413\u0440\u0443\u0431"
    ],
    "name:swe_x_preferred":[
        "Grub"
    ],
    "name:vol_x_preferred":[
        "Grub"
    ],
    "wof:name":"Grub",
    "wof:placetype":"locality",
    "wof:population":100
},
  "geometry": {"coordinates":[13.75651,48.52019],"type":"Point"}
}