{
  "type": "Feature",
  "properties": {
    "gn:admin1_code":"4.0",
    "gn:admin2_code":"417",
    "gn:admin3_code":"41747.0",
    "gn:asciiname":"Gopprechting",
    "gn:country_code":"AT",
    "gn:dem":531,
    "gn:feature_class":"P",
    "gn:feature_code":"PPL",
    "gn:name":"Gopprechting",
    "gn:population":26,
    "gn:timezone":"Europe/Vienna",
    "iso:country":"AT",
    "wof:name":"Gopprechting",
    "wof:placetype":"locality",
    "wof:population":26
},
  "geometry": {"coordinates":[13.51627,48.00069000000001],"type":"Point"}
}