{
  "type": "Feature",
  "properties": {
    "gn:admin1_code":"03",
    "gn:admin2_code":"315.0",
    "gn:admin3_code":"31506.0",
    "gn:asciiname":"Wurzeben",
    "gn:country_code":"AT",
    "gn:dem":900,
    "gn:feature_class":"P",
    "gn:feature_code":"PPL",
    "gn:name":"Wurzeben",
    "gn:population":0,
    "gn:timezone":"Europe/Vienna",
    "iso:country":"AT",
    "wof:name":"Wurzeben",
    "wof:placetype":"locality"
},
  "geometry": {"coordinates":[15.01667,48.36667],"type":"Point"}
}