{
  "type": "Feature",
  "properties": {
    "gn:admin1_code":"4.0",
    "gn:admin2_code":"410",
    "gn:admin3_code":"41022.0",
    "gn:asciiname":"Doernbach",
    "gn:country_code":"AT",
    "gn:dem":309,
    "gn:feature_class":"P",
    "gn:feature_code":"PPL",
    "gn:name":"D\u00f6rnbach",
    "gn:population":707,
    "gn:timezone":"Europe/Vienna",
    "iso:country":"AT",
    "wof:name":"Doernbach",
    "wof:placetype":"locality",
    "wof:population":707
},
  "geometry": {"coordinates":[14.20412,48.28234000000001],"type":"Point"}
}