{
  "type": "Feature",
  "properties": {
    "gn:admin1_code":"03",
    "gn:admin2_code":"318.0",
    "gn:admin3_code":"31847.0",
    "gn:asciiname":"Wolfsohl",
    "gn:country_code":"AT",
    "gn:dem":419,
    "gn:feature_class":"P",
    "gn:feature_code":"PPL",
    "gn:name":"Wolfsohl",
    "gn:population":204,
    "gn:timezone":"Europe/Vienna",
    "iso:country":"AT",
    "wof:name":"Wolfsohl",
    "wof:placetype":"locality",
    "wof:population":204
},
  "geometry": {"coordinates":[16.05137,47.76345],"type":"Point"}
}