{
  "type": "Feature",
  "properties": {
    "gn:admin1_code":"6.0",
    "gn:admin2_code":"603",
    "gn:admin3_code":"60350.0",
    "gn:asciiname":"Kraubath",
    "gn:country_code":"AT",
    "gn:dem":340,
    "gn:feature_class":"P",
    "gn:feature_code":"PPL",
    "gn:name":"Kraubath",
    "gn:population":0,
    "gn:timezone":"Europe/Vienna",
    "iso:country":"AT",
    "name:deu_x_preferred":[
        "Kraubath in der Weststeiermark"
    ],
    "wof:name":"Kraubath",
    "wof:placetype":"locality"
},
  "geometry": {"coordinates":[15.33297,46.85335],"type":"Point"}
}