{
  "type": "Feature",
  "properties": {
    "gn:admin1_code":"2.0",
    "gn:admin2_code":"204",
    "gn:admin3_code":"20405.0",
    "gn:asciiname":"Ploesnoutz",
    "gn:country_code":"AT",
    "gn:dem":831,
    "gn:feature_class":"P",
    "gn:feature_code":"PPL",
    "gn:name":"Pl\u00f6snoutz",
    "gn:population":0,
    "gn:timezone":"Europe/Vienna",
    "iso:country":"AT",
    "wof:name":"Ploesnoutz",
    "wof:placetype":"locality"
},
  "geometry": {"coordinates":[14.25167,46.48028],"type":"Point"}
}