{
  "type": "Feature",
  "properties": {
    "gn:admin1_code":"06",
    "gn:admin2_code":"617.0",
    "gn:admin3_code":"61759.0",
    "gn:asciiname":"Schachen am Roemerbach",
    "gn:country_code":"AT",
    "gn:dem":352,
    "gn:feature_class":"P",
    "gn:feature_code":"PPL",
    "gn:name":"Schachen am R\u00f6merbach",
    "gn:population":0,
    "gn:timezone":"Europe/Vienna",
    "iso:country":"AT",
    "name:und_x_variant":[
        "Schachen",
        "Schachen am R\u00f6merbach"
    ],
    "wof:name":"Schachen am Roemerbach",
    "wof:placetype":"locality"
},
  "geometry": {"coordinates":[15.81667,47.15],"type":"Point"}
}