{
  "type": "Feature",
  "properties": {
    "gn:admin1_code":"6.0",
    "gn:admin2_code":"623",
    "gn:admin3_code":"62380.0",
    "gn:asciiname":"Aug",
    "gn:country_code":"AT",
    "gn:dem":328,
    "gn:feature_class":"P",
    "gn:feature_code":"PPL",
    "gn:name":"Aug",
    "gn:population":93,
    "gn:timezone":"Europe/Vienna",
    "iso:country":"AT",
    "wof:name":"Aug",
    "wof:placetype":"locality",
    "wof:population":93
},
  "geometry": {"coordinates":[15.78333,46.85],"type":"Point"}
}