{
  "type": "Feature",
  "properties": {
    "gn:admin1_code":"4.0",
    "gn:admin2_code":"417",
    "gn:admin3_code":"41702.0",
    "gn:asciiname":"Aufham",
    "gn:country_code":"AT",
    "gn:dem":482,
    "gn:feature_class":"P",
    "gn:feature_code":"PPL",
    "gn:name":"Aufham",
    "gn:population":100,
    "gn:timezone":"Europe/Vienna",
    "iso:country":"AT",
    "wof:name":"Aufham",
    "wof:placetype":"locality",
    "wof:population":100
},
  "geometry": {"coordinates":[13.52775,47.90366],"type":"Point"}
}