{
  "type": "Feature",
  "properties": {
    "gn:admin1_code":"02",
    "gn:admin2_code":"208.0",
    "gn:admin3_code":"20815.0",
    "gn:asciiname":"Sonnegg",
    "gn:country_code":"AT",
    "gn:dem":560,
    "gn:feature_class":"P",
    "gn:feature_code":"PPL",
    "gn:name":"Sonnegg",
    "gn:population":30,
    "gn:timezone":"Europe/Vienna",
    "iso:country":"AT",
    "wof:name":"Sonnegg",
    "wof:placetype":"locality",
    "wof:population":30
},
  "geometry": {"coordinates":[14.63333,46.55],"type":"Point"}
}