{
  "type": "Feature",
  "properties": {
    "gn:admin1_code":"02",
    "gn:admin2_code":"208.0",
    "gn:admin3_code":"20817.0",
    "gn:asciiname":"Watzelsdorf",
    "gn:country_code":"AT",
    "gn:dem":510,
    "gn:feature_class":"P",
    "gn:feature_code":"PPL",
    "gn:name":"Watzelsdorf",
    "gn:population":82,
    "gn:timezone":"Europe/Vienna",
    "iso:country":"AT",
    "wof:name":"Watzelsdorf",
    "wof:placetype":"locality",
    "wof:population":82
},
  "geometry": {"coordinates":[14.66667,46.65],"type":"Point"}
}