{
  "type": "Feature",
  "properties": {
    "gn:admin1_code":"3.0",
    "gn:admin2_code":"313",
    "gn:admin3_code":"31322.0",
    "gn:asciiname":"Schiltern bei Langelois",
    "gn:country_code":"AT",
    "gn:dem":366,
    "gn:elevation":"0.0",
    "gn:feature_class":"P",
    "gn:feature_code":"PPL",
    "gn:name":"Schiltern bei Langelois",
    "gn:population":0,
    "gn:timezone":"Europe/Vienna",
    "iso:country":"AT",
    "wof:name":"Schiltern bei Langelois",
    "wof:placetype":"locality"
},
  "geometry": {"coordinates":[15.62422,48.51568],"type":"Point"}
}