{
  "type": "Feature",
  "properties": {
    "gn:admin1_code":"4.0",
    "gn:admin2_code":"417",
    "gn:admin3_code":"41706.0",
    "gn:asciiname":"Brandham",
    "gn:country_code":"AT",
    "gn:dem":555,
    "gn:feature_class":"P",
    "gn:feature_code":"PPL",
    "gn:name":"Brandham",
    "gn:population":32,
    "gn:timezone":"Europe/Vienna",
    "iso:country":"AT",
    "wof:name":"Brandham",
    "wof:placetype":"locality",
    "wof:population":32
},
  "geometry": {"coordinates":[13.517,47.96533],"type":"Point"}
}