{
  "type": "Feature",
  "properties": {
    "gn:admin1_code":"4.0",
    "gn:admin2_code":"417",
    "gn:admin3_code":"41711.0",
    "gn:asciiname":"Stoetten",
    "gn:country_code":"AT",
    "gn:dem":549,
    "gn:feature_class":"P",
    "gn:feature_code":"PPL",
    "gn:name":"St\u00f6tten",
    "gn:population":36,
    "gn:timezone":"Europe/Vienna",
    "iso:country":"AT",
    "wof:name":"Stoetten",
    "wof:placetype":"locality",
    "wof:population":36
},
  "geometry": {"coordinates":[13.54455,47.97895],"type":"Point"}
}