{
  "type": "Feature",
  "properties": {
    "gn:admin1_code":"06",
    "gn:admin2_code":"610.0",
    "gn:admin3_code":"61016.0",
    "gn:asciiname":"Weisheim",
    "gn:country_code":"AT",
    "gn:dem":400,
    "gn:feature_class":"P",
    "gn:feature_code":"PPL",
    "gn:name":"Weisheim",
    "gn:population":0,
    "gn:timezone":"Europe/Vienna",
    "iso:country":"AT",
    "wof:name":"Weisheim",
    "wof:placetype":"locality"
},
  "geometry": {"coordinates":[15.46667,46.75],"type":"Point"}
}