{
  "type": "Feature",
  "properties": {
    "gn:admin1_code":"4.0",
    "gn:admin2_code":"406",
    "gn:admin3_code":"40605.0",
    "gn:asciiname":"Vorwald",
    "gn:country_code":"AT",
    "gn:dem":779,
    "gn:feature_class":"P",
    "gn:feature_code":"PPL",
    "gn:name":"Vorwald",
    "gn:population":27,
    "gn:timezone":"Europe/Vienna",
    "iso:country":"AT",
    "wof:name":"Vorwald",
    "wof:placetype":"locality",
    "wof:population":27
},
  "geometry": {"coordinates":[14.40024,48.4901],"type":"Point"}
}