{
  "type": "Feature",
  "properties": {
    "gn:admin1_code":"6.0",
    "gn:admin2_code":"606",
    "gn:admin3_code":"60667.0",
    "gn:asciiname":"Duerwagersbach",
    "gn:country_code":"AT",
    "gn:dem":461,
    "gn:feature_class":"P",
    "gn:feature_code":"PPL",
    "gn:name":"D\u00fcrwagersbach",
    "gn:population":177,
    "gn:timezone":"Europe/Vienna",
    "iso:country":"AT",
    "wof:name":"Duerwagersbach",
    "wof:placetype":"locality",
    "wof:population":177
},
  "geometry": {"coordinates":[15.53333,47.03333],"type":"Point"}
}