{
  "type": "Feature",
  "properties": {
    "gn:admin1_code":"4.0",
    "gn:admin2_code":"415",
    "gn:admin3_code":"41506.0",
    "gn:asciiname":"Lahrndorf",
    "gn:country_code":"AT",
    "gn:dem":316,
    "gn:feature_class":"P",
    "gn:feature_code":"PPL",
    "gn:name":"Lahrndorf",
    "gn:population":504,
    "gn:timezone":"Europe/Vienna",
    "iso:country":"AT",
    "wof:name":"Lahrndorf",
    "wof:placetype":"locality",
    "wof:population":504
},
  "geometry": {"coordinates":[14.37994,47.99475],"type":"Point"}
}