{
  "type": "Feature",
  "properties": {
    "gn:admin1_code":"2.0",
    "gn:admin2_code":"203",
    "gn:admin3_code":"20316.0",
    "gn:asciiname":"Poertschach",
    "gn:country_code":"AT",
    "gn:dem":793,
    "gn:feature_class":"P",
    "gn:feature_code":"PPL",
    "gn:name":"P\u00f6rtschach",
    "gn:population":37,
    "gn:timezone":"Europe/Vienna",
    "iso:country":"AT",
    "wof:name":"Poertschach",
    "wof:placetype":"locality",
    "wof:population":37
},
  "geometry": {"coordinates":[13.53095,46.62398],"type":"Point"}
}