{
  "type": "Feature",
  "properties": {
    "gn:admin1_code":"3.0",
    "gn:admin2_code":"319",
    "gn:admin3_code":"31945.0",
    "gn:asciiname":"Edlitz",
    "gn:country_code":"AT",
    "gn:dem":319,
    "gn:feature_class":"P",
    "gn:feature_code":"PPL",
    "gn:name":"Edlitz",
    "gn:population":39,
    "gn:timezone":"Europe/Vienna",
    "iso:country":"AT",
    "wof:name":"Edlitz",
    "wof:placetype":"locality",
    "wof:population":39
},
  "geometry": {"coordinates":[15.50806,48.12382],"type":"Point"}
}