{
  "type": "Feature",
  "properties": {
    "gn:admin1_code":"5.0",
    "gn:admin2_code":"503",
    "gn:admin3_code":"50320.0",
    "gn:asciiname":"Dotleinsdorf",
    "gn:country_code":"AT",
    "gn:dem":603,
    "gn:feature_class":"P",
    "gn:feature_code":"PPL",
    "gn:name":"D\u00f6tleinsdorf",
    "gn:population":0,
    "gn:timezone":"Europe/Vienna",
    "iso:country":"AT",
    "wof:name":"Dotleinsdorf",
    "wof:placetype":"locality"
},
  "geometry": {"coordinates":[13.13333,47.93333],"type":"Point"}
}