{
  "type": "Feature",
  "properties": {
    "gn:admin1_code":"02",
    "gn:admin2_code":"210.0",
    "gn:admin3_code":"21001.0",
    "gn:asciiname":"Sankt Ruprecht",
    "gn:country_code":"AT",
    "gn:dem":984,
    "gn:feature_class":"P",
    "gn:feature_code":"PPL",
    "gn:name":"Sankt Ruprecht",
    "gn:population":23,
    "gn:timezone":"Europe/Vienna",
    "iso:country":"AT",
    "wof:name":"Sankt Ruprecht",
    "wof:placetype":"locality",
    "wof:population":23
},
  "geometry": {"coordinates":[14.03333,46.83333],"type":"Point"}
}