{
  "type": "Feature",
  "properties": {
    "gn:admin1_code":"4.0",
    "gn:admin2_code":"416",
    "gn:admin3_code":"41615.0",
    "gn:asciiname":"Hoef",
    "gn:country_code":"AT",
    "gn:dem":639,
    "gn:feature_class":"P",
    "gn:feature_code":"PPL",
    "gn:name":"H\u00f6f",
    "gn:population":115,
    "gn:timezone":"Europe/Vienna",
    "iso:country":"AT",
    "wof:name":"Hoef",
    "wof:placetype":"locality",
    "wof:population":115
},
  "geometry": {"coordinates":[14.17694,48.49472],"type":"Point"}
}