{
  "type": "Feature",
  "properties": {
    "gn:admin1_code":"4.0",
    "gn:admin2_code":"418",
    "gn:admin3_code":"41814.0",
    "gn:asciiname":"Maierhof",
    "gn:country_code":"AT",
    "gn:dem":390,
    "gn:feature_class":"P",
    "gn:feature_code":"PPL",
    "gn:name":"Maierhof",
    "gn:population":9,
    "gn:timezone":"Europe/Vienna",
    "iso:country":"AT",
    "wof:name":"Maierhof",
    "wof:placetype":"locality",
    "wof:population":9
},
  "geometry": {"coordinates":[13.8608,48.1571],"type":"Point"}
}