{
  "type": "Feature",
  "properties": {
    "gn:admin1_code":"6.0",
    "gn:admin2_code":"606",
    "gn:admin3_code":"60661.0",
    "gn:asciiname":"Freiingeregg",
    "gn:country_code":"AT",
    "gn:dem":506,
    "gn:feature_class":"P",
    "gn:feature_code":"PPL",
    "gn:name":"Freiingeregg",
    "gn:population":0,
    "gn:timezone":"Europe/Vienna",
    "iso:country":"AT",
    "wof:name":"Freiingeregg",
    "wof:placetype":"locality"
},
  "geometry": {"coordinates":[15.58333,47.15],"type":"Point"}
}