{
  "type": "Feature",
  "properties": {
    "gn:admin1_code":"03",
    "gn:admin2_code":"314.0",
    "gn:admin3_code":"31411.0",
    "gn:asciiname":"Seebach",
    "gn:country_code":"AT",
    "gn:dem":618,
    "gn:feature_class":"P",
    "gn:feature_code":"PPL",
    "gn:name":"Seebach",
    "gn:population":0,
    "gn:timezone":"Europe/Vienna",
    "iso:country":"AT",
    "name:als_x_preferred":[
        "Seebach"
    ],
    "name:cat_x_preferred":[
        "Seebach"
    ],
    "name:ceb_x_preferred":[
        "Seebach"
    ],
    "name:deu_x_preferred":[
        "Seebach"
    ],
    "name:epo_x_preferred":[
        "Seebach"
    ],
    "name:fra_x_preferred":[
        "Seebach"
    ],
    "name:ita_x_preferred":[
        "Seebach"
    ],
    "name:nld_x_preferred":[
        "Seebach"
    ],
    "name:pol_x_preferred":[
        "Seebach"
    ],
    "name:rus_x_preferred":[
        "\u0417\u0435\u0435\u0431\u0430\u0445"
    ],
    "name:swe_x_preferred":[
        "Seebach"
    ],
    "name:vol_x_preferred":[
        "Seebach"
    ],
    "wof:name":"Seebach",
    "wof:placetype":"locality"
},
  "geometry": {"coordinates":[15.6011,47.85107],"type":"Point"}
}