{
  "type": "Feature",
  "properties": {
    "gn:admin1_code":"03",
    "gn:admin2_code":"314.0",
    "gn:admin3_code":"31411.0",
    "gn:asciiname":"Seebach",
    "gn:country_code":"AT",
    "gn:dem":618,
    "gn:feature_class":"P",
    "gn:feature_code":"PPL",
    "gn:name":"Seebach",
    "gn:population":0,
    "gn:timezone":"Europe/Vienna",
    "iso:country":"AT",
    "wof:name":"Seebach",
    "wof:placetype":"locality"
},
  "geometry": {"coordinates":[15.6011,47.85107],"type":"Point"}
}