{
  "type": "Feature",
  "properties": {
    "gn:admin1_code":"4.0",
    "gn:admin2_code":"408",
    "gn:admin3_code":"40831.0",
    "gn:asciiname":"Schurrerprambach",
    "gn:country_code":"AT",
    "gn:dem":357,
    "gn:feature_class":"P",
    "gn:feature_code":"PPL",
    "gn:name":"Schurrerprambach",
    "gn:population":48,
    "gn:timezone":"Europe/Vienna",
    "iso:country":"AT",
    "wof:name":"Schurrerprambach",
    "wof:placetype":"locality",
    "wof:population":48
},
  "geometry": {"coordinates":[13.87702,48.34427],"type":"Point"}
}