{
  "type": "Feature",
  "properties": {
    "gn:admin1_code":"4.0",
    "gn:admin2_code":"412",
    "gn:admin3_code":"41204.0",
    "gn:asciiname":"Leopoldshofstadt",
    "gn:country_code":"AT",
    "gn:dem":553,
    "gn:feature_class":"P",
    "gn:feature_code":"PPL",
    "gn:name":"Leopoldshofstadt",
    "gn:population":0,
    "gn:timezone":"Europe/Vienna",
    "iso:country":"AT",
    "wof:name":"Leopoldshofstadt",
    "wof:placetype":"locality"
},
  "geometry": {"coordinates":[13.56667,48.13333],"type":"Point"}
}