{
  "type": "Feature",
  "properties": {
    "gn:admin1_code":"6.0",
    "gn:admin2_code":"612",
    "gn:admin3_code":"61266.0",
    "gn:asciiname":"Moessna",
    "gn:country_code":"AT",
    "gn:dem":1136,
    "gn:feature_class":"P",
    "gn:feature_code":"PPL",
    "gn:name":"M\u00f6ssna",
    "gn:population":0,
    "gn:timezone":"Europe/Vienna",
    "iso:country":"AT",
    "wof:name":"Moessna",
    "wof:placetype":"locality"
},
  "geometry": {"coordinates":[14.03333,47.33333],"type":"Point"}
}