{
  "type": "Feature",
  "properties": {
    "gn:admin1_code":"2.0",
    "gn:admin2_code":"204",
    "gn:admin3_code":"20412.0",
    "gn:asciiname":"Hoehe",
    "gn:country_code":"AT",
    "gn:dem":643,
    "gn:feature_class":"P",
    "gn:feature_code":"PPL",
    "gn:name":"H\u00f6he",
    "gn:population":155,
    "gn:timezone":"Europe/Vienna",
    "iso:country":"AT",
    "wof:name":"Hoehe",
    "wof:placetype":"locality",
    "wof:population":155
},
  "geometry": {"coordinates":[14.14306,46.59778],"type":"Point"}
}