{
  "type": "Feature",
  "properties": {
    "gn:admin1_code":"4.0",
    "gn:admin2_code":"417",
    "gn:admin3_code":"41712.0",
    "gn:asciiname":"Loibicht",
    "gn:country_code":"AT",
    "gn:dem":544,
    "gn:feature_class":"P",
    "gn:feature_code":"PPL",
    "gn:name":"Loibicht",
    "gn:population":0,
    "gn:timezone":"Europe/Vienna",
    "iso:country":"AT",
    "wof:name":"Loibicht",
    "wof:placetype":"locality"
},
  "geometry": {"coordinates":[13.43645,47.84945],"type":"Point"}
}