{
  "type": "Feature",
  "properties": {
    "gn:admin1_code":"04",
    "gn:admin2_code":"405.0",
    "gn:admin3_code":"40508.0",
    "gn:asciiname":"Untergallsbach",
    "gn:country_code":"AT",
    "gn:dem":301,
    "gn:feature_class":"P",
    "gn:feature_code":"PPL",
    "gn:name":"Untergallsbach",
    "gn:population":54,
    "gn:timezone":"Europe/Vienna",
    "iso:country":"AT",
    "wof:name":"Untergallsbach",
    "wof:placetype":"locality",
    "wof:population":54
},
  "geometry": {"coordinates":[13.96195,48.28882],"type":"Point"}
}