{
  "type": "Feature",
  "properties": {
    "gn:admin1_code":"06",
    "gn:admin2_code":"614.0",
    "gn:admin3_code":"61439.0",
    "gn:asciiname":"Vockenberg",
    "gn:country_code":"AT",
    "gn:dem":917,
    "gn:feature_class":"P",
    "gn:feature_code":"PPL",
    "gn:name":"Vockenberg",
    "gn:population":0,
    "gn:timezone":"Europe/Vienna",
    "iso:country":"AT",
    "wof:name":"Vockenberg",
    "wof:placetype":"locality"
},
  "geometry": {"coordinates":[14.38333,47.08333],"type":"Point"}
}