{
  "type": "Feature",
  "properties": {
    "gn:admin1_code":"4.0",
    "gn:admin2_code":"408",
    "gn:admin3_code":"40804.0",
    "gn:asciiname":"Stilzing",
    "gn:country_code":"AT",
    "gn:dem":485,
    "gn:feature_class":"P",
    "gn:feature_code":"PPL",
    "gn:name":"Stilzing",
    "gn:population":29,
    "gn:timezone":"Europe/Vienna",
    "iso:country":"AT",
    "wof:name":"Stilzing",
    "wof:placetype":"locality",
    "wof:population":29
},
  "geometry": {"coordinates":[13.8305,48.39556],"type":"Point"}
}