{
  "type": "Feature",
  "properties": {
    "gn:admin1_code":"03",
    "gn:admin2_code":"322.0",
    "gn:admin3_code":"32219.0",
    "gn:asciiname":"Warnungs",
    "gn:country_code":"AT",
    "gn:dem":548,
    "gn:feature_class":"P",
    "gn:feature_code":"PPL",
    "gn:name":"Warnungs",
    "gn:population":70,
    "gn:timezone":"Europe/Vienna",
    "iso:country":"AT",
    "wof:name":"Warnungs",
    "wof:placetype":"locality",
    "wof:population":70
},
  "geometry": {"coordinates":[15.16336,48.71475],"type":"Point"}
}