{
  "type": "Feature",
  "properties": {
    "gn:admin1_code":"4.0",
    "gn:admin2_code":"417",
    "gn:admin3_code":"41702.0",
    "gn:asciiname":"Erlath",
    "gn:country_code":"AT",
    "gn:dem":489,
    "gn:feature_class":"P",
    "gn:feature_code":"PPL",
    "gn:name":"Erlath",
    "gn:population":0,
    "gn:timezone":"Europe/Vienna",
    "iso:country":"AT",
    "wof:name":"Erlath",
    "wof:placetype":"locality"
},
  "geometry": {"coordinates":[13.52275,47.90392],"type":"Point"}
}