{
  "type": "Feature",
  "properties": {
    "gn:admin1_code":"02",
    "gn:admin2_code":"208.0",
    "gn:admin3_code":"20801.0",
    "gn:asciiname":"Rinkenberg",
    "gn:country_code":"AT",
    "gn:dem":476,
    "gn:feature_class":"P",
    "gn:feature_code":"PPL",
    "gn:name":"Rinkenberg",
    "gn:population":280,
    "gn:timezone":"Europe/Vienna",
    "iso:country":"AT",
    "name:deu_x_preferred":[
        "Rinkenberg"
    ],
    "name:slv_x_preferred":[
        "Vogr\u010de"
    ],
    "wof:name":"Rinkenberg",
    "wof:placetype":"locality",
    "wof:population":280
},
  "geometry": {"coordinates":[14.76583,46.62389],"type":"Point"}
}