{
  "type": "Feature",
  "properties": {
    "gn:admin1_code":"06",
    "gn:admin2_code":"623.0",
    "gn:admin3_code":"62379.0",
    "gn:asciiname":"Kornleiten",
    "gn:country_code":"AT",
    "gn:dem":350,
    "gn:feature_class":"P",
    "gn:feature_code":"PPL",
    "gn:name":"Kornleiten",
    "gn:population":0,
    "gn:timezone":"Europe/Vienna",
    "iso:country":"AT",
    "wof:name":"Kornleiten",
    "wof:placetype":"locality"
},
  "geometry": {"coordinates":[15.93333,46.93333],"type":"Point"}
}