{
  "type": "Feature",
  "properties": {
    "gn:admin1_code":"6.0",
    "gn:admin2_code":"621",
    "gn:admin3_code":"62148.0",
    "gn:asciiname":"Grossdorf",
    "gn:country_code":"AT",
    "gn:dem":869,
    "gn:feature_class":"P",
    "gn:feature_code":"PPL",
    "gn:name":"Grossdorf",
    "gn:population":0,
    "gn:timezone":"Europe/Vienna",
    "iso:country":"AT",
    "wof:name":"Grossdorf",
    "wof:placetype":"locality"
},
  "geometry": {"coordinates":[15.08333,47.51667],"type":"Point"}
}