{
  "type": "Feature",
  "properties": {
    "iso:country":"AT",
    "name:deu_x_preferred":[
        "F\u00f6lling"
    ],
    "name:eng_x_preferred":[
        "Foelling"
    ],
    "wof:name":"Foelling",
    "wof:placetype":"neighbourhood"
},
  "geometry": {"coordinates":[15.49796715639619,47.11388284776526],"type":"Point"}
}