{
  "type": "Feature",
  "properties": {
    "gn:admin1_code":"1.0",
    "gn:admin2_code":"106",
    "gn:admin3_code":"10617.0",
    "gn:asciiname":"Baumgarten im Burgenland",
    "gn:cc2":"AT",
    "gn:country_code":"AT",
    "gn:dem":254,
    "gn:feature_class":"P",
    "gn:feature_code":"PPL",
    "gn:name":"Baumgarten im Burgenland",
    "gn:population":894,
    "gn:timezone":"Europe/Vienna",
    "iso:country":"AT",
    "name:hrv_x_preferred":[
        "Pajngrt"
    ],
    "name:hun_x_preferred":[
        "Sopronkertes"
    ],
    "name:und_x_variant":[
        "Baumgarten",
        "Baumgarten im Burgenland"
    ],
    "wof:name":"Baumgarten im Burgenland",
    "wof:placetype":"locality",
    "wof:population":894
},
  "geometry": {"coordinates":[16.50056,47.73895],"type":"Point"}
}