{
  "type": "Feature",
  "properties": {
    "gn:admin1_code":"4.0",
    "gn:admin2_code":"408",
    "gn:admin3_code":"40811.0",
    "gn:asciiname":"Hof",
    "gn:country_code":"AT",
    "gn:dem":384,
    "gn:feature_class":"P",
    "gn:feature_code":"PPL",
    "gn:name":"Hof",
    "gn:population":47,
    "gn:timezone":"Europe/Vienna",
    "iso:country":"AT",
    "name:afr_x_preferred":[
        "Hof"
    ],
    "name:arg_x_preferred":[
        "Hof"
    ],
    "name:ceb_x_preferred":[
        "Hof"
    ],
    "name:ces_x_preferred":[
        "Hof"
    ],
    "name:dan_x_preferred":[
        "Hof"
    ],
    "name:deu_x_preferred":[
        "Hof"
    ],
    "name:est_x_preferred":[
        "Hof"
    ],
    "name:eus_x_preferred":[
        "Hof"
    ],
    "name:fra_x_preferred":[
        "Hof"
    ],
    "name:fry_x_preferred":[
        "H\u00f4f"
    ],
    "name:hrv_x_preferred":[
        "Hof"
    ],
    "name:hye_x_preferred":[
        "\u0540\u0578\u0586"
    ],
    "name:isl_x_preferred":[
        "Hof"
    ],
    "name:lmo_x_preferred":[
        "Hof"
    ],
    "name:nld_x_preferred":[
        "Hof"
    ],
    "name:nor_x_preferred":[
        "Hof"
    ],
    "name:pol_x_preferred":[
        "Hof"
    ],
    "name:por_x_preferred":[
        "Hof"
    ],
    "name:ron_x_preferred":[
        "Hof"
    ],
    "name:rus_x_preferred":[
        "\u0425\u043e\u0444"
    ],
    "name:spa_x_preferred":[
        "Hof"
    ],
    "name:srp_x_preferred":[
        "\u0425\u043e\u0444"
    ],
    "name:swe_x_preferred":[
        "Hof"
    ],
    "name:vol_x_preferred":[
        "Hof"
    ],
    "wof:name":"Hof",
    "wof:placetype":"locality",
    "wof:population":47
},
  "geometry": {"coordinates":[13.70673,48.23559],"type":"Point"}
}