{
  "type": "Feature",
  "properties": {
    "gn:admin1_code":"4.0",
    "gn:admin2_code":"408",
    "gn:admin3_code":"40811.0",
    "gn:asciiname":"Hof",
    "gn:country_code":"AT",
    "gn:dem":384,
    "gn:feature_class":"P",
    "gn:feature_code":"PPL",
    "gn:name":"Hof",
    "gn:population":47,
    "gn:timezone":"Europe/Vienna",
    "iso:country":"AT",
    "wof:name":"Hof",
    "wof:placetype":"locality",
    "wof:population":47
},
  "geometry": {"coordinates":[13.70673,48.23559],"type":"Point"}
}