{
  "type": "Feature",
  "properties": {
    "gn:admin1_code":"4.0",
    "gn:admin2_code":"417",
    "gn:admin3_code":"41745.0",
    "gn:asciiname":"Zettel-Mittel",
    "gn:country_code":"AT",
    "gn:dem":477,
    "gn:feature_class":"P",
    "gn:feature_code":"PPL",
    "gn:name":"Zettel-Mittel",
    "gn:population":0,
    "gn:timezone":"Europe/Vienna",
    "iso:country":"AT",
    "wof:name":"Zettel-Mittel",
    "wof:placetype":"locality"
},
  "geometry": {"coordinates":[13.50743,47.81632000000001],"type":"Point"}
}