{
  "type": "Feature",
  "properties": {
    "gn:admin1_code":"3.0",
    "gn:admin2_code":"322",
    "gn:admin3_code":"32217.0",
    "gn:asciiname":"Jarolden",
    "gn:country_code":"AT",
    "gn:dem":506,
    "gn:feature_class":"P",
    "gn:feature_code":"PPL",
    "gn:name":"Jarolden",
    "gn:population":86,
    "gn:timezone":"Europe/Vienna",
    "iso:country":"AT",
    "wof:name":"Jarolden",
    "wof:placetype":"locality",
    "wof:population":86
},
  "geometry": {"coordinates":[15.31383,48.83811],"type":"Point"}
}