{
  "type": "Feature",
  "properties": {
    "gn:admin1_code":"03",
    "gn:admin2_code":"301.0",
    "gn:admin3_code":"30101.0",
    "gn:asciiname":"Scheibenhof",
    "gn:country_code":"AT",
    "gn:dem":474,
    "gn:feature_class":"P",
    "gn:feature_code":"PPL",
    "gn:name":"Scheibenhof",
    "gn:population":97,
    "gn:timezone":"Europe/Vienna",
    "iso:country":"AT",
    "wof:name":"Scheibenhof",
    "wof:placetype":"locality",
    "wof:population":97
},
  "geometry": {"coordinates":[15.53333,48.41667],"type":"Point"}
}