{
  "type": "Feature",
  "properties": {
    "gn:admin1_code":"06",
    "gn:admin2_code":"612.0",
    "gn:admin3_code":"61204.0",
    "gn:asciiname":"Posern",
    "gn:country_code":"AT",
    "gn:dem":1020,
    "gn:feature_class":"P",
    "gn:feature_code":"PPL",
    "gn:name":"Posern",
    "gn:population":0,
    "gn:timezone":"Europe/Vienna",
    "iso:country":"AT",
    "wof:name":"Posern",
    "wof:placetype":"locality"
},
  "geometry": {"coordinates":[13.76667,47.65],"type":"Point"}
}