{
  "type": "Feature",
  "properties": {
    "gn:admin1_code":"4.0",
    "gn:admin2_code":"417",
    "gn:admin3_code":"41734.0",
    "gn:asciiname":"Bergham",
    "gn:country_code":"AT",
    "gn:dem":573,
    "gn:feature_class":"P",
    "gn:feature_code":"PPL",
    "gn:name":"Bergham",
    "gn:population":29,
    "gn:timezone":"Europe/Vienna",
    "iso:country":"AT",
    "wof:name":"Bergham",
    "wof:placetype":"locality",
    "wof:population":29
},
  "geometry": {"coordinates":[13.4719,47.91962],"type":"Point"}
}