{
  "type": "Feature",
  "properties": {
    "gn:admin1_code":"4.0",
    "gn:admin2_code":"416",
    "gn:admin3_code":"41604.0",
    "gn:asciiname":"Berndorf",
    "gn:country_code":"AT",
    "gn:dem":700,
    "gn:feature_class":"P",
    "gn:feature_code":"PPL",
    "gn:name":"Berndorf",
    "gn:population":168,
    "gn:timezone":"Europe/Vienna",
    "iso:country":"AT",
    "name:ceb_x_preferred":[
        "Berndorf"
    ],
    "name:deu_x_preferred":[
        "Berndorf"
    ],
    "name:fra_x_preferred":[
        "Berndorf"
    ],
    "name:ita_x_preferred":[
        "Berndorf"
    ],
    "name:nld_x_preferred":[
        "Berndorf"
    ],
    "name:pol_x_preferred":[
        "Berndorf"
    ],
    "name:swe_x_preferred":[
        "Berndorf"
    ],
    "name:vol_x_preferred":[
        "Berndorf"
    ],
    "name:zho_x_preferred":[
        "\u8d1d\u6069\u591a\u592b"
    ],
    "wof:name":"Berndorf",
    "wof:placetype":"locality",
    "wof:population":168
},
  "geometry": {"coordinates":[14.21667,48.43333],"type":"Point"}
}