{
  "type": "Feature",
  "properties": {
    "gn:admin1_code":"3.0",
    "gn:admin2_code":"313",
    "gn:admin3_code":"31324.0",
    "gn:asciiname":"Gloden",
    "gn:country_code":"AT",
    "gn:dem":692,
    "gn:feature_class":"P",
    "gn:feature_code":"PPL",
    "gn:name":"Gloden",
    "gn:population":80,
    "gn:timezone":"Europe/Vienna",
    "iso:country":"AT",
    "wof:name":"Gloden",
    "wof:placetype":"locality",
    "wof:population":80
},
  "geometry": {"coordinates":[15.31133,48.48552],"type":"Point"}
}