{
  "type": "Feature",
  "properties": {
    "gn:admin1_code":"6.0",
    "gn:admin2_code":"621",
    "gn:admin3_code":"62147.0",
    "gn:asciiname":"Edla",
    "gn:country_code":"AT",
    "gn:dem":993,
    "gn:feature_class":"P",
    "gn:feature_code":"PPL",
    "gn:name":"Edla",
    "gn:population":0,
    "gn:timezone":"Europe/Vienna",
    "iso:country":"AT",
    "name:deu_x_preferred":[
        "Edla"
    ],
    "name:nor_x_preferred":[
        "Edla"
    ],
    "name:rus_x_preferred":[
        "\u042d\u0434\u043b\u0430"
    ],
    "name:swe_x_preferred":[
        "Edla"
    ],
    "name:ukr_x_preferred":[
        "\u0415\u0434\u043b\u0430"
    ],
    "wof:name":"Edla",
    "wof:placetype":"locality"
},
  "geometry": {"coordinates":[15.16667,47.53333],"type":"Point"}
}