{
  "type": "Feature",
  "properties": {
    "gn:admin1_code":"01",
    "gn:admin2_code":"109.0",
    "gn:admin3_code":"10916.0",
    "gn:asciiname":"Unterschuetzen",
    "gn:country_code":"AT",
    "gn:dem":321,
    "gn:feature_class":"P",
    "gn:feature_code":"PPL",
    "gn:name":"Untersch\u00fctzen",
    "gn:population":451,
    "gn:timezone":"Europe/Vienna",
    "iso:country":"AT",
    "wof:name":"Unterschuetzen",
    "wof:placetype":"locality",
    "wof:population":451
},
  "geometry": {"coordinates":[16.20372,47.31893],"type":"Point"}
}