{
  "type": "Feature",
  "properties": {
    "gn:admin1_code":"4.0",
    "gn:admin2_code":"408",
    "gn:admin3_code":"40829.0",
    "gn:asciiname":"Damberg",
    "gn:country_code":"AT",
    "gn:dem":400,
    "gn:feature_class":"P",
    "gn:feature_code":"PPL",
    "gn:name":"Damberg",
    "gn:population":11,
    "gn:timezone":"Europe/Vienna",
    "iso:country":"AT",
    "wof:name":"Damberg",
    "wof:placetype":"locality",
    "wof:population":11
},
  "geometry": {"coordinates":[13.70871,48.2664],"type":"Point"}
}