{
  "type": "Feature",
  "properties": {
    "gn:admin1_code":"05",
    "gn:admin2_code":"503.0",
    "gn:admin3_code":"50335.0",
    "gn:asciiname":"Watzlberg",
    "gn:country_code":"AT",
    "gn:dem":642,
    "gn:feature_class":"P",
    "gn:feature_code":"PPL",
    "gn:name":"Watzlberg",
    "gn:population":139,
    "gn:timezone":"Europe/Vienna",
    "iso:country":"AT",
    "wof:name":"Watzlberg",
    "wof:placetype":"locality",
    "wof:population":139
},
  "geometry": {"coordinates":[13.29758,47.99291],"type":"Point"}
}