{
  "type": "Feature",
  "properties": {
    "iso:country":"AT",
    "name:deu_x_preferred":[
        "Auer M\u00fchlbach#Zufl\u00fcsse"
    ],
    "name:deu_x_variant":[
        "Bachl"
    ],
    "qs:gn_adm0_cc":"AT",
    "qs:gn_local":0,
    "qs:gn_nam_loc":"Linz, Linz Stadt, Ober\u00f6sterreich, AT",
    "qs:gn_namadm1":"04",
    "qs:local_max":22933,
    "qs:local_sum":38224,
    "qs:localhoods":15,
    "qs:name":"Bachl",
    "qs:name_adm0":"\u00d6sterreich",
    "qs:name_adm1":"Ober\u00f6sterreich",
    "qs:name_adm2":"Linz Stadt",
    "qs:name_lau":"Linz",
    "qs:name_local":"Linz",
    "qs:photo_max":2,
    "qs:photo_sum":2,
    "qs:placetype":"Suburb",
    "qs:quad_count":1,
    "qs:woe_adm0":23424750,
    "qs:woe_adm1":2344711,
    "qs:woe_adm2":12591722,
    "qs:woe_lau":12674377,
    "qs:woe_local":12674377,
    "qs:woe_ver":"7.10.0",
    "wof:lang":[
        "ger"
    ],
    "wof:name":"Bachl",
    "wof:placetype":"neighbourhood"
},
  "geometry": {"coordinates":[14.27948,48.325214],"type":"Point"}
}