{
  "type": "Feature",
  "properties": {
    "gn:admin1_code":"7.0",
    "gn:admin2_code":"707",
    "gn:admin3_code":"70721.0",
    "gn:asciiname":"Bergen",
    "gn:country_code":"AT",
    "gn:dem":1446,
    "gn:feature_class":"P",
    "gn:feature_code":"PPL",
    "gn:name":"Bergen",
    "gn:population":119,
    "gn:timezone":"Europe/Vienna",
    "iso:country":"AT",
    "wof:name":"Bergen",
    "wof:placetype":"locality",
    "wof:population":119
},
  "geometry": {"coordinates":[12.64361,46.70833],"type":"Point"}
}