{
  "type": "Feature",
  "properties": {
    "gn:admin1_code":"4.0",
    "gn:admin2_code":"417",
    "gn:admin3_code":"41752.0",
    "gn:asciiname":"Gerhardsberg",
    "gn:country_code":"AT",
    "gn:dem":607,
    "gn:feature_class":"P",
    "gn:feature_code":"PPL",
    "gn:name":"Gerhardsberg",
    "gn:population":59,
    "gn:timezone":"Europe/Vienna",
    "iso:country":"AT",
    "wof:name":"Gerhardsberg",
    "wof:placetype":"locality",
    "wof:population":59
},
  "geometry": {"coordinates":[13.62266,48.06928],"type":"Point"}
}