{
  "type": "Feature",
  "properties": {
    "gn:admin1_code":"2.0",
    "gn:admin2_code":"207",
    "gn:admin3_code":"20719.0",
    "gn:asciiname":"Kerschdorf",
    "gn:country_code":"AT",
    "gn:dem":772,
    "gn:feature_class":"P",
    "gn:feature_code":"PPL",
    "gn:name":"Kerschdorf",
    "gn:population":126,
    "gn:timezone":"Europe/Vienna",
    "iso:country":"AT",
    "wof:name":"Kerschdorf",
    "wof:placetype":"locality",
    "wof:population":126
},
  "geometry": {"coordinates":[13.55859,46.61779],"type":"Point"}
}