{
  "type": "Feature",
  "properties": {
    "gn:admin1_code":"6.0",
    "gn:admin2_code":"617",
    "gn:admin3_code":"61701.0",
    "gn:asciiname":"Albersdorf",
    "gn:country_code":"AT",
    "gn:dem":368,
    "gn:feature_class":"P",
    "gn:feature_code":"PPL",
    "gn:name":"Albersdorf",
    "gn:population":1172,
    "gn:timezone":"Europe/Vienna",
    "iso:country":"AT",
    "name:dan_x_preferred":[
        "Albersdorf"
    ],
    "name:deu_x_preferred":[
        "Albersdorf"
    ],
    "name:epo_x_preferred":[
        "Albersdorf"
    ],
    "name:eus_x_preferred":[
        "Albersdorf"
    ],
    "name:fas_x_preferred":[
        "\u0627\u0644\u0628\u0631\u0633\u200c\u062f\u0627\u0631\u0641"
    ],
    "name:fra_x_preferred":[
        "Albersdorf"
    ],
    "name:hun_x_preferred":[
        "Albersdorf"
    ],
    "name:ind_x_preferred":[
        "Albersdorf"
    ],
    "name:ita_x_preferred":[
        "Albersdorf"
    ],
    "name:kaz_x_preferred":[
        "\u0410\u043b\u044c\u0431\u0435\u0440\u0441\u0434\u043e\u0440\u0444"
    ],
    "name:mkd_x_preferred":[
        "\u0410\u043b\u0431\u0435\u0440\u0441\u0434\u043e\u0440\u0444"
    ],
    "name:msa_x_preferred":[
        "Albersdorf"
    ],
    "name:nds_x_preferred":[
        "Albersd\u00f6rp"
    ],
    "name:nld_x_preferred":[
        "Albersdorf"
    ],
    "name:nor_x_preferred":[
        "Albersdorf"
    ],
    "name:pol_x_preferred":[
        "Albersdorf"
    ],
    "name:por_x_preferred":[
        "Albersdorf"
    ],
    "name:ron_x_preferred":[
        "Albersdorf"
    ],
    "name:rus_x_preferred":[
        "\u0410\u043b\u044c\u0431\u0435\u0440\u0441\u0434\u043e\u0440\u0444"
    ],
    "name:spa_x_preferred":[
        "Albersdorf"
    ],
    "name:srp_x_preferred":[
        "\u0410\u043b\u0431\u0435\u0440\u0441\u0434\u043e\u0440\u0444"
    ],
    "name:tur_x_preferred":[
        "Albersdorf"
    ],
    "name:ukr_x_preferred":[
        "\u0410\u043b\u044c\u0431\u0435\u0440\u0441\u0434\u043e\u0440\u0444"
    ],
    "name:uzb_x_preferred":[
        "Albersdorf"
    ],
    "name:vie_x_preferred":[
        "Albersdorf"
    ],
    "name:vol_x_preferred":[
        "Albersdorf"
    ],
    "name:war_x_preferred":[
        "Albersdorf"
    ],
    "name:zho_x_preferred":[
        "\u963f\u5c14\u4f2f\u65af\u591a\u592b"
    ],
    "wof:name":"Albersdorf",
    "wof:placetype":"locality",
    "wof:population":1172
},
  "geometry": {"coordinates":[15.69826,47.12166],"type":"Point"}
}