{
  "type": "Feature",
  "properties": {
    "gn:admin1_code":"6.0",
    "gn:admin2_code":"617",
    "gn:admin3_code":"61701.0",
    "gn:asciiname":"Albersdorf",
    "gn:country_code":"AT",
    "gn:dem":368,
    "gn:feature_class":"P",
    "gn:feature_code":"PPL",
    "gn:name":"Albersdorf",
    "gn:population":1172,
    "gn:timezone":"Europe/Vienna",
    "iso:country":"AT",
    "wof:name":"Albersdorf",
    "wof:placetype":"locality",
    "wof:population":1172
},
  "geometry": {"coordinates":[15.69826,47.12166],"type":"Point"}
}