{
  "type": "Feature",
  "properties": {
    "gn:admin1_code":"6.0",
    "gn:admin2_code":"606",
    "gn:admin3_code":"60663.0",
    "gn:asciiname":"Murhof",
    "gn:country_code":"AT",
    "gn:dem":412,
    "gn:feature_class":"P",
    "gn:feature_code":"PPL",
    "gn:name":"Murhof",
    "gn:population":0,
    "gn:timezone":"Europe/Vienna",
    "iso:country":"AT",
    "wof:name":"Murhof",
    "wof:placetype":"locality"
},
  "geometry": {"coordinates":[15.31667,47.23333],"type":"Point"}
}