{
  "type": "Feature",
  "properties": {
    "gn:gn_country":"AT",
    "gn:gn_fcode":"PPL",
    "gn:gn_pop":0,
    "iso:country":"AT",
    "name:chi_x_preferred":[
        "\u9f50\u8d6b\u8d1d\u683c\u5c71\u9e93\u65bd\u6cf0\u56e0\u8d1d\u683c"
    ],
    "name:dut_x_preferred":[
        "Steinbach am Ziehberg"
    ],
    "name:eng_x_preferred":[
        "Steinbach am Ziehberg"
    ],
    "name:fre_x_preferred":[
        "Steinbach am Ziehberg"
    ],
    "name:ger_x_preferred":[
        "Steinbach am Ziehberg"
    ],
    "name:hun_x_preferred":[
        "Steinbach am Ziehberg"
    ],
    "name:ita_x_preferred":[
        "Steinbach am Ziehberg"
    ],
    "name:kaz_x_preferred":[
        "\u0428\u0442\u0430\u0439\u043d\u0431\u0430\u0445-\u0430\u043c-\u0426\u0438\u0431\u0435\u0440\u0433"
    ],
    "name:pol_x_preferred":[
        "Steinbach am Ziehberg"
    ],
    "name:por_x_preferred":[
        "Steinbach am Ziehberg"
    ],
    "name:rus_x_preferred":[
        "\u0428\u0442\u0430\u0439\u043d\u0431\u0430\u0445-\u0430\u043c-\u0426\u0438\u0431\u0435\u0440\u0433"
    ],
    "name:slo_x_preferred":[
        "Steinbach am Ziehberg"
    ],
    "name:swe_x_preferred":[
        "Steinbach am Ziehberg"
    ],
    "name:unk_x_variant":[
        "Steinbach"
    ],
    "name:uzb_x_preferred":[
        "Steinbach am Ziehberg"
    ],
    "name:vie_x_preferred":[
        "Steinbach am Ziehberg"
    ],
    "name:vol_x_preferred":[
        "Steinbach am Ziehberg"
    ],
    "name:war_x_preferred":[
        "Steinbach am Ziehberg"
    ],
    "qs_pg:aaroncc":"AT",
    "qs_pg:gn_country":"AT",
    "qs_pg:gn_fcode":"PPL",
    "qs_pg:gn_pop":0,
    "qs_pg:name":"Steinbach am Ziehberg",
    "qs_pg:name_adm0":"\u00d6sterreich",
    "qs_pg:name_adm1":"Ober\u00f6sterreich",
    "qs_pg:photos":29,
    "qs_pg:photos_1k":6,
    "qs_pg:photos_9k":1,
    "qs_pg:photos_9r":2,
    "qs_pg:photos_all":29,
    "qs_pg:photos_sr":2,
    "qs_pg:pop_sr":0,
    "qs_pg:qs_pg_placetype":"locality",
    "qs_pg:qs_pg_placetype_gp":"Town",
    "qs_pg:woe_adm0":23424750,
    "woe:adm0_id":23424750,
    "woe:name_adm0":"\u00d6sterreich",
    "woe:name_adm1":"Ober\u00f6sterreich",
    "woe:placetype":"Town",
    "wof:name":"Steinbach am Ziehberg",
    "wof:placetype":"locality"
},
  "geometry": {"coordinates":[14.0304,47.89264],"type":"Point"}
}