{
  "type": "Feature",
  "properties": {
    "gn:admin1_code":"6.0",
    "gn:admin2_code":"612",
    "gn:admin3_code":"61257.0",
    "gn:asciiname":"Erlsberg",
    "gn:country_code":"AT",
    "gn:dem":850,
    "gn:feature_class":"P",
    "gn:feature_code":"PPL",
    "gn:name":"Erlsberg",
    "gn:population":336,
    "gn:timezone":"Europe/Vienna",
    "iso:country":"AT",
    "wof:name":"Erlsberg",
    "wof:placetype":"locality",
    "wof:population":336
},
  "geometry": {"coordinates":[14.13333,47.46667],"type":"Point"}
}