{
  "type": "Feature",
  "properties": {
    "gn:admin1_code":"04",
    "gn:admin2_code":"413.0",
    "gn:admin3_code":"41305.0",
    "gn:asciiname":"Wippling",
    "gn:country_code":"AT",
    "gn:dem":576,
    "gn:feature_class":"P",
    "gn:feature_code":"PPL",
    "gn:name":"Wippling",
    "gn:population":63,
    "gn:timezone":"Europe/Vienna",
    "iso:country":"AT",
    "wof:name":"Wippling",
    "wof:placetype":"locality",
    "wof:population":63
},
  "geometry": {"coordinates":[14.02722,48.53315],"type":"Point"}
}