{
  "type": "Feature",
  "properties": {
    "gn:admin1_code":"5.0",
    "gn:admin2_code":"506",
    "gn:admin3_code":"50601.0",
    "gn:asciiname":"Muehlberg",
    "gn:country_code":"AT",
    "gn:dem":1032,
    "gn:feature_class":"P",
    "gn:feature_code":"PPL",
    "gn:name":"M\u00fchlberg",
    "gn:population":53,
    "gn:timezone":"Europe/Vienna",
    "iso:country":"AT",
    "wof:name":"Muehlberg",
    "wof:placetype":"locality",
    "wof:population":53
},
  "geometry": {"coordinates":[12.36667,47.28333],"type":"Point"}
}