{
  "type": "Feature",
  "properties": {
    "iso:country":"AT",
    "name:deu_x_preferred":[
        "Unter Andritz"
    ],
    "qs:gn_adm0_cc":"AT",
    "qs:gn_fcode":"PPLX",
    "qs:gn_local":7871499,
    "qs:gn_nam_loc":"Graz, Graz Stadt, Steiermark, AT",
    "qs:gn_namadm1":"06",
    "qs:gn_name":"Unter Andritz",
    "qs:local_max":3393,
    "qs:local_sum":13910,
    "qs:localhoods":22,
    "qs:name":"Unter Andritz",
    "qs:name_adm0":"\u00d6sterreich",
    "qs:name_adm1":"Steiermark",
    "qs:name_adm2":"Graz Stadt",
    "qs:name_lau":"Graz",
    "qs:name_local":"Graz",
    "qs:photo_max":244,
    "qs:photo_sum":480,
    "qs:placetype":"Suburb",
    "qs:quad_count":25,
    "qs:woe_adm0":23424750,
    "qs:woe_adm1":2344713,
    "qs:woe_adm2":12591740,
    "qs:woe_lau":12674996,
    "qs:woe_local":12674996,
    "qs:woe_ver":"7.10.0",
    "wof:lang":[
        "ger"
    ],
    "wof:name":"Unter Andritz",
    "wof:placetype":"neighbourhood"
},
  "geometry": {"coordinates":[15.412334,47.096632],"type":"Point"}
}