{
  "type": "Feature",
  "properties": {
    "gn:admin1_code":"3.0",
    "gn:admin2_code":"322",
    "gn:admin3_code":"32214.0",
    "gn:asciiname":"Arnolz",
    "gn:country_code":"AT",
    "gn:dem":522,
    "gn:feature_class":"P",
    "gn:feature_code":"PPL",
    "gn:name":"Arnolz",
    "gn:population":71,
    "gn:timezone":"Europe/Vienna",
    "iso:country":"AT",
    "wof:name":"Arnolz",
    "wof:placetype":"locality",
    "wof:population":71
},
  "geometry": {"coordinates":[15.21667,48.85],"type":"Point"}
}