{
  "type": "Feature",
  "properties": {
    "gn:admin1_code":"7.0",
    "gn:admin2_code":"703",
    "gn:admin3_code":"70333.0",
    "gn:asciiname":"Muehlen",
    "gn:country_code":"AT",
    "gn:dem":1107,
    "gn:feature_class":"P",
    "gn:feature_code":"PPL",
    "gn:name":"M\u00fchlen",
    "gn:population":0,
    "gn:timezone":"Europe/Vienna",
    "iso:country":"AT",
    "wof:name":"Muehlen",
    "wof:placetype":"locality"
},
  "geometry": {"coordinates":[11.46667,47.11667],"type":"Point"}
}