{
  "type": "Feature",
  "properties": {
    "iso:country":"AT",
    "name:deu_x_preferred":[
        "Jakomini"
    ],
    "name:eng_x_preferred":[
        "Jakomini"
    ],
    "wof:name":"Jakomini",
    "wof:placetype":"neighbourhood"
},
  "geometry": {"coordinates":[15.4446563129322,47.06049578711488],"type":"Point"}
}