{
  "type": "Feature",
  "properties": {
    "gn:admin1_code":"4.0",
    "gn:admin2_code":"408",
    "gn:admin3_code":"40824.0",
    "gn:asciiname":"Hoelzing",
    "gn:country_code":"AT",
    "gn:dem":552,
    "gn:feature_class":"P",
    "gn:feature_code":"PPL",
    "gn:name":"H\u00f6lzing",
    "gn:population":77,
    "gn:timezone":"Europe/Vienna",
    "iso:country":"AT",
    "wof:name":"Hoelzing",
    "wof:placetype":"locality",
    "wof:population":77
},
  "geometry": {"coordinates":[13.83784,48.40562],"type":"Point"}
}