{
  "type": "Feature",
  "properties": {
    "gn:admin1_code":"2.0",
    "gn:admin2_code":"206",
    "gn:admin3_code":"20613.0",
    "gn:asciiname":"Gajach",
    "gn:country_code":"AT",
    "gn:dem":573,
    "gn:feature_class":"P",
    "gn:feature_code":"PPL",
    "gn:name":"Gajach",
    "gn:population":0,
    "gn:timezone":"Europe/Vienna",
    "iso:country":"AT",
    "wof:name":"Gajach",
    "wof:placetype":"locality"
},
  "geometry": {"coordinates":[13.29194,46.75444],"type":"Point"}
}