{
  "type": "Feature",
  "properties": {
    "gn:admin1_code":"6.0",
    "gn:admin2_code":"622",
    "gn:admin3_code":"62235.0",
    "gn:asciiname":"Oberneuberg",
    "gn:country_code":"AT",
    "gn:dem":632,
    "gn:feature_class":"P",
    "gn:feature_code":"PPL",
    "gn:name":"Oberneuberg",
    "gn:population":769,
    "gn:timezone":"Europe/Vienna",
    "iso:country":"AT",
    "wof:name":"Oberneuberg",
    "wof:placetype":"locality",
    "wof:population":769
},
  "geometry": {"coordinates":[15.86667,47.31667],"type":"Point"}
}