{
  "type": "Feature",
  "properties": {
    "gn:admin1_code":"03",
    "gn:admin2_code":"320.0",
    "gn:admin3_code":"32007.0",
    "gn:asciiname":"Sulzbichl",
    "gn:cc2":"AT",
    "gn:country_code":"AT",
    "gn:dem":772,
    "gn:feature_class":"P",
    "gn:feature_code":"PPL",
    "gn:name":"Sulzbichl",
    "gn:population":15,
    "gn:timezone":"Europe/Vienna",
    "iso:country":"AT",
    "name:und_x_variant":[
        "Am Sulzbichl",
        "Sulzbichl"
    ],
    "wof:name":"Sulzbichl",
    "wof:placetype":"locality",
    "wof:population":15
},
  "geometry": {"coordinates":[15.25,47.91667],"type":"Point"}
}