{
  "type": "Feature",
  "properties": {
    "gn:admin1_code":"4.0",
    "gn:admin2_code":"404",
    "gn:admin3_code":"40434.0",
    "gn:asciiname":"Schiefeck",
    "gn:country_code":"AT",
    "gn:dem":449,
    "gn:feature_class":"P",
    "gn:feature_code":"PPL",
    "gn:name":"Schiefeck",
    "gn:population":24,
    "gn:timezone":"Europe/Vienna",
    "iso:country":"AT",
    "wof:name":"Schiefeck",
    "wof:placetype":"locality",
    "wof:population":24
},
  "geometry": {"coordinates":[13.2214,48.1963],"type":"Point"}
}