{
  "type": "Feature",
  "properties": {
    "gn:admin1_code":"05",
    "gn:admin2_code":"506.0",
    "gn:admin3_code":"50605.0",
    "gn:asciiname":"Reitlehen",
    "gn:country_code":"AT",
    "gn:dem":898,
    "gn:feature_class":"P",
    "gn:feature_code":"PPL",
    "gn:name":"Reitlehen",
    "gn:population":461,
    "gn:timezone":"Europe/Vienna",
    "iso:country":"AT",
    "wof:name":"Reitlehen",
    "wof:placetype":"locality",
    "wof:population":461
},
  "geometry": {"coordinates":[12.41667,47.26667],"type":"Point"}
}