{
  "type": "Feature",
  "properties": {
    "gn:admin1_code":"6.0",
    "gn:admin2_code":"611",
    "gn:admin3_code":"61119.0",
    "gn:asciiname":"Liesing",
    "gn:country_code":"AT",
    "gn:dem":1043,
    "gn:feature_class":"P",
    "gn:feature_code":"PPL",
    "gn:name":"Liesing",
    "gn:population":19,
    "gn:timezone":"Europe/Vienna",
    "iso:country":"AT",
    "wof:name":"Liesing",
    "wof:placetype":"locality",
    "wof:population":19
},
  "geometry": {"coordinates":[14.65,47.41667],"type":"Point"}
}