{
  "type": "Feature",
  "properties": {
    "gn:admin1_code":"4.0",
    "gn:admin2_code":"408",
    "gn:admin3_code":"40808.0",
    "gn:asciiname":"Moosham",
    "gn:country_code":"AT",
    "gn:dem":346,
    "gn:feature_class":"P",
    "gn:feature_code":"PPL",
    "gn:name":"Moosham",
    "gn:population":96,
    "gn:timezone":"Europe/Vienna",
    "iso:country":"AT",
    "wof:name":"Moosham",
    "wof:placetype":"locality",
    "wof:population":96
},
  "geometry": {"coordinates":[13.80775,48.23262],"type":"Point"}
}