{
  "type": "Feature",
  "properties": {
    "gn:admin1_code":"6.0",
    "gn:admin2_code":"601",
    "gn:admin3_code":"60101.0",
    "gn:asciiname":"Gartenstadt",
    "gn:country_code":"AT",
    "gn:dem":353,
    "gn:feature_class":"P",
    "gn:feature_code":"PPL",
    "gn:name":"Gartenstadt",
    "gn:population":0,
    "gn:timezone":"Europe/Vienna",
    "iso:country":"AT",
    "wof:name":"Gartenstadt",
    "wof:placetype":"locality"
},
  "geometry": {"coordinates":[15.46667,47.05],"type":"Point"}
}