{
  "type": "Feature",
  "properties": {
    "gn:admin1_code":"6.0",
    "gn:admin2_code":"612",
    "gn:admin3_code":"61213.0",
    "gn:asciiname":"Winkl",
    "gn:country_code":"AT",
    "gn:dem":807,
    "gn:feature_class":"P",
    "gn:feature_code":"PPL",
    "gn:name":"Winkl",
    "gn:population":0,
    "gn:timezone":"Europe/Vienna",
    "iso:country":"AT",
    "wof:name":"Winkl",
    "wof:placetype":"locality"
},
  "geometry": {"coordinates":[13.87611,47.44667000000001],"type":"Point"}
}