{
  "type": "Feature",
  "properties": {
    "gn:admin1_code":"2.0",
    "gn:admin2_code":"205",
    "gn:admin3_code":"20501.0",
    "gn:asciiname":"Muraniberg",
    "gn:country_code":"AT",
    "gn:dem":816,
    "gn:feature_class":"P",
    "gn:feature_code":"PPL",
    "gn:name":"Muraniberg",
    "gn:population":10,
    "gn:timezone":"Europe/Vienna",
    "iso:country":"AT",
    "wof:name":"Muraniberg",
    "wof:placetype":"locality",
    "wof:population":10
},
  "geometry": {"coordinates":[14.4599,46.8968],"type":"Point"}
}