{
  "type": "Feature",
  "properties": {
    "gn:admin1_code":"3.0",
    "gn:admin2_code":"310",
    "gn:admin3_code":"31008.0",
    "gn:asciiname":"Oberparschenbrunn",
    "gn:country_code":"AT",
    "gn:dem":258,
    "gn:feature_class":"P",
    "gn:feature_code":"PPL",
    "gn:name":"Oberparschenbrunn",
    "gn:population":95,
    "gn:timezone":"Europe/Vienna",
    "iso:country":"AT",
    "wof:name":"Oberparschenbrunn",
    "wof:placetype":"locality",
    "wof:population":95
},
  "geometry": {"coordinates":[16.09464,48.4718],"type":"Point"}
}