{
  "type": "Feature",
  "properties": {
    "gn:admin1_code":"06",
    "gn:admin2_code":"623.0",
    "gn:admin3_code":"62390.0",
    "gn:asciiname":"Unterkarla",
    "gn:country_code":"AT",
    "gn:dem":259,
    "gn:feature_class":"P",
    "gn:feature_code":"PPL",
    "gn:name":"Unterkarla",
    "gn:population":0,
    "gn:timezone":"Europe/Vienna",
    "iso:country":"AT",
    "wof:name":"Unterkarla",
    "wof:placetype":"locality"
},
  "geometry": {"coordinates":[15.88333,46.78333],"type":"Point"}
}