{
  "type": "Feature",
  "properties": {
    "gn:admin1_code":"02",
    "gn:admin2_code":"208.0",
    "gn:admin3_code":"20806.0",
    "gn:asciiname":"Robesch",
    "gn:country_code":"AT",
    "gn:dem":692,
    "gn:feature_class":"P",
    "gn:feature_code":"PPL",
    "gn:name":"Robesch",
    "gn:population":35,
    "gn:timezone":"Europe/Vienna",
    "iso:country":"AT",
    "wof:name":"Robesch",
    "wof:placetype":"locality",
    "wof:population":35
},
  "geometry": {"coordinates":[14.48333,46.55],"type":"Point"}
}