{
  "type": "Feature",
  "properties": {
    "gn:admin1_code":"6.0",
    "gn:admin2_code":"623",
    "gn:admin3_code":"62335.0",
    "gn:asciiname":"Deutsch Haseldorf",
    "gn:country_code":"AT",
    "gn:dem":327,
    "gn:feature_class":"P",
    "gn:feature_code":"PPL",
    "gn:name":"Deutsch Haseldorf",
    "gn:population":188,
    "gn:timezone":"Europe/Vienna",
    "iso:country":"AT",
    "wof:name":"Deutsch Haseldorf",
    "wof:placetype":"locality",
    "wof:population":188
},
  "geometry": {"coordinates":[15.97528,46.78472],"type":"Point"}
}