{
  "type": "Feature",
  "properties": {
    "gn:admin1_code":"4.0",
    "gn:admin2_code":"406",
    "gn:admin3_code":"40612.0",
    "gn:asciiname":"Au",
    "gn:country_code":"AT",
    "gn:dem":637,
    "gn:feature_class":"P",
    "gn:feature_code":"PPL",
    "gn:name":"Au",
    "gn:population":120,
    "gn:timezone":"Europe/Vienna",
    "iso:country":"AT",
    "name:cat_x_preferred":[
        "Au"
    ],
    "name:est_x_preferred":[
        "Au"
    ],
    "name:hun_x_preferred":[
        "Au"
    ],
    "wof:name":"Au",
    "wof:placetype":"locality",
    "wof:population":120
},
  "geometry": {"coordinates":[14.51002,48.41057],"type":"Point"}
}