{
  "type": "Feature",
  "properties": {
    "gn:admin1_code":"08",
    "gn:admin2_code":"802.0",
    "gn:admin3_code":"80221.0",
    "gn:asciiname":"Zwing",
    "gn:country_code":"AT",
    "gn:dem":669,
    "gn:feature_class":"P",
    "gn:feature_code":"PPL",
    "gn:name":"Zwing",
    "gn:population":0,
    "gn:timezone":"Europe/Vienna",
    "iso:country":"AT",
    "wof:name":"Zwing",
    "wof:placetype":"locality"
},
  "geometry": {"coordinates":[9.92806,47.49528],"type":"Point"}
}