{
  "type": "Feature",
  "properties": {
    "gn:admin1_code":"06",
    "gn:admin2_code":"616.0",
    "gn:admin3_code":"61626.0",
    "gn:asciiname":"Tregist",
    "gn:country_code":"AT",
    "gn:dem":595,
    "gn:feature_class":"P",
    "gn:feature_code":"PPL",
    "gn:name":"Tregist",
    "gn:population":0,
    "gn:timezone":"Europe/Vienna",
    "iso:country":"AT",
    "wof:name":"Tregist",
    "wof:placetype":"locality"
},
  "geometry": {"coordinates":[15.15,47.08333],"type":"Point"}
}