{
  "type": "Feature",
  "properties": {
    "gn:admin1_code":"6.0",
    "gn:admin2_code":"621",
    "gn:admin3_code":"62144.0",
    "gn:asciiname":"Altenberg",
    "gn:country_code":"AT",
    "gn:dem":851,
    "gn:feature_class":"P",
    "gn:feature_code":"PPL",
    "gn:name":"Altenberg",
    "gn:population":253,
    "gn:timezone":"Europe/Vienna",
    "iso:country":"AT",
    "name:bos_x_preferred":[
        "Altenberg"
    ],
    "name:ceb_x_preferred":[
        "Altenberg"
    ],
    "name:ces_x_preferred":[
        "Altenberg"
    ],
    "name:deu_x_preferred":[
        "Altenberg"
    ],
    "name:fra_x_preferred":[
        "Altenberg"
    ],
    "name:hsb_x_preferred":[
        "Altenberg"
    ],
    "name:ita_x_preferred":[
        "Altenberg"
    ],
    "name:nld_x_preferred":[
        "Altenberg"
    ],
    "name:pol_x_preferred":[
        "Altenberg"
    ],
    "name:ron_x_preferred":[
        "Altenberg"
    ],
    "name:rus_x_preferred":[
        "\u0410\u043b\u044c\u0442\u0435\u043d\u0431\u0435\u0440\u0433"
    ],
    "name:spa_x_preferred":[
        "Altenberg"
    ],
    "name:swe_x_preferred":[
        "Altenberg"
    ],
    "name:ukr_x_preferred":[
        "\u0410\u043b\u044c\u0442\u0435\u043d\u0431\u0435\u0440\u0491"
    ],
    "wof:name":"Altenberg",
    "wof:placetype":"locality",
    "wof:population":253
},
  "geometry": {"coordinates":[15.65,47.68333],"type":"Point"}
}