{
  "type": "Feature",
  "properties": {
    "gn:admin1_code":"6.0",
    "gn:admin2_code":"621",
    "gn:admin3_code":"62144.0",
    "gn:asciiname":"Altenberg",
    "gn:country_code":"AT",
    "gn:dem":851,
    "gn:feature_class":"P",
    "gn:feature_code":"PPL",
    "gn:name":"Altenberg",
    "gn:population":253,
    "gn:timezone":"Europe/Vienna",
    "iso:country":"AT",
    "wof:name":"Altenberg",
    "wof:placetype":"locality",
    "wof:population":253
},
  "geometry": {"coordinates":[15.65,47.68333],"type":"Point"}
}