{
  "type": "Feature",
  "properties": {
    "gn:admin1_code":"4.0",
    "gn:admin2_code":"418",
    "gn:admin3_code":"41817.0",
    "gn:asciiname":"Dirnberg",
    "gn:country_code":"AT",
    "gn:dem":423,
    "gn:feature_class":"P",
    "gn:feature_code":"PPL",
    "gn:name":"Dirnberg",
    "gn:population":12,
    "gn:timezone":"Europe/Vienna",
    "iso:country":"AT",
    "wof:name":"Dirnberg",
    "wof:placetype":"locality",
    "wof:population":12
},
  "geometry": {"coordinates":[14.07452,48.05456],"type":"Point"}
}