{
  "type": "Feature",
  "properties": {
    "gn:admin1_code":"6.0",
    "gn:admin2_code":"623",
    "gn:admin3_code":"62380.0",
    "gn:asciiname":"Krusdorf",
    "gn:country_code":"AT",
    "gn:dem":272,
    "gn:feature_class":"P",
    "gn:feature_code":"PPLA3",
    "gn:name":"Krusdorf",
    "gn:population":0,
    "gn:timezone":"Europe/Vienna",
    "iso:country":"AT",
    "name:ceb_x_preferred":[
        "Krusdorf"
    ],
    "name:deu_x_preferred":[
        "Krusdorf"
    ],
    "name:fas_x_preferred":[
        "\u06a9\u0631\u0648\u0633\u062f\u0648\u0631\u0641"
    ],
    "name:fra_x_preferred":[
        "Krusdorf"
    ],
    "name:ita_x_preferred":[
        "Krusdorf"
    ],
    "name:nld_x_preferred":[
        "Krusdorf"
    ],
    "name:rus_x_preferred":[
        "\u041a\u0440\u0443\u0441\u0434\u043e\u0440\u0444"
    ],
    "name:slk_x_preferred":[
        "Krusdorf"
    ],
    "name:swe_x_preferred":[
        "Krusdorf"
    ],
    "name:uzb_x_preferred":[
        "Krusdorf"
    ],
    "name:vie_x_preferred":[
        "Krusdorf"
    ],
    "name:vol_x_preferred":[
        "Krusdorf"
    ],
    "name:war_x_preferred":[
        "Krusdorf"
    ],
    "name:zho_x_preferred":[
        "\u514b\u9c81\u65af\u591a\u592b"
    ],
    "wof:name":"Krusdorf",
    "wof:placetype":"locality"
},
  "geometry": {"coordinates":[15.86083,46.83944],"type":"Point"}
}