{
  "type": "Feature",
  "properties": {
    "gn:admin1_code":"6.0",
    "gn:admin2_code":"623",
    "gn:admin3_code":"62380.0",
    "gn:asciiname":"Krusdorf",
    "gn:country_code":"AT",
    "gn:dem":272,
    "gn:feature_class":"P",
    "gn:feature_code":"PPLA3",
    "gn:name":"Krusdorf",
    "gn:population":0,
    "gn:timezone":"Europe/Vienna",
    "iso:country":"AT",
    "wof:name":"Krusdorf",
    "wof:placetype":"locality"
},
  "geometry": {"coordinates":[15.86083,46.83944],"type":"Point"}
}