{
  "type": "Feature",
  "properties": {
    "gn:admin1_code":"04",
    "gn:admin2_code":"407.0",
    "gn:admin3_code":"40720.0",
    "gn:asciiname":"Theuerwang",
    "gn:country_code":"AT",
    "gn:dem":428,
    "gn:feature_class":"P",
    "gn:feature_code":"PPL",
    "gn:name":"Theuerwang",
    "gn:population":0,
    "gn:timezone":"Europe/Vienna",
    "iso:country":"AT",
    "wof:name":"Theuerwang",
    "wof:placetype":"locality"
},
  "geometry": {"coordinates":[13.94577,47.99452],"type":"Point"}
}