{
  "type": "Feature",
  "properties": {
    "gn:admin1_code":"6.0",
    "gn:admin2_code":"610",
    "gn:admin3_code":"61057.0",
    "gn:asciiname":"Breitenfeld am Tannenriegel",
    "gn:country_code":"AT",
    "gn:dem":308,
    "gn:feature_class":"P",
    "gn:feature_code":"PPLA3",
    "gn:name":"Breitenfeld am Tannenriegel",
    "gn:population":183,
    "gn:timezone":"Europe/Vienna",
    "iso:country":"AT",
    "name:ceb_x_preferred":[
        "Breitenfeld am Tannenriegel"
    ],
    "name:deu_x_preferred":[
        "Breitenfeld am Tannenriegel"
    ],
    "name:fas_x_preferred":[
        "\u0628\u0631\u0627\u06cc\u062a\u0646\u0641\u0644\u062f \u0627\u0645 \u062a\u0627\u0646\u0646\u0631\u06cc\u06af\u0644"
    ],
    "name:fra_x_preferred":[
        "Breitenfeld am Tannenriegel"
    ],
    "name:ita_x_preferred":[
        "Breitenfeld am Tannenriegel"
    ],
    "name:kaz_x_preferred":[
        "\u0411\u0440\u0430\u0439\u0442\u0435\u043d\u0444\u0435\u043b\u044c\u0434-\u0430\u043c-\u0422\u0430\u043d\u043d\u0435\u043d\u0440\u0438\u0433\u0435\u043b\u044c"
    ],
    "name:nld_x_preferred":[
        "Breitenfeld am Tannenriegel"
    ],
    "name:rus_x_preferred":[
        "\u0411\u0440\u0430\u0439\u0442\u0435\u043d\u0444\u0435\u043b\u044c\u0434-\u0430\u043c-\u0422\u0430\u043d\u043d\u0435\u043d\u0440\u0438\u0433\u0435\u043b\u044c"
    ],
    "name:slk_x_preferred":[
        "Breitenfeld am Tannenriegel"
    ],
    "name:swe_x_preferred":[
        "Breitenfeld am Tannenriegel"
    ],
    "name:und_x_variant":[
        "Breitenfeld",
        "Breitenfeld am Tannenriegel"
    ],
    "name:uzb_x_preferred":[
        "Breitenfeld am Tannenriegel"
    ],
    "name:vie_x_preferred":[
        "Breitenfeld am Tannenriegel"
    ],
    "name:vol_x_preferred":[
        "Breitenfeld am Tannenriegel"
    ],
    "name:war_x_preferred":[
        "Breitenfeld am Tannenriegel"
    ],
    "name:zho_x_preferred":[
        "\u5e03\u96f7\u6ed5\u8d39\u5c14\u5fb7\u963f\u59c6\u5766\u5ae9\u91cc\u683c\u5c14"
    ],
    "wof:name":"Breitenfeld am Tannenriegel",
    "wof:placetype":"locality",
    "wof:population":183
},
  "geometry": {"coordinates":[15.63333,46.85],"type":"Point"}
}