{
  "type": "Feature",
  "properties": {
    "gn:admin1_code":"6.0",
    "gn:admin2_code":"610",
    "gn:admin3_code":"61057.0",
    "gn:asciiname":"Breitenfeld am Tannenriegel",
    "gn:country_code":"AT",
    "gn:dem":308,
    "gn:feature_class":"P",
    "gn:feature_code":"PPLA3",
    "gn:name":"Breitenfeld am Tannenriegel",
    "gn:population":183,
    "gn:timezone":"Europe/Vienna",
    "iso:country":"AT",
    "name:und_x_variant":[
        "Breitenfeld",
        "Breitenfeld am Tannenriegel"
    ],
    "wof:name":"Breitenfeld am Tannenriegel",
    "wof:placetype":"locality",
    "wof:population":183
},
  "geometry": {"coordinates":[15.63333,46.85],"type":"Point"}
}