{
  "type": "Feature",
  "properties": {
    "gn:admin1_code":"03",
    "gn:admin2_code":"321.0",
    "gn:admin3_code":"32110.0",
    "gn:asciiname":"Ruppersthal",
    "gn:country_code":"AT",
    "gn:dem":242,
    "gn:feature_class":"P",
    "gn:feature_code":"PPL",
    "gn:name":"Ruppersthal",
    "gn:population":416,
    "gn:timezone":"Europe/Vienna",
    "iso:country":"AT",
    "wof:name":"Ruppersthal",
    "wof:placetype":"locality",
    "wof:population":416
},
  "geometry": {"coordinates":[15.93333,48.45],"type":"Point"}
}