{
  "type": "Feature",
  "properties": {
    "gn:admin1_code":"4.0",
    "gn:admin2_code":"416",
    "gn:admin3_code":"41609.0",
    "gn:asciiname":"Tuerkstetten",
    "gn:country_code":"AT",
    "gn:dem":555,
    "gn:feature_class":"P",
    "gn:feature_code":"PPL",
    "gn:name":"T\u00fcrkstetten",
    "gn:population":511,
    "gn:timezone":"Europe/Vienna",
    "iso:country":"AT",
    "wof:name":"Tuerkstetten",
    "wof:placetype":"locality",
    "wof:population":511
},
  "geometry": {"coordinates":[14.21142,48.36942],"type":"Point"}
}