{
  "type": "Feature",
  "properties": {
    "gn:admin1_code":"3.0",
    "gn:admin2_code":"316",
    "gn:admin3_code":"31633.0",
    "gn:asciiname":"Fraettingsdorf",
    "gn:country_code":"AT",
    "gn:dem":255,
    "gn:feature_class":"P",
    "gn:feature_code":"PPL",
    "gn:name":"Fr\u00e4ttingsdorf",
    "gn:population":272,
    "gn:timezone":"Europe/Vienna",
    "iso:country":"AT",
    "wof:name":"Fraettingsdorf",
    "wof:placetype":"locality",
    "wof:population":272
},
  "geometry": {"coordinates":[16.51667,48.63333],"type":"Point"}
}