{
  "type": "Feature",
  "properties": {
    "gn:admin1_code":"6.0",
    "gn:admin2_code":"620",
    "gn:admin3_code":"62040.0",
    "gn:asciiname":"Passhammer",
    "gn:country_code":"AT",
    "gn:dem":754,
    "gn:feature_class":"P",
    "gn:feature_code":"PPL",
    "gn:name":"Pa\u00dfhammer",
    "gn:population":0,
    "gn:timezone":"Europe/Vienna",
    "iso:country":"AT",
    "wof:name":"Passhammer",
    "wof:placetype":"locality"
},
  "geometry": {"coordinates":[14.62718,47.20628],"type":"Point"}
}