{
  "type": "Feature",
  "properties": {
    "gn:admin1_code":"4.0",
    "gn:admin2_code":"408",
    "gn:admin3_code":"40829.0",
    "gn:asciiname":"Hehenberg",
    "gn:country_code":"AT",
    "gn:dem":395,
    "gn:feature_class":"P",
    "gn:feature_code":"PPL",
    "gn:name":"Hehenberg",
    "gn:population":109,
    "gn:timezone":"Europe/Vienna",
    "iso:country":"AT",
    "wof:name":"Hehenberg",
    "wof:placetype":"locality",
    "wof:population":109
},
  "geometry": {"coordinates":[13.70562,48.24371],"type":"Point"}
}