{
  "type": "Feature",
  "properties": {
    "gn:admin1_code":"1.0",
    "gn:admin2_code":"108",
    "gn:admin3_code":"10823.0",
    "gn:asciiname":"Kalkgruben",
    "gn:country_code":"AT",
    "gn:dem":369,
    "gn:feature_class":"P",
    "gn:feature_code":"PPL",
    "gn:name":"Kalkgruben",
    "gn:population":349,
    "gn:timezone":"Europe/Vienna",
    "iso:country":"AT",
    "name:hun_x_preferred":[
        "M\u00e9szverem"
    ],
    "wof:name":"Kalkgruben",
    "wof:placetype":"locality",
    "wof:population":349
},
  "geometry": {"coordinates":[16.39606,47.62109],"type":"Point"}
}