{
  "type": "Feature",
  "properties": {
    "gn:admin1_code":"04",
    "gn:admin2_code":"413.0",
    "gn:admin3_code":"41332.0",
    "gn:asciiname":"Ritzersdorf",
    "gn:country_code":"AT",
    "gn:dem":557,
    "gn:feature_class":"P",
    "gn:feature_code":"PPL",
    "gn:name":"Ritzersdorf",
    "gn:population":176,
    "gn:timezone":"Europe/Vienna",
    "iso:country":"AT",
    "wof:name":"Ritzersdorf",
    "wof:placetype":"locality",
    "wof:population":176
},
  "geometry": {"coordinates":[14.02421,48.433],"type":"Point"}
}