{
  "type": "Feature",
  "properties": {
    "gn:admin1_code":"06",
    "gn:admin2_code":"612.0",
    "gn:admin3_code":"61267.0",
    "gn:asciiname":"Rantenstein",
    "gn:country_code":"AT",
    "gn:dem":970,
    "gn:feature_class":"P",
    "gn:feature_code":"PPLL",
    "gn:name":"Rantenstein",
    "gn:population":0,
    "gn:timezone":"Europe/Vienna",
    "iso:country":"AT",
    "wof:name":"Rantenstein",
    "wof:placetype":"locality"
},
  "geometry": {"coordinates":[14.08333,47.53333],"type":"Point"}
}