{
  "type": "Feature",
  "properties": {
    "gn:admin1_code":"2.0",
    "gn:admin2_code":"210",
    "gn:admin3_code":"21001.0",
    "gn:asciiname":"Hochrindl-Kegel",
    "gn:country_code":"AT",
    "gn:dem":1520,
    "gn:feature_class":"P",
    "gn:feature_code":"PPLL",
    "gn:name":"Hochrindl-Kegel",
    "gn:population":52,
    "gn:timezone":"Europe/Vienna",
    "iso:country":"AT",
    "wof:name":"Hochrindl-Kegel",
    "wof:placetype":"locality",
    "wof:population":52
},
  "geometry": {"coordinates":[13.99336,46.85591],"type":"Point"}
}