{
  "type": "Feature",
  "properties": {
    "gn:country":"AT",
    "gn:fcode":"PPL",
    "gn:population":0,
    "iso:country":"AT",
    "name:bar_x_preferred":[
        "T\u00e5skira"
    ],
    "name:ceb_x_preferred":[
        "Taiskirchen im Innkreis"
    ],
    "name:deu_x_preferred":[
        "Taiskirchen im Innkreis"
    ],
    "name:eng_x_preferred":[
        "Taiskirchen im Innkreis"
    ],
    "name:fas_x_preferred":[
        "\u062a\u0627\u06cc\u0633\u06a9\u0631\u06cc\u0634\u0646 \u0627\u06cc\u0645 \u0627\u06cc\u0646\u06a9\u0631\u0627\u06cc\u0633"
    ],
    "name:fra_x_preferred":[
        "Taiskirchen im Innkreis"
    ],
    "name:hun_x_preferred":[
        "Taiskirchen im Innkreis"
    ],
    "name:ita_x_preferred":[
        "Taiskirchen im Innkreis"
    ],
    "name:kaz_x_preferred":[
        "\u0422\u0430\u0439\u0441\u043a\u0438\u0440\u0445\u0435\u043d"
    ],
    "name:nld_x_preferred":[
        "Taiskirchen im Innkreis"
    ],
    "name:pol_x_preferred":[
        "Taiskirchen im Innkreis"
    ],
    "name:por_x_preferred":[
        "Taiskirchen im Innkreis"
    ],
    "name:rus_x_preferred":[
        "\u0422\u0430\u0439\u0441\u043a\u0438\u0440\u0445\u0435\u043d (\u0418\u043d\u043a\u0440\u0430\u0439\u0441)"
    ],
    "name:rus_x_variant":[
        "\u0422\u0430\u0439\u0441\u043a\u0438\u0440\u0445\u0435\u043d"
    ],
    "name:slk_x_preferred":[
        "Taiskirchen im Innkreis"
    ],
    "name:spa_x_preferred":[
        "Taiskirchen im Innkreis"
    ],
    "name:swe_x_preferred":[
        "Taiskirchen im Innkreis"
    ],
    "name:und_x_variant":[
        "Taiskirchen"
    ],
    "name:uzb_x_preferred":[
        "Taiskirchen im Innkreis"
    ],
    "name:vie_x_preferred":[
        "Taiskirchen im Innkreis"
    ],
    "name:vol_x_preferred":[
        "Taiskirchen im Innkreis"
    ],
    "name:war_x_preferred":[
        "Taiskirchen im Innkreis"
    ],
    "name:zho_x_preferred":[
        "\u56e0\u6cb3\u5730\u533a\u6cf0\u65af\u57fa\u5174"
    ],
    "qs_pg:aaroncc":"AT",
    "qs_pg:gn_country":"AT",
    "qs_pg:gn_fcode":"PPL",
    "qs_pg:gn_pop":0,
    "qs_pg:name":"Taiskirchen im Innkreis",
    "qs_pg:name_adm0":"\u00d6sterreich",
    "qs_pg:name_adm1":"Ober\u00f6sterreich",
    "qs_pg:photos_9k":1,
    "qs_pg:photos_9r":1,
    "qs_pg:photos_all":9,
    "qs_pg:photos_sr":0,
    "qs_pg:pop_sr":0,
    "qs_pg:qs_pg_placetype":"locality",
    "qs_pg:qs_pg_placetype_gp":"Town",
    "qs_pg:woe_adm0":23424750,
    "woe:adm0_id":23424750,
    "woe:name_adm0":"\u00d6sterreich",
    "woe:name_adm1":"Ober\u00f6sterreich",
    "woe:placetype":"Town",
    "wof:name":"Taiskirchen im Innkreis",
    "wof:placetype":"locality"
},
  "geometry": {"coordinates":[13.57318,48.26468],"type":"Point"}
}