{
  "type": "Feature",
  "properties": {
    "gn:admin1_code":"03",
    "gn:admin2_code":"305.0",
    "gn:admin3_code":"30509.0",
    "gn:asciiname":"Waasen",
    "gn:country_code":"AT",
    "gn:dem":297,
    "gn:feature_class":"P",
    "gn:feature_code":"PPL",
    "gn:name":"Waasen",
    "gn:population":0,
    "gn:timezone":"Europe/Vienna",
    "iso:country":"AT",
    "wof:name":"Waasen",
    "wof:placetype":"locality"
},
  "geometry": {"coordinates":[14.51667,48.15],"type":"Point"}
}