{
  "type": "Feature",
  "properties": {
    "gn:gn_country":"AT",
    "gn:gn_fcode":"PPLX",
    "gn:gn_pop":0,
    "iso:country":"AT",
    "qs_pg:aaroncc":"AT",
    "qs_pg:gn_country":"AT",
    "qs_pg:gn_fcode":"PPLX",
    "qs_pg:gn_pop":0,
    "qs_pg:name":"Kendler-Siedlung",
    "qs_pg:name_adm0":"\u00d6sterreich",
    "qs_pg:name_adm1":"Salzburg",
    "qs_pg:photos":47,
    "qs_pg:photos_1k":10,
    "qs_pg:photos_9k":1,
    "qs_pg:photos_9r":2,
    "qs_pg:photos_all":47,
    "qs_pg:photos_sr":2,
    "qs_pg:pop_sr":0,
    "qs_pg:qs_pg_placetype":"neighbourhood",
    "qs_pg:qs_pg_placetype_gp":"Suburb",
    "qs_pg:woe_adm0":23424750,
    "woe:adm0_id":23424750,
    "woe:name_adm0":"\u00d6sterreich",
    "woe:name_adm1":"Salzburg",
    "woe:placetype":"Suburb",
    "wof:name":"Kendler-Siedlung",
    "wof:placetype":"neighbourhood"
},
  "geometry": {"coordinates":[13.00361,47.78],"type":"Point"}
}