{
  "type": "Feature",
  "properties": {
    "gn:admin1_code":"4.0",
    "gn:admin2_code":"417",
    "gn:admin3_code":"41723.0",
    "gn:asciiname":"Holzpoint",
    "gn:country_code":"AT",
    "gn:dem":555,
    "gn:feature_class":"P",
    "gn:feature_code":"PPL",
    "gn:name":"Holzpoint",
    "gn:population":60,
    "gn:timezone":"Europe/Vienna",
    "iso:country":"AT",
    "wof:name":"Holzpoint",
    "wof:placetype":"locality",
    "wof:population":60
},
  "geometry": {"coordinates":[13.48209,48.02371],"type":"Point"}
}