{
  "type": "Feature",
  "properties": {
    "gn:admin1_code":"4.0",
    "gn:admin2_code":"404",
    "gn:admin3_code":"40423.0",
    "gn:asciiname":"Bergham",
    "gn:country_code":"AT",
    "gn:dem":361,
    "gn:feature_class":"P",
    "gn:feature_code":"PPL",
    "gn:name":"Bergham",
    "gn:population":0,
    "gn:timezone":"Europe/Vienna",
    "iso:country":"AT",
    "wof:name":"Bergham",
    "wof:placetype":"locality"
},
  "geometry": {"coordinates":[13.13553,48.26268],"type":"Point"}
}