{
  "type": "Feature",
  "properties": {
    "gn:admin1_code":"4.0",
    "gn:admin2_code":"414",
    "gn:admin3_code":"41409.0",
    "gn:asciiname":"Retzwinkl",
    "gn:country_code":"AT",
    "gn:dem":615,
    "gn:feature_class":"P",
    "gn:feature_code":"PPL",
    "gn:name":"Retzwinkl",
    "gn:population":0,
    "gn:timezone":"Europe/Vienna",
    "iso:country":"AT",
    "wof:name":"Retzwinkl",
    "wof:placetype":"locality"
},
  "geometry": {"coordinates":[13.62417,48.52833],"type":"Point"}
}