{
  "type": "Feature",
  "properties": {
    "gn:admin1_code":"7.0",
    "gn:admin2_code":"703",
    "gn:admin3_code":"70330.0",
    "gn:asciiname":"Obfeldes",
    "gn:country_code":"AT",
    "gn:dem":1118,
    "gn:feature_class":"P",
    "gn:feature_code":"PPL",
    "gn:name":"Obfeldes",
    "gn:population":31,
    "gn:timezone":"Europe/Vienna",
    "iso:country":"AT",
    "wof:name":"Obfeldes",
    "wof:placetype":"locality",
    "wof:population":31
},
  "geometry": {"coordinates":[11.44604,47.12484],"type":"Point"}
}