{
  "type": "Feature",
  "properties": {
    "gn:admin1_code":"4.0",
    "gn:admin2_code":"407",
    "gn:admin3_code":"40713.0",
    "gn:asciiname":"Peiskam",
    "gn:country_code":"AT",
    "gn:dem":525,
    "gn:feature_class":"P",
    "gn:feature_code":"PPL",
    "gn:name":"Peiskam",
    "gn:population":143,
    "gn:timezone":"Europe/Vienna",
    "iso:country":"AT",
    "wof:name":"Peiskam",
    "wof:placetype":"locality",
    "wof:population":143
},
  "geometry": {"coordinates":[13.79531,47.96507],"type":"Point"}
}