{
  "type": "Feature",
  "properties": {
    "gn:admin1_code":"8.0",
    "gn:admin2_code":"804",
    "gn:admin3_code":"80410.0",
    "gn:asciiname":"Neuburg",
    "gn:country_code":"AT",
    "gn:dem":417,
    "gn:feature_class":"P",
    "gn:feature_code":"PPL",
    "gn:name":"Neuburg",
    "gn:population":0,
    "gn:timezone":"Europe/Vienna",
    "iso:country":"AT",
    "name:als_x_preferred":[
        "Neuburg"
    ],
    "name:bre_x_preferred":[
        "Neuburg"
    ],
    "name:ceb_x_preferred":[
        "Neuburg"
    ],
    "name:deu_x_preferred":[
        "Neuburg"
    ],
    "name:epo_x_preferred":[
        "Neuburg"
    ],
    "name:fra_x_preferred":[
        "Neuburg"
    ],
    "name:hun_x_preferred":[
        "Neuburg"
    ],
    "name:ita_x_preferred":[
        "Neuburg"
    ],
    "name:jpn_x_preferred":[
        "\u30ce\u30a4\u30d6\u30eb\u30af"
    ],
    "name:mkd_x_preferred":[
        "\u041d\u043e\u0458\u0431\u0443\u0440\u0433"
    ],
    "name:nld_x_preferred":[
        "Neuburg"
    ],
    "name:pol_x_preferred":[
        "Neuburg"
    ],
    "name:ron_x_preferred":[
        "Neuburg"
    ],
    "name:swe_x_preferred":[
        "Neuburg"
    ],
    "name:zho_x_preferred":[
        "\u8bfa\u4f0a\u5821"
    ],
    "wof:name":"Neuburg",
    "wof:placetype":"locality"
},
  "geometry": {"coordinates":[9.60944,47.34583],"type":"Point"}
}