{
  "type": "Feature",
  "properties": {
    "gn:admin1_code":"2.0",
    "gn:admin2_code":"208",
    "gn:admin3_code":"20801.0",
    "gn:asciiname":"Oberloibach",
    "gn:country_code":"AT",
    "gn:dem":496,
    "gn:feature_class":"P",
    "gn:feature_code":"PPL",
    "gn:name":"Oberloibach",
    "gn:population":0,
    "gn:timezone":"Europe/Vienna",
    "iso:country":"AT",
    "wof:name":"Oberloibach",
    "wof:placetype":"locality"
},
  "geometry": {"coordinates":[14.80861,46.55528],"type":"Point"}
}