{
  "type": "Feature",
  "properties": {
    "gn:country":"AT",
    "gn:fcode":"PPL",
    "gn:population":0,
    "iso:country":"AT",
    "name:ceb_x_preferred":[
        "Schwarzeck"
    ],
    "name:deu_x_preferred":[
        "Schwarzeck"
    ],
    "name:swe_x_preferred":[
        "Schwarzeck"
    ],
    "qs_pg:aaroncc":"AT",
    "qs_pg:gn_country":"AT",
    "qs_pg:gn_fcode":"PPL",
    "qs_pg:gn_pop":0,
    "qs_pg:name":"Schwarzeck",
    "qs_pg:name_adm0":"Deutschland",
    "qs_pg:name_adm1":"Bayern",
    "qs_pg:photos":52,
    "qs_pg:photos_1k":11,
    "qs_pg:photos_9k":1,
    "qs_pg:photos_9r":2,
    "qs_pg:photos_all":52,
    "qs_pg:photos_sr":2,
    "qs_pg:pop_sr":0,
    "qs_pg:qs_pg_placetype":"locality",
    "qs_pg:qs_pg_placetype_gp":"Town",
    "qs_pg:woe_adm0":23424829,
    "woe:adm0_id":23424829,
    "woe:name_adm0":"Deutschland",
    "woe:name_adm1":"Bayern",
    "woe:placetype":"Town",
    "wof:name":"Schwarzeck",
    "wof:placetype":"locality"
},
  "geometry": {"coordinates":[12.68333,47.43333],"type":"Point"}
}