{
  "type": "Feature",
  "properties": {
    "gn:admin1_code":"6.0",
    "gn:admin2_code":"623",
    "gn:admin3_code":"62384.0",
    "gn:asciiname":"Axbach",
    "gn:country_code":"AT",
    "gn:dem":324,
    "gn:feature_class":"P",
    "gn:feature_code":"PPL",
    "gn:name":"Axbach",
    "gn:population":285,
    "gn:timezone":"Europe/Vienna",
    "iso:country":"AT",
    "wof:name":"Axbach",
    "wof:placetype":"locality",
    "wof:population":285
},
  "geometry": {"coordinates":[15.76611,46.94611],"type":"Point"}
}