{
  "type": "Feature",
  "properties": {
    "gn:admin1_code":"7.0",
    "gn:admin2_code":"702",
    "gn:admin3_code":"70202.0",
    "gn:asciiname":"Schlierenzau",
    "gn:country_code":"AT",
    "gn:dem":672,
    "gn:feature_class":"P",
    "gn:feature_code":"PPL",
    "gn:name":"Schlierenzau",
    "gn:population":133,
    "gn:timezone":"Europe/Vienna",
    "iso:country":"AT",
    "wof:name":"Schlierenzau",
    "wof:placetype":"locality",
    "wof:population":133
},
  "geometry": {"coordinates":[10.85351,47.24134],"type":"Point"}
}