{
  "type": "Feature",
  "properties": {
    "gn:admin1_code":"4.0",
    "gn:admin2_code":"413",
    "gn:admin3_code":"41317.0",
    "gn:asciiname":"Mistlberg",
    "gn:country_code":"AT",
    "gn:dem":671,
    "gn:feature_class":"P",
    "gn:feature_code":"PPL",
    "gn:name":"Mistlberg",
    "gn:population":206,
    "gn:timezone":"Europe/Vienna",
    "iso:country":"AT",
    "wof:name":"Mistlberg",
    "wof:placetype":"locality",
    "wof:population":206
},
  "geometry": {"coordinates":[13.82372,48.59563],"type":"Point"}
}