{
  "type": "Feature",
  "properties": {
    "gn:admin1_code":"2.0",
    "gn:admin2_code":"209",
    "gn:admin3_code":"20911.0",
    "gn:asciiname":"Elend",
    "gn:country_code":"AT",
    "gn:dem":1283,
    "gn:feature_class":"P",
    "gn:feature_code":"PPL",
    "gn:name":"Elend",
    "gn:population":0,
    "gn:timezone":"Europe/Vienna",
    "iso:country":"AT",
    "name:deu_x_preferred":[
        "Elend"
    ],
    "name:fra_x_preferred":[
        "Elend"
    ],
    "name:nld_x_preferred":[
        "Elend"
    ],
    "name:rus_x_preferred":[
        "Elend"
    ],
    "wof:name":"Elend",
    "wof:placetype":"locality"
},
  "geometry": {"coordinates":[14.92972,46.97556],"type":"Point"}
}