{
  "type": "Feature",
  "properties": {
    "gn:admin1_code":"4.0",
    "gn:admin2_code":"416",
    "gn:admin3_code":"41609.0",
    "gn:asciiname":"Lassersdorf",
    "gn:country_code":"AT",
    "gn:dem":574,
    "gn:feature_class":"P",
    "gn:feature_code":"PPL",
    "gn:name":"Lassersdorf",
    "gn:population":123,
    "gn:timezone":"Europe/Vienna",
    "iso:country":"AT",
    "wof:name":"Lassersdorf",
    "wof:placetype":"locality",
    "wof:population":123
},
  "geometry": {"coordinates":[14.15,48.41667],"type":"Point"}
}