{
  "type": "Feature",
  "properties": {
    "gn:admin1_code":"3.0",
    "gn:admin2_code":"315",
    "gn:admin3_code":"31550.0",
    "gn:asciiname":"Freiningau",
    "gn:country_code":"AT",
    "gn:dem":215,
    "gn:feature_class":"P",
    "gn:feature_code":"PPL",
    "gn:name":"Freiningau",
    "gn:population":32,
    "gn:timezone":"Europe/Vienna",
    "iso:country":"AT",
    "wof:name":"Freiningau",
    "wof:placetype":"locality",
    "wof:population":32
},
  "geometry": {"coordinates":[15.28881,48.21861],"type":"Point"}
}