{
  "type": "Feature",
  "properties": {
    "gn:admin1_code":"6.0",
    "gn:admin2_code":"622",
    "gn:admin3_code":"62266.0",
    "gn:asciiname":"Blaindorf",
    "gn:country_code":"AT",
    "gn:dem":348,
    "gn:feature_class":"P",
    "gn:feature_code":"PPLA3",
    "gn:name":"Blaindorf",
    "gn:population":297,
    "gn:timezone":"Europe/Vienna",
    "iso:country":"AT",
    "name:rus_x_preferred":[
        "\u0411\u043b\u0430\u0439\u043d\u0434\u043e\u0440\u0444"
    ],
    "wof:name":"Blaindorf",
    "wof:placetype":"locality",
    "wof:population":297
},
  "geometry": {"coordinates":[15.86795,47.17498],"type":"Point"}
}