{
  "type": "Feature",
  "properties": {
    "gn:admin1_code":"6.0",
    "gn:admin2_code":"622",
    "gn:admin3_code":"62266.0",
    "gn:asciiname":"Blaindorf",
    "gn:country_code":"AT",
    "gn:dem":348,
    "gn:feature_class":"P",
    "gn:feature_code":"PPLA3",
    "gn:name":"Blaindorf",
    "gn:population":297,
    "gn:timezone":"Europe/Vienna",
    "iso:country":"AT",
    "name:ceb_x_preferred":[
        "Blaindorf"
    ],
    "name:deu_x_preferred":[
        "Blaindorf"
    ],
    "name:fas_x_preferred":[
        "\u0628\u0644\u0627\u06cc\u0646\u062f\u0648\u0631\u0641"
    ],
    "name:fra_x_preferred":[
        "Blaindorf"
    ],
    "name:ita_x_preferred":[
        "Blaindorf"
    ],
    "name:kaz_x_preferred":[
        "\u0411\u043b\u0430\u0439\u043d\u0434\u043e\u0440\u0444"
    ],
    "name:nld_x_preferred":[
        "Blaindorf"
    ],
    "name:pol_x_preferred":[
        "Blaindorf"
    ],
    "name:rus_x_preferred":[
        "\u0411\u043b\u0430\u0439\u043d\u0434\u043e\u0440\u0444"
    ],
    "name:slk_x_preferred":[
        "Blaindorf"
    ],
    "name:swe_x_preferred":[
        "Blaindorf"
    ],
    "name:uzb_x_preferred":[
        "Blaindorf"
    ],
    "name:vie_x_preferred":[
        "Blaindorf"
    ],
    "name:vol_x_preferred":[
        "Blaindorf"
    ],
    "name:war_x_preferred":[
        "Blaindorf"
    ],
    "name:zho_x_preferred":[
        "\u5e03\u83b1\u6069\u591a\u592b"
    ],
    "wof:name":"Blaindorf",
    "wof:placetype":"locality",
    "wof:population":297
},
  "geometry": {"coordinates":[15.86795,47.17498],"type":"Point"}
}