{
  "type": "Feature",
  "properties": {
    "gn:admin1_code":"05",
    "gn:admin2_code":"504.0",
    "gn:admin3_code":"50420.0",
    "gn:asciiname":"Althaus",
    "gn:country_code":"AT",
    "gn:dem":1120,
    "gn:feature_class":"P",
    "gn:feature_code":"PPL",
    "gn:name":"Althaus",
    "gn:population":0,
    "gn:timezone":"Europe/Vienna",
    "iso:country":"AT",
    "wof:name":"Althaus",
    "wof:placetype":"locality"
},
  "geometry": {"coordinates":[13.11667,47.35],"type":"Point"}
}