{
  "type": "Feature",
  "properties": {
    "gn:admin1_code":"05",
    "gn:admin2_code":"504.0",
    "gn:admin3_code":"50410.0",
    "gn:asciiname":"Maierhof",
    "gn:country_code":"AT",
    "gn:dem":832,
    "gn:feature_class":"P",
    "gn:feature_code":"PPL",
    "gn:name":"Maierhof",
    "gn:population":144,
    "gn:timezone":"Europe/Vienna",
    "iso:country":"AT",
    "wof:name":"Maierhof",
    "wof:placetype":"locality",
    "wof:population":144
},
  "geometry": {"coordinates":[13.08489,47.30484000000001],"type":"Point"}
}