{
  "type": "Feature",
  "properties": {
    "gn:admin1_code":"6.0",
    "gn:admin2_code":"620",
    "gn:admin3_code":"62010.0",
    "gn:asciiname":"Bergbau",
    "gn:country_code":"AT",
    "gn:dem":1179,
    "gn:feature_class":"P",
    "gn:feature_code":"PPL",
    "gn:name":"Bergbau",
    "gn:population":0,
    "gn:timezone":"Europe/Vienna",
    "iso:country":"AT",
    "wof:name":"Bergbau",
    "wof:placetype":"locality"
},
  "geometry": {"coordinates":[14.46417,47.44472],"type":"Point"}
}