{
  "type": "Feature",
  "properties": {
    "gn:admin1_code":"7.0",
    "gn:admin2_code":"704",
    "gn:admin3_code":"70402.0",
    "gn:asciiname":"Feuring",
    "gn:country_code":"AT",
    "gn:dem":812,
    "gn:feature_class":"P",
    "gn:feature_code":"PPL",
    "gn:name":"Feuring",
    "gn:population":0,
    "gn:timezone":"Europe/Vienna",
    "iso:country":"AT",
    "wof:name":"Feuring",
    "wof:placetype":"locality"
},
  "geometry": {"coordinates":[12.26667,47.45],"type":"Point"}
}