{
  "type": "Feature",
  "properties": {
    "gn:admin1_code":"02",
    "gn:admin2_code":"208.0",
    "gn:admin3_code":"20813.0",
    "gn:asciiname":"Sankt Marxen",
    "gn:country_code":"AT",
    "gn:dem":391,
    "gn:feature_class":"P",
    "gn:feature_code":"PPL",
    "gn:name":"Sankt Marxen",
    "gn:population":78,
    "gn:timezone":"Europe/Vienna",
    "iso:country":"AT",
    "wof:name":"Sankt Marxen",
    "wof:placetype":"locality",
    "wof:population":78
},
  "geometry": {"coordinates":[14.61667,46.63333],"type":"Point"}
}