{
  "type": "Feature",
  "properties": {
    "gn:admin1_code":"04",
    "gn:admin2_code":"418.0",
    "gn:admin3_code":"41805.0",
    "gn:asciiname":"Wipfing",
    "gn:country_code":"AT",
    "gn:dem":411,
    "gn:feature_class":"P",
    "gn:feature_code":"PPL",
    "gn:name":"Wipfing",
    "gn:population":712,
    "gn:timezone":"Europe/Vienna",
    "iso:country":"AT",
    "wof:name":"Wipfing",
    "wof:placetype":"locality",
    "wof:population":712
},
  "geometry": {"coordinates":[13.98594,48.04762],"type":"Point"}
}