{
  "type": "Feature",
  "properties": {
    "gn:country":"AT",
    "gn:fcode":"PPLA3",
    "gn:population":0,
    "iso:country":"AT",
    "name:ceb_x_preferred":[
        "Kartitsch"
    ],
    "name:ces_x_preferred":[
        "Kartitsch"
    ],
    "name:deu_x_preferred":[
        "Kartitsch"
    ],
    "name:eng_x_preferred":[
        "Kartitsch"
    ],
    "name:est_x_preferred":[
        "Kartitsch"
    ],
    "name:fas_x_preferred":[
        "\u06a9\u0627\u0631\u062a\u06cc\u0686"
    ],
    "name:fra_x_preferred":[
        "Kartitsch"
    ],
    "name:hun_x_preferred":[
        "Kartitsch"
    ],
    "name:ita_x_preferred":[
        "Kartitsch"
    ],
    "name:kaz_x_preferred":[
        "\u041a\u0430\u0440\u0442\u0438\u0447"
    ],
    "name:lmo_x_preferred":[
        "Kartitsch"
    ],
    "name:nld_x_preferred":[
        "Kartitsch"
    ],
    "name:pnb_x_preferred":[
        "\u06a9\u0627\u0631\u0679\u06cc\u0679\u0634"
    ],
    "name:pol_x_preferred":[
        "Kartitsch"
    ],
    "name:rus_x_preferred":[
        "\u041a\u0430\u0440\u0442\u0438\u0447"
    ],
    "name:slk_x_preferred":[
        "Kartitsch"
    ],
    "name:spa_x_preferred":[
        "Kartitsch"
    ],
    "name:swe_x_preferred":[
        "Kartitsch"
    ],
    "name:ukr_x_preferred":[
        "\u041a\u0430\u0440\u0442\u0456\u0447"
    ],
    "name:und_x_variant":[
        "Boden"
    ],
    "name:uzb_x_preferred":[
        "Kartitsch"
    ],
    "name:vec_x_preferred":[
        "Kartitsch"
    ],
    "name:vol_x_preferred":[
        "Kartitsch"
    ],
    "name:war_x_preferred":[
        "Kartitsch"
    ],
    "name:zho_x_preferred":[
        "\u5361\u5c14\u8482\u5947"
    ],
    "name:zho_x_variant":[
        "Kartitsch"
    ],
    "qs_pg:aaroncc":"AT",
    "qs_pg:gn_country":"AT",
    "qs_pg:gn_fcode":"PPLA3",
    "qs_pg:gn_pop":0,
    "qs_pg:name":"Kartitsch",
    "qs_pg:name_adm0":"\u00d6sterreich",
    "qs_pg:name_adm1":"Tirol",
    "qs_pg:photos":44,
    "qs_pg:photos_1k":9,
    "qs_pg:photos_9k":1,
    "qs_pg:photos_9r":2,
    "qs_pg:photos_all":44,
    "qs_pg:photos_sr":2,
    "qs_pg:pop_sr":0,
    "qs_pg:qs_pg_placetype":"locality",
    "qs_pg:qs_pg_placetype_gp":"Town",
    "qs_pg:woe_adm0":23424750,
    "woe:adm0_id":23424750,
    "woe:name_adm0":"\u00d6sterreich",
    "woe:name_adm1":"Tirol",
    "woe:placetype":"Town",
    "wof:name":"Kartitsch",
    "wof:placetype":"locality"
},
  "geometry": {"coordinates":[12.50083,46.72889],"type":"Point"}
}