{
  "type": "Feature",
  "properties": {
    "gn:admin1_code":"4.0",
    "gn:admin2_code":"408",
    "gn:admin3_code":"40812.0",
    "gn:asciiname":"Hading",
    "gn:country_code":"AT",
    "gn:dem":391,
    "gn:feature_class":"P",
    "gn:feature_code":"PPL",
    "gn:name":"Hading",
    "gn:population":75,
    "gn:timezone":"Europe/Vienna",
    "iso:country":"AT",
    "wof:name":"Hading",
    "wof:placetype":"locality",
    "wof:population":75
},
  "geometry": {"coordinates":[13.7148,48.27063],"type":"Point"}
}