{
  "type": "Feature",
  "properties": {
    "gn:admin1_code":"3.0",
    "gn:admin2_code":"305",
    "gn:admin3_code":"30541.0",
    "gn:asciiname":"Dippersdorf",
    "gn:country_code":"AT",
    "gn:dem":314,
    "gn:feature_class":"P",
    "gn:feature_code":"PPL",
    "gn:name":"Dippersdorf",
    "gn:population":0,
    "gn:timezone":"Europe/Vienna",
    "iso:country":"AT",
    "wof:name":"Dippersdorf",
    "wof:placetype":"locality"
},
  "geometry": {"coordinates":[14.8415,48.07441],"type":"Point"}
}