{
  "type": "Feature",
  "properties": {
    "gn:admin1_code":"3.0",
    "gn:admin2_code":"320",
    "gn:admin3_code":"32006.0",
    "gn:asciiname":"Gries bei Oberndorf",
    "gn:cc2":"AT",
    "gn:country_code":"AT",
    "gn:dem":292,
    "gn:feature_class":"P",
    "gn:feature_code":"PPL",
    "gn:name":"Gries bei Oberndorf",
    "gn:population":608,
    "gn:timezone":"Europe/Vienna",
    "iso:country":"AT",
    "name:und_x_variant":[
        "Gries"
    ],
    "wof:name":"Gries bei Oberndorf",
    "wof:placetype":"locality",
    "wof:population":608
},
  "geometry": {"coordinates":[15.21246,48.06512],"type":"Point"}
}