{
  "type": "Feature",
  "properties": {
    "gn:admin1_code":"7.0",
    "gn:admin2_code":"704",
    "gn:admin3_code":"70404.0",
    "gn:asciiname":"Schattseite",
    "gn:country_code":"AT",
    "gn:dem":857,
    "gn:feature_class":"P",
    "gn:feature_code":"PPL",
    "gn:name":"Schattseite",
    "gn:population":411,
    "gn:timezone":"Europe/Vienna",
    "iso:country":"AT",
    "wof:name":"Schattseite",
    "wof:placetype":"locality",
    "wof:population":411
},
  "geometry": {"coordinates":[12.34207,47.51204],"type":"Point"}
}