{
  "type": "Feature",
  "properties": {
    "gn:admin1_code":"6.0",
    "gn:admin2_code":"603",
    "gn:admin3_code":"60344.0",
    "gn:asciiname":"Gratzer",
    "gn:country_code":"AT",
    "gn:dem":1139,
    "gn:feature_class":"P",
    "gn:feature_code":"PPL",
    "gn:name":"Gratzer",
    "gn:population":0,
    "gn:timezone":"Europe/Vienna",
    "iso:country":"AT",
    "name:deu_x_preferred":[
        "Gratzer"
    ],
    "wof:name":"Gratzer",
    "wof:placetype":"locality"
},
  "geometry": {"coordinates":[15.06806,46.89833],"type":"Point"}
}