{
  "type": "Feature",
  "properties": {
    "gn:admin1_code":"02",
    "gn:admin2_code":"208.0",
    "gn:admin3_code":"20815.0",
    "gn:asciiname":"Sagerberg",
    "gn:cc2":"AT",
    "gn:country_code":"AT",
    "gn:dem":822,
    "gn:feature_class":"P",
    "gn:feature_code":"PPL",
    "gn:name":"Sagerberg",
    "gn:population":31,
    "gn:timezone":"Europe/Vienna",
    "iso:country":"AT",
    "name:und_x_variant":[
        "Saagerberg",
        "Sagerberg"
    ],
    "wof:name":"Sagerberg",
    "wof:placetype":"locality",
    "wof:population":31
},
  "geometry": {"coordinates":[14.65,46.53333],"type":"Point"}
}