{
  "type": "Feature",
  "properties": {
    "gn:admin1_code":"3.0",
    "gn:admin2_code":"322",
    "gn:admin3_code":"32219.0",
    "gn:asciiname":"Nonndorf bei Grunau",
    "gn:cc2":"AT",
    "gn:country_code":"AT",
    "gn:dem":536,
    "gn:feature_class":"P",
    "gn:feature_code":"PPL",
    "gn:name":"Nonndorf bei Gr\u00fcnau",
    "gn:population":0,
    "gn:timezone":"Europe/Vienna",
    "iso:country":"AT",
    "name:und_x_variant":[
        "Nonndorf",
        "Nonndorf bei Gr\u00fcnau"
    ],
    "wof:name":"Nonndorf bei Grunau",
    "wof:placetype":"locality"
},
  "geometry": {"coordinates":[15.2384,48.78743],"type":"Point"}
}