{
  "type": "Feature",
  "properties": {
    "gn:admin1_code":"3.0",
    "gn:admin2_code":"319",
    "gn:admin3_code":"31935.0",
    "gn:asciiname":"Deutschbach",
    "gn:country_code":"AT",
    "gn:dem":409,
    "gn:feature_class":"P",
    "gn:feature_code":"PPL",
    "gn:name":"Deutschbach",
    "gn:population":208,
    "gn:timezone":"Europe/Vienna",
    "iso:country":"AT",
    "wof:name":"Deutschbach",
    "wof:placetype":"locality",
    "wof:population":208
},
  "geometry": {"coordinates":[15.50102,48.05927],"type":"Point"}
}