{
  "type": "Feature",
  "properties": {
    "gn:country":"AT",
    "gn:fcode":"PPL",
    "gn:population":0,
    "iso:country":"AT",
    "name:ceb_x_preferred":[
        "Zederhaus"
    ],
    "name:deu_x_preferred":[
        "Zedras"
    ],
    "name:deu_x_variant":[
        "Zederhaus"
    ],
    "name:epo_x_preferred":[
        "Zederhaus"
    ],
    "name:fas_x_preferred":[
        "\u0633\u062f\u0631\u0647\u0648\u0633"
    ],
    "name:fra_x_preferred":[
        "Zederhaus"
    ],
    "name:hun_x_preferred":[
        "Zederhaus"
    ],
    "name:ita_x_preferred":[
        "Zederhaus"
    ],
    "name:kaz_x_preferred":[
        "\u0426\u0435\u0434\u0435\u0440\u0445\u0430\u0443\u0441"
    ],
    "name:nld_x_preferred":[
        "Zederhaus"
    ],
    "name:pol_x_preferred":[
        "Zederhaus"
    ],
    "name:rus_x_preferred":[
        "\u0426\u0435\u0434\u0435\u0440\u0445\u0430\u0443\u0441"
    ],
    "name:slk_x_preferred":[
        "Zederhaus"
    ],
    "name:slv_x_preferred":[
        "Sodra\u017eava"
    ],
    "name:spa_x_preferred":[
        "Zederhaus"
    ],
    "name:swe_x_preferred":[
        "Zederhaus"
    ],
    "name:ukr_x_preferred":[
        "\u0426\u0435\u0434\u0435\u0440\u0445\u0430\u0443\u0441"
    ],
    "name:uzb_x_preferred":[
        "Zederhaus"
    ],
    "name:vol_x_preferred":[
        "Zederhaus"
    ],
    "name:war_x_preferred":[
        "Zederhaus"
    ],
    "name:zho_x_preferred":[
        "\u91c7\u5fb7\u8c6a\u65af"
    ],
    "qs_pg:aaroncc":"AT",
    "qs_pg:gn_country":"AT",
    "qs_pg:gn_fcode":"PPL",
    "qs_pg:gn_pop":0,
    "qs_pg:name":"Zederhaus",
    "qs_pg:name_adm0":"\u00d6sterreich",
    "qs_pg:name_adm1":"Salzburg",
    "qs_pg:photos":33,
    "qs_pg:photos_1k":7,
    "qs_pg:photos_9k":1,
    "qs_pg:photos_9r":2,
    "qs_pg:photos_all":33,
    "qs_pg:photos_sr":2,
    "qs_pg:pop_sr":0,
    "qs_pg:qs_pg_placetype":"locality",
    "qs_pg:qs_pg_placetype_gp":"Town",
    "qs_pg:woe_adm0":23424750,
    "woe:adm0_id":23424750,
    "woe:name_adm0":"\u00d6sterreich",
    "woe:name_adm1":"Salzburg",
    "woe:placetype":"Town",
    "wof:name":"Zederhaus",
    "wof:placetype":"locality"
},
  "geometry": {"coordinates":[14.15,46.56667],"type":"Point"}
}