{
  "type": "Feature",
  "properties": {
    "gn:gn_country":"AT",
    "gn:gn_fcode":"PPL",
    "gn:gn_pop":0,
    "iso:country":"AT",
    "name:deu_x_preferred":[
        "Zedras"
    ],
    "name:slv_x_preferred":[
        "Sodra\u017eava"
    ],
    "qs_pg:aaroncc":"AT",
    "qs_pg:gn_country":"AT",
    "qs_pg:gn_fcode":"PPL",
    "qs_pg:gn_pop":0,
    "qs_pg:name":"Zederhaus",
    "qs_pg:name_adm0":"\u00d6sterreich",
    "qs_pg:name_adm1":"Salzburg",
    "qs_pg:photos":33,
    "qs_pg:photos_1k":7,
    "qs_pg:photos_9k":1,
    "qs_pg:photos_9r":2,
    "qs_pg:photos_all":33,
    "qs_pg:photos_sr":2,
    "qs_pg:pop_sr":0,
    "qs_pg:qs_pg_placetype":"locality",
    "qs_pg:qs_pg_placetype_gp":"Town",
    "qs_pg:woe_adm0":23424750,
    "woe:adm0_id":23424750,
    "woe:name_adm0":"\u00d6sterreich",
    "woe:name_adm1":"Salzburg",
    "woe:placetype":"Town",
    "wof:name":"Zederhaus",
    "wof:placetype":"locality"
},
  "geometry": {"coordinates":[14.15,46.56667],"type":"Point"}
}