{
  "type": "Feature",
  "properties": {
    "gn:admin1_code":"4.0",
    "gn:admin2_code":"413",
    "gn:admin3_code":"41324.0",
    "gn:asciiname":"Schoeffgattern",
    "gn:country_code":"AT",
    "gn:dem":674,
    "gn:feature_class":"P",
    "gn:feature_code":"PPL",
    "gn:name":"Sch\u00f6ffgattern",
    "gn:population":15,
    "gn:timezone":"Europe/Vienna",
    "iso:country":"AT",
    "wof:name":"Schoeffgattern",
    "wof:placetype":"locality",
    "wof:population":15
},
  "geometry": {"coordinates":[13.82806,48.57917],"type":"Point"}
}