{
  "type": "Feature",
  "properties": {
    "gn:admin1_code":"02",
    "gn:admin2_code":"202.0",
    "gn:admin3_code":"20201.0",
    "gn:asciiname":"Sankt Niklas an der Drau",
    "gn:cc2":"AT",
    "gn:country_code":"AT",
    "gn:dem":470,
    "gn:feature_class":"P",
    "gn:feature_code":"PPL",
    "gn:name":"Sankt Niklas an der Drau",
    "gn:population":273,
    "gn:timezone":"Europe/Vienna",
    "iso:country":"AT",
    "name:und_x_variant":[
        "Drau",
        "Sankt Niklas an der Drau"
    ],
    "wof:name":"Sankt Niklas an der Drau",
    "wof:placetype":"locality",
    "wof:population":273
},
  "geometry": {"coordinates":[13.94152,46.5996],"type":"Point"}
}