{
  "type": "Feature",
  "properties": {
    "gn:admin1_code":"06",
    "gn:admin2_code":"612.0",
    "gn:admin3_code":"61222.0",
    "gn:asciiname":"Schattenberg",
    "gn:country_code":"AT",
    "gn:dem":833,
    "gn:feature_class":"P",
    "gn:feature_code":"PPL",
    "gn:name":"Schattenberg",
    "gn:population":88,
    "gn:timezone":"Europe/Vienna",
    "iso:country":"AT",
    "wof:name":"Schattenberg",
    "wof:placetype":"locality",
    "wof:population":88
},
  "geometry": {"coordinates":[14.21667,47.53333],"type":"Point"}
}