{
  "type": "Feature",
  "properties": {
    "gn:admin1_code":"06",
    "gn:admin2_code":"611.0",
    "gn:admin3_code":"61118.0",
    "gn:asciiname":"Wegscheid",
    "gn:country_code":"AT",
    "gn:dem":1252,
    "gn:feature_class":"P",
    "gn:feature_code":"PPL",
    "gn:name":"Wegscheid",
    "gn:population":0,
    "gn:timezone":"Europe/Vienna",
    "iso:country":"AT",
    "wof:name":"Wegscheid",
    "wof:placetype":"locality"
},
  "geometry": {"coordinates":[14.98333,47.51667],"type":"Point"}
}