{
  "type": "Feature",
  "properties": {
    "gn:admin1_code":"06",
    "gn:admin2_code":"611.0",
    "gn:admin3_code":"61118.0",
    "gn:asciiname":"Wegscheid",
    "gn:country_code":"AT",
    "gn:dem":1252,
    "gn:feature_class":"P",
    "gn:feature_code":"PPL",
    "gn:name":"Wegscheid",
    "gn:population":0,
    "gn:timezone":"Europe/Vienna",
    "iso:country":"AT",
    "name:ara_x_preferred":[
        "\u0641\u064a\u063a\u0634\u064a\u0644\u062f"
    ],
    "name:ces_x_preferred":[
        "Wegscheid"
    ],
    "name:deu_x_preferred":[
        "Wegscheid"
    ],
    "name:epo_x_preferred":[
        "Wegscheid"
    ],
    "name:eus_x_preferred":[
        "Wegscheid"
    ],
    "name:fas_x_preferred":[
        "\u0648\u06af\u0634\u0627\u06cc\u062f"
    ],
    "name:fin_x_preferred":[
        "Wegscheid"
    ],
    "name:fra_x_preferred":[
        "Wegscheid"
    ],
    "name:hun_x_preferred":[
        "Wegscheid"
    ],
    "name:hye_x_preferred":[
        "\u054e\u0565\u0563\u0577\u0561\u0575\u0564"
    ],
    "name:ind_x_preferred":[
        "Wegscheid"
    ],
    "name:ita_x_preferred":[
        "Wegscheid"
    ],
    "name:lmo_x_preferred":[
        "Wegscheid"
    ],
    "name:msa_x_preferred":[
        "Wegscheid"
    ],
    "name:nld_x_preferred":[
        "Wegscheid"
    ],
    "name:pol_x_preferred":[
        "Wegscheid"
    ],
    "name:ron_x_preferred":[
        "Wegscheid"
    ],
    "name:rus_x_preferred":[
        "\u0412\u0435\u0433\u0448\u0430\u0439\u0434"
    ],
    "name:spa_x_preferred":[
        "Wegscheid"
    ],
    "name:srp_x_preferred":[
        "\u0412\u0435\u0433\u0448\u0430\u0458\u0434"
    ],
    "name:swe_x_preferred":[
        "Wegscheid"
    ],
    "name:ukr_x_preferred":[
        "\u0412\u0435\u0433\u0448\u0430\u0439\u0434"
    ],
    "name:uzb_x_preferred":[
        "Wegscheid"
    ],
    "name:vie_x_preferred":[
        "Wegscheid"
    ],
    "name:vol_x_preferred":[
        "Wegscheid"
    ],
    "name:war_x_preferred":[
        "Wegscheid"
    ],
    "name:zho_x_preferred":[
        "\u97e6\u683c\u6c99\u4f0a\u5fb7"
    ],
    "wof:name":"Wegscheid",
    "wof:placetype":"locality"
},
  "geometry": {"coordinates":[14.98333,47.51667],"type":"Point"}
}