{
  "type": "Feature",
  "properties": {
    "gn:admin1_code":"5.0",
    "gn:admin2_code":"503",
    "gn:admin3_code":"50327.0",
    "gn:asciiname":"Simmerstatt",
    "gn:country_code":"AT",
    "gn:dem":707,
    "gn:feature_class":"P",
    "gn:feature_code":"PPL",
    "gn:name":"Simmerstatt",
    "gn:population":0,
    "gn:timezone":"Europe/Vienna",
    "iso:country":"AT",
    "wof:name":"Simmerstatt",
    "wof:placetype":"locality"
},
  "geometry": {"coordinates":[13.01667,47.93417],"type":"Point"}
}