{
  "type": "Feature",
  "properties": {
    "gn:admin1_code":"03",
    "gn:admin2_code":"310.0",
    "gn:admin3_code":"31022.0",
    "gn:asciiname":"Weyerburg",
    "gn:country_code":"AT",
    "gn:dem":275,
    "gn:feature_class":"P",
    "gn:feature_code":"PPL",
    "gn:name":"Weyerburg",
    "gn:population":110,
    "gn:timezone":"Europe/Vienna",
    "iso:country":"AT",
    "wof:name":"Weyerburg",
    "wof:placetype":"locality",
    "wof:population":110
},
  "geometry": {"coordinates":[16.18333,48.56667],"type":"Point"}
}