{
  "type": "Feature",
  "properties": {
    "gn:admin1_code":"4.0",
    "gn:admin2_code":"410",
    "gn:admin3_code":"41019.0",
    "gn:asciiname":"Hasenufer",
    "gn:country_code":"AT",
    "gn:dem":277,
    "gn:feature_class":"P",
    "gn:feature_code":"PPL",
    "gn:name":"Hasenufer",
    "gn:population":447,
    "gn:timezone":"Europe/Vienna",
    "iso:country":"AT",
    "wof:name":"Hasenufer",
    "wof:placetype":"locality",
    "wof:population":447
},
  "geometry": {"coordinates":[14.22249,48.19745],"type":"Point"}
}