{
  "type": "Feature",
  "properties": {
    "gn:admin1_code":"06",
    "gn:admin2_code":"623.0",
    "gn:admin3_code":"62381.0",
    "gn:asciiname":"Obergleisbach",
    "gn:country_code":"AT",
    "gn:dem":375,
    "gn:feature_class":"P",
    "gn:feature_code":"PPL",
    "gn:name":"Obergleisbach",
    "gn:population":0,
    "gn:timezone":"Europe/Vienna",
    "iso:country":"AT",
    "wof:name":"Obergleisbach",
    "wof:placetype":"locality"
},
  "geometry": {"coordinates":[15.65,46.93333],"type":"Point"}
}