{
  "type": "Feature",
  "properties": {
    "gn:admin1_code":"04",
    "gn:admin2_code":"406.0",
    "gn:admin3_code":"40616.0",
    "gn:asciiname":"Rothenbachl",
    "gn:country_code":"AT",
    "gn:dem":925,
    "gn:feature_class":"P",
    "gn:feature_code":"PPL",
    "gn:name":"Rothenbachl",
    "gn:population":56,
    "gn:timezone":"Europe/Vienna",
    "iso:country":"AT",
    "wof:name":"Rothenbachl",
    "wof:placetype":"locality",
    "wof:population":56
},
  "geometry": {"coordinates":[14.62709,48.53769000000001],"type":"Point"}
}