{
  "type": "Feature",
  "properties": {
    "gn:admin1_code":"3.0",
    "gn:admin2_code":"315",
    "gn:admin3_code":"31503.0",
    "gn:asciiname":"Obereichen",
    "gn:country_code":"AT",
    "gn:dem":282,
    "gn:feature_class":"P",
    "gn:feature_code":"PPL",
    "gn:name":"Obereichen",
    "gn:population":0,
    "gn:timezone":"Europe/Vienna",
    "iso:country":"AT",
    "wof:name":"Obereichen",
    "wof:placetype":"locality"
},
  "geometry": {"coordinates":[15.15,48.16667],"type":"Point"}
}