{
  "type": "Feature",
  "properties": {
    "gn:admin1_code":"2.0",
    "gn:admin2_code":"206",
    "gn:admin3_code":"20609.0",
    "gn:asciiname":"Gnoppnitz Hintere Haeuser",
    "gn:country_code":"AT",
    "gn:dem":1233,
    "gn:feature_class":"P",
    "gn:feature_code":"PPL",
    "gn:name":"Gnoppnitz Hintere H\u00e4user",
    "gn:population":0,
    "gn:timezone":"Europe/Vienna",
    "iso:country":"AT",
    "wof:name":"Gnoppnitz Hintere Haeuser",
    "wof:placetype":"locality"
},
  "geometry": {"coordinates":[13.17611,46.78972],"type":"Point"}
}