{
  "type": "Feature",
  "properties": {
    "iso:country":"AT",
    "qs_pg:aaroncc":"AT",
    "qs_pg:name":"St. Nikolai im S\u00f6lktal",
    "qs_pg:name_adm0":"\u00d6sterreich",
    "qs_pg:name_adm1":"Steiermark",
    "qs_pg:photos":26,
    "qs_pg:photos_1k":5,
    "qs_pg:photos_9k":1,
    "qs_pg:photos_9r":2,
    "qs_pg:photos_all":26,
    "qs_pg:photos_sr":2,
    "qs_pg:pop_sr":0,
    "qs_pg:qs_pg_placetype":"locality",
    "qs_pg:qs_pg_placetype_gp":"Town",
    "qs_pg:woe_adm0":23424750,
    "woe:adm0_id":23424750,
    "woe:name_adm0":"\u00d6sterreich",
    "woe:name_adm1":"Steiermark",
    "woe:placetype":"Town",
    "wof:name":"St. Nikolai im S\u00f6lktal",
    "wof:placetype":"locality"
},
  "geometry": {"coordinates":[14.055762,47.311413],"type":"Point"}
}