{
  "type": "Feature",
  "properties": {
    "gn:admin1_code":"6.0",
    "gn:admin2_code":"606",
    "gn:admin3_code":"60623.0",
    "gn:asciiname":"Schaftal",
    "gn:country_code":"AT",
    "gn:dem":472,
    "gn:feature_class":"P",
    "gn:feature_code":"PPL",
    "gn:name":"Schaftal",
    "gn:population":456,
    "gn:timezone":"Europe/Vienna",
    "iso:country":"AT",
    "wof:name":"Schaftal",
    "wof:placetype":"locality",
    "wof:population":456
},
  "geometry": {"coordinates":[15.5248,47.11369000000001],"type":"Point"}
}