{
  "type": "Feature",
  "properties": {
    "gn:admin1_code":"6.0",
    "gn:admin2_code":"612",
    "gn:admin3_code":"61267.0",
    "gn:asciiname":"Niederstuttern",
    "gn:country_code":"AT",
    "gn:dem":655,
    "gn:feature_class":"P",
    "gn:feature_code":"PPL",
    "gn:name":"Niederstuttern",
    "gn:population":0,
    "gn:timezone":"Europe/Vienna",
    "iso:country":"AT",
    "wof:name":"Niederstuttern",
    "wof:placetype":"locality"
},
  "geometry": {"coordinates":[14.04885,47.50793],"type":"Point"}
}