{
  "type": "Feature",
  "properties": {
    "gn:admin1_code":"4.0",
    "gn:admin2_code":"406",
    "gn:admin3_code":"40622.0",
    "gn:asciiname":"Loibersdorf",
    "gn:country_code":"AT",
    "gn:dem":513,
    "gn:feature_class":"P",
    "gn:feature_code":"PPL",
    "gn:name":"Loibersdorf",
    "gn:population":181,
    "gn:timezone":"Europe/Vienna",
    "iso:country":"AT",
    "wof:name":"Loibersdorf",
    "wof:placetype":"locality",
    "wof:population":181
},
  "geometry": {"coordinates":[14.48256,48.38578],"type":"Point"}
}