{
  "type": "Feature",
  "properties": {
    "gn:gn_country":"AT",
    "gn:gn_fcode":"PPLA3",
    "gn:gn_pop":0,
    "iso:country":"AT",
    "name:bos_x_preferred":[
        "Spielfeld"
    ],
    "name:chi_x_preferred":[
        "\u65bd\u76ae\u5c14\u8d39\u5c14\u5fb7"
    ],
    "name:dut_x_preferred":[
        "Spielfeld"
    ],
    "name:eng_x_preferred":[
        "Spielfeld"
    ],
    "name:fre_x_preferred":[
        "Spielfeld"
    ],
    "name:ger_x_preferred":[
        "Spielfeld"
    ],
    "name:hun_x_preferred":[
        "Spielfeld"
    ],
    "name:ita_x_preferred":[
        "Spielfeld"
    ],
    "name:jpn_x_preferred":[
        "\u30b7\u30e5\u30d4\u30fc\u30eb\u30d5\u30a7\u30eb\u30c8"
    ],
    "name:kaz_x_preferred":[
        "\u0428\u043f\u0438\u043b\u044c\u0444\u0435\u043b\u044c\u0434"
    ],
    "name:rus_x_preferred":[
        "\u0428\u043f\u0438\u043b\u044c\u0444\u0435\u043b\u044c\u0434"
    ],
    "name:slo_x_preferred":[
        "Spielfeld"
    ],
    "name:slv_x_preferred":[
        "\u0160pilje"
    ],
    "name:swe_x_preferred":[
        "Spielfeld"
    ],
    "name:uzb_x_preferred":[
        "Spielfeld"
    ],
    "name:vie_x_preferred":[
        "Spielfeld"
    ],
    "name:vol_x_preferred":[
        "Spielfeld"
    ],
    "name:war_x_preferred":[
        "Spielfeld"
    ],
    "qs_pg:aaroncc":"AT",
    "qs_pg:gn_country":"AT",
    "qs_pg:gn_fcode":"PPLA3",
    "qs_pg:gn_pop":0,
    "qs_pg:name":"Spielfeld",
    "qs_pg:name_adm0":"\u00d6sterreich",
    "qs_pg:name_adm1":"Steiermark",
    "qs_pg:photos":22,
    "qs_pg:photos_1k":4,
    "qs_pg:photos_9k":1,
    "qs_pg:photos_9r":1,
    "qs_pg:photos_all":22,
    "qs_pg:photos_sr":1,
    "qs_pg:pop_sr":0,
    "qs_pg:qs_pg_placetype":"locality",
    "qs_pg:qs_pg_placetype_gp":"Town",
    "qs_pg:woe_adm0":23424750,
    "woe:adm0_id":23424750,
    "woe:name_adm0":"\u00d6sterreich",
    "woe:name_adm1":"Steiermark",
    "woe:placetype":"Town",
    "wof:name":"Spielfeld",
    "wof:placetype":"locality"
},
  "geometry": {"coordinates":[15.63722,46.70556],"type":"Point"}
}