{
  "type": "Feature",
  "properties": {
    "gn:admin1_code":"4.0",
    "gn:admin2_code":"405",
    "gn:admin3_code":"40508.0",
    "gn:asciiname":"Mairing",
    "gn:country_code":"AT",
    "gn:dem":370,
    "gn:feature_class":"P",
    "gn:feature_code":"PPL",
    "gn:name":"Mairing",
    "gn:population":139,
    "gn:timezone":"Europe/Vienna",
    "iso:country":"AT",
    "wof:name":"Mairing",
    "wof:placetype":"locality",
    "wof:population":139
},
  "geometry": {"coordinates":[13.89856,48.30843],"type":"Point"}
}