{
  "type": "Feature",
  "properties": {
    "gn:admin1_code":"05",
    "gn:admin2_code":"504.0",
    "gn:admin3_code":"50403.0",
    "gn:asciiname":"Remsach",
    "gn:country_code":"AT",
    "gn:dem":854,
    "gn:feature_class":"P",
    "gn:feature_code":"PPL",
    "gn:name":"Remsach",
    "gn:population":0,
    "gn:timezone":"Europe/Vienna",
    "iso:country":"AT",
    "wof:name":"Remsach",
    "wof:placetype":"locality"
},
  "geometry": {"coordinates":[13.13333,47.13333],"type":"Point"}
}