{
  "type": "Feature",
  "properties": {
    "gn:admin1_code":"03",
    "gn:admin2_code":"322.0",
    "gn:admin3_code":"32216.0",
    "gn:asciiname":"Unterpertholz",
    "gn:country_code":"AT",
    "gn:dem":463,
    "gn:feature_class":"P",
    "gn:feature_code":"PPL",
    "gn:name":"Unterpertholz",
    "gn:population":72,
    "gn:timezone":"Europe/Vienna",
    "iso:country":"AT",
    "wof:name":"Unterpertholz",
    "wof:placetype":"locality",
    "wof:population":72
},
  "geometry": {"coordinates":[15.46667,48.93333],"type":"Point"}
}