{
  "type": "Feature",
  "properties": {
    "gn:admin1_code":"2.0",
    "gn:admin2_code":"205",
    "gn:admin3_code":"20523.0",
    "gn:asciiname":"Hochosterwitz",
    "gn:country_code":"AT",
    "gn:dem":557,
    "gn:feature_class":"P",
    "gn:feature_code":"PPL",
    "gn:name":"Hochosterwitz",
    "gn:population":27,
    "gn:timezone":"Europe/Vienna",
    "iso:country":"AT",
    "wof:name":"Hochosterwitz",
    "wof:placetype":"locality",
    "wof:population":27
},
  "geometry": {"coordinates":[14.45,46.75],"type":"Point"}
}