{
  "type": "Feature",
  "properties": {
    "gn:admin1_code":"7.0",
    "gn:admin2_code":"702",
    "gn:admin3_code":"70220.0",
    "gn:asciiname":"Heiligkreuz",
    "gn:country_code":"AT",
    "gn:dem":1698,
    "gn:feature_class":"P",
    "gn:feature_code":"PPL",
    "gn:name":"Heiligkreuz",
    "gn:population":127,
    "gn:timezone":"Europe/Vienna",
    "iso:country":"AT",
    "wof:name":"Heiligkreuz",
    "wof:placetype":"locality",
    "wof:population":127
},
  "geometry": {"coordinates":[10.97551,46.9097],"type":"Point"}
}