{
  "type": "Feature",
  "properties": {
    "gn:admin1_code":"4.0",
    "gn:admin2_code":"408",
    "gn:admin3_code":"40805.0",
    "gn:asciiname":"Schuetzendorf",
    "gn:country_code":"AT",
    "gn:dem":411,
    "gn:feature_class":"P",
    "gn:feature_code":"PPL",
    "gn:name":"Sch\u00fctzendorf",
    "gn:population":281,
    "gn:timezone":"Europe/Vienna",
    "iso:country":"AT",
    "wof:name":"Schuetzendorf",
    "wof:placetype":"locality",
    "wof:population":281
},
  "geometry": {"coordinates":[13.80012,48.20889],"type":"Point"}
}