{
  "type": "Feature",
  "properties": {
    "gn:admin1_code":"04",
    "gn:admin2_code":"404.0",
    "gn:admin3_code":"40413.0",
    "gn:asciiname":"Sonnleiten",
    "gn:country_code":"AT",
    "gn:dem":477,
    "gn:feature_class":"P",
    "gn:feature_code":"PPL",
    "gn:name":"Sonnleiten",
    "gn:population":106,
    "gn:timezone":"Europe/Vienna",
    "iso:country":"AT",
    "wof:name":"Sonnleiten",
    "wof:placetype":"locality",
    "wof:population":106
},
  "geometry": {"coordinates":[13.16686,48.16173],"type":"Point"}
}