{
  "type": "Feature",
  "properties": {
    "gn:admin1_code":"4.0",
    "gn:admin2_code":"405",
    "gn:admin3_code":"40505.0",
    "gn:asciiname":"Oberhub",
    "gn:country_code":"AT",
    "gn:dem":519,
    "gn:feature_class":"P",
    "gn:feature_code":"PPL",
    "gn:name":"Oberhub",
    "gn:population":51,
    "gn:timezone":"Europe/Vienna",
    "iso:country":"AT",
    "wof:name":"Oberhub",
    "wof:placetype":"locality",
    "wof:population":51
},
  "geometry": {"coordinates":[13.90474,48.43336],"type":"Point"}
}