{
  "type": "Feature",
  "properties": {
    "gn:admin1_code":"2.0",
    "gn:admin2_code":"204",
    "gn:admin3_code":"20405.0",
    "gn:asciiname":"Dornach",
    "gn:country_code":"AT",
    "gn:dem":448,
    "gn:feature_class":"P",
    "gn:feature_code":"PPL",
    "gn:name":"Dornach",
    "gn:population":102,
    "gn:timezone":"Europe/Vienna",
    "iso:country":"AT",
    "wof:name":"Dornach",
    "wof:placetype":"locality",
    "wof:population":102
},
  "geometry": {"coordinates":[14.25188,46.52987],"type":"Point"}
}