{
  "type": "Feature",
  "properties": {
    "gn:admin1_code":"2.0",
    "gn:admin2_code":"204",
    "gn:admin3_code":"20405.0",
    "gn:asciiname":"Dornach",
    "gn:country_code":"AT",
    "gn:dem":448,
    "gn:feature_class":"P",
    "gn:feature_code":"PPL",
    "gn:name":"Dornach",
    "gn:population":102,
    "gn:timezone":"Europe/Vienna",
    "iso:country":"AT",
    "name:als_x_preferred":[
        "Dornach"
    ],
    "name:ast_x_preferred":[
        "Dornach"
    ],
    "name:bul_x_preferred":[
        "\u0414\u043e\u0440\u043d\u0430\u0445"
    ],
    "name:cat_x_preferred":[
        "Dornach"
    ],
    "name:ceb_x_preferred":[
        "Dornach"
    ],
    "name:ces_x_preferred":[
        "Dornach"
    ],
    "name:chv_x_preferred":[
        "\u0414\u043e\u0440\u043d\u0430\u0445"
    ],
    "name:deu_x_preferred":[
        "Dornach"
    ],
    "name:epo_x_preferred":[
        "Dornach"
    ],
    "name:eus_x_preferred":[
        "Dornach"
    ],
    "name:fas_x_preferred":[
        "\u062f\u0631\u0646\u0627\u0634"
    ],
    "name:fin_x_preferred":[
        "Dornach"
    ],
    "name:fra_x_preferred":[
        "Dornach"
    ],
    "name:heb_x_preferred":[
        "\u05d3\u05d5\u05e8\u05e0\u05d0\u05da"
    ],
    "name:ita_x_preferred":[
        "Dornach"
    ],
    "name:kaz_x_preferred":[
        "\u0414\u043e\u0440\u043d\u0430\u0445"
    ],
    "name:lmo_x_preferred":[
        "Dornach"
    ],
    "name:msa_x_preferred":[
        "Dornach"
    ],
    "name:nld_x_preferred":[
        "Dornach"
    ],
    "name:nno_x_preferred":[
        "Dornach"
    ],
    "name:nor_x_preferred":[
        "Dornach"
    ],
    "name:pol_x_preferred":[
        "Dornach"
    ],
    "name:por_x_preferred":[
        "Dornach"
    ],
    "name:ron_x_preferred":[
        "Dornach"
    ],
    "name:rus_x_preferred":[
        "\u0414\u043e\u0440\u043d\u0430\u0445"
    ],
    "name:spa_x_preferred":[
        "Dornach"
    ],
    "name:sqi_x_preferred":[
        "Dornach"
    ],
    "name:swe_x_preferred":[
        "Dornach"
    ],
    "name:ukr_x_preferred":[
        "\u0414\u043e\u0440\u043d\u0430\u0445"
    ],
    "name:uzb_x_preferred":[
        "Dornach"
    ],
    "name:vol_x_preferred":[
        "Dornach"
    ],
    "name:war_x_preferred":[
        "Dornach"
    ],
    "name:zho_x_preferred":[
        "\u591a\u723e\u7d0d\u8d6b"
    ],
    "wof:name":"Dornach",
    "wof:placetype":"locality",
    "wof:population":102
},
  "geometry": {"coordinates":[14.25188,46.52987],"type":"Point"}
}