{
  "type": "Feature",
  "properties": {
    "gn:admin1_code":"2.0",
    "gn:admin2_code":"205",
    "gn:admin3_code":"20527.0",
    "gn:asciiname":"Seidlhof",
    "gn:country_code":"AT",
    "gn:dem":479,
    "gn:feature_class":"P",
    "gn:feature_code":"PPL",
    "gn:name":"Seidlhof",
    "gn:population":0,
    "gn:timezone":"Europe/Vienna",
    "iso:country":"AT",
    "wof:name":"Seidlhof",
    "wof:placetype":"locality"
},
  "geometry": {"coordinates":[14.30333,46.73778],"type":"Point"}
}