{
  "type": "Feature",
  "properties": {
    "gn:admin1_code":"4.0",
    "gn:admin2_code":"417",
    "gn:admin3_code":"41735.0",
    "gn:asciiname":"Gries",
    "gn:country_code":"AT",
    "gn:dem":488,
    "gn:feature_class":"P",
    "gn:feature_code":"PPL",
    "gn:name":"Gries",
    "gn:population":0,
    "gn:timezone":"Europe/Vienna",
    "iso:country":"AT",
    "wof:name":"Gries",
    "wof:placetype":"locality"
},
  "geometry": {"coordinates":[13.365,47.81607],"type":"Point"}
}