{
  "type": "Feature",
  "properties": {
    "gn:admin1_code":"4.0",
    "gn:admin2_code":"411",
    "gn:admin3_code":"41118.0",
    "gn:asciiname":"Niederzirking",
    "gn:country_code":"AT",
    "gn:dem":254,
    "gn:feature_class":"P",
    "gn:feature_code":"PPL",
    "gn:name":"Niederzirking",
    "gn:population":281,
    "gn:timezone":"Europe/Vienna",
    "iso:country":"AT",
    "wof:name":"Niederzirking",
    "wof:placetype":"locality",
    "wof:population":281
},
  "geometry": {"coordinates":[14.55,48.26667],"type":"Point"}
}