{
  "type": "Feature",
  "properties": {
    "gn:admin1_code":"8.0",
    "gn:admin2_code":"802",
    "gn:admin3_code":"80228.0",
    "gn:asciiname":"Hoefle",
    "gn:country_code":"AT",
    "gn:dem":1478,
    "gn:feature_class":"P",
    "gn:feature_code":"PPL",
    "gn:name":"H\u00f6fle",
    "gn:population":0,
    "gn:timezone":"Europe/Vienna",
    "iso:country":"AT",
    "wof:name":"Hoefle",
    "wof:placetype":"locality"
},
  "geometry": {"coordinates":[10.16667,47.31667],"type":"Point"}
}