{
  "type": "Feature",
  "properties": {
    "gn:admin1_code":"04",
    "gn:admin2_code":"406.0",
    "gn:admin3_code":"40616.0",
    "gn:asciiname":"Rindlberg",
    "gn:country_code":"AT",
    "gn:dem":887,
    "gn:feature_class":"P",
    "gn:feature_code":"PPL",
    "gn:name":"Rindlberg",
    "gn:population":34,
    "gn:timezone":"Europe/Vienna",
    "iso:country":"AT",
    "wof:name":"Rindlberg",
    "wof:placetype":"locality",
    "wof:population":34
},
  "geometry": {"coordinates":[14.66228,48.53303],"type":"Point"}
}