{
  "type": "Feature",
  "properties": {
    "gn:admin1_code":"6.0",
    "gn:admin2_code":"614",
    "gn:admin3_code":"61425.0",
    "gn:asciiname":"Althofen",
    "gn:country_code":"AT",
    "gn:dem":1220,
    "gn:feature_class":"P",
    "gn:feature_code":"PPL",
    "gn:name":"Althofen",
    "gn:population":220,
    "gn:timezone":"Europe/Vienna",
    "iso:country":"AT",
    "wof:name":"Althofen",
    "wof:placetype":"locality",
    "wof:population":220
},
  "geometry": {"coordinates":[14.23333,47.15],"type":"Point"}
}