{
  "type": "Feature",
  "properties": {
    "gn:admin1_code":"4.0",
    "gn:admin2_code":"413",
    "gn:admin3_code":"41329.0",
    "gn:asciiname":"Dorf",
    "gn:country_code":"AT",
    "gn:dem":547,
    "gn:feature_class":"P",
    "gn:feature_code":"PPL",
    "gn:name":"Dorf",
    "gn:population":144,
    "gn:timezone":"Europe/Vienna",
    "iso:country":"AT",
    "name:als_x_preferred":[
        "Dorf"
    ],
    "name:ceb_x_preferred":[
        "Dorf"
    ],
    "name:dan_x_preferred":[
        "Dorf"
    ],
    "name:deu_x_preferred":[
        "Dorf"
    ],
    "name:epo_x_preferred":[
        "Dorf"
    ],
    "name:fra_x_preferred":[
        "Dorf"
    ],
    "name:ita_x_preferred":[
        "Dorf"
    ],
    "name:pol_x_preferred":[
        "Dorf"
    ],
    "name:rus_x_preferred":[
        "\u0414\u043e\u0440\u0444"
    ],
    "name:swe_x_preferred":[
        "Dorf"
    ],
    "wof:name":"Dorf",
    "wof:placetype":"locality",
    "wof:population":144
},
  "geometry": {"coordinates":[13.7651,48.4917],"type":"Point"}
}