{
  "type": "Feature",
  "properties": {
    "gn:admin1_code":"4.0",
    "gn:admin2_code":"409",
    "gn:admin3_code":"40917.0",
    "gn:asciiname":"Blumau",
    "gn:country_code":"AT",
    "gn:dem":426,
    "gn:feature_class":"P",
    "gn:feature_code":"PPL",
    "gn:name":"Blumau",
    "gn:population":0,
    "gn:timezone":"Europe/Vienna",
    "iso:country":"AT",
    "wof:name":"Blumau",
    "wof:placetype":"locality"
},
  "geometry": {"coordinates":[14.10636,47.91565],"type":"Point"}
}