{
  "type": "Feature",
  "properties": {
    "gn:admin1_code":"3.0",
    "gn:admin2_code":"315",
    "gn:admin3_code":"31534.0",
    "gn:asciiname":"Unteraschelberg",
    "gn:country_code":"AT",
    "gn:dem":784,
    "gn:feature_class":"P",
    "gn:feature_code":"PPL",
    "gn:name":"Unteraschelberg",
    "gn:population":0,
    "gn:timezone":"Europe/Vienna",
    "iso:country":"AT",
    "wof:name":"Unteraschelberg",
    "wof:placetype":"locality"
},
  "geometry": {"coordinates":[15.19855,48.34176],"type":"Point"}
}