{
  "type": "Feature",
  "properties": {
    "gn:admin1_code":"7.0",
    "gn:admin2_code":"707",
    "gn:admin3_code":"70729.0",
    "gn:asciiname":"Hof",
    "gn:country_code":"AT",
    "gn:dem":1078,
    "gn:feature_class":"P",
    "gn:feature_code":"PPL",
    "gn:name":"Hof",
    "gn:population":0,
    "gn:timezone":"Europe/Vienna",
    "iso:country":"AT",
    "wof:name":"Hof",
    "wof:placetype":"locality"
},
  "geometry": {"coordinates":[12.48333,46.75],"type":"Point"}
}