{
  "type": "Feature",
  "properties": {
    "gn:admin1_code":"06",
    "gn:admin2_code":"620.0",
    "gn:admin3_code":"62044.0",
    "gn:asciiname":"Oberzeiring",
    "gn:country_code":"AT",
    "gn:dem":937,
    "gn:feature_class":"P",
    "gn:feature_code":"PPLA3",
    "gn:name":"Oberzeiring",
    "gn:population":611,
    "gn:timezone":"Europe/Vienna",
    "iso:country":"AT",
    "name:ceb_x_preferred":[
        "Oberzeiring"
    ],
    "name:deu_x_preferred":[
        "Oberzeiring"
    ],
    "name:fas_x_preferred":[
        "\u0627\u0648\u0628\u0631\u062a\u0633\u0627\u06cc\u0631\u06cc\u0646\u06af"
    ],
    "name:fra_x_preferred":[
        "Oberzeiring"
    ],
    "name:ita_x_preferred":[
        "Oberzeiring"
    ],
    "name:nld_x_preferred":[
        "Oberzeiring"
    ],
    "name:pol_x_preferred":[
        "Oberzeiring"
    ],
    "name:rus_x_preferred":[
        "\u041e\u0431\u0435\u0440\u0446\u0430\u0439\u0440\u0438\u043d\u0433"
    ],
    "name:slk_x_preferred":[
        "Oberzeiring"
    ],
    "name:swe_x_preferred":[
        "Oberzeiring"
    ],
    "name:uzb_x_preferred":[
        "Oberzeiring"
    ],
    "name:vie_x_preferred":[
        "Oberzeiring"
    ],
    "name:vol_x_preferred":[
        "Oberzeiring"
    ],
    "name:war_x_preferred":[
        "Oberzeiring"
    ],
    "name:zho_x_preferred":[
        "\u4e0a\u8521\u7075"
    ],
    "wof:name":"Oberzeiring",
    "wof:placetype":"locality",
    "wof:population":611
},
  "geometry": {"coordinates":[14.48333,47.25],"type":"Point"}
}