{
  "type": "Feature",
  "properties": {
    "gn:admin1_code":"6.0",
    "gn:admin2_code":"606",
    "gn:admin3_code":"60663.0",
    "gn:asciiname":"Laufnitzgraben",
    "gn:country_code":"AT",
    "gn:dem":977,
    "gn:feature_class":"P",
    "gn:feature_code":"PPL",
    "gn:name":"Laufnitzgraben",
    "gn:population":0,
    "gn:timezone":"Europe/Vienna",
    "iso:country":"AT",
    "wof:name":"Laufnitzgraben",
    "wof:placetype":"locality"
},
  "geometry": {"coordinates":[15.26667,47.31667],"type":"Point"}
}