{
  "type": "Feature",
  "properties": {
    "gn:admin1_code":"02",
    "gn:admin2_code":"207.0",
    "gn:admin3_code":"20727.0",
    "gn:asciiname":"Ragain",
    "gn:country_code":"AT",
    "gn:dem":670,
    "gn:feature_class":"P",
    "gn:feature_code":"PPL",
    "gn:name":"Ragain",
    "gn:population":147,
    "gn:timezone":"Europe/Vienna",
    "iso:country":"AT",
    "wof:name":"Ragain",
    "wof:placetype":"locality",
    "wof:population":147
},
  "geometry": {"coordinates":[13.94944,46.63694],"type":"Point"}
}