{
  "type": "Feature",
  "properties": {
    "gn:admin1_code":"3.0",
    "gn:admin2_code":"319",
    "gn:admin3_code":"31912.0",
    "gn:asciiname":"Ederding",
    "gn:country_code":"AT",
    "gn:dem":253,
    "gn:feature_class":"P",
    "gn:feature_code":"PPL",
    "gn:name":"Ederding",
    "gn:population":73,
    "gn:timezone":"Europe/Vienna",
    "iso:country":"AT",
    "wof:name":"Ederding",
    "wof:placetype":"locality",
    "wof:population":73
},
  "geometry": {"coordinates":[15.66994,48.29633],"type":"Point"}
}