{
  "type": "Feature",
  "properties": {
    "gn:admin1_code":"5.0",
    "gn:admin2_code":"503",
    "gn:admin3_code":"50315.0",
    "gn:asciiname":"Holzeck",
    "gn:country_code":"AT",
    "gn:dem":483,
    "gn:feature_class":"P",
    "gn:feature_code":"PPL",
    "gn:name":"Holzeck",
    "gn:population":0,
    "gn:timezone":"Europe/Vienna",
    "iso:country":"AT",
    "wof:name":"Holzeck",
    "wof:placetype":"locality"
},
  "geometry": {"coordinates":[12.94056,47.74972],"type":"Point"}
}