{
  "type": "Feature",
  "properties": {
    "gn:admin1_code":"06",
    "gn:admin2_code":"610.0",
    "gn:admin3_code":"61055.0",
    "gn:asciiname":"Prinnenberg",
    "gn:country_code":"AT",
    "gn:dem":427,
    "gn:feature_class":"P",
    "gn:feature_code":"PPL",
    "gn:name":"Prinnenberg",
    "gn:population":0,
    "gn:timezone":"Europe/Vienna",
    "iso:country":"AT",
    "wof:name":"Prinnenberg",
    "wof:placetype":"locality"
},
  "geometry": {"coordinates":[15.61667,46.88333],"type":"Point"}
}