{
  "type": "Feature",
  "properties": {
    "gn:admin1_code":"6.0",
    "gn:admin2_code":"623",
    "gn:admin3_code":"62330.0",
    "gn:asciiname":"Lugitsch",
    "gn:country_code":"AT",
    "gn:dem":304,
    "gn:feature_class":"P",
    "gn:feature_code":"PPL",
    "gn:name":"Lugitsch",
    "gn:population":191,
    "gn:timezone":"Europe/Vienna",
    "iso:country":"AT",
    "wof:name":"Lugitsch",
    "wof:placetype":"locality",
    "wof:population":191
},
  "geometry": {"coordinates":[15.76667,46.83333],"type":"Point"}
}