{
  "type": "Feature",
  "properties": {
    "gn:admin1_code":"2.0",
    "gn:admin2_code":"206",
    "gn:admin3_code":"20610.0",
    "gn:asciiname":"Apriach",
    "gn:country_code":"AT",
    "gn:dem":1618,
    "gn:feature_class":"P",
    "gn:feature_code":"PPL",
    "gn:name":"Apriach",
    "gn:population":121,
    "gn:timezone":"Europe/Vienna",
    "iso:country":"AT",
    "wof:name":"Apriach",
    "wof:placetype":"locality",
    "wof:population":121
},
  "geometry": {"coordinates":[12.88333,47.01667],"type":"Point"}
}