{
  "type": "Feature",
  "properties": {
    "gn:admin1_code":"3.0",
    "gn:admin2_code":"312",
    "gn:admin3_code":"31201.0",
    "gn:asciiname":"Klein-Engersdorf",
    "gn:country_code":"AT",
    "gn:dem":209,
    "gn:feature_class":"P",
    "gn:feature_code":"PPL",
    "gn:name":"Klein-Engersdorf",
    "gn:population":619,
    "gn:timezone":"Europe/Vienna",
    "iso:country":"AT",
    "wof:name":"Klein-Engersdorf",
    "wof:placetype":"locality",
    "wof:population":619
},
  "geometry": {"coordinates":[16.38306,48.33306],"type":"Point"}
}