{
  "type": "Feature",
  "properties": {
    "gn:admin1_code":"8.0",
    "gn:admin2_code":"802",
    "gn:admin3_code":"80203.0",
    "gn:asciiname":"Hinter Boden Vorsaess",
    "gn:country_code":"AT",
    "gn:dem":1219,
    "gn:feature_class":"P",
    "gn:feature_code":"PPLF",
    "gn:name":"Hinter Boden Vors\u00e4\u00df",
    "gn:population":0,
    "gn:timezone":"Europe/Vienna",
    "iso:country":"AT",
    "wof:name":"Hinter Boden Vorsaess",
    "wof:placetype":"locality"
},
  "geometry": {"coordinates":[9.9881,47.29581],"type":"Point"}
}