{
  "type": "Feature",
  "properties": {
    "gn:admin1_code":"7.0",
    "gn:admin2_code":"703",
    "gn:admin3_code":"70326.0",
    "gn:asciiname":"Ahrn",
    "gn:country_code":"AT",
    "gn:dem":1100,
    "gn:feature_class":"P",
    "gn:feature_code":"PPL",
    "gn:name":"Ahrn",
    "gn:population":0,
    "gn:timezone":"Europe/Vienna",
    "iso:country":"AT",
    "wof:name":"Ahrn",
    "wof:placetype":"locality"
},
  "geometry": {"coordinates":[11.16667,47.38333],"type":"Point"}
}