{
  "type": "Feature",
  "properties": {
    "gn:country":"AT",
    "gn:fcode":"PPL",
    "gn:population":0,
    "iso:country":"AT",
    "name:ces_x_preferred":[
        "Mils"
    ],
    "name:deu_x_preferred":[
        "Mils"
    ],
    "name:eng_x_preferred":[
        "Mils"
    ],
    "name:est_x_preferred":[
        "Milsi vald"
    ],
    "name:fas_x_preferred":[
        "\u0645\u06cc\u0644\u0633 \u062a\u06cc\u0631\u0648\u0644"
    ],
    "name:fra_x_preferred":[
        "Mils"
    ],
    "name:hun_x_preferred":[
        "Mils"
    ],
    "name:ita_x_preferred":[
        "Mils"
    ],
    "name:kaz_x_preferred":[
        "\u041c\u0438\u043b\u044c\u0441"
    ],
    "name:lmo_x_preferred":[
        "Mils"
    ],
    "name:nld_x_preferred":[
        "Mils bei Hall"
    ],
    "name:nno_x_preferred":[
        "Mils"
    ],
    "name:pol_x_preferred":[
        "Mils"
    ],
    "name:rus_x_preferred":[
        "\u041c\u0438\u043b\u044c\u0441"
    ],
    "name:slk_x_preferred":[
        "Mils"
    ],
    "name:swe_x_preferred":[
        "Mils"
    ],
    "name:ukr_x_preferred":[
        "\u041c\u0456\u043b\u044c\u0441"
    ],
    "name:uzb_x_preferred":[
        "Mils"
    ],
    "name:vol_x_preferred":[
        "Mils"
    ],
    "name:war_x_preferred":[
        "Mils"
    ],
    "name:zho_x_preferred":[
        "\u7c73\u5c14\u65af"
    ],
    "qs_pg:aaroncc":"AT",
    "qs_pg:gn_country":"AT",
    "qs_pg:gn_fcode":"PPL",
    "qs_pg:gn_pop":0,
    "qs_pg:name":"Mils bei Solbad Hall",
    "qs_pg:name_adm0":"\u00d6sterreich",
    "qs_pg:name_adm1":"Tirol",
    "qs_pg:photos":32,
    "qs_pg:photos_1k":6,
    "qs_pg:photos_9k":1,
    "qs_pg:photos_9r":2,
    "qs_pg:photos_all":32,
    "qs_pg:photos_sr":2,
    "qs_pg:pop_sr":0,
    "qs_pg:qs_pg_placetype":"locality",
    "qs_pg:qs_pg_placetype_gp":"Town",
    "qs_pg:woe_adm0":23424750,
    "woe:adm0_id":23424750,
    "woe:name_adm0":"\u00d6sterreich",
    "woe:name_adm1":"Tirol",
    "woe:placetype":"Town",
    "wof:name":"Mils bei Solbad Hall",
    "wof:placetype":"locality"
},
  "geometry": {"coordinates":[11.53333,47.28333],"type":"Point"}
}