{
  "type": "Feature",
  "properties": {
    "gn:gn_country":"AT",
    "gn:gn_fcode":"ADM3",
    "gn:gn_pop":1250,
    "gn:population":1250,
    "iso:country":"AT",
    "name:chi_x_preferred":[
        "Gutenberg an der Raabklamm"
    ],
    "name:dut_x_preferred":[
        "Gutenberg an der Raabklamm"
    ],
    "name:eng_x_preferred":[
        "Gutenberg an der Raabklamm"
    ],
    "name:fre_x_preferred":[
        "Gutenberg an der Raabklamm"
    ],
    "name:ger_x_preferred":[
        "Gutenberg an der Raabklamm"
    ],
    "name:hun_x_preferred":[
        "Gutenberg an der Raabklamm"
    ],
    "name:ita_x_preferred":[
        "Gutenberg an der Raabklamm"
    ],
    "name:kaz_x_preferred":[
        "\u0413\u0443\u0442\u0435\u043d\u0431\u0435\u0440\u0433-\u043d\u0430-\u0420\u0430\u0431\u0435\u043a\u043b\u0430\u043c"
    ],
    "name:rus_x_preferred":[
        "\u0413\u0443\u0442\u0435\u043d\u0431\u0435\u0440\u0433-\u043d\u0430-\u0420\u0430\u0431\u0435\u043a\u043b\u0430\u043c"
    ],
    "name:slo_x_preferred":[
        "Gutenberg an der Raabklamm"
    ],
    "name:swe_x_preferred":[
        "Gutenberg an der Raabklamm"
    ],
    "name:uzb_x_preferred":[
        "Gutenberg an der Raabklamm"
    ],
    "name:vie_x_preferred":[
        "Gutenberg an der Raabklamm"
    ],
    "name:vol_x_preferred":[
        "Gutenberg an der Raabklamm"
    ],
    "name:war_x_preferred":[
        "Gutenberg an der Raabklamm"
    ],
    "qs_pg:aaroncc":"AT",
    "qs_pg:gn_country":"AT",
    "qs_pg:gn_fcode":"ADM3",
    "qs_pg:gn_pop":1250,
    "qs_pg:name":"Gutenberg an der Raabklamm",
    "qs_pg:name_adm0":"\u00d6sterreich",
    "qs_pg:name_adm1":"Steiermark",
    "qs_pg:photos_9r":0,
    "qs_pg:photos_sr":0,
    "qs_pg:pop_sr":3,
    "qs_pg:qs_pg_placetype":"locality",
    "qs_pg:qs_pg_placetype_gp":"Town",
    "qs_pg:woe_adm0":23424750,
    "woe:adm0_id":23424750,
    "woe:name_adm0":"\u00d6sterreich",
    "woe:name_adm1":"Steiermark",
    "woe:placetype":"Town",
    "wof:name":"Gutenberg an der Raabklamm",
    "wof:placetype":"locality",
    "wof:population":1250
},
  "geometry": {"coordinates":[15.54875,47.21424],"type":"Point"}
}