{
  "type": "Feature",
  "properties": {
    "gn:country":"AT",
    "gn:fcode":"ADM3",
    "gn:population":1250,
    "iso:country":"AT",
    "name:cat_x_preferred":[
        "Gutenberg an der Raabklamm"
    ],
    "name:ceb_x_preferred":[
        "Gutenberg an der Raabklamm"
    ],
    "name:deu_x_preferred":[
        "Gutenberg an der Raabklamm"
    ],
    "name:eng_x_preferred":[
        "Gutenberg an der Raabklamm"
    ],
    "name:est_x_preferred":[
        "Gutenberg an der Raabklamm"
    ],
    "name:fas_x_preferred":[
        "\u06af\u0648\u062a\u0646\u0628\u0631\u06af \u0622\u0646\u062f\u0631 \u0631\u0627\u0628\u06a9\u0644\u0627\u0645"
    ],
    "name:fra_x_preferred":[
        "Gutenberg an der Raabklamm"
    ],
    "name:hun_x_preferred":[
        "Gutenberg an der Raabklamm"
    ],
    "name:ita_x_preferred":[
        "Gutenberg an der Raabklamm"
    ],
    "name:kaz_x_preferred":[
        "\u0413\u0443\u0442\u0435\u043d\u0431\u0435\u0440\u0433-\u043d\u0430-\u0420\u0430\u0431\u0435\u043a\u043b\u0430\u043c"
    ],
    "name:lld_x_preferred":[
        "Gutenberg an der Raabklamm"
    ],
    "name:nld_x_preferred":[
        "Gutenberg an der Raabklamm"
    ],
    "name:nob_x_preferred":[
        "Gutenberg an der Raabklamm"
    ],
    "name:rus_x_preferred":[
        "\u0413\u0443\u0442\u0435\u043d\u0431\u0435\u0440\u0433-\u043d\u0430-\u0420\u0430\u0431\u0435\u043a\u043b\u0430\u043c"
    ],
    "name:slk_x_preferred":[
        "Gutenberg an der Raabklamm"
    ],
    "name:swe_x_preferred":[
        "Gutenberg an der Raabklamm"
    ],
    "name:uzb_x_preferred":[
        "Gutenberg an der Raabklamm"
    ],
    "name:vie_x_preferred":[
        "Gutenberg an der Raabklamm"
    ],
    "name:vol_x_preferred":[
        "Gutenberg an der Raabklamm"
    ],
    "name:war_x_preferred":[
        "Gutenberg an der Raabklamm"
    ],
    "name:zho_x_preferred":[
        "Gutenberg an der Raabklamm"
    ],
    "qs_pg:aaroncc":"AT",
    "qs_pg:gn_country":"AT",
    "qs_pg:gn_fcode":"ADM3",
    "qs_pg:gn_pop":1250,
    "qs_pg:name":"Gutenberg an der Raabklamm",
    "qs_pg:name_adm0":"\u00d6sterreich",
    "qs_pg:name_adm1":"Steiermark",
    "qs_pg:photos_9r":0,
    "qs_pg:photos_sr":0,
    "qs_pg:pop_sr":3,
    "qs_pg:qs_pg_placetype":"locality",
    "qs_pg:qs_pg_placetype_gp":"Town",
    "qs_pg:woe_adm0":23424750,
    "woe:adm0_id":23424750,
    "woe:name_adm0":"\u00d6sterreich",
    "woe:name_adm1":"Steiermark",
    "woe:placetype":"Town",
    "wof:name":"Gutenberg an der Raabklamm",
    "wof:placetype":"locality",
    "wof:population":1250
},
  "geometry": {"coordinates":[15.54875,47.21424],"type":"Point"}
}