{
  "type": "Feature",
  "properties": {
    "gn:admin1_code":"4.0",
    "gn:admin2_code":"416",
    "gn:admin3_code":"41626.0",
    "gn:asciiname":"Lindham",
    "gn:country_code":"AT",
    "gn:dem":275,
    "gn:feature_class":"P",
    "gn:feature_code":"PPL",
    "gn:name":"Lindham",
    "gn:population":0,
    "gn:timezone":"Europe/Vienna",
    "iso:country":"AT",
    "wof:name":"Lindham",
    "wof:placetype":"locality"
},
  "geometry": {"coordinates":[14.13837,48.34056],"type":"Point"}
}