{
  "type": "Feature",
  "properties": {
    "gn:admin1_code":"6.0",
    "gn:admin2_code":"623",
    "gn:admin3_code":"62387.0",
    "gn:asciiname":"Giesselsdorf",
    "gn:country_code":"AT",
    "gn:dem":334,
    "gn:feature_class":"P",
    "gn:feature_code":"PPL",
    "gn:name":"Gie\u00dfelsdorf",
    "gn:population":256,
    "gn:timezone":"Europe/Vienna",
    "iso:country":"AT",
    "wof:name":"Giesselsdorf",
    "wof:placetype":"locality",
    "wof:population":256
},
  "geometry": {"coordinates":[15.93333,46.81667],"type":"Point"}
}