{
  "type": "Feature",
  "properties": {
    "gn:admin1_code":"02",
    "gn:admin2_code":"209.0",
    "gn:admin3_code":"20905.0",
    "gn:asciiname":"Vorderwoelch",
    "gn:country_code":"AT",
    "gn:dem":712,
    "gn:feature_class":"P",
    "gn:feature_code":"PPL",
    "gn:name":"Vorderw\u00f6lch",
    "gn:population":182,
    "gn:timezone":"Europe/Vienna",
    "iso:country":"AT",
    "wof:name":"Vorderwoelch",
    "wof:placetype":"locality",
    "wof:population":182
},
  "geometry": {"coordinates":[14.85,46.86667],"type":"Point"}
}