{
  "type": "Feature",
  "properties": {
    "gn:admin1_code":"4.0",
    "gn:admin2_code":"414",
    "gn:admin3_code":"41402.0",
    "gn:asciiname":"Hoetzlarn",
    "gn:country_code":"AT",
    "gn:dem":351,
    "gn:feature_class":"P",
    "gn:feature_code":"PPL",
    "gn:name":"H\u00f6tzlarn",
    "gn:population":79,
    "gn:timezone":"Europe/Vienna",
    "iso:country":"AT",
    "wof:name":"Hoetzlarn",
    "wof:placetype":"locality",
    "wof:population":79
},
  "geometry": {"coordinates":[13.58786,48.34804000000001],"type":"Point"}
}