{
  "type": "Feature",
  "properties": {
    "gn:admin1_code":"03",
    "gn:admin2_code":"306.0",
    "gn:admin3_code":"30602.0",
    "gn:asciiname":"Thenneberg",
    "gn:country_code":"AT",
    "gn:dem":419,
    "gn:feature_class":"P",
    "gn:feature_code":"PPL",
    "gn:name":"Thenneberg",
    "gn:population":558,
    "gn:timezone":"Europe/Vienna",
    "iso:country":"AT",
    "wof:name":"Thenneberg",
    "wof:placetype":"locality",
    "wof:population":558
},
  "geometry": {"coordinates":[15.96554,48.01703],"type":"Point"}
}