{
  "type": "Feature",
  "properties": {
    "gn:admin1_code":"4.0",
    "gn:admin2_code":"412",
    "gn:admin3_code":"41205.0",
    "gn:asciiname":"Kirchberg",
    "gn:country_code":"AT",
    "gn:dem":422,
    "gn:feature_class":"P",
    "gn:feature_code":"PPL",
    "gn:name":"Kirchberg",
    "gn:population":17,
    "gn:timezone":"Europe/Vienna",
    "iso:country":"AT",
    "wof:name":"Kirchberg",
    "wof:placetype":"locality",
    "wof:population":17
},
  "geometry": {"coordinates":[13.43602,48.22462],"type":"Point"}
}