{
  "type": "Feature",
  "properties": {
    "gn:admin1_code":"4.0",
    "gn:admin2_code":"405",
    "gn:admin3_code":"40512.0",
    "gn:asciiname":"Grossstroheim",
    "gn:country_code":"AT",
    "gn:dem":290,
    "gn:feature_class":"P",
    "gn:feature_code":"PPL",
    "gn:name":"Grossstroheim",
    "gn:population":0,
    "gn:timezone":"Europe/Vienna",
    "iso:country":"AT",
    "wof:name":"Grossstroheim",
    "wof:placetype":"locality"
},
  "geometry": {"coordinates":[13.96663,48.32156],"type":"Point"}
}