{
  "type": "Feature",
  "properties": {
    "gn:admin1_code":"7.0",
    "gn:admin2_code":"707",
    "gn:admin3_code":"70704.0",
    "gn:asciiname":"Goll",
    "gn:country_code":"AT",
    "gn:dem":1234,
    "gn:feature_class":"P",
    "gn:feature_code":"PPL",
    "gn:name":"Goll",
    "gn:population":48,
    "gn:timezone":"Europe/Vienna",
    "iso:country":"AT",
    "name:ces_x_preferred":[
        "Goll"
    ],
    "name:deu_x_preferred":[
        "Goll"
    ],
    "name:fra_x_preferred":[
        "Goll"
    ],
    "name:nds_x_preferred":[
        "Goll"
    ],
    "name:rus_x_preferred":[
        "\u0413\u043e\u043b\u043b"
    ],
    "wof:name":"Goll",
    "wof:placetype":"locality",
    "wof:population":48
},
  "geometry": {"coordinates":[12.55128,46.76965],"type":"Point"}
}