{
  "type": "Feature",
  "properties": {
    "gn:admin1_code":"2.0",
    "gn:admin2_code":"207",
    "gn:admin3_code":"20720.0",
    "gn:asciiname":"Rubland",
    "gn:country_code":"AT",
    "gn:dem":810,
    "gn:feature_class":"P",
    "gn:feature_code":"PPL",
    "gn:name":"Rubland",
    "gn:population":88,
    "gn:timezone":"Europe/Vienna",
    "iso:country":"AT",
    "wof:name":"Rubland",
    "wof:placetype":"locality",
    "wof:population":88
},
  "geometry": {"coordinates":[13.65861,46.66111],"type":"Point"}
}