{
  "type": "Feature",
  "properties": {
    "gn:admin1_code":"03",
    "gn:admin2_code":"321.0",
    "gn:admin3_code":"32139.0",
    "gn:asciiname":"Mittermoos",
    "gn:country_code":"AT",
    "gn:dem":214,
    "gn:feature_class":"P",
    "gn:feature_code":"PPL",
    "gn:name":"Mittermoos",
    "gn:population":22,
    "gn:timezone":"Europe/Vienna",
    "iso:country":"AT",
    "wof:name":"Mittermoos",
    "wof:placetype":"locality",
    "wof:population":22
},
  "geometry": {"coordinates":[15.88057,48.25086],"type":"Point"}
}