{
  "type": "Feature",
  "properties": {
    "gn:admin1_code":"4.0",
    "gn:admin2_code":"417",
    "gn:admin3_code":"41709.0",
    "gn:asciiname":"Halt",
    "gn:country_code":"AT",
    "gn:dem":561,
    "gn:feature_class":"P",
    "gn:feature_code":"PPL",
    "gn:name":"Halt",
    "gn:population":37,
    "gn:timezone":"Europe/Vienna",
    "iso:country":"AT",
    "name:deu_x_preferred":[
        "Halt"
    ],
    "name:swe_x_preferred":[
        "Halt"
    ],
    "wof:name":"Halt",
    "wof:placetype":"locality",
    "wof:population":37
},
  "geometry": {"coordinates":[13.49524,48.08247],"type":"Point"}
}