{
  "type": "Feature",
  "properties": {
    "gn:admin1_code":"6.0",
    "gn:admin2_code":"610",
    "gn:admin3_code":"61020.0",
    "gn:asciiname":"Joess",
    "gn:country_code":"AT",
    "gn:dem":279,
    "gn:feature_class":"P",
    "gn:feature_code":"PPL",
    "gn:name":"J\u00f6ss",
    "gn:population":317,
    "gn:timezone":"Europe/Vienna",
    "iso:country":"AT",
    "name:deu_x_preferred":[
        "J\u00f6\u00df"
    ],
    "wof:name":"Joess",
    "wof:placetype":"locality",
    "wof:population":317
},
  "geometry": {"coordinates":[15.51751,46.83761],"type":"Point"}
}