{
  "type": "Feature",
  "properties": {
    "gn:admin1_code":"06",
    "gn:admin2_code":"621.0",
    "gn:admin3_code":"62140.0",
    "gn:asciiname":"Sankt Martin",
    "gn:country_code":"AT",
    "gn:dem":514,
    "gn:feature_class":"P",
    "gn:feature_code":"PPL",
    "gn:name":"Sankt Martin",
    "gn:population":2417,
    "gn:timezone":"Europe/Vienna",
    "iso:country":"AT",
    "name:als_x_preferred":[
        "Sankt Martin"
    ],
    "name:ceb_x_preferred":[
        "Sankt Martin"
    ],
    "name:deu_x_preferred":[
        "Sankt Martin"
    ],
    "name:epo_x_preferred":[
        "Sankt Martin"
    ],
    "name:fra_x_preferred":[
        "Sankt Martin"
    ],
    "name:hun_x_preferred":[
        "Szent M\u00e1rton"
    ],
    "name:ita_x_preferred":[
        "Sankt Martin"
    ],
    "name:nld_x_preferred":[
        "Sankt Martin"
    ],
    "name:pol_x_preferred":[
        "Sankt Martin"
    ],
    "name:rus_x_preferred":[
        "\u0421\u0430\u043d\u043a\u0442-\u041c\u0430\u0440\u0442\u0438\u043d"
    ],
    "name:swe_x_preferred":[
        "Sankt Martin"
    ],
    "name:vol_x_preferred":[
        "Sankt Martin"
    ],
    "wof:name":"Sankt Martin",
    "wof:placetype":"locality",
    "wof:population":2417
},
  "geometry": {"coordinates":[15.2849,47.44667000000001],"type":"Point"}
}