{
  "type": "Feature",
  "properties": {
    "gn:admin1_code":"06",
    "gn:admin2_code":"621.0",
    "gn:admin3_code":"62140.0",
    "gn:asciiname":"Sankt Martin",
    "gn:country_code":"AT",
    "gn:dem":514,
    "gn:feature_class":"P",
    "gn:feature_code":"PPL",
    "gn:name":"Sankt Martin",
    "gn:population":2417,
    "gn:timezone":"Europe/Vienna",
    "iso:country":"AT",
    "wof:name":"Sankt Martin",
    "wof:placetype":"locality",
    "wof:population":2417
},
  "geometry": {"coordinates":[15.2849,47.44667000000001],"type":"Point"}
}