{
  "type": "Feature",
  "properties": {
    "gn:admin1_code":"3.0",
    "gn:admin2_code":"319",
    "gn:admin3_code":"31922.0",
    "gn:asciiname":"Haindorf",
    "gn:country_code":"AT",
    "gn:dem":244,
    "gn:feature_class":"P",
    "gn:feature_code":"PPL",
    "gn:name":"Haindorf",
    "gn:population":103,
    "gn:timezone":"Europe/Vienna",
    "iso:country":"AT",
    "wof:name":"Haindorf",
    "wof:placetype":"locality",
    "wof:population":103
},
  "geometry": {"coordinates":[15.47527,48.17753],"type":"Point"}
}