{
  "type": "Feature",
  "properties": {
    "gn:admin1_code":"04",
    "gn:admin2_code":"409.0",
    "gn:admin3_code":"40912.0",
    "gn:asciiname":"Steinfelden",
    "gn:country_code":"AT",
    "gn:dem":499,
    "gn:feature_class":"P",
    "gn:feature_code":"PPL",
    "gn:name":"Steinfelden",
    "gn:population":130,
    "gn:timezone":"Europe/Vienna",
    "iso:country":"AT",
    "wof:name":"Steinfelden",
    "wof:placetype":"locality",
    "wof:population":130
},
  "geometry": {"coordinates":[13.98954,47.9164],"type":"Point"}
}