{
  "type": "Feature",
  "properties": {
    "gn:admin1_code":"8.0",
    "gn:admin2_code":"802",
    "gn:admin3_code":"80229.0",
    "gn:asciiname":"Andreute",
    "gn:cc2":"AT",
    "gn:country_code":"AT",
    "gn:dem":731,
    "gn:feature_class":"P",
    "gn:feature_code":"PPL",
    "gn:name":"Andreute",
    "gn:population":0,
    "gn:timezone":"Europe/Vienna",
    "iso:country":"AT",
    "name:und_x_variant":[
        "Handreute",
        "Andreute"
    ],
    "wof:name":"Andreute",
    "wof:placetype":"locality"
},
  "geometry": {"coordinates":[9.78306,47.56667],"type":"Point"}
}