{
  "type": "Feature",
  "properties": {
    "gn:admin1_code":"6.0",
    "gn:admin2_code":"610",
    "gn:admin3_code":"61046.0",
    "gn:asciiname":"Kainach bei Wildon",
    "gn:cc2":"AT",
    "gn:country_code":"AT",
    "gn:dem":297,
    "gn:feature_class":"P",
    "gn:feature_code":"PPL",
    "gn:name":"Kainach bei Wildon",
    "gn:population":0,
    "gn:timezone":"Europe/Vienna",
    "iso:country":"AT",
    "name:und_x_variant":[
        "Kainach",
        "Kainach bei Wildon"
    ],
    "wof:name":"Kainach bei Wildon",
    "wof:placetype":"locality"
},
  "geometry": {"coordinates":[15.48333,46.88333],"type":"Point"}
}