{
  "type": "Feature",
  "properties": {
    "gn:admin1_code":"3.0",
    "gn:admin2_code":"315",
    "gn:admin3_code":"31522.0",
    "gn:asciiname":"Granz",
    "gn:country_code":"AT",
    "gn:dem":256,
    "gn:feature_class":"P",
    "gn:feature_code":"PPL",
    "gn:name":"Granz",
    "gn:population":206,
    "gn:timezone":"Europe/Vienna",
    "iso:country":"AT",
    "name:deu_x_preferred":[
        "Granz"
    ],
    "name:nds_x_preferred":[
        "Granz"
    ],
    "wof:name":"Granz",
    "wof:placetype":"locality",
    "wof:population":206
},
  "geometry": {"coordinates":[15.15,48.21667],"type":"Point"}
}