{
  "type": "Feature",
  "properties": {
    "gn:gn_country":"AT",
    "gn:gn_fcode":"PPLA3",
    "gn:gn_pop":0,
    "iso:country":"AT",
    "name:deu_x_preferred":[
        "Scheffau am Wilden Kaiser"
    ],
    "name:eng_x_preferred":[
        "Scheffau am Wilden Kaiser"
    ],
    "name:fra_x_preferred":[
        "Scheffau am Wilden Kaiser"
    ],
    "name:heb_x_preferred":[
        "\u05e9\u05e4\u05d0\u05d5 \u05d0\u05dd \u05d5\u05d9\u05dc\u05d3\u05df \u05e7\u05d9\u05d9\u05d6\u05e8"
    ],
    "name:hun_x_preferred":[
        "Scheffau am Wilden Kaiser"
    ],
    "name:ita_x_preferred":[
        "Scheffau am Wilden Kaiser"
    ],
    "name:jpn_x_preferred":[
        "\u30b7\u30a7\u30c3\u30d5\u30a1\u30a6\u30fb\u30a2\u30e0\u30fb\u30f4\u30a3\u30eb\u30c7\u30f3\u30fb\u30ab\u30a4\u30b6\u30fc"
    ],
    "name:kaz_x_preferred":[
        "\u0428\u0435\u0444\u0444\u0430\u0443-\u0430\u043c-\u0412\u0438\u043b\u044c\u0434\u0435\u043d-\u041a\u0430\u0439\u0437\u0435\u0440"
    ],
    "name:lmo_x_preferred":[
        "Scheffau am Wilden Kaiser"
    ],
    "name:nld_x_preferred":[
        "Scheffau am Wilden Kaiser"
    ],
    "name:pol_x_preferred":[
        "Scheffau am Wilden Kaiser"
    ],
    "name:rus_x_preferred":[
        "\u0428\u0435\u0444\u0444\u0430\u0443-\u0430\u043c-\u0412\u0438\u043b\u044c\u0434\u0435\u043d-\u041a\u0430\u0439\u0437\u0435\u0440"
    ],
    "name:slk_x_preferred":[
        "Scheffau am Wilden Kaiser"
    ],
    "name:spa_x_preferred":[
        "Scheffau"
    ],
    "name:swe_x_preferred":[
        "Scheffau am Wilden Kaiser"
    ],
    "name:ukr_x_preferred":[
        "\u0428\u0435\u0444\u0444\u0430\u0443-\u0430\u043c-\u0412\u0456\u043b\u044c\u0434\u0435\u043d-\u041a\u0430\u0439\u0437\u0435\u0440"
    ],
    "name:unk_x_variant":[
        "Scheffau"
    ],
    "name:uzb_x_preferred":[
        "Scheffau am Wilden Kaiser"
    ],
    "name:vol_x_preferred":[
        "Scheffau am Wilden Kaiser"
    ],
    "name:war_x_preferred":[
        "Scheffau am Wilden Kaiser"
    ],
    "name:zho_x_preferred":[
        "\u51ef\u6492\u5c71\u9e93\u820d\u798f"
    ],
    "qs_pg:aaroncc":"AT",
    "qs_pg:gn_country":"AT",
    "qs_pg:gn_fcode":"PPLA3",
    "qs_pg:gn_pop":0,
    "qs_pg:name":"Scheffau am Wilden Kaiser",
    "qs_pg:photos_9r":0,
    "qs_pg:photos_sr":0,
    "qs_pg:pop_sr":0,
    "qs_pg:qs_pg_placetype":"locality",
    "wof:name":"Scheffau am Wilden Kaiser",
    "wof:placetype":"locality"
},
  "geometry": {"coordinates":[12.25139,47.52943],"type":"Point"}
}