{
  "type": "Feature",
  "properties": {
    "gn:admin1_code":"4.0",
    "gn:admin2_code":"404",
    "gn:admin3_code":"40406.0",
    "gn:asciiname":"Mariae Himmelfahrt",
    "gn:country_code":"AT",
    "gn:dem":461,
    "gn:feature_class":"P",
    "gn:feature_code":"PPL",
    "gn:name":"Mariae Himmelfahrt",
    "gn:population":0,
    "gn:timezone":"Europe/Vienna",
    "iso:country":"AT",
    "wof:name":"Mariae Himmelfahrt",
    "wof:placetype":"locality"
},
  "geometry": {"coordinates":[12.97897,48.07025],"type":"Point"}
}