{
  "type": "Feature",
  "properties": {
    "gn:admin1_code":"6.0",
    "gn:admin2_code":"621",
    "gn:admin3_code":"62148.0",
    "gn:asciiname":"Rastal",
    "gn:country_code":"AT",
    "gn:dem":659,
    "gn:feature_class":"P",
    "gn:feature_code":"PPL",
    "gn:name":"Rastal",
    "gn:population":184,
    "gn:timezone":"Europe/Vienna",
    "iso:country":"AT",
    "wof:name":"Rastal",
    "wof:placetype":"locality",
    "wof:population":184
},
  "geometry": {"coordinates":[15.14143,47.46898],"type":"Point"}
}