{
  "type": "Feature",
  "properties": {
    "gn:admin1_code":"2.0",
    "gn:admin2_code":"205",
    "gn:admin3_code":"20518.0",
    "gn:asciiname":"Feistritz",
    "gn:country_code":"AT",
    "gn:dem":958,
    "gn:feature_class":"P",
    "gn:feature_code":"PPL",
    "gn:name":"Feistritz",
    "gn:population":133,
    "gn:timezone":"Europe/Vienna",
    "iso:country":"AT",
    "name:ceb_x_preferred":[
        "Feistritz"
    ],
    "name:deu_x_preferred":[
        "Feistritz"
    ],
    "name:fra_x_preferred":[
        "Feistritz"
    ],
    "name:ita_x_preferred":[
        "Feistritz"
    ],
    "name:nld_x_preferred":[
        "Feistritz"
    ],
    "name:pol_x_preferred":[
        "Feistritz"
    ],
    "name:por_x_preferred":[
        "Feistritz"
    ],
    "name:swe_x_preferred":[
        "Feistritz"
    ],
    "wof:name":"Feistritz",
    "wof:placetype":"locality",
    "wof:population":133
},
  "geometry": {"coordinates":[14.26667,46.95],"type":"Point"}
}