{
  "type": "Feature",
  "properties": {
    "gn:admin1_code":"4.0",
    "gn:admin2_code":"404",
    "gn:admin3_code":"40405.0",
    "gn:asciiname":"Burgkirchen",
    "gn:country_code":"AT",
    "gn:dem":391,
    "gn:feature_class":"P",
    "gn:feature_code":"PPL",
    "gn:name":"Burgkirchen",
    "gn:population":613,
    "gn:timezone":"Europe/Vienna",
    "iso:country":"AT",
    "name:rus_x_preferred":[
        "\u0411\u0443\u0440\u0433\u043a\u0438\u0440\u0445\u0435\u043d"
    ],
    "wof:name":"Burgkirchen",
    "wof:placetype":"locality",
    "wof:population":613
},
  "geometry": {"coordinates":[13.09991,48.20443],"type":"Point"}
}