{
  "type": "Feature",
  "properties": {
    "gn:admin1_code":"4.0",
    "gn:admin2_code":"418",
    "gn:admin3_code":"41812.0",
    "gn:asciiname":"Unterneufahrn",
    "gn:country_code":"AT",
    "gn:dem":299,
    "gn:feature_class":"P",
    "gn:feature_code":"PPL",
    "gn:name":"Unterneufahrn",
    "gn:population":29,
    "gn:timezone":"Europe/Vienna",
    "iso:country":"AT",
    "wof:name":"Unterneufahrn",
    "wof:placetype":"locality",
    "wof:population":29
},
  "geometry": {"coordinates":[14.13172,48.21143],"type":"Point"}
}